Workbook

Sheet 2025 Summary
B1: McIntyre Summary
C3: HT | D3: CarboProp | E3: CarboHSP | F3: Bauxite Pellets | G3: ID | H3: Nanomite C | L3: HT | M3: CarboProp | N3: CarboHSP | O3: Bauxite Pellets | P3: ID | Q3: Nanomite C
B4: Nov | K4: Nov | L4: ='Nov23'!$B$22 -> 0 | M4: ='Nov23'!$B$45 -> 0 | N4: ='Nov23'!$E$45 -> 0 | P4: ='Nov23'!$H$22 -> 0 | Q4: ='Nov23'!$H$45 -> 0
B5: Dec | K5: Dec | L5: ='Dec23'!$B$22 -> 0 | M5: ='Dec23'!$B$45 -> 0 | N5: ='Dec23'!$E$45 -> 0 | P5: ='Dec23'!$H$22 -> 0 | Q5: ='Dec23'!$H$45 -> 0
B6: Jan | C6: 0 | D6: 0 | E6: 0 | G6: 0 | H6: 2000 | K6: Jan | L6: =Jan!$B$22 -> 0 | M6: =Jan!$B$45 -> 0 | N6: =Jan!$E$45 -> 0 | P6: =Jan!$H$22 -> 0 | Q6: =Jan!$H$45 -> 0.3459
B7: Feb | C7: 1750 | D7: 3500 | E7: 0 | F7: 6400 | G7: 2590 | H7: 0 | K7: Feb | L7: =Feb!$B$22 -> 0.28330977 | M7: =Feb!B45 -> 0.26666777 | N7: =Feb!$E$45 -> 0 | O7: =Feb!E22 -> 0.22642002 | P7: =Feb!$H$22 -> 0.26666777 | Q7: =Feb!$H$45 -> 0
B8: Mar | C8: 0 | D8: 3000 | E8: 0 | F8: 9600 | G8: 4440 | H8: 0 | K8: Mar | L8: =Mar!$B$22 -> 0 | M8: =Mar!B45 -> 0.25593102 | N8: =Mar!$E$45 -> 0 | O8: =Mar!E22 -> 0.21568327 | P8: =Mar!$H$22 -> 0.25593102 | Q8: =Mar!$H$45 -> 0
B9: Apr | C9: 0 | D9: 0 | E9: 0 | F9: 0 | G9: 0 | H9: 2000 | K9: Apr | L9: =Apr!$B$22 -> 0 | M9: =Apr!B45 -> 0 | N9: =Apr!$E$45 -> 0 | P9: =Apr!$H$22 -> 0 | Q9: =Apr!$H$45 -> 0.3459
B10: May | C10: 0 | D10: 0 | E10: 900 | F10: 6400 | G10: 4000 | H10: 0 | K10: May | L10: =May!$B$22 -> 0 | M10: =May!$B$45 -> 0 | N10: =May!$E$45 -> 0.30724 | O10: =May!E22 -> 0.24342019 | P10: =May!$H$22 -> 0.28366794 | Q10: =May!$H$45 -> 0
B11: Jun | C11: 0 | D11: 0 | E11: 0 | F11: 6400 | G11: 3700 | H11: 2000 | K11: Jun | L11: =Jun!$B$22 -> 0 | M11: =Jun!$B$45 -> 0 | N11: =Jun!$E$45 -> 0 | O11: =Jun!E22 -> 0.23797616 | P11: =Jun!$H$22 -> 0.27822391 | Q11: =Jun!$H$45 -> 0.16147997
B12: Jul | C12: 0 | D12: 0 | E12: 0 | G12: 0 | H12: 6000 | K12: Jul | L12: =Jul!$B$22 -> 0 | M12: =Jul!$B$45 -> 0 | N12: =Jul!$E$45 -> 0 | P12: =Jul!$H$22 -> 0 | Q12: =Jul!$H$45 -> 0.2396585
B13: Aug | C13: 0 | D13: 0 | E13: 0 | G13: 0 | H13: 6000 | K13: Aug | L13: =Aug!$B$22 -> 0 | M13: =Aug!$B$45 -> 0 | N13: =Aug!$E$45 -> 0 | P13: =Aug!$H$22 -> 0 | Q13: =Aug!$H$45 -> 0.2396585
B14: Sep | C14: 0 | D14: 0 | E14: 0 | G14: 2590 | H14: 4600 | K14: Sep | L14: =Sep!$B$22 -> 0 | M14: =Sep!$B$45 -> 0 | N14: =Sep!$E$45 -> 0 | P14: =Sep!$H$22 -> 0.33073626 | Q14: =Sep!$H$45 -> 0.21399233
B15: Oct | C15: 1500 | D15: 0 | E15: 0 | G15: 1850 | H15: 2000 | K15: Oct | L15: =Oct!$B$22 -> 0.39188537 | M15: =Oct!$B$45 -> 0 | N15: =Oct!$E$45 -> 0 | P15: =Oct!$H$22 -> 0.37524337 | Q15: =Oct!$H$45 -> 0.25849944
B16: Nov | C16: 0 | D16: 0 | E16: 0 | G16: 0 | K16: Nov | L16: =Nov!$B$22 -> 0 | M16: =Nov!$B$45 -> 0 | N16: =Nov!$E$45 -> 0 | P16: =Nov!$H$22 -> 0 | Q16: =Nov!$H$45 -> 0
B17: Dec | C17: 0 | D17: 0 | E17: 0 | G17: 0 | H17: 0 | K17: Dec | L17: =Dec!$B$22 -> 0 | M17: =Dec!$B$45 -> 0 | N17: =Dec!$E$45 -> 0 | P17: =Dec!$H$22 -> 0 | Q17: =Dec!$H$45 -> 0
B19: Total | C19: =SUM(C6:C17) -> 3250 | D19: =SUM(D4:D17) -> 6500 | E19: =SUM(E4:E17) -> 900 | F19: =SUM(F6:F17) -> 28800 | G19: =SUM(G6:G17) -> 19170 | H19: =SUM(H6:H17) -> 24600

Sheet Nov23
A1: McINTYRE STANDARD 2025 | S1: COST CENTER 10001003 | AE1: Gross | AF1: Std | AG1: Abs Limit | AH1: Absorb | AI1: 10001003 | AJ1: Absorbed | AK1: 10001003 | AX1: Abs Cost
S2: CG | T2: CP | U2: HSP | V2: CL | W2: Nanomite C | X2: NRT | Y2: To Production | Z2: Idle Plant | AA2: TOTAL | AB2: Activity / Material | AC2: UOM | AD2: Ttl Unit Qty | AE2: Unit Cost | AF2: Cost/lb | AG2: Cost/lb | AH2: Cost/lb | AI2: Absorption | AJ2: Unit Cost | AK2: Underabs | AL2: EP Unit Qty | AM2: CP Unit Qty | AN2: HSP Unit Qty | AO2: CL Unit Qty | AP2: Nano C Qty | AQ2: NRT Unit Qty | AR2: EP Units/1000lb | AS2: CP Units/1000lb | AT2: HSP Units/1000lb | AU2: CL Units/1000lb | AV2: Nano C Units/1000lb | AW2: NRT Units/1000lb | AX2: per 10000
B3: HT | E3: Bauxite Pellets | H3: ID
B4: 25 Standard | C4: 23 Actual | D4: 22 Standard | E4: =B4 -> 25 Standard | F4: 23 Actual | G4: =+D4 -> 22 Standard | H4: =B4 -> 25 Standard | I4: 23 Actual | J4: =+D4 -> 22 Standard
F5: (Jan-Aug)
A6: Materials | B6: =IF($B$24<>0,$D$80,0) -> 0 | D6: 0 | E6: =IF(E24<>0,$L$88,0) -> 0 | F6: 0.071053254 | G6: 0.02685 | H6: =IF($H$24<>0,$D$88,0) -> 0 | J6: 0
A7: Electricity | B7: =IF($B$24<>0,$D$151,0) -> 0 | D7: 0 | E7: =IF(E24<>0,$D$151,0) -> 0 | F7: 0.03392679 | G7: 0.018883379 | H7: =IF(H24<>0,$D$151,0) -> 0 | J7: 0 | S7: =$C145*$B$24*1000*$B145 -> 0 | T7: =$C151*$B$47*1000*$B151 -> 0 | U7: =$F151*$E$47*1000*$E151 -> 0 | V7: =$F145*$E$24*1000*$E145 -> #DIV/0! | W7: =$I151*$H$47*1000*$H151 -> 0 | X7: =$I145*$H$24*1000*$H145 -> 0 | Y7: =SUM(S7:X7) -> #DIV/0! | Z7: 0 | AA7: =SUM(Y7:Z7) -> #DIV/0! | AB7: ELE01 | AC7: kwh | AD7: =ROUND((B145*B$24*1000)+(B151*B$47*1000)+(E145*E$24*1000)+(E151*E$47*1000)+(H145*H$24*1000)+(H151*H$47*1000),0) -> #DIV/0! | AE7: =Y7/AD7 -> #DIV/0! | AF7: =Y7/$AF$24/1000 -> #DIV/0! | AG7: 0.014890786 | AH7: =IF($AF$21<$AG$21,AF7,IF($AF$12<$AG$12,AF7,IF(AND($AF$12>$AG$12,$AF$20<$AG$20),($AG$12+($AG$20-$AF$20))/$AF$12*AF7,AF7/$AF$12*$AG$12))) -> #DIV/0! | AI7: =AH7*$Y$24*1000 -> #DIV/0! | AJ7: =AI7/AD7 -> #DIV/0! | AK7: =Y7-AI7 -> #DIV/0! | AL7: =ROUND($B145*$B$24*1000,0) -> 0 | AM7: =ROUND($B151*$B$47*1000,0) -> 0 | AN7: =ROUND($E151*$E$47*1000,0) -> 0 | AO7: =ROUND($E145*$E$24*1000,0) -> #DIV/0! | AP7: =ROUND($H151*$H$47*1000,0) -> 0 | AQ7: =ROUND($H145*$H$24*1000,0) -> 0 | AR7: =IF($B$24<>0,ROUND(AL7/B$24,3),0) -> 0 | AS7: =ROUND(AM7/B$47,3) -> #DIV/0! | AT7: =IF(E$47<>0,ROUND(AN7/E$47,3),0) -> 0 | AU7: =IF(F$24<>0,ROUND(AO7/F$24,3),0) -> #DIV/0! | AV7: =IF(H$47<>0,ROUND(AP7/H$47,3),0) -> 0 | AW7: =IF(H$24<>0,ROUND(AQ7/H$24,3),0) -> 0 | AX7: =AJ7*10000 -> #DIV/0!
A8: Gas | B8: =IF($B$24<>0,$D$152,0) -> 0 | D8: 0 | E8: =IF(E24<>0,$D$152,0) -> 0 | F8: 0.14600441 | G8: 0.04184 | H8: =IF(H24<>0,$D$152,0) -> 0 | J8: 0 | S8: =$C146*$B$24*1000*$B146 -> 0 | T8: =$C152*$B$47*1000*$B152 -> 0 | U8: =$F152*$E$47*1000*$E152 -> 0 | V8: =$F146*$E$24*1000*$E146 -> 0 | W8: =$I152*$H$47*1000*$H152 -> 0 | X8: =$I146*$H$24*1000*$H146 -> 0 | Y8: =SUM(S8:X8) -> 0 | Z8: 0 | AA8: =SUM(Y8:Z8) -> 0 | AB8: GAS01 | AC8: mbtu | AD8: =ROUND((B146*B$24*1000*1000)+(B152*B$47*1000*1000)+(E146*E$24*1000*1000)+(E152*E$47*1000*1000)+(H146*H$24*1000*1000)+(H152*H$47*1000*1000),0) -> 0 | AE8: =Y8/AD8 -> #DIV/0! | AF8: =Y8/$AF$24/1000 -> #DIV/0! | AG8: 0.042004912 | AH8: =IF($AF$21<$AG$21,AF8,IF($AF$12<$AG$12,AF8,IF(AND($AF$12>$AG$12,$AF$20<$AG$20),($AG$12+($AG$20-$AF$20))/$AF$12*AF8,AF8/$AF$12*$AG$12))) -> #DIV/0! | AI8: =AH8*$Y$24*1000 -> #DIV/0! | AJ8: =AI8/AD8 -> #DIV/0! | AK8: =Y8-AI8 -> #DIV/0! | AL8: =ROUND($B146*$B$24*1000*1000,0) -> 0 | AM8: =ROUND($B152*$B$47*1000*1000,0) -> 0 | AN8: =ROUND($E152*$E$47*1000*1000,0) -> 0 | AO8: =ROUND($E146*$E$24*1000*1000,0) -> 0 | AP8: =ROUND($H152*$H$47*1000*1000,0) -> 0 | AQ8: =ROUND($H146*$H$24*1000*1000,0) -> 0 | AR8: =IF($B$24<>0,ROUND(AL8/B$24,3),0) -> 0 | AS8: =ROUND(AM8/B$47,3) -> #DIV/0! | AT8: =IF(E$47<>0,ROUND(AN8/E$47,3),0) -> 0 | AU8: =IF(E$24<>0,ROUND(AO8/E$24,3),0) -> 0 | AV8: =IF(H$47<>0,ROUND(AP8/H$47,3),0) -> 0 | AW8: =IF(H$24<>0,ROUND(AQ8/H$24,3),0) -> 0 | AX8: =AJ8*10000 -> #DIV/0!
A9: R&M Supplies and Service | B9: =IF($B$24<>0,$H$159,0) -> 0 | D9: 0 | E9: =IF(E24<>0,$H$159,0) -> 0 | F9: 0.043366417 | G9: 0.022368421 | H9: =IF(H24<>0,$H$159,0) -> 0 | J9: 0 | S9: =B9*B$24*1000 -> 0 | T9: =B32*B$47*1000 -> 0 | U9: =E32*E$47*1000 -> 0 | V9: =E9*E$24*1000 -> 0 | W9: =H32*H$47*1000 -> 0 | X9: =H9*H$24*1000 -> 0 | Y9: =SUM(S9:X9) -> 0 | Z9: 0 | AA9: =SUM(Y9:Z9) -> 0 | AB9: RMS01 | AC9: lb | AD9: =ROUND((S9/H$159)+(T9/H$159)+(U9/H$159)+(V9/H$159)+(W9/H$159)+(X9/H$159),0) -> #DIV/0! | AE9: =Y9/AD9 -> #DIV/0! | AF9: =Y9/$AF$24/1000 -> #DIV/0! | AG9: 0.019544347 | AH9: =IF($AF$21<$AG$21,AF9,IF($AF$12<$AG$12,AF9,IF(AND($AF$12>$AG$12,$AF$20<$AG$20),($AG$12+($AG$20-$AF$20))/$AF$12*AF9,AF9/$AF$12*$AG$12))) -> #DIV/0! | AI9: =AH9*$Y$24*1000 -> #DIV/0! | AJ9: =AI9/AD9 -> #DIV/0! | AK9: =Y9-AI9 -> #DIV/0! | AL9: =S9/$AE9 -> #DIV/0! | AM9: =T9/$AE9 -> #DIV/0! | AN9: =U9/$AE9 -> #DIV/0! | AO9: =V9/$AE9 -> #DIV/0! | AP9: =W9/$AE9 -> #DIV/0! | AQ9: =X9/$AE9 -> #DIV/0! | AR9: =IF($B$24<>0,ROUND(AL9/B$24,3),0) -> 0 | AS9: =ROUND(AM9/B$47,3) -> #DIV/0! | AT9: =IF(E$47<>0,ROUND(AN9/E$47,3),0) -> 0 | AU9: =IF(E$24<>0,ROUND(AO9/E$24,3),0) -> 0 | AV9: =IF(H$47<>0,ROUND(AP9/H$47,3),0) -> 0 | AW9: =IF(H$24<>0,ROUND(AQ9/H$24,3),0) -> 0 | AX9: =AJ9*10000 -> #DIV/0!
A10: Manufacturing Supplies | B10: =IF($B$24<>0,$H$163,0) -> 0 | D10: 0 | E10: =IF(E24<>0,$H$163,0) -> 0 | F10: 0.00073336258 | G10: 0.00065789474 | H10: =IF($H$24<>0,$H$163,0) -> 0 | J10: 0 | S10: =B10*B$24*1000 -> 0 | T10: =B33*B$47*1000 -> 0 | U10: =E33*E$47*1000 -> 0 | V10: =E10*E$24*1000 -> 0 | W10: =H33*H$47*1000 -> 0 | X10: =H10*H$24*1000 -> 0 | Y10: =SUM(S10:X10) -> 0 | Z10: 0 | AA10: =SUM(Y10:Z10) -> 0 | AB10: MFG01 | AC10: lb | AD10: =ROUND((S10/H$163)+(T10/H$163)+(U10/H$163)+(V10/H$163)+(W10/H$163)+(X10/H$163),0) -> #DIV/0! | AE10: =Y10/AD10 -> #DIV/0! | AF10: =Y10/$AF$24/1000 -> #DIV/0! | AG10: 0.0012510769 | AH10: =IF($AF$21<$AG$21,AF10,IF($AF$12<$AG$12,AF10,IF(AND($AF$12>$AG$12,$AF$20<$AG$20),($AG$12+($AG$20-$AF$20))/$AF$12*AF10,AF10/$AF$12*$AG$12))) -> #DIV/0! | AI10: =AH10*$Y$24*1000 -> #DIV/0! | AJ10: =AI10/AD10 -> #DIV/0! | AK10: =Y10-AI10 -> #DIV/0! | AL10: =S10/$AE10 -> #DIV/0! | AM10: =T10/$AE10 -> #DIV/0! | AN10: =U10/$AE10 -> #DIV/0! | AO10: =V10/$AE10 -> #DIV/0! | AP10: =W10/$AE10 -> #DIV/0! | AQ10: =X10/$AE10 -> #DIV/0! | AR10: =IF($B$24<>0,ROUND(AL10/B$24,3),0) -> 0 | AS10: =ROUND(AM10/B$47,3) -> #DIV/0! | AT10: =IF(E$47<>0,ROUND(AN10/E$47,3),0) -> 0 | AU10: =IF(E$24<>0,ROUND(AO10/E$24,3),0) -> 0 | AV10: =IF(H$47<>0,ROUND(AP10/H$47,3),0) -> 0 | AW10: =IF(H$24<>0,ROUND(AQ10/H$24,3),0) -> 0 | AX10: =AJ10*10000 -> #DIV/0!
A11: Other variable | B11: =IF($B$24<>0,$H$166,0) -> 0 | D11: 0 | E11: =IF(E24<>0,$H$166,0) -> 0 | F11: 0.010235236 | G11: 0.0046052632 | H11: =IF($H$24<>0,$H$166,0) -> 0 | J11: 0 | S11: =B11*B$24*1000 -> 0 | T11: =B34*B$47*1000 -> 0 | U11: =E34*E$47*1000 -> 0 | V11: =E11*E$24*1000 -> 0 | W11: =H34*H$47*1000 -> 0 | X11: =H11*H$24*1000 -> 0 | Y11: =SUM(S11:X11) -> 0 | Z11: 0 | AA11: =SUM(Y11:Z11) -> 0 | AB11: VAR01 | AC11: lb | AD11: =ROUND((S11/H$166)+(T11/H$166)+(U11/H$166)+(V11/H$166)+(W11/H$166)+(X11/H$166),0) -> #DIV/0! | AE11: =Y11/AD11 -> #DIV/0! | AF11: =Y11/$AF$24/1000 -> #DIV/0! | AG11: 0.0037333371 | AH11: =IF($AF$21<$AG$21,AF11,IF($AF$12<$AG$12,AF11,IF(AND($AF$12>$AG$12,$AF$20<$AG$20),($AG$12+($AG$20-$AF$20))/$AF$12*AF11,AF11/$AF$12*$AG$12))) -> #DIV/0! | AI11: =AH11*$Y$24*1000 -> #DIV/0! | AJ11: =AI11/AD11 -> #DIV/0! | AK11: =Y11-AI11 -> #DIV/0! | AL11: =S11/$AE11 -> #DIV/0! | AM11: =T11/$AE11 -> #DIV/0! | AN11: =U11/$AE11 -> #DIV/0! | AO11: =V11/$AE11 -> #DIV/0! | AP11: =W11/$AE11 -> #DIV/0! | AQ11: =X11/$AE11 -> #DIV/0! | AR11: =IF($B$24<>0,ROUND(AL11/B$24,3),0) -> 0 | AS11: =ROUND(AM11/B$47,3) -> #DIV/0! | AT11: =IF(E$47<>0,ROUND(AN11/E$47,3),0) -> 0 | AU11: =IF(E$24<>0,ROUND(AO11/E$24,3),0) -> 0 | AV11: =IF(H$47<>0,ROUND(AP11/H$47,3),0) -> 0 | AW11: =IF(H$24<>0,ROUND(AQ11/H$24,3),0) -> 0 | AX11: =AJ11*10000 -> #DIV/0!
A12: Total Variable Costs | B12: =SUM(B6:B11) -> 0 | D12: =SUM(D6:D11) -> 0 | E12: =SUM(E6:E11) -> 0 | F12: =SUM(F6:F11) -> 0.30531947 | G12: =SUM(G6:G11) -> 0.11520496 | H12: =SUM(H6:H11) -> 0 | J12: =SUM(J6:J11) -> 0 | S12: =SUM(S7:S11) -> 0 | T12: =SUM(T7:T11) -> 0 | U12: =SUM(U7:U11) -> 0 | V12: =SUM(V7:V11) -> #DIV/0! | W12: =SUM(W7:W11) -> 0 | X12: =SUM(X7:X11) -> 0 | Y12: =SUM(Y7:Y11) -> #DIV/0! | Z12: =SUM(Z7:Z11) -> 0 | AA12: =SUM(AA7:AA11) -> #DIV/0! | AF12: =SUM(AF7:AF11) -> #DIV/0! | AG12: =SUM(AG7:AG11) -> 0.081424459 | AH12: =SUM(AH7:AH11) -> #DIV/0! | AI12: =SUM(AI7:AI11) -> #DIV/0! | AK12: =SUM(AK7:AK11) -> #DIV/0!
A14: Production Labor | B14: =IF($B$24<>0,$F$112/$B$49/1000,0) -> 0 | D14: 0 | E14: =IF(E24<>0,$F$112/$B$49/1000,0) -> 0 | F14: 0.055685781 | G14: 0.02638428 | H14: =IF($H$24<>0,$F$112/$B$49/1000,0) -> 0 | J14: 0 | S14: =B14*B$24*1000 -> 0 | T14: =B37*B$47*1000 -> 0 | U14: =E37*E$47*1000 -> 0 | V14: =E14*E$24*1000 -> 0 | W14: =H37*H$47*1000 -> 0 | X14: =H14*H$24*1000 -> 0 | Y14: =SUM(S14:X14) -> 0 | Z14: =-$D$115 -> 0 | AA14: =SUM(Y14:Z14) -> 0 | AB14: DLAB01 | AC14: hr | AD14: =ROUND((S14/C$116)+(T14/C$116)+(U14/C$116)+(V14/C$116)+(W14/C$116)+(X14/C$116),0) -> #DIV/0! | AE14: =Y14/AD14 -> #DIV/0! | AF14: =Y14/$AF$24/1000 -> #DIV/0! | AG14: 0.011488554 | AH14: =IF($AF$21<$AG$21,AF14,IF($AF$20<$AG$20,AF14,IF(AND($AF$20>$AG$20,$AF$12<$AG$12),($AG$20+($AG$12-$AF$12))/$AF$20*AF14,AF14/$AF$20*$AG$20))) -> #DIV/0! | AI14: =AH14*$Y$24*1000 -> #DIV/0! | AJ14: =AI14/AD14 -> #DIV/0! | AK14: =Y14-AI14 -> #DIV/0! | AL14: =ROUND(S14/$C116,0) -> #DIV/0! | AM14: =ROUND(T14/$C116,0) -> #DIV/0! | AN14: =ROUND(U14/$C116,0) -> #DIV/0! | AO14: =ROUND(V14/$C116,0) -> #DIV/0! | AP14: =ROUND(W14/$C116,0) -> #DIV/0! | AQ14: =ROUND(X14/$C116,0) -> #DIV/0! | AR14: =IF($B$24<>0,ROUND(AL14/B$24,3),0) -> 0 | AS14: =ROUND(AM14/B$47,3) -> #DIV/0! | AT14: =IF(E$47<>0,ROUND(AN14/E$47,3),0) -> 0 | AU14: =IF(E$24<>0,ROUND(AO14/E$24,3),0) -> 0 | AV14: =IF(H$47<>0,ROUND(AP14/H$47,3),0) -> 0 | AW14: =IF(H$24<>0,ROUND(AQ14/H$24,3),0) -> 0 | AX14: =AJ14*10000 -> #DIV/0!
A15: Repairs & Maintenance Labor | B15: =IF($B$24<>0,$F$113/$B$49/1000,0) -> 0 | D15: 0 | E15: =IF(E24<>0,$F$113/$B$49/1000,0) -> 0 | F15: 0.019535758 | G15: 0.00902044 | H15: =IF($H$24<>0,$F$113/$B$49/1000,0) -> 0 | J15: 0 | S15: =B15*B$24*1000 -> 0 | T15: =B38*B$47*1000 -> 0 | U15: =E38*E$47*1000 -> 0 | V15: =E15*E$24*1000 -> 0 | W15: =H38*H$47*1000 -> 0 | X15: =H15*H$24*1000 -> 0 | Y15: =SUM(S15:X15) -> 0 | Z15: =-$H$115 -> 0 | AA15: =SUM(Y15:Z15) -> 0 | AB15: MLAB01 | AC15: hr | AD15: =ROUND((S15/G$116)+(T15/G$116)+(U15/G$116)+(V15/G$116)+(W15/G$116)+(X15/G$116),0) -> #DIV/0! | AE15: =Y15/AD15 -> #DIV/0! | AF15: =Y15/$AF$24/1000 -> #DIV/0! | AG15: 0.007650221 | AH15: =IF($AF$21<$AG$21,AF15,IF($AF$20<$AG$20,AF15,IF(AND($AF$20>$AG$20,$AF$12<$AG$12),($AG$20+($AG$12-$AF$12))/$AF$20*AF15,AF15/$AF$20*$AG$20))) -> #DIV/0! | AI15: =AH15*$Y$24*1000 -> #DIV/0! | AJ15: =AI15/AD15 -> #DIV/0! | AK15: =Y15-AI15 -> #DIV/0! | AL15: =ROUND(S15/$G$116,0) -> #DIV/0! | AM15: =ROUND(T15/$G$116,0) -> #DIV/0! | AN15: =ROUND(U15/$G$116,0) -> #DIV/0! | AO15: =ROUND(V15/$G$116,0)-1 -> #DIV/0! | AP15: =ROUND(W15/$G$116,0) -> #DIV/0! | AQ15: =ROUND(X15/$G$116,0) -> #DIV/0! | AR15: =IF($B$24<>0,ROUND(AL15/B$24,3),0) -> 0 | AS15: =ROUND(AM15/B$47,3) -> #DIV/0! | AT15: =IF(E$47<>0,ROUND(AN15/E$47,3),0) -> 0 | AU15: =IF(E$24<>0,ROUND(AO15/E$24,3),0) -> 0 | AV15: =IF(H$47<>0,ROUND(AP15/H$47,3),0) -> 0 | AW15: =IF(H$24<>0,ROUND(AQ15/H$24,3),0) -> 0 | AX15: =AJ15*10000 -> #DIV/0!
A16: Indirect Payroll Costs (Benefits) | B16: =IF(B24<>0,$F$115/$B$49/1000,0) -> 0 | D16: 0 | E16: =IF(E24<>0,$F$115/$B$49/1000,0) -> 0 | F16: 0.01706523 | G16: 0.013928937 | H16: =IF($H$24<>0,$F$115/$B$49/1000,0) -> 0 | J16: 0 | S16: =B16*B$24*1000 -> 0 | T16: =B39*B$47*1000 -> 0 | U16: =E39*E$47*1000 -> 0 | V16: =E16*E$24*1000 -> 0 | W16: =H39*H$47*1000 -> 0 | X16: =H16*H$24*1000 -> 0 | Y16: =SUM(S16:X16) -> 0 | Z16: =-$D$122 -> 0 | AA16: =SUM(Y16:Z16) -> 0 | AB16: IPC01 | AC16: hr | AD16: =ROUND((S16/C$123)+(T16/C$123)+(U16/C$123)+(V16/C$123)+(W16/C$123)+(X16/C$123),0) -> #DIV/0! | AE16: =Y16/AD16 -> #DIV/0! | AF16: =Y16/$AF$24/1000 -> #DIV/0! | AG16: 0.0088563301 | AH16: =IF($AF$21<$AG$21,AF16,IF($AF$20<$AG$20,AF16,IF(AND($AF$20>$AG$20,$AF$12<$AG$12),($AG$20+($AG$12-$AF$12))/$AF$20*AF16,AF16/$AF$20*$AG$20))) -> #DIV/0! | AI16: =AH16*$Y$24*1000 -> #DIV/0! | AJ16: =AI16/AD16 -> #DIV/0! | AK16: =Y16-AI16 -> #DIV/0! | AL16: =ROUND(S16/$C123,0) -> #DIV/0! | AM16: =ROUND(T16/$C123,0) -> #DIV/0! | AN16: =ROUND(U16/$C123,0) -> #DIV/0! | AO16: =ROUND(V16/$C123,0) -> #DIV/0! | AP16: =ROUND(W16/$C123,0) -> #DIV/0! | AQ16: =ROUND(X16/$C123,0) -> #DIV/0! | AR16: =IF($B$24<>0,ROUND(AL16/B$24,3),0) -> 0 | AS16: =ROUND(AM16/B$47,3) -> #DIV/0! | AT16: =IF(E$47<>0,ROUND(AN16/E$47,3),0) -> 0 | AU16: =IF(E$24<>0,ROUND(AO16/E$24,3),0) -> 0 | AV16: =IF(H$47<>0,ROUND(AP16/H$47,3),0) -> 0 | AW16: =IF(H$24<>0,ROUND(AQ16/H$24,3),0) -> 0 | AX16: =AJ16*10000 -> #DIV/0!
A17: Supervision | B17: =IF($B$24<>0,$F$114/$B$49/1000,0) -> 0 | D17: 0 | E17: =IF(E24<>0,$F$114/$B$49/1000,0) -> 0 | F17: 0.0045810516 | G17: 0.0015771316 | H17: =IF($H$24<>0,$F$114/$B$49/1000,0) -> 0 | J17: 0 | S17: =B17*B$24*1000 -> 0 | T17: =B40*B$47*1000 -> 0 | U17: =E40*E$47*1000 -> 0 | V17: =E17*E$24*1000 -> 0 | W17: =H40*H$47*1000 -> 0 | X17: =H17*H$24*1000 -> 0 | Y17: =SUM(S17:X17) -> 0 | Z17: =C176/($C$184+$C$185)*$C$185 -> 0 | AA17: =SUM(Y17:Z17) -> 0 | AB17: SUP01 | AC17: lb | AD17: =ROUND((S17/F$176)+(T17/F$176)+(U17/F$176)+(V17/F$176)+(W17/F$176)+(X17/F$176),0) -> #DIV/0! | AE17: =Y17/AD17 -> #DIV/0! | AF17: =Y17/$AF$24/1000 -> #DIV/0! | AG17: 0.0021273119 | AH17: =IF($AF$21<$AG$21,AF17,IF($AF$20<$AG$20,AF17,IF(AND($AF$20>$AG$20,$AF$12<$AG$12),($AG$20+($AG$12-$AF$12))/$AF$20*AF17,AF17/$AF$20*$AG$20))) -> #DIV/0! | AI17: =AH17*$Y$24*1000 -> #DIV/0! | AJ17: =AI17/AD17 -> #DIV/0! | AK17: =Y17-AI17 -> #DIV/0! | AL17: =S17/$AE17 -> #DIV/0! | AM17: =T17/$AE17 -> #DIV/0! | AN17: =U17/$AE17 -> #DIV/0! | AO17: =V17/$AE17 -> #DIV/0! | AP17: =W17/$AE17 -> #DIV/0! | AQ17: =X17/$AE17 -> #DIV/0! | AR17: =IF($B$24<>0,ROUND(AL17/B$24,3),0) -> 0 | AS17: =ROUND(AM17/B$47,3) -> #DIV/0! | AT17: =IF(E$47<>0,ROUND(AN17/E$47,3),0) -> 0 | AU17: =IF(E$24<>0,ROUND(AO17/E$24,3),0) -> 0 | AV17: =IF(H$47<>0,ROUND(AP17/H$47,3),0) -> 0 | AW17: =IF(H$24<>0,ROUND(AQ17/H$24,3),0) -> 0 | AX17: =AJ17*10000 -> #DIV/0!
A18: Depreciation | B18: =IF($B$24<>0,$B$178/$B$49/1000,0) -> 0 | D18: 0 | E18: =IF(E24<>0,$B$178/$B$49/1000,0) -> 0 | F18: 0.0038559807 | G18: 0.0016578947 | H18: =IF($H$24<>0,$B$178/$B$49/1000,0) -> 0 | J18: 0 | S18: =B18*B$24*1000 -> 0 | T18: =B41*B$47*1000 -> 0 | U18: =E41*E$47*1000 -> 0 | V18: =E18*E$24*1000 -> 0 | W18: =H41*H$47*1000 -> 0 | X18: =H18*H$24*1000 -> 0 | Y18: =SUM(S18:X18) -> 0 | Z18: =C178/($C$184+$C$185)*$C$185 -> 0 | AA18: =SUM(Y18:Z18) -> 0 | AB18: DEP01 | AC18: lb | AD18: =ROUND((S18/F$178)+(T18/F$178)+(U18/F$178)+(V18/F$178)+(W18/F$178)+(X18/F$178),0) -> #DIV/0! | AE18: =Y18/AD18 -> #DIV/0! | AF18: =Y18/$AF$24/1000 -> #DIV/0! | AG18: 0.032747211 | AH18: =IF($AF$21<$AG$21,AF18,IF($AF$20<$AG$20,AF18,IF(AND($AF$20>$AG$20,$AF$12<$AG$12),($AG$20+($AG$12-$AF$12))/$AF$20*AF18,AF18/$AF$20*$AG$20))) -> #DIV/0! | AI18: =AH18*$Y$24*1000 -> #DIV/0! | AJ18: =AI18/AD18 -> #DIV/0! | AK18: =Y18-AI18 -> #DIV/0! | AL18: =S18/$AE18 -> #DIV/0! | AM18: =T18/$AE18 -> #DIV/0! | AN18: =U18/$AE18 -> #DIV/0! | AO18: =V18/$AE18 -> #DIV/0! | AP18: =W18/$AE18 -> #DIV/0! | AQ18: =X18/$AE18 -> #DIV/0! | AR18: =IF($B$24<>0,ROUND(AL18/B$24,3),0) -> 0 | AS18: =ROUND(AM18/B$47,3) -> #DIV/0! | AT18: =IF(E$47<>0,ROUND(AN18/E$47,3),0) -> 0 | AU18: =IF(E$24<>0,ROUND(AO18/E$24,3),0) -> 0 | AV18: =IF(H$47<>0,ROUND(AP18/H$47,3),0) -> 0 | AW18: =IF(H$24<>0,ROUND(AQ18/H$24,3),0) -> 0 | AX18: =AJ18*10000 -> #DIV/0!
A19: Insurance & Taxes | B19: =IF($B$24<>0,$B$177/$B$49/1000,0) -> 0 | D19: 0 | E19: =IF(E24<>0,$B$177/E26/1000,0) -> 0 | F19: 0.010801566 | G19: 0.0058026316 | H19: =IF($H$24<>0,$B$177/$B$49/1000,0) -> 0 | J19: 0 | S19: =B19*B$24*1000 -> 0 | T19: =B42*B$47*1000 -> 0 | U19: =E42*E$47*1000 -> 0 | V19: =E19*E$24*1000 -> 0 | W19: =H42*H$47*1000 -> 0 | X19: =H19*H$24*1000 -> 0 | Y19: =SUM(S19:X19) -> 0 | Z19: =C177/($C$184+$C$185)*$C$185 -> 0 | AA19: =SUM(Y19:Z19) -> 0 | AB19: INS01 | AC19: lb | AD19: =ROUND((S19/F$177)+(T19/F$177)+(U19/F$177)+(V19/F$177)+(W19/F$177)+(X19/F$177),0) -> #DIV/0! | AE19: =Y19/AD19 -> #DIV/0! | AF19: =Y19/$AF$24/1000 -> #DIV/0! | AG19: 0.0073609622 | AH19: =IF($AF$21<$AG$21,AF19,IF($AF$20<$AG$20,AF19,IF(AND($AF$20>$AG$20,$AF$12<$AG$12),($AG$20+($AG$12-$AF$12))/$AF$20*AF19,AF19/$AF$20*$AG$20))) -> #DIV/0! | AI19: =AH19*$Y$24*1000 -> #DIV/0! | AJ19: =AI19/AD19 -> #DIV/0! | AK19: =Y19-AI19 -> #DIV/0! | AL19: =S19/$AE19 -> #DIV/0! | AM19: =T19/$AE19 -> #DIV/0! | AN19: =U19/$AE19 -> #DIV/0! | AO19: =V19/$AE19 -> #DIV/0! | AP19: =W19/$AE19 -> #DIV/0! | AQ19: =X19/$AE19 -> #DIV/0! | AR19: =IF($B$24<>0,ROUND(AL19/B$24,3),0) -> 0 | AS19: =ROUND(AM19/B$47,3) -> #DIV/0! | AT19: =IF(E$47<>0,ROUND(AN19/E$47,3),0) -> 0 | AU19: =IF(E$24<>0,ROUND(AO19/E$24,3),0) -> 0 | AV19: =IF(H$47<>0,ROUND(AP19/H$47,3),0) -> 0 | AW19: =IF(H$24<>0,ROUND(AQ19/H$24,3),0) -> 0 | AX19: =AJ19*10000 -> #DIV/0!
A20: Total Fixed Costs | B20: =SUM(B14:B19) -> 0 | C20: =SUM(C14:C19) -> 0 | D20: =SUM(D14:D19) -> 0 | E20: =SUM(E14:E19) -> 0 | F20: =SUM(F14:F19) -> 0.11152537 | G20: =SUM(G14:G19) -> 0.058371315 | H20: =SUM(H14:H19) -> 0 | I20: =SUM(I14:I19) -> 0 | J20: =SUM(J14:J19) -> 0 | S20: =SUM(S14:S19) -> 0 | T20: =SUM(T14:T19) -> 0 | U20: =SUM(U14:U19) -> 0 | V20: =SUM(V14:V19) -> 0 | W20: =SUM(W14:W19) -> 0 | X20: =SUM(X14:X19) -> 0 | Y20: =SUM(Y14:Y19) -> 0 | Z20: =SUM(Z14:Z19) -> 0 | AA20: =SUM(AA14:AA19) -> 0 | AF20: =SUM(AF14:AF19) -> #DIV/0! | AG20: =SUM(AG14:AG19) -> 0.07023059 | AH20: =SUM(AH14:AH19) -> #DIV/0! | AI20: =SUM(AI14:AI19) -> #DIV/0! | AK20: =SUM(AK14:AK19) -> #DIV/0!
A21: Excess Costs | C21: -0.0273 | F21: -0.050457361 | S21: =S12+S20 -> 0 | T21: =T12+T20 -> 0 | U21: =U12+U20 -> 0 | V21: =V12+V20 -> #DIV/0! | W21: =W12+W20 -> 0 | X21: =X12+X20 -> 0 | Y21: =Y12+Y20 -> #DIV/0! | Z21: =Z12+Z20 -> 0 | AA21: =AA12+AA20 -> #DIV/0! | AB21: CCtr Total | AF21: =AF12+AF20 -> #DIV/0! | AG21: =AG12+AG20 -> 0.15165505 | AH21: =AH12+AH20 -> #DIV/0! | AI21: =AI12+AI20 -> #DIV/0! | AK21: =AK12+AK20 -> #DIV/0!
A22: TOTAL COSTS PER POUND | B22: =B12+B20 -> 0 | C22: =+C20+C21+C12 -> -0.0273 | D22: =D12+D20 -> 0 | E22: =E12+E20 -> 0 | F22: =F12+F20+F21 -> 0.36638748 | G22: =G12+G20 -> 0.17357627 | H22: =H12+H20 -> 0 | I22: =I12+I20 -> 0 | J22: =J12+J20 -> 0 | S22: =IF(B24<>0,ROUND(S21/(B24*1000),5),0) -> 0 | T22: =IF(B47<>0,ROUND(T21/(B47*1000),5),0) -> 0 | U22: =IF(E47<>0,ROUND(U21/(E47*1000),5),0) -> 0 | V22: =IF(E24<>0,ROUND(V21/(E24*1000),5),0) -> 0 | W22: =IF(H47<>0,ROUND(W21/(H47*1000),5),0) -> 0 | X22: =IF(H24<>0,ROUND(X21/(H24*1000),5),0) -> 0 | Y22: =Y21/Y24/1000 -> #DIV/0! | Z22: 0 | AA22: =ROUND(AA21/(B49*1000),5) -> #DIV/0! | AB22: Excl Matl | AI22: =AI21/AI24/1000 -> #DIV/0! | AK22: =AK21/AK24/1000 -> #DIV/0!
S23: =ROUND(S22+B6,5) -> 0 | T23: =ROUND(T22+B29,5) -> 0 | U23: =ROUND(U22+E29,5) -> 0 | V23: =ROUND(V22+E6,5) -> 0 | W23: =ROUND(W22+H29,5) -> 0 | X23: =ROUND(X22+H6,5) -> 0 | Y23: =Y22+(($B$6*$B$24*1000+$B$29*$B$47*1000+$E$29*$E$47*1000+$H$6*$H$24*1000+$H$29*$H$47*1000+$E$6*$E$24*1000)/($B$49*1000)) -> #DIV/0! | Z23: 0 | AA23: =AA22+(($B$6*$B$24*1000+$B$29*$B$47*1000+$E$6*$E$24*1000+$E$29*$E$47*1000+$H$6*$H$24*1000+$H$29*$H$47*1000)/($B$49*1000)) -> #DIV/0! | AB23: Incl Matl
A24: PRODUCTION ( in 000 lbs ) | B24: =B54 -> 0 | C24: 6211 | D24: 0 | E24: =B57 -> 0 | F24: 3204 | G24: 51000 | H24: =B58 -> 0 | I24: 4207 | J24: 0 | S24: =B24 -> 0 | T24: =B47 -> 0 | U24: =E47 -> 0 | V24: =E24 -> 0 | W24: =H47 -> 0 | X24: =H24 -> 0 | Y24: =SUM(S24:X24) -> 0 | Z24: 0 | AA24: =SUM(Y24:Z24) -> 0 | AF24: =Y24 -> 0 | AI24: =Y24 -> 0 | AK24: =Y24 -> 0
B26: CP | E26: HSP | H26: Nanomite C | AS26: 0.936
B27: =B4 -> 25 Standard | C27: 23 Actual | D27: =+D4 -> 22 Standard | E27: =E4 -> 25 Standard | F27: =+C27 -> 23 Actual | G27: =+D27 -> 22 Standard | H27: =H4 -> 25 Standard | I27: 23 Actual | J27: =+J4 -> 22 Standard | AS27: 0.264
C28: (Jan-Aug) | F28: (Jan-Aug) | I28: (Jan-Aug) | AS28: 286
A29: Materials | B29: =IF($B$47<>0,$D$88,0) -> 0 | C29: 0.1396 | D29: 0.06037434 | E29: =IF(E47<>0,$D$88,0) -> 0 | F29: 0.0865 | G29: 0 | H29: =IF(H47<>0,$L$80,0) -> 0 | I29: 0.0792 | J29: 0.02 | AS29: 8000
A30: Electricity | B30: =IF(B47<>0,$D$151,0) -> 0 | C30: 0.0273 | D30: 0.018883379 | E30: =IF(E47<>0,$G$151,0) -> 0 | F30: 0.0294 | G30: 0 | H30: =IF(H47<>0,$J$151,0) -> 0 | I30: 0.0124 | J30: 0.0027366213 | AS30: 1.2
A31: Gas | B31: =IF(B47<>0,$D$152,0) -> 0 | C31: 0.0379 | D31: 0.04184 | E31: =IF(E47<>0,$G$152,0) -> 0 | F31: 0.0465 | G31: 0 | H31: =IF(H47<>0,$J$152,0) -> 0 | I31: 0 | J31: 0
A32: R&M Supplies and Service | B32: =IF(B47<>0,$H$159,0) -> 0 | C32: 0.0358 | D32: 0.022368421 | E32: =IF(E47<>0,$H$159,0) -> 0 | F32: 0.0304 | G32: 0 | H32: =IF(H47<>0,$H$159,0) -> 0 | I32: 0.0164 | J32: 0.022368421
A33: Manufacturing Supplies | B33: =IF(B47<>0,$H$163,0) -> 0 | C33: 0.0006 | D33: 0.00065789474 | E33: =IF(E47<>0,$H$163,0) -> 0 | F33: 0.002 | G33: 0 | H33: =IF(H47<>0,$H$163,0) -> 0 | I33: 0.0014 | J33: 0.00065789474
A34: Other variable | B34: =IF($B$47<>0,$H$166,0) -> 0 | C34: 0.0101 | D34: 0.0046052632 | E34: =IF(E47<>0,$H$166,0) -> 0 | F34: 0.0118 | G34: 0 | H34: =IF(H47<>0,$H$166,0) -> 0 | I34: 0.0108 | J34: 0.0046052632
A35: Total Variable Costs | B35: =SUM(B29:B34) -> 0 | C35: =SUM(C29:C34) -> 0.2513 | D35: =SUM(D29:D34) -> 0.1487293 | E35: =SUM(E29:E34) -> 0 | F35: =SUM(F29:F34) -> 0.2066 | G35: =SUM(G29:G34) -> 0 | H35: =SUM(H29:H34) -> 0 | I35: =SUM(I29:I34) -> 0.1202 | J35: =SUM(J29:J34) -> 0.0503682
A37: Production Labor | B37: =IF(B47<>0,$F$112/$B$49/1000,0) -> 0 | C37: 0.0445 | D37: 0.02638428 | E37: =IF(E47<>0,$F$112/$B$49/1000,0) -> 0 | F37: 0.0483 | G37: 0 | H37: =IF(H47<>0,$F$112/$B$49/1000,0) -> 0 | I37: 0.0451 | J37: 0.02638428
A38: Repairs & Maintenance Labor | B38: =IF(B47<>0,$F$113/$B$49/1000,0) -> 0 | C38: 0.015 | D38: 0.00902044 | E38: =IF(E47<>0,$F$113/$B$49/1000,0) -> 0 | F38: 0.0144 | G38: 0 | H38: =IF(H47<>0,$F$113/$B$49/1000,0) -> 0 | I38: 0.0156 | J38: 0.00902044
A39: Indirect Payroll Costs (Benefits) | B39: =IF(B47<>0,$F$115/$B$49/1000,0) -> 0 | C39: 0.0194 | D39: 0.013928937 | E39: =IF(E47<>0,$F$115/$B$49/1000,0) -> 0 | F39: 0.0196 | G39: 0 | H39: =IF(H47<>0,$F$115/$B$49/1000,0) -> 0 | I39: 0.0285 | J39: 0.013928937
A40: Supervision | B40: =IF($B$47<>0,$F$114/$B$49/1000,0) -> 0 | C40: 0.0018 | D40: 0.0015771316 | E40: =IF(E47<>0,$F$114/$B$49/1000,0) -> 0 | F40: 0.0014 | G40: 0 | H40: =IF(H47<>0,$F$114/$B$49/1000,0) -> 0 | I40: 0.0022 | J40: 0.0015771316
A41: Depreciation | B41: =IF(B47<>0,$B$178/$B$49/1000,0) -> 0 | C41: 0.0043 | D41: 0.0016578947 | E41: =IF(E47<>0,$B$178/$B$49/1000,0) -> 0 | F41: 0.0042 | G41: 0 | H41: =IF(H47<>0,$B$178/$B$49/1000,0) -> 0 | I41: 0.0067 | J41: 0.0016578947
A42: Insurance & Taxes | B42: =IF(B47<>0,$B$177/B49/1000,0) -> 0 | C42: 0.0093 | D42: 0.0058026316 | E42: =IF(E47<>0,$B$177/B49/1000,0) -> 0 | F42: 0.0098 | G42: 0 | H42: =IF(H47<>0,$B$177/$B$49/1000,0) -> 0 | I42: 0.014 | J42: 0.0058026316
A43: Total Fixed Costs | B43: =SUM(B37:B42) -> 0 | C43: =SUM(C37:C42) -> 0.0943 | D43: =SUM(D37:D42) -> 0.058371315 | E43: =SUM(E37:E42) -> 0 | F43: =SUM(F37:F42) -> 0.0977 | G43: =SUM(G37:G42) -> 0 | H43: =SUM(H37:H42) -> 0 | I43: =SUM(I37:I42) -> 0.1121 | J43: =SUM(J37:J42) -> 0.058371315
A44: Excess Costs
A45: TOTAL COSTS PER POUND | B45: =B35+B43 -> 0 | C45: =C35+C43+C44 -> 0.3456 | D45: =D35+D43 -> 0.20710061 | E45: =E35+E43 -> 0 | F45: =F35+F43+F44 -> 0.3043 | G45: 0 | H45: =H35+H43 -> 0 | I45: =I35+I43+I44 -> 0.2323 | J45: =+J35+J43 -> 0.10873952
A47: PRODUCTION ( in 000 lbs ) | B47: =B55 -> 0 | C47: 13494 | D47: 22600 | E47: =B56 -> 0 | F47: 1391 | G47: 0 | H47: =B59 -> 0 | I47: 6147 | J47: 2400
A49: TOTAL PLANT PRODUCTION ( in 000 lbs) | B49: =B24+E24+H24+B47+E47+H47 -> 0 | C49: =C24+F24+I24+C47+F47+I47 -> 34654 | D49: 76000
A51: Variable Costs - Material | B51: Purchase Price/lb * Yield Factor * Scrap Factor * Mix = Std. Cost Contribution
A53: Production Plan: | B53: Pounds (000) | C53: Product Split | D53: Days
A54: HT (foundry) | B54: ='2025 Summary'!$C$4 -> 0 | C54: =B54/$B$60 -> #DIV/0!
A55: CarboProp | B55: ='2025 Summary'!D$4 -> 0 | C55: =B55/$B$60 -> #DIV/0! | D55: =B55/180/2 -> 0
A56: CarboHSP | B56: ='2025 Summary'!E$4 -> 0 | C56: =B56/$B$60 -> #DIV/0! | D56: =B56/200/2 -> 0
A57: Bauxite Pellets | B57: ='2025 Summary'!$F$4 -> 0 | C57: =B57/$B$60 -> #DIV/0!
A58: ID (foundry) | B58: ='2025 Summary'!$G$4 -> 0 | C58: =B58/$B$60 -> #DIV/0!
A59: Nanomite C | B59: ='2025 Summary'!$H$4 -> 0 | C59: =B59/$B$60 -> #DIV/0! | D59: =B59/200 -> 0
A60: Total | B60: =SUM(B54:B59) -> 0 | C60: =B60/$B$60 -> #DIV/0!
AB61: NEED TO VERIFY ALL FORMULAS IN THE SECTION BELOW: Done
C62: Yield Factor | G62: Mix %
A63: Local Kaolin | B63: Price ($/Ton) | C63: CG | D63: CP | E63: HSP | F63: CL | G63: Cristobalite | H63: CG | I63: CP / ID | J63: HSP | K63: CL | L63: Cristobalite | AE63: price/1000/lb | AM63: Mix%
A64: Arcilla (local kaolin) 30012 | B64: =11.75*2 -> 23.5 | C64: =$C$76*H64 -> 0.2668 | D64: =$C$84*I64 -> 0.056 | E64: =$G$84*J64 -> 0 | F64: =$K$84*K64 -> 0 | G64: =$K$84*L64 -> 0 | H64: 0.667 | I64: 0.14 | J64: 0 | K64: 1 | L64: 0 | AB64: 30012/U103 | AE64: =B64/2000*1000 -> 11.75 | AM64: =$AM$76*I64 -> 56 | AO64: =$AO$84*K64 -> 0
A65: Dixon (local kaolin) | B65: 0 | C65: =$C$76*H65 -> 0 | D65: =$C$84*I65 -> 0 | E65: =$G$84*J65 -> 0 | F65: =$K$84*K65 -> 0 | G65: =$K$84*L65 -> 0 | H65: 0 | I65: 0 | J65: 0 | K65: 0 | L65: 0 | AB65: 30012/U103 | AE65: =B65/2000*1000 -> 0 | AM65: =$AM$76*I65 -> 0 | AO65: =$AO$85*J65 -> 0
C66: =SUM(C64:C65) -> 0.2668 | D66: =SUM(D64:D65) -> 0.056 | E66: =SUM(E64:E65) -> 0 | F66: =SUM(F64:F65) -> 0 | G66: =SUM(G64:G65) -> 0
A67: Bauxite: | AO67: =$AO$85*J66 -> 0
A68: MRN (30006) Lord Allen & ECT | B68: =60.33+8+44 -> 112.33 | C68: =$C$77*H68 -> 0.1837 | D68: =$C$85*I68 -> 0.98 | E68: =$G$85*J68 -> 1.8 | F68: =$K$85*K68 -> 0 | G68: =$K$85*L68 -> 0 | H68: 0.167 | I68: 0.56 | J68: 1 | K68: 0 | L68: 0 | AB68: 30006/U103 | AE68: =B68/2000*1000 -> 56.165 | AM68: =$AM$77*I68 -> 980 | AN68: =$AN$85*I68 -> 980 | AO68: =$AO$85*J68 -> 1000
A69: Rusal (30008) Lord Allen & ECT | B69: =56.29*2 -> 112.58 | C69: =$C$77*H69 -> 0 | D69: =$C$85*I69 -> 0 | E69: =$G$85*J69 -> 0 | F69: =$K$85*K69 -> 0 | G69: =$K$85*L69 -> 0 | H69: 0 | I69: 0 | J69: 0 | K69: 0 | L69: 0 | AB69: 30008/U103 | AE69: =B69/2000*1000 -> 56.29 | AM69: =$AM$77*I69 -> 0 | AN69: =$AN$85*I69 -> 0 | AO69: =$AO$85*J69 -> 0
A70: Bosai Chem Grade (30002) | B70: 160 | C70: 0 | D70: =$C$85*I70 -> 0 | E70: =$G$85*J70 -> 0 | F70: =$K$85*K70 -> 0 | G70: =$K$85*L70 -> 0 | H70: 0 | I70: 0 | J70: 0 | K70: 0 | L70: 0 | M70: Changed Bosai Chem Grade Price | AB70: 30003/U103 | AE70: =B70/2000*1000 -> 80 | AM70: =$AM$77*I70 -> 0 | AN70: =$AN$85*I70 -> 0
A71: First Bauxite (30440) | B71: =194+44 -> 238 | C71: =$C$77*H71 -> 0.1837 | D71: =$C$85*I71 -> 0.525 | E71: =$G$85*J71 -> 0 | F71: =$K$85*K71 -> 0 | G71: =$K$85*L71 -> 0 | H71: 0.167 | I71: 0.3 | J71: 0 | K71: 0 | L71: 0 | AB71: 30440/U103 | AE71: =B71/2000*1000 -> 119 | AM71: =$AM$77*I71 -> 525 | AN71: =$AN$85*I71 -> 525 | AO71: =$AO$85*J70 -> 0
C72: =SUM(C68:C71) -> 0.3674 | D72: =SUM(D68:D71) -> 1.505 | E72: =SUM(E68:E71) -> 1.8 | F72: =SUM(F68:F71) -> 0 | G72: =SUM(G68:G71) -> 0
B74: HT | F74: Cristobalite | J74: Nanomite | AE74: CG
B75: Price ($/lb) | C75: Yield Factor | D75: Std $ Contrib | F75: Price ($/lb) | G75: Yield Factor | H75: Std $ Contrib | J75: Price ($/lb) | K75: Yield Factor | L75: Std $ Contrib | AE75: price/1000/lb
A76: Local Kaolin | B76: 0.013 | C76: 0.4 | D76: =B76*C76 -> 0.0052 | F76: =($B$64*$L$64+$B$65*$L$65)/2000 -> 0 | G76: 0 | H76: =F76*G76 -> 0 | J76: =($B$64*$L$64+$B$65*$L$65)/2000 -> 0 | K76: 0 | L76: =J76*K76 -> 0 | AB76: 30012/U103 | AE76: =B76*1000 -> 13 | AK76: kaolin | AM76: =IF(B84<>0,D84/B84*1000,0) -> 400
A77: Bauxite | B77: =B71/2000 -> 0.119 | C77: 1.1 | D77: =B77*C77 -> 0.1309 | F77: =($B$68*$L$68+$B$69*$L$69+$B$70*$L$70+$B$71*$L$71)/2000 -> 0 | G77: 0 | H77: =F77*G77 -> 0 | J77: =($B$68*$L$68+$B$69*$L$69+$B$70*$L$70+$B$71*$L$71)/2000 -> 0 | K77: 0 | L77: =J77*K77 -> 0 | AB77: 30060/U103 | AE77: =B77*1000 -> 119 | AK77: bauxite | AM77: =IF(B85<>0,D85/B85*1000,0) -> 1750
A78: Starch (30020) | B78: 0.88 | C78: 0.01 | D78: =B78*C78 -> 0.0088 | F78: =B86 -> 0.726 | G78: 0 | H78: =F78*G78 -> 0 | K78: 0 | L78: =J78*K78 -> 0 | AB78: 30020/U103 | AE78: =B78*1000 -> 880 | AK78: starch | AM78: =IF(B86<>0,D86/B86*1000,0) -> 8
A79: Taggant | D79: 0 | G79: 0 | H79: =F79*G79 -> 0 | K79: 0 | L79: =J79*K79 -> 0
A80: Total Material Cost Per Pound | D80: =SUM(D76:D79) -> 0.1449 | H80: =SUM(H76:H79) -> 0 | L80: 0.08
B82: =B26 -> CP | F82: =E26 -> HSP | J82: Bauxite Pellets | AE82: CP/ID | AG82: CL
B83: Price ($/lb) | C83: Yield Factor | D83: Std $ Contrib | F83: Price ($/lb) | G83: Yield Factor | H83: Std $ Contrib | J83: Price ($/lb) | K83: Yield Factor | L83: Std $ Contrib | AE83: price/1000/lb | AG83: price/1000/lb
A84: Local kaolin | B84: 0.013 | C84: 0.4 | D84: =B84*C84 -> 0.0052 | F84: =($B$64*$J$64+$B$65*$J$65)/2000 -> 0 | G84: 0 | H84: =F84*G84 -> 0 | J84: =($B$64*$K$64+$B$65*$K$65)/2000 -> 0.01175 | K84: 0 | L84: =J84*K84 -> 0 | AB84: 30012/U103 | AE84: =B84*1000 -> 13 | AG84: =J84*1000 -> 11.75 | AN84: =IF(B84<>0,D84/B84*1000,0) -> 400 | AO84: =IF(J84<>0,L84/J84*1000,0) -> 0
A85: Bauxite | B85: 0.067 | C85: 1.75 | D85: =B85*C85 -> 0.11725 | F85: =($B$68*$J$68+$B$69*$J$69+$B$70*$J$70+$B$71*$J$71)/2000 -> 0.056165 | G85: 1.8 | H85: =F85*G85 -> 0.101097 | J85: =(B71/2000*0.75)+(B68/2000*0.25) -> 0.10329125 | K85: 1 | L85: =J85*K85 -> 0.10329125 | AB85: Various (see above) | AE85: =B85*1000 -> 67 | AG85: =J85*1000 -> 103.29125 | AN85: =IF(B85<>0,D85/B85*1000,0) -> 1750 | AO85: =IF(J85<>0,L85/J85*1000,0) -> 1000
A86: Starch (30020) | B86: 0.726 | C86: 0.008 | D86: =B86*C86 -> 0.005808 | F86: =B86 -> 0.726 | G86: 0.008 | H86: =F86*G86 -> 0.005808 | J86: =B86 -> 0.726 | K86: 0.0065 | L86: =J86*K86 -> 0.004719 | M86: Increased starch to 0.8% | AB86: 30020/U103 | AE86: =B86*1000 -> 726 | AG86: =J86*1000 -> 726 | AN86: =IF(B86<>0,D86/B86*1000,0) -> 8 | AO86: =IF(J86<>0,L86/J86*1000,0) -> 6.5
A87: Taggant | D87: 0 | H87: 0 | L87: 0
A88: Total Material Cost Per Pound | D88: =SUM(D84:D86) -> 0.128258 | H88: =SUM(H84:H86) -> 0.106905 | L88: =SUM(L84:L87) -> 0.10801025
A90: Variable Cost - Labor & Benefits - 12 hour shift
AE91: Nov-20 YTD
U92: =$Z$14*$AD92 -> 0 | Z92: =AA14*$AD92 -> 0 | AB92: DLAB01 (s/t) | AC92: 611030 | AD92: =+AE92/AE94 -> 0.7411825 | AE92: 882400
U93: =$Z$14*$AD93 -> 0 | Z93: =AA14*$AD93 -> 0 | AB93: DLAB01 (o/t) | AC93: 610210 | AD93: =+AE93/AE94 -> 0.2588175 | AE93: 308130
U94: =SUM(U92:U93) -> 0 | Z94: =SUM(Z92:Z93) -> 0 | AA94: hr | AB94: DLAB01 | AC94: Total | AE94: =SUM(AE92:AE93) -> 1190530
B97: Jan | C97: Feb | D97: Mar | E97: Apr | F97: May | G97: Jun | H97: Jul
A98: Production Labor | B98: 268968.01 | C98: 288390.24 | D98: 154345.41 | E98: 13412.75 | F98: 229529.76 | G98: 274156.29 | H98: 267092.21
A99: R & M Labor | B99: 67812.91 | C99: 64354.51 | D99: 40616.39 | E99: 14950.76 | F99: 74301.16 | G99: 85619.44 | H99: 74393.95 | U99: =$Z$15*$AD99 -> 0 | Z99: =AA15*$AD99 -> 0 | AB99: MLAB01 (s/t) | AC99: 611040 | AD99: =+AE99/AE102 -> 0.78080694 | AE99: 392660
A100: IPC | B100: 102162.56 | C100: 97023.8 | D100: 87771.29 | E100: 18740.91 | F100: 135347.7 | G100: 89284.14 | H100: 88862.54 | U100: =$Z$15*$AD100 -> 0 | Z100: =AA15*$AD100 -> 0 | AB100: MLAB01 (o/t) | AC100: 610215 | AD100: =+AE100/AE102 -> 0.21919306 | AE100: 110230
A101: Supervision | B101: 6248.2 | C101: 7823.13 | D101: 4541.85 | E101: 10625.36 | F101: 11684.3 | G101: 7724.39 | H101: 6820.85
A102: Temp | B102: 35640 | C102: 61311 | D102: 50554 | F102: 65416 | G102: 62538 | H102: 37211 | U102: =SUM(U99:U100) -> 0 | Z102: =SUM(Z99:Z100) -> 0 | AA102: hr | AB102: MLAB01 | AC102: Total | AE102: =SUM(AE99:AE100) -> 502890
A103: IPC (estimated) | B103: =B100/(B98+B99-B102+B101) -> 0.33235581 | C103: =C100/(C98+C99-C102+C101) -> 0.32421577 | D103: =D100/(D98+D99-D102+D101) -> 0.58926819 | E103: =E100/(E98+E99-E102+E101) -> 0.48067333 | F103: =F100/(F98+F99-F102+F101) -> 0.54117602 | G103: =G100/(G98+G99-G102+G101) -> 0.29277125 | H103: =H100/(H98+H99-H102+H101) -> 0.28564346
U104: =$Z$16*$AD104 -> 0 | Z104: =$AA$16*$AD104 -> 0 | AB104: IPC01 (vac) | AC104: 610220 | AD104: =+AE104/AE110 -> 0.1679896 | AE104: 109692
D105: $/FTE/month | F105: $ Rolling Total | U105: =$Z$16*$AD105 -> 0 | Z105: =$AA$16*$AD105 -> 0 | AB105: IPC01 (hol) | AC105: 610510 | AD105: =+AE105/AE110 -> 0.14075553 | AE105: 91909
A106: Current Production Labor | B106: 46 | D106: =(AVERAGE((B98-B102),(C98-C102),(G98-G102),(H98-H102)))/B106 -> 4901.6671 | F106: =D106*B106 -> 225476.69 | U106: =$Z$16*$AD106 -> 0 | Z106: =$AA$16*$AD106 -> 0 | AB106: IPC01 (401k) | AC106: 610600 | AD106: =+AE106/AE110 -> 0.069911435 | AE106: 45650
A107: Current R & M Labor | B107: 16 | D107: =AVERAGE($G$99:$H$99,B99:C99)/B107 -> 4565.3252 | F107: =D107*B107 -> 73045.202 | U107: =$Z$16*$AD107 -> 0 | Z107: =$AA$16*$AD107 -> 0 | AB107: IPC01 (ins) | AC107: 610610 | AD107: =+AE107/AE110 -> 0.33790731 | AE107: 220643
U108: =$Z$16*$AD108 -> 0 | Z108: =$AA$16*$AD108 -> 0 | AB108: IPC01 (tax) | AC108: 612000 | AD108: =+AE108/AE110 -> 0.25840584 | AE108: 168731
A109: Future Production Labor Increase | B109: 6 | D109: =D106 -> 4901.6671 | F109: =D109*B109 -> 29410.003 | U109: =$Z$16*$AD109 -> 0 | Z109: =$AA$16*$AD109 -> 0 | AB109: IPC01 (w/c) | AC109: 612100 | AD109: =+AE109/AE110 -> 0.025030285 | AE109: 16344
A110: Future R&M Labor Increase | B110: 6 | D110: =D107 -> 4565.3252 | F110: =D110*B110 -> 27391.951 | U110: =SUM(U104:U109) -> 0 | Z110: =SUM(Z104:Z109) -> 0 | AA110: hr | AB110: IPC01 | AC110: Total | AE110: =SUM(AE104:AE109) -> 652969
A112: Total Production Labor | B112: =B106+B109 -> 52 | D112: =D106 -> 4901.6671 | F112: =D112*B112 -> 254886.69
A113: Total R & M Labor | B113: =B107+B110 -> 22 | D113: =D106 -> 4901.6671 | F113: =D113*B113 -> 107836.68
...

Sheet Dec23
A1: McINTYRE STANDARD 2025 | S1: COST CENTER 10001003 | AE1: Gross | AF1: Std | AG1: Abs Limit | AH1: Absorb | AI1: 10001003 | AJ1: Absorbed | AK1: 10001003 | AX1: Abs Cost
S2: CG | T2: CP | U2: HSP | V2: CL | W2: Nanomite C | X2: NRT | Y2: To Production | Z2: Idle Plant | AA2: TOTAL | AB2: Activity / Material | AC2: UOM | AD2: Ttl Unit Qty | AE2: Unit Cost | AF2: Cost/lb | AG2: Cost/lb | AH2: Cost/lb | AI2: Absorption | AJ2: Unit Cost | AK2: Underabs | AL2: EP Unit Qty | AM2: CP Unit Qty | AN2: HSP Unit Qty | AO2: CL Unit Qty | AP2: Nano C Qty | AQ2: NRT Unit Qty | AR2: EP Units/1000lb | AS2: CP Units/1000lb | AT2: HSP Units/1000lb | AU2: CL Units/1000lb | AV2: Nano C Units/1000lb | AW2: NRT Units/1000lb | AX2: per 10000
B3: HT | E3: Bauxite Pellets | H3: ID
B4: 25 Standard | C4: 23 Actual | D4: 22 Standard | E4: =B4 -> 25 Standard | F4: 23 Actual | G4: =+D4 -> 22 Standard | H4: =B4 -> 25 Standard | I4: 23 Actual | J4: =+D4 -> 22 Standard
F5: (Jan-Aug)
A6: Materials | B6: =IF($B$24<>0,$D$80,0) -> 0 | D6: 0 | E6: =IF(E24<>0,$L$88,0) -> 0 | F6: 0.071053254 | G6: 0.02685 | H6: =IF($H$24<>0,$D$88,0) -> 0 | J6: 0
A7: Electricity | B7: =IF($B$24<>0,$D$151,0) -> 0 | D7: 0 | E7: =IF(E24<>0,$D$151,0) -> 0 | F7: 0.03392679 | G7: 0.018883379 | H7: =IF(H24<>0,$D$151,0) -> 0 | J7: 0 | S7: =$C145*$B$24*1000*$B145 -> 0 | T7: =$C151*$B$47*1000*$B151 -> 0 | U7: =$F151*$E$47*1000*$E151 -> 0 | V7: =$F145*$E$24*1000*$E145 -> #DIV/0! | W7: =$I151*$H$47*1000*$H151 -> 0 | X7: =$I145*$H$24*1000*$H145 -> 0 | Y7: =SUM(S7:X7) -> #DIV/0! | Z7: 0 | AA7: =SUM(Y7:Z7) -> #DIV/0! | AB7: ELE01 | AC7: kwh | AD7: =ROUND((B145*B$24*1000)+(B151*B$47*1000)+(E145*E$24*1000)+(E151*E$47*1000)+(H145*H$24*1000)+(H151*H$47*1000),0) -> #DIV/0! | AE7: =Y7/AD7 -> #DIV/0! | AF7: =Y7/$AF$24/1000 -> #DIV/0! | AG7: 0.014890786 | AH7: =IF($AF$21<$AG$21,AF7,IF($AF$12<$AG$12,AF7,IF(AND($AF$12>$AG$12,$AF$20<$AG$20),($AG$12+($AG$20-$AF$20))/$AF$12*AF7,AF7/$AF$12*$AG$12))) -> #DIV/0! | AI7: =AH7*$Y$24*1000 -> #DIV/0! | AJ7: =AI7/AD7 -> #DIV/0! | AK7: =Y7-AI7 -> #DIV/0! | AL7: =ROUND($B145*$B$24*1000,0) -> 0 | AM7: =ROUND($B151*$B$47*1000,0) -> 0 | AN7: =ROUND($E151*$E$47*1000,0) -> 0 | AO7: =ROUND($E145*$E$24*1000,0) -> #DIV/0! | AP7: =ROUND($H151*$H$47*1000,0) -> 0 | AQ7: =ROUND($H145*$H$24*1000,0) -> 0 | AR7: =IF($B$24<>0,ROUND(AL7/B$24,3),0) -> 0 | AS7: =ROUND(AM7/B$47,3) -> #DIV/0! | AT7: =IF(E$47<>0,ROUND(AN7/E$47,3),0) -> 0 | AU7: =IF(F$24<>0,ROUND(AO7/F$24,3),0) -> #DIV/0! | AV7: =IF(H$47<>0,ROUND(AP7/H$47,3),0) -> 0 | AW7: =IF(H$24<>0,ROUND(AQ7/H$24,3),0) -> 0 | AX7: =AJ7*10000 -> #DIV/0!
A8: Gas | B8: =IF($B$24<>0,$D$152,0) -> 0 | D8: 0 | E8: =IF(E24<>0,$D$152,0) -> 0 | F8: 0.14600441 | G8: 0.04184 | H8: =IF(H24<>0,$D$152,0) -> 0 | J8: 0 | S8: =$C146*$B$24*1000*$B146 -> 0 | T8: =$C152*$B$47*1000*$B152 -> 0 | U8: =$F152*$E$47*1000*$E152 -> 0 | V8: =$F146*$E$24*1000*$E146 -> 0 | W8: =$I152*$H$47*1000*$H152 -> 0 | X8: =$I146*$H$24*1000*$H146 -> 0 | Y8: =SUM(S8:X8) -> 0 | Z8: 0 | AA8: =SUM(Y8:Z8) -> 0 | AB8: GAS01 | AC8: mbtu | AD8: =ROUND((B146*B$24*1000*1000)+(B152*B$47*1000*1000)+(E146*E$24*1000*1000)+(E152*E$47*1000*1000)+(H146*H$24*1000*1000)+(H152*H$47*1000*1000),0) -> 0 | AE8: =Y8/AD8 -> #DIV/0! | AF8: =Y8/$AF$24/1000 -> #DIV/0! | AG8: 0.042004912 | AH8: =IF($AF$21<$AG$21,AF8,IF($AF$12<$AG$12,AF8,IF(AND($AF$12>$AG$12,$AF$20<$AG$20),($AG$12+($AG$20-$AF$20))/$AF$12*AF8,AF8/$AF$12*$AG$12))) -> #DIV/0! | AI8: =AH8*$Y$24*1000 -> #DIV/0! | AJ8: =AI8/AD8 -> #DIV/0! | AK8: =Y8-AI8 -> #DIV/0! | AL8: =ROUND($B146*$B$24*1000*1000,0) -> 0 | AM8: =ROUND($B152*$B$47*1000*1000,0) -> 0 | AN8: =ROUND($E152*$E$47*1000*1000,0) -> 0 | AO8: =ROUND($E146*$E$24*1000*1000,0) -> 0 | AP8: =ROUND($H152*$H$47*1000*1000,0) -> 0 | AQ8: =ROUND($H146*$H$24*1000*1000,0) -> 0 | AR8: =IF($B$24<>0,ROUND(AL8/B$24,3),0) -> 0 | AS8: =ROUND(AM8/B$47,3) -> #DIV/0! | AT8: =IF(E$47<>0,ROUND(AN8/E$47,3),0) -> 0 | AU8: =IF(E$24<>0,ROUND(AO8/E$24,3),0) -> 0 | AV8: =IF(H$47<>0,ROUND(AP8/H$47,3),0) -> 0 | AW8: =IF(H$24<>0,ROUND(AQ8/H$24,3),0) -> 0 | AX8: =AJ8*10000 -> #DIV/0!
A9: R&M Supplies and Service | B9: =IF($B$24<>0,$H$159,0) -> 0 | D9: 0 | E9: =IF(E24<>0,$H$159,0) -> 0 | F9: 0.043366417 | G9: 0.022368421 | H9: =IF(H24<>0,$H$159,0) -> 0 | J9: 0 | S9: =B9*B$24*1000 -> 0 | T9: =B32*B$47*1000 -> 0 | U9: =E32*E$47*1000 -> 0 | V9: =E9*E$24*1000 -> 0 | W9: =H32*H$47*1000 -> 0 | X9: =H9*H$24*1000 -> 0 | Y9: =SUM(S9:X9) -> 0 | Z9: 0 | AA9: =SUM(Y9:Z9) -> 0 | AB9: RMS01 | AC9: lb | AD9: =ROUND((S9/H$159)+(T9/H$159)+(U9/H$159)+(V9/H$159)+(W9/H$159)+(X9/H$159),0) -> #DIV/0! | AE9: =Y9/AD9 -> #DIV/0! | AF9: =Y9/$AF$24/1000 -> #DIV/0! | AG9: 0.019544347 | AH9: =IF($AF$21<$AG$21,AF9,IF($AF$12<$AG$12,AF9,IF(AND($AF$12>$AG$12,$AF$20<$AG$20),($AG$12+($AG$20-$AF$20))/$AF$12*AF9,AF9/$AF$12*$AG$12))) -> #DIV/0! | AI9: =AH9*$Y$24*1000 -> #DIV/0! | AJ9: =AI9/AD9 -> #DIV/0! | AK9: =Y9-AI9 -> #DIV/0! | AL9: =S9/$AE9 -> #DIV/0! | AM9: =T9/$AE9 -> #DIV/0! | AN9: =U9/$AE9 -> #DIV/0! | AO9: =V9/$AE9 -> #DIV/0! | AP9: =W9/$AE9 -> #DIV/0! | AQ9: =X9/$AE9 -> #DIV/0! | AR9: =IF($B$24<>0,ROUND(AL9/B$24,3),0) -> 0 | AS9: =ROUND(AM9/B$47,3) -> #DIV/0! | AT9: =IF(E$47<>0,ROUND(AN9/E$47,3),0) -> 0 | AU9: =IF(E$24<>0,ROUND(AO9/E$24,3),0) -> 0 | AV9: =IF(H$47<>0,ROUND(AP9/H$47,3),0) -> 0 | AW9: =IF(H$24<>0,ROUND(AQ9/H$24,3),0) -> 0 | AX9: =AJ9*10000 -> #DIV/0!
A10: Manufacturing Supplies | B10: =IF($B$24<>0,$H$163,0) -> 0 | D10: 0 | E10: =IF(E24<>0,$H$163,0) -> 0 | F10: 0.00073336258 | G10: 0.00065789474 | H10: =IF($H$24<>0,$H$163,0) -> 0 | J10: 0 | S10: =B10*B$24*1000 -> 0 | T10: =B33*B$47*1000 -> 0 | U10: =E33*E$47*1000 -> 0 | V10: =E10*E$24*1000 -> 0 | W10: =H33*H$47*1000 -> 0 | X10: =H10*H$24*1000 -> 0 | Y10: =SUM(S10:X10) -> 0 | Z10: 0 | AA10: =SUM(Y10:Z10) -> 0 | AB10: MFG01 | AC10: lb | AD10: =ROUND((S10/H$163)+(T10/H$163)+(U10/H$163)+(V10/H$163)+(W10/H$163)+(X10/H$163),0) -> #DIV/0! | AE10: =Y10/AD10 -> #DIV/0! | AF10: =Y10/$AF$24/1000 -> #DIV/0! | AG10: 0.0012510769 | AH10: =IF($AF$21<$AG$21,AF10,IF($AF$12<$AG$12,AF10,IF(AND($AF$12>$AG$12,$AF$20<$AG$20),($AG$12+($AG$20-$AF$20))/$AF$12*AF10,AF10/$AF$12*$AG$12))) -> #DIV/0! | AI10: =AH10*$Y$24*1000 -> #DIV/0! | AJ10: =AI10/AD10 -> #DIV/0! | AK10: =Y10-AI10 -> #DIV/0! | AL10: =S10/$AE10 -> #DIV/0! | AM10: =T10/$AE10 -> #DIV/0! | AN10: =U10/$AE10 -> #DIV/0! | AO10: =V10/$AE10 -> #DIV/0! | AP10: =W10/$AE10 -> #DIV/0! | AQ10: =X10/$AE10 -> #DIV/0! | AR10: =IF($B$24<>0,ROUND(AL10/B$24,3),0) -> 0 | AS10: =ROUND(AM10/B$47,3) -> #DIV/0! | AT10: =IF(E$47<>0,ROUND(AN10/E$47,3),0) -> 0 | AU10: =IF(E$24<>0,ROUND(AO10/E$24,3),0) -> 0 | AV10: =IF(H$47<>0,ROUND(AP10/H$47,3),0) -> 0 | AW10: =IF(H$24<>0,ROUND(AQ10/H$24,3),0) -> 0 | AX10: =AJ10*10000 -> #DIV/0!
A11: Other variable | B11: =IF($B$24<>0,$H$166,0) -> 0 | D11: 0 | E11: =IF(E24<>0,$H$166,0) -> 0 | F11: 0.010235236 | G11: 0.0046052632 | H11: =IF($H$24<>0,$H$166,0) -> 0 | J11: 0 | S11: =B11*B$24*1000 -> 0 | T11: =B34*B$47*1000 -> 0 | U11: =E34*E$47*1000 -> 0 | V11: =E11*E$24*1000 -> 0 | W11: =H34*H$47*1000 -> 0 | X11: =H11*H$24*1000 -> 0 | Y11: =SUM(S11:X11) -> 0 | Z11: 0 | AA11: =SUM(Y11:Z11) -> 0 | AB11: VAR01 | AC11: lb | AD11: =ROUND((S11/H$166)+(T11/H$166)+(U11/H$166)+(V11/H$166)+(W11/H$166)+(X11/H$166),0) -> #DIV/0! | AE11: =Y11/AD11 -> #DIV/0! | AF11: =Y11/$AF$24/1000 -> #DIV/0! | AG11: 0.0037333371 | AH11: =IF($AF$21<$AG$21,AF11,IF($AF$12<$AG$12,AF11,IF(AND($AF$12>$AG$12,$AF$20<$AG$20),($AG$12+($AG$20-$AF$20))/$AF$12*AF11,AF11/$AF$12*$AG$12))) -> #DIV/0! | AI11: =AH11*$Y$24*1000 -> #DIV/0! | AJ11: =AI11/AD11 -> #DIV/0! | AK11: =Y11-AI11 -> #DIV/0! | AL11: =S11/$AE11 -> #DIV/0! | AM11: =T11/$AE11 -> #DIV/0! | AN11: =U11/$AE11 -> #DIV/0! | AO11: =V11/$AE11 -> #DIV/0! | AP11: =W11/$AE11 -> #DIV/0! | AQ11: =X11/$AE11 -> #DIV/0! | AR11: =IF($B$24<>0,ROUND(AL11/B$24,3),0) -> 0 | AS11: =ROUND(AM11/B$47,3) -> #DIV/0! | AT11: =IF(E$47<>0,ROUND(AN11/E$47,3),0) -> 0 | AU11: =IF(E$24<>0,ROUND(AO11/E$24,3),0) -> 0 | AV11: =IF(H$47<>0,ROUND(AP11/H$47,3),0) -> 0 | AW11: =IF(H$24<>0,ROUND(AQ11/H$24,3),0) -> 0 | AX11: =AJ11*10000 -> #DIV/0!
A12: Total Variable Costs | B12: =SUM(B6:B11) -> 0 | D12: =SUM(D6:D11) -> 0 | E12: =SUM(E6:E11) -> 0 | F12: =SUM(F6:F11) -> 0.30531947 | G12: =SUM(G6:G11) -> 0.11520496 | H12: =SUM(H6:H11) -> 0 | J12: =SUM(J6:J11) -> 0 | S12: =SUM(S7:S11) -> 0 | T12: =SUM(T7:T11) -> 0 | U12: =SUM(U7:U11) -> 0 | V12: =SUM(V7:V11) -> #DIV/0! | W12: =SUM(W7:W11) -> 0 | X12: =SUM(X7:X11) -> 0 | Y12: =SUM(Y7:Y11) -> #DIV/0! | Z12: =SUM(Z7:Z11) -> 0 | AA12: =SUM(AA7:AA11) -> #DIV/0! | AF12: =SUM(AF7:AF11) -> #DIV/0! | AG12: =SUM(AG7:AG11) -> 0.081424459 | AH12: =SUM(AH7:AH11) -> #DIV/0! | AI12: =SUM(AI7:AI11) -> #DIV/0! | AK12: =SUM(AK7:AK11) -> #DIV/0!
A14: Production Labor | B14: =IF($B$24<>0,$F$112/$B$49/1000,0) -> 0 | D14: 0 | E14: =IF(E24<>0,$F$112/$B$49/1000,0) -> 0 | F14: 0.055685781 | G14: 0.02638428 | H14: =IF($H$24<>0,$F$112/$B$49/1000,0) -> 0 | J14: 0 | S14: =B14*B$24*1000 -> 0 | T14: =B37*B$47*1000 -> 0 | U14: =E37*E$47*1000 -> 0 | V14: =E14*E$24*1000 -> 0 | W14: =H37*H$47*1000 -> 0 | X14: =H14*H$24*1000 -> 0 | Y14: =SUM(S14:X14) -> 0 | Z14: =-$D$115 -> 0 | AA14: =SUM(Y14:Z14) -> 0 | AB14: DLAB01 | AC14: hr | AD14: =ROUND((S14/C$116)+(T14/C$116)+(U14/C$116)+(V14/C$116)+(W14/C$116)+(X14/C$116),0) -> #DIV/0! | AE14: =Y14/AD14 -> #DIV/0! | AF14: =Y14/$AF$24/1000 -> #DIV/0! | AG14: 0.011488554 | AH14: =IF($AF$21<$AG$21,AF14,IF($AF$20<$AG$20,AF14,IF(AND($AF$20>$AG$20,$AF$12<$AG$12),($AG$20+($AG$12-$AF$12))/$AF$20*AF14,AF14/$AF$20*$AG$20))) -> #DIV/0! | AI14: =AH14*$Y$24*1000 -> #DIV/0! | AJ14: =AI14/AD14 -> #DIV/0! | AK14: =Y14-AI14 -> #DIV/0! | AL14: =ROUND(S14/$C116,0) -> #DIV/0! | AM14: =ROUND(T14/$C116,0) -> #DIV/0! | AN14: =ROUND(U14/$C116,0) -> #DIV/0! | AO14: =ROUND(V14/$C116,0) -> #DIV/0! | AP14: =ROUND(W14/$C116,0) -> #DIV/0! | AQ14: =ROUND(X14/$C116,0) -> #DIV/0! | AR14: =IF($B$24<>0,ROUND(AL14/B$24,3),0) -> 0 | AS14: =ROUND(AM14/B$47,3) -> #DIV/0! | AT14: =IF(E$47<>0,ROUND(AN14/E$47,3),0) -> 0 | AU14: =IF(E$24<>0,ROUND(AO14/E$24,3),0) -> 0 | AV14: =IF(H$47<>0,ROUND(AP14/H$47,3),0) -> 0 | AW14: =IF(H$24<>0,ROUND(AQ14/H$24,3),0) -> 0 | AX14: =AJ14*10000 -> #DIV/0!
A15: Repairs & Maintenance Labor | B15: =IF($B$24<>0,$F$113/$B$49/1000,0) -> 0 | D15: 0 | E15: =IF(E24<>0,$F$113/$B$49/1000,0) -> 0 | F15: 0.019535758 | G15: 0.00902044 | H15: =IF($H$24<>0,$F$113/$B$49/1000,0) -> 0 | J15: 0 | S15: =B15*B$24*1000 -> 0 | T15: =B38*B$47*1000 -> 0 | U15: =E38*E$47*1000 -> 0 | V15: =E15*E$24*1000 -> 0 | W15: =H38*H$47*1000 -> 0 | X15: =H15*H$24*1000 -> 0 | Y15: =SUM(S15:X15) -> 0 | Z15: =-$H$115 -> 0 | AA15: =SUM(Y15:Z15) -> 0 | AB15: MLAB01 | AC15: hr | AD15: =ROUND((S15/G$116)+(T15/G$116)+(U15/G$116)+(V15/G$116)+(W15/G$116)+(X15/G$116),0) -> #DIV/0! | AE15: =Y15/AD15 -> #DIV/0! | AF15: =Y15/$AF$24/1000 -> #DIV/0! | AG15: 0.007650221 | AH15: =IF($AF$21<$AG$21,AF15,IF($AF$20<$AG$20,AF15,IF(AND($AF$20>$AG$20,$AF$12<$AG$12),($AG$20+($AG$12-$AF$12))/$AF$20*AF15,AF15/$AF$20*$AG$20))) -> #DIV/0! | AI15: =AH15*$Y$24*1000 -> #DIV/0! | AJ15: =AI15/AD15 -> #DIV/0! | AK15: =Y15-AI15 -> #DIV/0! | AL15: =ROUND(S15/$G$116,0) -> #DIV/0! | AM15: =ROUND(T15/$G$116,0) -> #DIV/0! | AN15: =ROUND(U15/$G$116,0) -> #DIV/0! | AO15: =ROUND(V15/$G$116,0)-1 -> #DIV/0! | AP15: =ROUND(W15/$G$116,0) -> #DIV/0! | AQ15: =ROUND(X15/$G$116,0) -> #DIV/0! | AR15: =IF($B$24<>0,ROUND(AL15/B$24,3),0) -> 0 | AS15: =ROUND(AM15/B$47,3) -> #DIV/0! | AT15: =IF(E$47<>0,ROUND(AN15/E$47,3),0) -> 0 | AU15: =IF(E$24<>0,ROUND(AO15/E$24,3),0) -> 0 | AV15: =IF(H$47<>0,ROUND(AP15/H$47,3),0) -> 0 | AW15: =IF(H$24<>0,ROUND(AQ15/H$24,3),0) -> 0 | AX15: =AJ15*10000 -> #DIV/0!
A16: Indirect Payroll Costs (Benefits) | B16: =IF(B24<>0,$F$115/$B$49/1000,0) -> 0 | D16: 0 | E16: =IF(E24<>0,$F$115/$B$49/1000,0) -> 0 | F16: 0.01706523 | G16: 0.013928937 | H16: =IF($H$24<>0,$F$115/$B$49/1000,0) -> 0 | J16: 0 | S16: =B16*B$24*1000 -> 0 | T16: =B39*B$47*1000 -> 0 | U16: =E39*E$47*1000 -> 0 | V16: =E16*E$24*1000 -> 0 | W16: =H39*H$47*1000 -> 0 | X16: =H16*H$24*1000 -> 0 | Y16: =SUM(S16:X16) -> 0 | Z16: =-$D$122 -> 0 | AA16: =SUM(Y16:Z16) -> 0 | AB16: IPC01 | AC16: hr | AD16: =ROUND((S16/C$123)+(T16/C$123)+(U16/C$123)+(V16/C$123)+(W16/C$123)+(X16/C$123),0) -> #DIV/0! | AE16: =Y16/AD16 -> #DIV/0! | AF16: =Y16/$AF$24/1000 -> #DIV/0! | AG16: 0.0088563301 | AH16: =IF($AF$21<$AG$21,AF16,IF($AF$20<$AG$20,AF16,IF(AND($AF$20>$AG$20,$AF$12<$AG$12),($AG$20+($AG$12-$AF$12))/$AF$20*AF16,AF16/$AF$20*$AG$20))) -> #DIV/0! | AI16: =AH16*$Y$24*1000 -> #DIV/0! | AJ16: =AI16/AD16 -> #DIV/0! | AK16: =Y16-AI16 -> #DIV/0! | AL16: =ROUND(S16/$C123,0) -> #DIV/0! | AM16: =ROUND(T16/$C123,0) -> #DIV/0! | AN16: =ROUND(U16/$C123,0) -> #DIV/0! | AO16: =ROUND(V16/$C123,0) -> #DIV/0! | AP16: =ROUND(W16/$C123,0) -> #DIV/0! | AQ16: =ROUND(X16/$C123,0) -> #DIV/0! | AR16: =IF($B$24<>0,ROUND(AL16/B$24,3),0) -> 0 | AS16: =ROUND(AM16/B$47,3) -> #DIV/0! | AT16: =IF(E$47<>0,ROUND(AN16/E$47,3),0) -> 0 | AU16: =IF(E$24<>0,ROUND(AO16/E$24,3),0) -> 0 | AV16: =IF(H$47<>0,ROUND(AP16/H$47,3),0) -> 0 | AW16: =IF(H$24<>0,ROUND(AQ16/H$24,3),0) -> 0 | AX16: =AJ16*10000 -> #DIV/0!
A17: Supervision | B17: =IF($B$24<>0,$F$114/$B$49/1000,0) -> 0 | D17: 0 | E17: =IF(E24<>0,$F$114/$B$49/1000,0) -> 0 | F17: 0.0045810516 | G17: 0.0015771316 | H17: =IF($H$24<>0,$F$114/$B$49/1000,0) -> 0 | J17: 0 | S17: =B17*B$24*1000 -> 0 | T17: =B40*B$47*1000 -> 0 | U17: =E40*E$47*1000 -> 0 | V17: =E17*E$24*1000 -> 0 | W17: =H40*H$47*1000 -> 0 | X17: =H17*H$24*1000 -> 0 | Y17: =SUM(S17:X17) -> 0 | Z17: =C176/($C$184+$C$185)*$C$185 -> 0 | AA17: =SUM(Y17:Z17) -> 0 | AB17: SUP01 | AC17: lb | AD17: =ROUND((S17/F$176)+(T17/F$176)+(U17/F$176)+(V17/F$176)+(W17/F$176)+(X17/F$176),0) -> #DIV/0! | AE17: =Y17/AD17 -> #DIV/0! | AF17: =Y17/$AF$24/1000 -> #DIV/0! | AG17: 0.0021273119 | AH17: =IF($AF$21<$AG$21,AF17,IF($AF$20<$AG$20,AF17,IF(AND($AF$20>$AG$20,$AF$12<$AG$12),($AG$20+($AG$12-$AF$12))/$AF$20*AF17,AF17/$AF$20*$AG$20))) -> #DIV/0! | AI17: =AH17*$Y$24*1000 -> #DIV/0! | AJ17: =AI17/AD17 -> #DIV/0! | AK17: =Y17-AI17 -> #DIV/0! | AL17: =S17/$AE17 -> #DIV/0! | AM17: =T17/$AE17 -> #DIV/0! | AN17: =U17/$AE17 -> #DIV/0! | AO17: =V17/$AE17 -> #DIV/0! | AP17: =W17/$AE17 -> #DIV/0! | AQ17: =X17/$AE17 -> #DIV/0! | AR17: =IF($B$24<>0,ROUND(AL17/B$24,3),0) -> 0 | AS17: =ROUND(AM17/B$47,3) -> #DIV/0! | AT17: =IF(E$47<>0,ROUND(AN17/E$47,3),0) -> 0 | AU17: =IF(E$24<>0,ROUND(AO17/E$24,3),0) -> 0 | AV17: =IF(H$47<>0,ROUND(AP17/H$47,3),0) -> 0 | AW17: =IF(H$24<>0,ROUND(AQ17/H$24,3),0) -> 0 | AX17: =AJ17*10000 -> #DIV/0!
A18: Depreciation | B18: =IF($B$24<>0,$B$178/$B$49/1000,0) -> 0 | D18: 0 | E18: =IF(E24<>0,$B$178/$B$49/1000,0) -> 0 | F18: 0.0038559807 | G18: 0.0016578947 | H18: =IF($H$24<>0,$B$178/$B$49/1000,0) -> 0 | J18: 0 | S18: =B18*B$24*1000 -> 0 | T18: =B41*B$47*1000 -> 0 | U18: =E41*E$47*1000 -> 0 | V18: =E18*E$24*1000 -> 0 | W18: =H41*H$47*1000 -> 0 | X18: =H18*H$24*1000 -> 0 | Y18: =SUM(S18:X18) -> 0 | Z18: =C178/($C$184+$C$185)*$C$185 -> 0 | AA18: =SUM(Y18:Z18) -> 0 | AB18: DEP01 | AC18: lb | AD18: =ROUND((S18/F$178)+(T18/F$178)+(U18/F$178)+(V18/F$178)+(W18/F$178)+(X18/F$178),0) -> #DIV/0! | AE18: =Y18/AD18 -> #DIV/0! | AF18: =Y18/$AF$24/1000 -> #DIV/0! | AG18: 0.032747211 | AH18: =IF($AF$21<$AG$21,AF18,IF($AF$20<$AG$20,AF18,IF(AND($AF$20>$AG$20,$AF$12<$AG$12),($AG$20+($AG$12-$AF$12))/$AF$20*AF18,AF18/$AF$20*$AG$20))) -> #DIV/0! | AI18: =AH18*$Y$24*1000 -> #DIV/0! | AJ18: =AI18/AD18 -> #DIV/0! | AK18: =Y18-AI18 -> #DIV/0! | AL18: =S18/$AE18 -> #DIV/0! | AM18: =T18/$AE18 -> #DIV/0! | AN18: =U18/$AE18 -> #DIV/0! | AO18: =V18/$AE18 -> #DIV/0! | AP18: =W18/$AE18 -> #DIV/0! | AQ18: =X18/$AE18 -> #DIV/0! | AR18: =IF($B$24<>0,ROUND(AL18/B$24,3),0) -> 0 | AS18: =ROUND(AM18/B$47,3) -> #DIV/0! | AT18: =IF(E$47<>0,ROUND(AN18/E$47,3),0) -> 0 | AU18: =IF(E$24<>0,ROUND(AO18/E$24,3),0) -> 0 | AV18: =IF(H$47<>0,ROUND(AP18/H$47,3),0) -> 0 | AW18: =IF(H$24<>0,ROUND(AQ18/H$24,3),0) -> 0 | AX18: =AJ18*10000 -> #DIV/0!
A19: Insurance & Taxes | B19: =IF($B$24<>0,$B$177/$B$49/1000,0) -> 0 | D19: 0 | E19: =IF(E24<>0,$B$177/E26/1000,0) -> 0 | F19: 0.010801566 | G19: 0.0058026316 | H19: =IF($H$24<>0,$B$177/$B$49/1000,0) -> 0 | J19: 0 | S19: =B19*B$24*1000 -> 0 | T19: =B42*B$47*1000 -> 0 | U19: =E42*E$47*1000 -> 0 | V19: =E19*E$24*1000 -> 0 | W19: =H42*H$47*1000 -> 0 | X19: =H19*H$24*1000 -> 0 | Y19: =SUM(S19:X19) -> 0 | Z19: =C177/($C$184+$C$185)*$C$185 -> 0 | AA19: =SUM(Y19:Z19) -> 0 | AB19: INS01 | AC19: lb | AD19: =ROUND((S19/F$177)+(T19/F$177)+(U19/F$177)+(V19/F$177)+(W19/F$177)+(X19/F$177),0) -> #DIV/0! | AE19: =Y19/AD19 -> #DIV/0! | AF19: =Y19/$AF$24/1000 -> #DIV/0! | AG19: 0.0073609622 | AH19: =IF($AF$21<$AG$21,AF19,IF($AF$20<$AG$20,AF19,IF(AND($AF$20>$AG$20,$AF$12<$AG$12),($AG$20+($AG$12-$AF$12))/$AF$20*AF19,AF19/$AF$20*$AG$20))) -> #DIV/0! | AI19: =AH19*$Y$24*1000 -> #DIV/0! | AJ19: =AI19/AD19 -> #DIV/0! | AK19: =Y19-AI19 -> #DIV/0! | AL19: =S19/$AE19 -> #DIV/0! | AM19: =T19/$AE19 -> #DIV/0! | AN19: =U19/$AE19 -> #DIV/0! | AO19: =V19/$AE19 -> #DIV/0! | AP19: =W19/$AE19 -> #DIV/0! | AQ19: =X19/$AE19 -> #DIV/0! | AR19: =IF($B$24<>0,ROUND(AL19/B$24,3),0) -> 0 | AS19: =ROUND(AM19/B$47,3) -> #DIV/0! | AT19: =IF(E$47<>0,ROUND(AN19/E$47,3),0) -> 0 | AU19: =IF(E$24<>0,ROUND(AO19/E$24,3),0) -> 0 | AV19: =IF(H$47<>0,ROUND(AP19/H$47,3),0) -> 0 | AW19: =IF(H$24<>0,ROUND(AQ19/H$24,3),0) -> 0 | AX19: =AJ19*10000 -> #DIV/0!
A20: Total Fixed Costs | B20: =SUM(B14:B19) -> 0 | C20: =SUM(C14:C19) -> 0 | D20: =SUM(D14:D19) -> 0 | E20: =SUM(E14:E19) -> 0 | F20: =SUM(F14:F19) -> 0.11152537 | G20: =SUM(G14:G19) -> 0.058371315 | H20: =SUM(H14:H19) -> 0 | I20: =SUM(I14:I19) -> 0 | J20: =SUM(J14:J19) -> 0 | S20: =SUM(S14:S19) -> 0 | T20: =SUM(T14:T19) -> 0 | U20: =SUM(U14:U19) -> 0 | V20: =SUM(V14:V19) -> 0 | W20: =SUM(W14:W19) -> 0 | X20: =SUM(X14:X19) -> 0 | Y20: =SUM(Y14:Y19) -> 0 | Z20: =SUM(Z14:Z19) -> 0 | AA20: =SUM(AA14:AA19) -> 0 | AF20: =SUM(AF14:AF19) -> #DIV/0! | AG20: =SUM(AG14:AG19) -> 0.07023059 | AH20: =SUM(AH14:AH19) -> #DIV/0! | AI20: =SUM(AI14:AI19) -> #DIV/0! | AK20: =SUM(AK14:AK19) -> #DIV/0!
A21: Excess Costs | C21: -0.0273 | F21: -0.050457361 | S21: =S12+S20 -> 0 | T21: =T12+T20 -> 0 | U21: =U12+U20 -> 0 | V21: =V12+V20 -> #DIV/0! | W21: =W12+W20 -> 0 | X21: =X12+X20 -> 0 | Y21: =Y12+Y20 -> #DIV/0! | Z21: =Z12+Z20 -> 0 | AA21: =AA12+AA20 -> #DIV/0! | AB21: CCtr Total | AF21: =AF12+AF20 -> #DIV/0! | AG21: =AG12+AG20 -> 0.15165505 | AH21: =AH12+AH20 -> #DIV/0! | AI21: =AI12+AI20 -> #DIV/0! | AK21: =AK12+AK20 -> #DIV/0!
A22: TOTAL COSTS PER POUND | B22: =B12+B20 -> 0 | C22: =+C20+C21+C12 -> -0.0273 | D22: =D12+D20 -> 0 | E22: =E12+E20 -> 0 | F22: =F12+F20+F21 -> 0.36638748 | G22: =G12+G20 -> 0.17357627 | H22: =H12+H20 -> 0 | I22: =I12+I20 -> 0 | J22: =J12+J20 -> 0 | S22: =IF(B24<>0,ROUND(S21/(B24*1000),5),0) -> 0 | T22: =IF(B47<>0,ROUND(T21/(B47*1000),5),0) -> 0 | U22: =IF(E47<>0,ROUND(U21/(E47*1000),5),0) -> 0 | V22: =IF(E24<>0,ROUND(V21/(E24*1000),5),0) -> 0 | W22: =IF(H47<>0,ROUND(W21/(H47*1000),5),0) -> 0 | X22: =IF(H24<>0,ROUND(X21/(H24*1000),5),0) -> 0 | Y22: =Y21/Y24/1000 -> #DIV/0! | Z22: 0 | AA22: =ROUND(AA21/(B49*1000),5) -> #DIV/0! | AB22: Excl Matl | AI22: =AI21/AI24/1000 -> #DIV/0! | AK22: =AK21/AK24/1000 -> #DIV/0!
S23: =ROUND(S22+B6,5) -> 0 | T23: =ROUND(T22+B29,5) -> 0 | U23: =ROUND(U22+E29,5) -> 0 | V23: =ROUND(V22+E6,5) -> 0 | W23: =ROUND(W22+H29,5) -> 0 | X23: =ROUND(X22+H6,5) -> 0 | Y23: =Y22+(($B$6*$B$24*1000+$B$29*$B$47*1000+$E$29*$E$47*1000+$H$6*$H$24*1000+$H$29*$H$47*1000+$E$6*$E$24*1000)/($B$49*1000)) -> #DIV/0! | Z23: 0 | AA23: =AA22+(($B$6*$B$24*1000+$B$29*$B$47*1000+$E$6*$E$24*1000+$E$29*$E$47*1000+$H$6*$H$24*1000+$H$29*$H$47*1000)/($B$49*1000)) -> #DIV/0! | AB23: Incl Matl
A24: PRODUCTION ( in 000 lbs ) | B24: =B54 -> 0 | C24: 6211 | D24: 0 | E24: =B57 -> 0 | F24: 3204 | G24: 51000 | H24: =B58 -> 0 | I24: 4207 | J24: 0 | S24: =B24 -> 0 | T24: =B47 -> 0 | U24: =E47 -> 0 | V24: =E24 -> 0 | W24: =H47 -> 0 | X24: =H24 -> 0 | Y24: =SUM(S24:X24) -> 0 | Z24: 0 | AA24: =SUM(Y24:Z24) -> 0 | AF24: =Y24 -> 0 | AI24: =Y24 -> 0 | AK24: =Y24 -> 0
B26: CP | E26: HSP | H26: Nanomite C | AS26: 0.936
B27: =B4 -> 25 Standard | C27: 23 Actual | D27: =+D4 -> 22 Standard | E27: =E4 -> 25 Standard | F27: =+C27 -> 23 Actual | G27: =+D27 -> 22 Standard | H27: =H4 -> 25 Standard | I27: 23 Actual | J27: =+J4 -> 22 Standard | AS27: 0.264
C28: (Jan-Aug) | F28: (Jan-Aug) | I28: (Jan-Aug) | AS28: 286
A29: Materials | B29: =IF($B$47<>0,$D$88,0) -> 0 | C29: 0.1396 | D29: 0.06037434 | E29: =IF(E47<>0,$D$88,0) -> 0 | F29: 0.0865 | G29: 0 | H29: =IF(H47<>0,$L$80,0) -> 0 | I29: 0.0792 | J29: 0.02 | AS29: 8000
A30: Electricity | B30: =IF(B47<>0,$D$151,0) -> 0 | C30: 0.0273 | D30: 0.018883379 | E30: =IF(E47<>0,$G$151,0) -> 0 | F30: 0.0294 | G30: 0 | H30: =IF(H47<>0,$J$151,0) -> 0 | I30: 0.0124 | J30: 0.0027366213 | AS30: 1.2
A31: Gas | B31: =IF(B47<>0,$D$152,0) -> 0 | C31: 0.0379 | D31: 0.04184 | E31: =IF(E47<>0,$G$152,0) -> 0 | F31: 0.0465 | G31: 0 | H31: =IF(H47<>0,$J$152,0) -> 0 | I31: 0 | J31: 0
A32: R&M Supplies and Service | B32: =IF(B47<>0,$H$159,0) -> 0 | C32: 0.0358 | D32: 0.022368421 | E32: =IF(E47<>0,$H$159,0) -> 0 | F32: 0.0304 | G32: 0 | H32: =IF(H47<>0,$H$159,0) -> 0 | I32: 0.0164 | J32: 0.022368421
A33: Manufacturing Supplies | B33: =IF(B47<>0,$H$163,0) -> 0 | C33: 0.0006 | D33: 0.00065789474 | E33: =IF(E47<>0,$H$163,0) -> 0 | F33: 0.002 | G33: 0 | H33: =IF(H47<>0,$H$163,0) -> 0 | I33: 0.0014 | J33: 0.00065789474
A34: Other variable | B34: =IF($B$47<>0,$H$166,0) -> 0 | C34: 0.0101 | D34: 0.0046052632 | E34: =IF(E47<>0,$H$166,0) -> 0 | F34: 0.0118 | G34: 0 | H34: =IF(H47<>0,$H$166,0) -> 0 | I34: 0.0108 | J34: 0.0046052632
A35: Total Variable Costs | B35: =SUM(B29:B34) -> 0 | C35: =SUM(C29:C34) -> 0.2513 | D35: =SUM(D29:D34) -> 0.1487293 | E35: =SUM(E29:E34) -> 0 | F35: =SUM(F29:F34) -> 0.2066 | G35: =SUM(G29:G34) -> 0 | H35: =SUM(H29:H34) -> 0 | I35: =SUM(I29:I34) -> 0.1202 | J35: =SUM(J29:J34) -> 0.0503682
A37: Production Labor | B37: =IF(B47<>0,$F$112/$B$49/1000,0) -> 0 | C37: 0.0445 | D37: 0.02638428 | E37: =IF(E47<>0,$F$112/$B$49/1000,0) -> 0 | F37: 0.0483 | G37: 0 | H37: =IF(H47<>0,$F$112/$B$49/1000,0) -> 0 | I37: 0.0451 | J37: 0.02638428
A38: Repairs & Maintenance Labor | B38: =IF(B47<>0,$F$113/$B$49/1000,0) -> 0 | C38: 0.015 | D38: 0.00902044 | E38: =IF(E47<>0,$F$113/$B$49/1000,0) -> 0 | F38: 0.0144 | G38: 0 | H38: =IF(H47<>0,$F$113/$B$49/1000,0) -> 0 | I38: 0.0156 | J38: 0.00902044
A39: Indirect Payroll Costs (Benefits) | B39: =IF(B47<>0,$F$115/$B$49/1000,0) -> 0 | C39: 0.0194 | D39: 0.013928937 | E39: =IF(E47<>0,$F$115/$B$49/1000,0) -> 0 | F39: 0.0196 | G39: 0 | H39: =IF(H47<>0,$F$115/$B$49/1000,0) -> 0 | I39: 0.0285 | J39: 0.013928937
A40: Supervision | B40: =IF($B$47<>0,$F$114/$B$49/1000,0) -> 0 | C40: 0.0018 | D40: 0.0015771316 | E40: =IF(E47<>0,$F$114/$B$49/1000,0) -> 0 | F40: 0.0014 | G40: 0 | H40: =IF(H47<>0,$F$114/$B$49/1000,0) -> 0 | I40: 0.0022 | J40: 0.0015771316
A41: Depreciation | B41: =IF(B47<>0,$B$178/$B$49/1000,0) -> 0 | C41: 0.0043 | D41: 0.0016578947 | E41: =IF(E47<>0,$B$178/$B$49/1000,0) -> 0 | F41: 0.0042 | G41: 0 | H41: =IF(H47<>0,$B$178/$B$49/1000,0) -> 0 | I41: 0.0067 | J41: 0.0016578947
A42: Insurance & Taxes | B42: =IF(B47<>0,$B$177/B49/1000,0) -> 0 | C42: 0.0093 | D42: 0.0058026316 | E42: =IF(E47<>0,$B$177/B49/1000,0) -> 0 | F42: 0.0098 | G42: 0 | H42: =IF(H47<>0,$B$177/$B$49/1000,0) -> 0 | I42: 0.014 | J42: 0.0058026316
A43: Total Fixed Costs | B43: =SUM(B37:B42) -> 0 | C43: =SUM(C37:C42) -> 0.0943 | D43: =SUM(D37:D42) -> 0.058371315 | E43: =SUM(E37:E42) -> 0 | F43: =SUM(F37:F42) -> 0.0977 | G43: =SUM(G37:G42) -> 0 | H43: =SUM(H37:H42) -> 0 | I43: =SUM(I37:I42) -> 0.1121 | J43: =SUM(J37:J42) -> 0.058371315
A44: Excess Costs
A45: TOTAL COSTS PER POUND | B45: =B35+B43 -> 0 | C45: =C35+C43+C44 -> 0.3456 | D45: =D35+D43 -> 0.20710061 | E45: =E35+E43 -> 0 | F45: =F35+F43+F44 -> 0.3043 | G45: 0 | H45: =H35+H43 -> 0 | I45: =I35+I43+I44 -> 0.2323 | J45: =+J35+J43 -> 0.10873952
A47: PRODUCTION ( in 000 lbs ) | B47: =B55 -> 0 | C47: 13494 | D47: 22600 | E47: =B56 -> 0 | F47: 1391 | G47: 0 | H47: =B59 -> 0 | I47: 6147 | J47: 2400
A49: TOTAL PLANT PRODUCTION ( in 000 lbs) | B49: =B24+E24+H24+B47+E47+H47 -> 0 | C49: =C24+F24+I24+C47+F47+I47 -> 34654 | D49: 76000
A51: Variable Costs - Material | B51: Purchase Price/lb * Yield Factor * Scrap Factor * Mix = Std. Cost Contribution
A53: Production Plan: | B53: Pounds (000) | C53: Product Split | D53: Days
A54: HT (foundry) | B54: ='2025 Summary'!$C$5 -> 0 | C54: =B54/$B$60 -> #DIV/0!
A55: CarboProp | B55: ='2025 Summary'!D$5 -> 0 | C55: =B55/$B$60 -> #DIV/0! | D55: =B55/180/2 -> 0
A56: CarboHSP | B56: ='2025 Summary'!E$5 -> 0 | C56: =B56/$B$60 -> #DIV/0! | D56: =B56/200/2 -> 0
A57: Bauxite Pellets | B57: ='2025 Summary'!$F$5 -> 0 | C57: =B57/$B$60 -> #DIV/0!
A58: ID (foundry) | B58: ='2025 Summary'!$G$5 -> 0 | C58: =B58/$B$60 -> #DIV/0!
A59: Nanomite C | B59: ='2025 Summary'!$H$5 -> 0 | C59: =B59/$B$60 -> #DIV/0! | D59: =B59/200 -> 0
A60: Total | B60: =SUM(B54:B59) -> 0 | C60: =B60/$B$60 -> #DIV/0!
AB61: NEED TO VERIFY ALL FORMULAS IN THE SECTION BELOW: Done
C62: Yield Factor | G62: Mix %
A63: Local Kaolin | B63: Price ($/Ton) | C63: CG | D63: CP | E63: HSP | F63: CL | G63: Cristobalite | H63: CG | I63: CP / ID | J63: HSP | K63: CL | L63: Cristobalite | AE63: price/1000/lb | AM63: Mix%
A64: Arcilla (local kaolin) 30012 | B64: =11.75*2 -> 23.5 | C64: =$C$76*H64 -> 0.2668 | D64: =$C$84*I64 -> 0.056 | E64: =$G$84*J64 -> 0 | F64: =$K$84*K64 -> 2 | G64: =$K$84*L64 -> 0 | H64: 0.667 | I64: 0.14 | J64: 0 | K64: 1 | L64: 0 | AB64: 30012/U103 | AE64: =B64/2000*1000 -> 11.75 | AM64: =$AM$76*I64 -> 56 | AO64: =$AO$84*K64 -> 2000
A65: Dixon (local kaolin) | B65: 0 | C65: =$C$76*H65 -> 0 | D65: =$C$84*I65 -> 0 | E65: =$G$84*J65 -> 0 | F65: =$K$84*K65 -> 0 | G65: =$K$84*L65 -> 0 | H65: 0 | I65: 0 | J65: 0 | K65: 0 | L65: 0 | AB65: 30012/U103 | AE65: =B65/2000*1000 -> 0 | AM65: =$AM$76*I65 -> 0 | AO65: =$AO$85*J65 -> 0
C66: =SUM(C64:C65) -> 0.2668 | D66: =SUM(D64:D65) -> 0.056 | E66: =SUM(E64:E65) -> 0 | F66: =SUM(F64:F65) -> 2 | G66: =SUM(G64:G65) -> 0
A67: Bauxite: | AO67: =$AO$85*J66 -> 0
A68: MRN (30006) Lord Allen & ECT | B68: =60.33+8+44 -> 112.33 | C68: =$C$77*H68 -> 0.1837 | D68: =$C$85*I68 -> 0.98 | E68: =$G$85*J68 -> 1.8 | F68: =$K$85*K68 -> 0 | G68: =$K$85*L68 -> 0 | H68: 0.167 | I68: 0.56 | J68: 1 | K68: 0 | L68: 0 | AB68: 30006/U103 | AE68: =B68/2000*1000 -> 56.165 | AM68: =$AM$77*I68 -> 980 | AN68: =$AN$85*I68 -> 980 | AO68: =$AO$85*J68 -> 0
A69: Rusal (30008) Lord Allen & ECT | B69: =56.29*2 -> 112.58 | C69: =$C$77*H69 -> 0 | D69: =$C$85*I69 -> 0 | E69: =$G$85*J69 -> 0 | F69: =$K$85*K69 -> 0 | G69: =$K$85*L69 -> 0 | H69: 0 | I69: 0 | J69: 0 | K69: 0 | L69: 0 | AB69: 30008/U103 | AE69: =B69/2000*1000 -> 56.29 | AM69: =$AM$77*I69 -> 0 | AN69: =$AN$85*I69 -> 0 | AO69: =$AO$85*J69 -> 0
A70: Bosai Chem Grade (30002) | B70: 160 | C70: 0 | D70: =$C$85*I70 -> 0 | E70: =$G$85*J70 -> 0 | F70: =$K$85*K70 -> 0 | G70: =$K$85*L70 -> 0 | H70: 0 | I70: 0 | J70: 0 | K70: 0 | L70: 0 | M70: Changed Bosai Chem Grade Price | AB70: 30003/U103 | AE70: =B70/2000*1000 -> 80 | AM70: =$AM$77*I70 -> 0 | AN70: =$AN$85*I70 -> 0
A71: First Bauxite (30440) | B71: =194+44 -> 238 | C71: =$C$77*H71 -> 0.1837 | D71: =$C$85*I71 -> 0.525 | E71: =$G$85*J71 -> 0 | F71: =$K$85*K71 -> 0 | G71: =$K$85*L71 -> 0 | H71: 0.167 | I71: 0.3 | J71: 0 | K71: 0 | L71: 0 | AB71: 30440/U103 | AE71: =B71/2000*1000 -> 119 | AM71: =$AM$77*I71 -> 525 | AN71: =$AN$85*I71 -> 525 | AO71: =$AO$85*J70 -> 0
C72: =SUM(C68:C71) -> 0.3674 | D72: =SUM(D68:D71) -> 1.505 | E72: =SUM(E68:E71) -> 1.8 | F72: =SUM(F68:F71) -> 0 | G72: =SUM(G68:G71) -> 0
B74: HT | F74: Cristobalite | J74: Nanomite | AE74: CG
B75: Price ($/lb) | C75: Yield Factor | D75: Std $ Contrib | F75: Price ($/lb) | G75: Yield Factor | H75: Std $ Contrib | J75: Price ($/lb) | K75: Yield Factor | L75: Std $ Contrib | AE75: price/1000/lb
A76: Local Kaolin | B76: 0.013 | C76: 0.4 | D76: =B76*C76 -> 0.0052 | F76: =($B$64*$L$64+$B$65*$L$65)/2000 -> 0 | G76: 0 | H76: =F76*G76 -> 0 | J76: =($B$64*$L$64+$B$65*$L$65)/2000 -> 0 | K76: 0 | L76: =J76*K76 -> 0 | AB76: 30012/U103 | AE76: =B76*1000 -> 13 | AK76: kaolin | AM76: =IF(B84<>0,D84/B84*1000,0) -> 400
A77: Bauxite | B77: =B71/2000 -> 0.119 | C77: 1.1 | D77: =B77*C77 -> 0.1309 | F77: =($B$68*$L$68+$B$69*$L$69+$B$70*$L$70+$B$71*$L$71)/2000 -> 0 | G77: 0 | H77: =F77*G77 -> 0 | J77: =($B$68*$L$68+$B$69*$L$69+$B$70*$L$70+$B$71*$L$71)/2000 -> 0 | K77: 0 | L77: =J77*K77 -> 0 | AB77: 30060/U103 | AE77: =B77*1000 -> 119 | AK77: bauxite | AM77: =IF(B85<>0,D85/B85*1000,0) -> 1750
A78: Starch (30020) | B78: 0.88 | C78: 0.01 | D78: =B78*C78 -> 0.0088 | F78: =B86 -> 0.726 | G78: 0 | H78: =F78*G78 -> 0 | K78: 0 | L78: =J78*K78 -> 0 | AB78: 30020/U103 | AE78: =B78*1000 -> 880 | AK78: starch | AM78: =IF(B86<>0,D86/B86*1000,0) -> 8
A79: Taggant | D79: 0 | G79: 0 | H79: =F79*G79 -> 0 | K79: 0 | L79: =J79*K79 -> 0
A80: Total Material Cost Per Pound | D80: =SUM(D76:D79) -> 0.1449 | H80: =SUM(H76:H79) -> 0 | L80: 0.08
B82: =B26 -> CP | F82: =E26 -> HSP | J82: CL | AE82: CP/ID | AG82: CL
B83: Price ($/lb) | C83: Yield Factor | D83: Std $ Contrib | F83: Price ($/lb) | G83: Yield Factor | H83: Std $ Contrib | J83: Price ($/lb) | K83: Yield Factor | L83: Std $ Contrib | AE83: price/1000/lb | AG83: price/1000/lb
A84: Local kaolin | B84: 0.013 | C84: 0.4 | D84: =B84*C84 -> 0.0052 | F84: =($B$64*$J$64+$B$65*$J$65)/2000 -> 0 | G84: 0 | H84: =F84*G84 -> 0 | J84: =($B$64*$K$64+$B$65*$K$65)/2000 -> 0.01175 | K84: 2 | L84: =J84*K84 -> 0.0235 | AB84: 30012/U103 | AE84: =B84*1000 -> 13 | AG84: =J84*1000 -> 11.75 | AN84: =IF(B84<>0,D84/B84*1000,0) -> 400 | AO84: =IF(J84<>0,L84/J84*1000,0) -> 2000
A85: Bauxite | B85: 0.067 | C85: 1.75 | D85: =B85*C85 -> 0.11725 | F85: =($B$68*$J$68+$B$69*$J$69+$B$70*$J$70+$B$71*$J$71)/2000 -> 0.056165 | G85: 1.8 | H85: =F85*G85 -> 0.101097 | J85: =($B$68*$K$68+$B$69*$K$69+$B$70*$K$70+$B$71*$K$71)/2000 -> 0 | K85: 1.065 | L85: =J85*K85 -> 0 | AB85: Various (see above) | AE85: =B85*1000 -> 67 | AG85: =J85*1000 -> 0 | AN85: =IF(B85<>0,D85/B85*1000,0) -> 1750 | AO85: =IF(J85<>0,L85/J85*1000,0) -> 0
A86: Starch (30020) | B86: 0.726 | C86: 0.008 | D86: =B86*C86 -> 0.005808 | F86: =B86 -> 0.726 | G86: 0.008 | H86: =F86*G86 -> 0.005808 | J86: =B86 -> 0.726 | K86: 0.0065 | L86: =J86*K86 -> 0.004719 | M86: Increased starch to 0.8% | AB86: 30020/U103 | AE86: =B86*1000 -> 726 | AG86: =J86*1000 -> 726 | AN86: =IF(B86<>0,D86/B86*1000,0) -> 8 | AO86: =IF(J86<>0,L86/J86*1000,0) -> 6.5
A87: Taggant | D87: 0 | H87: 0 | L87: 0
A88: Total Material Cost Per Pound | D88: =SUM(D84:D86) -> 0.128258 | H88: =SUM(H84:H86) -> 0.106905 | L88: =SUM(L84:L87) -> 0.028219
A90: Variable Cost - Labor & Benefits - 12 hour shift
AE91: Nov-20 YTD
U92: =$Z$14*$AD92 -> 0 | Z92: =AA14*$AD92 -> 0 | AB92: DLAB01 (s/t) | AC92: 611030 | AD92: =+AE92/AE94 -> 0.7411825 | AE92: 882400
U93: =$Z$14*$AD93 -> 0 | Z93: =AA14*$AD93 -> 0 | AB93: DLAB01 (o/t) | AC93: 610210 | AD93: =+AE93/AE94 -> 0.2588175 | AE93: 308130
U94: =SUM(U92:U93) -> 0 | Z94: =SUM(Z92:Z93) -> 0 | AA94: hr | AB94: DLAB01 | AC94: Total | AE94: =SUM(AE92:AE93) -> 1190530
B97: Jan | C97: Feb | D97: Mar | E97: Apr | F97: May | G97: Jun | H97: Jul
A98: Production Labor | B98: 268968.01 | C98: 288390.24 | D98: 154345.41 | E98: 13412.75 | F98: 229529.76 | G98: 274156.29 | H98: 267092.21
A99: R & M Labor | B99: 67812.91 | C99: 64354.51 | D99: 40616.39 | E99: 14950.76 | F99: 74301.16 | G99: 85619.44 | H99: 74393.95 | U99: =$Z$15*$AD99 -> 0 | Z99: =AA15*$AD99 -> 0 | AB99: MLAB01 (s/t) | AC99: 611040 | AD99: =+AE99/AE102 -> 0.78080694 | AE99: 392660
A100: IPC | B100: 102162.56 | C100: 97023.8 | D100: 87771.29 | E100: 18740.91 | F100: 135347.7 | G100: 89284.14 | H100: 88862.54 | U100: =$Z$15*$AD100 -> 0 | Z100: =AA15*$AD100 -> 0 | AB100: MLAB01 (o/t) | AC100: 610215 | AD100: =+AE100/AE102 -> 0.21919306 | AE100: 110230
A101: Supervision | B101: 6248.2 | C101: 7823.13 | D101: 4541.85 | E101: 10625.36 | F101: 11684.3 | G101: 7724.39 | H101: 6820.85
A102: Temp | B102: 35640 | C102: 61311 | D102: 50554 | F102: 65416 | G102: 62538 | H102: 37211 | U102: =SUM(U99:U100) -> 0 | Z102: =SUM(Z99:Z100) -> 0 | AA102: hr | AB102: MLAB01 | AC102: Total | AE102: =SUM(AE99:AE100) -> 502890
A103: IPC (estimated) | B103: =B100/(B98+B99-B102+B101) -> 0.33235581 | C103: =C100/(C98+C99-C102+C101) -> 0.32421577 | D103: =D100/(D98+D99-D102+D101) -> 0.58926819 | E103: =E100/(E98+E99-E102+E101) -> 0.48067333 | F103: =F100/(F98+F99-F102+F101) -> 0.54117602 | G103: =G100/(G98+G99-G102+G101) -> 0.29277125 | H103: =H100/(H98+H99-H102+H101) -> 0.28564346
U104: =$Z$16*$AD104 -> 0 | Z104: =$AA$16*$AD104 -> 0 | AB104: IPC01 (vac) | AC104: 610220 | AD104: =+AE104/AE110 -> 0.1679896 | AE104: 109692
D105: $/FTE/month | F105: $ Rolling Total | U105: =$Z$16*$AD105 -> 0 | Z105: =$AA$16*$AD105 -> 0 | AB105: IPC01 (hol) | AC105: 610510 | AD105: =+AE105/AE110 -> 0.14075553 | AE105: 91909
A106: Current Production Labor | B106: 46 | D106: =(AVERAGE((B98-B102),(C98-C102),(G98-G102),(H98-H102)))/B106 -> 4901.6671 | F106: =D106*B106 -> 225476.69 | U106: =$Z$16*$AD106 -> 0 | Z106: =$AA$16*$AD106 -> 0 | AB106: IPC01 (401k) | AC106: 610600 | AD106: =+AE106/AE110 -> 0.069911435 | AE106: 45650
A107: Current R & M Labor | B107: 16 | D107: =AVERAGE($G$99:$H$99,B99:C99)/B107 -> 4565.3252 | F107: =D107*B107 -> 73045.202 | U107: =$Z$16*$AD107 -> 0 | Z107: =$AA$16*$AD107 -> 0 | AB107: IPC01 (ins) | AC107: 610610 | AD107: =+AE107/AE110 -> 0.33790731 | AE107: 220643
U108: =$Z$16*$AD108 -> 0 | Z108: =$AA$16*$AD108 -> 0 | AB108: IPC01 (tax) | AC108: 612000 | AD108: =+AE108/AE110 -> 0.25840584 | AE108: 168731
A109: Future Production Labor Increase | B109: 6 | D109: =D106 -> 4901.6671 | F109: =D109*B109 -> 29410.003 | U109: =$Z$16*$AD109 -> 0 | Z109: =$AA$16*$AD109 -> 0 | AB109: IPC01 (w/c) | AC109: 612100 | AD109: =+AE109/AE110 -> 0.025030285 | AE109: 16344
A110: Future R&M Labor Increase | B110: 6 | D110: =D107 -> 4565.3252 | F110: =D110*B110 -> 27391.951 | U110: =SUM(U104:U109) -> 0 | Z110: =SUM(Z104:Z109) -> 0 | AA110: hr | AB110: IPC01 | AC110: Total | AE110: =SUM(AE104:AE109) -> 652969
A112: Total Production Labor | B112: =B106+B109 -> 52 | D112: =D106 -> 4901.6671 | F112: =D112*B112 -> 254886.69
A113: Total R & M Labor | B113: =B107+B110 -> 22 | D113: =D106 -> 4901.6671 | F113: =D113*B113 -> 107836.68
...

Sheet Jan
A1: McINTYRE STANDARD 2025 | S1: COST CENTER 10001003 | AE1: Gross | AF1: Std | AG1: Abs Limit | AH1: Absorb | AI1: 10001003 | AJ1: Absorbed | AK1: 10001003 | AX1: Abs Cost
S2: CG | T2: CP | U2: HSP | V2: CL | W2: Nanomite C | X2: NRT | Y2: To Production | Z2: Idle Plant | AA2: TOTAL | AB2: Activity / Material | AC2: UOM | AD2: Ttl Unit Qty | AE2: Unit Cost | AF2: Cost/lb | AG2: Cost/lb | AH2: Cost/lb | AI2: Absorption | AJ2: Unit Cost | AK2: Underabs | AL2: EP Unit Qty | AM2: CP Unit Qty | AN2: HSP Unit Qty | AO2: CL Unit Qty | AP2: Nano C Qty | AQ2: NRT Unit Qty | AR2: EP Units/1000lb | AS2: CP Units/1000lb | AT2: HSP Units/1000lb | AU2: CL Units/1000lb | AV2: Nano C Units/1000lb | AW2: NRT Units/1000lb | AX2: per 10000
B3: HT | E3: Bauxite Pellets | H3: ID
B4: 25 Standard | C4: 23 Actual | D4: 22 Standard | E4: =B4 -> 25 Standard | F4: 23 Actual | G4: =+D4 -> 22 Standard | H4: =B4 -> 25 Standard | I4: 23 Actual | J4: =+D4 -> 22 Standard
F5: (Jan-Aug)
A6: Materials | B6: =IF($B$24<>0,$D$80,0) -> 0 | D6: 0 | E6: =IF(E24<>0,$L$88,0) -> 0 | F6: 0.071053254 | G6: 0.02685 | H6: =IF($H$24<>0,$D$88,0) -> 0 | J6: 0
A7: Electricity | B7: =IF($B$24<>0,$D$151,0) -> 0 | D7: 0 | E7: =IF(E24<>0,$D$151,0) -> 0 | F7: 0.03392679 | G7: 0.018883379 | H7: =IF(H24<>0,$D$151,0) -> 0 | J7: 0 | S7: =$C145*$B$24*1000*$B145 -> 0 | T7: =$C151*$B$47*1000*$B151 -> 0 | U7: =$F151*$E$47*1000*$E151 -> 0 | V7: =$F145*$E$24*1000*$E145 -> 0 | W7: =$I151*$H$47*1000*$H151 -> 9166.1355 | X7: =$I145*$H$24*1000*$H145 -> 0 | Y7: =SUM(S7:X7) -> 9166.1355 | Z7: 0 | AA7: =SUM(Y7:Z7) -> 9166.1355 | AB7: ELE01 | AC7: kwh | AD7: =ROUND((B145*B$24*1000)+(B151*B$47*1000)+(E145*E$24*1000)+(E151*E$47*1000)+(H145*H$24*1000)+(H151*H$47*1000),0) -> 125563 | AE7: =Y7/AD7 -> 0.073000291 | AF7: =Y7/$AF$24/1000 -> 0.0045830677 | AG7: 0.014890786 | AH7: =IF($AF$21<$AG$21,AF7,IF($AF$12<$AG$12,AF7,IF(AND($AF$12>$AG$12,$AF$20<$AG$20),($AG$12+($AG$20-$AF$20))/$AF$12*AF7,AF7/$AF$12*$AG$12))) -> 0.0019184927 | AI7: =AH7*$Y$24*1000 -> 3836.9853 | AJ7: =AI7/AD7 -> 0.030558248 | AK7: =Y7-AI7 -> 5329.1502 | AL7: =ROUND($B145*$B$24*1000,0) -> 0 | AM7: =ROUND($B151*$B$47*1000,0) -> 0 | AN7: =ROUND($E151*$E$47*1000,0) -> 0 | AO7: =ROUND($E145*$E$24*1000,0) -> 0 | AP7: =ROUND($H151*$H$47*1000,0) -> 125563 | AQ7: =ROUND($H145*$H$24*1000,0) -> 0 | AR7: =IF($B$24<>0,ROUND(AL7/B$24,3),0) -> 0 | AS7: =ROUND(AM7/B$47,3) -> #DIV/0! | AT7: =IF(E$47<>0,ROUND(AN7/E$47,3),0) -> 0 | AU7: =IF(F$24<>0,ROUND(AO7/F$24,3),0) -> 0 | AV7: =IF(H$47<>0,ROUND(AP7/H$47,3),0) -> 62.782 | AW7: =IF(H$24<>0,ROUND(AQ7/H$24,3),0) -> 0 | AX7: =AJ7*10000 -> 305.58248
A8: Gas | B8: =IF($B$24<>0,$D$152,0) -> 0 | D8: 0 | E8: =IF(E24<>0,$D$152,0) -> 0 | F8: 0.14600441 | G8: 0.04184 | H8: =IF(H24<>0,$D$152,0) -> 0 | J8: 0 | S8: =$C146*$B$24*1000*$B146 -> 0 | T8: =$C152*$B$47*1000*$B152 -> 0 | U8: =$F152*$E$47*1000*$E152 -> 0 | V8: =$F146*$E$24*1000*$E146 -> 0 | W8: =$I152*$H$47*1000*$H152 -> 0 | X8: =$I146*$H$24*1000*$H146 -> 0 | Y8: =SUM(S8:X8) -> 0 | Z8: 0 | AA8: =SUM(Y8:Z8) -> 0 | AB8: GAS01 | AC8: mbtu | AD8: =ROUND((B146*B$24*1000*1000)+(B152*B$47*1000*1000)+(E146*E$24*1000*1000)+(E152*E$47*1000*1000)+(H146*H$24*1000*1000)+(H152*H$47*1000*1000),0) -> 0 | AE8: =Y8/AD8 -> #DIV/0! | AF8: =Y8/$AF$24/1000 -> 0 | AG8: 0.042004912 | AH8: =IF($AF$21<$AG$21,AF8,IF($AF$12<$AG$12,AF8,IF(AND($AF$12>$AG$12,$AF$20<$AG$20),($AG$12+($AG$20-$AF$20))/$AF$12*AF8,AF8/$AF$12*$AG$12))) -> 0 | AI8: =AH8*$Y$24*1000 -> 0 | AJ8: =AI8/AD8 -> #DIV/0! | AK8: =Y8-AI8 -> 0 | AL8: =ROUND($B146*$B$24*1000*1000,0) -> 0 | AM8: =ROUND($B152*$B$47*1000*1000,0) -> 0 | AN8: =ROUND($E152*$E$47*1000*1000,0) -> 0 | AO8: =ROUND($E146*$E$24*1000*1000,0) -> 0 | AP8: =ROUND($H152*$H$47*1000*1000,0) -> 0 | AQ8: =ROUND($H146*$H$24*1000*1000,0) -> 0 | AR8: =IF($B$24<>0,ROUND(AL8/B$24,3),0) -> 0 | AS8: =ROUND(AM8/B$47,3) -> #DIV/0! | AT8: =IF(E$47<>0,ROUND(AN8/E$47,3),0) -> 0 | AU8: =IF(E$24<>0,ROUND(AO8/E$24,3),0) -> 0 | AV8: =IF(H$47<>0,ROUND(AP8/H$47,3),0) -> 0 | AW8: =IF(H$24<>0,ROUND(AQ8/H$24,3),0) -> 0 | AX8: =AJ8*10000 -> #DIV/0!
A9: R&M Supplies and Service | B9: =IF($B$24<>0,$H$159,0) -> 0 | D9: 0 | E9: =IF(E24<>0,$H$159,0) -> 0 | F9: 0.043366417 | G9: 0.022368421 | H9: =IF(H24<>0,$H$159,0) -> 0 | J9: 0 | S9: =B9*B$24*1000 -> 0 | T9: =B32*B$47*1000 -> 0 | U9: =E32*E$47*1000 -> 0 | V9: =E9*E$24*1000 -> 0 | W9: =H32*H$47*1000 -> 297000 | X9: =H9*H$24*1000 -> 0 | Y9: =SUM(S9:X9) -> 297000 | Z9: 0 | AA9: =SUM(Y9:Z9) -> 297000 | AB9: RMS01 | AC9: lb | AD9: =ROUND((S9/H$159)+(T9/H$159)+(U9/H$159)+(V9/H$159)+(W9/H$159)+(X9/H$159),0) -> 2000000 | AE9: =Y9/AD9 -> 0.1485 | AF9: =Y9/$AF$24/1000 -> 0.1485 | AG9: 0.019544347 | AH9: =IF($AF$21<$AG$21,AF9,IF($AF$12<$AG$12,AF9,IF(AND($AF$12>$AG$12,$AF$20<$AG$20),($AG$12+($AG$20-$AF$20))/$AF$12*AF9,AF9/$AF$12*$AG$12))) -> 0.062162764 | AI9: =AH9*$Y$24*1000 -> 124325.53 | AJ9: =AI9/AD9 -> 0.062162764 | AK9: =Y9-AI9 -> 172674.47 | AL9: =S9/$AE9 -> 0 | AM9: =T9/$AE9 -> 0 | AN9: =U9/$AE9 -> 0 | AO9: =V9/$AE9 -> 0 | AP9: =W9/$AE9 -> 2000000 | AQ9: =X9/$AE9 -> 0 | AR9: =IF($B$24<>0,ROUND(AL9/B$24,3),0) -> 0 | AS9: =ROUND(AM9/B$47,3) -> #DIV/0! | AT9: =IF(E$47<>0,ROUND(AN9/E$47,3),0) -> 0 | AU9: =IF(E$24<>0,ROUND(AO9/E$24,3),0) -> 0 | AV9: =IF(H$47<>0,ROUND(AP9/H$47,3),0) -> 1000 | AW9: =IF(H$24<>0,ROUND(AQ9/H$24,3),0) -> 0 | AX9: =AJ9*10000 -> 621.62764
A10: Manufacturing Supplies | B10: =IF($B$24<>0,$H$163,0) -> 0 | D10: 0 | E10: =IF(E24<>0,$H$163,0) -> 0 | F10: 0.00073336258 | G10: 0.00065789474 | H10: =IF($H$24<>0,$H$163,0) -> 0 | J10: 0 | S10: =B10*B$24*1000 -> 0 | T10: =B33*B$47*1000 -> 0 | U10: =E33*E$47*1000 -> 0 | V10: =E10*E$24*1000 -> 0 | W10: =H33*H$47*1000 -> 16862 | X10: =H10*H$24*1000 -> 0 | Y10: =SUM(S10:X10) -> 16862 | Z10: 0 | AA10: =SUM(Y10:Z10) -> 16862 | AB10: MFG01 | AC10: lb | AD10: =ROUND((S10/H$163)+(T10/H$163)+(U10/H$163)+(V10/H$163)+(W10/H$163)+(X10/H$163),0) -> 2000000 | AE10: =Y10/AD10 -> 0.008431 | AF10: =Y10/$AF$24/1000 -> 0.008431 | AG10: 0.0012510769 | AH10: =IF($AF$21<$AG$21,AF10,IF($AF$12<$AG$12,AF10,IF(AND($AF$12>$AG$12,$AF$20<$AG$20),($AG$12+($AG$20-$AF$20))/$AF$12*AF10,AF10/$AF$12*$AG$12))) -> 0.0035292543 | AI10: =AH10*$Y$24*1000 -> 7058.5086 | AJ10: =AI10/AD10 -> 0.0035292543 | AK10: =Y10-AI10 -> 9803.4914 | AL10: =S10/$AE10 -> 0 | AM10: =T10/$AE10 -> 0 | AN10: =U10/$AE10 -> 0 | AO10: =V10/$AE10 -> 0 | AP10: =W10/$AE10 -> 2000000 | AQ10: =X10/$AE10 -> 0 | AR10: =IF($B$24<>0,ROUND(AL10/B$24,3),0) -> 0 | AS10: =ROUND(AM10/B$47,3) -> #DIV/0! | AT10: =IF(E$47<>0,ROUND(AN10/E$47,3),0) -> 0 | AU10: =IF(E$24<>0,ROUND(AO10/E$24,3),0) -> 0 | AV10: =IF(H$47<>0,ROUND(AP10/H$47,3),0) -> 1000 | AW10: =IF(H$24<>0,ROUND(AQ10/H$24,3),0) -> 0 | AX10: =AJ10*10000 -> 35.292543
A11: Other variable | B11: =IF($B$24<>0,$H$166,0) -> 0 | D11: 0 | E11: =IF(E24<>0,$H$166,0) -> 0 | F11: 0.010235236 | G11: 0.0046052632 | H11: =IF($H$24<>0,$H$166,0) -> 0 | J11: 0 | S11: =B11*B$24*1000 -> 0 | T11: =B34*B$47*1000 -> 0 | U11: =E34*E$47*1000 -> 0 | V11: =E11*E$24*1000 -> 0 | W11: =H34*H$47*1000 -> 66000 | X11: =H11*H$24*1000 -> 0 | Y11: =SUM(S11:X11) -> 66000 | Z11: 0 | AA11: =SUM(Y11:Z11) -> 66000 | AB11: VAR01 | AC11: lb | AD11: =ROUND((S11/H$166)+(T11/H$166)+(U11/H$166)+(V11/H$166)+(W11/H$166)+(X11/H$166),0) -> 2000000 | AE11: =Y11/AD11 -> 0.033 | AF11: =Y11/$AF$24/1000 -> 0.033 | AG11: 0.0037333371 | AH11: =IF($AF$21<$AG$21,AF11,IF($AF$12<$AG$12,AF11,IF(AND($AF$12>$AG$12,$AF$20<$AG$20),($AG$12+($AG$20-$AF$20))/$AF$12*AF11,AF11/$AF$12*$AG$12))) -> 0.013813948 | AI11: =AH11*$Y$24*1000 -> 27627.895 | AJ11: =AI11/AD11 -> 0.013813948 | AK11: =Y11-AI11 -> 38372.105 | AL11: =S11/$AE11 -> 0 | AM11: =T11/$AE11 -> 0 | AN11: =U11/$AE11 -> 0 | AO11: =V11/$AE11 -> 0 | AP11: =W11/$AE11 -> 2000000 | AQ11: =X11/$AE11 -> 0 | AR11: =IF($B$24<>0,ROUND(AL11/B$24,3),0) -> 0 | AS11: =ROUND(AM11/B$47,3) -> #DIV/0! | AT11: =IF(E$47<>0,ROUND(AN11/E$47,3),0) -> 0 | AU11: =IF(E$24<>0,ROUND(AO11/E$24,3),0) -> 0 | AV11: =IF(H$47<>0,ROUND(AP11/H$47,3),0) -> 1000 | AW11: =IF(H$24<>0,ROUND(AQ11/H$24,3),0) -> 0 | AX11: =AJ11*10000 -> 138.13948
A12: Total Variable Costs | B12: =SUM(B6:B11) -> 0 | D12: =SUM(D6:D11) -> 0 | E12: =SUM(E6:E11) -> 0 | F12: =SUM(F6:F11) -> 0.30531947 | G12: =SUM(G6:G11) -> 0.11520496 | H12: =SUM(H6:H11) -> 0 | J12: =SUM(J6:J11) -> 0 | S12: =SUM(S7:S11) -> 0 | T12: =SUM(T7:T11) -> 0 | U12: =SUM(U7:U11) -> 0 | V12: =SUM(V7:V11) -> 0 | W12: =SUM(W7:W11) -> 389028.14 | X12: =SUM(X7:X11) -> 0 | Y12: =SUM(Y7:Y11) -> 389028.14 | Z12: =SUM(Z7:Z11) -> 0 | AA12: =SUM(AA7:AA11) -> 389028.14 | AF12: =SUM(AF7:AF11) -> 0.19451407 | AG12: =SUM(AG7:AG11) -> 0.081424459 | AH12: =SUM(AH7:AH11) -> 0.081424459 | AI12: =SUM(AI7:AI11) -> 162848.92 | AK12: =SUM(AK7:AK11) -> 226179.22
A14: Production Labor | B14: =IF($B$24<>0,$F$112/$B$49/1000,0) -> 0 | D14: 0 | E14: =IF(E24<>0,$F$112/$B$49/1000,0) -> 0 | F14: 0.055685781 | G14: 0.02638428 | H14: =IF($H$24<>0,$F$112/$B$49/1000,0) -> 0 | J14: 0 | S14: =B14*B$24*1000 -> 0 | T14: =B37*B$47*1000 -> 0 | U14: =E37*E$47*1000 -> 0 | V14: =E14*E$24*1000 -> 0 | W14: =H37*H$47*1000 -> 24508.336 | X14: =H14*H$24*1000 -> 0 | Y14: =SUM(S14:X14) -> 24508.336 | Z14: =-$D$115 -> 0 | AA14: =SUM(Y14:Z14) -> 24508.336 | AB14: DLAB01 | AC14: hr | AD14: =ROUND((S14/C$116)+(T14/C$116)+(U14/C$116)+(V14/C$116)+(W14/C$116)+(X14/C$116),0) -> #DIV/0! | AE14: =Y14/AD14 -> #DIV/0! | AF14: =Y14/$AF$24/1000 -> 0.012254168 | AG14: 0.011488554 | AH14: =IF($AF$21<$AG$21,AF14,IF($AF$20<$AG$20,AF14,IF(AND($AF$20>$AG$20,$AF$12<$AG$12),($AG$20+($AG$12-$AF$12))/$AF$20*AF14,AF14/$AF$20*$AG$20))) -> 0.01205584 | AI14: =AH14*$Y$24*1000 -> 24111.68 | AJ14: =AI14/AD14 -> #DIV/0! | AK14: =Y14-AI14 -> 396.65529 | AL14: =ROUND(S14/$C116,0) -> #DIV/0! | AM14: =ROUND(T14/$C116,0) -> #DIV/0! | AN14: =ROUND(U14/$C116,0) -> #DIV/0! | AO14: =ROUND(V14/$C116,0) -> #DIV/0! | AP14: =ROUND(W14/$C116,0) -> #DIV/0! | AQ14: =ROUND(X14/$C116,0) -> #DIV/0! | AR14: =IF($B$24<>0,ROUND(AL14/B$24,3),0) -> 0 | AS14: =ROUND(AM14/B$47,3) -> #DIV/0! | AT14: =IF(E$47<>0,ROUND(AN14/E$47,3),0) -> 0 | AU14: =IF(E$24<>0,ROUND(AO14/E$24,3),0) -> 0 | AV14: =IF(H$47<>0,ROUND(AP14/H$47,3),0) -> #DIV/0! | AW14: =IF(H$24<>0,ROUND(AQ14/H$24,3),0) -> 0 | AX14: =AJ14*10000 -> #DIV/0!
A15: Repairs & Maintenance Labor | B15: =IF($B$24<>0,$F$113/$B$49/1000,0) -> 0 | D15: 0 | E15: =IF(E24<>0,$F$113/$B$49/1000,0) -> 0 | F15: 0.019535758 | G15: 0.00902044 | H15: =IF($H$24<>0,$F$113/$B$49/1000,0) -> 0 | J15: 0 | S15: =B15*B$24*1000 -> 0 | T15: =B38*B$47*1000 -> 0 | U15: =E38*E$47*1000 -> 0 | V15: =E15*E$24*1000 -> 0 | W15: =H38*H$47*1000 -> 24508.336 | X15: =H15*H$24*1000 -> 0 | Y15: =SUM(S15:X15) -> 24508.336 | Z15: =-$H$115 -> 0 | AA15: =SUM(Y15:Z15) -> 24508.336 | AB15: MLAB01 | AC15: hr | AD15: =ROUND((S15/G$116)+(T15/G$116)+(U15/G$116)+(V15/G$116)+(W15/G$116)+(X15/G$116),0) -> #DIV/0! | AE15: =Y15/AD15 -> #DIV/0! | AF15: =Y15/$AF$24/1000 -> 0.012254168 | AG15: 0.007650221 | AH15: =IF($AF$21<$AG$21,AF15,IF($AF$20<$AG$20,AF15,IF(AND($AF$20>$AG$20,$AF$12<$AG$12),($AG$20+($AG$12-$AF$12))/$AF$20*AF15,AF15/$AF$20*$AG$20))) -> 0.01205584 | AI15: =AH15*$Y$24*1000 -> 24111.68 | AJ15: =AI15/AD15 -> #DIV/0! | AK15: =Y15-AI15 -> 396.65529 | AL15: =ROUND(S15/$G$116,0) -> #DIV/0! | AM15: =ROUND(T15/$G$116,0) -> #DIV/0! | AN15: =ROUND(U15/$G$116,0) -> #DIV/0! | AO15: =ROUND(V15/$G$116,0)-1 -> #DIV/0! | AP15: =ROUND(W15/$G$116,0) -> #DIV/0! | AQ15: =ROUND(X15/$G$116,0) -> #DIV/0! | AR15: =IF($B$24<>0,ROUND(AL15/B$24,3),0) -> 0 | AS15: =ROUND(AM15/B$47,3) -> #DIV/0! | AT15: =IF(E$47<>0,ROUND(AN15/E$47,3),0) -> 0 | AU15: =IF(E$24<>0,ROUND(AO15/E$24,3),0) -> 0 | AV15: =IF(H$47<>0,ROUND(AP15/H$47,3),0) -> #DIV/0! | AW15: =IF(H$24<>0,ROUND(AQ15/H$24,3),0) -> 0 | AX15: =AJ15*10000 -> #DIV/0!
A16: Indirect Payroll Costs (Benefits) | B16: =IF(B24<>0,$F$115/$B$49/1000,0) -> 0 | D16: 0 | E16: =IF(E24<>0,$F$115/$B$49/1000,0) -> 0 | F16: 0.01706523 | G16: 0.013928937 | H16: =IF($H$24<>0,$F$115/$B$49/1000,0) -> 0 | J16: 0 | S16: =B16*B$24*1000 -> 0 | T16: =B39*B$47*1000 -> 0 | U16: =E39*E$47*1000 -> 0 | V16: =E16*E$24*1000 -> 0 | W16: =H39*H$47*1000 -> 16851.201 | X16: =H16*H$24*1000 -> 0 | Y16: =SUM(S16:X16) -> 16851.201 | Z16: =-$D$122 -> 0 | AA16: =SUM(Y16:Z16) -> 16851.201 | AB16: IPC01 | AC16: hr | AD16: =ROUND((S16/C$123)+(T16/C$123)+(U16/C$123)+(V16/C$123)+(W16/C$123)+(X16/C$123),0) -> #DIV/0! | AE16: =Y16/AD16 -> #DIV/0! | AF16: =Y16/$AF$24/1000 -> 0.0084256007 | AG16: 0.0088563301 | AH16: =IF($AF$21<$AG$21,AF16,IF($AF$20<$AG$20,AF16,IF(AND($AF$20>$AG$20,$AF$12<$AG$12),($AG$20+($AG$12-$AF$12))/$AF$20*AF16,AF16/$AF$20*$AG$20))) -> 0.0082892365 | AI16: =AH16*$Y$24*1000 -> 16578.473 | AJ16: =AI16/AD16 -> #DIV/0! | AK16: =Y16-AI16 -> 272.72836 | AL16: =ROUND(S16/$C123,0) -> #DIV/0! | AM16: =ROUND(T16/$C123,0) -> #DIV/0! | AN16: =ROUND(U16/$C123,0) -> #DIV/0! | AO16: =ROUND(V16/$C123,0) -> #DIV/0! | AP16: =ROUND(W16/$C123,0) -> #DIV/0! | AQ16: =ROUND(X16/$C123,0) -> #DIV/0! | AR16: =IF($B$24<>0,ROUND(AL16/B$24,3),0) -> 0 | AS16: =ROUND(AM16/B$47,3) -> #DIV/0! | AT16: =IF(E$47<>0,ROUND(AN16/E$47,3),0) -> 0 | AU16: =IF(E$24<>0,ROUND(AO16/E$24,3),0) -> 0 | AV16: =IF(H$47<>0,ROUND(AP16/H$47,3),0) -> #DIV/0! | AW16: =IF(H$24<>0,ROUND(AQ16/H$24,3),0) -> 0 | AX16: =AJ16*10000 -> #DIV/0!
A17: Supervision | B17: =IF($B$24<>0,$F$114/$B$49/1000,0) -> 0 | D17: 0 | E17: =IF(E24<>0,$F$114/$B$49/1000,0) -> 0 | F17: 0.0045810516 | G17: 0.0015771316 | H17: =IF($H$24<>0,$F$114/$B$49/1000,0) -> 0 | J17: 0 | S17: =B17*B$24*1000 -> 0 | T17: =B40*B$47*1000 -> 0 | U17: =E40*E$47*1000 -> 0 | V17: =E17*E$24*1000 -> 0 | W17: =H40*H$47*1000 -> 7154 | X17: =H17*H$24*1000 -> 0 | Y17: =SUM(S17:X17) -> 7154 | Z17: =C176/($C$184+$C$185)*$C$185 -> 0 | AA17: =SUM(Y17:Z17) -> 7154 | AB17: SUP01 | AC17: lb | AD17: =ROUND((S17/F$176)+(T17/F$176)+(U17/F$176)+(V17/F$176)+(W17/F$176)+(X17/F$176),0) -> #DIV/0! | AE17: =Y17/AD17 -> #DIV/0! | AF17: =Y17/$AF$24/1000 -> 0.003577 | AG17: 0.0021273119 | AH17: =IF($AF$21<$AG$21,AF17,IF($AF$20<$AG$20,AF17,IF(AND($AF$20>$AG$20,$AF$12<$AG$12),($AG$20+($AG$12-$AF$12))/$AF$20*AF17,AF17/$AF$20*$AG$20))) -> 0.003519108 | AI17: =AH17*$Y$24*1000 -> 7038.216 | AJ17: =AI17/AD17 -> #DIV/0! | AK17: =Y17-AI17 -> 115.78395 | AL17: =S17/$AE17 -> #DIV/0! | AM17: =T17/$AE17 -> #DIV/0! | AN17: =U17/$AE17 -> #DIV/0! | AO17: =V17/$AE17 -> #DIV/0! | AP17: =W17/$AE17 -> #DIV/0! | AQ17: =X17/$AE17 -> #DIV/0! | AR17: =IF($B$24<>0,ROUND(AL17/B$24,3),0) -> 0 | AS17: =ROUND(AM17/B$47,3) -> #DIV/0! | AT17: =IF(E$47<>0,ROUND(AN17/E$47,3),0) -> 0 | AU17: =IF(E$24<>0,ROUND(AO17/E$24,3),0) -> 0 | AV17: =IF(H$47<>0,ROUND(AP17/H$47,3),0) -> #DIV/0! | AW17: =IF(H$24<>0,ROUND(AQ17/H$24,3),0) -> 0 | AX17: =AJ17*10000 -> #DIV/0!
A18: Depreciation | B18: =IF($B$24<>0,$B$178/$B$49/1000,0) -> 0 | D18: 0 | E18: =IF(E24<>0,$B$178/$B$49/1000,0) -> 0 | F18: 0.0038559807 | G18: 0.0016578947 | H18: =IF($H$24<>0,$B$178/$B$49/1000,0) -> 0 | J18: 0 | S18: =B18*B$24*1000 -> 0 | T18: =B41*B$47*1000 -> 0 | U18: =E41*E$47*1000 -> 0 | V18: =E18*E$24*1000 -> 0 | W18: =H41*H$47*1000 -> 25872 | X18: =H18*H$24*1000 -> 0 | Y18: =SUM(S18:X18) -> 25872 | Z18: =C178/($C$184+$C$185)*$C$185 -> 0 | AA18: =SUM(Y18:Z18) -> 25872 | AB18: DEP01 | AC18: lb | AD18: =ROUND((S18/F$178)+(T18/F$178)+(U18/F$178)+(V18/F$178)+(W18/F$178)+(X18/F$178),0) -> 166667 | AE18: =Y18/AD18 -> 0.15523169 | AF18: =Y18/$AF$24/1000 -> 0.012936 | AG18: 0.032747211 | AH18: =IF($AF$21<$AG$21,AF18,IF($AF$20<$AG$20,AF18,IF(AND($AF$20>$AG$20,$AF$12<$AG$12),($AG$20+($AG$12-$AF$12))/$AF$20*AF18,AF18/$AF$20*$AG$20))) -> 0.012726637 | AI18: =AH18*$Y$24*1000 -> 25453.274 | AJ18: =AI18/AD18 -> 0.15271934 | AK18: =Y18-AI18 -> 418.72552 | AL18: =S18/$AE18 -> 0 | AM18: =T18/$AE18 -> 0 | AN18: =U18/$AE18 -> 0 | AO18: =V18/$AE18 -> 0 | AP18: =W18/$AE18 -> 166667 | AQ18: =X18/$AE18 -> 0 | AR18: =IF($B$24<>0,ROUND(AL18/B$24,3),0) -> 0 | AS18: =ROUND(AM18/B$47,3) -> #DIV/0! | AT18: =IF(E$47<>0,ROUND(AN18/E$47,3),0) -> 0 | AU18: =IF(E$24<>0,ROUND(AO18/E$24,3),0) -> 0 | AV18: =IF(H$47<>0,ROUND(AP18/H$47,3),0) -> 83.334 | AW18: =IF(H$24<>0,ROUND(AQ18/H$24,3),0) -> 0 | AX18: =AJ18*10000 -> 1527.1934
A19: Insurance & Taxes | B19: =IF($B$24<>0,$B$177/$B$49/1000,0) -> 0 | D19: 0 | E19: =IF(E24<>0,$B$177/E26/1000,0) -> 0 | F19: 0.010801566 | G19: 0.0058026316 | H19: =IF($H$24<>0,$B$177/$B$49/1000,0) -> 0 | J19: 0 | S19: =B19*B$24*1000 -> 0 | T19: =B42*B$47*1000 -> 0 | U19: =E42*E$47*1000 -> 0 | V19: =E19*E$24*1000 -> 0 | W19: =H42*H$47*1000 -> 43878 | X19: =H19*H$24*1000 -> 0 | Y19: =SUM(S19:X19) -> 43878 | Z19: =C177/($C$184+$C$185)*$C$185 -> 0 | AA19: =SUM(Y19:Z19) -> 43878 | AB19: INS01 | AC19: lb | AD19: =ROUND((S19/F$177)+(T19/F$177)+(U19/F$177)+(V19/F$177)+(W19/F$177)+(X19/F$177),0) -> 166667 | AE19: =Y19/AD19 -> 0.26326747 | AF19: =Y19/$AF$24/1000 -> 0.021939 | AG19: 0.0073609622 | AH19: =IF($AF$21<$AG$21,AF19,IF($AF$20<$AG$20,AF19,IF(AND($AF$20>$AG$20,$AF$12<$AG$12),($AG$20+($AG$12-$AF$12))/$AF$20*AF19,AF19/$AF$20*$AG$20))) -> 0.021583928 | AI19: =AH19*$Y$24*1000 -> 43167.856 | AJ19: =AI19/AD19 -> 0.25900662 | AK19: =Y19-AI19 -> 710.14373 | AL19: =S19/$AE19 -> 0 | AM19: =T19/$AE19 -> 0 | AN19: =U19/$AE19 -> 0 | AO19: =V19/$AE19 -> 0 | AP19: =W19/$AE19 -> 166667 | AQ19: =X19/$AE19 -> 0 | AR19: =IF($B$24<>0,ROUND(AL19/B$24,3),0) -> 0 | AS19: =ROUND(AM19/B$47,3) -> #DIV/0! | AT19: =IF(E$47<>0,ROUND(AN19/E$47,3),0) -> 0 | AU19: =IF(E$24<>0,ROUND(AO19/E$24,3),0) -> 0 | AV19: =IF(H$47<>0,ROUND(AP19/H$47,3),0) -> 83.334 | AW19: =IF(H$24<>0,ROUND(AQ19/H$24,3),0) -> 0 | AX19: =AJ19*10000 -> 2590.0662
A20: Total Fixed Costs | B20: =SUM(B14:B19) -> 0 | C20: =SUM(C14:C19) -> 0 | D20: =SUM(D14:D19) -> 0 | E20: =SUM(E14:E19) -> 0 | F20: =SUM(F14:F19) -> 0.11152537 | G20: =SUM(G14:G19) -> 0.058371315 | H20: =SUM(H14:H19) -> 0 | I20: =SUM(I14:I19) -> 0 | J20: =SUM(J14:J19) -> 0 | S20: =SUM(S14:S19) -> 0 | T20: =SUM(T14:T19) -> 0 | U20: =SUM(U14:U19) -> 0 | V20: =SUM(V14:V19) -> 0 | W20: =SUM(W14:W19) -> 142771.87 | X20: =SUM(X14:X19) -> 0 | Y20: =SUM(Y14:Y19) -> 142771.87 | Z20: =SUM(Z14:Z19) -> 0 | AA20: =SUM(AA14:AA19) -> 142771.87 | AF20: =SUM(AF14:AF19) -> 0.071385936 | AG20: =SUM(AG14:AG19) -> 0.07023059 | AH20: =SUM(AH14:AH19) -> 0.07023059 | AI20: =SUM(AI14:AI19) -> 140461.18 | AK20: =SUM(AK14:AK19) -> 2310.6921
A21: Excess Costs | C21: -0.0273 | F21: -0.050457361 | S21: =S12+S20 -> 0 | T21: =T12+T20 -> 0 | U21: =U12+U20 -> 0 | V21: =V12+V20 -> 0 | W21: =W12+W20 -> 531800.01 | X21: =X12+X20 -> 0 | Y21: =Y12+Y20 -> 531800.01 | Z21: =Z12+Z20 -> 0 | AA21: =AA12+AA20 -> 531800.01 | AB21: CCtr Total | AF21: =AF12+AF20 -> 0.2659 | AG21: =AG12+AG20 -> 0.15165505 | AH21: =AH12+AH20 -> 0.15165505 | AI21: =AI12+AI20 -> 303310.1 | AK21: =AK12+AK20 -> 228489.91
A22: TOTAL COSTS PER POUND | B22: =B12+B20 -> 0 | C22: =+C20+C21+C12 -> -0.0273 | D22: =D12+D20 -> 0 | E22: =E12+E20 -> 0 | F22: =F12+F20+F21 -> 0.36638748 | G22: =G12+G20 -> 0.17357627 | H22: =H12+H20 -> 0 | I22: =I12+I20 -> 0 | J22: =J12+J20 -> 0 | S22: =IF(B24<>0,ROUND(S21/(B24*1000),5),0) -> 0 | T22: =IF(B47<>0,ROUND(T21/(B47*1000),5),0) -> 0 | U22: =IF(E47<>0,ROUND(U21/(E47*1000),5),0) -> 0 | V22: =IF(E24<>0,ROUND(V21/(E24*1000),5),0) -> 0 | W22: =IF(H47<>0,ROUND(W21/(H47*1000),5),0) -> 0.2659 | X22: =IF(H24<>0,ROUND(X21/(H24*1000),5),0) -> 0 | Y22: =Y21/Y24/1000 -> 0.2659 | Z22: 0 | AA22: =ROUND(AA21/(B49*1000),5) -> 0.2659 | AB22: Excl Matl | AI22: =AI21/AI24/1000 -> 0.15165505 | AK22: =AK21/AK24/1000 -> 0.11424496
S23: =ROUND(S22+B6,5) -> 0 | T23: =ROUND(T22+B29,5) -> 0 | U23: =ROUND(U22+E29,5) -> 0 | V23: =ROUND(V22+E6,5) -> 0 | W23: =ROUND(W22+H29,5) -> 0.3459 | X23: =ROUND(X22+H6,5) -> 0 | Y23: =Y22+(($B$6*$B$24*1000+$B$29*$B$47*1000+$E$29*$E$47*1000+$H$6*$H$24*1000+$H$29*$H$47*1000+$E$6*$E$24*1000)/($B$49*1000)) -> 0.3459 | Z23: 0 | AA23: =AA22+(($B$6*$B$24*1000+$B$29*$B$47*1000+$E$6*$E$24*1000+$E$29*$E$47*1000+$H$6*$H$24*1000+$H$29*$H$47*1000)/($B$49*1000)) -> 0.3459 | AB23: Incl Matl
A24: PRODUCTION ( in 000 lbs ) | B24: =B54 -> 0 | C24: 6211 | D24: 0 | E24: =B57 -> 0 | F24: 3204 | G24: 51000 | H24: =B58 -> 0 | I24: 4207 | J24: 0 | S24: =B24 -> 0 | T24: =B47 -> 0 | U24: =E47 -> 0 | V24: =E24 -> 0 | W24: =H47 -> 2000 | X24: =H24 -> 0 | Y24: =SUM(S24:X24) -> 2000 | Z24: 0 | AA24: =SUM(Y24:Z24) -> 2000 | AF24: =Y24 -> 2000 | AI24: =Y24 -> 2000 | AK24: =Y24 -> 2000
B26: CP | E26: HSP | H26: Nanomite C | AS26: 0.936
B27: =B4 -> 25 Standard | C27: 23 Actual | D27: =+D4 -> 22 Standard | E27: =E4 -> 25 Standard | F27: =+C27 -> 23 Actual | G27: =+D27 -> 22 Standard | H27: =H4 -> 25 Standard | I27: 23 Actual | J27: =+J4 -> 22 Standard | AS27: 0.264
C28: (Jan-Aug) | F28: (Jan-Aug) | I28: (Jan-Aug) | AS28: 286
A29: Materials | B29: =IF($B$47<>0,$D$88,0) -> 0 | C29: 0.1396 | D29: 0.06037434 | E29: =IF(E47<>0,$D$88,0) -> 0 | F29: 0.0865 | G29: 0 | H29: =IF(H47<>0,$L$80,0) -> 0.08 | I29: 0.0792 | J29: 0.02 | AS29: 8000
A30: Electricity | B30: =IF(B47<>0,$D$151,0) -> 0 | C30: 0.0273 | D30: 0.018883379 | E30: =IF(E47<>0,$G$151,0) -> 0 | F30: 0.0294 | G30: 0 | H30: =IF(H47<>0,$J$151,0) -> 0.0045830677 | I30: 0.0124 | J30: 0.0027366213 | AS30: 1.2
A31: Gas | B31: =IF(B47<>0,$D$152,0) -> 0 | C31: 0.0379 | D31: 0.04184 | E31: =IF(E47<>0,$G$152,0) -> 0 | F31: 0.0465 | G31: 0 | H31: =IF(H47<>0,$J$152,0) -> 0 | I31: 0 | J31: 0
A32: R&M Supplies and Service | B32: =IF(B47<>0,$H$159,0) -> 0 | C32: 0.0358 | D32: 0.022368421 | E32: =IF(E47<>0,$H$159,0) -> 0 | F32: 0.0304 | G32: 0 | H32: =IF(H47<>0,$H$159,0) -> 0.1485 | I32: 0.0164 | J32: 0.022368421
A33: Manufacturing Supplies | B33: =IF(B47<>0,$H$163,0) -> 0 | C33: 0.0006 | D33: 0.00065789474 | E33: =IF(E47<>0,$H$163,0) -> 0 | F33: 0.002 | G33: 0 | H33: =IF(H47<>0,$H$163,0) -> 0.008431 | I33: 0.0014 | J33: 0.00065789474
A34: Other variable | B34: =IF($B$47<>0,$H$166,0) -> 0 | C34: 0.0101 | D34: 0.0046052632 | E34: =IF(E47<>0,$H$166,0) -> 0 | F34: 0.0118 | G34: 0 | H34: =IF(H47<>0,$H$166,0) -> 0.033 | I34: 0.0108 | J34: 0.0046052632
A35: Total Variable Costs | B35: =SUM(B29:B34) -> 0 | C35: =SUM(C29:C34) -> 0.2513 | D35: =SUM(D29:D34) -> 0.1487293 | E35: =SUM(E29:E34) -> 0 | F35: =SUM(F29:F34) -> 0.2066 | G35: =SUM(G29:G34) -> 0 | H35: =SUM(H29:H34) -> 0.27451407 | I35: =SUM(I29:I34) -> 0.1202 | J35: =SUM(J29:J34) -> 0.0503682
A37: Production Labor | B37: =IF(B47<>0,$F$112/$B$49/1000,0) -> 0 | C37: 0.0445 | D37: 0.02638428 | E37: =IF(E47<>0,$F$112/$B$49/1000,0) -> 0 | F37: 0.0483 | G37: 0 | H37: =IF(H47<>0,$F$112/$B$49/1000,0) -> 0.012254168 | I37: 0.0451 | J37: 0.02638428
A38: Repairs & Maintenance Labor | B38: =IF(B47<>0,$F$113/$B$49/1000,0) -> 0 | C38: 0.015 | D38: 0.00902044 | E38: =IF(E47<>0,$F$113/$B$49/1000,0) -> 0 | F38: 0.0144 | G38: 0 | H38: =IF(H47<>0,$F$113/$B$49/1000,0) -> 0.012254168 | I38: 0.0156 | J38: 0.00902044
A39: Indirect Payroll Costs (Benefits) | B39: =IF(B47<>0,$F$115/$B$49/1000,0) -> 0 | C39: 0.0194 | D39: 0.013928937 | E39: =IF(E47<>0,$F$115/$B$49/1000,0) -> 0 | F39: 0.0196 | G39: 0 | H39: =IF(H47<>0,$F$115/$B$49/1000,0) -> 0.0084256007 | I39: 0.0285 | J39: 0.013928937
A40: Supervision | B40: =IF($B$47<>0,$F$114/$B$49/1000,0) -> 0 | C40: 0.0018 | D40: 0.0015771316 | E40: =IF(E47<>0,$F$114/$B$49/1000,0) -> 0 | F40: 0.0014 | G40: 0 | H40: =IF(H47<>0,$F$114/$B$49/1000,0) -> 0.003577 | I40: 0.0022 | J40: 0.0015771316
A41: Depreciation | B41: =IF(B47<>0,$B$178/$B$49/1000,0) -> 0 | C41: 0.0043 | D41: 0.0016578947 | E41: =IF(E47<>0,$B$178/$B$49/1000,0) -> 0 | F41: 0.0042 | G41: 0 | H41: =IF(H47<>0,$B$178/$B$49/1000,0) -> 0.012936 | I41: 0.0067 | J41: 0.0016578947
A42: Insurance & Taxes | B42: =IF(B47<>0,$B$177/B49/1000,0) -> 0 | C42: 0.0093 | D42: 0.0058026316 | E42: =IF(E47<>0,$B$177/B49/1000,0) -> 0 | F42: 0.0098 | G42: 0 | H42: =IF(H47<>0,$B$177/$B$49/1000,0) -> 0.021939 | I42: 0.014 | J42: 0.0058026316
A43: Total Fixed Costs | B43: =SUM(B37:B42) -> 0 | C43: =SUM(C37:C42) -> 0.0943 | D43: =SUM(D37:D42) -> 0.058371315 | E43: =SUM(E37:E42) -> 0 | F43: =SUM(F37:F42) -> 0.0977 | G43: =SUM(G37:G42) -> 0 | H43: =SUM(H37:H42) -> 0.071385936 | I43: =SUM(I37:I42) -> 0.1121 | J43: =SUM(J37:J42) -> 0.058371315
A44: Excess Costs
A45: TOTAL COSTS PER POUND | B45: =B35+B43 -> 0 | C45: =C35+C43+C44 -> 0.3456 | D45: =D35+D43 -> 0.20710061 | E45: =E35+E43 -> 0 | F45: =F35+F43+F44 -> 0.3043 | G45: 0 | H45: =H35+H43 -> 0.3459 | I45: =I35+I43+I44 -> 0.2323 | J45: =+J35+J43 -> 0.10873952
A47: PRODUCTION ( in 000 lbs ) | B47: =B55 -> 0 | C47: 13494 | D47: 22600 | E47: =B56 -> 0 | F47: 1391 | G47: 0 | H47: =B59 -> 2000 | I47: 6147 | J47: 2400
A49: TOTAL PLANT PRODUCTION ( in 000 lbs) | B49: =B24+E24+H24+B47+E47+H47 -> 2000 | C49: =C24+F24+I24+C47+F47+I47 -> 34654 | D49: 76000
A51: Variable Costs - Material | B51: Purchase Price/lb * Yield Factor * Scrap Factor * Mix = Std. Cost Contribution
A53: Production Plan: | B53: Pounds (000) | C53: Product Split | D53: Days
A54: HT (foundry) | B54: ='2025 Summary'!$C$6 -> 0 | C54: =B54/$B$60 -> 0
A55: CarboProp | B55: ='2025 Summary'!D$6 -> 0 | C55: =B55/$B$60 -> 0 | D55: =B55/180/2 -> 0
A56: CarboHSP | B56: ='2025 Summary'!E$6 -> 0 | C56: =B56/$B$60 -> 0 | D56: =B56/200/2 -> 0
A57: Bauxite Pellets | B57: ='2025 Summary'!$F$6 -> 0 | C57: =B57/$B$60 -> 0
A58: ID (foundry) | B58: ='2025 Summary'!$G$6 -> 0 | C58: =B58/$B$60 -> 0
A59: Nanomite C | B59: ='2025 Summary'!$H$6 -> 2000 | C59: =B59/$B$60 -> 1 | D59: =B59/200 -> 10
A60: Total | B60: =SUM(B54:B59) -> 2000 | C60: =B60/$B$60 -> 1
AB61: NEED TO VERIFY ALL FORMULAS IN THE SECTION BELOW: Done
C62: Yield Factor | G62: Mix %
A63: Local Kaolin | B63: Price ($/Ton) | C63: CG | D63: CP | E63: HSP | F63: CL | G63: Cristobalite | H63: CG | I63: CP / ID | J63: HSP | K63: CL | L63: Cristobalite | AE63: price/1000/lb | AM63: Mix%
A64: Arcilla (local kaolin) 30012 | B64: =11.75*2 -> 23.5 | C64: =$C$76*H64 -> 0.2668 | D64: =$C$84*I64 -> 0.056 | E64: =$G$84*J64 -> 0 | F64: =$K$84*K64 -> 2 | G64: =$K$84*L64 -> 0 | H64: 0.667 | I64: 0.14 | J64: 0 | K64: 1 | L64: 0 | AB64: 30012/U103 | AE64: =B64/2000*1000 -> 11.75 | AM64: =$AM$76*I64 -> 56 | AO64: =$AO$84*K64 -> 2000
A65: Dixon (local kaolin) | B65: 0 | C65: =$C$76*H65 -> 0 | D65: =$C$84*I65 -> 0 | E65: =$G$84*J65 -> 0 | F65: =$K$84*K65 -> 0 | G65: =$K$84*L65 -> 0 | H65: 0 | I65: 0 | J65: 0 | K65: 0 | L65: 0 | AB65: 30012/U103 | AE65: =B65/2000*1000 -> 0 | AM65: =$AM$76*I65 -> 0 | AO65: =$AO$85*J65 -> 0
C66: =SUM(C64:C65) -> 0.2668 | D66: =SUM(D64:D65) -> 0.056 | E66: =SUM(E64:E65) -> 0 | F66: =SUM(F64:F65) -> 2 | G66: =SUM(G64:G65) -> 0
A67: Bauxite: | AO67: =$AO$85*J66 -> 0
A68: MRN (30006) Lord Allen & ECT | B68: =60.33+8+44 -> 112.33 | C68: =$C$77*H68 -> 0.1837 | D68: =$C$85*I68 -> 0.98 | E68: =$G$85*J68 -> 1.8 | F68: =$K$85*K68 -> 0 | G68: =$K$85*L68 -> 0 | H68: 0.167 | I68: 0.56 | J68: 1 | K68: 0 | L68: 0 | AB68: 30006/U103 | AE68: =B68/2000*1000 -> 56.165 | AM68: =$AM$77*I68 -> 980 | AN68: =$AN$85*I68 -> 980 | AO68: =$AO$85*J68 -> 0
A69: Rusal (30008) Lord Allen & ECT | B69: =56.29*2 -> 112.58 | C69: =$C$77*H69 -> 0 | D69: =$C$85*I69 -> 0 | E69: =$G$85*J69 -> 0 | F69: =$K$85*K69 -> 0 | G69: =$K$85*L69 -> 0 | H69: 0 | I69: 0 | J69: 0 | K69: 0 | L69: 0 | AB69: 30008/U103 | AE69: =B69/2000*1000 -> 56.29 | AM69: =$AM$77*I69 -> 0 | AN69: =$AN$85*I69 -> 0 | AO69: =$AO$85*J69 -> 0
A70: Bosai Chem Grade (30002) | B70: 160 | C70: 0 | D70: =$C$85*I70 -> 0 | E70: =$G$85*J70 -> 0 | F70: =$K$85*K70 -> 0 | G70: =$K$85*L70 -> 0 | H70: 0 | I70: 0 | J70: 0 | K70: 0 | L70: 0 | M70: Changed Bosai Chem Grade Price | AB70: 30003/U103 | AE70: =B70/2000*1000 -> 80 | AM70: =$AM$77*I70 -> 0 | AN70: =$AN$85*I70 -> 0
A71: First Bauxite (30440) | B71: =194+44 -> 238 | C71: =$C$77*H71 -> 0.1837 | D71: =$C$85*I71 -> 0.525 | E71: =$G$85*J71 -> 0 | F71: =$K$85*K71 -> 0 | G71: =$K$85*L71 -> 0 | H71: 0.167 | I71: 0.3 | J71: 0 | K71: 0 | L71: 0 | AB71: 30440/U103 | AE71: =B71/2000*1000 -> 119 | AM71: =$AM$77*I71 -> 525 | AN71: =$AN$85*I71 -> 525 | AO71: =$AO$85*J70 -> 0
C72: =SUM(C68:C71) -> 0.3674 | D72: =SUM(D68:D71) -> 1.505 | E72: =SUM(E68:E71) -> 1.8 | F72: =SUM(F68:F71) -> 0 | G72: =SUM(G68:G71) -> 0
B74: HT | F74: Cristobalite | J74: Nanomite | AE74: CG
B75: Price ($/lb) | C75: Yield Factor | D75: Std $ Contrib | F75: Price ($/lb) | G75: Yield Factor | H75: Std $ Contrib | J75: Price ($/lb) | K75: Yield Factor | L75: Std $ Contrib | AE75: price/1000/lb
A76: Local Kaolin | B76: 0.013 | C76: 0.4 | D76: =B76*C76 -> 0.0052 | F76: =($B$64*$L$64+$B$65*$L$65)/2000 -> 0 | G76: 0 | H76: =F76*G76 -> 0 | J76: =($B$64*$L$64+$B$65*$L$65)/2000 -> 0 | K76: 0 | L76: =J76*K76 -> 0 | AB76: 30012/U103 | AE76: =B76*1000 -> 13 | AK76: kaolin | AM76: =IF(B84<>0,D84/B84*1000,0) -> 400
A77: Bauxite | B77: =B71/2000 -> 0.119 | C77: 1.1 | D77: =B77*C77 -> 0.1309 | F77: =($B$68*$L$68+$B$69*$L$69+$B$70*$L$70+$B$71*$L$71)/2000 -> 0 | G77: 0 | H77: =F77*G77 -> 0 | J77: =($B$68*$L$68+$B$69*$L$69+$B$70*$L$70+$B$71*$L$71)/2000 -> 0 | K77: 0 | L77: =J77*K77 -> 0 | AB77: 30060/U103 | AE77: =B77*1000 -> 119 | AK77: bauxite | AM77: =IF(B85<>0,D85/B85*1000,0) -> 1750
A78: Starch (30020) | B78: 0.88 | C78: 0.01 | D78: =B78*C78 -> 0.0088 | F78: =B86 -> 0.726 | G78: 0 | H78: =F78*G78 -> 0 | K78: 0 | L78: =J78*K78 -> 0 | AB78: 30020/U103 | AE78: =B78*1000 -> 880 | AK78: starch | AM78: =IF(B86<>0,D86/B86*1000,0) -> 8
A79: Taggant | D79: 0 | G79: 0 | H79: =F79*G79 -> 0 | K79: 0 | L79: =J79*K79 -> 0
A80: Total Material Cost Per Pound | D80: =SUM(D76:D79) -> 0.1449 | H80: =SUM(H76:H79) -> 0 | L80: 0.08
B82: =B26 -> CP | F82: =E26 -> HSP | J82: CL | AE82: CP/ID | AG82: CL
B83: Price ($/lb) | C83: Yield Factor | D83: Std $ Contrib | F83: Price ($/lb) | G83: Yield Factor | H83: Std $ Contrib | J83: Price ($/lb) | K83: Yield Factor | L83: Std $ Contrib | AE83: price/1000/lb | AG83: price/1000/lb
A84: Local kaolin | B84: 0.013 | C84: 0.4 | D84: =B84*C84 -> 0.0052 | F84: =($B$64*$J$64+$B$65*$J$65)/2000 -> 0 | G84: 0 | H84: =F84*G84 -> 0 | J84: =($B$64*$K$64+$B$65*$K$65)/2000 -> 0.01175 | K84: 2 | L84: =J84*K84 -> 0.0235 | AB84: 30012/U103 | AE84: =B84*1000 -> 13 | AG84: =J84*1000 -> 11.75 | AN84: =IF(B84<>0,D84/B84*1000,0) -> 400 | AO84: =IF(J84<>0,L84/J84*1000,0) -> 2000
A85: Bauxite | B85: 0.067 | C85: 1.75 | D85: =B85*C85 -> 0.11725 | F85: =($B$68*$J$68+$B$69*$J$69+$B$70*$J$70+$B$71*$J$71)/2000 -> 0.056165 | G85: 1.8 | H85: =F85*G85 -> 0.101097 | J85: =($B$68*$K$68+$B$69*$K$69+$B$70*$K$70+$B$71*$K$71)/2000 -> 0 | K85: 1.065 | L85: =J85*K85 -> 0 | AB85: Various (see above) | AE85: =B85*1000 -> 67 | AG85: =J85*1000 -> 0 | AN85: =IF(B85<>0,D85/B85*1000,0) -> 1750 | AO85: =IF(J85<>0,L85/J85*1000,0) -> 0
A86: Starch (30020) | B86: 0.726 | C86: 0.008 | D86: =B86*C86 -> 0.005808 | F86: =B86 -> 0.726 | G86: 0.008 | H86: =F86*G86 -> 0.005808 | J86: =B86 -> 0.726 | K86: 0.0065 | L86: =J86*K86 -> 0.004719 | M86: Increased starch to 0.8% | AB86: 30020/U103 | AE86: =B86*1000 -> 726 | AG86: =J86*1000 -> 726 | AN86: =IF(B86<>0,D86/B86*1000,0) -> 8 | AO86: =IF(J86<>0,L86/J86*1000,0) -> 6.5
A87: Taggant | D87: 0 | H87: 0 | L87: 0
A88: Total Material Cost Per Pound | D88: =SUM(D84:D86) -> 0.128258 | H88: =SUM(H84:H86) -> 0.106905 | L88: =SUM(L84:L87) -> 0.028219
A90: Variable Cost - Labor & Benefits - 12 hour shift
AE91: Nov-20 YTD
U92: =$Z$14*$AD92 -> 0 | Z92: =AA14*$AD92 -> 18165.149 | AB92: DLAB01 (s/t) | AC92: 611030 | AD92: =+AE92/AE94 -> 0.7411825 | AE92: 882400
U93: =$Z$14*$AD93 -> 0 | Z93: =AA14*$AD93 -> 6343.1862 | AB93: DLAB01 (o/t) | AC93: 610210 | AD93: =+AE93/AE94 -> 0.2588175 | AE93: 308130
U94: =SUM(U92:U93) -> 0 | Z94: =SUM(Z92:Z93) -> 24508.336 | AA94: hr | AB94: DLAB01 | AC94: Total | AE94: =SUM(AE92:AE93) -> 1190530
B97: Jan | C97: Feb | D97: Mar | E97: Apr | F97: May | G97: Jun | H97: Jul
A98: Production Labor | B98: 268968.01 | C98: 288390.24 | D98: 154345.41 | E98: 13412.75 | F98: 229529.76 | G98: 274156.29 | H98: 267092.21
A99: R & M Labor | B99: 67812.91 | C99: 64354.51 | D99: 40616.39 | E99: 14950.76 | F99: 74301.16 | G99: 85619.44 | H99: 74393.95 | U99: =$Z$15*$AD99 -> 0 | Z99: =AA15*$AD99 -> 19136.278 | AB99: MLAB01 (s/t) | AC99: 611040 | AD99: =+AE99/AE102 -> 0.78080694 | AE99: 392660
A100: IPC | B100: 102162.56 | C100: 97023.8 | D100: 87771.29 | E100: 18740.91 | F100: 135347.7 | G100: 89284.14 | H100: 88862.54 | U100: =$Z$15*$AD100 -> 0 | Z100: =AA15*$AD100 -> 5372.0572 | AB100: MLAB01 (o/t) | AC100: 610215 | AD100: =+AE100/AE102 -> 0.21919306 | AE100: 110230
A101: Supervision | B101: 6248.2 | C101: 7823.13 | D101: 4541.85 | E101: 10625.36 | F101: 11684.3 | G101: 7724.39 | H101: 6820.85
A102: Temp | B102: 35640 | C102: 61311 | D102: 50554 | F102: 65416 | G102: 62538 | H102: 37211 | U102: =SUM(U99:U100) -> 0 | Z102: =SUM(Z99:Z100) -> 24508.336 | AA102: hr | AB102: MLAB01 | AC102: Total | AE102: =SUM(AE99:AE100) -> 502890
A103: IPC (estimated) | B103: =B100/(B98+B99-B102+B101) -> 0.33235581 | C103: =C100/(C98+C99-C102+C101) -> 0.32421577 | D103: =D100/(D98+D99-D102+D101) -> 0.58926819 | E103: =E100/(E98+E99-E102+E101) -> 0.48067333 | F103: =F100/(F98+F99-F102+F101) -> 0.54117602 | G103: =G100/(G98+G99-G102+G101) -> 0.29277125 | H103: =H100/(H98+H99-H102+H101) -> 0.28564346
U104: =$Z$16*$AD104 -> 0 | Z104: =$AA$16*$AD104 -> 2830.8265 | AB104: IPC01 (vac) | AC104: 610220 | AD104: =+AE104/AE110 -> 0.1679896 | AE104: 109692
D105: $/FTE/month | F105: $ Rolling Total | U105: =$Z$16*$AD105 -> 0 | Z105: =$AA$16*$AD105 -> 2371.8998 | AB105: IPC01 (hol) | AC105: 610510 | AD105: =+AE105/AE110 -> 0.14075553 | AE105: 91909
A106: Current Production Labor | B106: 46 | D106: =(AVERAGE((B98-B102),(C98-C102),(G98-G102),(H98-H102)))/B106 -> 4901.6671 | F106: =D106*B106 -> 225476.69 | U106: =$Z$16*$AD106 -> 0 | Z106: =$AA$16*$AD106 -> 1178.0917 | AB106: IPC01 (401k) | AC106: 610600 | AD106: =+AE106/AE110 -> 0.069911435 | AE106: 45650
A107: Current R & M Labor | B107: 16 | D107: =AVERAGE($G$99:$H$99,B99:C99)/B107 -> 4565.3252 | F107: =D107*B107 -> 73045.202 | U107: =$Z$16*$AD107 -> 0 | Z107: =$AA$16*$AD107 -> 5694.1442 | AB107: IPC01 (ins) | AC107: 610610 | AD107: =+AE107/AE110 -> 0.33790731 | AE107: 220643
U108: =$Z$16*$AD108 -> 0 | Z108: =$AA$16*$AD108 -> 4354.4488 | AB108: IPC01 (tax) | AC108: 612000 | AD108: =+AE108/AE110 -> 0.25840584 | AE108: 168731
A109: Future Production Labor Increase | B109: 6 | D109: =D106 -> 4901.6671 | F109: =D109*B109 -> 29410.003 | U109: =$Z$16*$AD109 -> 0 | Z109: =$AA$16*$AD109 -> 421.79037 | AB109: IPC01 (w/c) | AC109: 612100 | AD109: =+AE109/AE110 -> 0.025030285 | AE109: 16344
A110: Future R&M Labor Increase | B110: 6 | D110: =D107 -> 4565.3252 | F110: =D110*B110 -> 27391.951 | U110: =SUM(U104:U109) -> 0 | Z110: =SUM(Z104:Z109) -> 16851.201 | AA110: hr | AB110: IPC01 | AC110: Total | AE110: =SUM(AE104:AE109) -> 652969
A112: Total Production Labor | B112: 5 | D112: =D106 -> 4901.6671 | F112: =D112*B112 -> 24508.336
A113: Total R & M Labor | B113: 5 | D113: =D106 -> 4901.6671 | F113: =D113*B113 -> 24508.336
...

Sheet Feb
A1: McINTYRE STANDARD 2025 | S1: COST CENTER 10001003 | AE1: Gross | AF1: Std | AG1: Abs Limit | AH1: Absorb | AI1: 10001003 | AJ1: Absorbed | AK1: 10001003 | AX1: Abs Cost
S2: CG | T2: CP | U2: HSP | V2: CL | W2: Nanomite C | X2: NRT | Y2: To Production | Z2: Idle Plant | AA2: TOTAL | AB2: Activity / Material | AC2: UOM | AD2: Ttl Unit Qty | AE2: Unit Cost | AF2: Cost/lb | AG2: Cost/lb | AH2: Cost/lb | AI2: Absorption | AJ2: Unit Cost | AK2: Underabs | AL2: EP Unit Qty | AM2: CP Unit Qty | AN2: HSP Unit Qty | AO2: CL Unit Qty | AP2: Nano C Qty | AQ2: NRT Unit Qty | AR2: EP Units/1000lb | AS2: CP Units/1000lb | AT2: HSP Units/1000lb | AU2: CL Units/1000lb | AV2: Nano C Units/1000lb | AW2: NRT Units/1000lb | AX2: per 10000
B3: HT | E3: Bauxite Pellets | H3: ID
B4: 25 Standard | C4: 23 Actual | D4: 22 Standard | E4: =B4 -> 25 Standard | F4: 23 Actual | G4: =+D4 -> 22 Standard | H4: =B4 -> 25 Standard | I4: 23 Actual | J4: =+D4 -> 22 Standard
F5: (Jan-Aug)
A6: Materials | B6: =IF($B$24<>0,$D$80,0) -> 0.1449 | D6: 0 | E6: =IF(E24<>0,$L$88,0) -> 0.10801025 | F6: 0.071053254 | G6: 0.02685 | H6: =IF($H$24<>0,$D$88,0) -> 0.128258 | J6: 0
A7: Electricity | B7: =IF($B$24<>0,$D$151,0) -> 0.033069 | D7: 0 | E7: =IF(E24<>0,$D$151,0) -> 0.033069 | F7: 0.03392679 | G7: 0.018883379 | H7: =IF(H24<>0,$D$151,0) -> 0.033069 | J7: 0 | S7: =$C145*$B$24*1000*$B145 -> 82431.165 | T7: =$C151*$B$47*1000*$B151 -> 115741.5 | U7: =$F151*$E$47*1000*$E151 -> 0 | V7: =$F145*$E$24*1000*$E145 -> 252592.4 | W7: =$I151*$H$47*1000*$H151 -> 0 | X7: =$I145*$H$24*1000*$H145 -> 21132.554 | Y7: =SUM(S7:X7) -> 471897.61 | Z7: 0 | AA7: =SUM(Y7:Z7) -> 471897.61 | AB7: ELE01 | AC7: kwh | AD7: =ROUND((B145*B$24*1000)+(B151*B$47*1000)+(E145*E$24*1000)+(E151*E$47*1000)+(H145*H$24*1000)+(H151*H$47*1000),0) -> 6834346 | AE7: =Y7/AD7 -> 0.069047955 | AF7: =Y7/$AF$24/1000 -> 0.033138877 | AG7: 0.014890786 | AH7: =IF($AF$21<$AG$21,AF7,IF($AF$12<$AG$12,AF7,IF(AND($AF$12>$AG$12,$AF$20<$AG$20),($AG$12+($AG$20-$AF$20))/$AF$12*AF7,AF7/$AF$12*$AG$12))) -> 0.033138877 | AI7: =AH7*$Y$24*1000 -> 471897.61 | AJ7: =AI7/AD7 -> 0.069047955 | AK7: =Y7-AI7 -> 0 | AL7: =ROUND($B145*$B$24*1000,0) -> 1129194 | AM7: =ROUND($B151*$B$47*1000,0) -> 1585500 | AN7: =ROUND($E151*$E$47*1000,0) -> 0 | AO7: =ROUND($E145*$E$24*1000,0) -> 3801600 | AP7: =ROUND($H151*$H$47*1000,0) -> 0 | AQ7: =ROUND($H145*$H$24*1000,0) -> 318052 | AR7: =IF($B$24<>0,ROUND(AL7/B$24,3),0) -> 645.254 | AS7: =ROUND(AM7/B$47,3) -> 453 | AT7: =IF(E$47<>0,ROUND(AN7/E$47,3),0) -> 0 | AU7: =IF(F$24<>0,ROUND(AO7/F$24,3),0) -> 1186.517 | AV7: =IF(H$47<>0,ROUND(AP7/H$47,3),0) -> 0 | AW7: =IF(H$24<>0,ROUND(AQ7/H$24,3),0) -> 122.8 | AX7: =AJ7*10000 -> 690.47955
A8: Gas | B8: =IF($B$24<>0,$D$152,0) -> 0.04 | D8: 0 | E8: =IF(E24<>0,$D$152,0)/2 -> 0.02 | F8: 0.14600441 | G8: 0.04184 | H8: =IF(H24<>0,$D$152,0) -> 0.04 | J8: 0 | S8: =$C146*$B$24*1000*$B146 -> 103658.52 | T8: =$C152*$B$47*1000*$B152 -> 140000 | U8: =$F152*$E$47*1000*$E152 -> 0 | V8: =$F146*$E$24*1000*$E146 -> 460800 | W8: =$I152*$H$47*1000*$H152 -> 0 | X8: =$I146*$H$24*1000*$H146 -> 39627 | Y8: =SUM(S8:X8) -> 744085.52 | Z8: 0 | AA8: =SUM(Y8:Z8) -> 744085.52 | AB8: GAS01 | AC8: mbtu | AD8: =ROUND((B146*B$24*1000*1000)+(B152*B$47*1000*1000)+(E146*E$24*1000*1000)+(E152*E$47*1000*1000)+(H146*H$24*1000*1000)+(H152*H$47*1000*1000),0) -> 116517630 | AE8: =Y8/AD8 -> 0.0063860338 | AF8: =Y8/$AF$24/1000 -> 0.052253197 | AG8: 0.042004912 | AH8: =IF($AF$21<$AG$21,AF8,IF($AF$12<$AG$12,AF8,IF(AND($AF$12>$AG$12,$AF$20<$AG$20),($AG$12+($AG$20-$AF$20))/$AF$12*AF8,AF8/$AF$12*$AG$12))) -> 0.052253197 | AI8: =AH8*$Y$24*1000 -> 744085.52 | AJ8: =AI8/AD8 -> 0.0063860338 | AK8: =Y8-AI8 -> 0 | AL8: =ROUND($B146*$B$24*1000*1000,0) -> 25914630 | AM8: =ROUND($B152*$B$47*1000*1000,0) -> 35000000 | AN8: =ROUND($E152*$E$47*1000*1000,0) -> 0 | AO8: =ROUND($E146*$E$24*1000*1000,0) -> 51200000 | AP8: =ROUND($H152*$H$47*1000*1000,0) -> 0 | AQ8: =ROUND($H146*$H$24*1000*1000,0) -> 4403000 | AR8: =IF($B$24<>0,ROUND(AL8/B$24,3),0) -> 14808.36 | AS8: =ROUND(AM8/B$47,3) -> 10000 | AT8: =IF(E$47<>0,ROUND(AN8/E$47,3),0) -> 0 | AU8: =IF(E$24<>0,ROUND(AO8/E$24,3),0) -> 8000 | AV8: =IF(H$47<>0,ROUND(AP8/H$47,3),0) -> 0 | AW8: =IF(H$24<>0,ROUND(AQ8/H$24,3),0) -> 1700 | AX8: =AJ8*10000 -> 63.860338
A9: R&M Supplies and Service | B9: =IF($B$24<>0,$H$159,0) -> 0.020856742 | D9: 0 | E9: =IF(E24<>0,$H$159,0) -> 0.020856742 | F9: 0.043366417 | G9: 0.022368421 | H9: =IF(H24<>0,$H$159,0) -> 0.020856742 | J9: 0 | S9: =B9*B$24*1000 -> 36499.298 | T9: =B32*B$47*1000 -> 72998.596 | U9: =E32*E$47*1000 -> 0 | V9: =E9*E$24*1000 -> 133483.15 | W9: =H32*H$47*1000 -> 0 | X9: =H9*H$24*1000 -> 54018.961 | Y9: =SUM(S9:X9) -> 297000 | Z9: 0 | AA9: =SUM(Y9:Z9) -> 297000 | AB9: RMS01 | AC9: lb | AD9: =ROUND((S9/H$159)+(T9/H$159)+(U9/H$159)+(V9/H$159)+(W9/H$159)+(X9/H$159),0) -> 14240000 | AE9: =Y9/AD9 -> 0.020856742 | AF9: =Y9/$AF$24/1000 -> 0.020856742 | AG9: 0.019544347 | AH9: =IF($AF$21<$AG$21,AF9,IF($AF$12<$AG$12,AF9,IF(AND($AF$12>$AG$12,$AF$20<$AG$20),($AG$12+($AG$20-$AF$20))/$AF$12*AF9,AF9/$AF$12*$AG$12))) -> 0.020856742 | AI9: =AH9*$Y$24*1000 -> 297000 | AJ9: =AI9/AD9 -> 0.020856742 | AK9: =Y9-AI9 -> 0 | AL9: =S9/$AE9 -> 1750000 | AM9: =T9/$AE9 -> 3500000 | AN9: =U9/$AE9 -> 0 | AO9: =V9/$AE9 -> 6400000 | AP9: =W9/$AE9 -> 0 | AQ9: =X9/$AE9 -> 2590000 | AR9: =IF($B$24<>0,ROUND(AL9/B$24,3),0) -> 1000 | AS9: =ROUND(AM9/B$47,3) -> 1000 | AT9: =IF(E$47<>0,ROUND(AN9/E$47,3),0) -> 0 | AU9: =IF(E$24<>0,ROUND(AO9/E$24,3),0) -> 1000 | AV9: =IF(H$47<>0,ROUND(AP9/H$47,3),0) -> 0 | AW9: =IF(H$24<>0,ROUND(AQ9/H$24,3),0) -> 1000 | AX9: =AJ9*10000 -> 208.56742
A10: Manufacturing Supplies | B10: =IF($B$24<>0,$H$163,0) -> 0.0011841292 | D10: 0 | E10: =IF(E24<>0,$H$163,0) -> 0.0011841292 | F10: 0.00073336258 | G10: 0.00065789474 | H10: =IF($H$24<>0,$H$163,0) -> 0.0011841292 | J10: 0 | S10: =B10*B$24*1000 -> 2072.2261 | T10: =B33*B$47*1000 -> 4144.4522 | U10: =E33*E$47*1000 -> 0 | V10: =E10*E$24*1000 -> 7578.427 | W10: =H33*H$47*1000 -> 0 | X10: =H10*H$24*1000 -> 3066.8947 | Y10: =SUM(S10:X10) -> 16862 | Z10: 0 | AA10: =SUM(Y10:Z10) -> 16862 | AB10: MFG01 | AC10: lb | AD10: =ROUND((S10/H$163)+(T10/H$163)+(U10/H$163)+(V10/H$163)+(W10/H$163)+(X10/H$163),0) -> 14240000 | AE10: =Y10/AD10 -> 0.0011841292 | AF10: =Y10/$AF$24/1000 -> 0.0011841292 | AG10: 0.0012510769 | AH10: =IF($AF$21<$AG$21,AF10,IF($AF$12<$AG$12,AF10,IF(AND($AF$12>$AG$12,$AF$20<$AG$20),($AG$12+($AG$20-$AF$20))/$AF$12*AF10,AF10/$AF$12*$AG$12))) -> 0.0011841292 | AI10: =AH10*$Y$24*1000 -> 16862 | AJ10: =AI10/AD10 -> 0.0011841292 | AK10: =Y10-AI10 -> 0 | AL10: =S10/$AE10 -> 1750000 | AM10: =T10/$AE10 -> 3500000 | AN10: =U10/$AE10 -> 0 | AO10: =V10/$AE10 -> 6400000 | AP10: =W10/$AE10 -> 0 | AQ10: =X10/$AE10 -> 2590000 | AR10: =IF($B$24<>0,ROUND(AL10/B$24,3),0) -> 1000 | AS10: =ROUND(AM10/B$47,3) -> 1000 | AT10: =IF(E$47<>0,ROUND(AN10/E$47,3),0) -> 0 | AU10: =IF(E$24<>0,ROUND(AO10/E$24,3),0) -> 1000 | AV10: =IF(H$47<>0,ROUND(AP10/H$47,3),0) -> 0 | AW10: =IF(H$24<>0,ROUND(AQ10/H$24,3),0) -> 1000 | AX10: =AJ10*10000 -> 11.841292
A11: Other variable | B11: =IF($B$24<>0,$H$166,0) -> 0.0046348315 | D11: 0 | E11: =IF(E24<>0,$H$166,0) -> 0.0046348315 | F11: 0.010235236 | G11: 0.0046052632 | H11: =IF($H$24<>0,$H$166,0) -> 0.0046348315 | J11: 0 | S11: =B11*B$24*1000 -> 8110.9551 | T11: =B34*B$47*1000 -> 16221.91 | U11: =E34*E$47*1000 -> 0 | V11: =E11*E$24*1000 -> 29662.921 | W11: =H34*H$47*1000 -> 0 | X11: =H11*H$24*1000 -> 12004.213 | Y11: =SUM(S11:X11) -> 66000 | Z11: 0 | AA11: =SUM(Y11:Z11) -> 66000 | AB11: VAR01 | AC11: lb | AD11: =ROUND((S11/H$166)+(T11/H$166)+(U11/H$166)+(V11/H$166)+(W11/H$166)+(X11/H$166),0) -> 14240000 | AE11: =Y11/AD11 -> 0.0046348315 | AF11: =Y11/$AF$24/1000 -> 0.0046348315 | AG11: 0.0037333371 | AH11: =IF($AF$21<$AG$21,AF11,IF($AF$12<$AG$12,AF11,IF(AND($AF$12>$AG$12,$AF$20<$AG$20),($AG$12+($AG$20-$AF$20))/$AF$12*AF11,AF11/$AF$12*$AG$12))) -> 0.0046348315 | AI11: =AH11*$Y$24*1000 -> 66000 | AJ11: =AI11/AD11 -> 0.0046348315 | AK11: =Y11-AI11 -> 0 | AL11: =S11/$AE11 -> 1750000 | AM11: =T11/$AE11 -> 3500000 | AN11: =U11/$AE11 -> 0 | AO11: =V11/$AE11 -> 6400000 | AP11: =W11/$AE11 -> 0 | AQ11: =X11/$AE11 -> 2590000 | AR11: =IF($B$24<>0,ROUND(AL11/B$24,3),0) -> 1000 | AS11: =ROUND(AM11/B$47,3) -> 1000 | AT11: =IF(E$47<>0,ROUND(AN11/E$47,3),0) -> 0 | AU11: =IF(E$24<>0,ROUND(AO11/E$24,3),0) -> 1000 | AV11: =IF(H$47<>0,ROUND(AP11/H$47,3),0) -> 0 | AW11: =IF(H$24<>0,ROUND(AQ11/H$24,3),0) -> 1000 | AX11: =AJ11*10000 -> 46.348315
A12: Total Variable Costs | B12: =SUM(B6:B11) -> 0.2446447 | D12: =SUM(D6:D11) -> 0 | E12: =SUM(E6:E11) -> 0.18775495 | F12: =SUM(F6:F11) -> 0.30531947 | G12: =SUM(G6:G11) -> 0.11520496 | H12: =SUM(H6:H11) -> 0.2280027 | J12: =SUM(J6:J11) -> 0 | S12: =SUM(S7:S11) -> 232772.16 | T12: =SUM(T7:T11) -> 349106.46 | U12: =SUM(U7:U11) -> 0 | V12: =SUM(V7:V11) -> 884116.89 | W12: =SUM(W7:W11) -> 0 | X12: =SUM(X7:X11) -> 129849.62 | Y12: =SUM(Y7:Y11) -> 1595845.1 | Z12: =SUM(Z7:Z11) -> 0 | AA12: =SUM(AA7:AA11) -> 1595845.1 | AF12: =SUM(AF7:AF11) -> 0.11206778 | AG12: =SUM(AG7:AG11) -> 0.081424459 | AH12: =SUM(AH7:AH11) -> 0.11206778 | AI12: =SUM(AI7:AI11) -> 1595845.1 | AK12: =SUM(AK7:AK11) -> 0
A14: Production Labor | B14: =IF($B$24<>0,$F$112/$B$49/1000,0) -> 0.017899346 | D14: 0 | E14: =IF(E24<>0,$F$112/$B$49/1000,0) -> 0.017899346 | F14: 0.055685781 | G14: 0.02638428 | H14: =IF($H$24<>0,$F$112/$B$49/1000,0) -> 0.017899346 | J14: 0 | S14: =B14*B$24*1000 -> 31323.856 | T14: =B37*B$47*1000 -> 62647.712 | U14: =E37*E$47*1000 -> 0 | V14: =E14*E$24*1000 -> 114555.82 | W14: =H37*H$47*1000 -> 0 | X14: =H14*H$24*1000 -> 46359.307 | Y14: =SUM(S14:X14) -> 254886.69 | Z14: =-$D$115 -> 0 | AA14: =SUM(Y14:Z14) -> 254886.69 | AB14: DLAB01 | AC14: hr | AD14: =ROUND((S14/C$116)+(T14/C$116)+(U14/C$116)+(V14/C$116)+(W14/C$116)+(X14/C$116),0) -> #DIV/0! | AE14: =Y14/AD14 -> #DIV/0! | AF14: =Y14/$AF$24/1000 -> 0.017899346 | AG14: 0.011488554 | AH14: =IF($AF$21<$AG$21,AF14,IF($AF$20<$AG$20,AF14,IF(AND($AF$20>$AG$20,$AF$12<$AG$12),($AG$20+($AG$12-$AF$12))/$AF$20*AF14,AF14/$AF$20*$AG$20))) -> 0.017899346 | AI14: =AH14*$Y$24*1000 -> 254886.69 | AJ14: =AI14/AD14 -> #DIV/0! | AK14: =Y14-AI14 -> 0 | AL14: =ROUND(S14/$C116,0) -> #DIV/0! | AM14: =ROUND(T14/$C116,0) -> #DIV/0! | AN14: =ROUND(U14/$C116,0) -> #DIV/0! | AO14: =ROUND(V14/$C116,0) -> #DIV/0! | AP14: =ROUND(W14/$C116,0) -> #DIV/0! | AQ14: =ROUND(X14/$C116,0) -> #DIV/0! | AR14: =IF($B$24<>0,ROUND(AL14/B$24,3),0) -> #DIV/0! | AS14: =ROUND(AM14/B$47,3) -> #DIV/0! | AT14: =IF(E$47<>0,ROUND(AN14/E$47,3),0) -> 0 | AU14: =IF(E$24<>0,ROUND(AO14/E$24,3),0) -> #DIV/0! | AV14: =IF(H$47<>0,ROUND(AP14/H$47,3),0) -> 0 | AW14: =IF(H$24<>0,ROUND(AQ14/H$24,3),0) -> #DIV/0! | AX14: =AJ14*10000 -> #DIV/0!
A15: Repairs & Maintenance Labor | B15: =IF($B$24<>0,$F$113/$B$49/1000,0) -> 0.0075728003 | D15: 0 | E15: =IF(E24<>0,$F$113/$B$49/1000,0) -> 0.0075728003 | F15: 0.019535758 | G15: 0.00902044 | H15: =IF($H$24<>0,$F$113/$B$49/1000,0) -> 0.0075728003 | J15: 0 | S15: =B15*B$24*1000 -> 13252.401 | T15: =B38*B$47*1000 -> 26504.801 | U15: =E38*E$47*1000 -> 0 | V15: =E15*E$24*1000 -> 48465.922 | W15: =H38*H$47*1000 -> 0 | X15: =H15*H$24*1000 -> 19613.553 | Y15: =SUM(S15:X15) -> 107836.68 | Z15: =-$H$115 -> 0 | AA15: =SUM(Y15:Z15) -> 107836.68 | AB15: MLAB01 | AC15: hr | AD15: =ROUND((S15/G$116)+(T15/G$116)+(U15/G$116)+(V15/G$116)+(W15/G$116)+(X15/G$116),0) -> #DIV/0! | AE15: =Y15/AD15 -> #DIV/0! | AF15: =Y15/$AF$24/1000 -> 0.0075728003 | AG15: 0.007650221 | AH15: =IF($AF$21<$AG$21,AF15,IF($AF$20<$AG$20,AF15,IF(AND($AF$20>$AG$20,$AF$12<$AG$12),($AG$20+($AG$12-$AF$12))/$AF$20*AF15,AF15/$AF$20*$AG$20))) -> 0.0075728003 | AI15: =AH15*$Y$24*1000 -> 107836.68 | AJ15: =AI15/AD15 -> #DIV/0! | AK15: =Y15-AI15 -> 0 | AL15: =ROUND(S15/$G$116,0) -> #DIV/0! | AM15: =ROUND(T15/$G$116,0) -> #DIV/0! | AN15: =ROUND(U15/$G$116,0) -> #DIV/0! | AO15: =ROUND(V15/$G$116,0)-1 -> #DIV/0! | AP15: =ROUND(W15/$G$116,0) -> #DIV/0! | AQ15: =ROUND(X15/$G$116,0) -> #DIV/0! | AR15: =IF($B$24<>0,ROUND(AL15/B$24,3),0) -> #DIV/0! | AS15: =ROUND(AM15/B$47,3) -> #DIV/0! | AT15: =IF(E$47<>0,ROUND(AN15/E$47,3),0) -> 0 | AU15: =IF(E$24<>0,ROUND(AO15/E$24,3),0) -> #DIV/0! | AV15: =IF(H$47<>0,ROUND(AP15/H$47,3),0) -> 0 | AW15: =IF(H$24<>0,ROUND(AQ15/H$24,3),0) -> #DIV/0! | AX15: =AJ15*10000 -> #DIV/0!
A16: Indirect Payroll Costs (Benefits) | B16: =IF(B24<>0,$F$115/$B$49/1000,0) -> 0.0077923603 | D16: 0 | E16: =IF(E24<>0,$F$115/$B$49/1000,0) -> 0.0077923603 | F16: 0.01706523 | G16: 0.013928937 | H16: =IF($H$24<>0,$F$115/$B$49/1000,0) -> 0.0077923603 | J16: 0 | S16: =B16*B$24*1000 -> 13636.63 | T16: =B39*B$47*1000 -> 27273.261 | U16: =E39*E$47*1000 -> 0 | V16: =E16*E$24*1000 -> 49871.106 | W16: =H39*H$47*1000 -> 0 | X16: =H16*H$24*1000 -> 20182.213 | Y16: =SUM(S16:X16) -> 110963.21 | Z16: =-$D$122 -> 0 | AA16: =SUM(Y16:Z16) -> 110963.21 | AB16: IPC01 | AC16: hr | AD16: =ROUND((S16/C$123)+(T16/C$123)+(U16/C$123)+(V16/C$123)+(W16/C$123)+(X16/C$123),0) -> #DIV/0! | AE16: =Y16/AD16 -> #DIV/0! | AF16: =Y16/$AF$24/1000 -> 0.0077923603 | AG16: 0.0088563301 | AH16: =IF($AF$21<$AG$21,AF16,IF($AF$20<$AG$20,AF16,IF(AND($AF$20>$AG$20,$AF$12<$AG$12),($AG$20+($AG$12-$AF$12))/$AF$20*AF16,AF16/$AF$20*$AG$20))) -> 0.0077923603 | AI16: =AH16*$Y$24*1000 -> 110963.21 | AJ16: =AI16/AD16 -> #DIV/0! | AK16: =Y16-AI16 -> 0 | AL16: =ROUND(S16/$C123,0) -> #DIV/0! | AM16: =ROUND(T16/$C123,0) -> #DIV/0! | AN16: =ROUND(U16/$C123,0) -> #DIV/0! | AO16: =ROUND(V16/$C123,0) -> #DIV/0! | AP16: =ROUND(W16/$C123,0) -> #DIV/0! | AQ16: =ROUND(X16/$C123,0) -> #DIV/0! | AR16: =IF($B$24<>0,ROUND(AL16/B$24,3),0) -> #DIV/0! | AS16: =ROUND(AM16/B$47,3) -> #DIV/0! | AT16: =IF(E$47<>0,ROUND(AN16/E$47,3),0) -> 0 | AU16: =IF(E$24<>0,ROUND(AO16/E$24,3),0) -> #DIV/0! | AV16: =IF(H$47<>0,ROUND(AP16/H$47,3),0) -> 0 | AW16: =IF(H$24<>0,ROUND(AQ16/H$24,3),0) -> #DIV/0! | AX16: =AJ16*10000 -> #DIV/0!
A17: Supervision | B17: =IF($B$24<>0,$F$114/$B$49/1000,0) -> 0.00050238764 | D17: 0 | E17: =IF(E24<>0,$F$114/$B$49/1000,0) -> 0.00050238764 | F17: 0.0045810516 | G17: 0.0015771316 | H17: =IF($H$24<>0,$F$114/$B$49/1000,0) -> 0.00050238764 | J17: 0 | S17: =B17*B$24*1000 -> 879.17837 | T17: =B40*B$47*1000 -> 1758.3567 | U17: =E40*E$47*1000 -> 0 | V17: =E17*E$24*1000 -> 3215.2809 | W17: =H40*H$47*1000 -> 0 | X17: =H17*H$24*1000 -> 1301.184 | Y17: =SUM(S17:X17) -> 7154 | Z17: =C176/($C$184+$C$185)*$C$185 -> 0 | AA17: =SUM(Y17:Z17) -> 7154 | AB17: SUP01 | AC17: lb | AD17: =ROUND((S17/F$176)+(T17/F$176)+(U17/F$176)+(V17/F$176)+(W17/F$176)+(X17/F$176),0) -> #DIV/0! | AE17: =Y17/AD17 -> #DIV/0! | AF17: =Y17/$AF$24/1000 -> 0.00050238764 | AG17: 0.0021273119 | AH17: =IF($AF$21<$AG$21,AF17,IF($AF$20<$AG$20,AF17,IF(AND($AF$20>$AG$20,$AF$12<$AG$12),($AG$20+($AG$12-$AF$12))/$AF$20*AF17,AF17/$AF$20*$AG$20))) -> 0.00050238764 | AI17: =AH17*$Y$24*1000 -> 7154 | AJ17: =AI17/AD17 -> #DIV/0! | AK17: =Y17-AI17 -> 0 | AL17: =S17/$AE17 -> #DIV/0! | AM17: =T17/$AE17 -> #DIV/0! | AN17: =U17/$AE17 -> #DIV/0! | AO17: =V17/$AE17 -> #DIV/0! | AP17: =W17/$AE17 -> #DIV/0! | AQ17: =X17/$AE17 -> #DIV/0! | AR17: =IF($B$24<>0,ROUND(AL17/B$24,3),0) -> #DIV/0! | AS17: =ROUND(AM17/B$47,3) -> #DIV/0! | AT17: =IF(E$47<>0,ROUND(AN17/E$47,3),0) -> 0 | AU17: =IF(E$24<>0,ROUND(AO17/E$24,3),0) -> #DIV/0! | AV17: =IF(H$47<>0,ROUND(AP17/H$47,3),0) -> 0 | AW17: =IF(H$24<>0,ROUND(AQ17/H$24,3),0) -> #DIV/0! | AX17: =AJ17*10000 -> #DIV/0!
A18: Depreciation | B18: =IF($B$24<>0,$B$178/$B$49/1000,0) -> 0.0018168539 | D18: 0 | E18: =IF(E24<>0,$B$178/$B$49/1000,0) -> 0.0018168539 | F18: 0.0038559807 | G18: 0.0016578947 | H18: =IF($H$24<>0,$B$178/$B$49/1000,0) -> 0.0018168539 | J18: 0 | S18: =B18*B$24*1000 -> 3179.4944 | T18: =B41*B$47*1000 -> 6358.9888 | U18: =E41*E$47*1000 -> 0 | V18: =E18*E$24*1000 -> 11627.865 | W18: =H41*H$47*1000 -> 0 | X18: =H18*H$24*1000 -> 4705.6517 | Y18: =SUM(S18:X18) -> 25872 | Z18: =C178/($C$184+$C$185)*$C$185 -> 0 | AA18: =SUM(Y18:Z18) -> 25872 | AB18: DEP01 | AC18: lb | AD18: =ROUND((S18/F$178)+(T18/F$178)+(U18/F$178)+(V18/F$178)+(W18/F$178)+(X18/F$178),0) -> 1186667 | AE18: =Y18/AD18 -> 0.021802241 | AF18: =Y18/$AF$24/1000 -> 0.0018168539 | AG18: 0.032747211 | AH18: =IF($AF$21<$AG$21,AF18,IF($AF$20<$AG$20,AF18,IF(AND($AF$20>$AG$20,$AF$12<$AG$12),($AG$20+($AG$12-$AF$12))/$AF$20*AF18,AF18/$AF$20*$AG$20))) -> 0.0018168539 | AI18: =AH18*$Y$24*1000 -> 25872 | AJ18: =AI18/AD18 -> 0.021802241 | AK18: =Y18-AI18 -> 0 | AL18: =S18/$AE18 -> 145833.37 | AM18: =T18/$AE18 -> 291666.75 | AN18: =U18/$AE18 -> 0 | AO18: =V18/$AE18 -> 533333.48 | AP18: =W18/$AE18 -> 0 | AQ18: =X18/$AE18 -> 215833.39 | AR18: =IF($B$24<>0,ROUND(AL18/B$24,3),0) -> 83.333 | AS18: =ROUND(AM18/B$47,3) -> 83.333 | AT18: =IF(E$47<>0,ROUND(AN18/E$47,3),0) -> 0 | AU18: =IF(E$24<>0,ROUND(AO18/E$24,3),0) -> 83.333 | AV18: =IF(H$47<>0,ROUND(AP18/H$47,3),0) -> 0 | AW18: =IF(H$24<>0,ROUND(AQ18/H$24,3),0) -> 83.333 | AX18: =AJ18*10000 -> 218.02241
A19: Insurance & Taxes | B19: =IF($B$24<>0,$B$177/$B$49/1000,0) -> 0.0030813202 | D19: 0 | E19: =IF(E24<>0,$B$177/B49/1000,0) -> 0.0030813202 | F19: 0.010801566 | G19: 0.0058026316 | H19: =IF($H$24<>0,$B$177/$B$49/1000,0) -> 0.0030813202 | J19: 0 | S19: =B19*B$24*1000 -> 5392.3104 | T19: =B42*B$47*1000 -> 10784.621 | U19: =E42*E$47*1000 -> 0 | V19: =E19*E$24*1000 -> 19720.449 | W19: =H42*H$47*1000 -> 0 | X19: =H19*H$24*1000 -> 7980.6194 | Y19: =SUM(S19:X19) -> 43878 | Z19: =C177/($C$184+$C$185)*$C$185 -> 0 | AA19: =SUM(Y19:Z19) -> 43878 | AB19: INS01 | AC19: lb | AD19: =ROUND((S19/F$177)+(T19/F$177)+(U19/F$177)+(V19/F$177)+(W19/F$177)+(X19/F$177),0) -> 1186667 | AE19: =Y19/AD19 -> 0.036975832 | AF19: =Y19/$AF$24/1000 -> 0.0030813202 | AG19: 0.0073609622 | AH19: =IF($AF$21<$AG$21,AF19,IF($AF$20<$AG$20,AF19,IF(AND($AF$20>$AG$20,$AF$12<$AG$12),($AG$20+($AG$12-$AF$12))/$AF$20*AF19,AF19/$AF$20*$AG$20))) -> 0.0030813202 | AI19: =AH19*$Y$24*1000 -> 43878 | AJ19: =AI19/AD19 -> 0.036975832 | AK19: =Y19-AI19 -> 0 | AL19: =S19/$AE19 -> 145833.37 | AM19: =T19/$AE19 -> 291666.75 | AN19: =U19/$AE19 -> 0 | AO19: =V19/$AE19 -> 533333.48 | AP19: =W19/$AE19 -> 0 | AQ19: =X19/$AE19 -> 215833.39 | AR19: =IF($B$24<>0,ROUND(AL19/B$24,3),0) -> 83.333 | AS19: =ROUND(AM19/B$47,3) -> 83.333 | AT19: =IF(E$47<>0,ROUND(AN19/E$47,3),0) -> 0 | AU19: =IF(E$24<>0,ROUND(AO19/E$24,3),0) -> 83.333 | AV19: =IF(H$47<>0,ROUND(AP19/H$47,3),0) -> 0 | AW19: =IF(H$24<>0,ROUND(AQ19/H$24,3),0) -> 83.333 | AX19: =AJ19*10000 -> 369.75832
A20: Total Fixed Costs | B20: =SUM(B14:B19) -> 0.038665069 | C20: =SUM(C14:C19) -> 0 | D20: =SUM(D14:D19) -> 0 | E20: =SUM(E14:E19) -> 0.038665069 | F20: =SUM(F14:F19) -> 0.11152537 | G20: =SUM(G14:G19) -> 0.058371315 | H20: =SUM(H14:H19) -> 0.038665069 | I20: =SUM(I14:I19) -> 0 | J20: =SUM(J14:J19) -> 0 | S20: =SUM(S14:S19) -> 67663.87 | T20: =SUM(T14:T19) -> 135327.74 | U20: =SUM(U14:U19) -> 0 | V20: =SUM(V14:V19) -> 247456.44 | W20: =SUM(W14:W19) -> 0 | X20: =SUM(X14:X19) -> 100142.53 | Y20: =SUM(Y14:Y19) -> 550590.58 | Z20: =SUM(Z14:Z19) -> 0 | AA20: =SUM(AA14:AA19) -> 550590.58 | AF20: =SUM(AF14:AF19) -> 0.038665069 | AG20: =SUM(AG14:AG19) -> 0.07023059 | AH20: =SUM(AH14:AH19) -> 0.038665069 | AI20: =SUM(AI14:AI19) -> 550590.58 | AK20: =SUM(AK14:AK19) -> 0
A21: Excess Costs | C21: -0.0273 | F21: -0.050457361 | S21: =S12+S20 -> 300436.03 | T21: =T12+T20 -> 484434.2 | U21: =U12+U20 -> 0 | V21: =V12+V20 -> 1131573.3 | W21: =W12+W20 -> 0 | X21: =X12+X20 -> 229992.15 | Y21: =Y12+Y20 -> 2146435.7 | Z21: =Z12+Z20 -> 0 | AA21: =AA12+AA20 -> 2146435.7 | AB21: CCtr Total | AF21: =AF12+AF20 -> 0.15073284 | AG21: =AG12+AG20 -> 0.15165505 | AH21: =AH12+AH20 -> 0.15073284 | AI21: =AI12+AI20 -> 2146435.7 | AK21: =AK12+AK20 -> 0
A22: TOTAL COSTS PER POUND | B22: =B12+B20 -> 0.28330977 | C22: =+C20+C21+C12 -> -0.0273 | D22: =D12+D20 -> 0 | E22: =E12+E20 -> 0.22642002 | F22: =F12+F20+F21 -> 0.36638748 | G22: =G12+G20 -> 0.17357627 | H22: =H12+H20 -> 0.26666777 | I22: =I12+I20 -> 0 | J22: =J12+J20 -> 0 | S22: =IF(B24<>0,ROUND(S21/(B24*1000),5),0) -> 0.17168 | T22: =IF(B47<>0,ROUND(T21/(B47*1000),5),0) -> 0.13841 | U22: =IF(E47<>0,ROUND(U21/(E47*1000),5),0) -> 0 | V22: =IF(E24<>0,ROUND(V21/(E24*1000),5),0) -> 0.17681 | W22: =IF(H47<>0,ROUND(W21/(H47*1000),5),0) -> 0 | X22: =IF(H24<>0,ROUND(X21/(H24*1000),5),0) -> 0.0888 | Y22: =Y21/Y24/1000 -> 0.15073284 | Z22: 0 | AA22: =ROUND(AA21/(B49*1000),5) -> 0.15073 | AB22: Excl Matl | AI22: =AI21/AI24/1000 -> 0.15073284 | AK22: =AK21/AK24/1000 -> 0
S23: =ROUND(S22+B6,5) -> 0.31658 | T23: =ROUND(T22+B29,5) -> 0.26667 | U23: =ROUND(U22+E29,5) -> 0 | V23: =ROUND(V22+E6,5) -> 0.28482 | W23: =ROUND(W22+H29,5) -> 0 | X23: =ROUND(X22+H6,5) -> 0.21706 | Y23: =Y22+(($B$6*$B$24*1000+$B$29*$B$47*1000+$E$29*$E$47*1000+$H$6*$H$24*1000+$H$29*$H$47*1000+$E$6*$E$24*1000)/($B$49*1000)) -> 0.27193592 | Z23: 0 | AA23: =AA22+(($B$6*$B$24*1000+$B$29*$B$47*1000+$E$6*$E$24*1000+$E$29*$E$47*1000+$H$6*$H$24*1000+$H$29*$H$47*1000)/($B$49*1000)) -> 0.27193308 | AB23: Incl Matl
A24: PRODUCTION ( in 000 lbs ) | B24: =B54 -> 1750 | C24: 6211 | D24: 0 | E24: =B57 -> 6400 | F24: 3204 | G24: 51000 | H24: =B58 -> 2590 | I24: 4207 | J24: 0 | S24: =B24 -> 1750 | T24: =B47 -> 3500 | U24: =E47 -> 0 | V24: =E24 -> 6400 | W24: =H47 -> 0 | X24: =H24 -> 2590 | Y24: =SUM(S24:X24) -> 14240 | Z24: 0 | AA24: =SUM(Y24:Z24) -> 14240 | AF24: =Y24 -> 14240 | AI24: =Y24 -> 14240 | AK24: =Y24 -> 14240
B26: CP | E26: HSP | H26: Nanomite C | AS26: 0.936
B27: =B4 -> 25 Standard | C27: 23 Actual | D27: =+D4 -> 22 Standard | E27: =E4 -> 25 Standard | F27: =+C27 -> 23 Actual | G27: =+D27 -> 22 Standard | H27: =H4 -> 25 Standard | I27: 23 Actual | J27: =+J4 -> 22 Standard | AS27: 0.264
C28: (Jan-Aug) | F28: (Jan-Aug) | I28: (Jan-Aug) | AS28: 286
A29: Materials | B29: =IF($B$47<>0,$D$88,0) -> 0.128258 | C29: 0.1396 | D29: 0.06037434 | E29: =IF(E47<>0,$D$88,0) -> 0 | F29: 0.0865 | G29: 0 | H29: =IF(H47<>0,$L$80,0) -> 0 | I29: 0.0792 | J29: 0.02 | AS29: 8000
A30: Electricity | B30: =IF(B47<>0,$D$151,0) -> 0.033069 | C30: 0.0273 | D30: 0.018883379 | E30: =IF(E47<>0,$G$151,0) -> 0 | F30: 0.0294 | G30: 0 | H30: =IF(H47<>0,$J$151,0) -> 0 | I30: 0.0124 | J30: 0.0027366213 | AS30: 1.2
A31: Gas | B31: =IF(B47<>0,$D$152,0) -> 0.04 | C31: 0.0379 | D31: 0.04184 | E31: =IF(E47<>0,$G$152,0) -> 0 | F31: 0.0465 | G31: 0 | H31: =IF(H47<>0,$J$152,0) -> 0 | I31: 0 | J31: 0
A32: R&M Supplies and Service | B32: =IF(B47<>0,$H$159,0) -> 0.020856742 | C32: 0.0358 | D32: 0.022368421 | E32: =IF(E47<>0,$H$159,0) -> 0 | F32: 0.0304 | G32: 0 | H32: =IF(H47<>0,$H$159,0) -> 0 | I32: 0.0164 | J32: 0.022368421
A33: Manufacturing Supplies | B33: =IF(B47<>0,$H$163,0) -> 0.0011841292 | C33: 0.0006 | D33: 0.00065789474 | E33: =IF(E47<>0,$H$163,0) -> 0 | F33: 0.002 | G33: 0 | H33: =IF(H47<>0,$H$163,0) -> 0 | I33: 0.0014 | J33: 0.00065789474
A34: Other variable | B34: =IF($B$47<>0,$H$166,0) -> 0.0046348315 | C34: 0.0101 | D34: 0.0046052632 | E34: =IF(E47<>0,$H$166,0) -> 0 | F34: 0.0118 | G34: 0 | H34: =IF(H47<>0,$H$166,0) -> 0 | I34: 0.0108 | J34: 0.0046052632
A35: Total Variable Costs | B35: =SUM(B29:B34) -> 0.2280027 | C35: =SUM(C29:C34) -> 0.2513 | D35: =SUM(D29:D34) -> 0.1487293 | E35: =SUM(E29:E34) -> 0 | F35: =SUM(F29:F34) -> 0.2066 | G35: =SUM(G29:G34) -> 0 | H35: =SUM(H29:H34) -> 0 | I35: =SUM(I29:I34) -> 0.1202 | J35: =SUM(J29:J34) -> 0.0503682
A37: Production Labor | B37: =IF(B47<>0,$F$112/$B$49/1000,0) -> 0.017899346 | C37: 0.0445 | D37: 0.02638428 | E37: =IF(E47<>0,$F$112/$B$49/1000,0) -> 0 | F37: 0.0483 | G37: 0 | H37: =IF(H47<>0,$F$112/$B$49/1000,0) -> 0 | I37: 0.0451 | J37: 0.02638428
A38: Repairs & Maintenance Labor | B38: =IF(B47<>0,$F$113/$B$49/1000,0) -> 0.0075728003 | C38: 0.015 | D38: 0.00902044 | E38: =IF(E47<>0,$F$113/$B$49/1000,0) -> 0 | F38: 0.0144 | G38: 0 | H38: =IF(H47<>0,$F$113/$B$49/1000,0) -> 0 | I38: 0.0156 | J38: 0.00902044
A39: Indirect Payroll Costs (Benefits) | B39: =IF(B47<>0,$F$115/$B$49/1000,0) -> 0.0077923603 | C39: 0.0194 | D39: 0.013928937 | E39: =IF(E47<>0,$F$115/$B$49/1000,0) -> 0 | F39: 0.0196 | G39: 0 | H39: =IF(H47<>0,$F$115/$B$49/1000,0) -> 0 | I39: 0.0285 | J39: 0.013928937
A40: Supervision | B40: =IF($B$47<>0,$F$114/$B$49/1000,0) -> 0.00050238764 | C40: 0.0018 | D40: 0.0015771316 | E40: =IF(E47<>0,$F$114/$B$49/1000,0) -> 0 | F40: 0.0014 | G40: 0 | H40: =IF(H47<>0,$F$114/$B$49/1000,0) -> 0 | I40: 0.0022 | J40: 0.0015771316
A41: Depreciation | B41: =IF(B47<>0,$B$178/$B$49/1000,0) -> 0.0018168539 | C41: 0.0043 | D41: 0.0016578947 | E41: =IF(E47<>0,$B$178/$B$49/1000,0) -> 0 | F41: 0.0042 | G41: 0 | H41: =IF(H47<>0,$B$178/$B$49/1000,0) -> 0 | I41: 0.0067 | J41: 0.0016578947
A42: Insurance & Taxes | B42: =IF(B47<>0,$B$177/B49/1000,0) -> 0.0030813202 | C42: 0.0093 | D42: 0.0058026316 | E42: =IF(E47<>0,$B$177/B49/1000,0) -> 0 | F42: 0.0098 | G42: 0 | H42: =IF(H47<>0,$B$177/$B$49/1000,0) -> 0 | I42: 0.014 | J42: 0.0058026316
A43: Total Fixed Costs | B43: =SUM(B37:B42) -> 0.038665069 | C43: =SUM(C37:C42) -> 0.0943 | D43: =SUM(D37:D42) -> 0.058371315 | E43: =SUM(E37:E42) -> 0 | F43: =SUM(F37:F42) -> 0.0977 | G43: =SUM(G37:G42) -> 0 | H43: =SUM(H37:H42) -> 0 | I43: =SUM(I37:I42) -> 0.1121 | J43: =SUM(J37:J42) -> 0.058371315
A44: Excess Costs
A45: TOTAL COSTS PER POUND | B45: =B35+B43 -> 0.26666777 | C45: =C35+C43+C44 -> 0.3456 | D45: =D35+D43 -> 0.20710061 | E45: =E35+E43 -> 0 | F45: =F35+F43+F44 -> 0.3043 | G45: 0 | H45: =H35+H43 -> 0 | I45: =I35+I43+I44 -> 0.2323 | J45: =+J35+J43 -> 0.10873952
A47: PRODUCTION ( in 000 lbs ) | B47: =B55 -> 3500 | C47: 13494 | D47: 22600 | E47: =B56 -> 0 | F47: 1391 | G47: 0 | H47: =B59 -> 0 | I47: 6147 | J47: 2400
A49: TOTAL PLANT PRODUCTION ( in 000 lbs) | B49: =B24+E24+H24+B47+E47+H47 -> 14240 | C49: =C24+F24+I24+C47+F47+I47 -> 34654 | D49: 76000
A51: Variable Costs - Material | B51: Purchase Price/lb * Yield Factor * Scrap Factor * Mix = Std. Cost Contribution
A53: Production Plan: | B53: Pounds (000) | C53: Product Split | D53: Days
A54: HT (foundry) | B54: ='2025 Summary'!$C$7 -> 1750 | C54: =B54/$B$60 -> 0.12289326
A55: CarboProp | B55: ='2025 Summary'!D$7 -> 3500 | C55: =B55/$B$60 -> 0.24578652 | D55: =B55/180/2 -> 9.7222222
A56: CarboHSP | B56: ='2025 Summary'!E$7 -> 0 | C56: =B56/$B$60 -> 0 | D56: =B56/200/2 -> 0
A57: Bauxite Pellets | B57: ='2025 Summary'!$F$7 -> 6400 | C57: =B57/$B$60 -> 0.4494382
A58: ID (foundry) | B58: ='2025 Summary'!$G$7 -> 2590 | C58: =B58/$B$60 -> 0.18188202
A59: Nanomite C | B59: ='2025 Summary'!$H$7 -> 0 | C59: =B59/$B$60 -> 0 | D59: =B59/200 -> 0
A60: Total | B60: =SUM(B54:B59) -> 14240 | C60: =B60/$B$60 -> 1
AB61: NEED TO VERIFY ALL FORMULAS IN THE SECTION BELOW: Done
C62: Yield Factor | G62: Mix %
A63: Local Kaolin | B63: Price ($/Ton) | C63: CG | D63: CP | E63: HSP | F63: CL | G63: Cristobalite | H63: CG | I63: CP / ID | J63: HSP | K63: CL | L63: Cristobalite | AE63: price/1000/lb | AM63: Mix%
A64: Arcilla (local kaolin) 30012 | B64: =11.75*2 -> 23.5 | C64: =$C$76*H64 -> 0.2668 | D64: =$C$84*I64 -> 0.056 | E64: =$G$84*J64 -> 0 | F64: =$K$84*K64 -> 0 | G64: =$K$84*L64 -> 0 | H64: 0.667 | I64: 0.14 | J64: 0 | K64: 1 | L64: 0 | AB64: 30012/U103 | AE64: =B64/2000*1000 -> 11.75 | AM64: =$AM$76*I64 -> 56 | AO64: =$AO$84*K64 -> 0
A65: Dixon (local kaolin) | B65: 0 | C65: =$C$76*H65 -> 0 | D65: =$C$84*I65 -> 0 | E65: =$G$84*J65 -> 0 | F65: =$K$84*K65 -> 0 | G65: =$K$84*L65 -> 0 | H65: 0 | I65: 0 | J65: 0 | K65: 0 | L65: 0 | AB65: 30012/U103 | AE65: =B65/2000*1000 -> 0 | AM65: =$AM$76*I65 -> 0 | AO65: =$AO$85*J65 -> 0
C66: =SUM(C64:C65) -> 0.2668 | D66: =SUM(D64:D65) -> 0.056 | E66: =SUM(E64:E65) -> 0 | F66: =SUM(F64:F65) -> 0 | G66: =SUM(G64:G65) -> 0
A67: Bauxite: | AO67: =$AO$85*J66 -> 0
A68: MRN (30006) Lord Allen & ECT | B68: =60.33+8+44 -> 112.33 | C68: =$C$77*H68 -> 0.1837 | D68: =$C$85*I68 -> 0.98 | E68: =$G$85*J68 -> 1.8 | F68: =$K$85*K68 -> 0 | G68: =$K$85*L68 -> 0 | H68: 0.167 | I68: 0.56 | J68: 1 | K68: 0 | L68: 0 | AB68: 30006/U103 | AE68: =B68/2000*1000 -> 56.165 | AM68: =$AM$77*I68 -> 980 | AN68: =$AN$85*I68 -> 980 | AO68: =$AO$85*J68 -> 1000
A69: Rusal (30008) Lord Allen & ECT | B69: =56.29*2 -> 112.58 | C69: =$C$77*H69 -> 0 | D69: =$C$85*I69 -> 0 | E69: =$G$85*J69 -> 0 | F69: =$K$85*K69 -> 0 | G69: =$K$85*L69 -> 0 | H69: 0 | I69: 0 | J69: 0 | K69: 0 | L69: 0 | AB69: 30008/U103 | AE69: =B69/2000*1000 -> 56.29 | AM69: =$AM$77*I69 -> 0 | AN69: =$AN$85*I69 -> 0 | AO69: =$AO$85*J69 -> 0
A70: Bosai Chem Grade (30002) | B70: 160 | C70: 0 | D70: =$C$85*I70 -> 0 | E70: =$G$85*J70 -> 0 | F70: =$K$85*K70 -> 0 | G70: =$K$85*L70 -> 0 | H70: 0 | I70: 0 | J70: 0 | K70: 0 | L70: 0 | M70: Changed Bosai Chem Grade Price | AB70: 30003/U103 | AE70: =B70/2000*1000 -> 80 | AM70: =$AM$77*I70 -> 0 | AN70: =$AN$85*I70 -> 0
A71: First Bauxite (30440) | B71: =194+44 -> 238 | C71: =$C$77*H71 -> 0.1837 | D71: =$C$85*I71 -> 0.525 | E71: =$G$85*J71 -> 0 | F71: =$K$85*K71 -> 0 | G71: =$K$85*L71 -> 0 | H71: 0.167 | I71: 0.3 | J71: 0 | K71: 0 | L71: 0 | AB71: 30440/U103 | AE71: =B71/2000*1000 -> 119 | AM71: =$AM$77*I71 -> 525 | AN71: =$AN$85*I71 -> 525 | AO71: =$AO$85*J70 -> 0
C72: =SUM(C68:C71) -> 0.3674 | D72: =SUM(D68:D71) -> 1.505 | E72: =SUM(E68:E71) -> 1.8 | F72: =SUM(F68:F71) -> 0 | G72: =SUM(G68:G71) -> 0
B74: HT | F74: Cristobalite | J74: Nanomite | AE74: CG
B75: Price ($/lb) | C75: Yield Factor | D75: Std $ Contrib | F75: Price ($/lb) | G75: Yield Factor | H75: Std $ Contrib | J75: Price ($/lb) | K75: Yield Factor | L75: Std $ Contrib | AE75: price/1000/lb
A76: Local Kaolin | B76: 0.013 | C76: 0.4 | D76: =B76*C76 -> 0.0052 | F76: =($B$64*$L$64+$B$65*$L$65)/2000 -> 0 | G76: 0 | H76: =F76*G76 -> 0 | J76: =($B$64*$L$64+$B$65*$L$65)/2000 -> 0 | K76: 0 | L76: =J76*K76 -> 0 | AB76: 30012/U103 | AE76: =B76*1000 -> 13 | AK76: kaolin | AM76: =IF(B84<>0,D84/B84*1000,0) -> 400
A77: Bauxite | B77: =B71/2000 -> 0.119 | C77: 1.1 | D77: =B77*C77 -> 0.1309 | F77: =($B$68*$L$68+$B$69*$L$69+$B$70*$L$70+$B$71*$L$71)/2000 -> 0 | G77: 0 | H77: =F77*G77 -> 0 | J77: =($B$68*$L$68+$B$69*$L$69+$B$70*$L$70+$B$71*$L$71)/2000 -> 0 | K77: 0 | L77: =J77*K77 -> 0 | AB77: 30060/U103 | AE77: =B77*1000 -> 119 | AK77: bauxite | AM77: =IF(B85<>0,D85/B85*1000,0) -> 1750
A78: Starch (30020) | B78: 0.88 | C78: 0.01 | D78: =B78*C78 -> 0.0088 | F78: =B86 -> 0.726 | G78: 0 | H78: =F78*G78 -> 0 | K78: 0 | L78: =J78*K78 -> 0 | AB78: 30020/U103 | AE78: =B78*1000 -> 880 | AK78: starch | AM78: =IF(B86<>0,D86/B86*1000,0) -> 8
A79: Taggant | D79: 0 | G79: 0 | H79: =F79*G79 -> 0 | K79: 0 | L79: =J79*K79 -> 0
A80: Total Material Cost Per Pound | D80: =SUM(D76:D79) -> 0.1449 | H80: =SUM(H76:H79) -> 0 | L80: 0.08
B82: =B26 -> CP | F82: =E26 -> HSP | J82: Bauxite Pellets | AE82: CP/ID | AG82: CL
B83: Price ($/lb) | C83: Yield Factor | D83: Std $ Contrib | F83: Price ($/lb) | G83: Yield Factor | H83: Std $ Contrib | J83: Price ($/lb) | K83: Yield Factor | L83: Std $ Contrib | AE83: price/1000/lb | AG83: price/1000/lb
A84: Local kaolin | B84: 0.013 | C84: 0.4 | D84: =B84*C84 -> 0.0052 | F84: =($B$64*$J$64+$B$65*$J$65)/2000 -> 0 | G84: 0 | H84: =F84*G84 -> 0 | J84: =($B$64*$K$64+$B$65*$K$65)/2000 -> 0.01175 | K84: 0 | L84: =J84*K84 -> 0 | AB84: 30012/U103 | AE84: =B84*1000 -> 13 | AG84: =J84*1000 -> 11.75 | AN84: =IF(B84<>0,D84/B84*1000,0) -> 400 | AO84: =IF(J84<>0,L84/J84*1000,0) -> 0
A85: Bauxite | B85: 0.067 | C85: 1.75 | D85: =B85*C85 -> 0.11725 | F85: =($B$68*$J$68+$B$69*$J$69+$B$70*$J$70+$B$71*$J$71)/2000 -> 0.056165 | G85: 1.8 | H85: =F85*G85 -> 0.101097 | J85: =(B71/2000*0.75)+(B68/2000*0.25) -> 0.10329125 | K85: 1 | L85: =J85*K85 -> 0.10329125 | AB85: Various (see above) | AE85: =B85*1000 -> 67 | AG85: =J85*1000 -> 103.29125 | AN85: =IF(B85<>0,D85/B85*1000,0) -> 1750 | AO85: =IF(J85<>0,L85/J85*1000,0) -> 1000
A86: Starch (30020) | B86: 0.726 | C86: 0.008 | D86: =B86*C86 -> 0.005808 | F86: =B86 -> 0.726 | G86: 0.008 | H86: =F86*G86 -> 0.005808 | J86: =B86 -> 0.726 | K86: 0.0065 | L86: =J86*K86 -> 0.004719 | M86: Increased starch to 0.8% | AB86: 30020/U103 | AE86: =B86*1000 -> 726 | AG86: =J86*1000 -> 726 | AN86: =IF(B86<>0,D86/B86*1000,0) -> 8 | AO86: =IF(J86<>0,L86/J86*1000,0) -> 6.5
A87: Taggant | D87: 0 | H87: 0 | L87: 0
A88: Total Material Cost Per Pound | D88: =SUM(D84:D86) -> 0.128258 | H88: =SUM(H84:H86) -> 0.106905 | L88: =SUM(L84:L87) -> 0.10801025
A90: Variable Cost - Labor & Benefits - 12 hour shift
AE91: Nov-20 YTD
U92: =$Z$14*$AD92 -> 0 | Z92: =AA14*$AD92 -> 188917.55 | AB92: DLAB01 (s/t) | AC92: 611030 | AD92: =+AE92/AE94 -> 0.7411825 | AE92: 882400
U93: =$Z$14*$AD93 -> 0 | Z93: =AA14*$AD93 -> 65969.136 | AB93: DLAB01 (o/t) | AC93: 610210 | AD93: =+AE93/AE94 -> 0.2588175 | AE93: 308130
U94: =SUM(U92:U93) -> 0 | Z94: =SUM(Z92:Z93) -> 254886.69 | AA94: hr | AB94: DLAB01 | AC94: Total | AE94: =SUM(AE92:AE93) -> 1190530
B97: Jan | C97: Feb | D97: Mar | E97: Apr | F97: May | G97: Jun | H97: Jul
A98: Production Labor | B98: 268968.01 | C98: 288390.24 | D98: 154345.41 | E98: 13412.75 | F98: 229529.76 | G98: 274156.29 | H98: 267092.21
A99: R & M Labor | B99: 67812.91 | C99: 64354.51 | D99: 40616.39 | E99: 14950.76 | F99: 74301.16 | G99: 85619.44 | H99: 74393.95 | U99: =$Z$15*$AD99 -> 0 | Z99: =AA15*$AD99 -> 84199.625 | AB99: MLAB01 (s/t) | AC99: 611040 | AD99: =+AE99/AE102 -> 0.78080694 | AE99: 392660
A100: IPC | B100: 102162.56 | C100: 97023.8 | D100: 87771.29 | E100: 18740.91 | F100: 135347.7 | G100: 89284.14 | H100: 88862.54 | U100: =$Z$15*$AD100 -> 0 | Z100: =AA15*$AD100 -> 23637.052 | AB100: MLAB01 (o/t) | AC100: 610215 | AD100: =+AE100/AE102 -> 0.21919306 | AE100: 110230
A101: Supervision | B101: 6248.2 | C101: 7823.13 | D101: 4541.85 | E101: 10625.36 | F101: 11684.3 | G101: 7724.39 | H101: 6820.85
A102: Temp | B102: 35640 | C102: 61311 | D102: 50554 | F102: 65416 | G102: 62538 | H102: 37211 | U102: =SUM(U99:U100) -> 0 | Z102: =SUM(Z99:Z100) -> 107836.68 | AA102: hr | AB102: MLAB01 | AC102: Total | AE102: =SUM(AE99:AE100) -> 502890
A103: IPC (estimated) | B103: =B100/(B98+B99-B102+B101) -> 0.33235581 | C103: =C100/(C98+C99-C102+C101) -> 0.32421577 | D103: =D100/(D98+D99-D102+D101) -> 0.58926819 | E103: =E100/(E98+E99-E102+E101) -> 0.48067333 | F103: =F100/(F98+F99-F102+F101) -> 0.54117602 | G103: =G100/(G98+G99-G102+G101) -> 0.29277125 | H103: =H100/(H98+H99-H102+H101) -> 0.28564346
U104: =$Z$16*$AD104 -> 0 | Z104: =$AA$16*$AD104 -> 18640.665 | AB104: IPC01 (vac) | AC104: 610220 | AD104: =+AE104/AE110 -> 0.1679896 | AE104: 109692
D105: $/FTE/month | F105: $ Rolling Total | U105: =$Z$16*$AD105 -> 0 | Z105: =$AA$16*$AD105 -> 15618.686 | AB105: IPC01 (hol) | AC105: 610510 | AD105: =+AE105/AE110 -> 0.14075553 | AE105: 91909
A106: Current Production Labor | B106: 46 | D106: =(AVERAGE((B98-B102),(C98-C102),(G98-G102),(H98-H102)))/B106 -> 4901.6671 | F106: =D106*B106 -> 225476.69 | U106: =$Z$16*$AD106 -> 0 | Z106: =$AA$16*$AD106 -> 7757.5973 | AB106: IPC01 (401k) | AC106: 610600 | AD106: =+AE106/AE110 -> 0.069911435 | AE106: 45650
A107: Current R & M Labor | B107: 16 | D107: =AVERAGE($G$99:$H$99,B99:C99)/B107 -> 4565.3252 | F107: =D107*B107 -> 73045.202 | U107: =$Z$16*$AD107 -> 0 | Z107: =$AA$16*$AD107 -> 37495.28 | AB107: IPC01 (ins) | AC107: 610610 | AD107: =+AE107/AE110 -> 0.33790731 | AE107: 220643
U108: =$Z$16*$AD108 -> 0 | Z108: =$AA$16*$AD108 -> 28673.541 | AB108: IPC01 (tax) | AC108: 612000 | AD108: =+AE108/AE110 -> 0.25840584 | AE108: 168731
A109: Future Production Labor Increase | B109: 6 | D109: =D106 -> 4901.6671 | F109: =D109*B109 -> 29410.003 | U109: =$Z$16*$AD109 -> 0 | Z109: =$AA$16*$AD109 -> 2777.4407 | AB109: IPC01 (w/c) | AC109: 612100 | AD109: =+AE109/AE110 -> 0.025030285 | AE109: 16344
A110: Future R&M Labor Increase | B110: 6 | D110: =D107 -> 4565.3252 | F110: =D110*B110 -> 27391.951 | U110: =SUM(U104:U109) -> 0 | Z110: =SUM(Z104:Z109) -> 110963.21 | AA110: hr | AB110: IPC01 | AC110: Total | AE110: =SUM(AE104:AE109) -> 652969
A112: Total Production Labor | B112: =B106+B109 -> 52 | D112: =D106 -> 4901.6671 | F112: =D112*B112 -> 254886.69
A113: Total R & M Labor | B113: =B107+B110 -> 22 | D113: =D106 -> 4901.6671 | F113: =D113*B113 -> 107836.68
...

Sheet Mar
A1: McINTYRE STANDARD 2025 | S1: COST CENTER 10001003 | AE1: Gross | AF1: Std | AG1: Abs Limit | AH1: Absorb | AI1: 10001003 | AJ1: Absorbed | AK1: 10001003 | AX1: Abs Cost
S2: CG | T2: CP | U2: HSP | V2: CL | W2: Nanomite C | X2: NRT | Y2: To Production | Z2: Idle Plant | AA2: TOTAL | AB2: Activity / Material | AC2: UOM | AD2: Ttl Unit Qty | AE2: Unit Cost | AF2: Cost/lb | AG2: Cost/lb | AH2: Cost/lb | AI2: Absorption | AJ2: Unit Cost | AK2: Underabs | AL2: EP Unit Qty | AM2: CP Unit Qty | AN2: HSP Unit Qty | AO2: CL Unit Qty | AP2: Nano C Qty | AQ2: NRT Unit Qty | AR2: EP Units/1000lb | AS2: CP Units/1000lb | AT2: HSP Units/1000lb | AU2: CL Units/1000lb | AV2: Nano C Units/1000lb | AW2: NRT Units/1000lb | AX2: per 10000
B3: HT | E3: Bauxite Pellets | H3: ID
B4: 25 Standard | C4: 23 Actual | D4: 22 Standard | E4: =B4 -> 25 Standard | F4: 23 Actual | G4: =+D4 -> 22 Standard | H4: =B4 -> 25 Standard | I4: 23 Actual | J4: =+D4 -> 22 Standard
F5: (Jan-Aug)
A6: Materials | B6: =IF($B$24<>0,$D$80,0) -> 0 | D6: 0 | E6: =IF(E24<>0,$L$88,0) -> 0.10801025 | F6: 0.071053254 | G6: 0.02685 | H6: =IF($H$24<>0,$D$88,0) -> 0.128258 | J6: 0
A7: Electricity | B7: =IF($B$24<>0,$D$151,0) -> 0 | D7: 0 | E7: =IF(E24<>0,$D$151,0) -> 0.033069 | F7: 0.03392679 | G7: 0.018883379 | H7: =IF(H24<>0,$D$151,0) -> 0.033069 | J7: 0 | S7: =$C145*$B$24*1000*$B145 -> 0 | T7: =$C151*$B$47*1000*$B151 -> 99207 | U7: =$F151*$E$47*1000*$E151 -> 0 | V7: =$F145*$E$24*1000*$E145 -> 339341.3 | W7: =$I151*$H$47*1000*$H151 -> 0 | X7: =$I145*$H$24*1000*$H145 -> 36227.235 | Y7: =SUM(S7:X7) -> 474775.53 | Z7: 0 | AA7: =SUM(Y7:Z7) -> 474775.53 | AB7: ELE01 | AC7: kwh | AD7: =ROUND((B145*B$24*1000)+(B151*B$47*1000)+(E145*E$24*1000)+(E151*E$47*1000)+(H145*H$24*1000)+(H151*H$47*1000),0) -> 7011432 | AE7: =Y7/AD7 -> 0.067714489 | AF7: =Y7/$AF$24/1000 -> 0.027862414 | AG7: 0.014890786 | AH7: =IF($AF$21<$AG$21,AF7,IF($AF$12<$AG$12,AF7,IF(AND($AF$12>$AG$12,$AF$20<$AG$20),($AG$12+($AG$20-$AF$20))/$AF$12*AF7,AF7/$AF$12*$AG$12))) -> 0.027862414 | AI7: =AH7*$Y$24*1000 -> 474775.53 | AJ7: =AI7/AD7 -> 0.067714489 | AK7: =Y7-AI7 -> 0 | AL7: =ROUND($B145*$B$24*1000,0) -> 0 | AM7: =ROUND($B151*$B$47*1000,0) -> 1359000 | AN7: =ROUND($E151*$E$47*1000,0) -> 0 | AO7: =ROUND($E145*$E$24*1000,0) -> 5107200 | AP7: =ROUND($H151*$H$47*1000,0) -> 0 | AQ7: =ROUND($H145*$H$24*1000,0) -> 545232 | AR7: =IF($B$24<>0,ROUND(AL7/B$24,3),0) -> 0 | AS7: =ROUND(AM7/B$47,3) -> 453 | AT7: =IF(E$47<>0,ROUND(AN7/E$47,3),0) -> 0 | AU7: =IF(F$24<>0,ROUND(AO7/F$24,3),0) -> 1594.007 | AV7: =IF(H$47<>0,ROUND(AP7/H$47,3),0) -> 0 | AW7: =IF(H$24<>0,ROUND(AQ7/H$24,3),0) -> 122.8 | AX7: =AJ7*10000 -> 677.14489
A8: Gas | B8: =IF($B$24<>0,$D$152,0) -> 0 | D8: 0 | E8: =IF(E24<>0,$D$152,0)/2 -> 0.02 | F8: 0.14600441 | G8: 0.04184 | H8: =IF(H24<>0,$D$152,0) -> 0.04 | J8: 0 | S8: =$C146*$B$24*1000*$B146 -> 0 | T8: =$C152*$B$47*1000*$B152 -> 120000 | U8: =$F152*$E$47*1000*$E152 -> 0 | V8: =$F146*$E$24*1000*$E146 -> 691200 | W8: =$I152*$H$47*1000*$H152 -> 0 | X8: =$I146*$H$24*1000*$H146 -> 67932 | Y8: =SUM(S8:X8) -> 879132 | Z8: 0 | AA8: =SUM(Y8:Z8) -> 879132 | AB8: GAS01 | AC8: mbtu | AD8: =ROUND((B146*B$24*1000*1000)+(B152*B$47*1000*1000)+(E146*E$24*1000*1000)+(E152*E$47*1000*1000)+(H146*H$24*1000*1000)+(H152*H$47*1000*1000),0) -> 114348000 | AE8: =Y8/AD8 -> 0.0076882149 | AF8: =Y8/$AF$24/1000 -> 0.051592254 | AG8: 0.042004912 | AH8: =IF($AF$21<$AG$21,AF8,IF($AF$12<$AG$12,AF8,IF(AND($AF$12>$AG$12,$AF$20<$AG$20),($AG$12+($AG$20-$AF$20))/$AF$12*AF8,AF8/$AF$12*$AG$12))) -> 0.051592254 | AI8: =AH8*$Y$24*1000 -> 879132 | AJ8: =AI8/AD8 -> 0.0076882149 | AK8: =Y8-AI8 -> 0 | AL8: =ROUND($B146*$B$24*1000*1000,0) -> 0 | AM8: =ROUND($B152*$B$47*1000*1000,0) -> 30000000 | AN8: =ROUND($E152*$E$47*1000*1000,0) -> 0 | AO8: =ROUND($E146*$E$24*1000*1000,0) -> 76800000 | AP8: =ROUND($H152*$H$47*1000*1000,0) -> 0 | AQ8: =ROUND($H146*$H$24*1000*1000,0) -> 7548000 | AR8: =IF($B$24<>0,ROUND(AL8/B$24,3),0) -> 0 | AS8: =ROUND(AM8/B$47,3) -> 10000 | AT8: =IF(E$47<>0,ROUND(AN8/E$47,3),0) -> 0 | AU8: =IF(E$24<>0,ROUND(AO8/E$24,3),0) -> 8000 | AV8: =IF(H$47<>0,ROUND(AP8/H$47,3),0) -> 0 | AW8: =IF(H$24<>0,ROUND(AQ8/H$24,3),0) -> 1700 | AX8: =AJ8*10000 -> 76.882149
A9: R&M Supplies and Service | B9: =IF($B$24<>0,$H$159,0) -> 0 | D9: 0 | E9: =IF(E24<>0,$H$159,0) -> 0.017429577 | F9: 0.043366417 | G9: 0.022368421 | H9: =IF(H24<>0,$H$159,0) -> 0.017429577 | J9: 0 | S9: =B9*B$24*1000 -> 0 | T9: =B32*B$47*1000 -> 52288.732 | U9: =E32*E$47*1000 -> 0 | V9: =E9*E$24*1000 -> 167323.94 | W9: =H32*H$47*1000 -> 0 | X9: =H9*H$24*1000 -> 77387.324 | Y9: =SUM(S9:X9) -> 297000 | Z9: 0 | AA9: =SUM(Y9:Z9) -> 297000 | AB9: RMS01 | AC9: lb | AD9: =ROUND((S9/H$159)+(T9/H$159)+(U9/H$159)+(V9/H$159)+(W9/H$159)+(X9/H$159),0) -> 17040000 | AE9: =Y9/AD9 -> 0.017429577 | AF9: =Y9/$AF$24/1000 -> 0.017429577 | AG9: 0.019544347 | AH9: =IF($AF$21<$AG$21,AF9,IF($AF$12<$AG$12,AF9,IF(AND($AF$12>$AG$12,$AF$20<$AG$20),($AG$12+($AG$20-$AF$20))/$AF$12*AF9,AF9/$AF$12*$AG$12))) -> 0.017429577 | AI9: =AH9*$Y$24*1000 -> 297000 | AJ9: =AI9/AD9 -> 0.017429577 | AK9: =Y9-AI9 -> 0 | AL9: =S9/$AE9 -> 0 | AM9: =T9/$AE9 -> 3000000 | AN9: =U9/$AE9 -> 0 | AO9: =V9/$AE9 -> 9600000 | AP9: =W9/$AE9 -> 0 | AQ9: =X9/$AE9 -> 4440000 | AR9: =IF($B$24<>0,ROUND(AL9/B$24,3),0) -> 0 | AS9: =ROUND(AM9/B$47,3) -> 1000 | AT9: =IF(E$47<>0,ROUND(AN9/E$47,3),0) -> 0 | AU9: =IF(E$24<>0,ROUND(AO9/E$24,3),0) -> 1000 | AV9: =IF(H$47<>0,ROUND(AP9/H$47,3),0) -> 0 | AW9: =IF(H$24<>0,ROUND(AQ9/H$24,3),0) -> 1000 | AX9: =AJ9*10000 -> 174.29577
A10: Manufacturing Supplies | B10: =IF($B$24<>0,$H$163,0) -> 0 | D10: 0 | E10: =IF(E24<>0,$H$163,0) -> 0.00098955399 | F10: 0.00073336258 | G10: 0.00065789474 | H10: =IF($H$24<>0,$H$163,0) -> 0.00098955399 | J10: 0 | S10: =B10*B$24*1000 -> 0 | T10: =B33*B$47*1000 -> 2968.662 | U10: =E33*E$47*1000 -> 0 | V10: =E10*E$24*1000 -> 9499.7183 | W10: =H33*H$47*1000 -> 0 | X10: =H10*H$24*1000 -> 4393.6197 | Y10: =SUM(S10:X10) -> 16862 | Z10: 0 | AA10: =SUM(Y10:Z10) -> 16862 | AB10: MFG01 | AC10: lb | AD10: =ROUND((S10/H$163)+(T10/H$163)+(U10/H$163)+(V10/H$163)+(W10/H$163)+(X10/H$163),0) -> 17040000 | AE10: =Y10/AD10 -> 0.00098955399 | AF10: =Y10/$AF$24/1000 -> 0.00098955399 | AG10: 0.0012510769 | AH10: =IF($AF$21<$AG$21,AF10,IF($AF$12<$AG$12,AF10,IF(AND($AF$12>$AG$12,$AF$20<$AG$20),($AG$12+($AG$20-$AF$20))/$AF$12*AF10,AF10/$AF$12*$AG$12))) -> 0.00098955399 | AI10: =AH10*$Y$24*1000 -> 16862 | AJ10: =AI10/AD10 -> 0.00098955399 | AK10: =Y10-AI10 -> 0 | AL10: =S10/$AE10 -> 0 | AM10: =T10/$AE10 -> 3000000 | AN10: =U10/$AE10 -> 0 | AO10: =V10/$AE10 -> 9600000 | AP10: =W10/$AE10 -> 0 | AQ10: =X10/$AE10 -> 4440000 | AR10: =IF($B$24<>0,ROUND(AL10/B$24,3),0) -> 0 | AS10: =ROUND(AM10/B$47,3) -> 1000 | AT10: =IF(E$47<>0,ROUND(AN10/E$47,3),0) -> 0 | AU10: =IF(E$24<>0,ROUND(AO10/E$24,3),0) -> 1000 | AV10: =IF(H$47<>0,ROUND(AP10/H$47,3),0) -> 0 | AW10: =IF(H$24<>0,ROUND(AQ10/H$24,3),0) -> 1000 | AX10: =AJ10*10000 -> 9.8955399
A11: Other variable | B11: =IF($B$24<>0,$H$166,0) -> 0 | D11: 0 | E11: =IF(E24<>0,$H$166,0) -> 0.0038732394 | F11: 0.010235236 | G11: 0.0046052632 | H11: =IF($H$24<>0,$H$166,0) -> 0.0038732394 | J11: 0 | S11: =B11*B$24*1000 -> 0 | T11: =B34*B$47*1000 -> 11619.718 | U11: =E34*E$47*1000 -> 0 | V11: =E11*E$24*1000 -> 37183.099 | W11: =H34*H$47*1000 -> 0 | X11: =H11*H$24*1000 -> 17197.183 | Y11: =SUM(S11:X11) -> 66000 | Z11: 0 | AA11: =SUM(Y11:Z11) -> 66000 | AB11: VAR01 | AC11: lb | AD11: =ROUND((S11/H$166)+(T11/H$166)+(U11/H$166)+(V11/H$166)+(W11/H$166)+(X11/H$166),0) -> 17040000 | AE11: =Y11/AD11 -> 0.0038732394 | AF11: =Y11/$AF$24/1000 -> 0.0038732394 | AG11: 0.0037333371 | AH11: =IF($AF$21<$AG$21,AF11,IF($AF$12<$AG$12,AF11,IF(AND($AF$12>$AG$12,$AF$20<$AG$20),($AG$12+($AG$20-$AF$20))/$AF$12*AF11,AF11/$AF$12*$AG$12))) -> 0.0038732394 | AI11: =AH11*$Y$24*1000 -> 66000 | AJ11: =AI11/AD11 -> 0.0038732394 | AK11: =Y11-AI11 -> 0 | AL11: =S11/$AE11 -> 0 | AM11: =T11/$AE11 -> 3000000 | AN11: =U11/$AE11 -> 0 | AO11: =V11/$AE11 -> 9600000 | AP11: =W11/$AE11 -> 0 | AQ11: =X11/$AE11 -> 4440000 | AR11: =IF($B$24<>0,ROUND(AL11/B$24,3),0) -> 0 | AS11: =ROUND(AM11/B$47,3) -> 1000 | AT11: =IF(E$47<>0,ROUND(AN11/E$47,3),0) -> 0 | AU11: =IF(E$24<>0,ROUND(AO11/E$24,3),0) -> 1000 | AV11: =IF(H$47<>0,ROUND(AP11/H$47,3),0) -> 0 | AW11: =IF(H$24<>0,ROUND(AQ11/H$24,3),0) -> 1000 | AX11: =AJ11*10000 -> 38.732394
A12: Total Variable Costs | B12: =SUM(B6:B11) -> 0 | D12: =SUM(D6:D11) -> 0 | E12: =SUM(E6:E11) -> 0.18337162 | F12: =SUM(F6:F11) -> 0.30531947 | G12: =SUM(G6:G11) -> 0.11520496 | H12: =SUM(H6:H11) -> 0.22361937 | J12: =SUM(J6:J11) -> 0 | S12: =SUM(S7:S11) -> 0 | T12: =SUM(T7:T11) -> 286084.11 | U12: =SUM(U7:U11) -> 0 | V12: =SUM(V7:V11) -> 1244548.1 | W12: =SUM(W7:W11) -> 0 | X12: =SUM(X7:X11) -> 203137.36 | Y12: =SUM(Y7:Y11) -> 1733769.5 | Z12: =SUM(Z7:Z11) -> 0 | AA12: =SUM(AA7:AA11) -> 1733769.5 | AF12: =SUM(AF7:AF11) -> 0.10174704 | AG12: =SUM(AG7:AG11) -> 0.081424459 | AH12: =SUM(AH7:AH11) -> 0.10174704 | AI12: =SUM(AI7:AI11) -> 1733769.5 | AK12: =SUM(AK7:AK11) -> 0
A14: Production Labor | B14: =IF($B$24<>0,$F$112/$B$49/1000,0) -> 0 | D14: 0 | E14: =IF(E24<>0,$F$112/$B$49/1000,0) -> 0.014958139 | F14: 0.055685781 | G14: 0.02638428 | H14: =IF($H$24<>0,$F$112/$B$49/1000,0) -> 0.014958139 | J14: 0 | S14: =B14*B$24*1000 -> 0 | T14: =B37*B$47*1000 -> 44874.417 | U14: =E37*E$47*1000 -> 0 | V14: =E14*E$24*1000 -> 143598.14 | W14: =H37*H$47*1000 -> 0 | X14: =H14*H$24*1000 -> 66414.138 | Y14: =SUM(S14:X14) -> 254886.69 | Z14: =-$D$115 -> 0 | AA14: =SUM(Y14:Z14) -> 254886.69 | AB14: DLAB01 | AC14: hr | AD14: =ROUND((S14/C$116)+(T14/C$116)+(U14/C$116)+(V14/C$116)+(W14/C$116)+(X14/C$116),0) -> #DIV/0! | AE14: =Y14/AD14 -> #DIV/0! | AF14: =Y14/$AF$24/1000 -> 0.014958139 | AG14: 0.011488554 | AH14: =IF($AF$21<$AG$21,AF14,IF($AF$20<$AG$20,AF14,IF(AND($AF$20>$AG$20,$AF$12<$AG$12),($AG$20+($AG$12-$AF$12))/$AF$20*AF14,AF14/$AF$20*$AG$20))) -> 0.014958139 | AI14: =AH14*$Y$24*1000 -> 254886.69 | AJ14: =AI14/AD14 -> #DIV/0! | AK14: =Y14-AI14 -> 0 | AL14: =ROUND(S14/$C116,0) -> #DIV/0! | AM14: =ROUND(T14/$C116,0) -> #DIV/0! | AN14: =ROUND(U14/$C116,0) -> #DIV/0! | AO14: =ROUND(V14/$C116,0) -> #DIV/0! | AP14: =ROUND(W14/$C116,0) -> #DIV/0! | AQ14: =ROUND(X14/$C116,0) -> #DIV/0! | AR14: =IF($B$24<>0,ROUND(AL14/B$24,3),0) -> 0 | AS14: =ROUND(AM14/B$47,3) -> #DIV/0! | AT14: =IF(E$47<>0,ROUND(AN14/E$47,3),0) -> 0 | AU14: =IF(E$24<>0,ROUND(AO14/E$24,3),0) -> #DIV/0! | AV14: =IF(H$47<>0,ROUND(AP14/H$47,3),0) -> 0 | AW14: =IF(H$24<>0,ROUND(AQ14/H$24,3),0) -> #DIV/0! | AX14: =AJ14*10000 -> #DIV/0!
A15: Repairs & Maintenance Labor | B15: =IF($B$24<>0,$F$113/$B$49/1000,0) -> 0 | D15: 0 | E15: =IF(E24<>0,$F$113/$B$49/1000,0) -> 0.0063284435 | F15: 0.019535758 | G15: 0.00902044 | H15: =IF($H$24<>0,$F$113/$B$49/1000,0) -> 0.0063284435 | J15: 0 | S15: =B15*B$24*1000 -> 0 | T15: =B38*B$47*1000 -> 18985.33 | U15: =E38*E$47*1000 -> 0 | V15: =E15*E$24*1000 -> 60753.057 | W15: =H38*H$47*1000 -> 0 | X15: =H15*H$24*1000 -> 28098.289 | Y15: =SUM(S15:X15) -> 107836.68 | Z15: =-$H$115 -> 0 | AA15: =SUM(Y15:Z15) -> 107836.68 | AB15: MLAB01 | AC15: hr | AD15: =ROUND((S15/G$116)+(T15/G$116)+(U15/G$116)+(V15/G$116)+(W15/G$116)+(X15/G$116),0) -> #DIV/0! | AE15: =Y15/AD15 -> #DIV/0! | AF15: =Y15/$AF$24/1000 -> 0.0063284435 | AG15: 0.007650221 | AH15: =IF($AF$21<$AG$21,AF15,IF($AF$20<$AG$20,AF15,IF(AND($AF$20>$AG$20,$AF$12<$AG$12),($AG$20+($AG$12-$AF$12))/$AF$20*AF15,AF15/$AF$20*$AG$20))) -> 0.0063284435 | AI15: =AH15*$Y$24*1000 -> 107836.68 | AJ15: =AI15/AD15 -> #DIV/0! | AK15: =Y15-AI15 -> 0 | AL15: =ROUND(S15/$G$116,0) -> #DIV/0! | AM15: =ROUND(T15/$G$116,0) -> #DIV/0! | AN15: =ROUND(U15/$G$116,0) -> #DIV/0! | AO15: =ROUND(V15/$G$116,0)-1 -> #DIV/0! | AP15: =ROUND(W15/$G$116,0) -> #DIV/0! | AQ15: =ROUND(X15/$G$116,0) -> #DIV/0! | AR15: =IF($B$24<>0,ROUND(AL15/B$24,3),0) -> 0 | AS15: =ROUND(AM15/B$47,3) -> #DIV/0! | AT15: =IF(E$47<>0,ROUND(AN15/E$47,3),0) -> 0 | AU15: =IF(E$24<>0,ROUND(AO15/E$24,3),0) -> #DIV/0! | AV15: =IF(H$47<>0,ROUND(AP15/H$47,3),0) -> 0 | AW15: =IF(H$24<>0,ROUND(AQ15/H$24,3),0) -> #DIV/0! | AX15: =AJ15*10000 -> #DIV/0!
A16: Indirect Payroll Costs (Benefits) | B16: =IF(B24<>0,$F$115/$B$49/1000,0) -> 0 | D16: 0 | E16: =IF(E24<>0,$F$115/$B$49/1000,0) -> 0.0065119255 | F16: 0.01706523 | G16: 0.013928937 | H16: =IF($H$24<>0,$F$115/$B$49/1000,0) -> 0.0065119255 | J16: 0 | S16: =B16*B$24*1000 -> 0 | T16: =B39*B$47*1000 -> 19535.776 | U16: =E39*E$47*1000 -> 0 | V16: =E16*E$24*1000 -> 62514.485 | W16: =H39*H$47*1000 -> 0 | X16: =H16*H$24*1000 -> 28912.949 | Y16: =SUM(S16:X16) -> 110963.21 | Z16: =-$D$122 -> 0 | AA16: =SUM(Y16:Z16) -> 110963.21 | AB16: IPC01 | AC16: hr | AD16: =ROUND((S16/C$123)+(T16/C$123)+(U16/C$123)+(V16/C$123)+(W16/C$123)+(X16/C$123),0) -> #DIV/0! | AE16: =Y16/AD16 -> #DIV/0! | AF16: =Y16/$AF$24/1000 -> 0.0065119255 | AG16: 0.0088563301 | AH16: =IF($AF$21<$AG$21,AF16,IF($AF$20<$AG$20,AF16,IF(AND($AF$20>$AG$20,$AF$12<$AG$12),($AG$20+($AG$12-$AF$12))/$AF$20*AF16,AF16/$AF$20*$AG$20))) -> 0.0065119255 | AI16: =AH16*$Y$24*1000 -> 110963.21 | AJ16: =AI16/AD16 -> #DIV/0! | AK16: =Y16-AI16 -> 0 | AL16: =ROUND(S16/$C123,0) -> #DIV/0! | AM16: =ROUND(T16/$C123,0) -> #DIV/0! | AN16: =ROUND(U16/$C123,0) -> #DIV/0! | AO16: =ROUND(V16/$C123,0) -> #DIV/0! | AP16: =ROUND(W16/$C123,0) -> #DIV/0! | AQ16: =ROUND(X16/$C123,0) -> #DIV/0! | AR16: =IF($B$24<>0,ROUND(AL16/B$24,3),0) -> 0 | AS16: =ROUND(AM16/B$47,3) -> #DIV/0! | AT16: =IF(E$47<>0,ROUND(AN16/E$47,3),0) -> 0 | AU16: =IF(E$24<>0,ROUND(AO16/E$24,3),0) -> #DIV/0! | AV16: =IF(H$47<>0,ROUND(AP16/H$47,3),0) -> 0 | AW16: =IF(H$24<>0,ROUND(AQ16/H$24,3),0) -> #DIV/0! | AX16: =AJ16*10000 -> #DIV/0!
A17: Supervision | B17: =IF($B$24<>0,$F$114/$B$49/1000,0) -> 0 | D17: 0 | E17: =IF(E24<>0,$F$114/$B$49/1000,0) -> 0.00041983568 | F17: 0.0045810516 | G17: 0.0015771316 | H17: =IF($H$24<>0,$F$114/$B$49/1000,0) -> 0.00041983568 | J17: 0 | S17: =B17*B$24*1000 -> 0 | T17: =B40*B$47*1000 -> 1259.507 | U17: =E40*E$47*1000 -> 0 | V17: =E17*E$24*1000 -> 4030.4225 | W17: =H40*H$47*1000 -> 0 | X17: =H17*H$24*1000 -> 1864.0704 | Y17: =SUM(S17:X17) -> 7154 | Z17: =C176/($C$184+$C$185)*$C$185 -> 0 | AA17: =SUM(Y17:Z17) -> 7154 | AB17: SUP01 | AC17: lb | AD17: =ROUND((S17/F$176)+(T17/F$176)+(U17/F$176)+(V17/F$176)+(W17/F$176)+(X17/F$176),0) -> #DIV/0! | AE17: =Y17/AD17 -> #DIV/0! | AF17: =Y17/$AF$24/1000 -> 0.00041983568 | AG17: 0.0021273119 | AH17: =IF($AF$21<$AG$21,AF17,IF($AF$20<$AG$20,AF17,IF(AND($AF$20>$AG$20,$AF$12<$AG$12),($AG$20+($AG$12-$AF$12))/$AF$20*AF17,AF17/$AF$20*$AG$20))) -> 0.00041983568 | AI17: =AH17*$Y$24*1000 -> 7154 | AJ17: =AI17/AD17 -> #DIV/0! | AK17: =Y17-AI17 -> 0 | AL17: =S17/$AE17 -> #DIV/0! | AM17: =T17/$AE17 -> #DIV/0! | AN17: =U17/$AE17 -> #DIV/0! | AO17: =V17/$AE17 -> #DIV/0! | AP17: =W17/$AE17 -> #DIV/0! | AQ17: =X17/$AE17 -> #DIV/0! | AR17: =IF($B$24<>0,ROUND(AL17/B$24,3),0) -> 0 | AS17: =ROUND(AM17/B$47,3) -> #DIV/0! | AT17: =IF(E$47<>0,ROUND(AN17/E$47,3),0) -> 0 | AU17: =IF(E$24<>0,ROUND(AO17/E$24,3),0) -> #DIV/0! | AV17: =IF(H$47<>0,ROUND(AP17/H$47,3),0) -> 0 | AW17: =IF(H$24<>0,ROUND(AQ17/H$24,3),0) -> #DIV/0! | AX17: =AJ17*10000 -> #DIV/0!
A18: Depreciation | B18: =IF($B$24<>0,$B$178/$B$49/1000,0) -> 0 | D18: 0 | E18: =IF(E24<>0,$B$178/$B$49/1000,0) -> 0.0015183099 | F18: 0.0038559807 | G18: 0.0016578947 | H18: =IF($H$24<>0,$B$178/$B$49/1000,0) -> 0.0015183099 | J18: 0 | S18: =B18*B$24*1000 -> 0 | T18: =B41*B$47*1000 -> 4554.9296 | U18: =E41*E$47*1000 -> 0 | V18: =E18*E$24*1000 -> 14575.775 | W18: =H41*H$47*1000 -> 0 | X18: =H18*H$24*1000 -> 6741.2958 | Y18: =SUM(S18:X18) -> 25872 | Z18: =C178/($C$184+$C$185)*$C$185 -> 0 | AA18: =SUM(Y18:Z18) -> 25872 | AB18: DEP01 | AC18: lb | AD18: =ROUND((S18/F$178)+(T18/F$178)+(U18/F$178)+(V18/F$178)+(W18/F$178)+(X18/F$178),0) -> 1420000 | AE18: =Y18/AD18 -> 0.018219718 | AF18: =Y18/$AF$24/1000 -> 0.0015183099 | AG18: 0.032747211 | AH18: =IF($AF$21<$AG$21,AF18,IF($AF$20<$AG$20,AF18,IF(AND($AF$20>$AG$20,$AF$12<$AG$12),($AG$20+($AG$12-$AF$12))/$AF$20*AF18,AF18/$AF$20*$AG$20))) -> 0.0015183099 | AI18: =AH18*$Y$24*1000 -> 25872 | AJ18: =AI18/AD18 -> 0.018219718 | AK18: =Y18-AI18 -> 0 | AL18: =S18/$AE18 -> 0 | AM18: =T18/$AE18 -> 250000 | AN18: =U18/$AE18 -> 0 | AO18: =V18/$AE18 -> 800000 | AP18: =W18/$AE18 -> 0 | AQ18: =X18/$AE18 -> 370000 | AR18: =IF($B$24<>0,ROUND(AL18/B$24,3),0) -> 0 | AS18: =ROUND(AM18/B$47,3) -> 83.333 | AT18: =IF(E$47<>0,ROUND(AN18/E$47,3),0) -> 0 | AU18: =IF(E$24<>0,ROUND(AO18/E$24,3),0) -> 83.333 | AV18: =IF(H$47<>0,ROUND(AP18/H$47,3),0) -> 0 | AW18: =IF(H$24<>0,ROUND(AQ18/H$24,3),0) -> 83.333 | AX18: =AJ18*10000 -> 182.19718
A19: Insurance & Taxes | B19: =IF($B$24<>0,$B$177/$B$49/1000,0) -> 0 | D19: 0 | E19: =IF(E24<>0,$B$177/B49/1000,0) -> 0.002575 | F19: 0.010801566 | G19: 0.0058026316 | H19: =IF($H$24<>0,$B$177/$B$49/1000,0) -> 0.002575 | J19: 0 | S19: =B19*B$24*1000 -> 0 | T19: =B42*B$47*1000 -> 7725 | U19: =E42*E$47*1000 -> 0 | V19: =E19*E$24*1000 -> 24720 | W19: =H42*H$47*1000 -> 0 | X19: =H19*H$24*1000 -> 11433 | Y19: =SUM(S19:X19) -> 43878 | Z19: =C177/($C$184+$C$185)*$C$185 -> 0 | AA19: =SUM(Y19:Z19) -> 43878 | AB19: INS01 | AC19: lb | AD19: =ROUND((S19/F$177)+(T19/F$177)+(U19/F$177)+(V19/F$177)+(W19/F$177)+(X19/F$177),0) -> 1420000 | AE19: =Y19/AD19 -> 0.0309 | AF19: =Y19/$AF$24/1000 -> 0.002575 | AG19: 0.0073609622 | AH19: =IF($AF$21<$AG$21,AF19,IF($AF$20<$AG$20,AF19,IF(AND($AF$20>$AG$20,$AF$12<$AG$12),($AG$20+($AG$12-$AF$12))/$AF$20*AF19,AF19/$AF$20*$AG$20))) -> 0.002575 | AI19: =AH19*$Y$24*1000 -> 43878 | AJ19: =AI19/AD19 -> 0.0309 | AK19: =Y19-AI19 -> 0 | AL19: =S19/$AE19 -> 0 | AM19: =T19/$AE19 -> 250000 | AN19: =U19/$AE19 -> 0 | AO19: =V19/$AE19 -> 800000 | AP19: =W19/$AE19 -> 0 | AQ19: =X19/$AE19 -> 370000 | AR19: =IF($B$24<>0,ROUND(AL19/B$24,3),0) -> 0 | AS19: =ROUND(AM19/B$47,3) -> 83.333 | AT19: =IF(E$47<>0,ROUND(AN19/E$47,3),0) -> 0 | AU19: =IF(E$24<>0,ROUND(AO19/E$24,3),0) -> 83.333 | AV19: =IF(H$47<>0,ROUND(AP19/H$47,3),0) -> 0 | AW19: =IF(H$24<>0,ROUND(AQ19/H$24,3),0) -> 83.333 | AX19: =AJ19*10000 -> 309
A20: Total Fixed Costs | B20: =SUM(B14:B19) -> 0 | C20: =SUM(C14:C19) -> 0 | D20: =SUM(D14:D19) -> 0 | E20: =SUM(E14:E19) -> 0.032311654 | F20: =SUM(F14:F19) -> 0.11152537 | G20: =SUM(G14:G19) -> 0.058371315 | H20: =SUM(H14:H19) -> 0.032311654 | I20: =SUM(I14:I19) -> 0 | J20: =SUM(J14:J19) -> 0 | S20: =SUM(S14:S19) -> 0 | T20: =SUM(T14:T19) -> 96934.961 | U20: =SUM(U14:U19) -> 0 | V20: =SUM(V14:V19) -> 310191.87 | W20: =SUM(W14:W19) -> 0 | X20: =SUM(X14:X19) -> 143463.74 | Y20: =SUM(Y14:Y19) -> 550590.58 | Z20: =SUM(Z14:Z19) -> 0 | AA20: =SUM(AA14:AA19) -> 550590.58 | AF20: =SUM(AF14:AF19) -> 0.032311654 | AG20: =SUM(AG14:AG19) -> 0.07023059 | AH20: =SUM(AH14:AH19) -> 0.032311654 | AI20: =SUM(AI14:AI19) -> 550590.58 | AK20: =SUM(AK14:AK19) -> 0
A21: Excess Costs | C21: -0.0273 | F21: -0.050457361 | S21: =S12+S20 -> 0 | T21: =T12+T20 -> 383019.07 | U21: =U12+U20 -> 0 | V21: =V12+V20 -> 1554739.9 | W21: =W12+W20 -> 0 | X21: =X12+X20 -> 346601.1 | Y21: =Y12+Y20 -> 2284360.1 | Z21: =Z12+Z20 -> 0 | AA21: =AA12+AA20 -> 2284360.1 | AB21: CCtr Total | AF21: =AF12+AF20 -> 0.13405869 | AG21: =AG12+AG20 -> 0.15165505 | AH21: =AH12+AH20 -> 0.13405869 | AI21: =AI12+AI20 -> 2284360.1 | AK21: =AK12+AK20 -> 0
A22: TOTAL COSTS PER POUND | B22: =B12+B20 -> 0 | C22: =+C20+C21+C12 -> -0.0273 | D22: =D12+D20 -> 0 | E22: =E12+E20 -> 0.21568327 | F22: =F12+F20+F21 -> 0.36638748 | G22: =G12+G20 -> 0.17357627 | H22: =H12+H20 -> 0.25593102 | I22: =I12+I20 -> 0 | J22: =J12+J20 -> 0 | S22: =IF(B24<>0,ROUND(S21/(B24*1000),5),0) -> 0 | T22: =IF(B47<>0,ROUND(T21/(B47*1000),5),0) -> 0.12767 | U22: =IF(E47<>0,ROUND(U21/(E47*1000),5),0) -> 0 | V22: =IF(E24<>0,ROUND(V21/(E24*1000),5),0) -> 0.16195 | W22: =IF(H47<>0,ROUND(W21/(H47*1000),5),0) -> 0 | X22: =IF(H24<>0,ROUND(X21/(H24*1000),5),0) -> 0.07806 | Y22: =Y21/Y24/1000 -> 0.13405869 | Z22: 0 | AA22: =ROUND(AA21/(B49*1000),5) -> 0.13406 | AB22: Excl Matl | AI22: =AI21/AI24/1000 -> 0.13405869 | AK22: =AK21/AK24/1000 -> 0
S23: =ROUND(S22+B6,5) -> 0 | T23: =ROUND(T22+B29,5) -> 0.25593 | U23: =ROUND(U22+E29,5) -> 0 | V23: =ROUND(V22+E6,5) -> 0.26996 | W23: =ROUND(W22+H29,5) -> 0 | X23: =ROUND(X22+H6,5) -> 0.20632 | Y23: =Y22+(($B$6*$B$24*1000+$B$29*$B$47*1000+$E$29*$E$47*1000+$H$6*$H$24*1000+$H$29*$H$47*1000+$E$6*$E$24*1000)/($B$49*1000)) -> 0.25090951 | Z23: 0 | AA23: =AA22+(($B$6*$B$24*1000+$B$29*$B$47*1000+$E$6*$E$24*1000+$E$29*$E$47*1000+$H$6*$H$24*1000+$H$29*$H$47*1000)/($B$49*1000)) -> 0.25091082 | AB23: Incl Matl
A24: PRODUCTION ( in 000 lbs ) | B24: =B54 -> 0 | C24: 6211 | D24: 0 | E24: =B57 -> 9600 | F24: 3204 | G24: 51000 | H24: =B58 -> 4440 | I24: 4207 | J24: 0 | S24: =B24 -> 0 | T24: =B47 -> 3000 | U24: =E47 -> 0 | V24: =E24 -> 9600 | W24: =H47 -> 0 | X24: =H24 -> 4440 | Y24: =SUM(S24:X24) -> 17040 | Z24: 0 | AA24: =SUM(Y24:Z24) -> 17040 | AF24: =Y24 -> 17040 | AI24: =Y24 -> 17040 | AK24: =Y24 -> 17040
B26: CP | E26: HSP | H26: Nanomite C | AS26: 0.936
B27: =B4 -> 25 Standard | C27: 23 Actual | D27: =+D4 -> 22 Standard | E27: =E4 -> 25 Standard | F27: =+C27 -> 23 Actual | G27: =+D27 -> 22 Standard | H27: =H4 -> 25 Standard | I27: 23 Actual | J27: =+J4 -> 22 Standard | AS27: 0.264
C28: (Jan-Aug) | F28: (Jan-Aug) | I28: (Jan-Aug) | AS28: 286
A29: Materials | B29: =IF($B$47<>0,$D$88,0) -> 0.128258 | C29: 0.1396 | D29: 0.06037434 | E29: =IF(E47<>0,$D$88,0) -> 0 | F29: 0.0865 | G29: 0 | H29: =IF(H47<>0,$L$80,0) -> 0 | I29: 0.0792 | J29: 0.02 | AS29: 8000
A30: Electricity | B30: =IF(B47<>0,$D$151,0) -> 0.033069 | C30: 0.0273 | D30: 0.018883379 | E30: =IF(E47<>0,$G$151,0) -> 0 | F30: 0.0294 | G30: 0 | H30: =IF(H47<>0,$J$151,0) -> 0 | I30: 0.0124 | J30: 0.0027366213 | AS30: 1.2
A31: Gas | B31: =IF(B47<>0,$D$152,0) -> 0.04 | C31: 0.0379 | D31: 0.04184 | E31: =IF(E47<>0,$G$152,0) -> 0 | F31: 0.0465 | G31: 0 | H31: =IF(H47<>0,$J$152,0) -> 0 | I31: 0 | J31: 0
A32: R&M Supplies and Service | B32: =IF(B47<>0,$H$159,0) -> 0.017429577 | C32: 0.0358 | D32: 0.022368421 | E32: =IF(E47<>0,$H$159,0) -> 0 | F32: 0.0304 | G32: 0 | H32: =IF(H47<>0,$H$159,0) -> 0 | I32: 0.0164 | J32: 0.022368421
A33: Manufacturing Supplies | B33: =IF(B47<>0,$H$163,0) -> 0.00098955399 | C33: 0.0006 | D33: 0.00065789474 | E33: =IF(E47<>0,$H$163,0) -> 0 | F33: 0.002 | G33: 0 | H33: =IF(H47<>0,$H$163,0) -> 0 | I33: 0.0014 | J33: 0.00065789474
A34: Other variable | B34: =IF($B$47<>0,$H$166,0) -> 0.0038732394 | C34: 0.0101 | D34: 0.0046052632 | E34: =IF(E47<>0,$H$166,0) -> 0 | F34: 0.0118 | G34: 0 | H34: =IF(H47<>0,$H$166,0) -> 0 | I34: 0.0108 | J34: 0.0046052632
A35: Total Variable Costs | B35: =SUM(B29:B34) -> 0.22361937 | C35: =SUM(C29:C34) -> 0.2513 | D35: =SUM(D29:D34) -> 0.1487293 | E35: =SUM(E29:E34) -> 0 | F35: =SUM(F29:F34) -> 0.2066 | G35: =SUM(G29:G34) -> 0 | H35: =SUM(H29:H34) -> 0 | I35: =SUM(I29:I34) -> 0.1202 | J35: =SUM(J29:J34) -> 0.0503682
A37: Production Labor | B37: =IF(B47<>0,$F$112/$B$49/1000,0) -> 0.014958139 | C37: 0.0445 | D37: 0.02638428 | E37: =IF(E47<>0,$F$112/$B$49/1000,0) -> 0 | F37: 0.0483 | G37: 0 | H37: =IF(H47<>0,$F$112/$B$49/1000,0) -> 0 | I37: 0.0451 | J37: 0.02638428
A38: Repairs & Maintenance Labor | B38: =IF(B47<>0,$F$113/$B$49/1000,0) -> 0.0063284435 | C38: 0.015 | D38: 0.00902044 | E38: =IF(E47<>0,$F$113/$B$49/1000,0) -> 0 | F38: 0.0144 | G38: 0 | H38: =IF(H47<>0,$F$113/$B$49/1000,0) -> 0 | I38: 0.0156 | J38: 0.00902044
A39: Indirect Payroll Costs (Benefits) | B39: =IF(B47<>0,$F$115/$B$49/1000,0) -> 0.0065119255 | C39: 0.0194 | D39: 0.013928937 | E39: =IF(E47<>0,$F$115/$B$49/1000,0) -> 0 | F39: 0.0196 | G39: 0 | H39: =IF(H47<>0,$F$115/$B$49/1000,0) -> 0 | I39: 0.0285 | J39: 0.013928937
A40: Supervision | B40: =IF($B$47<>0,$F$114/$B$49/1000,0) -> 0.00041983568 | C40: 0.0018 | D40: 0.0015771316 | E40: =IF(E47<>0,$F$114/$B$49/1000,0) -> 0 | F40: 0.0014 | G40: 0 | H40: =IF(H47<>0,$F$114/$B$49/1000,0) -> 0 | I40: 0.0022 | J40: 0.0015771316
A41: Depreciation | B41: =IF(B47<>0,$B$178/$B$49/1000,0) -> 0.0015183099 | C41: 0.0043 | D41: 0.0016578947 | E41: =IF(E47<>0,$B$178/$B$49/1000,0) -> 0 | F41: 0.0042 | G41: 0 | H41: =IF(H47<>0,$B$178/$B$49/1000,0) -> 0 | I41: 0.0067 | J41: 0.0016578947
A42: Insurance & Taxes | B42: =IF(B47<>0,$B$177/B49/1000,0) -> 0.002575 | C42: 0.0093 | D42: 0.0058026316 | E42: =IF(E47<>0,$B$177/B49/1000,0) -> 0 | F42: 0.0098 | G42: 0 | H42: =IF(H47<>0,$B$177/$B$49/1000,0) -> 0 | I42: 0.014 | J42: 0.0058026316
A43: Total Fixed Costs | B43: =SUM(B37:B42) -> 0.032311654 | C43: =SUM(C37:C42) -> 0.0943 | D43: =SUM(D37:D42) -> 0.058371315 | E43: =SUM(E37:E42) -> 0 | F43: =SUM(F37:F42) -> 0.0977 | G43: =SUM(G37:G42) -> 0 | H43: =SUM(H37:H42) -> 0 | I43: =SUM(I37:I42) -> 0.1121 | J43: =SUM(J37:J42) -> 0.058371315
A44: Excess Costs
A45: TOTAL COSTS PER POUND | B45: =B35+B43 -> 0.25593102 | C45: =C35+C43+C44 -> 0.3456 | D45: =D35+D43 -> 0.20710061 | E45: =E35+E43 -> 0 | F45: =F35+F43+F44 -> 0.3043 | G45: 0 | H45: =H35+H43 -> 0 | I45: =I35+I43+I44 -> 0.2323 | J45: =+J35+J43 -> 0.10873952
A47: PRODUCTION ( in 000 lbs ) | B47: =B55 -> 3000 | C47: 13494 | D47: 22600 | E47: =B56 -> 0 | F47: 1391 | G47: 0 | H47: =B59 -> 0 | I47: 6147 | J47: 2400
A49: TOTAL PLANT PRODUCTION ( in 000 lbs) | B49: =B24+E24+H24+B47+E47+H47 -> 17040 | C49: =C24+F24+I24+C47+F47+I47 -> 34654 | D49: 76000
A51: Variable Costs - Material | B51: Purchase Price/lb * Yield Factor * Scrap Factor * Mix = Std. Cost Contribution
A53: Production Plan: | B53: Pounds (000) | C53: Product Split | D53: Days
A54: HT (foundry) | B54: ='2025 Summary'!$C$8 -> 0 | C54: =B54/$B$60 -> 0
A55: CarboProp | B55: ='2025 Summary'!D$8 -> 3000 | C55: =B55/$B$60 -> 0.17605634 | D55: =B55/180/2 -> 8.3333333
A56: CarboHSP | B56: ='2025 Summary'!E$8 -> 0 | C56: =B56/$B$60 -> 0 | D56: =B56/200/2 -> 0
A57: Bauxite Pellets | B57: ='2025 Summary'!$F$8 -> 9600 | C57: =B57/$B$60 -> 0.56338028
A58: ID (foundry) | B58: ='2025 Summary'!$G$8 -> 4440 | C58: =B58/$B$60 -> 0.26056338
A59: Nanomite C | B59: ='2025 Summary'!$H$8 -> 0 | C59: =B59/$B$60 -> 0 | D59: =B59/200 -> 0
A60: Total | B60: =SUM(B54:B59) -> 17040 | C60: =B60/$B$60 -> 1
AB61: NEED TO VERIFY ALL FORMULAS IN THE SECTION BELOW: Done
C62: Yield Factor | G62: Mix %
A63: Local Kaolin | B63: Price ($/Ton) | C63: CG | D63: CP | E63: HSP | F63: CL | G63: Cristobalite | H63: CG | I63: CP / ID | J63: HSP | K63: CL | L63: Cristobalite | AE63: price/1000/lb | AM63: Mix%
A64: Arcilla (local kaolin) 30012 | B64: =11.75*2 -> 23.5 | C64: =$C$76*H64 -> 0.2668 | D64: =$C$84*I64 -> 0.056 | E64: =$G$84*J64 -> 0 | F64: =$K$84*K64 -> 0 | G64: =$K$84*L64 -> 0 | H64: 0.667 | I64: 0.14 | J64: 0 | K64: 1 | L64: 0 | AB64: 30012/U103 | AE64: =B64/2000*1000 -> 11.75 | AM64: =$AM$76*I64 -> 56 | AO64: =$AO$84*K64 -> 0
A65: Dixon (local kaolin) | B65: 0 | C65: =$C$76*H65 -> 0 | D65: =$C$84*I65 -> 0 | E65: =$G$84*J65 -> 0 | F65: =$K$84*K65 -> 0 | G65: =$K$84*L65 -> 0 | H65: 0 | I65: 0 | J65: 0 | K65: 0 | L65: 0 | AB65: 30012/U103 | AE65: =B65/2000*1000 -> 0 | AM65: =$AM$76*I65 -> 0 | AO65: =$AO$85*J65 -> 0
C66: =SUM(C64:C65) -> 0.2668 | D66: =SUM(D64:D65) -> 0.056 | E66: =SUM(E64:E65) -> 0 | F66: =SUM(F64:F65) -> 0 | G66: =SUM(G64:G65) -> 0
A67: Bauxite: | AO67: =$AO$85*J66 -> 0
A68: MRN (30006) Lord Allen & ECT | B68: =60.33+8+44 -> 112.33 | C68: =$C$77*H68 -> 0.1837 | D68: =$C$85*I68 -> 0.98 | E68: =$G$85*J68 -> 1.8 | F68: =$K$85*K68 -> 0 | G68: =$K$85*L68 -> 0 | H68: 0.167 | I68: 0.56 | J68: 1 | K68: 0 | L68: 0 | AB68: 30006/U103 | AE68: =B68/2000*1000 -> 56.165 | AM68: =$AM$77*I68 -> 980 | AN68: =$AN$85*I68 -> 980 | AO68: =$AO$85*J68 -> 1000
A69: Rusal (30008) Lord Allen & ECT | B69: =56.29*2 -> 112.58 | C69: =$C$77*H69 -> 0 | D69: =$C$85*I69 -> 0 | E69: =$G$85*J69 -> 0 | F69: =$K$85*K69 -> 0 | G69: =$K$85*L69 -> 0 | H69: 0 | I69: 0 | J69: 0 | K69: 0 | L69: 0 | AB69: 30008/U103 | AE69: =B69/2000*1000 -> 56.29 | AM69: =$AM$77*I69 -> 0 | AN69: =$AN$85*I69 -> 0 | AO69: =$AO$85*J69 -> 0
A70: Bosai Chem Grade (30002) | B70: 160 | C70: 0 | D70: =$C$85*I70 -> 0 | E70: =$G$85*J70 -> 0 | F70: =$K$85*K70 -> 0 | G70: =$K$85*L70 -> 0 | H70: 0 | I70: 0 | J70: 0 | K70: 0 | L70: 0 | M70: Changed Bosai Chem Grade Price | AB70: 30003/U103 | AE70: =B70/2000*1000 -> 80 | AM70: =$AM$77*I70 -> 0 | AN70: =$AN$85*I70 -> 0
A71: First Bauxite (30440) | B71: =194+44 -> 238 | C71: =$C$77*H71 -> 0.1837 | D71: =$C$85*I71 -> 0.525 | E71: =$G$85*J71 -> 0 | F71: =$K$85*K71 -> 0 | G71: =$K$85*L71 -> 0 | H71: 0.167 | I71: 0.3 | J71: 0 | K71: 0 | L71: 0 | AB71: 30440/U103 | AE71: =B71/2000*1000 -> 119 | AM71: =$AM$77*I71 -> 525 | AN71: =$AN$85*I71 -> 525 | AO71: =$AO$85*J70 -> 0
C72: =SUM(C68:C71) -> 0.3674 | D72: =SUM(D68:D71) -> 1.505 | E72: =SUM(E68:E71) -> 1.8 | F72: =SUM(F68:F71) -> 0 | G72: =SUM(G68:G71) -> 0
B74: HT | F74: Cristobalite | J74: Nanomite | AE74: CG
B75: Price ($/lb) | C75: Yield Factor | D75: Std $ Contrib | F75: Price ($/lb) | G75: Yield Factor | H75: Std $ Contrib | J75: Price ($/lb) | K75: Yield Factor | L75: Std $ Contrib | AE75: price/1000/lb
A76: Local Kaolin | B76: 0.013 | C76: 0.4 | D76: =B76*C76 -> 0.0052 | F76: =($B$64*$L$64+$B$65*$L$65)/2000 -> 0 | G76: 0 | H76: =F76*G76 -> 0 | J76: =($B$64*$L$64+$B$65*$L$65)/2000 -> 0 | K76: 0 | L76: =J76*K76 -> 0 | AB76: 30012/U103 | AE76: =B76*1000 -> 13 | AK76: kaolin | AM76: =IF(B84<>0,D84/B84*1000,0) -> 400
A77: Bauxite | B77: =B71/2000 -> 0.119 | C77: 1.1 | D77: =B77*C77 -> 0.1309 | F77: =($B$68*$L$68+$B$69*$L$69+$B$70*$L$70+$B$71*$L$71)/2000 -> 0 | G77: 0 | H77: =F77*G77 -> 0 | J77: =($B$68*$L$68+$B$69*$L$69+$B$70*$L$70+$B$71*$L$71)/2000 -> 0 | K77: 0 | L77: =J77*K77 -> 0 | AB77: 30060/U103 | AE77: =B77*1000 -> 119 | AK77: bauxite | AM77: =IF(B85<>0,D85/B85*1000,0) -> 1750
A78: Starch (30020) | B78: 0.88 | C78: 0.01 | D78: =B78*C78 -> 0.0088 | F78: =B86 -> 0.726 | G78: 0 | H78: =F78*G78 -> 0 | K78: 0 | L78: =J78*K78 -> 0 | AB78: 30020/U103 | AE78: =B78*1000 -> 880 | AK78: starch | AM78: =IF(B86<>0,D86/B86*1000,0) -> 8
A79: Taggant | D79: 0 | G79: 0 | H79: =F79*G79 -> 0 | K79: 0 | L79: =J79*K79 -> 0
A80: Total Material Cost Per Pound | D80: =SUM(D76:D79) -> 0.1449 | H80: =SUM(H76:H79) -> 0 | L80: 0.08
B82: =B26 -> CP | F82: =E26 -> HSP | J82: Bauxite Pellets | AE82: CP/ID | AG82: CL
B83: Price ($/lb) | C83: Yield Factor | D83: Std $ Contrib | F83: Price ($/lb) | G83: Yield Factor | H83: Std $ Contrib | J83: Price ($/lb) | K83: Yield Factor | L83: Std $ Contrib | AE83: price/1000/lb | AG83: price/1000/lb
A84: Local kaolin | B84: 0.013 | C84: 0.4 | D84: =B84*C84 -> 0.0052 | F84: =($B$64*$J$64+$B$65*$J$65)/2000 -> 0 | G84: 0 | H84: =F84*G84 -> 0 | J84: =($B$64*$K$64+$B$65*$K$65)/2000 -> 0.01175 | K84: 0 | L84: =J84*K84 -> 0 | AB84: 30012/U103 | AE84: =B84*1000 -> 13 | AG84: =J84*1000 -> 11.75 | AN84: =IF(B84<>0,D84/B84*1000,0) -> 400 | AO84: =IF(J84<>0,L84/J84*1000,0) -> 0
A85: Bauxite | B85: 0.067 | C85: 1.75 | D85: =B85*C85 -> 0.11725 | F85: =($B$68*$J$68+$B$69*$J$69+$B$70*$J$70+$B$71*$J$71)/2000 -> 0.056165 | G85: 1.8 | H85: =F85*G85 -> 0.101097 | J85: =(B71/2000*0.75)+(B68/2000*0.25) -> 0.10329125 | K85: 1 | L85: =J85*K85 -> 0.10329125 | AB85: Various (see above) | AE85: =B85*1000 -> 67 | AG85: =J85*1000 -> 103.29125 | AN85: =IF(B85<>0,D85/B85*1000,0) -> 1750 | AO85: =IF(J85<>0,L85/J85*1000,0) -> 1000
A86: Starch (30020) | B86: 0.726 | C86: 0.008 | D86: =B86*C86 -> 0.005808 | F86: =B86 -> 0.726 | G86: 0.008 | H86: =F86*G86 -> 0.005808 | J86: =B86 -> 0.726 | K86: 0.0065 | L86: =J86*K86 -> 0.004719 | M86: Increased starch to 0.8% | AB86: 30020/U103 | AE86: =B86*1000 -> 726 | AG86: =J86*1000 -> 726 | AN86: =IF(B86<>0,D86/B86*1000,0) -> 8 | AO86: =IF(J86<>0,L86/J86*1000,0) -> 6.5
A87: Taggant | D87: 0 | H87: 0 | L87: 0
A88: Total Material Cost Per Pound | D88: =SUM(D84:D86) -> 0.128258 | H88: =SUM(H84:H86) -> 0.106905 | L88: =SUM(L84:L87) -> 0.10801025
A90: Variable Cost - Labor & Benefits - 12 hour shift
AE91: Nov-20 YTD
U92: =$Z$14*$AD92 -> 0 | Z92: =AA14*$AD92 -> 188917.55 | AB92: DLAB01 (s/t) | AC92: 611030 | AD92: =+AE92/AE94 -> 0.7411825 | AE92: 882400
U93: =$Z$14*$AD93 -> 0 | Z93: =AA14*$AD93 -> 65969.136 | AB93: DLAB01 (o/t) | AC93: 610210 | AD93: =+AE93/AE94 -> 0.2588175 | AE93: 308130
U94: =SUM(U92:U93) -> 0 | Z94: =SUM(Z92:Z93) -> 254886.69 | AA94: hr | AB94: DLAB01 | AC94: Total | AE94: =SUM(AE92:AE93) -> 1190530
B97: Jan | C97: Feb | D97: Mar | E97: Apr | F97: May | G97: Jun | H97: Jul
A98: Production Labor | B98: 268968.01 | C98: 288390.24 | D98: 154345.41 | E98: 13412.75 | F98: 229529.76 | G98: 274156.29 | H98: 267092.21
A99: R & M Labor | B99: 67812.91 | C99: 64354.51 | D99: 40616.39 | E99: 14950.76 | F99: 74301.16 | G99: 85619.44 | H99: 74393.95 | U99: =$Z$15*$AD99 -> 0 | Z99: =AA15*$AD99 -> 84199.625 | AB99: MLAB01 (s/t) | AC99: 611040 | AD99: =+AE99/AE102 -> 0.78080694 | AE99: 392660
A100: IPC | B100: 102162.56 | C100: 97023.8 | D100: 87771.29 | E100: 18740.91 | F100: 135347.7 | G100: 89284.14 | H100: 88862.54 | U100: =$Z$15*$AD100 -> 0 | Z100: =AA15*$AD100 -> 23637.052 | AB100: MLAB01 (o/t) | AC100: 610215 | AD100: =+AE100/AE102 -> 0.21919306 | AE100: 110230
A101: Supervision | B101: 6248.2 | C101: 7823.13 | D101: 4541.85 | E101: 10625.36 | F101: 11684.3 | G101: 7724.39 | H101: 6820.85
A102: Temp | B102: 35640 | C102: 61311 | D102: 50554 | F102: 65416 | G102: 62538 | H102: 37211 | U102: =SUM(U99:U100) -> 0 | Z102: =SUM(Z99:Z100) -> 107836.68 | AA102: hr | AB102: MLAB01 | AC102: Total | AE102: =SUM(AE99:AE100) -> 502890
A103: IPC (estimated) | B103: =B100/(B98+B99-B102+B101) -> 0.33235581 | C103: =C100/(C98+C99-C102+C101) -> 0.32421577 | D103: =D100/(D98+D99-D102+D101) -> 0.58926819 | E103: =E100/(E98+E99-E102+E101) -> 0.48067333 | F103: =F100/(F98+F99-F102+F101) -> 0.54117602 | G103: =G100/(G98+G99-G102+G101) -> 0.29277125 | H103: =H100/(H98+H99-H102+H101) -> 0.28564346
U104: =$Z$16*$AD104 -> 0 | Z104: =$AA$16*$AD104 -> 18640.665 | AB104: IPC01 (vac) | AC104: 610220 | AD104: =+AE104/AE110 -> 0.1679896 | AE104: 109692
D105: $/FTE/month | F105: $ Rolling Total | U105: =$Z$16*$AD105 -> 0 | Z105: =$AA$16*$AD105 -> 15618.686 | AB105: IPC01 (hol) | AC105: 610510 | AD105: =+AE105/AE110 -> 0.14075553 | AE105: 91909
A106: Current Production Labor | B106: 46 | D106: =(AVERAGE((B98-B102),(C98-C102),(G98-G102),(H98-H102)))/B106 -> 4901.6671 | F106: =D106*B106 -> 225476.69 | U106: =$Z$16*$AD106 -> 0 | Z106: =$AA$16*$AD106 -> 7757.5973 | AB106: IPC01 (401k) | AC106: 610600 | AD106: =+AE106/AE110 -> 0.069911435 | AE106: 45650
A107: Current R & M Labor | B107: 16 | D107: =AVERAGE($G$99:$H$99,B99:C99)/B107 -> 4565.3252 | F107: =D107*B107 -> 73045.202 | U107: =$Z$16*$AD107 -> 0 | Z107: =$AA$16*$AD107 -> 37495.28 | AB107: IPC01 (ins) | AC107: 610610 | AD107: =+AE107/AE110 -> 0.33790731 | AE107: 220643
U108: =$Z$16*$AD108 -> 0 | Z108: =$AA$16*$AD108 -> 28673.541 | AB108: IPC01 (tax) | AC108: 612000 | AD108: =+AE108/AE110 -> 0.25840584 | AE108: 168731
A109: Future Production Labor Increase | B109: 6 | D109: =D106 -> 4901.6671 | F109: =D109*B109 -> 29410.003 | U109: =$Z$16*$AD109 -> 0 | Z109: =$AA$16*$AD109 -> 2777.4407 | AB109: IPC01 (w/c) | AC109: 612100 | AD109: =+AE109/AE110 -> 0.025030285 | AE109: 16344
A110: Future R&M Labor Increase | B110: 6 | D110: =D107 -> 4565.3252 | F110: =D110*B110 -> 27391.951 | U110: =SUM(U104:U109) -> 0 | Z110: =SUM(Z104:Z109) -> 110963.21 | AA110: hr | AB110: IPC01 | AC110: Total | AE110: =SUM(AE104:AE109) -> 652969
A112: Total Production Labor | B112: =B106+B109 -> 52 | D112: =D106 -> 4901.6671 | F112: =D112*B112 -> 254886.69
A113: Total R & M Labor | B113: =B107+B110 -> 22 | D113: =D106 -> 4901.6671 | F113: =D113*B113 -> 107836.68
...

Sheet Apr
A1: McINTYRE STANDARD 2025 | S1: COST CENTER 10001003 | AE1: Gross | AF1: Std | AG1: Abs Limit | AH1: Absorb | AI1: 10001003 | AJ1: Absorbed | AK1: 10001003 | AX1: Abs Cost
S2: CG | T2: CP | U2: HSP | V2: CL | W2: Nanomite C | X2: NRT | Y2: To Production | Z2: Idle Plant | AA2: TOTAL | AB2: Activity / Material | AC2: UOM | AD2: Ttl Unit Qty | AE2: Unit Cost | AF2: Cost/lb | AG2: Cost/lb | AH2: Cost/lb | AI2: Absorption | AJ2: Unit Cost | AK2: Underabs | AL2: EP Unit Qty | AM2: CP Unit Qty | AN2: HSP Unit Qty | AO2: CL Unit Qty | AP2: Nano C Qty | AQ2: NRT Unit Qty | AR2: EP Units/1000lb | AS2: CP Units/1000lb | AT2: HSP Units/1000lb | AU2: CL Units/1000lb | AV2: Nano C Units/1000lb | AW2: NRT Units/1000lb | AX2: per 10000
B3: HT | E3: Bauxite Pellets | H3: ID
B4: 25 Standard | C4: 23 Actual | D4: 22 Standard | E4: =B4 -> 25 Standard | F4: 23 Actual | G4: =+D4 -> 22 Standard | H4: =B4 -> 25 Standard | I4: 23 Actual | J4: =+D4 -> 22 Standard
F5: (Jan-Aug)
A6: Materials | B6: =IF($B$24<>0,$D$80,0) -> 0 | D6: 0 | E6: =IF(E24<>0,$L$88,0) -> 0 | F6: 0.071053254 | G6: 0.02685 | H6: =IF($H$24<>0,$D$88,0) -> 0 | J6: 0
A7: Electricity | B7: =IF($B$24<>0,$D$151,0) -> 0 | D7: 0 | E7: =IF(E24<>0,$D$151,0) -> 0 | F7: 0.03392679 | G7: 0.018883379 | H7: =IF(H24<>0,$D$151,0) -> 0 | J7: 0 | S7: =$C145*$B$24*1000*$B145 -> 0 | T7: =$C151*$B$47*1000*$B151 -> 0 | U7: =$F151*$E$47*1000*$E151 -> 0 | V7: =$F145*$E$24*1000*$E145 -> 0 | W7: =$I151*$H$47*1000*$H151 -> 9166.1355 | X7: =$I145*$H$24*1000*$H145 -> 0 | Y7: =SUM(S7:X7) -> 9166.1355 | Z7: 0 | AA7: =SUM(Y7:Z7) -> 9166.1355 | AB7: ELE01 | AC7: kwh | AD7: =ROUND((B145*B$24*1000)+(B151*B$47*1000)+(E145*E$24*1000)+(E151*E$47*1000)+(H145*H$24*1000)+(H151*H$47*1000),0) -> 125563 | AE7: =Y7/AD7 -> 0.073000291 | AF7: =Y7/$AF$24/1000 -> 0.0045830677 | AG7: 0.014890786 | AH7: =IF($AF$21<$AG$21,AF7,IF($AF$12<$AG$12,AF7,IF(AND($AF$12>$AG$12,$AF$20<$AG$20),($AG$12+($AG$20-$AF$20))/$AF$12*AF7,AF7/$AF$12*$AG$12))) -> 0.0019184927 | AI7: =AH7*$Y$24*1000 -> 3836.9853 | AJ7: =AI7/AD7 -> 0.030558248 | AK7: =Y7-AI7 -> 5329.1502 | AL7: =ROUND($B145*$B$24*1000,0) -> 0 | AM7: =ROUND($B151*$B$47*1000,0) -> 0 | AN7: =ROUND($E151*$E$47*1000,0) -> 0 | AO7: =ROUND($E145*$E$24*1000,0) -> 0 | AP7: =ROUND($H151*$H$47*1000,0) -> 125563 | AQ7: =ROUND($H145*$H$24*1000,0) -> 0 | AR7: =IF($B$24<>0,ROUND(AL7/B$24,3),0) -> 0 | AS7: =ROUND(AM7/B$47,3) -> #DIV/0! | AT7: =IF(E$47<>0,ROUND(AN7/E$47,3),0) -> 0 | AU7: =IF(F$24<>0,ROUND(AO7/F$24,3),0) -> 0 | AV7: =IF(H$47<>0,ROUND(AP7/H$47,3),0) -> 62.782 | AW7: =IF(H$24<>0,ROUND(AQ7/H$24,3),0) -> 0 | AX7: =AJ7*10000 -> 305.58248
A8: Gas | B8: =IF($B$24<>0,$D$152,0) -> 0 | D8: 0 | E8: =IF(E24<>0,$D$152,0) -> 0 | F8: 0.14600441 | G8: 0.04184 | H8: =IF(H24<>0,$D$152,0) -> 0 | J8: 0 | S8: =$C146*$B$24*1000*$B146 -> 0 | T8: =$C152*$B$47*1000*$B152 -> 0 | U8: =$F152*$E$47*1000*$E152 -> 0 | V8: =$F146*$E$24*1000*$E146 -> 0 | W8: =$I152*$H$47*1000*$H152 -> 0 | X8: =$I146*$H$24*1000*$H146 -> 0 | Y8: =SUM(S8:X8) -> 0 | Z8: 0 | AA8: =SUM(Y8:Z8) -> 0 | AB8: GAS01 | AC8: mbtu | AD8: =ROUND((B146*B$24*1000*1000)+(B152*B$47*1000*1000)+(E146*E$24*1000*1000)+(E152*E$47*1000*1000)+(H146*H$24*1000*1000)+(H152*H$47*1000*1000),0) -> 0 | AE8: =Y8/AD8 -> #DIV/0! | AF8: =Y8/$AF$24/1000 -> 0 | AG8: 0.042004912 | AH8: =IF($AF$21<$AG$21,AF8,IF($AF$12<$AG$12,AF8,IF(AND($AF$12>$AG$12,$AF$20<$AG$20),($AG$12+($AG$20-$AF$20))/$AF$12*AF8,AF8/$AF$12*$AG$12))) -> 0 | AI8: =AH8*$Y$24*1000 -> 0 | AJ8: =AI8/AD8 -> #DIV/0! | AK8: =Y8-AI8 -> 0 | AL8: =ROUND($B146*$B$24*1000*1000,0) -> 0 | AM8: =ROUND($B152*$B$47*1000*1000,0) -> 0 | AN8: =ROUND($E152*$E$47*1000*1000,0) -> 0 | AO8: =ROUND($E146*$E$24*1000*1000,0) -> 0 | AP8: =ROUND($H152*$H$47*1000*1000,0) -> 0 | AQ8: =ROUND($H146*$H$24*1000*1000,0) -> 0 | AR8: =IF($B$24<>0,ROUND(AL8/B$24,3),0) -> 0 | AS8: =ROUND(AM8/B$47,3) -> #DIV/0! | AT8: =IF(E$47<>0,ROUND(AN8/E$47,3),0) -> 0 | AU8: =IF(E$24<>0,ROUND(AO8/E$24,3),0) -> 0 | AV8: =IF(H$47<>0,ROUND(AP8/H$47,3),0) -> 0 | AW8: =IF(H$24<>0,ROUND(AQ8/H$24,3),0) -> 0 | AX8: =AJ8*10000 -> #DIV/0!
A9: R&M Supplies and Service | B9: =IF($B$24<>0,$H$159,0) -> 0 | D9: 0 | E9: =IF(E24<>0,$H$159,0) -> 0 | F9: 0.043366417 | G9: 0.022368421 | H9: =IF(H24<>0,$H$159,0) -> 0 | J9: 0 | S9: =B9*B$24*1000 -> 0 | T9: =B32*B$47*1000 -> 0 | U9: =E32*E$47*1000 -> 0 | V9: =E9*E$24*1000 -> 0 | W9: =H32*H$47*1000 -> 297000 | X9: =H9*H$24*1000 -> 0 | Y9: =SUM(S9:X9) -> 297000 | Z9: 0 | AA9: =SUM(Y9:Z9) -> 297000 | AB9: RMS01 | AC9: lb | AD9: =ROUND((S9/H$159)+(T9/H$159)+(U9/H$159)+(V9/H$159)+(W9/H$159)+(X9/H$159),0) -> 2000000 | AE9: =Y9/AD9 -> 0.1485 | AF9: =Y9/$AF$24/1000 -> 0.1485 | AG9: 0.019544347 | AH9: =IF($AF$21<$AG$21,AF9,IF($AF$12<$AG$12,AF9,IF(AND($AF$12>$AG$12,$AF$20<$AG$20),($AG$12+($AG$20-$AF$20))/$AF$12*AF9,AF9/$AF$12*$AG$12))) -> 0.062162764 | AI9: =AH9*$Y$24*1000 -> 124325.53 | AJ9: =AI9/AD9 -> 0.062162764 | AK9: =Y9-AI9 -> 172674.47 | AL9: =S9/$AE9 -> 0 | AM9: =T9/$AE9 -> 0 | AN9: =U9/$AE9 -> 0 | AO9: =V9/$AE9 -> 0 | AP9: =W9/$AE9 -> 2000000 | AQ9: =X9/$AE9 -> 0 | AR9: =IF($B$24<>0,ROUND(AL9/B$24,3),0) -> 0 | AS9: =ROUND(AM9/B$47,3) -> #DIV/0! | AT9: =IF(E$47<>0,ROUND(AN9/E$47,3),0) -> 0 | AU9: =IF(E$24<>0,ROUND(AO9/E$24,3),0) -> 0 | AV9: =IF(H$47<>0,ROUND(AP9/H$47,3),0) -> 1000 | AW9: =IF(H$24<>0,ROUND(AQ9/H$24,3),0) -> 0 | AX9: =AJ9*10000 -> 621.62764
A10: Manufacturing Supplies | B10: =IF($B$24<>0,$H$163,0) -> 0 | D10: 0 | E10: =IF(E24<>0,$H$163,0) -> 0 | F10: 0.00073336258 | G10: 0.00065789474 | H10: =IF($H$24<>0,$H$163,0) -> 0 | J10: 0 | S10: =B10*B$24*1000 -> 0 | T10: =B33*B$47*1000 -> 0 | U10: =E33*E$47*1000 -> 0 | V10: =E10*E$24*1000 -> 0 | W10: =H33*H$47*1000 -> 16862 | X10: =H10*H$24*1000 -> 0 | Y10: =SUM(S10:X10) -> 16862 | Z10: 0 | AA10: =SUM(Y10:Z10) -> 16862 | AB10: MFG01 | AC10: lb | AD10: =ROUND((S10/H$163)+(T10/H$163)+(U10/H$163)+(V10/H$163)+(W10/H$163)+(X10/H$163),0) -> 2000000 | AE10: =Y10/AD10 -> 0.008431 | AF10: =Y10/$AF$24/1000 -> 0.008431 | AG10: 0.0012510769 | AH10: =IF($AF$21<$AG$21,AF10,IF($AF$12<$AG$12,AF10,IF(AND($AF$12>$AG$12,$AF$20<$AG$20),($AG$12+($AG$20-$AF$20))/$AF$12*AF10,AF10/$AF$12*$AG$12))) -> 0.0035292543 | AI10: =AH10*$Y$24*1000 -> 7058.5086 | AJ10: =AI10/AD10 -> 0.0035292543 | AK10: =Y10-AI10 -> 9803.4914 | AL10: =S10/$AE10 -> 0 | AM10: =T10/$AE10 -> 0 | AN10: =U10/$AE10 -> 0 | AO10: =V10/$AE10 -> 0 | AP10: =W10/$AE10 -> 2000000 | AQ10: =X10/$AE10 -> 0 | AR10: =IF($B$24<>0,ROUND(AL10/B$24,3),0) -> 0 | AS10: =ROUND(AM10/B$47,3) -> #DIV/0! | AT10: =IF(E$47<>0,ROUND(AN10/E$47,3),0) -> 0 | AU10: =IF(E$24<>0,ROUND(AO10/E$24,3),0) -> 0 | AV10: =IF(H$47<>0,ROUND(AP10/H$47,3),0) -> 1000 | AW10: =IF(H$24<>0,ROUND(AQ10/H$24,3),0) -> 0 | AX10: =AJ10*10000 -> 35.292543
A11: Other variable | B11: =IF($B$24<>0,$H$166,0) -> 0 | D11: 0 | E11: =IF(E24<>0,$H$166,0) -> 0 | F11: 0.010235236 | G11: 0.0046052632 | H11: =IF($H$24<>0,$H$166,0) -> 0 | J11: 0 | S11: =B11*B$24*1000 -> 0 | T11: =B34*B$47*1000 -> 0 | U11: =E34*E$47*1000 -> 0 | V11: =E11*E$24*1000 -> 0 | W11: =H34*H$47*1000 -> 66000 | X11: =H11*H$24*1000 -> 0 | Y11: =SUM(S11:X11) -> 66000 | Z11: 0 | AA11: =SUM(Y11:Z11) -> 66000 | AB11: VAR01 | AC11: lb | AD11: =ROUND((S11/H$166)+(T11/H$166)+(U11/H$166)+(V11/H$166)+(W11/H$166)+(X11/H$166),0) -> 2000000 | AE11: =Y11/AD11 -> 0.033 | AF11: =Y11/$AF$24/1000 -> 0.033 | AG11: 0.0037333371 | AH11: =IF($AF$21<$AG$21,AF11,IF($AF$12<$AG$12,AF11,IF(AND($AF$12>$AG$12,$AF$20<$AG$20),($AG$12+($AG$20-$AF$20))/$AF$12*AF11,AF11/$AF$12*$AG$12))) -> 0.013813948 | AI11: =AH11*$Y$24*1000 -> 27627.895 | AJ11: =AI11/AD11 -> 0.013813948 | AK11: =Y11-AI11 -> 38372.105 | AL11: =S11/$AE11 -> 0 | AM11: =T11/$AE11 -> 0 | AN11: =U11/$AE11 -> 0 | AO11: =V11/$AE11 -> 0 | AP11: =W11/$AE11 -> 2000000 | AQ11: =X11/$AE11 -> 0 | AR11: =IF($B$24<>0,ROUND(AL11/B$24,3),0) -> 0 | AS11: =ROUND(AM11/B$47,3) -> #DIV/0! | AT11: =IF(E$47<>0,ROUND(AN11/E$47,3),0) -> 0 | AU11: =IF(E$24<>0,ROUND(AO11/E$24,3),0) -> 0 | AV11: =IF(H$47<>0,ROUND(AP11/H$47,3),0) -> 1000 | AW11: =IF(H$24<>0,ROUND(AQ11/H$24,3),0) -> 0 | AX11: =AJ11*10000 -> 138.13948
A12: Total Variable Costs | B12: =SUM(B6:B11) -> 0 | D12: =SUM(D6:D11) -> 0 | E12: =SUM(E6:E11) -> 0 | F12: =SUM(F6:F11) -> 0.30531947 | G12: =SUM(G6:G11) -> 0.11520496 | H12: =SUM(H6:H11) -> 0 | J12: =SUM(J6:J11) -> 0 | S12: =SUM(S7:S11) -> 0 | T12: =SUM(T7:T11) -> 0 | U12: =SUM(U7:U11) -> 0 | V12: =SUM(V7:V11) -> 0 | W12: =SUM(W7:W11) -> 389028.14 | X12: =SUM(X7:X11) -> 0 | Y12: =SUM(Y7:Y11) -> 389028.14 | Z12: =SUM(Z7:Z11) -> 0 | AA12: =SUM(AA7:AA11) -> 389028.14 | AF12: =SUM(AF7:AF11) -> 0.19451407 | AG12: =SUM(AG7:AG11) -> 0.081424459 | AH12: =SUM(AH7:AH11) -> 0.081424459 | AI12: =SUM(AI7:AI11) -> 162848.92 | AK12: =SUM(AK7:AK11) -> 226179.22
A14: Production Labor | B14: =IF($B$24<>0,$F$112/$B$49/1000,0) -> 0 | D14: 0 | E14: =IF(E24<>0,$F$112/$B$49/1000,0) -> 0 | F14: 0.055685781 | G14: 0.02638428 | H14: =IF($H$24<>0,$F$112/$B$49/1000,0) -> 0 | J14: 0 | S14: =B14*B$24*1000 -> 0 | T14: =B37*B$47*1000 -> 0 | U14: =E37*E$47*1000 -> 0 | V14: =E14*E$24*1000 -> 0 | W14: =H37*H$47*1000 -> 24508.336 | X14: =H14*H$24*1000 -> 0 | Y14: =SUM(S14:X14) -> 24508.336 | Z14: =-$D$115 -> 0 | AA14: =SUM(Y14:Z14) -> 24508.336 | AB14: DLAB01 | AC14: hr | AD14: =ROUND((S14/C$116)+(T14/C$116)+(U14/C$116)+(V14/C$116)+(W14/C$116)+(X14/C$116),0) -> #DIV/0! | AE14: =Y14/AD14 -> #DIV/0! | AF14: =Y14/$AF$24/1000 -> 0.012254168 | AG14: 0.011488554 | AH14: =IF($AF$21<$AG$21,AF14,IF($AF$20<$AG$20,AF14,IF(AND($AF$20>$AG$20,$AF$12<$AG$12),($AG$20+($AG$12-$AF$12))/$AF$20*AF14,AF14/$AF$20*$AG$20))) -> 0.01205584 | AI14: =AH14*$Y$24*1000 -> 24111.68 | AJ14: =AI14/AD14 -> #DIV/0! | AK14: =Y14-AI14 -> 396.65529 | AL14: =ROUND(S14/$C116,0) -> #DIV/0! | AM14: =ROUND(T14/$C116,0) -> #DIV/0! | AN14: =ROUND(U14/$C116,0) -> #DIV/0! | AO14: =ROUND(V14/$C116,0) -> #DIV/0! | AP14: =ROUND(W14/$C116,0) -> #DIV/0! | AQ14: =ROUND(X14/$C116,0) -> #DIV/0! | AR14: =IF($B$24<>0,ROUND(AL14/B$24,3),0) -> 0 | AS14: =ROUND(AM14/B$47,3) -> #DIV/0! | AT14: =IF(E$47<>0,ROUND(AN14/E$47,3),0) -> 0 | AU14: =IF(E$24<>0,ROUND(AO14/E$24,3),0) -> 0 | AV14: =IF(H$47<>0,ROUND(AP14/H$47,3),0) -> #DIV/0! | AW14: =IF(H$24<>0,ROUND(AQ14/H$24,3),0) -> 0 | AX14: =AJ14*10000 -> #DIV/0!
A15: Repairs & Maintenance Labor | B15: =IF($B$24<>0,$F$113/$B$49/1000,0) -> 0 | D15: 0 | E15: =IF(E24<>0,$F$113/$B$49/1000,0) -> 0 | F15: 0.019535758 | G15: 0.00902044 | H15: =IF($H$24<>0,$F$113/$B$49/1000,0) -> 0 | J15: 0 | S15: =B15*B$24*1000 -> 0 | T15: =B38*B$47*1000 -> 0 | U15: =E38*E$47*1000 -> 0 | V15: =E15*E$24*1000 -> 0 | W15: =H38*H$47*1000 -> 24508.336 | X15: =H15*H$24*1000 -> 0 | Y15: =SUM(S15:X15) -> 24508.336 | Z15: =-$H$115 -> 0 | AA15: =SUM(Y15:Z15) -> 24508.336 | AB15: MLAB01 | AC15: hr | AD15: =ROUND((S15/G$116)+(T15/G$116)+(U15/G$116)+(V15/G$116)+(W15/G$116)+(X15/G$116),0) -> #DIV/0! | AE15: =Y15/AD15 -> #DIV/0! | AF15: =Y15/$AF$24/1000 -> 0.012254168 | AG15: 0.007650221 | AH15: =IF($AF$21<$AG$21,AF15,IF($AF$20<$AG$20,AF15,IF(AND($AF$20>$AG$20,$AF$12<$AG$12),($AG$20+($AG$12-$AF$12))/$AF$20*AF15,AF15/$AF$20*$AG$20))) -> 0.01205584 | AI15: =AH15*$Y$24*1000 -> 24111.68 | AJ15: =AI15/AD15 -> #DIV/0! | AK15: =Y15-AI15 -> 396.65529 | AL15: =ROUND(S15/$G$116,0) -> #DIV/0! | AM15: =ROUND(T15/$G$116,0) -> #DIV/0! | AN15: =ROUND(U15/$G$116,0) -> #DIV/0! | AO15: =ROUND(V15/$G$116,0)-1 -> #DIV/0! | AP15: =ROUND(W15/$G$116,0) -> #DIV/0! | AQ15: =ROUND(X15/$G$116,0) -> #DIV/0! | AR15: =IF($B$24<>0,ROUND(AL15/B$24,3),0) -> 0 | AS15: =ROUND(AM15/B$47,3) -> #DIV/0! | AT15: =IF(E$47<>0,ROUND(AN15/E$47,3),0) -> 0 | AU15: =IF(E$24<>0,ROUND(AO15/E$24,3),0) -> 0 | AV15: =IF(H$47<>0,ROUND(AP15/H$47,3),0) -> #DIV/0! | AW15: =IF(H$24<>0,ROUND(AQ15/H$24,3),0) -> 0 | AX15: =AJ15*10000 -> #DIV/0!
A16: Indirect Payroll Costs (Benefits) | B16: =IF(B24<>0,$F$115/$B$49/1000,0) -> 0 | D16: 0 | E16: =IF(E24<>0,$F$115/$B$49/1000,0) -> 0 | F16: 0.01706523 | G16: 0.013928937 | H16: =IF($H$24<>0,$F$115/$B$49/1000,0) -> 0 | J16: 0 | S16: =B16*B$24*1000 -> 0 | T16: =B39*B$47*1000 -> 0 | U16: =E39*E$47*1000 -> 0 | V16: =E16*E$24*1000 -> 0 | W16: =H39*H$47*1000 -> 16851.201 | X16: =H16*H$24*1000 -> 0 | Y16: =SUM(S16:X16) -> 16851.201 | Z16: =-$D$122 -> 0 | AA16: =SUM(Y16:Z16) -> 16851.201 | AB16: IPC01 | AC16: hr | AD16: =ROUND((S16/C$123)+(T16/C$123)+(U16/C$123)+(V16/C$123)+(W16/C$123)+(X16/C$123),0) -> #DIV/0! | AE16: =Y16/AD16 -> #DIV/0! | AF16: =Y16/$AF$24/1000 -> 0.0084256007 | AG16: 0.0088563301 | AH16: =IF($AF$21<$AG$21,AF16,IF($AF$20<$AG$20,AF16,IF(AND($AF$20>$AG$20,$AF$12<$AG$12),($AG$20+($AG$12-$AF$12))/$AF$20*AF16,AF16/$AF$20*$AG$20))) -> 0.0082892365 | AI16: =AH16*$Y$24*1000 -> 16578.473 | AJ16: =AI16/AD16 -> #DIV/0! | AK16: =Y16-AI16 -> 272.72836 | AL16: =ROUND(S16/$C123,0) -> #DIV/0! | AM16: =ROUND(T16/$C123,0) -> #DIV/0! | AN16: =ROUND(U16/$C123,0) -> #DIV/0! | AO16: =ROUND(V16/$C123,0) -> #DIV/0! | AP16: =ROUND(W16/$C123,0) -> #DIV/0! | AQ16: =ROUND(X16/$C123,0) -> #DIV/0! | AR16: =IF($B$24<>0,ROUND(AL16/B$24,3),0) -> 0 | AS16: =ROUND(AM16/B$47,3) -> #DIV/0! | AT16: =IF(E$47<>0,ROUND(AN16/E$47,3),0) -> 0 | AU16: =IF(E$24<>0,ROUND(AO16/E$24,3),0) -> 0 | AV16: =IF(H$47<>0,ROUND(AP16/H$47,3),0) -> #DIV/0! | AW16: =IF(H$24<>0,ROUND(AQ16/H$24,3),0) -> 0 | AX16: =AJ16*10000 -> #DIV/0!
A17: Supervision | B17: =IF($B$24<>0,$F$114/$B$49/1000,0) -> 0 | D17: 0 | E17: =IF(E24<>0,$F$114/$B$49/1000,0) -> 0 | F17: 0.0045810516 | G17: 0.0015771316 | H17: =IF($H$24<>0,$F$114/$B$49/1000,0) -> 0 | J17: 0 | S17: =B17*B$24*1000 -> 0 | T17: =B40*B$47*1000 -> 0 | U17: =E40*E$47*1000 -> 0 | V17: =E17*E$24*1000 -> 0 | W17: =H40*H$47*1000 -> 7154 | X17: =H17*H$24*1000 -> 0 | Y17: =SUM(S17:X17) -> 7154 | Z17: =C176/($C$184+$C$185)*$C$185 -> 0 | AA17: =SUM(Y17:Z17) -> 7154 | AB17: SUP01 | AC17: lb | AD17: =ROUND((S17/F$176)+(T17/F$176)+(U17/F$176)+(V17/F$176)+(W17/F$176)+(X17/F$176),0) -> #DIV/0! | AE17: =Y17/AD17 -> #DIV/0! | AF17: =Y17/$AF$24/1000 -> 0.003577 | AG17: 0.0021273119 | AH17: =IF($AF$21<$AG$21,AF17,IF($AF$20<$AG$20,AF17,IF(AND($AF$20>$AG$20,$AF$12<$AG$12),($AG$20+($AG$12-$AF$12))/$AF$20*AF17,AF17/$AF$20*$AG$20))) -> 0.003519108 | AI17: =AH17*$Y$24*1000 -> 7038.216 | AJ17: =AI17/AD17 -> #DIV/0! | AK17: =Y17-AI17 -> 115.78395 | AL17: =S17/$AE17 -> #DIV/0! | AM17: =T17/$AE17 -> #DIV/0! | AN17: =U17/$AE17 -> #DIV/0! | AO17: =V17/$AE17 -> #DIV/0! | AP17: =W17/$AE17 -> #DIV/0! | AQ17: =X17/$AE17 -> #DIV/0! | AR17: =IF($B$24<>0,ROUND(AL17/B$24,3),0) -> 0 | AS17: =ROUND(AM17/B$47,3) -> #DIV/0! | AT17: =IF(E$47<>0,ROUND(AN17/E$47,3),0) -> 0 | AU17: =IF(E$24<>0,ROUND(AO17/E$24,3),0) -> 0 | AV17: =IF(H$47<>0,ROUND(AP17/H$47,3),0) -> #DIV/0! | AW17: =IF(H$24<>0,ROUND(AQ17/H$24,3),0) -> 0 | AX17: =AJ17*10000 -> #DIV/0!
A18: Depreciation | B18: =IF($B$24<>0,$B$178/$B$49/1000,0) -> 0 | D18: 0 | E18: =IF(E24<>0,$B$178/$B$49/1000,0) -> 0 | F18: 0.0038559807 | G18: 0.0016578947 | H18: =IF($H$24<>0,$B$178/$B$49/1000,0) -> 0 | J18: 0 | S18: =B18*B$24*1000 -> 0 | T18: =B41*B$47*1000 -> 0 | U18: =E41*E$47*1000 -> 0 | V18: =E18*E$24*1000 -> 0 | W18: =H41*H$47*1000 -> 25872 | X18: =H18*H$24*1000 -> 0 | Y18: =SUM(S18:X18) -> 25872 | Z18: =C178/($C$184+$C$185)*$C$185 -> 0 | AA18: =SUM(Y18:Z18) -> 25872 | AB18: DEP01 | AC18: lb | AD18: =ROUND((S18/F$178)+(T18/F$178)+(U18/F$178)+(V18/F$178)+(W18/F$178)+(X18/F$178),0) -> 166667 | AE18: =Y18/AD18 -> 0.15523169 | AF18: =Y18/$AF$24/1000 -> 0.012936 | AG18: 0.032747211 | AH18: =IF($AF$21<$AG$21,AF18,IF($AF$20<$AG$20,AF18,IF(AND($AF$20>$AG$20,$AF$12<$AG$12),($AG$20+($AG$12-$AF$12))/$AF$20*AF18,AF18/$AF$20*$AG$20))) -> 0.012726637 | AI18: =AH18*$Y$24*1000 -> 25453.274 | AJ18: =AI18/AD18 -> 0.15271934 | AK18: =Y18-AI18 -> 418.72552 | AL18: =S18/$AE18 -> 0 | AM18: =T18/$AE18 -> 0 | AN18: =U18/$AE18 -> 0 | AO18: =V18/$AE18 -> 0 | AP18: =W18/$AE18 -> 166667 | AQ18: =X18/$AE18 -> 0 | AR18: =IF($B$24<>0,ROUND(AL18/B$24,3),0) -> 0 | AS18: =ROUND(AM18/B$47,3) -> #DIV/0! | AT18: =IF(E$47<>0,ROUND(AN18/E$47,3),0) -> 0 | AU18: =IF(E$24<>0,ROUND(AO18/E$24,3),0) -> 0 | AV18: =IF(H$47<>0,ROUND(AP18/H$47,3),0) -> 83.334 | AW18: =IF(H$24<>0,ROUND(AQ18/H$24,3),0) -> 0 | AX18: =AJ18*10000 -> 1527.1934
A19: Insurance & Taxes | B19: =IF($B$24<>0,$B$177/$B$49/1000,0) -> 0 | D19: 0 | E19: =IF(E24<>0,$B$177/E26/1000,0) -> 0 | F19: 0.010801566 | G19: 0.0058026316 | H19: =IF($H$24<>0,$B$177/$B$49/1000,0) -> 0 | J19: 0 | S19: =B19*B$24*1000 -> 0 | T19: =B42*B$47*1000 -> 0 | U19: =E42*E$47*1000 -> 0 | V19: =E19*E$24*1000 -> 0 | W19: =H42*H$47*1000 -> 43878 | X19: =H19*H$24*1000 -> 0 | Y19: =SUM(S19:X19) -> 43878 | Z19: =C177/($C$184+$C$185)*$C$185 -> 0 | AA19: =SUM(Y19:Z19) -> 43878 | AB19: INS01 | AC19: lb | AD19: =ROUND((S19/F$177)+(T19/F$177)+(U19/F$177)+(V19/F$177)+(W19/F$177)+(X19/F$177),0) -> 166667 | AE19: =Y19/AD19 -> 0.26326747 | AF19: =Y19/$AF$24/1000 -> 0.021939 | AG19: 0.0073609622 | AH19: =IF($AF$21<$AG$21,AF19,IF($AF$20<$AG$20,AF19,IF(AND($AF$20>$AG$20,$AF$12<$AG$12),($AG$20+($AG$12-$AF$12))/$AF$20*AF19,AF19/$AF$20*$AG$20))) -> 0.021583928 | AI19: =AH19*$Y$24*1000 -> 43167.856 | AJ19: =AI19/AD19 -> 0.25900662 | AK19: =Y19-AI19 -> 710.14373 | AL19: =S19/$AE19 -> 0 | AM19: =T19/$AE19 -> 0 | AN19: =U19/$AE19 -> 0 | AO19: =V19/$AE19 -> 0 | AP19: =W19/$AE19 -> 166667 | AQ19: =X19/$AE19 -> 0 | AR19: =IF($B$24<>0,ROUND(AL19/B$24,3),0) -> 0 | AS19: =ROUND(AM19/B$47,3) -> #DIV/0! | AT19: =IF(E$47<>0,ROUND(AN19/E$47,3),0) -> 0 | AU19: =IF(E$24<>0,ROUND(AO19/E$24,3),0) -> 0 | AV19: =IF(H$47<>0,ROUND(AP19/H$47,3),0) -> 83.334 | AW19: =IF(H$24<>0,ROUND(AQ19/H$24,3),0) -> 0 | AX19: =AJ19*10000 -> 2590.0662
A20: Total Fixed Costs | B20: =SUM(B14:B19) -> 0 | C20: =SUM(C14:C19) -> 0 | D20: =SUM(D14:D19) -> 0 | E20: =SUM(E14:E19) -> 0 | F20: =SUM(F14:F19) -> 0.11152537 | G20: =SUM(G14:G19) -> 0.058371315 | H20: =SUM(H14:H19) -> 0 | I20: =SUM(I14:I19) -> 0 | J20: =SUM(J14:J19) -> 0 | S20: =SUM(S14:S19) -> 0 | T20: =SUM(T14:T19) -> 0 | U20: =SUM(U14:U19) -> 0 | V20: =SUM(V14:V19) -> 0 | W20: =SUM(W14:W19) -> 142771.87 | X20: =SUM(X14:X19) -> 0 | Y20: =SUM(Y14:Y19) -> 142771.87 | Z20: =SUM(Z14:Z19) -> 0 | AA20: =SUM(AA14:AA19) -> 142771.87 | AF20: =SUM(AF14:AF19) -> 0.071385936 | AG20: =SUM(AG14:AG19) -> 0.07023059 | AH20: =SUM(AH14:AH19) -> 0.07023059 | AI20: =SUM(AI14:AI19) -> 140461.18 | AK20: =SUM(AK14:AK19) -> 2310.6921
A21: Excess Costs | C21: -0.0273 | F21: -0.050457361 | S21: =S12+S20 -> 0 | T21: =T12+T20 -> 0 | U21: =U12+U20 -> 0 | V21: =V12+V20 -> 0 | W21: =W12+W20 -> 531800.01 | X21: =X12+X20 -> 0 | Y21: =Y12+Y20 -> 531800.01 | Z21: =Z12+Z20 -> 0 | AA21: =AA12+AA20 -> 531800.01 | AB21: CCtr Total | AF21: =AF12+AF20 -> 0.2659 | AG21: =AG12+AG20 -> 0.15165505 | AH21: =AH12+AH20 -> 0.15165505 | AI21: =AI12+AI20 -> 303310.1 | AK21: =AK12+AK20 -> 228489.91
A22: TOTAL COSTS PER POUND | B22: =B12+B20 -> 0 | C22: =+C20+C21+C12 -> -0.0273 | D22: =D12+D20 -> 0 | E22: =E12+E20 -> 0 | F22: =F12+F20+F21 -> 0.36638748 | G22: =G12+G20 -> 0.17357627 | H22: =H12+H20 -> 0 | I22: =I12+I20 -> 0 | J22: =J12+J20 -> 0 | S22: =IF(B24<>0,ROUND(S21/(B24*1000),5),0) -> 0 | T22: =IF(B47<>0,ROUND(T21/(B47*1000),5),0) -> 0 | U22: =IF(E47<>0,ROUND(U21/(E47*1000),5),0) -> 0 | V22: =IF(E24<>0,ROUND(V21/(E24*1000),5),0) -> 0 | W22: =IF(H47<>0,ROUND(W21/(H47*1000),5),0) -> 0.2659 | X22: =IF(H24<>0,ROUND(X21/(H24*1000),5),0) -> 0 | Y22: =Y21/Y24/1000 -> 0.2659 | Z22: 0 | AA22: =ROUND(AA21/(B49*1000),5) -> 0.2659 | AB22: Excl Matl | AI22: =AI21/AI24/1000 -> 0.15165505 | AK22: =AK21/AK24/1000 -> 0.11424496
S23: =ROUND(S22+B6,5) -> 0 | T23: =ROUND(T22+B29,5) -> 0 | U23: =ROUND(U22+E29,5) -> 0 | V23: =ROUND(V22+E6,5) -> 0 | W23: =ROUND(W22+H29,5) -> 0.3459 | X23: =ROUND(X22+H6,5) -> 0 | Y23: =Y22+(($B$6*$B$24*1000+$B$29*$B$47*1000+$E$29*$E$47*1000+$H$6*$H$24*1000+$H$29*$H$47*1000+$E$6*$E$24*1000)/($B$49*1000)) -> 0.3459 | Z23: 0 | AA23: =AA22+(($B$6*$B$24*1000+$B$29*$B$47*1000+$E$6*$E$24*1000+$E$29*$E$47*1000+$H$6*$H$24*1000+$H$29*$H$47*1000)/($B$49*1000)) -> 0.3459 | AB23: Incl Matl
A24: PRODUCTION ( in 000 lbs ) | B24: =B54 -> 0 | C24: 6211 | D24: 0 | E24: =B57 -> 0 | F24: 3204 | G24: 51000 | H24: =B58 -> 0 | I24: 4207 | J24: 0 | S24: =B24 -> 0 | T24: =B47 -> 0 | U24: =E47 -> 0 | V24: =E24 -> 0 | W24: =H47 -> 2000 | X24: =H24 -> 0 | Y24: =SUM(S24:X24) -> 2000 | Z24: 0 | AA24: =SUM(Y24:Z24) -> 2000 | AF24: =Y24 -> 2000 | AI24: =Y24 -> 2000 | AK24: =Y24 -> 2000
B26: CP | E26: HSP | H26: Nanomite C | AS26: 0.936
B27: =B4 -> 25 Standard | C27: 23 Actual | D27: =+D4 -> 22 Standard | E27: =E4 -> 25 Standard | F27: =+C27 -> 23 Actual | G27: =+D27 -> 22 Standard | H27: =H4 -> 25 Standard | I27: 23 Actual | J27: =+J4 -> 22 Standard | AS27: 0.264
C28: (Jan-Aug) | F28: (Jan-Aug) | I28: (Jan-Aug) | AS28: 286
A29: Materials | B29: =IF($B$47<>0,$D$88,0) -> 0 | C29: 0.1396 | D29: 0.06037434 | E29: =IF(E47<>0,$D$88,0) -> 0 | F29: 0.0865 | G29: 0 | H29: =IF(H47<>0,$L$80,0) -> 0.08 | I29: 0.0792 | J29: 0.02 | AS29: 8000
A30: Electricity | B30: =IF(B47<>0,$D$151,0) -> 0 | C30: 0.0273 | D30: 0.018883379 | E30: =IF(E47<>0,$G$151,0) -> 0 | F30: 0.0294 | G30: 0 | H30: =IF(H47<>0,$J$151,0) -> 0.0045830677 | I30: 0.0124 | J30: 0.0027366213 | AS30: 1.2
A31: Gas | B31: =IF(B47<>0,$D$152,0) -> 0 | C31: 0.0379 | D31: 0.04184 | E31: =IF(E47<>0,$G$152,0) -> 0 | F31: 0.0465 | G31: 0 | H31: =IF(H47<>0,$J$152,0) -> 0 | I31: 0 | J31: 0
