Workbook

Sheet NI RC 2025 Std
A1: New Iberia Resin Coating
A2: 2025 STANDARDS
B3: CARBOBond Lite | E3: CARBOBond Lite EU | H3: CARBOBond KSLD | K3: RPM LITE / NEUTRAPROP LWC | N3: CARBOBond HSP | Q3: CARBO AIR
B4: 24 Standard | C4: 23 Actual | D4: 22 Standard | E4: 24 Standard | F4: 23 Actual | G4: 22 Standard | H4: 24 Standard | I4: 23 Actual | J4: 22 Standard | K4: 24 Standard | L4: 23 Actual | M4: 22 Standard | N4: 24 Standard | O4: 23 Actual | P4: 22 Standard | Q4: 24 Standard | R4: 23 Actual | S4: =+D4 -> 22 Standard
C5: Jan | F5: Jan | I5: (Aug) | L5: (Jan) | O5: (Aug) | R5: (Jan-Aug)
A6: Materials - Substrate | B6: =E119 -> 0.21293144 | C6: 0.261 | D6: 0.1639529 | E6: =G119 -> 0.21706426 | F6: 0.259 | G6: 0.18884365 | H6: =+I119 -> 0.52154785 | I6: 0.4369 | J6: 0.41938749 | K6: =K119 -> 0.2149 | L6: 0.1827 | M6: 0.15362762 | N6: =+M100 -> 0 | O6: 0.431 | P6: 0.80389422 | Q6: =+O98 -> 0.30469739 | R6: 0.15968841 | S6: 0.19086145
A7: Materials - Substrate Under-Absorption | B7: =$C97*D97 -> 0 | D7: 0 | E7: =$C97*F97 -> 0 | G7: 0 | H7: =$C97*I97 -> 0 | J7: 0 | K7: =$C97*J97 -> 0 | M7: 0.094857323 | N7: =$C97*O97 -> 0 | P7: 0
A8: Materials - Resin & Chemicals | B8: =E120+E121 -> 0.050440017 | C8: 0.0667 | D8: 0.038078 | E8: =G120+G121 -> 0.064046066 | F8: 0.0652 | G8: 0.060015662 | H8: =+I120+I121 -> 0.076234045 | I8: =0.5149-I6 -> 0.078 | J8: 0.056384154 | K8: =K120+K121 -> 0.2181838 | L8: =0.2569-L6 -> 0.0742 | M8: 0.15903358 | N8: =+M120+M121 -> 0.087444565 | O8: =0.5164-O6 -> 0.0854 | P8: 0.056384154 | Q8: =+O120+O121 -> 0.10145692 | R8: 0.072759577 | S8: 0.087415456
A9: Electricity | B9: =E164 -> 0.0083887564 | C9: 0.0019 | D9: 0.0059095494 | E9: =G164 -> 0.010531407 | F9: 0.0019 | G9: 0.0092314722 | H9: =J164 -> 0.06212471 | I9: 0.0088 | J9: 0.043221874 | K9: =K164 -> 0.018513164 | L9: 0.0117 | M9: 0.010135435 | N9: =+M164 -> 0.0088229437 | O9: 0.0088 | P9: 0.006738662 | Q9: =+O164 -> 0.011271451 | R9: 0.006525594 | S9: 0.0089969295
A10: Gas | B10: =E165 -> 0.0017786261 | C10: 0.004 | D10: 0.0013242333 | E10: =G165 -> 0.001820037 | F10: 0.0041 | G10: 0.00153375 | H10: =J165 -> 0.00023681914 | I10: 0.0038 | J10: 0.00029427407 | K10: =K165 -> 0.0012487474 | L10: 0.0011 | M10: 0.0011247591 | N10: =+M165 -> 0.0038181212 | O10: 0.0038 | P10: 0.0013537383 | Q10: =+O165 -> 0.0033852574 | R10: 0.0011625955 | S10: 0.0038428259
A11: R&M Supplies and Service | B11: =$H$180 -> 0.016297262 | C11: 0.0016 | D11: 0.006 | E11: =$H$180 -> 0.016297262 | F11: 0.0016 | G11: 0.0031413613 | H11: =$H$180 -> 0.016297262 | I11: 0.0094 | J11: 0.0031413613 | K11: =$H$180 -> 0.016297262 | L11: 0.0076 | M11: 0.0086705202 | N11: =$H$180 -> 0.016297262 | O11: 0.0094 | P11: 0.0031413613 | Q11: =$H$180 -> 0.016297262 | R11: 0.016241103 | S11: 0.0031413613
A12: Manufacturing Supplies | B12: =$H$183 -> 0.001303781 | C12: 0 | D12: 0.002 | E12: =$H$183 -> 0.001303781 | F12: 0 | G12: 0.0002617801 | H12: =$H$183 -> 0.001303781 | I12: 0.0003 | J12: 0.0002617801 | K12: =$H$183 -> 0.001303781 | L12: 0.0002 | M12: 0.00043352601 | N12: =$H$183 -> 0.001303781 | O12: 0.0003 | P12: 0.0002617801 | Q12: =$H$183 -> 0.001303781 | R12: 0.00053366327 | S12: 0.0002617801
A13: Other variable | B13: =$H$186 -> 0.022816167 | C13: 0.005 | D13: 0.006 | E13: =$H$186 -> 0.022816167 | F13: 0.0052 | G13: 0.0039267016 | H13: =$H$186 -> 0.022816167 | I13: 0.0134 | J13: 0.0039267016 | K13: =$H$186 -> 0.022816167 | L13: 0.0035 | M13: 0.0057803468 | N13: =$H$186 -> 0.022816167 | O13: 0.0134 | P13: 0.0039267016 | Q13: =$H$186 -> 0.022816167 | R13: 0.0059964109 | S13: 0.0039267016
A14: Total Variable Costs | B14: =SUM(B6:B13) -> 0.31395605 | C14: =SUM(C6:C13) -> 0.3402 | D14: =SUM(D6:D13) -> 0.22326468 | E14: =SUM(E6:E13) -> 0.33387898 | F14: =SUM(F6:F13) -> 0.337 | G14: =SUM(G6:G13) -> 0.26695437 | H14: =SUM(H6:H13) -> 0.70056064 | I14: =SUM(I6:I13) -> 0.5506 | ... L14: =SUM(L6:L13) -> 0.281 | M14: 0.43366311 | N14: =SUM(N6:N13) -> 0.14050284 | O14: =SUM(O6:O13) -> 0.5521 | P14: =SUM(P6:P13) -> 0.87570062 | Q14: =SUM(Q6:Q13) -> 0.46122824 | R14: =SUM(R6:R13) -> 0.26290735 | S14: 0.33373539
A16: Production Labor | B16: =$D$217/$B$64/1000 -> 0.048558141 | C16: 0.0165 | D16: 0.035940795 | E16: =$D$217/$B$64/1000 -> 0.048558141 | F16: 0.0165 | G16: 0.016663174 | H16: =$D$217/$B$64/1000 -> 0.048558141 | I16: 0.0283 | J16: 0.016663174 | K16: =$D$217/$B$64/1000 -> 0.048558141 | L16: 0.0095 | M16: 0.011741675 | N16: =$D$217/$B$64/1000 -> 0.048558141 | O16: 0.0283 | P16: 0.016663174 | Q16: =$D$217/$B$64/1000 -> 0.048558141 | R16: 0.013727223 | S16: 0.016663174
A17: Repairs & Maintenance Labor | B17: =$G$217/$B$64/1000 -> 0.015673026 | C17: 0.007 | D17: 0.0113712 | E17: =$G$217/$B$64/1000 -> 0.015673026 | F17: 0.007 | G17: 0.0040701571 | H17: =$G$217/$B$64/1000 -> 0.015673026 | I17: 0.0072 | J17: 0.0040701571 | K17: =$G$217/$B$64/1000 -> 0.015673026 | L17: 0.005 | M17: 0.0041080925 | N17: =$G$217/$B$64/1000 -> 0.015673026 | O17: 0.0072 | P17: 0.0040701571 | Q17: =$G$217/$B$64/1000 -> 0.015673026 | R17: 0.0016693747 | S17: 0.0040701571
A18: Indirect Payroll Costs (Benefits) | B18: =$J$217/$B$64/1000 -> 0.020872242 | C18: 0.0114 | D18: 0.014188877 | E18: =$J$217/$B$64/1000 -> 0.020872242 | F18: 0.0114 | G18: 0.0073786377 | H18: =$J$217/$B$64/1000 -> 0.020872242 | I18: 0.0071 | J18: 0.0073786377 | K18: =$J$217/$B$64/1000 -> 0.020872242 | L18: 0.0111 | M18: 0.0072598437 | N18: =$J$217/$B$64/1000 -> 0.020872242 | O18: 0.0071 | P18: 0.0073786377 | Q18: =$J$217/$B$64/1000 -> 0.020872242 | R18: 0.0056633179 | S18: 0.0073786377
A19: Supervision | B19: =$E$243 -> 0.0054291551 | C19: 0.035 | D19: 0 | E19: =$E$243 -> 0.0054291551 | F19: 0.0035 | G19: 0.0040554974 | H19: =$E$243 -> 0.0054291551 | I19: 0.002 | J19: 0.0040554974 | K19: =$E$243 -> 0.0054291551 | L19: 0.0073 | M19: 0.002449852 | N19: =$E$243 -> 0.0054291551 | O19: 0.002 | P19: 0.0040554974 | Q19: =$E$243 -> 0.0054291551 | R19: 0.0023710733 | S19: 0.0040554974
A20: Depreciation | B20: =$E$244 -> 0.0073063885 | C20: 0.0053 | D20: 0.01039048 | E20: =$E$244 -> 0.0073063885 | F20: 0.0053 | G20: 0.0029340314 | H20: =$E$244 -> 0.0073063885 | I20: 0.0038 | J20: 0.0029340314 | K20: =$E$244 -> 0.0073063885 | L20: 0.0058 | M20: 0.06367052 | N20: =$E$244 -> 0.0073063885 | O20: 0.0038 | P20: 0.0029340314 | Q20: =$E$244 -> 0.0073063885 | R20: 0.064182394 | S20: 0.0029340314
A21: Insurance & Taxes | B21: =$E$245 -> 0.02589309 | C21: 0.0168 | D21: 0.03763008 | E21: =$E$245 -> 0.02589309 | F21: 0.0168 | G21: 0.014736126 | H21: =$E$245 -> 0.02589309 | I21: 0.0135 | J21: 0.014736126 | K21: =$E$245 -> 0.02589309 | L21: 0.0037 | M21: 0.014046243 | N21: =$E$245 -> 0.02589309 | O21: 0.0135 | P21: 0.014736126 | Q21: =$E$245 -> 0.02589309 | R21: 0.015675972 | S21: 0.014736126
A22: Total Fixed Costs | B22: =SUM(B16:B21) -> 0.12373204 | C22: =SUM(C16:C21) -> 0.092 | D22: =SUM(D16:D21) -> 0.10952143 | E22: =SUM(E16:E21) -> 0.12373204 | F22: =SUM(F16:F21) -> 0.0605 | G22: =SUM(G16:G21) -> 0.049837623 | H22: =SUM(H16:H21) -> 0.12373204 | I22: =SUM(I16:I21) -> 0.0619 | ... L22: =SUM(L16:L21) -> 0.0424 | M22: 0.10327623 | N22: =SUM(N16:N21) -> 0.12373204 | O22: =SUM(O16:O21) -> 0.0619 | P22: =SUM(P16:P21) -> 0.049837623 | Q22: =SUM(Q16:Q21) -> 0.12373204 | R22: =SUM(R16:R21) -> 0.10328935 | S22: 0.10327623
A24: Total Cost per Pound at Gross | B24: =B14+B22 -> 0.43768809 | C24: =C14+C22 -> 0.4322 | D24: =D14+D22 -> 0.33278611 | E24: =E14+E22 -> 0.45761102 | F24: =F14+F22 -> 0.3975 | G24: =G14+G22 -> 0.316792 | H24: =H14+H22 -> 0.82429268 | I24: =I14+I22 -> 0.6125 | ... S24: =S14+S22 -> 0.43701161
A25: Less: Substrate Plant Under-absorption | B25: =-B7 -> 0 | D25: 0 | E25: =-E7 -> 0 | G25: 0 | H25: =-H7 -> 0 | J25: 0 | K25: =-K7 -> 0 | M25: 0 | N25: =-N7 -> 0 | Q25: =-Q7 -> 0 | S25: 0
A26: Less: RC Under-absorption | B26: 0 | C26: -0.079184632 | D26: 0 | E26: 0 | F26: 0 | G26: 0 | H26: 0 | I26: 0 | J26: 0 | K26: 0 | L26: 0 | M26: 0 | N26: 0 | O26: 0 | P26: 0 | Q26: 0 | R26: =IF(R9+R10+R11+R12+R13+R22>0.0498,0.0498-R9-R10-R11-R12-R13-R22,0) -> -0.083948722 | S26: 0
A27: Net Cost per Pound Absorbed | B27: =SUM(B24:B26) -> 0.43768809 | C27: =SUM(C24:C26) -> 0.35301537 | D27: =SUM(D24:D26) -> 0.33278611 | E27: =SUM(E24:E26) -> 0.45761102 | F27: =SUM(F24:F26) -> 0.3975 | G27: =SUM(G24:G26) -> 0.316792 | H27: =SUM(H24:H26) -> 0.82429268 | I27: =SUM(I24:I26) -> 0.6125 | ... S27: =SUM(S24:S26) -> 0.43701161
A29: Total Production (000 lbs) | B29: =+B79*0.5 -> 5250 | C29: 15431 | D29: 3000 | E29: =+B79*0.5 -> 5250 | F29: 9412 | G29: 25500 | H29: =+B81 -> 3000 | I29: 198 | J29: 300 | K29: =+B82 -> 90 | L29: 160 | M29: 1000 | N29: =+B80 -> 0 | O29: 827 | P29: 5000 | Q29: =+B84 -> 0 | R29: 3647.15 | S29: 1300
B34: Fusion | E34: ScaleGuard II CL | H34: KSXT | K34: ScaleGuard II KSHD (H) | N34: FilterGuard | Q34: XX
B35: 24 Standard | C35: 21 Actual | D35: 22 Standard | E35: 24 Standard | F35: 23 Actual | G35: 22 Standard | H35: 23 Standard | I35: 22 Actual | J35: =+D4 -> 22 Standard | K35: =+B4 -> 24 Standard | L35: 19 Actual | M35: =+D4 -> 22 Standard | N35: =+B4 -> 24 Standard | O35: XX Actual | P35: XX Standard | Q35: =+B4 -> 24 Standard | R35: 19 Actual | S35: =+D4 -> 22 Standard
C36: (Jul) | F36: (May) | I36: (Jan-Aug) | L36: (Jan-Sept)
A37: Materials - Substrate | B37: =E152 -> 0.34423291 | C37: 0.3421 | D37: 0.21326582 | E37: =G152 -> 0.63341571 | F37: 0.5729 | G37: 0.51387049 | H37: =I152 -> 0.4684443 | I37: 0.3911 | J37: 0 | L37: 0 | M37: 1.8829093 | N37: =+M152 -> 0.28401991 | O37: 0 | P37: 0 | R37: 0 | S37: 0
A38: Materials - Substrate Under-Absorption | B38: =$C137*D137 -> 0 | D38: 0 | E38: =$C134*F134 -> 0 | G38: 0 | H38: =$C129*H129 -> 0 | J38: 0 | M38: 0.16177979 | N38: 0 | P38: 0 | S38: 0
A39: Materials - Resin & Chemicals | B39: =E153+E154 -> 0.067817592 | C39: =0.4041-C37 -> 0.062 | D39: 0.067925472 | E39: =G153+G154 -> 0.053814952 | F39: 0.0496 | G39: 0.04253052 | H39: =I153+I154 -> 0.0065721369 | I39: 0.0058396524 | J39: 0 | L39: 0 | M39: 0.042578635 | N39: =+M153+M154 -> 0.78698195 | O39: 0 | P39: 0 | R39: 0 | S39: 0
A40: Electricity | B40: =E171 -> 0.01207814 | C40: 0.01 | D40: 0.009641779 | E40: =G171 -> 0.01384973 | F40: 0.0167 | G40: 0.0058784926 | H40: =I171 -> 0.0096111165 | I40: 0.017771324 | J40: 0 | L40: 0 | M40: 0.010135435 | N40: =M171 -> 0.046127878 | O40: 0 | P40: 0 | R40: 0 | S40: 0
A41: Gas | B41: =E172 -> 0.001583098 | C41: 0.002 | D41: 0.0017836723 | E41: =G172 -> 0.0027058421 | F41: 0.0011 | G41: 0.0012263426 | H41: =I172 -> 0.0013457382 | I41: 0.0036105204 | J41: 0 | L41: 0 | M41: 0.0011247591 | N41: =M172 -> 0.0020507934 | O41: 0 | P41: 0 | R41: 0 | S41: 0
A42: R&M Supplies and Service | B42: =$H$180 -> 0.016297262 | C42: 0.0036 | D42: 0.0031413613 | E42: =$H$180 -> 0.016297262 | F42: 0.0036 | G42: 0.0031413613 | H42: =$H$180 -> 0.016297262 | I42: 0.0059485597 | J42: 0 | L42: 0 | M42: 0.0086705202 | N42: =$H$180 -> 0.016297262 | O42: 0 | P42: 0 | R42: 0 | S42: 0
A43: Manufacturing Supplies | B43: =$H$183 -> 0.001303781 | C43: 0.0002 | D43: 0.0002617801 | E43: =$H$183 -> 0.001303781 | F43: 0 | G43: 0.0002617801 | H43: =$H$183 -> 0.001303781 | I43: 0.0009914408 | J43: 0 | L43: 0 | M43: 0.00043352601 | N43: =$H$183 -> 0.001303781 | O43: 0 | P43: 0 | R43: 0 | S43: 0
A44: Other variable | B44: =$H$186 -> 0.022816167 | C44: 0.0125 | D44: 0.0039267016 | E44: =$H$186 -> 0.022816167 | F44: 0.012 | G44: 0.0039267016 | H44: =$H$186 -> 0.022816167 | I44: 0.0092202407 | J44: 0 | L44: 0 | M44: 0.0057803468 | N44: =$H$186 -> 0.022816167 | O44: 0 | P44: 0 | R44: 0 | S44: 0
A45: Total Variable Costs | B45: =SUM(B37:B44) -> 0.46612895 | C45: =SUM(C37:C44) -> 0.4324 | D45: =SUM(D37:D44) -> 0.29994659 | E45: =SUM(E37:E44) -> 0.74420344 | F45: =SUM(F37:F44) -> 0.6559 | G45: =SUM(G37:G44) -> 0.57083569 | H45: =SUM(H37:H44) -> 0.5263905 | I45: =SUM(I37:I44) -> 0.43448174 | J45: =SUM(J37:J44) -> 0 | L45: =SUM(L37:L44) -> 0 | M45: 2.1134123 | N45: =SUM(N37:N44) -> 1.1595977 | O45: =SUM(O37:O44) -> 0 | P45: =SUM(P37:P44) -> 0 | R45: =SUM(R37:R44) -> 0 | S45: =SUM(S37:S44) -> 0
A47: Production Labor | B47: =$D$217/$B$64/1000 -> 0.048558141 | C47: 0.0172 | D47: 0.016663174 | E47: =$D$217/$B$64/1000 -> 0.048558141 | F47: 0.0253 | G47: 0.016663174 | H47: =$D$217/$B$64/1000 -> 0.048558141 | I47: 0.026626711 | J47: 0 | L47: 0 | M47: 0.011741675 | N47: =$D$217/$B$64/1000 -> 0.048558141 | O47: 0 | P47: 0 | R47: 0 | S47: 0
A48: Repairs & Maintenance Labor | B48: =$G$217/$B$64/1000 -> 0.015673026 | C48: 0.0064 | D48: 0.0040701571 | E48: =$G$217/$B$64/1000 -> 0.015673026 | F48: 0.0101 | G48: 0.0040701571 | H48: =$G$217/$B$64/1000 -> 0.015673026 | I48: 0.0076324228 | J48: 0 | L48: 0 | M48: 0.0041080925 | N48: =$G$217/$B$64/1000 -> 0.015673026 | O48: 0 | P48: 0 | R48: 0 | S48: 0
A49: Indirect Payroll Costs (Benefits) | B49: =$J$217/$B$64/1000 -> 0.020872242 | C49: 0.0084 | D49: 0.0073786377 | E49: =$J$217/$B$64/1000 -> 0.020872242 | F49: 0.012 | G49: 0.0073786377 | H49: =$J$217/$B$64/1000 -> 0.020872242 | I49: 0.011265424 | J49: 0 | L49: 0 | M49: 0.0072598437 | N49: =$J$217/$B$64/1000 -> 0.020872242 | O49: 0 | P49: 0 | R49: 0 | S49: 0
A50: Supervision | B50: =$E$243 -> 0.0054291551 | C50: 0.0078 | D50: 0.0040554974 | E50: =$E$243 -> 0.0054291551 | F50: 0 | G50: 0.0040554974 | H50: =$E$243 -> 0.0054291551 | I50: 0.0064561315 | J50: 0 | L50: 0 | M50: 0.002449852 | N50: =$E$243 -> 0.0054291551 | O50: 0 | P50: 0 | R50: 0 | S50: 0
A51: Depreciation | B51: =$E$244 -> 0.0073063885 | C51: 0.0058 | D51: 0.0029340314 | E51: =$E$244 -> 0.0073063885 | F51: 0.0076 | G51: 0.0029340314 | H51: =$E$244 -> 0.0073063885 | I51: 0.0050242986 | J51: 0 | L51: 0 | M51: 0.06367052 | N51: =$E$244 -> 0.0073063885 | O51: 0 | P51: 0 | R51: 0 | S51: 0
A52: Insurance & Taxes | B52: =$E$245 -> 0.02589309 | C52: 0.0291 | D52: 0.014736126 | E52: =$E$245 -> 0.02589309 | F52: 0.025 | G52: 0.014736126 | H52: =$E$245 -> 0.02589309 | I52: 0.017794205 | J52: 0 | L52: 0 | M52: 0.014046243 | N52: =$E$245 -> 0.02589309 | O52: 0 | P52: 0 | R52: 0 | S52: 0
A53: Total Fixed Costs | B53: =SUM(B47:B52) -> 0.12373204 | C53: =SUM(C47:C52) -> 0.0747 | D53: =SUM(D47:D52) -> 0.049837623 | E53: =SUM(E47:E52) -> 0.12373204 | F53: =SUM(F47:F52) -> 0.08 | G53: =SUM(G47:G52) -> 0.049837623 | H53: =SUM(H47:H52) -> 0.12373204 | I53: =SUM(I47:I52) -> 0.074799193 | J53: =SUM(J47:J52) -> 0 | L53: =SUM(L47:L52) -> 0 | M53: 0.10327623 | N53: =SUM(N47:N52) -> 0.12373204 | O53: =SUM(O47:O52) -> 0 | P53: =SUM(P47:P52) -> 0 | R53: =SUM(R47:R52) -> 0 | S53: =SUM(S47:S52) -> 0
A55: Total Cost per Pound at Gross | B55: =B45+B53 -> 0.58986099 | C55: =C45+C53 -> 0.5071 | D55: =D45+D53 -> 0.34978421 | E55: =E45+E53 -> 0.86793548 | F55: =F45+F53 -> 0.7359 | G55: =G45+G53 -> 0.62067331 | H55: =H45+H53 -> 0.65012255 | I55: =I45+I53 -> 0.50928093 | ... S55: =S45+S53 -> 0
A56: Less: Substrate Plant Under-absorption | B56: =-B38 -> 0 | C56: =-C38 -> 0 | D56: 0 | E56: =-E38 -> 0 | G56: 0 | H56: =-H38 -> 0 | J56: 0 | K56: =-K38 -> 0 | M56: -0.0074705959 | N56: =-N38 -> 0 | P56: 0 | Q56: =-Q38 -> 0
A57: Less: RC Under-absorption | B57: 0 | C57: 0 | D57: 0 | E57: 0 | F57: 0 | G57: 0 | H57: 0 | I57: 0 | J57: 0 | K57: =IF(K40+K41+K42+K43+K44+K53>0.0498,0.0498-K40-K41-K42-K43-K44-K53,0) -> 0 | L57: =IF(L40+L41+L42+L43+L44+L53>0.0498,0.0498-L40-L41-L42-L43-L44-L53,0) -> 0 | M57: =IF(M40+M41+M42+M43+M44+M53>0.0498,0.0498-M40-M41-M42-M43-M44-M53,0) -> -0.079620814 | N57: 0 | O57: 0 | P57: =IF(P40+P41+P42+P43+P44+P53>0.0498,0.0498-P40-P41-P42-P43-P44-P53,0) -> 0 | Q57: =IF(Q40+Q41+Q42+Q43+Q44+Q53>0.0498,0.0498-Q40-Q41-Q42-Q43-Q44-Q53,0) -> 0 | R57: 0 | S57: =IF(S40+S41+S42+S43+S44+S53>0.0498,0.0498-S40-S41-S42-S43-S44-S53,0) -> 0
A58: Net Cost per Pound Absorbed | B58: =SUM(B55:B57) -> 0.58986099 | C58: =SUM(C55:C57) -> 0.5071 | D58: =SUM(D55:D57) -> 0.34978421 | E58: =SUM(E55:E57) -> 0.86793548 | F58: =SUM(F55:F57) -> 0.7359 | G58: =SUM(G55:G57) -> 0.62067331 | H58: =SUM(H55:H57) -> 0.65012255 | I58: =SUM(I55:I57) -> 0.50928093 | ... S58: =SUM(S55:S57) -> 0
A60: Total Production (000 lbs) | B60: =+B85 -> 450 | C60: 123 | D60: 1100 | E60: =+B86 -> 1300 | F60: 979 | G60: 1700 | H60: =+B90 -> 0 | I60: 4813 | J60: 0 | K60: =+B88 -> 0 | L60: 0 | M60: 100 | N60: =+B83 -> 0 | O60: 0 | P60: 0 | Q60: 0 | R60: 0 | S60: 0
A64: Total Plant Production (000 lbs) | B64: =B29+E29+H29+K29+N29+Q29+B60+E60+H60+K60+N60+Q60 -> 15340 | C64: =C29+F29+I29+L29+O29+R29+C60+F60+I60+L60+O60+R60 -> 35590.15 | D64: =D29+G29+J29+M29+P29+S29+D60+G60+J60+M60+P60+S60 -> 39000
B66: Total | C66: Variable | D66: Fixed
A67: Cost Summary: | B67: ($ in 000s)
A68: Absorbed by Production | B68: =SUM(C68:D68) -> 0 | C68: =W14*$V$29 -> 0 | D68: =W22*$V$29 -> 0
A69: Underabsorption Expensed | B69: =SUM(C69:D69) -> 0 | C69: =X14*$V$29 -> 0 | D69: =X22*$V$29 -> 0
A70: Loss on Excess Gas Net Settled | B70: =SUM(C70:D70) -> 0 | C70: 0 | D70: 0
A71: Total Cost | B71: =SUM(B68:B70) -> 0 | C71: =SUM(C68:C70) -> 0 | D71: =SUM(D68:D70) -> 0
A72: Less: Non-Cash | B72: =SUM(C72:D72) -> 0 | C72: 0 | D72: =-V20*V29 -> 0
A73: Cash Cost | B73: =SUM(B71:B72) -> 0 | C73: =SUM(C71:C72) -> 0 | D73: =SUM(D71:D72) -> 0
B77: Quantity | C77: Rate
A78: Production Plan | B78: (000 lbs) | C78: (000 lbs/day) | D78: Prodn Days | E78: % Split
A79: CB Lite | B79: 10500 | C79: 80 | D79: =IF(C79<>0,B79/C79,0) -> 131.25 | E79: =IF($D$91<>0,D79/$D$91,0) -> 0.65190397
A80: CB HSP | C80: =350 -> 350 | D80: =IF(C80<>0,B80/C80,0) -> 0 | E80: =IF($D$91<>0,D80/$D$91,0) -> 0
A81: CB KSLD | B81: 3000 | C81: 150 | D81: =IF(C81<>0,B81/C81,0) -> 20 | E81: =IF($D$91<>0,D81/$D$91,0) -> 0.099337748
A82: RPM Lite / NP LWC | B82: 90 | C82: 80 | D82: =IF(C82<>0,B82/C82,0) -> 1.125 | E82: =IF($D$91<>0,D82/$D$91,0) -> 0.0055877483
A83: FilterGuard | C83: =350 -> 350 | D83: =IF(C83<>0,B83/C83,0) -> 0 | E83: =IF($D$91<>0,D83/$D$91,0) -> 0
A84: Air | C84: =350 -> 350 | D84: =IF(C84<>0,B84/C84,0) -> 0 | E84: =IF($D$91<>0,D84/$D$91,0) -> 0
A85: Fusion (#998, 999, 1025) | B85: 450 | C85: 80 | D85: =IF(C85<>0,B85/C85,0) -> 5.625 | E85: =IF($D$91<>0,D85/$D$91,0) -> 0.027938742
A86: SG II CL | B86: 1300 | C86: 30 | D86: =IF(C86<>0,B86/C86,0) -> 43.333333 | E86: =IF($D$91<>0,D86/$D$91,0) -> 0.21523179
A87: SG II Ultra CL | B87: 0 | C87: =350 -> 350 | D87: =IF(C87<>0,B87/C87,0) -> 0 | E87: =IF($D$91<>0,D87/$D$91,0) -> 0
A88: SG II KSHD (H) | B88: 0 | C88: =350 -> 350 | D88: =IF(C88<>0,B88/C88,0) -> 0 | E88: =IF($D$91<>0,D88/$D$91,0) -> 0
A89: SaltGuard (FDP-806) | B89: 0 | C89: =350 -> 350 | D89: =IF(C89<>0,B89/C89,0) -> 0 | E89: =IF($D$91<>0,D89/$D$91,0) -> 0
A90: KSXT | B90: 0 | C90: =350 -> 350 | D90: =IF(C90<>0,B90/C90,0) -> 0 | E90: =IF($D$91<>0,D90/$D$91,0) -> 0
A91: Total | B91: =SUM(B79:B90) -> 15340 | C91: =B91/D91 -> 76.192053 | D91: =SUM(D79:D90) -> 201.33333 | E91: =IF($D$91<>0,D91/$D$91,0) -> 1
A93: Variable Costs - Material
D95: CB Lite | F95: CB Lite EU | H95: CB KSLD | J95: RPM Lite / NP LWC | L95: CB HSP | N95: Air | AL95: RPM | AN95: CBL KSHD | AP95: AIR
A96: Materials Cost: | B96: Price ($/lb) | C96: Source plant under-absorb | D96: BOM Use/lb | E96: Standard Cost | F96: BOM Use/lb | G96: Standard Cost | H96: BOM Use/lb | I96: Standard Cost | J96: BOM Use/lb | K96: Standard Cost | L96: BOM Use/lb | M96: Standard Cost | N96: BOM Use/lb | O96: Standard Cost | AL96: cost BOM | AM96: plan price 1 | AN96: cost BOM | AO96: plan price 1 | AP96: cost BOM
A97: CARBO LITE (32, 36, 115) | B97: =0.1829+0.032-C97 -> 0.2149 | C97: 0 | D97: =1251371/1262940 -> 0.99083963 | E97: =$B97*D97 -> 0.21293144 | F97: =3608216/3572240 -> 1.010071 | G97: =$B97*F97 -> 0.21706426 | H97: 0 | I97: =$B97*H97 -> 0 | J97: 1 | K97: =$B97*J97 -> 0.2149 | L97: 0 | M97: =$B97*L97 -> 0 | N97: 0 | O97: =$B97*N97 -> 0 | AL97: =K97/B97*1000 -> 1000
A98: CARBOAIR UL (861, 938) GUARD (822) | B98: =0.27228+0.032-C98 -> 0.30428 | C98: 0 | D98: 0 | E98: =$B98*D98 -> 0 | F98: 0 | G98: =$B98*F98 -> 0 | H98: 0 | I98: =$B98*H98 -> 0 | J98: 0 | K98: =$B98*J98 -> 0 | L98: 0 | M98: =$B98*L98 -> 0 | N98: =262800/262440 -> 1.0013717 | O98: =$B98*N98 -> 0.30469739 | AO98: =+B98*1000 -> 304.28 | AP98: =O98/B98*1000 -> 1001.3717
A99: KRYPTOSPHERE LD (976) | B99: =0.465+0.032-C99 -> 0.497 | C99: 0 | D99: 0 | E99: =$B99*D99 -> 0 | F99: 0 | G99: =$B99*F99 -> 0 | H99: =208000/198210 -> 1.0493921 | I99: =$B99*H99 -> 0.52154785 | J99: 0 | K99: =$B99*J99 -> 0 | L99: 0 | M99: =$B99*L99 -> 0 | N99: 0 | O99: =$B99*N99 -> 0
A100: KRYPTOSPHERE HD (873) | B100: =0.973+0.032-C100 -> 1.005 | C100: 0 | D100: 0 | E100: =$B100*D100 -> 0 | F100: 0 | G100: =$B100*F100 -> 0 | H100: 0 | I100: =$B100*H100 -> 0 | J100: 0 | K100: =$B100*J100 -> 0 | L100: 0 | M100: =$B100*L100 -> 0 | N100: 0 | O100: =$B100*N100 -> 0 | AM100: =+B102*1000 -> 377.8 | AN100: =M100/B100*1000 -> 0
A101: NRT KRYPTOSPHERE LD (1200) | B101: =306.29/1000 -> 0.30629 | D101: 0 | E101: =$B101*D101 -> 0 | F101: 0 | G101: =$B101*F101 -> 0 | H101: 0 | I101: =$B101*H101 -> 0 | J101: 0 | K101: =$B101*J101 -> 0 | L101: 0 | M101: =$B101*L101 -> 0 | N101: 0 | O101: =$B101*N101 -> 0
A102: CARBO HSP (19, 824) | B102: =0.3458+0.032-C102 -> 0.3778 | C102: 0 | D102: 0 | E102: =$B102*D102 -> 0 | F102: 0 | G102: =$B102*F102 -> 0 | H102: 0 | I102: =$B102*H102 -> 0 | J102: 0 | K102: =$B102*J102 -> 0 | L102: =429020/422600 -> 1.0151917 | M102: =$B102*L102 -> 0.38353941 | N102: 0 | O102: =$B102*N102 -> 0
A103: CARBOPROP (50) | B103: 0 | C103: 0 | D103: 0 | E103: =$B103*D103 -> 0 | F103: 0 | G103: =$B103*F103 -> 0 | H103: 0 | I103: =$B103*H103 -> 0 | J103: 0 | K103: =$B103*J103 -> 0 | L103: 0 | M103: =$B103*L103 -> 0 | N103: 0 | O103: =$B103*N103 -> 0
A104: SCALEGUARD I CL (812, 951, 1941, 1981, 2006) | B104: 0.6364 | C104: 0 | D104: 0 | E104: =$B104*D104 -> 0 | F104: 0 | G104: =$B104*F104 -> 0 | H104: 0 | I104: =$B104*H104 -> 0 | J104: 0 | K104: =$B104*J104 -> 0 | L104: 0 | M104: =$B104*L104 -> 0 | N104: 0 | O104: =$B104*N104 -> 0
A105: SCALEGUARD IX CL | B105: 0.6364 | C105: 0 | D105: 0 | E105: =$B105*D105 -> 0 | F105: 0 | G105: =$B105*F105 -> 0 | H105: 0 | I105: =$B105*H105 -> 0 | J105: 0 | K105: =$B105*J105 -> 0 | L105: 0 | M105: =$B105*L105 -> 0 | N105: 0 | O105: =$B105*N105 -> 0
A106: SCALEGUARD I KSHD (H) | B106: =1.9036-C106 -> 1.9036 | C106: 0 | D106: 0 | E106: =$B106*D106 -> 0 | F106: 0 | G106: =$B106*F106 -> 0 | H106: 0 | I106: =$B106*H106 -> 0 | J106: 0 | K106: =$B106*J106 -> 0 | L106: 0 | M106: =$B106*L106 -> 0 | N106: 0 | O106: =$B106*N106 -> 0
A107: CL FUSION SUBSTRATE (994) | B107: =337.81/1000 -> 0.33781 | C107: 0 | D107: 0 | E107: =$B107*D107 -> 0 | F107: 0 | G107: =$B107*F107 -> 0 | H107: 0 | I107: =$B107*H107 -> 0 | J107: 0 | K107: =$B107*J107 -> 0 | L107: 0 | M107: =$B107*L107 -> 0 | N107: 0 | O107: =$B107*N107 -> 0
A108: Plenco Resin (30090) | B108: 1.451 | C108: 0 | D108: =36955/1262940 -> 0.029261089 | E108: =$B108*D108 -> 0.04245784 | F108: =134560/3572240 -> 0.037668242 | G108: =$B108*F108 -> 0.054656619 | H108: =7110/198210 -> 0.035871046 | I108: =$B108*H108 -> 0.052048888 | J108: 0 | K108: =$B108*J108 -> 0 | L108: =17363/422600 -> 0.041086133 | M108: =$B108*L108 -> 0.05961598 | N108: =10645/262440 -> 0.040561652 | O108: =$B108*N108 -> 0.058854957 | AM108: =+B109*1000 -> 1200 | AN108: =M108/B108*1000 -> 41.086133 | AO108: =+B108*1000 -> 1451 | AP108: =O108/B108*1000 -> 40.561652
A109: HEXA-EU (30362) | B109: 1.2 | C109: 0 | D109: 0 | E109: =$B109*D109 -> 0 | F109: =15443/3572240 -> 0.0043230578 | G109: =$B109*F109 -> 0.0051876694 | H109: 0 | I109: =$B109*H109 -> 0 | J109: 0 | K109: =$B109*J109 -> 0 | L109: =+H109 -> 0 | M109: =$B109*L109 -> 0 | N109: =1190/262440 -> 0.0045343698 | O109: =$B109*N109 -> 0.0054412437 | AM109: =+B110*1000 -> 3920 | AN109: =M109/B109*1000 -> 0 | AO109: =+B109*1000 -> 1200 | AP109: =O109/B109*1000 -> 4.5343698
A110: Silane-EU (30360) | B110: 3.92 | C110: 0 | D110: =335/1262940 -> 0.00026525409 | E110: =$B110*D110 -> 0.001039796 | F110: =2650/3572240 -> 0.00074183146 | G110: =$B110*F110 -> 0.0029079793 | H110: =127/198210 -> 0.00064073457 | I110: =$B110*H110 -> 0.0025116795 | J110: 0 | K110: =$B110*J110 -> 0 | L110: =330/422600 -> 0.00078088027 | M110: =$B110*L110 -> 0.0030610506 | N110: =320/262440 -> 0.0012193263 | O110: =$B110*N110 -> 0.0047797592 | AM110: =+B111*1000 -> 2080 | AN110: =M110/B110*1000 -> 0.78088027 | AO110: =+B110*1000 -> 3920 | AP110: =O110/B110*1000 -> 1.2193263
A111: Surfactant-EU (30361) | B111: 2.08 | C111: 0 | D111: 0 | E111: =$B111*D111 -> 0 | F111: =2222/3572240 -> 0.00062201868 | G111: =$B111*F111 -> 0.0012937988 | H111: 0 | I111: =$B111*H111 -> 0 | J111: 0 | K111: =$B111*J111 -> 0 | L111: =+H111 -> 0 | M111: =$B111*L111 -> 0 | N111: =542/262440 -> 0.002065234 | O111: =$B111*N111 -> 0.0042956866 | AM111: =+B112*1000 -> 2470 | AN111: =M111/B111*1000 -> 0 | AO111: =+B111*1000 -> 2080 | AP111: =O111/B111*1000 -> 2.065234
A112: Surfactant (30054) | B112: 2.47 | C112: 0 | D112: =923/1262940 -> 0.0007308344 | E112: =$B112*D112 -> 0.001805161 | F112: 0 | G112: =$B112*F112 -> 0 | H112: =170/198210 -> 0.0008576762 | I112: =$B112*H112 -> 0.0021184602 | J112: 0 | K112: =$B112*J112 -> 0 | L112: =108/422600 -> 0.00025556081 | M112: =$B112*L112 -> 0.00063123521 | N112: 0 | O112: =$B112*N112 -> 0 | AN112: =M112/B112*1000 -> 0.25556081 | AP112: =O112/B112*1000 -> 0
A113: Hexamine (30055) | B113: 2.04 | C113: 0 | D113: =2700/1262940 -> 0.0021378688 | E113: =$B113*D113 -> 0.0043612523 | F113: 0 | G113: =$B113*F113 -> 0 | H113: =1900/198210 -> 0.0095857928 | I113: =$B113*H113 -> 0.019555017 | J113: 0 | K113: =$B113*J113 -> 0 | L113: =5000/422600 -> 0.011831519 | M113: =$B113*L113 -> 0.024136299 | N113: 0 | O113: =$B113*N113 -> 0 | AN113: =M113/B113*1000 -> 11.831519 | AP113: =O113/B113*1000 -> 0
A114: Silane (30058) | B114: 3.92 | C114: 0 | D114: =250/1262940 -> 0.00019795081 | E114: =$B114*D114 -> 0.00077596719 | F114: 0 | G114: =$B114*F114 -> 0 | H114: 0 | I114: =$B114*H114 -> 0 | J114: 0 | K114: =$B114*J114 -> 0 | L114: 0 | M114: =$B114*L114 -> 0 | N114: 0 | O114: =$B114*N114 -> 0
A115: WB Concentrate (30454) | B115: 15.83 | C115: 0 | D115: 0 | E115: =$B115*D115 -> 0 | F115: 0 | G115: =$B115*F115 -> 0 | H115: 0 | I115: =$B115*H115 -> 0 | J115: 0.0125 | K115: =$B115*J115 -> 0.197875 | L115: 0 | M115: =$B115*L115 -> 0 | N115: 0 | O115: =$B115*N115 -> 0 | AL115: =K115/B115*1000 -> 12.5 | AN115: =M115/B115*1000 -> 0 | AP115: =O115/B115*1000 -> 0
A116: BYK 20798 (30242) | B116: 11.85 | C116: 0 | D116: 0 | E116: =$B116*D116 -> 0 | F116: 0 | G116: =$B116*F116 -> 0 | H116: 0 | I116: =$B116*H116 -> 0 | J116: =275/160460 -> 0.0017138228 | K116: =$B116*J116 -> 0.0203088 | L116: 0 | M116: =$B116*L116 -> 0 | N116: =622/262440 -> 0.0023700655 | O116: =$B116*N116 -> 0.028085277 | AN116: =M116/B116*1000 -> 0 | AO116: =+B116*1000 -> 11850 | AP116: =O116/B116*1000 -> 2.3700655
A118: Standard Cost Contribution: | E118: $/lb | G118: $/lb | I118: $/lb | K118: $/lb | M118: $/lb | O118: $/lb
A119: Substrate* | E119: =SUM(E97:E107) -> 0.21293144 | G119: =SUM(G97:G107) -> 0.21706426 | I119: =SUM(I97:I107) -> 0.52154785 | K119: =SUM(K97:K107) -> 0.2149 | M119: =SUM(M97:M107) -> 0.38353941 | O119: =SUM(O97:O107) -> 0.30469739
A120: Resin | E120: =SUM(E108:E108) -> 0.04245784 | G120: =SUM(G108:G108) -> 0.054656619 | I120: =SUM(I108:I108) -> 0.052048888 | K120: =SUM(K108:K108) -> 0 | M120: =SUM(M108:M108) -> 0.05961598 | O120: =SUM(O108:O108) -> 0.058854957 | AL120: =SUM(AL97:AL115) -> 1012.5 | AN120: =SUM(AN97:AN116) -> 53.954094 | AP120: =SUM(AP97:AP116) -> 1052.1224
...

Sheet NI RC 2024 Std
A1: New Iberia Resin Coating
A2: 2024 STANDARDS
B3: CARBOBond Lite | E3: CARBOBond Lite EU | H3: CARBOBond KSLD | K3: RPM LITE / NEUTRAPROP LWC | N3: CARBOBond HSP | Q3: CARBO AIR
B4: 24 Standard | C4: 23 Actual | D4: 22 Standard | E4: 24 Standard | F4: 23 Actual | G4: 22 Standard | H4: 24 Standard | I4: 23 Actual | J4: 22 Standard | K4: 24 Standard | L4: 23 Actual | M4: 22 Standard | N4: 24 Standard | O4: 23 Actual | P4: 22 Standard | Q4: 24 Standard | R4: 23 Actual | S4: =+D4 -> 22 Standard
C5: Jan | F5: Jan | I5: (Aug) | L5: (Jan) | O5: (Aug) | R5: (Jan-Aug)
A6: Materials - Substrate | B6: =E119 -> 0.21293144 | C6: 0.261 | D6: 0.1639529 | E6: =G119 -> 0.21706426 | F6: 0.259 | G6: 0.18884365 | H6: =+I119 -> 0.52154785 | I6: 0.4369 | J6: 0.41938749 | K6: =K119 -> 0.2149 | L6: 0.1827 | M6: 0.15362762 | N6: =+M100 -> 0 | O6: 0.431 | P6: 0.80389422 | Q6: =+O98 -> 0.30469739 | R6: 0.15968841 | S6: 0.19086145
A7: Materials - Substrate Under-Absorption | B7: =$C97*D97 -> 0 | D7: 0 | E7: =$C97*F97 -> 0 | G7: 0 | H7: =$C97*I97 -> 0 | J7: 0 | K7: =$C97*J97 -> 0 | M7: 0.094857323 | N7: =$C97*O97 -> 0 | P7: 0
A8: Materials - Resin & Chemicals | B8: =E120+E121 -> 0.050440017 | C8: 0.0667 | D8: 0.038078 | E8: =G120+G121 -> 0.064046066 | F8: 0.0652 | G8: 0.060015662 | H8: =+I120+I121 -> 0.076234045 | I8: =0.5149-I6 -> 0.078 | J8: 0.056384154 | K8: =K120+K121 -> 0.2181838 | L8: =0.2569-L6 -> 0.0742 | M8: 0.15903358 | N8: =+M120+M121 -> 0.087444565 | O8: =0.5164-O6 -> 0.0854 | P8: 0.056384154 | Q8: =+O120+O121 -> 0.10145692 | R8: 0.072759577 | S8: 0.087415456
A9: Electricity | B9: =E164 -> 0.0083887564 | C9: 0.0019 | D9: 0.0059095494 | E9: =G164 -> 0.010531407 | F9: 0.0019 | G9: 0.0092314722 | H9: =J164 -> 0.06212471 | I9: 0.0088 | J9: 0.043221874 | K9: =K164 -> 0.018513164 | L9: 0.0117 | M9: 0.010135435 | N9: =+M164 -> 0.0088229437 | O9: 0.0088 | P9: 0.006738662 | Q9: =+O164 -> 0.011271451 | R9: 0.006525594 | S9: 0.0089969295
A10: Gas | B10: =E165 -> 0.0017786261 | C10: 0.004 | D10: 0.0013242333 | E10: =G165 -> 0.001820037 | F10: 0.0041 | G10: 0.00153375 | H10: =J165 -> 0.00023681914 | I10: 0.0038 | J10: 0.00029427407 | K10: =K165 -> 0.0012487474 | L10: 0.0011 | M10: 0.0011247591 | N10: =+M165 -> 0.0038181212 | O10: 0.0038 | P10: 0.0013537383 | Q10: =+O165 -> 0.0033852574 | R10: 0.0011625955 | S10: 0.0038428259
A11: R&M Supplies and Service | B11: =$H$180 -> 0.01650165 | C11: 0.0016 | D11: 0.006 | E11: =$H$180 -> 0.01650165 | F11: 0.0016 | G11: 0.0031413613 | H11: =$H$180 -> 0.01650165 | I11: 0.0094 | J11: 0.0031413613 | K11: =$H$180 -> 0.01650165 | L11: 0.0076 | M11: 0.0086705202 | N11: =$H$180 -> 0.01650165 | O11: 0.0094 | P11: 0.0031413613 | Q11: =$H$180 -> 0.01650165 | R11: 0.016241103 | S11: 0.0031413613
A12: Manufacturing Supplies | B12: =$H$183 -> 0.001320132 | C12: 0 | D12: 0.002 | E12: =$H$183 -> 0.001320132 | F12: 0 | G12: 0.0002617801 | H12: =$H$183 -> 0.001320132 | I12: 0.0003 | J12: 0.0002617801 | K12: =$H$183 -> 0.001320132 | L12: 0.0002 | M12: 0.00043352601 | N12: =$H$183 -> 0.001320132 | O12: 0.0003 | P12: 0.0002617801 | Q12: =$H$183 -> 0.001320132 | R12: 0.00053366327 | S12: 0.0002617801
A13: Other variable | B13: =$H$186 -> 0.02310231 | C13: 0.005 | D13: 0.006 | E13: =$H$186 -> 0.02310231 | F13: 0.0052 | G13: 0.0039267016 | H13: =$H$186 -> 0.02310231 | I13: 0.0134 | J13: 0.0039267016 | K13: =$H$186 -> 0.02310231 | L13: 0.0035 | M13: 0.0057803468 | N13: =$H$186 -> 0.02310231 | O13: 0.0134 | P13: 0.0039267016 | Q13: =$H$186 -> 0.02310231 | R13: 0.0059964109 | S13: 0.0039267016
A14: Total Variable Costs | B14: =SUM(B6:B13) -> 0.31446293 | C14: =SUM(C6:C13) -> 0.3402 | D14: =SUM(D6:D13) -> 0.22326468 | E14: =SUM(E6:E13) -> 0.33438586 | F14: =SUM(F6:F13) -> 0.337 | G14: =SUM(G6:G13) -> 0.26695437 | H14: =SUM(H6:H13) -> 0.70106752 | I14: =SUM(I6:I13) -> 0.5506 | ... L14: =SUM(L6:L13) -> 0.281 | M14: 0.43366311 | N14: =SUM(N6:N13) -> 0.14100972 | O14: =SUM(O6:O13) -> 0.5521 | P14: =SUM(P6:P13) -> 0.87570062 | Q14: =SUM(Q6:Q13) -> 0.46173512 | R14: =SUM(R6:R13) -> 0.26290735 | S14: 0.33373539
A16: Production Labor | B16: =$D$217/$B$64/1000 -> 0.040795043 | C16: 0.0165 | D16: 0.035940795 | E16: =$D$217/$B$64/1000 -> 0.040795043 | F16: 0.0165 | G16: 0.016663174 | H16: =$D$217/$B$64/1000 -> 0.040795043 | I16: 0.0283 | J16: 0.016663174 | K16: =$D$217/$B$64/1000 -> 0.040795043 | L16: 0.0095 | M16: 0.011741675 | N16: =$D$217/$B$64/1000 -> 0.040795043 | O16: 0.0283 | P16: 0.016663174 | Q16: =$D$217/$B$64/1000 -> 0.040795043 | R16: 0.013727223 | S16: 0.016663174
A17: Repairs & Maintenance Labor | B17: =$G$217/$B$64/1000 -> 0.013212612 | C17: 0.007 | D17: 0.0113712 | E17: =$G$217/$B$64/1000 -> 0.013212612 | F17: 0.007 | G17: 0.0040701571 | H17: =$G$217/$B$64/1000 -> 0.013212612 | I17: 0.0072 | J17: 0.0040701571 | K17: =$G$217/$B$64/1000 -> 0.013212612 | L17: 0.005 | M17: 0.0041080925 | N17: =$G$217/$B$64/1000 -> 0.013212612 | O17: 0.0072 | P17: 0.0040701571 | Q17: =$G$217/$B$64/1000 -> 0.013212612 | R17: 0.0016693747 | S17: 0.0040701571
A18: Indirect Payroll Costs (Benefits) | B18: =$J$217/$B$64/1000 -> 0.017821096 | C18: 0.0114 | D18: 0.014188877 | E18: =$J$217/$B$64/1000 -> 0.017821096 | F18: 0.0114 | G18: 0.0073786377 | H18: =$J$217/$B$64/1000 -> 0.017821096 | I18: 0.0071 | J18: 0.0073786377 | K18: =$J$217/$B$64/1000 -> 0.017821096 | L18: 0.0111 | M18: 0.0072598437 | N18: =$J$217/$B$64/1000 -> 0.017821096 | O18: 0.0071 | P18: 0.0073786377 | Q18: =$J$217/$B$64/1000 -> 0.017821096 | R18: 0.0056633179 | S18: 0.0073786377
A19: Supervision | B19: =$E$243 -> 0.0054972436 | C19: 0.035 | D19: 0 | E19: =$E$243 -> 0.0054972436 | F19: 0.0035 | G19: 0.0040554974 | H19: =$E$243 -> 0.0054972436 | I19: 0.002 | J19: 0.0040554974 | K19: =$E$243 -> 0.0054972436 | L19: 0.0073 | M19: 0.002449852 | N19: =$E$243 -> 0.0054972436 | O19: 0.002 | P19: 0.0040554974 | Q19: =$E$243 -> 0.0054972436 | R19: 0.0023710733 | S19: 0.0040554974
A20: Depreciation | B20: =$E$244 -> 0.0073980198 | C20: 0.0053 | D20: 0.01039048 | E20: =$E$244 -> 0.0073980198 | F20: 0.0053 | G20: 0.0029340314 | H20: =$E$244 -> 0.0073980198 | I20: 0.0038 | J20: 0.0029340314 | K20: =$E$244 -> 0.0073980198 | L20: 0.0058 | M20: 0.06367052 | N20: =$E$244 -> 0.0073980198 | O20: 0.0038 | P20: 0.0029340314 | Q20: =$E$244 -> 0.0073980198 | R20: 0.064182394 | S20: 0.0029340314
A21: Insurance & Taxes | B21: =$E$245 -> 0.026217822 | C21: 0.0168 | D21: 0.03763008 | E21: =$E$245 -> 0.026217822 | F21: 0.0168 | G21: 0.014736126 | H21: =$E$245 -> 0.026217822 | I21: 0.0135 | J21: 0.014736126 | K21: =$E$245 -> 0.026217822 | L21: 0.0037 | M21: 0.014046243 | N21: =$E$245 -> 0.026217822 | O21: 0.0135 | P21: 0.014736126 | Q21: =$E$245 -> 0.026217822 | R21: 0.015675972 | S21: 0.014736126
A22: Total Fixed Costs | B22: =SUM(B16:B21) -> 0.11094184 | C22: =SUM(C16:C21) -> 0.092 | D22: =SUM(D16:D21) -> 0.10952143 | E22: =SUM(E16:E21) -> 0.11094184 | F22: =SUM(F16:F21) -> 0.0605 | G22: =SUM(G16:G21) -> 0.049837623 | H22: =SUM(H16:H21) -> 0.11094184 | I22: =SUM(I16:I21) -> 0.0619 | ... L22: =SUM(L16:L21) -> 0.0424 | M22: 0.10327623 | N22: =SUM(N16:N21) -> 0.11094184 | O22: =SUM(O16:O21) -> 0.0619 | P22: =SUM(P16:P21) -> 0.049837623 | Q22: =SUM(Q16:Q21) -> 0.11094184 | R22: =SUM(R16:R21) -> 0.10328935 | S22: 0.10327623
A24: Total Cost per Pound at Gross | B24: =B14+B22 -> 0.42540476 | C24: =C14+C22 -> 0.4322 | D24: =D14+D22 -> 0.33278611 | E24: =E14+E22 -> 0.44532769 | F24: =F14+F22 -> 0.3975 | G24: =G14+G22 -> 0.316792 | H24: =H14+H22 -> 0.81200936 | I24: =I14+I22 -> 0.6125 | ... S24: =S14+S22 -> 0.43701161
A25: Less: Substrate Plant Under-absorption | B25: =-B7 -> 0 | D25: 0 | E25: =-E7 -> 0 | G25: 0 | H25: =-H7 -> 0 | J25: 0 | K25: =-K7 -> 0 | M25: 0 | N25: =-N7 -> 0 | Q25: =-Q7 -> 0 | S25: 0
A26: Less: RC Under-absorption | B26: 0 | C26: -0.079184632 | D26: 0 | E26: 0 | F26: 0 | G26: 0 | H26: 0 | I26: 0 | J26: 0 | K26: 0 | L26: 0 | M26: 0 | N26: 0 | O26: 0 | P26: 0 | Q26: 0 | R26: =IF(R9+R10+R11+R12+R13+R22>0.0498,0.0498-R9-R10-R11-R12-R13-R22,0) -> -0.083948722 | S26: 0
A27: Net Cost per Pound Absorbed | B27: =SUM(B24:B26) -> 0.42540476 | C27: =SUM(C24:C26) -> 0.35301537 | D27: =SUM(D24:D26) -> 0.33278611 | E27: =SUM(E24:E26) -> 0.44532769 | F27: =SUM(F24:F26) -> 0.3975 | G27: =SUM(G24:G26) -> 0.316792 | H27: =SUM(H24:H26) -> 0.81200936 | I27: =SUM(I24:I26) -> 0.6125 | ... S27: =SUM(S24:S26) -> 0.43701161
A29: Total Production (000 lbs) | B29: =+B79*0.5 -> 4350 | C29: 15431 | D29: 3000 | E29: =+B79*0.5 -> 4350 | F29: 9412 | G29: 25500 | H29: =+B81 -> 0 | I29: 198 | J29: 300 | K29: =+B82 -> 0 | L29: 160 | M29: 1000 | N29: =+B80 -> 0 | O29: 827 | P29: 5000 | Q29: =+B84 -> 0 | R29: 3647.15 | S29: 1300
B34: Fusion | E34: ScaleGuard II CL | H34: KSXT | K34: ScaleGuard II KSHD (H) | N34: FilterGuard | Q34: XX
B35: 24 Standard | C35: 21 Actual | D35: 22 Standard | E35: 24 Standard | F35: 23 Actual | G35: 22 Standard | H35: 23 Standard | I35: 22 Actual | J35: =+D4 -> 22 Standard | K35: =+B4 -> 24 Standard | L35: 19 Actual | M35: =+D4 -> 22 Standard | N35: =+B4 -> 24 Standard | O35: XX Actual | P35: XX Standard | Q35: =+B4 -> 24 Standard | R35: 19 Actual | S35: =+D4 -> 22 Standard
C36: (Jul) | F36: (May) | I36: (Jan-Aug) | L36: (Jan-Sept)
A37: Materials - Substrate | B37: =E152 -> 0.34423291 | C37: 0.3421 | D37: 0.21326582 | E37: =G152 -> 0.63341571 | F37: 0.5729 | G37: 0.51387049 | H37: =I152 -> 0.4684443 | I37: 0.3911 | J37: 0 | L37: 0 | M37: 1.8829093 | N37: =+M152 -> 0.28401991 | O37: 0 | P37: 0 | R37: 0 | S37: 0
A38: Materials - Substrate Under-Absorption | B38: =$C137*D137 -> 0 | D38: 0 | E38: =$C134*F134 -> 0 | G38: 0 | H38: =$C129*H129 -> 0 | J38: 0 | M38: 0.16177979 | N38: 0 | P38: 0 | S38: 0
A39: Materials - Resin & Chemicals | B39: =E153+E154 -> 0.067817592 | C39: =0.4041-C37 -> 0.062 | D39: 0.067925472 | E39: =G153+G154 -> 0.053814952 | F39: 0.0496 | G39: 0.04253052 | H39: =I153+I154 -> 0.0065721369 | I39: 0.0058396524 | J39: 0 | L39: 0 | M39: 0.042578635 | N39: =+M153+M154 -> 0.78698195 | O39: 0 | P39: 0 | R39: 0 | S39: 0
A40: Electricity | B40: =E171 -> 0.01207814 | C40: 0.01 | D40: 0.009641779 | E40: =G171 -> 0.01384973 | F40: 0.0167 | G40: 0.0058784926 | H40: =I171 -> 0.0096111165 | I40: 0.017771324 | J40: 0 | L40: 0 | M40: 0.010135435 | N40: =M171 -> 0.046127878 | O40: 0 | P40: 0 | R40: 0 | S40: 0
A41: Gas | B41: =E172 -> 0.001583098 | C41: 0.002 | D41: 0.0017836723 | E41: =G172 -> 0.0027058421 | F41: 0.0011 | G41: 0.0012263426 | H41: =I172 -> 0.0013457382 | I41: 0.0036105204 | J41: 0 | L41: 0 | M41: 0.0011247591 | N41: =M172 -> 0.0020507934 | O41: 0 | P41: 0 | R41: 0 | S41: 0
A42: R&M Supplies and Service | B42: =$H$180 -> 0.01650165 | C42: 0.0036 | D42: 0.0031413613 | E42: =$H$180 -> 0.01650165 | F42: 0.0036 | G42: 0.0031413613 | H42: =$H$180 -> 0.01650165 | I42: 0.0059485597 | J42: 0 | L42: 0 | M42: 0.0086705202 | N42: =$H$180 -> 0.01650165 | O42: 0 | P42: 0 | R42: 0 | S42: 0
A43: Manufacturing Supplies | B43: =$H$183 -> 0.001320132 | C43: 0.0002 | D43: 0.0002617801 | E43: =$H$183 -> 0.001320132 | F43: 0 | G43: 0.0002617801 | H43: =$H$183 -> 0.001320132 | I43: 0.0009914408 | J43: 0 | L43: 0 | M43: 0.00043352601 | N43: =$H$183 -> 0.001320132 | O43: 0 | P43: 0 | R43: 0 | S43: 0
A44: Other variable | B44: =$H$186 -> 0.02310231 | C44: 0.0125 | D44: 0.0039267016 | E44: =$H$186 -> 0.02310231 | F44: 0.012 | G44: 0.0039267016 | H44: =$H$186 -> 0.02310231 | I44: 0.0092202407 | J44: 0 | L44: 0 | M44: 0.0057803468 | N44: =$H$186 -> 0.02310231 | O44: 0 | P44: 0 | R44: 0 | S44: 0
A45: Total Variable Costs | B45: =SUM(B37:B44) -> 0.46663583 | C45: =SUM(C37:C44) -> 0.4324 | D45: =SUM(D37:D44) -> 0.29994659 | E45: =SUM(E37:E44) -> 0.74471032 | F45: =SUM(F37:F44) -> 0.6559 | G45: =SUM(G37:G44) -> 0.57083569 | H45: =SUM(H37:H44) -> 0.52689739 | I45: =SUM(I37:I44) -> 0.43448174 | J45: =SUM(J37:J44) -> 0 | L45: =SUM(L37:L44) -> 0 | M45: 2.1134123 | N45: =SUM(N37:N44) -> 1.1601046 | O45: =SUM(O37:O44) -> 0 | P45: =SUM(P37:P44) -> 0 | R45: =SUM(R37:R44) -> 0 | S45: =SUM(S37:S44) -> 0
A47: Production Labor | B47: =$D$217/$B$64/1000 -> 0.040795043 | C47: 0.0172 | D47: 0.016663174 | E47: =$D$217/$B$64/1000 -> 0.040795043 | F47: 0.0253 | G47: 0.016663174 | H47: =$D$217/$B$64/1000 -> 0.040795043 | I47: 0.026626711 | J47: 0 | L47: 0 | M47: 0.011741675 | N47: =$D$217/$B$64/1000 -> 0.040795043 | O47: 0 | P47: 0 | R47: 0 | S47: 0
A48: Repairs & Maintenance Labor | B48: =$G$217/$B$64/1000 -> 0.013212612 | C48: 0.0064 | D48: 0.0040701571 | E48: =$G$217/$B$64/1000 -> 0.013212612 | F48: 0.0101 | G48: 0.0040701571 | H48: =$G$217/$B$64/1000 -> 0.013212612 | I48: 0.0076324228 | J48: 0 | L48: 0 | M48: 0.0041080925 | N48: =$G$217/$B$64/1000 -> 0.013212612 | O48: 0 | P48: 0 | R48: 0 | S48: 0
A49: Indirect Payroll Costs (Benefits) | B49: =$J$217/$B$64/1000 -> 0.017821096 | C49: 0.0084 | D49: 0.0073786377 | E49: =$J$217/$B$64/1000 -> 0.017821096 | F49: 0.012 | G49: 0.0073786377 | H49: =$J$217/$B$64/1000 -> 0.017821096 | I49: 0.011265424 | J49: 0 | L49: 0 | M49: 0.0072598437 | N49: =$J$217/$B$64/1000 -> 0.017821096 | O49: 0 | P49: 0 | R49: 0 | S49: 0
A50: Supervision | B50: =$E$243 -> 0.0054972436 | C50: 0.0078 | D50: 0.0040554974 | E50: =$E$243 -> 0.0054972436 | F50: 0 | G50: 0.0040554974 | H50: =$E$243 -> 0.0054972436 | I50: 0.0064561315 | J50: 0 | L50: 0 | M50: 0.002449852 | N50: =$E$243 -> 0.0054972436 | O50: 0 | P50: 0 | R50: 0 | S50: 0
A51: Depreciation | B51: =$E$244 -> 0.0073980198 | C51: 0.0058 | D51: 0.0029340314 | E51: =$E$244 -> 0.0073980198 | F51: 0.0076 | G51: 0.0029340314 | H51: =$E$244 -> 0.0073980198 | I51: 0.0050242986 | J51: 0 | L51: 0 | M51: 0.06367052 | N51: =$E$244 -> 0.0073980198 | O51: 0 | P51: 0 | R51: 0 | S51: 0
A52: Insurance & Taxes | B52: =$E$245 -> 0.026217822 | C52: 0.0291 | D52: 0.014736126 | E52: =$E$245 -> 0.026217822 | F52: 0.025 | G52: 0.014736126 | H52: =$E$245 -> 0.026217822 | I52: 0.017794205 | J52: 0 | L52: 0 | M52: 0.014046243 | N52: =$E$245 -> 0.026217822 | O52: 0 | P52: 0 | R52: 0 | S52: 0
A53: Total Fixed Costs | B53: =SUM(B47:B52) -> 0.11094184 | C53: =SUM(C47:C52) -> 0.0747 | D53: =SUM(D47:D52) -> 0.049837623 | E53: =SUM(E47:E52) -> 0.11094184 | F53: =SUM(F47:F52) -> 0.08 | G53: =SUM(G47:G52) -> 0.049837623 | H53: =SUM(H47:H52) -> 0.11094184 | I53: =SUM(I47:I52) -> 0.074799193 | J53: =SUM(J47:J52) -> 0 | L53: =SUM(L47:L52) -> 0 | M53: 0.10327623 | N53: =SUM(N47:N52) -> 0.11094184 | O53: =SUM(O47:O52) -> 0 | P53: =SUM(P47:P52) -> 0 | R53: =SUM(R47:R52) -> 0 | S53: =SUM(S47:S52) -> 0
A55: Total Cost per Pound at Gross | B55: =B45+B53 -> 0.57757767 | C55: =C45+C53 -> 0.5071 | D55: =D45+D53 -> 0.34978421 | E55: =E45+E53 -> 0.85565216 | F55: =F45+F53 -> 0.7359 | G55: =G45+G53 -> 0.62067331 | H55: =H45+H53 -> 0.63783922 | I55: =I45+I53 -> 0.50928093 | ... S55: =S45+S53 -> 0
A56: Less: Substrate Plant Under-absorption | B56: =-B38 -> 0 | C56: =-C38 -> 0 | D56: 0 | E56: =-E38 -> 0 | G56: 0 | H56: =-H38 -> 0 | J56: 0 | K56: =-K38 -> 0 | M56: -0.0074705959 | N56: =-N38 -> 0 | P56: 0 | Q56: =-Q38 -> 0
A57: Less: RC Under-absorption | B57: 0 | C57: 0 | D57: 0 | E57: 0 | F57: 0 | G57: 0 | H57: 0 | I57: 0 | J57: 0 | K57: =IF(K40+K41+K42+K43+K44+K53>0.0498,0.0498-K40-K41-K42-K43-K44-K53,0) -> 0 | L57: =IF(L40+L41+L42+L43+L44+L53>0.0498,0.0498-L40-L41-L42-L43-L44-L53,0) -> 0 | M57: =IF(M40+M41+M42+M43+M44+M53>0.0498,0.0498-M40-M41-M42-M43-M44-M53,0) -> -0.079620814 | N57: 0 | O57: 0 | P57: =IF(P40+P41+P42+P43+P44+P53>0.0498,0.0498-P40-P41-P42-P43-P44-P53,0) -> 0 | Q57: =IF(Q40+Q41+Q42+Q43+Q44+Q53>0.0498,0.0498-Q40-Q41-Q42-Q43-Q44-Q53,0) -> 0 | R57: 0 | S57: =IF(S40+S41+S42+S43+S44+S53>0.0498,0.0498-S40-S41-S42-S43-S44-S53,0) -> 0
A58: Net Cost per Pound Absorbed | B58: =SUM(B55:B57) -> 0.57757767 | C58: =SUM(C55:C57) -> 0.5071 | D58: =SUM(D55:D57) -> 0.34978421 | E58: =SUM(E55:E57) -> 0.85565216 | F58: =SUM(F55:F57) -> 0.7359 | G58: =SUM(G55:G57) -> 0.62067331 | H58: =SUM(H55:H57) -> 0.63783922 | I58: =SUM(I55:I57) -> 0.50928093 | ... S58: =SUM(S55:S57) -> 0
A60: Total Production (000 lbs) | B60: =+B85 -> 950 | C60: 123 | D60: 1100 | E60: =+B86 -> 5500 | F60: 979 | G60: 1700 | H60: =+B90 -> 0 | I60: 4813 | J60: 0 | K60: =+B88 -> 0 | L60: 0 | M60: 100 | N60: =+B83 -> 0 | O60: 0 | P60: 0 | Q60: 0 | R60: 0 | S60: 0
A64: Total Plant Production (000 lbs) | B64: =B29+E29+H29+K29+N29+Q29+B60+E60+H60+K60+N60+Q60 -> 15150 | C64: =C29+F29+I29+L29+O29+R29+C60+F60+I60+L60+O60+R60 -> 35590.15 | D64: =D29+G29+J29+M29+P29+S29+D60+G60+J60+M60+P60+S60 -> 39000
B66: Total | C66: Variable | D66: Fixed
A67: Cost Summary: | B67: ($ in 000s)
A68: Absorbed by Production | B68: =SUM(C68:D68) -> 0 | C68: =W14*$V$29 -> 0 | D68: =W22*$V$29 -> 0
A69: Underabsorption Expensed | B69: =SUM(C69:D69) -> 0 | C69: =X14*$V$29 -> 0 | D69: =X22*$V$29 -> 0
A70: Loss on Excess Gas Net Settled | B70: =SUM(C70:D70) -> 0 | C70: 0 | D70: 0
A71: Total Cost | B71: =SUM(B68:B70) -> 0 | C71: =SUM(C68:C70) -> 0 | D71: =SUM(D68:D70) -> 0
A72: Less: Non-Cash | B72: =SUM(C72:D72) -> 0 | C72: 0 | D72: =-V20*V29 -> 0
A73: Cash Cost | B73: =SUM(B71:B72) -> 0 | C73: =SUM(C71:C72) -> 0 | D73: =SUM(D71:D72) -> 0
B77: Quantity | C77: Rate
A78: Production Plan | B78: (000 lbs) | C78: (000 lbs/day) | D78: Prodn Days | E78: % Split
A79: CB Lite | B79: 8700 | C79: 100 | D79: =IF(C79<>0,B79/C79,0) -> 87 | E79: =IF($D$91<>0,D79/$D$91,0) -> 0.51901566
A80: CB HSP | C80: =350 -> 350 | D80: =IF(C80<>0,B80/C80,0) -> 0 | E80: =IF($D$91<>0,D80/$D$91,0) -> 0
A81: CB KSLD | C81: =350 -> 350 | D81: =IF(C81<>0,B81/C81,0) -> 0 | E81: =IF($D$91<>0,D81/$D$91,0) -> 0
A82: RPM Lite / NP LWC | C82: =350 -> 350 | D82: =IF(C82<>0,B82/C82,0) -> 0 | E82: =IF($D$91<>0,D82/$D$91,0) -> 0
A83: FilterGuard | C83: =350 -> 350 | D83: =IF(C83<>0,B83/C83,0) -> 0 | E83: =IF($D$91<>0,D83/$D$91,0) -> 0
A84: Air | C84: =350 -> 350 | D84: =IF(C84<>0,B84/C84,0) -> 0 | E84: =IF($D$91<>0,D84/$D$91,0) -> 0
A85: Fusion (#998, 999, 1025) | B85: 950 | C85: 80 | D85: =IF(C85<>0,B85/C85,0) -> 11.875 | E85: =IF($D$91<>0,D85/$D$91,0) -> 0.070842655
A86: SG II CL | B86: 5500 | C86: 80 | D86: =IF(C86<>0,B86/C86,0) -> 68.75 | E86: =IF($D$91<>0,D86/$D$91,0) -> 0.41014169
A87: SG II Ultra CL | B87: 0 | C87: =350 -> 350 | D87: =IF(C87<>0,B87/C87,0) -> 0 | E87: =IF($D$91<>0,D87/$D$91,0) -> 0
A88: SG II KSHD (H) | B88: 0 | C88: =350 -> 350 | D88: =IF(C88<>0,B88/C88,0) -> 0 | E88: =IF($D$91<>0,D88/$D$91,0) -> 0
A89: SaltGuard (FDP-806) | B89: 0 | C89: =350 -> 350 | D89: =IF(C89<>0,B89/C89,0) -> 0 | E89: =IF($D$91<>0,D89/$D$91,0) -> 0
A90: KSXT | B90: 0 | C90: =350 -> 350 | D90: =IF(C90<>0,B90/C90,0) -> 0 | E90: =IF($D$91<>0,D90/$D$91,0) -> 0
A91: Total | B91: =SUM(B79:B90) -> 15150 | C91: =B91/D91 -> 90.380313 | D91: =SUM(D79:D90) -> 167.625 | E91: =IF($D$91<>0,D91/$D$91,0) -> 1
A93: Variable Costs - Material
D95: CB Lite | F95: CB Lite EU | H95: CB KSLD | J95: RPM Lite / NP LWC | L95: CB HSP | N95: Air | AL95: RPM | AN95: CBL KSHD | AP95: AIR
A96: Materials Cost: | B96: Price ($/lb) | C96: Source plant under-absorb | D96: BOM Use/lb | E96: Standard Cost | F96: BOM Use/lb | G96: Standard Cost | H96: BOM Use/lb | I96: Standard Cost | J96: BOM Use/lb | K96: Standard Cost | L96: BOM Use/lb | M96: Standard Cost | N96: BOM Use/lb | O96: Standard Cost | AL96: cost BOM | AM96: plan price 1 | AN96: cost BOM | AO96: plan price 1 | AP96: cost BOM
A97: CARBO LITE (32, 36, 115) | B97: =0.1829+0.032-C97 -> 0.2149 | C97: 0 | D97: =1251371/1262940 -> 0.99083963 | E97: =$B97*D97 -> 0.21293144 | F97: =3608216/3572240 -> 1.010071 | G97: =$B97*F97 -> 0.21706426 | H97: 0 | I97: =$B97*H97 -> 0 | J97: 1 | K97: =$B97*J97 -> 0.2149 | L97: 0 | M97: =$B97*L97 -> 0 | N97: 0 | O97: =$B97*N97 -> 0 | AL97: =K97/B97*1000 -> 1000
A98: CARBOAIR UL (861, 938) GUARD (822) | B98: =0.27228+0.032-C98 -> 0.30428 | C98: 0 | D98: 0 | E98: =$B98*D98 -> 0 | F98: 0 | G98: =$B98*F98 -> 0 | H98: 0 | I98: =$B98*H98 -> 0 | J98: 0 | K98: =$B98*J98 -> 0 | L98: 0 | M98: =$B98*L98 -> 0 | N98: =262800/262440 -> 1.0013717 | O98: =$B98*N98 -> 0.30469739 | AO98: =+B98*1000 -> 304.28 | AP98: =O98/B98*1000 -> 1001.3717
A99: KRYPTOSPHERE LD (976) | B99: =0.465+0.032-C99 -> 0.497 | C99: 0 | D99: 0 | E99: =$B99*D99 -> 0 | F99: 0 | G99: =$B99*F99 -> 0 | H99: =208000/198210 -> 1.0493921 | I99: =$B99*H99 -> 0.52154785 | J99: 0 | K99: =$B99*J99 -> 0 | L99: 0 | M99: =$B99*L99 -> 0 | N99: 0 | O99: =$B99*N99 -> 0
A100: KRYPTOSPHERE HD (873) | B100: =0.973+0.032-C100 -> 1.005 | C100: 0 | D100: 0 | E100: =$B100*D100 -> 0 | F100: 0 | G100: =$B100*F100 -> 0 | H100: 0 | I100: =$B100*H100 -> 0 | J100: 0 | K100: =$B100*J100 -> 0 | L100: 0 | M100: =$B100*L100 -> 0 | N100: 0 | O100: =$B100*N100 -> 0 | AM100: =+B102*1000 -> 377.8 | AN100: =M100/B100*1000 -> 0
A101: NRT KRYPTOSPHERE LD (1200) | B101: =306.29/1000 -> 0.30629 | D101: 0 | E101: =$B101*D101 -> 0 | F101: 0 | G101: =$B101*F101 -> 0 | H101: 0 | I101: =$B101*H101 -> 0 | J101: 0 | K101: =$B101*J101 -> 0 | L101: 0 | M101: =$B101*L101 -> 0 | N101: 0 | O101: =$B101*N101 -> 0
A102: CARBO HSP (19, 824) | B102: =0.3458+0.032-C102 -> 0.3778 | C102: 0 | D102: 0 | E102: =$B102*D102 -> 0 | F102: 0 | G102: =$B102*F102 -> 0 | H102: 0 | I102: =$B102*H102 -> 0 | J102: 0 | K102: =$B102*J102 -> 0 | L102: =429020/422600 -> 1.0151917 | M102: =$B102*L102 -> 0.38353941 | N102: 0 | O102: =$B102*N102 -> 0
A103: CARBOPROP (50) | B103: 0 | C103: 0 | D103: 0 | E103: =$B103*D103 -> 0 | F103: 0 | G103: =$B103*F103 -> 0 | H103: 0 | I103: =$B103*H103 -> 0 | J103: 0 | K103: =$B103*J103 -> 0 | L103: 0 | M103: =$B103*L103 -> 0 | N103: 0 | O103: =$B103*N103 -> 0
A104: SCALEGUARD I CL (812, 951, 1941, 1981, 2006) | B104: 0.6364 | C104: 0 | D104: 0 | E104: =$B104*D104 -> 0 | F104: 0 | G104: =$B104*F104 -> 0 | H104: 0 | I104: =$B104*H104 -> 0 | J104: 0 | K104: =$B104*J104 -> 0 | L104: 0 | M104: =$B104*L104 -> 0 | N104: 0 | O104: =$B104*N104 -> 0
A105: SCALEGUARD IX CL | B105: 0.6364 | C105: 0 | D105: 0 | E105: =$B105*D105 -> 0 | F105: 0 | G105: =$B105*F105 -> 0 | H105: 0 | I105: =$B105*H105 -> 0 | J105: 0 | K105: =$B105*J105 -> 0 | L105: 0 | M105: =$B105*L105 -> 0 | N105: 0 | O105: =$B105*N105 -> 0
A106: SCALEGUARD I KSHD (H) | B106: =1.9036-C106 -> 1.9036 | C106: 0 | D106: 0 | E106: =$B106*D106 -> 0 | F106: 0 | G106: =$B106*F106 -> 0 | H106: 0 | I106: =$B106*H106 -> 0 | J106: 0 | K106: =$B106*J106 -> 0 | L106: 0 | M106: =$B106*L106 -> 0 | N106: 0 | O106: =$B106*N106 -> 0
A107: CL FUSION SUBSTRATE (994) | B107: =337.81/1000 -> 0.33781 | C107: 0 | D107: 0 | E107: =$B107*D107 -> 0 | F107: 0 | G107: =$B107*F107 -> 0 | H107: 0 | I107: =$B107*H107 -> 0 | J107: 0 | K107: =$B107*J107 -> 0 | L107: 0 | M107: =$B107*L107 -> 0 | N107: 0 | O107: =$B107*N107 -> 0
A108: Plenco Resin (30090) | B108: 1.451 | C108: 0 | D108: =36955/1262940 -> 0.029261089 | E108: =$B108*D108 -> 0.04245784 | F108: =134560/3572240 -> 0.037668242 | G108: =$B108*F108 -> 0.054656619 | H108: =7110/198210 -> 0.035871046 | I108: =$B108*H108 -> 0.052048888 | J108: 0 | K108: =$B108*J108 -> 0 | L108: =17363/422600 -> 0.041086133 | M108: =$B108*L108 -> 0.05961598 | N108: =10645/262440 -> 0.040561652 | O108: =$B108*N108 -> 0.058854957 | AM108: =+B109*1000 -> 1200 | AN108: =M108/B108*1000 -> 41.086133 | AO108: =+B108*1000 -> 1451 | AP108: =O108/B108*1000 -> 40.561652
A109: HEXA-EU (30362) | B109: 1.2 | C109: 0 | D109: 0 | E109: =$B109*D109 -> 0 | F109: =15443/3572240 -> 0.0043230578 | G109: =$B109*F109 -> 0.0051876694 | H109: 0 | I109: =$B109*H109 -> 0 | J109: 0 | K109: =$B109*J109 -> 0 | L109: =+H109 -> 0 | M109: =$B109*L109 -> 0 | N109: =1190/262440 -> 0.0045343698 | O109: =$B109*N109 -> 0.0054412437 | AM109: =+B110*1000 -> 3920 | AN109: =M109/B109*1000 -> 0 | AO109: =+B109*1000 -> 1200 | AP109: =O109/B109*1000 -> 4.5343698
A110: Silane-EU (30360) | B110: 3.92 | C110: 0 | D110: =335/1262940 -> 0.00026525409 | E110: =$B110*D110 -> 0.001039796 | F110: =2650/3572240 -> 0.00074183146 | G110: =$B110*F110 -> 0.0029079793 | H110: =127/198210 -> 0.00064073457 | I110: =$B110*H110 -> 0.0025116795 | J110: 0 | K110: =$B110*J110 -> 0 | L110: =330/422600 -> 0.00078088027 | M110: =$B110*L110 -> 0.0030610506 | N110: =320/262440 -> 0.0012193263 | O110: =$B110*N110 -> 0.0047797592 | AM110: =+B111*1000 -> 2080 | AN110: =M110/B110*1000 -> 0.78088027 | AO110: =+B110*1000 -> 3920 | AP110: =O110/B110*1000 -> 1.2193263
A111: Surfactant-EU (30361) | B111: 2.08 | C111: 0 | D111: 0 | E111: =$B111*D111 -> 0 | F111: =2222/3572240 -> 0.00062201868 | G111: =$B111*F111 -> 0.0012937988 | H111: 0 | I111: =$B111*H111 -> 0 | J111: 0 | K111: =$B111*J111 -> 0 | L111: =+H111 -> 0 | M111: =$B111*L111 -> 0 | N111: =542/262440 -> 0.002065234 | O111: =$B111*N111 -> 0.0042956866 | AM111: =+B112*1000 -> 2470 | AN111: =M111/B111*1000 -> 0 | AO111: =+B111*1000 -> 2080 | AP111: =O111/B111*1000 -> 2.065234
A112: Surfactant (30054) | B112: 2.47 | C112: 0 | D112: =923/1262940 -> 0.0007308344 | E112: =$B112*D112 -> 0.001805161 | F112: 0 | G112: =$B112*F112 -> 0 | H112: =170/198210 -> 0.0008576762 | I112: =$B112*H112 -> 0.0021184602 | J112: 0 | K112: =$B112*J112 -> 0 | L112: =108/422600 -> 0.00025556081 | M112: =$B112*L112 -> 0.00063123521 | N112: 0 | O112: =$B112*N112 -> 0 | AN112: =M112/B112*1000 -> 0.25556081 | AP112: =O112/B112*1000 -> 0
A113: Hexamine (30055) | B113: 2.04 | C113: 0 | D113: =2700/1262940 -> 0.0021378688 | E113: =$B113*D113 -> 0.0043612523 | F113: 0 | G113: =$B113*F113 -> 0 | H113: =1900/198210 -> 0.0095857928 | I113: =$B113*H113 -> 0.019555017 | J113: 0 | K113: =$B113*J113 -> 0 | L113: =5000/422600 -> 0.011831519 | M113: =$B113*L113 -> 0.024136299 | N113: 0 | O113: =$B113*N113 -> 0 | AN113: =M113/B113*1000 -> 11.831519 | AP113: =O113/B113*1000 -> 0
A114: Silane (30058) | B114: 3.92 | C114: 0 | D114: =250/1262940 -> 0.00019795081 | E114: =$B114*D114 -> 0.00077596719 | F114: 0 | G114: =$B114*F114 -> 0 | H114: 0 | I114: =$B114*H114 -> 0 | J114: 0 | K114: =$B114*J114 -> 0 | L114: 0 | M114: =$B114*L114 -> 0 | N114: 0 | O114: =$B114*N114 -> 0
A115: WB Concentrate (30454) | B115: 15.83 | C115: 0 | D115: 0 | E115: =$B115*D115 -> 0 | F115: 0 | G115: =$B115*F115 -> 0 | H115: 0 | I115: =$B115*H115 -> 0 | J115: 0.0125 | K115: =$B115*J115 -> 0.197875 | L115: 0 | M115: =$B115*L115 -> 0 | N115: 0 | O115: =$B115*N115 -> 0 | AL115: =K115/B115*1000 -> 12.5 | AN115: =M115/B115*1000 -> 0 | AP115: =O115/B115*1000 -> 0
A116: BYK 20798 (30242) | B116: 11.85 | C116: 0 | D116: 0 | E116: =$B116*D116 -> 0 | F116: 0 | G116: =$B116*F116 -> 0 | H116: 0 | I116: =$B116*H116 -> 0 | J116: =275/160460 -> 0.0017138228 | K116: =$B116*J116 -> 0.0203088 | L116: 0 | M116: =$B116*L116 -> 0 | N116: =622/262440 -> 0.0023700655 | O116: =$B116*N116 -> 0.028085277 | AN116: =M116/B116*1000 -> 0 | AO116: =+B116*1000 -> 11850 | AP116: =O116/B116*1000 -> 2.3700655
A118: Standard Cost Contribution: | E118: $/lb | G118: $/lb | I118: $/lb | K118: $/lb | M118: $/lb | O118: $/lb
A119: Substrate* | E119: =SUM(E97:E107) -> 0.21293144 | G119: =SUM(G97:G107) -> 0.21706426 | I119: =SUM(I97:I107) -> 0.52154785 | K119: =SUM(K97:K107) -> 0.2149 | M119: =SUM(M97:M107) -> 0.38353941 | O119: =SUM(O97:O107) -> 0.30469739
A120: Resin | E120: =SUM(E108:E108) -> 0.04245784 | G120: =SUM(G108:G108) -> 0.054656619 | I120: =SUM(I108:I108) -> 0.052048888 | K120: =SUM(K108:K108) -> 0 | M120: =SUM(M108:M108) -> 0.05961598 | O120: =SUM(O108:O108) -> 0.058854957 | AL120: =SUM(AL97:AL115) -> 1012.5 | AN120: =SUM(AN97:AN116) -> 53.954094 | AP120: =SUM(AP97:AP116) -> 1052.1224
...

Sheet NI RC 2022 Std (BOD)
A1: New Iberia Resin Coating | AB1: Activity | AC1: 10001005 | AD1: 10001005 | AE1: Gross | AF1: Qty/1000 | AG1: 10001005 | AH1: Absorbed | AI1: 10001005 | AJ1: Abs Cost
A2: 2022 STANDARDS | AA2: Unit | AB2: Type | AC2: Total Cost | AD2: Total Qty | AE2: Unit Cost | AF2: Prod lbs | AG2: Absorption | AH2: Unit Cost | AI2: Underabs | AJ2: per 10000
B3: CARBOBond Lite | E3: CARBOBond Lite EU | H3: CARBOBond KSLD | K3: RPM LITE / NEUTRAPROP LWC | N3: CARBOBond KSHD | Q3: CARBO AIR
B4: 21 Standard | C4: 19 Actual | D4: 21 Standard | E4: 22 Standard | F4: 19 Actual | G4: =+D4 -> 21 Standard | H4: 22 Standard | I4: =+C4 -> 19 Actual | J4: =+D4 -> 21 Standard | K4: 21 Standard | L4: 18 Actual | M4: =+D4 -> 21 Standard | N4: 22 Standard | O4: 21 Actual | P4: =+D4 -> 21 Standard | Q4: 22 Standard | R4: 18 Actual | S4: =+D4 -> 21 Standard | V4: Composite | W4: Absorb | X4: Underabsorb
C5: (Jan-Sept) | F5: (Jan-Sept) | I5: =+C5 -> (Jan-Sept) | L5: (Jan-Nov) | R5: (Jan-Oct)
A6: Materials - Substrate | B6: =E120 -> 0.18382013 | C6: 0.16092998 | D6: 0.1639529 | E6: =G120 -> 0.18884365 | F6: 0.15896741 | G6: 0.13998074 | H6: =+I120 -> 0.41938749 | I6: 0.30191317 | J6: 0.28067655 | K6: =K120 -> 0.19651963 | L6: 0.18307969 | M6: 0.15362762 | N6: =+M101 -> 0.80389422 | O6: 0 | P6: 0 | Q6: =+O99 -> 0.19086145 | R6: 0.15968841 | S6: 0.14400712 | V6: =($B6*$B$29+$E6*$E$29+$H6*$H$29+$K6*$K$29+$N6*$N$29+$Q6*$Q$29+$B37*$B$60+$E37*$E$60+$H37*$H$60+$K37*$K$60+$N37*$N$60+$Q37*$Q$60)/$B$64 -> 0.2930518 | W6: =V6 -> 0.2930518
A7: Materials - Substrate Under-Absorption | B7: =$C98*D98 -> 0 | D7: 0 | E7: =$C98*F98 -> 0 | G7: 0.08643106 | H7: =$C98*I98 -> 0 | J7: 0.22562455 | K7: =$C98*J98 -> 0 | M7: 0.094857323 | N7: =$C98*O98 -> 0 | P7: 0 | S7: 0.08891715 | V7: 0 | W7: 0
A8: Materials - Resin & Chemicals | B8: =E121+E122 -> 0.04393998 | C8: 0.051903794 | D8: 0.038078 | E8: =G121+G122 -> 0.060015662 | F8: 0.053990671 | G8: 0.053042779 | H8: =+I121+I122 -> 0.056384154 | I8: 0.05384576 | J8: 0.0471079 | K8: =K121+K122 -> 0.070148364 | L8: 0.071924563 | M8: 0.15903358 | N8: =+M121+M122 -> 0.056384154 | O8: 0 | P8: 0 | Q8: =+O121+O122 -> 0.087415456 | R8: 0.072759577 | S8: 0.074666525 | V8: =($B8*$B$29+$E8*$E$29+$H8*$H$29+$K8*$K$29+$N8*$N$29+$Q8*$Q$29+$B39*$B$60+$E39*$E$60+$H39*$H$60+$K39*$K$60+$N39*$N$60+$Q39*$Q$60)/$B$64 -> 0.059937247 | W8: =V8 -> 0.059937247 | X8: =V8-W8 -> 0
A9: Electricity | B9: =E161 -> 0.010280976 | C9: 0.0077075348 | D9: 0.0059095494 | E9: =G161 -> 0.0092314722 | F9: 0.0064153677 | G9: 0.010135435 | H9: =J161 -> 0.043221874 | I9: 0.023850562 | J9: 0.010726 | K9: =K161 -> 0.010280976 | L9: 0.019218863 | M9: 0.010135435 | N9: =+M161 -> 0.006738662 | O9: 0 | P9: 0 | Q9: =+O161 -> 0.0089969295 | R9: 0.006525594 | S9: 0.010135435 | V9: =($B9*$B$29+$E9*$E$29+$H9*$H$29+$K9*$K$29+$N9*$N$29+$Q9*$Q$29+$B40*$B$60+$E40*$E$60+$H40*$H$60+$K40*$K$60+$N40*$N$60+$Q40*$Q$60)/$B$64 -> 0.0090509841 | W9: =V9 -> 0.0090509841 | X9: =V9-W9 -> 0 | AA9: kwh | AB9: ELE01 | AC9: =ROUND(((D161*B$29*1000)+(F161*E$29*1000)+(H161*H$29*1000)+(J161*K$29*1000)+(L161*N$29*1000)+(N161*Q$29*1000)+(D168*B$60*1000)+(F168*E$60*1000)+(H168*H$60*1000)+(J168*K$60*1000)+(L168*N$60*1000)+(N168*Q$60*1000))*$B161,0) -> 302219 | AD9: =ROUND((D161*B$29*1000)+(F161*E$29*1000)+(H161*H$29*1000)+(J161*K$29*1000)+(L161*N$29*1000)+(N161*Q$29*1000)+(D168*B$60*1000)+(F168*E$60*1000)+(H168*H$60*1000)+(J168*K$60*1000)+(L168*N$60*1000)+(N168*Q$60*1000),0) -> 1270548 | AE9: =AC9/AD9 -> 0.23786508 | AF9: =ROUND(AD9/$B$64,3) -> 36.721 | AG9: =ROUND(W9*$AC$29,0) -> 313164 | AH9: =AG9/AD9 -> 0.24647947 | AI9: =AC9-AG9 -> -10945 | AJ9: =AH9*10000 -> 2464.7947
A10: Gas | B10: =E162 -> 0.0017614437 | C10: 0.00096524487 | D10: 0.0013242333 | E10: =G162 -> 0.00153375 | F10: 0.00088623983 | G10: 0.0011247591 | H10: =J162 -> 0.00029427407 | I10: 0.0011573683 | J10: 0.00126 | K10: =K162 -> 0.0017614437 | L10: 0.0011031846 | M10: 0.0011247591 | N10: =+M162 -> 0.0013537383 | O10: 0 | P10: 0 | Q10: =+O162 -> 0.0038428259 | R10: 0.0011625955 | S10: 0.0011247591 | V10: =($B10*$B$29+$E10*$E$29+$H10*$H$29+$K10*$K$29+$N10*$N$29+$Q10*$Q$29+$B41*$B$60+$E41*$E$60+$H41*$H$60+$K41*$K$60+$N41*$N$60+$Q41*$Q$60)/$B$64 -> 0.001563011 | W10: =V10 -> 0.001563011 | X10: =V10-W10 -> 0 | AA10: mbtu | AB10: GAS01 | AC10: =ROUND(((D162*B$29*1000)+(F162*E$29*1000)+(H162*H$29*1000)+(J162*K$29*1000)+(L162*N$29*1000)+(N162*Q$29*1000)+(D169*B$60*1000)+(F169*E$60*1000)+(H169*H$60*1000)+(J169*K$60*1000)+(L169*N$60*1000)+(N169*Q$60*1000))*$B162,0) -> 54398 | AD10: =ROUND(((D162*B$29*1000)+(F162*E$29*1000)+(H162*H$29*1000)+(J162*K$29*1000)+(L162*N$29*1000)+(N162*Q$29*1000)+(D169*B$60*1000)+(F169*E$60*1000)+(H169*H$60*1000)+(J169*K$60*1000)+(L169*N$60*1000)+(N169*Q$60*1000))*1000,0) -> 9087958 | AE10: =AC10/AD10 -> 0.0059857231 | AF10: =ROUND(AD10/$B$64,3) -> 262.658 | AG10: =ROUND(W10*$AC$29,0) -> 54080 | AH10: =AG10/AD10 -> 0.0059507317 | AI10: =AC10-AG10 -> 318 | AJ10: =AH10*10000 -> 59.507317
A11: R&M Supplies and Service | B11: =$H$177 -> 0.0034682081 | C11: 0.0052601959 | D11: 0.006 | E11: =$H$177 -> 0.0034682081 | F11: 0.0051242876 | G11: 0.0086705202 | H11: =$H$177 -> 0.0034682081 | I11: 0.023215913 | J11: 0.0099121126 | K11: =$H$177 -> 0.0034682081 | L11: 0.026688594 | M11: 0.0086705202 | N11: =$H$177 -> 0.0034682081 | O11: 0 | P11: 0 | Q11: =$H$177 -> 0.0034682081 | R11: 0.016241103 | S11: 0.0086705202 | V11: =($B11*$B$29+$E11*$E$29+$H11*$H$29+$K11*$K$29+$N11*$N$29+$Q11*$Q$29+$B42*$B$60+$E42*$E$60+$H42*$H$60+$K42*$K$60+$N42*$N$60+$Q42*$Q$60)/$B$64 -> 0.0034682081 | W11: =V11 -> 0.0034682081 | X11: =V11-W11 -> 0 | AA11: lb | AB11: RMS01 | AC11: =ROUND(G177,0) -> 120000 | AD11: =$B$64*1000 -> 34600000 | AE11: =AC11/AD11 -> 0.0034682081 | AF11: =ROUND(AD11/$B$64,3) -> 1000 | AG11: =ROUND(W11*$AC$29,0) -> 120000 | AH11: =AG11/AD11 -> 0.0034682081 | AI11: =AC11-AG11 -> 0 | AJ11: =AH11*10000 -> 34.682081
A12: Manufacturing Supplies | B12: =$H$180 -> 0.00028901734 | C12: 0.00028145605 | D12: 0.002 | E12: =$H$180 -> 0.00028901734 | F12: 0.0001613237 | G12: 0.00043352601 | H12: =$H$180 -> 0.00028901734 | I12: 0.00076914757 | J12: 0.00049560563 | K12: =$H$180 -> 0.00028901734 | L12: 0.0013365915 | M12: 0.00043352601 | N12: =$H$180 -> 0.00028901734 | O12: 0 | P12: 0 | Q12: =$H$180 -> 0.00028901734 | R12: 0.00053366327 | S12: 0.00043352601 | V12: =($B12*$B$29+$E12*$E$29+$H12*$H$29+$K12*$K$29+$N12*$N$29+$Q12*$Q$29+$B43*$B$60+$E43*$E$60+$H43*$H$60+$K43*$K$60+$N43*$N$60+$Q43*$Q$60)/$B$64 -> 0.00028901734 | W12: =V12 -> 0.00028901734 | X12: =V12-W12 -> 0 | AA12: lb | AB12: MFG01 | AC12: =ROUND(G180,0) -> 10000 | AD12: =$B$64*1000 -> 34600000 | AE12: =AC12/AD12 -> 0.00028901734 | AF12: =ROUND(AD12/$B$64,3) -> 1000 | AG12: =ROUND(W12*$AC$29,0) -> 10000 | AH12: =AG12/AD12 -> 0.00028901734 | AI12: =AC12-AG12 -> 0 | AJ12: =AH12*10000 -> 2.8901734
A13: Other variable | B13: =$H$183 -> 0.0043352601 | C13: 0.005539271 | D13: 0.006 | E13: =$H$183 -> 0.0043352601 | F13: 0.0047523717 | G13: 0.0057803468 | H13: =$H$183 -> 0.0043352601 | I13: 0.017048253 | J13: 0.0066080751 | K13: =$H$183 -> 0.0043352601 | L13: 0.026821614 | M13: 0.0057803468 | N13: =$H$183 -> 0.0043352601 | O13: 0 | P13: 0 | Q13: =$H$183 -> 0.0043352601 | R13: 0.0059964109 | S13: 0.0057803468 | V13: =($B13*$B$29+$E13*$E$29+$H13*$H$29+$K13*$K$29+$N13*$N$29+$Q13*$Q$29+$B44*$B$60+$E44*$E$60+$H44*$H$60+$K44*$K$60+$N44*$N$60+$Q44*$Q$60)/$B$64 -> 0.0043352601 | W13: =V13 -> 0.0043352601 | X13: =V13-W13 -> 0 | AA13: lb | AB13: VAR01 | AC13: =ROUND(G183,0) -> 150000 | AD13: =$B$64*1000 -> 34600000 | AE13: =AC13/AD13 -> 0.0043352601 | AF13: =ROUND(AD13/$B$64,3) -> 1000 | AG13: =ROUND(W13*$AC$29,0) -> 150000 | AH13: =AG13/AD13 -> 0.0043352601 | AI13: =AC13-AG13 -> 0 | AJ13: =AH13*10000 -> 43.352601
A14: Total Variable Costs | B14: =SUM(B6:B13) -> 0.24789502 | C14: =SUM(C6:C13) -> 0.23258747 | D14: =SUM(D6:D13) -> 0.22326468 | E14: =SUM(E6:E13) -> 0.26771702 | F14: =SUM(F6:F13) -> 0.23029767 | G14: 0.30559917 | H14: =SUM(H6:H13) -> 0.52738028 | I14: =SUM(I6:I13) -> 0.42180018 | J14: =SUM(J6:J13) -> 0.5824108 | K14: =SUM(K6:K13) -> 0.2868029 | L14: =SUM(L6:L13) -> 0.3301731 | M14: 0.43366311 | N14: =SUM(N6:N13) -> 0.87646326 | O14: =SUM(O6:O13) -> 0 | P14: =SUM(P6:P13) -> 0 | Q14: =SUM(Q6:Q13) -> 0.29920915 | R14: =SUM(R6:R13) -> 0.26290735 | S14: 0.33373539 | V14: =SUM(V6:V13) -> 0.37169553 | W14: =SUM(W6:W13) -> 0.37169553 | X14: =SUM(X6:X13) -> 0 | AC14: =SUM(AC9:AC13) -> 636617 | AG14: =SUM(AG9:AG13) -> 647244 | AI14: =SUM(AI9:AI13) -> -10627
A16: Production Labor | B16: =$D$214/$B$64/1000 -> 0.018490042 | C16: 0.018200142 | D16: 0.035940795 | E16: =$D$214/$B$64/1000 -> 0.018490042 | F16: 0.020063713 | G16: 0.011741675 | H16: =$D$214/$B$64/1000 -> 0.018490042 | I16: 0.012521635 | J16: 0.014552451 | K16: =$D$214/$B$64/1000 -> 0.018490042 | L16: 0.032785827 | M16: 0.011741675 | N16: =$D$214/$B$64/1000 -> 0.018490042 | O16: 0 | P16: 0 | Q16: =$D$214/$B$64/1000 -> 0.018490042 | R16: 0.013727223 | S16: 0.011741675 | V16: =($B16*$B$29+$E16*$E$29+$H16*$H$29+$K16*$K$29+$N16*$N$29+$Q16*$Q$29+$B47*$B$60+$E47*$E$60+$H47*$H$60+$K47*$K$60+$N47*$N$60+$Q47*$Q$60)/$B$64 -> 0.018490042 | W16: =+W24-W14 -> 0.031093519 | X16: =V16-W16 -> -0.012603477 | AA16: hr | AB16: DLAB01 | AC16: =ROUND(D212,0) -> 670220 | AD16: =ROUND(B212,0) -> 22000 | AE16: =AC16/AD16 -> 30.464545 | AF16: =ROUND(AD16/$B$64,3) -> 0.636 | AG16: =ROUND(W16*$AC$29,0) -> 1075836 | AH16: =AG16/AD16 -> 48.901636 | AI16: =AC16-AG16 -> -405616 | AJ16: =AH16*10000 -> 489016.36
A17: Repairs & Maintenance Labor | B17: =$G$214/$B$64/1000 -> 0.0044936416 | C17: 0.0048304191 | D17: 0.0113712 | E17: =$G$214/$B$64/1000 -> 0.0044936416 | F17: 0.0044471791 | G17: 0.0041080925 | H17: =$G$214/$B$64/1000 -> 0.0044936416 | I17: 0.0044303098 | J17: 0.004696359 | K17: =$G$214/$B$64/1000 -> 0.0044936416 | L17: 0.0088578354 | M17: 0.0041080925 | N17: =$G$214/$B$64/1000 -> 0.0044936416 | O17: 0 | P17: 0 | Q17: =$G$214/$B$64/1000 -> 0.0044936416 | R17: 0.0016693747 | S17: 0.0041080925 | V17: =($B17*$B$29+$E17*$E$29+$H17*$H$29+$K17*$K$29+$N17*$N$29+$Q17*$Q$29+$B48*$B$60+$E48*$E$60+$H48*$H$60+$K48*$K$60+$N48*$N$60+$Q48*$Q$60)/$B$64 -> 0.0044936416 | W17: 0 | X17: =V17-W17 -> 0.0044936416 | AA17: hr | AB17: MLAB01 | AC17: =ROUND(G212,0) -> 155480 | AD17: =ROUND(E212,0) -> 4400 | AE17: =AC17/AD17 -> 35.336364 | AF17: =ROUND(AD17/$B$64,3) -> 0.127 | AG17: =ROUND(W17*$AC$29,0) -> 0 | AH17: =AG17/AD17 -> 0 | AI17: =AC17-AG17 -> 155480 | AJ17: =AH17*10000 -> 0
A18: Indirect Payroll Costs (Benefits) | B18: =$J$214/$B$64/1000 -> 0.0081804217 | C18: 0.0068508297 | D18: 0.014188877 | E18: =$J$214/$B$64/1000 -> 0.0081804217 | F18: 0.0059757405 | G18: 0.0072598437 | H18: =$J$214/$B$64/1000 -> 0.0081804217 | I18: 0.014238166 | J18: 0.008765191 | K18: =$J$214/$B$64/1000 -> 0.0081804217 | L18: 0.038686584 | M18: 0.0072598437 | N18: =$J$214/$B$64/1000 -> 0.0081804217 | O18: 0 | P18: 0 | Q18: =$J$214/$B$64/1000 -> 0.0081804217 | R18: 0.0056633179 | S18: 0.0072598437 | V18: =($B18*$B$29+$E18*$E$29+$H18*$H$29+$K18*$K$29+$N18*$N$29+$Q18*$Q$29+$B49*$B$60+$E49*$E$60+$H49*$H$60+$K49*$K$60+$N49*$N$60+$Q49*$Q$60)/$B$64 -> 0.0081804217 | W18: 0 | X18: =V18-W18 -> 0.0081804217 | AA18: hr | AB18: IPC01 | AC18: =ROUND(J212,0) -> 294186 | AD18: =ROUND(H212,0) -> 26400 | AE18: =AC18/AD18 -> 11.143409 | AF18: =ROUND(AD18/$B$64,3) -> 0.763 | AG18: =ROUND(W18*$AC$29,0) -> 0 | AH18: =AG18/AD18 -> 0 | AI18: =AC18-AG18 -> 294186 | AJ18: =AH18*10000 -> 0
A19: Supervision | B19: =$E$240 -> 0.0044774566 | C19: 0.0022776301 | D19: 0 | E19: =$E$240 -> 0.0044774566 | F19: 0.0019225049 | G19: 0.002449852 | H19: =$E$240 -> 0.0044774566 | I19: 0.0092721693 | J19: 0.0028006635 | K19: =$E$240 -> 0.0044774566 | L19: 0.01254166 | M19: 0.002449852 | N19: =$E$240 -> 0.0044774566 | O19: 0 | P19: 0 | Q19: =$E$240 -> 0.0044774566 | R19: 0.0023710733 | S19: 0.002449852 | V19: =($B19*$B$29+$E19*$E$29+$H19*$H$29+$K19*$K$29+$N19*$N$29+$Q19*$Q$29+$B50*$B$60+$E50*$E$60+$H50*$H$60+$K50*$K$60+$N50*$N$60+$Q50*$Q$60)/$B$64 -> 0.0044774566 | W19: 0 | X19: =V19-W19 -> 0.0044774566 | AA19: lb | AB19: SUP01 | AC19: =ROUND(C240,0) -> 154920 | AD19: =$B$64*1000 -> 34600000 | AE19: =AC19/AD19 -> 0.0044774566 | AF19: =ROUND(AD19/$B$64,3) -> 1000 | AG19: =ROUND(W19*$AC$29,0) -> 0 | AH19: =AG19/AD19 -> 0 | AI19: =AC19-AG19 -> 154920 | AJ19: =AH19*10000 -> 0
A20: Depreciation | B20: =$E$241 -> 0.0032393064 | C20: 0.061012872 | D20: 0.01039048 | E20: =$E$241 -> 0.0032393064 | F20: 0.051498884 | G20: 0.06367052 | H20: =$E$241 -> 0.0032393064 | I20: 0.24870656 | J20: 0.072787947 | K20: =$E$241 -> 0.0032393064 | L20: 0.34045176 | M20: 0.06367052 | N20: =$E$241 -> 0.0032393064 | O20: 0 | P20: 0 | Q20: =$E$241 -> 0.0032393064 | R20: 0.064182394 | S20: 0.06367052 | V20: =($B20*$B$29+$E20*$E$29+$H20*$H$29+$K20*$K$29+$N20*$N$29+$Q20*$Q$29+$B51*$B$60+$E51*$E$60+$H51*$H$60+$K51*$K$60+$N51*$N$60+$Q51*$Q$60)/$B$64 -> 0.0032393064 | W20: =W24-W14-W16-W17-W18-W19-W21 -> 0 | X20: =V20-W20 -> 0.0032393064 | AA20: lb | AB20: DEP01 | AC20: =ROUND(C241,0) -> 112080 | AD20: =($B$29+$E$29+$H$29+$K$29+$N$29+B60+E60+H60+K60+N60+$Q$29+Q60)*1000 -> 34600000 | AE20: =AC20/AD20 -> 0.0032393064 | AF20: =ROUND(AD20/($B$29+$E$29+$H$29+$K$29+$N$29+B60+E60+H60+K60+N60),3) -> 1029.762 | AG20: =ROUND(W20*$AC$29,0) -> 0 | AH20: =AG20/AD20 -> 0 | AI20: =AC20-AG20 -> 112080 | AJ20: =AH20*10000 -> 0
A21: Insurance & Taxes | B21: =$E$242 -> 0.016269364 | C21: 0.01547789 | D21: 0.03763008 | E21: =$E$242 -> 0.016269364 | F21: 0.012959419 | G21: 0.014046243 | H21: =$E$242 -> 0.016269364 | I21: 0.064467032 | J21: 0.018172206 | K21: =$E$242 -> 0.016269364 | L21: 0.083528141 | M21: 0.014046243 | N21: =$E$242 -> 0.016269364 | O21: 0 | P21: 0 | Q21: =$E$242 -> 0.016269364 | R21: 0.015675972 | S21: 0.014046243 | V21: =($B21*$B$29+$E21*$E$29+$H21*$H$29+$K21*$K$29+$N21*$N$29+$Q21*$Q$29+$B52*$B$60+$E52*$E$60+$H52*$H$60+$K52*$K$60+$N52*$N$60+$Q52*$Q$60)/$B$64 -> 0.016269364 | W21: =W24-W14-W16-W17-W18-W19 -> 0 | X21: =V21-W21 -> 0.016269364 | AA21: lb | AB21: INS01 | AC21: =ROUND(C242,0) -> 562920 | AD21: =$B$64*1000 -> 34600000 | AE21: =AC21/AD21 -> 0.016269364 | AF21: =ROUND(AD21/$B$64,3) -> 1000 | AG21: =ROUND(W21*$AC$29,0) -> 0 | AH21: =AG21/AD21 -> 0 | AI21: =AC21-AG21 -> 562920 | AJ21: =AH21*10000 -> 0
A22: Total Fixed Costs | B22: =SUM(B16:B21) -> 0.055150233 | C22: =SUM(C16:C21) -> 0.10864978 | D22: =SUM(D16:D21) -> 0.10952143 | E22: =SUM(E16:E21) -> 0.055150233 | F22: =SUM(F16:F21) -> 0.09686744 | G22: 0.10327623 | H22: =SUM(H16:H21) -> 0.055150233 | I22: =SUM(I16:I21) -> 0.35363588 | J22: =SUM(J16:J21) -> 0.12177482 | K22: =SUM(K16:K21) -> 0.055150233 | L22: =SUM(L16:L21) -> 0.51685181 | M22: 0.10327623 | N22: =SUM(N16:N21) -> 0.055150233 | O22: =SUM(O16:O21) -> 0 | P22: =SUM(P16:P21) -> 0 | Q22: =SUM(Q16:Q21) -> 0.055150233 | R22: =SUM(R16:R21) -> 0.10328935 | S22: 0.10327623 | V22: =SUM(V16:V21) -> 0.055150233 | W22: =SUM(W16:W21) -> 0.031093519 | X22: =SUM(X16:X21) -> 0.024056713 | AC22: =SUM(AC16:AC21) -> 1949806 | AG22: =SUM(AG16:AG21) -> 1075836 | AI22: =SUM(AI16:AI21) -> 873970
AA23: Activity Cost | AC23: =AC14+AC22 -> 2586423 | AG23: =AG14+AG22 -> 1723080 | AI23: =AI14+AI22 -> 863343
A24: Total Cost per Pound at Gross | B24: =B14+B22 -> 0.30304525 | C24: =C14+C22 -> 0.34123726 | D24: =D14+D22 -> 0.33278611 | E24: =E14+E22 -> 0.32286725 | F24: =F14+F22 -> 0.32716511 | G24: =G14+G22 -> 0.40887539 | H24: =H14+H22 -> 0.58253051 | I24: =I14+I22 -> 0.77543605 | ... S24: =S14+S22 -> 0.43701161 | V24: =V14+V22 -> 0.42684576 | W24: =0.0498+V6+V7+V8 -> 0.40278904 | X24: =X14+X22 -> 0.024056713 | AA24: $/lb excl matl | AC24: =ROUND(AC23/AC29,5) -> 0.07475 | AG24: =ROUND(AG23/AC29,5) -> 0.0498 | AI24: =ROUND(AI23/AC29,5) -> 0.02495
A25: Less: Substrate Plant Under-absorption | B25: =-B7 -> 0 | D25: 0 | E25: =-E7 -> 0 | G25: -0.02807392 | H25: =-H7 -> 0 | J25: -0.22562455 | K25: =-K7 -> 0 | M25: -0.02886962 | N25: =-N7 -> 0 | Q25: =-Q7 -> 0 | S25: -0.027061741 | V25: 0
A26: Less: RC Under-absorption | B26: =IF(B9+B10+B11+B12+B13+B22>0.0498,0.0498-B9-B10-B11-B12-B13-B22,0) -> -0.025485138 | C26: -0.079184632 | D26: -0.081 | E26: 0 | F26: =IF(F9+F10+F11+F12+F13+F22>0.0498,0.0498-F9-F10-F11-F12-F13-F22,0) -> -0.064407031 | G26: =IF(G9+G10+G11+G12+G13+G22>0.0498,0.0498-G9-G10-G11-G12-G13-G22,0) -> -0.079620814 | H26: 0 | I26: -0.36723743 | J26: =IF(J9+J10+J11+J12+J13+J22>0.0498,0.0498-J9-J10-J11-J12-J13-J22,0) -> -0.10097661 | K26: =IF(K9+K10+K11+K12+K13+K22>0.0498,0.0498-K9-K10-K11-K12-K13-K22,0) -> -0.025485138 | L26: =IF(L9+L10+L11+L12+L13+L22>0.0498,0.0498-L9-L10-L11-L12-L13-L22,0) -> -0.54222065 | M26: =IF(M9+M10+M11+M12+M13+M22>0.0498,0.0498-M9-M10-M11-M12-M13-M22,0) -> -0.079620814 | N26: 0 | O26: =IF(O9+O10+O11+O12+O13+O22>0.0498,0.0498-O9-O10-O11-O12-O13-O22,0) -> 0 | P26: =IF(P9+P10+P11+P12+P13+P22>0.0498,0.0498-P9-P10-P11-P12-P13-P22,0) -> 0 | Q26: 0 | R26: =IF(R9+R10+R11+R12+R13+R22>0.0498,0.0498-R9-R10-R11-R12-R13-R22,0) -> -0.083948722 | S26: =IF(S9+S10+S11+S12+S13+S22>0.0498,0.0498-S9-S10-S11-S12-S13-S22,0) -> -0.079620814 | V26: =($B26*$B$29+$E26*$E$29+$H26*$H$29+$K26*$K$29+$N26*$N$29+$Q26*$Q$29+$B57*$B$60+$E57*$E$60+$H57*$H$60+$K57*$K$60+$N57*$N$60+$Q57*$Q$60)/$B$64 -> 0
A27: Net Cost per Pound Absorbed | B27: =SUM(B24:B26) -> 0.27756011 | C27: =SUM(C24:C26) -> 0.26205262 | D27: =SUM(D24:D26) -> 0.25178611 | E27: =SUM(E24:E26) -> 0.32286725 | F27: =SUM(F24:F26) -> 0.26275808 | G27: =SUM(G24:G26) -> 0.30118066 | H27: =SUM(H24:H26) -> 0.58253051 | I27: =SUM(I24:I26) -> 0.40819862 | ... S27: =SUM(S24:S26) -> 0.33032906 | V27: =SUM(V24:V26) -> 0.42684576
AA28: $/lb incl matl | AC28: =ROUND((AC24+(B8*B29+E8*E29+H8*H29+K8*K29+N8*N29+Q8*Q29+B39*B60+E39*E60+H39*H60)/B64),5) -> 0.13469 | AG28: =ROUND(AG24+W8,5) -> 0.10974 | AI28: =ROUND(AI24+X8,5) -> 0.02495
A29: Total Production (000 lbs) | B29: 0 | C29: 15431 | D29: 3000 | E29: 25500 | F29: 9412 | G29: 10000 | H29: =+B81 -> 300 | I29: 74 | J29: 0 | K29: =+B82 -> 0 | L29: 254 | M29: 1000 | N29: =+B80 -> 5000 | O29: 0 | P29: 0 | Q29: =+B84 -> 1000 | R29: 3647.15 | S29: 1300 | V29: =B29+E29+H29+K29+N29+Q29+B60+E60+H60+K60+N60+Q60 -> 34600 | AA29: Prod lbs | AC29: =ROUND($B$64*1000,0) -> 34600000
B34: Fusion | E34: ScaleGuard II CL | H34: KSXT | K34: ScaleGuard II KSHD (H) | N34: XX | Q34: XX
B35: 22 Standard | C35: 19 Actual | D35: =+D4 -> 21 Standard | E35: 22 Standard | F35: 19 Actual | G35: =+D4 -> 21 Standard | H35: 22 Standard | I35: 19 Actual | J35: =+D4 -> 21 Standard | K35: =+B4 -> 21 Standard | L35: 19 Actual | M35: =+D4 -> 21 Standard | N35: =+B4 -> 21 Standard | O35: 19 Actual | P35: =+D4 -> 21 Standard | Q35: =+B4 -> 21 Standard | R35: 19 Actual | S35: =+D4 -> 21 Standard
C36: (Jan-Sept) | F36: (Jan-Sept) | I36: (Jan-Sept) | L36: (Jan-Sept)
A37: Materials - Substrate | B37: =E149 -> 0.21326582 | C37: 0.34054143 | D37: 0.22007722 | E37: =G149 -> 0.51387049 | F37: 0.4105 | G37: 0.41282107 | H37: =I149 -> 0.41122404 | I37: 0.26541432 | J37: 0.28800984 | L37: 0 | M37: 1.8829093 | O37: 0 | P37: 0 | R37: 0 | S37: 0
A38: Materials - Substrate Under-Absorption | B38: =$C135*D135 -> 0 | D38: 0 | E38: =$C133*F133 -> 0 | G38: 0.046029189 | H38: =$C130*H130 -> 0 | J38: 0.09332723 | M38: 0.16177979 | P38: 0 | S38: 0
A39: Materials - Resin & Chemicals | B39: =E150+E151 -> 0.067925472 | C39: 0.093737947 | D39: 0.0467607 | E39: =G150+G151 -> 0.04253052 | F39: 0.043894371 | G39: 0.04221848 | H39: =I150+I151 -> 0.0059336936 | I39: 0.04843802 | J39: 0.008758525 | L39: 0 | M39: 0.042578635 | O39: 0 | P39: 0 | R39: 0 | S39: 0
A40: Electricity | B40: =E168 -> 0.009641779 | C40: 0.026041382 | D40: 0.0059095494 | E40: =G168 -> 0.0058784926 | F40: 0.014645894 | G40: 0.0059095494 | H40: =I168 -> 0.0076716424 | I40: 0.010462455 | J40: 0.0059095494 | L40: 0 | M40: 0.010135435 | O40: 0 | P40: 0 | R40: 0 | S40: 0
A41: Gas | B41: =E169 -> 0.0017836723 | C41: 0.0016828037 | D41: 0.0013242333 | E41: =G169 -> 0.0012263426 | F41: 0.0055474856 | G41: 0.0013242333 | H41: =I169 -> 0.001527635 | I41: 0.00084305984 | J41: 0.0013242333 | L41: 0 | M41: 0.0011247591 | O41: 0 | P41: 0 | R41: 0 | S41: 0
A42: R&M Supplies and Service | B42: =$H$177 -> 0.0034682081 | C42: 0.019710326 | D42: 0.006 | E42: =$H$177 -> 0.0034682081 | F42: 0.012018642 | G42: 0.006 | H42: =$H$177 -> 0.0034682081 | I42: 0.0073389729 | J42: 0.006 | L42: 0 | M42: 0.0086705202 | O42: 0 | P42: 0 | R42: 0 | S42: 0
A43: Manufacturing Supplies | B43: =$H$180 -> 0.00028901734 | C43: 0.0024000594 | D43: 0.002 | E43: =$H$180 -> 0.00028901734 | F43: 0.0007808962 | G43: 0.002 | H43: =$H$180 -> 0.00028901734 | I43: 0.00063205421 | J43: 0.002 | L43: 0 | M43: 0.00043352601 | O43: 0 | P43: 0 | R43: 0 | S43: 0
A44: Other variable | B44: =$H$183 -> 0.0043352601 | C44: 0.026652312 | D44: 0.006 | E44: =$H$183 -> 0.0043352601 | F44: 0.026473851 | G44: 0.006 | H44: =$H$183 -> 0.0043352601 | I44: 0.0094086246 | J44: 0.006 | L44: 0 | M44: 0.0057803468 | O44: 0 | P44: 0 | R44: 0 | S44: 0
A45: Total Variable Costs | B45: =SUM(B37:B44) -> 0.30070923 | C45: =SUM(C37:C44) -> 0.51076626 | D45: =SUM(D37:D44) -> 0.2880717 | E45: =SUM(E37:E44) -> 0.57159833 | F45: =SUM(F37:F44) -> 0.51386114 | G45: =SUM(G37:G44) -> 0.52230252 | H45: =SUM(H37:H44) -> 0.4344495 | I45: =SUM(I37:I44) -> 0.34253751 | J45: =SUM(J37:J44) -> 0.41132937 | L45: =SUM(L37:L44) -> 0 | M45: 2.1134123 | O45: =SUM(O37:O44) -> 0 | P45: =SUM(P37:P44) -> 0 | R45: =SUM(R37:R44) -> 0 | S45: =SUM(S37:S44) -> 0
A47: Production Labor | B47: =$D$214/$B$64/1000 -> 0.018490042 | C47: 0.02099802 | D47: 0.035940795 | E47: =$D$214/$B$64/1000 -> 0.018490042 | F47: 0.020095412 | G47: 0.035940795 | H47: =$D$214/$B$64/1000 -> 0.018490042 | I47: 0.017675634 | J47: 0.035940795 | L47: 0 | M47: 0.011741675 | O47: 0 | P47: 0 | R47: 0 | S47: 0
A48: Repairs & Maintenance Labor | B48: =$G$214/$B$64/1000 -> 0.0044936416 | C48: 0.010055044 | D48: 0.0113712 | E48: =$G$214/$B$64/1000 -> 0.0044936416 | F48: 0.0031155542 | G48: 0.0113712 | H48: =$G$214/$B$64/1000 -> 0.0044936416 | I48: 0.0047406695 | J48: 0.0113712 | L48: 0 | M48: 0.0041080925 | O48: 0 | P48: 0 | R48: 0 | S48: 0
A49: Indirect Payroll Costs (Benefits) | B49: =$J$214/$B$64/1000 -> 0.0081804217 | C49: 0.020373428 | D49: 0.014188877 | E49: =$J$214/$B$64/1000 -> 0.0081804217 | F49: 0.01913635 | G49: 0.014188877 | H49: =$J$214/$B$64/1000 -> 0.0081804217 | I49: 0.0076540782 | J49: 0.014188877 | L49: 0 | M49: 0.0072598437 | O49: 0 | P49: 0 | R49: 0 | S49: 0
A50: Supervision | B50: =$E$240 -> 0.0044774566 | C50: 0.0068127908 | D50: 0 | E50: =$E$240 -> 0.0044774566 | F50: 0.0082982662 | G50: 0 | H50: =$E$240 -> 0.0044774566 | I50: 0.0028565151 | J50: 0 | L50: 0 | M50: 0.002449852 | O50: 0 | P50: 0 | R50: 0 | S50: 0
A51: Depreciation | B51: =$E$241 -> 0.0032393064 | C51: 0.18195763 | D51: 0.01039048 | E51: =$E$241 -> 0.0032393064 | F51: 0.22264847 | G51: 0.01039048 | H51: =$E$241 -> 0.0032393064 | I51: 0.07640353 | J51: 0.01039048 | L51: 0 | M51: 0.06367052 | O51: 0 | P51: 0 | R51: 0 | S51: 0
A52: Insurance & Taxes | B52: =$E$242 -> 0.016269364 | C52: 0.045121869 | D52: 0.03763008 | E52: =$E$242 -> 0.016269364 | F52: 0.064601784 | G52: 0.03763008 | H52: =$E$242 -> 0.016269364 | I52: 0.019244874 | J52: 0.03763008 | L52: 0 | M52: 0.014046243 | O52: 0 | P52: 0 | R52: 0 | S52: 0
A53: Total Fixed Costs | B53: =SUM(B47:B52) -> 0.055150233 | C53: =SUM(C47:C52) -> 0.28531878 | D53: =SUM(D47:D52) -> 0.10952143 | E53: =SUM(E47:E52) -> 0.055150233 | F53: =SUM(F47:F52) -> 0.33789584 | G53: =SUM(G47:G52) -> 0.10952143 | H53: =SUM(H47:H52) -> 0.055150233 | I53: =SUM(I47:I52) -> 0.1285753 | J53: =SUM(J47:J52) -> 0.10952143 | L53: =SUM(L47:L52) -> 0 | M53: 0.10327623 | O53: =SUM(O47:O52) -> 0 | P53: =SUM(P47:P52) -> 0 | R53: =SUM(R47:R52) -> 0 | S53: =SUM(S47:S52) -> 0
A55: Total Cost per Pound at Gross | B55: =B45+B53 -> 0.35585946 | C55: =C45+C53 -> 0.79608504 | D55: =D45+D53 -> 0.39759313 | E55: =E45+E53 -> 0.62674857 | F55: =F45+F53 -> 0.85175698 | G55: =G45+G53 -> 0.63182396 | H55: =H45+H53 -> 0.48959973 | I55: =I45+I53 -> 0.47111281 | ... S55: =S45+S53 -> 0
A56: Less: Substrate Plant Under-absorption | B56: =-B38 -> 0 | C56: =-C38 -> 0 | D56: 0 | E56: =-E38 -> 0 | G56: -0.046 | H56: =-H38 -> 0 | J56: -0.09332723 | K56: =-K38 -> 0 | M56: -0.0074705959 | N56: =-N38 -> 0 | P56: 0 | Q56: =-Q38 -> 0
A57: Less: RC Under-absorption | B57: 0 | C57: -0.31205821 | D57: =IF(D40+D41+D42+D43+D44+D53>0.0498,0.0498-D40-D41-D42-D43-D44-D53,0) -> -0.080955215 | E57: 0 | F57: =IF(F40+F41+F42+F43+F44+F53>0.0498,0.0498-F40-F41-F42-F43-F44-F53,0) -> -0.34756261 | G57: =IF(G40+G41+G42+G43+G44+G53>0.0498,0.0498-G40-G41-G42-G43-G44-G53,0) -> -0.080955215 | H57: 0 | I57: =IF(I40+I41+I42+I43+I44+I53>0.0498,0.0498-I40-I41-I42-I43-I44-I53,0) -> -0.10746047 | J57: -0.080955215 | K57: =IF(K40+K41+K42+K43+K44+K53>0.0498,0.0498-K40-K41-K42-K43-K44-K53,0) -> 0 | L57: =IF(L40+L41+L42+L43+L44+L53>0.0498,0.0498-L40-L41-L42-L43-L44-L53,0) -> 0 | M57: =IF(M40+M41+M42+M43+M44+M53>0.0498,0.0498-M40-M41-M42-M43-M44-M53,0) -> -0.079620814 | N57: =IF(N40+N41+N42+N43+N44+N53>0.0498,0.0498-N40-N41-N42-N43-N44-N53,0) -> 0 | O57: 0 | P57: =IF(P40+P41+P42+P43+P44+P53>0.0498,0.0498-P40-P41-P42-P43-P44-P53,0) -> 0 | Q57: =IF(Q40+Q41+Q42+Q43+Q44+Q53>0.0498,0.0498-Q40-Q41-Q42-Q43-Q44-Q53,0) -> 0 | R57: 0 | S57: =IF(S40+S41+S42+S43+S44+S53>0.0498,0.0498-S40-S41-S42-S43-S44-S53,0) -> 0
A58: Net Cost per Pound Absorbed | B58: =SUM(B55:B57) -> 0.35585946 | C58: =SUM(C55:C57) -> 0.48402683 | D58: =SUM(D55:D57) -> 0.31663792 | E58: =SUM(E55:E57) -> 0.62674857 | F58: =SUM(F55:F57) -> 0.50419437 | G58: =SUM(G55:G57) -> 0.50486874 | H58: =SUM(H55:H57) -> 0.48959973 | I58: =SUM(I55:I57) -> 0.36365234 | ... S58: =SUM(S55:S57) -> 0
A60: Total Production (000 lbs) | B60: =+B85 -> 1500 | C60: 101 | D60: 1100 | E60: =+B86 -> 1300 | F60: 979 | G60: 1700 | H60: 0 | I60: 2743 | J60: 5500 | K60: =+B88 -> 0 | L60: 0 | M60: 100 | N60: 0 | O60: 0 | P60: 0 | Q60: 0 | R60: 0 | S60: 0
A64: Total Plant Production (000 lbs) | B64: =B29+E29+H29+K29+N29+Q29+B60+E60+H60+K60+N60+Q60 -> 34600 | C64: =C29+F29+I29+L29+O29+R29+C60+F60+I60+L60+O60+R60 -> 32641.15 | D64: =D29+G29+J29+M29+P29+S29+D60+G60+J60+M60+P60+S60 -> 23700
B66: Total | C66: Variable | D66: Fixed | V66: 2078820 | W66: 2289955 | AC66: 1.102 | AD66: 0.099 | AE66: =+AC66-AD66 -> 1.003
A67: Cost Summary: | B67: ($ in 000s) | V67: 22566 | W67: 22313 | AC67: 0.989 | AD67: 0 | AE67: =+AC67-AD67 -> 0.989
A68: Absorbed by Production | B68: =SUM(C68:D68) -> 13936.501 | C68: =W14*$V$29 -> 12860.665 | D68: =W22*$V$29 -> 1075.8358 | V68: 469400 | W68: 521591 | AC68: 1.111 | AD68: 0.07 | AE68: =+AC68-AD68 -> 1.041
A69: Underabsorption Expensed | B69: =SUM(C69:D69) -> 832.36228 | C69: =X14*$V$29 -> 0 | D69: =X22*$V$29 -> 832.36228 | V69: 514675 | W69: 642354 | AC69: 1.248 | AD69: 0.015 | AE69: =+AC69-AD69 -> 1.233
A70: Loss on Excess Gas Net Settled | B70: =SUM(C70:D70) -> 0 | C70: 0 | D70: 0 | V70: 62400 | W70: 68640 | AC70: 1.1 | AD70: 0.158 | AE70: =+AC70-AD70 -> 0.942
A71: Total Cost | B71: =SUM(B68:B70) -> 14768.863 | C71: =SUM(C68:C70) -> 12860.665 | D71: =SUM(D68:D70) -> 1908.198 | V71: 22275 | W71: 27844 | AC71: 1.25 | AD71: 0 | AE71: =+AC71-AD71 -> 1.25
A72: Less: Non-Cash | B72: =SUM(C72:D72) -> -112.08 | C72: 0 | D72: =-V20*V29 -> -112.08 | V72: 10980 | W72: 13725 | AC72: 1.25 | AD72: 0 | AE72: =+AC72-AD72 -> 1.25
A73: Cash Cost | B73: =SUM(B71:B72) -> 14656.783 | C73: =SUM(C71:C72) -> 12860.665 | D73: =SUM(D71:D72) -> 1796.118 | AE73: =AVERAGE(AE66:AE72) -> 1.1011429
V74: =SUM(V66:V73) -> 3181116 | W74: =SUM(W66:W73) -> 3586422
V75: 3233726 | W75: 1569174 | X75: =+W75/V75 -> 0.48525262
V76: =+V74-V75 -> -52610 | W76: =+W74-W75 -> 2017248
B77: Quantity | C77: Rate
A78: Production Plan | B78: (000 lbs) | C78: (000 lbs/day) | D78: Prodn Days | E78: % Split
A79: CB Lite | B79: 25500 | C79: 350 | D79: =IF(C79<>0,B79/C79,0) -> 72.857143 | E79: =IF($D$91<>0,D79/$D$91,0) -> 0.66753927
A80: CB KSHD | B80: 5000 | C80: =350 -> 350 | D80: =IF(C80<>0,B80/C80,0) -> 14.285714 | E80: =IF($D$91<>0,D80/$D$91,0) -> 0.13089005
A81: CB KSLD | B81: 300 | C81: =350 -> 350 | D81: =IF(C81<>0,B81/C81,0) -> 0.85714286 | E81: =IF($D$91<>0,D81/$D$91,0) -> 0.0078534031
A82: RPM Lite / NP LWC | B82: 0 | C82: =350 -> 350 | D82: =IF(C82<>0,B82/C82,0) -> 0 | E82: =IF($D$91<>0,D82/$D$91,0) -> 0
A83: RPM CP / NP ISP | B83: 0 | C83: =350 -> 350 | D83: =IF(C83<>0,B83/C83,0) -> 0 | E83: =IF($D$91<>0,D83/$D$91,0) -> 0
A84: Air | B84: 1000 | C84: =350 -> 350 | D84: =IF(C84<>0,B84/C84,0) -> 2.8571429 | E84: =IF($D$91<>0,D84/$D$91,0) -> 0.02617801
A85: Fusion (#998, 999, 1025) | B85: 1500 | C85: =350 -> 350 | D85: =IF(C85<>0,B85/C85,0) -> 4.2857143 | E85: =IF($D$91<>0,D85/$D$91,0) -> 0.039267016
A86: SG II CL | B86: 1300 | C86: =350 -> 350 | D86: =IF(C86<>0,B86/C86,0) -> 3.7142857 | E86: =IF($D$91<>0,D86/$D$91,0) -> 0.034031414
A87: SG II Ultra CL | B87: 0 | C87: =350 -> 350 | D87: =IF(C87<>0,B87/C87,0) -> 0 | E87: =IF($D$91<>0,D87/$D$91,0) -> 0
A88: SG II KSHD (H) | B88: 0 | C88: =350 -> 350 | D88: =IF(C88<>0,B88/C88,0) -> 0 | E88: =IF($D$91<>0,D88/$D$91,0) -> 0
A89: SaltGuard (FDP-806) | B89: 0 | C89: =350 -> 350 | D89: =IF(C89<>0,B89/C89,0) -> 0 | E89: =IF($D$91<>0,D89/$D$91,0) -> 0
A90: KSXT | B90: 3600 | C90: =350 -> 350 | D90: =IF(C90<>0,B90/C90,0) -> 10.285714 | E90: =IF($D$91<>0,D90/$D$91,0) -> 0.094240838
A91: Total | B91: =SUM(B79:B90) -> 38200 | C91: =B91/D91 -> 350 | D91: =SUM(D79:D90) -> 109.14286 | E91: =IF($D$91<>0,D91/$D$91,0) -> 1
A94: Variable Costs - Material
D96: CB Lite | F96: CB Lite EU | H96: CB KSLD | J96: RPM Lite / NP LWC | L96: CB KSHD | N96: Air | AF96: CBL | AH96: CBL (EU) | AJ96: CBL KSLD | AL96: RPM | AN96: CBL KSHD | AP96: AIR
A97: Materials Cost: | B97: Price ($/lb) | C97: Source plant under-absorb | D97: BOM Use/lb | E97: Standard Cost | F97: BOM Use/lb | G97: Standard Cost | H97: BOM Use/lb | I97: Standard Cost | J97: BOM Use/lb | K97: Standard Cost | L97: BOM Use/lb | M97: Standard Cost | N97: BOM Use/lb | O97: Standard Cost | AB97: material | AE97: plan price 1 | AF97: cost BOM | AG97: plan price 1 | AH97: cost BOM | AI97: plan price 1 | AJ97: cost BOM | AK97: plan price 1 | AL97: cost BOM | AM97: plan price 1 | AN97: cost BOM | AO97: plan price 1 | AP97: cost BOM
A98: CARBO LITE (32, 36, 115) | B98: =0.1586+0.032-C98 -> 0.1906 | C98: 0 | D98: 0.96442882 | E98: =$B98*D98 -> 0.18382013 | F98: 0.99078514 | G98: =$B98*F98 -> 0.18884365 | H98: 0 | I98: =$B98*H98 -> 0 | J98: 1.0310579 | K98: =$B98*J98 -> 0.19651963 | L98: 0 | M98: =$B98*L98 -> 0 | N98: 0 | O98: =$B98*N98 -> 0 | AB98: CL | AE98: =B98*1000 -> 190.6 | AF98: =E98/$B$98*1000 -> 964.42882 | AG98: =+B98*1000 -> 190.6 | AH98: =G98/B98*1000 -> 990.78514 | AL98: =K98/B98*1000 -> 1031.0579
A99: CARBOAIR UL (861, 938) | B99: =0.1586+0.032-C99 -> 0.1906 | C99: 0 | D99: 0 | E99: =$B99*D99 -> 0 | F99: 0 | G99: =$B99*F99 -> 0 | H99: 0 | I99: =$B99*H99 -> 0 | J99: 0 | K99: =$B99*J99 -> 0 | L99: 0 | M99: =$B99*L99 -> 0 | N99: =262800/262440 -> 1.0013717 | O99: =$B99*N99 -> 0.19086145 | AO99: =+B99*1000 -> 190.6 | AP99: =O99/B99*1000 -> 1001.3717
A100: KRYPTOSPHERE LD (976) | B100: =0.378+0.032-C100 -> 0.41 | C100: 0 | D100: 0 | E100: =$B100*D100 -> 0 | F100: 0 | G100: =$B100*F100 -> 0 | H100: =880100/860400 -> 1.0228963 | I100: =$B100*H100 -> 0.41938749 | J100: 0 | K100: =$B100*J100 -> 0 | L100: 0 | M100: =$B100*L100 -> 0 | N100: 0 | O100: =$B100*N100 -> 0 | AI100: =+B100*1000 -> 410 | AJ100: =I100/B100*1000 -> 1022.8963
A101: KRYPTOSPHERE HD (873) | B101: =0.7539+0.032-C101 -> 0.7859 | C101: 0 | D101: 0 | E101: =$B101*D101 -> 0 | F101: 0 | G101: =$B101*F101 -> 0 | H101: 0 | I101: =$B101*H101 -> 0 | J101: 0 | K101: =$B101*J101 -> 0 | L101: =+H100 -> 1.0228963 | M101: =$B101*L101 -> 0.80389422 | N101: 0 | O101: =$B101*N101 -> 0 | AM101: =+B102*1000 -> 232 | AN101: =M101/B101*1000 -> 1022.8963
A102: CARBO HSP (19) | B102: =0.2+0.032-C102 -> 0.232 | C102: 0 | D102: 0 | E102: =$B102*D102 -> 0 | F102: 0 | G102: =$B102*F102 -> 0 | H102: 0 | I102: =$B102*H102 -> 0 | J102: 0 | K102: =$B102*J102 -> 0 | L102: 0 | M102: =$B102*L102 -> 0 | N102: 0 | O102: =$B102*N102 -> 0
A103: CARBOPROP (50) | B103: 0 | C103: 0 | D103: 0 | E103: =$B103*D103 -> 0 | F103: 0 | G103: =$B103*F103 -> 0 | H103: 0 | I103: =$B103*H103 -> 0 | J103: 0 | K103: =$B103*J103 -> 0 | L103: 0 | M103: =$B103*L103 -> 0 | N103: 0 | O103: =$B103*N103 -> 0
A104: SCALEGUARD I CL (812, 951) | B104: =0.5084-C104 -> 0.5084 | C104: 0 | D104: 0 | E104: =$B104*D104 -> 0 | F104: 0 | G104: =$B104*F104 -> 0 | H104: 0 | I104: =$B104*H104 -> 0 | J104: 0 | K104: =$B104*J104 -> 0 | L104: 0 | M104: =$B104*L104 -> 0 | N104: 0 | O104: =$B104*N104 -> 0
A105: SCALEGUARD I KSHD (H) | B105: =1.9036-C105 -> 1.9036 | C105: 0 | D105: 0 | E105: =$B105*D105 -> 0 | F105: 0 | G105: =$B105*F105 -> 0 | H105: 0 | I105: =$B105*H105 -> 0 | J105: 0 | K105: =$B105*J105 -> 0 | L105: 0 | M105: =$B105*L105 -> 0 | N105: 0 | O105: =$B105*N105 -> 0
A106: CL FUSION SUBSTRATE (994) | B106: =0.1586+0.032-C106+0.02 -> 0.2106 | C106: 0 | D106: 0 | E106: =$B106*D106 -> 0 | F106: 0 | G106: =$B106*F106 -> 0 | H106: 0 | I106: =$B106*H106 -> 0 | J106: 0 | K106: =$B106*J106 -> 0 | L106: 0 | M106: =$B106*L106 -> 0 | N106: 0 | O106: =$B106*N106 -> 0
A107: Plenco Resin (30090) | B107: =1506/1000 -> 1.506 | C107: 0 | D107: 0 | E107: =$B107*D107 -> 0 | F107: 0.030157074 | G107: =$B107*F107 -> 0.045416554 | H107: 0 | I107: =$B107*H107 -> 0 | J107: 0 | K107: =$B107*J107 -> 0 | L107: 0 | M107: =$B107*L107 -> 0 | N107: 0 | O107: =$B107*N107 -> 0 | AB107: 30090 | AE107: =B107*1000 -> 1506 | AF107: =E107/B107*1000 -> 0 | AG107: =+B107*1000 -> 1506 | AH107: =G107/B107*1000 -> 30.157074 | AI107: =+B107*1000 -> 1506 | AJ107: =I107/B107*1000 -> 0 | AN107: =M107/B107*1000 -> 0 | AP107: =O107/B107*1000 -> 0
A108: Bimex Resin-EU (30120) | B108: 1.262 | C108: 0 | D108: 0.0317 | E108: =$B108*D108 -> 0.0400054 | F108: 0.0052246952 | G108: =$B108*F108 -> 0.0065935654 | H108: =31125/860400 -> 0.036175035 | I108: =$B108*H108 -> 0.045652894 | J108: 0 | K108: =$B108*J108 -> 0 | L108: =+H108 -> 0.036175035 | M108: =$B108*L108 -> 0.045652894 | N108: =10645/262440 -> 0.040561652 | O108: =$B108*N108 -> 0.051188805 | AB108: 30120 | AE108: =B108*1000 -> 1262 | AF108: =E108/B108*1000 -> 31.7 | AG108: =+B108*1000 -> 1262 | AH108: =G108/B108*1000 -> 5.2246952 | AI108: =+B108*1000 -> 1262 | AJ108: =I108/B108*1000 -> 36.175035 | AM108: =+B109*1000 -> 788.33 | AN108: =M108/B108*1000 -> 36.175035 | AO108: =+B108*1000 -> 1262 | AP108: =O108/B108*1000 -> 40.561652
A109: HEXA-EU (30362) | B109: 0.78833 | C109: 0 | D109: 0.0044 | E109: =$B109*D109 -> 0.003468652 | F109: 0.0061505935 | G109: =$B109*F109 -> 0.0048486974 | H109: =4307/860400 -> 0.0050058113 | I109: =$B109*H109 -> 0.0039462312 | J109: 0 | K109: =$B109*J109 -> 0 | L109: =+H109 -> 0.0050058113 | M109: =$B109*L109 -> 0.0039462312 | N109: =1190/262440 -> 0.0045343698 | O109: =$B109*N109 -> 0.0035745797 | AB109: 30362 | AE109: =B109*1000 -> 788.33 | AF109: =E109/B109*1000 -> 4.4 | AG109: =+B109*1000 -> 788.33 | AH109: =G109/B109*1000 -> 6.1505935 | AI109: =+B109*1000 -> 788.33 | AJ109: =I109/B109*1000 -> 5.0058113 | AM109: =+B110*1000 -> 4460 | AN109: =M109/B109*1000 -> 5.0058113 | AO109: =+B109*1000 -> 788.33 | AP109: =O109/B109*1000 -> 4.5343698
A110: Silane-EU (30360) | B110: 4.46 | C110: 0 | D110: 0 | E110: =$B110*D110 -> 0 | F110: 0.00052718059 | G110: =$B110*F110 -> 0.0023512255 | H110: =1031/860400 -> 0.0011982799 | I110: =$B110*H110 -> 0.0053443282 | J110: 0 | K110: =$B110*J110 -> 0 | L110: =+H110 -> 0.0011982799 | M110: =$B110*L110 -> 0.0053443282 | N110: =320/262440 -> 0.0012193263 | O110: =$B110*N110 -> 0.0054381954 | AB110: 30360 | AG110: =+B110*1000 -> 4460 | AH110: =G110/B110*1000 -> 0.52718059 | AI110: =+B110*1000 -> 4460 | AJ110: =I110/B110*1000 -> 1.1982799 | AM110: =+B111*1000 -> 1449.8 | AN110: =M110/B110*1000 -> 1.1982799 | AO110: =+B110*1000 -> 4460 | AP110: =O110/B110*1000 -> 1.2193263
A111: Surfactant-EU (30361) | B111: =1449.8/1000 -> 1.4498 | C111: 0 | D111: 0 | E111: =$B111*D111 -> 0 | F111: 0.00055567684 | G111: =$B111*F111 -> 0.00080562029 | H111: =855/860400 -> 0.00099372385 | I111: =$B111*H111 -> 0.0014407008 | J111: 0 | K111: =$B111*J111 -> 0 | L111: =+H111 -> 0.00099372385 | M111: =$B111*L111 -> 0.0014407008 | N111: =542/262440 -> 0.002065234 | O111: =$B111*N111 -> 0.0029941762 | AB111: 30361 | AG111: =+B111*1000 -> 1449.8 | AH111: =G111/B111*1000 -> 0.55567684 | AI111: =+B111*1000 -> 1449.8 | AJ111: =I111/B111*1000 -> 0.99372385 | AM111: =+B112*1000 -> 1164.82 | AN111: =M111/B111*1000 -> 0.99372385 | AO111: =+B111*1000 -> 1449.8 | AP111: =O111/B111*1000 -> 2.065234
A112: Surfactant (30054) | B112: =1164.82/1000 -> 1.16482 | C112: 0 | D112: 0.0004 | E112: =$B112*D112 -> 0.000465928 | F112: 0 | G112: =$B112*F112 -> 0 | H112: 0 | I112: =$B112*H112 -> 0 | J112: 0 | K112: =$B112*J112 -> 0 | L112: 0 | M112: =$B112*L112 -> 0 | N112: 0 | O112: =$B112*N112 -> 0 | AB112: 30054 | AE112: =B112*1000 -> 1164.82 | AF112: =E112/B112*1000 -> 0.4 | AH112: =G112/B112*1000 -> 0 | AJ112: =I112/B112*1000 -> 0 | AN112: =M112/B112*1000 -> 0 | AP112: =O112/B112*1000 -> 0
A113: Hexamine (30055) | B113: =1096.46/1000 -> 1.09646 | C113: 0 | D113: 0 | E113: =$B113*D113 -> 0 | F113: 0 | G113: =$B113*F113 -> 0 | H113: 0 | I113: =$B113*H113 -> 0 | J113: 0 | K113: =$B113*J113 -> 0 | L113: 0 | M113: =$B113*L113 -> 0 | N113: 0 | O113: =$B113*N113 -> 0 | AB113: 30055 | AE113: =B113*1000 -> 1096.46 | AF113: =E113/B113*1000 -> 0 | AH113: =G113/B113*1000 -> 0 | AJ113: =I113/B113*1000 -> 0 | AN113: =M113/B113*1000 -> 0 | AP113: =O113/B113*1000 -> 0
A114: Silane (30058) | B114: =4019.96/1000 -> 4.01996 | C114: 0 | D114: 0 | E114: =$B114*D114 -> 0 | F114: 0 | G114: =$B114*F114 -> 0 | H114: 0 | I114: =$B114*H114 -> 0 | J114: 0 | K114: =$B114*J114 -> 0 | L114: 0 | M114: =$B114*L114 -> 0 | N114: 0 | O114: =$B114*N114 -> 0 | AB114: 30058 | AE114: =B114*1000 -> 4019.96 | AF114: =E114/B114*1000 -> 0 | AH114: =G114/B114*1000 -> 0 | AJ114: =I114/B114*1000 -> 0 | AN114: =M114/B114*1000 -> 0 | AP114: =O114/B114*1000 -> 0
A115: WB Concentrate (30454) | B115: 16.504 | C115: 0 | D115: 0 | E115: =$B115*D115 -> 0 | F115: 0 | G115: =$B115*F115 -> 0 | H115: 0 | I115: =$B115*H115 -> 0 | J115: 0 | K115: =$B115*J115 -> 0 | L115: 0 | M115: =$B115*L115 -> 0 | N115: 0 | O115: =$B115*N115 -> 0 | AB115: 30454 | AL115: =K115/B115*1000 -> 0 | AN115: =M115/B115*1000 -> 0 | AP115: =O115/B115*1000 -> 0
...

Sheet NI RC 2022 Std 
A1: New Iberia Resin Coating | AB1: Activity | AC1: 10001005 | AD1: 10001005 | AE1: Gross | AF1: Qty/1000 | AG1: 10001005 | AH1: Absorbed | AI1: 10001005 | AJ1: Abs Cost
A2: 2022 STANDARDS | AA2: Unit | AB2: Type | AC2: Total Cost | AD2: Total Qty | AE2: Unit Cost | AF2: Prod lbs | AG2: Absorption | AH2: Unit Cost | AI2: Underabs | AJ2: per 10000
B3: CARBOBond Lite | E3: CARBOBond Lite EU | H3: CARBOBond KSLD | K3: RPM LITE / NEUTRAPROP LWC | N3: XX | Q3: CARBO AIR
B4: 21 Standard | C4: 19 Actual | D4: 21 Standard | E4: 22 Standard | F4: 19 Actual | G4: =+D4 -> 21 Standard | H4: 21 Standard | I4: =+C4 -> 19 Actual | J4: =+D4 -> 21 Standard | K4: 21 Standard | L4: 18 Actual | M4: =+D4 -> 21 Standard | N4: 21 Standard | O4: 19 Actual | P4: =+D4 -> 21 Standard | Q4: 21 Standard | R4: 18 Actual | S4: =+D4 -> 21 Standard | V4: Composite | W4: Absorb | X4: Underabsorb
C5: (Jan-Sept) | F5: (Jan-Sept) | I5: =+C5 -> (Jan-Sept) | L5: (Jan-Nov) | R5: (Jan-Oct)
A6: Materials - Substrate | B6: =E121 -> 0.18382013 | C6: 0.16092998 | D6: 0.1639529 | E6: =G121 -> 0.18884365 | F6: 0.15896741 | G6: 0.13998074 | I6: 0.30191317 | J6: 0.28067655 | K6: =K121 -> 0.19651963 | L6: 0.18307969 | M6: 0.15362762 | O6: 0 | P6: 0 | R6: 0.15968841 | S6: 0.14400712 | V6: =($B6*$B$29+$E6*$E$29+$H6*$H$29+$K6*$K$29+$N6*$N$29+$Q6*$Q$29+$B37*$B$60+$E37*$E$60+$H37*$H$60+$K37*$K$60+$N37*$N$60+$Q37*$Q$60)/$B$64 -> 0.22071572 | W6: =V6 -> 0.22071572
A7: Materials - Substrate Under-Absorption | B7: =$C100*D100 -> 0 | D7: 0 | E7: =$C100*F100 -> 0 | G7: 0.08643106 | J7: 0.22562455 | K7: =$C100*J100 -> 0 | M7: 0.094857323 | P7: 0 | S7: 0.08891715 | V7: 0 | W7: 0
A8: Materials - Resin & Chemicals | B8: =E122+E123 -> 0.04393998 | C8: 0.051903794 | D8: 0.038078 | E8: =G122+G123 -> 0.060015662 | F8: 0.053990671 | G8: 0.053042779 | I8: 0.05384576 | J8: 0.0471079 | K8: =K122+K123 -> 0.070148364 | L8: 0.071924563 | M8: 0.15903358 | O8: 0 | P8: 0 | R8: 0.072759577 | S8: 0.074666525 | V8: =($B8*$B$29+$E8*$E$29+$H8*$H$29+$K8*$K$29+$N8*$N$29+$Q8*$Q$29+$B39*$B$60+$E39*$E$60+$H39*$H$60+$K39*$K$60+$N39*$N$60+$Q39*$Q$60)/$B$64 -> 0.059302804 | W8: =V8 -> 0.059302804 | X8: =V8-W8 -> 0
A9: Electricity | B9: =E163 -> 0.010280976 | C9: 0.0077075348 | D9: 0.0059095494 | E9: =G163 -> 0.008774935 | F9: 0.0064153677 | G9: 0.010135435 | I9: 0.023850562 | J9: 0.010726 | K9: =K163 -> 0.010280976 | L9: 0.019218863 | M9: 0.010135435 | O9: 0 | P9: 0 | R9: 0.006525594 | S9: 0.010135435 | V9: =($B9*$B$29+$E9*$E$29+$H9*$H$29+$K9*$K$29+$N9*$N$29+$Q9*$Q$29+$B40*$B$60+$E40*$E$60+$H40*$H$60+$K40*$K$60+$N40*$N$60+$Q40*$Q$60)/$B$64 -> 0.0086692394 | W9: =V9 -> 0.0086692394 | X9: =V9-W9 -> 0 | AA9: kwh | AB9: ELE01 | AC9: =ROUND(((D163*B$29*1000)+(F163*E$29*1000)+(H163*H$29*1000)+(J163*K$29*1000)+(L163*N$29*1000)+(N163*Q$29*1000)+(D170*B$60*1000)+(F170*E$60*1000)+(H170*H$60*1000)+(J170*K$60*1000)+(L170*N$60*1000)+(N170*Q$60*1000))*$B163,0) -> 241872 | AD9: =ROUND((D163*B$29*1000)+(F163*E$29*1000)+(H163*H$29*1000)+(J163*K$29*1000)+(L163*N$29*1000)+(N163*Q$29*1000)+(D170*B$60*1000)+(F170*E$60*1000)+(H170*H$60*1000)+(J170*K$60*1000)+(L170*N$60*1000)+(N170*Q$60*1000),0) -> 1016844 | AE9: =AC9/AD9 -> 0.2378654 | AF9: =ROUND(AD9/$B$64,3) -> 36.446 | AG9: =ROUND(W9*$AC$29,0) -> 241872 | AH9: =AG9/AD9 -> 0.2378654 | AI9: =AC9-AG9 -> 0 | AJ9: =AH9*10000 -> 2378.654
A10: Gas | B10: =E164 -> 1.6495208e-06 | C10: 0.00096524487 | D10: 0.0013242333 | E10: =G164 -> 0.0013349276 | F10: 0.00088623983 | G10: 0.0011247591 | I10: 0.0011573683 | J10: 0.00126 | K10: =K164 -> 1.6495208e-06 | L10: 0.0011031846 | M10: 0.0011247591 | O10: 0 | P10: 0 | R10: 0.0011625955 | S10: 0.0011247591 | V10: =($B10*$B$29+$E10*$E$29+$H10*$H$29+$K10*$K$29+$N10*$N$29+$Q10*$Q$29+$B41*$B$60+$E41*$E$60+$H41*$H$60+$K41*$K$60+$N41*$N$60+$Q41*$Q$60)/$B$64 -> 0.0013734225 | W10: =V10 -> 0.0013734225 | X10: =V10-W10 -> 0 | AA10: mbtu | AB10: GAS01 | AC10: =ROUND(((D164*B$29*1000)+(F164*E$29*1000)+(H164*H$29*1000)+(J164*K$29*1000)+(L164*N$29*1000)+(N164*Q$29*1000)+(D171*B$60*1000)+(F171*E$60*1000)+(H171*H$60*1000)+(J171*K$60*1000)+(L171*N$60*1000)+(N171*Q$60*1000))*$B164,0) -> 38318 | AD10: =ROUND(((D164*B$29*1000)+(F164*E$29*1000)+(H164*H$29*1000)+(J164*K$29*1000)+(L164*N$29*1000)+(N164*Q$29*1000)+(D171*B$60*1000)+(F171*E$60*1000)+(H171*H$60*1000)+(J171*K$60*1000)+(L171*N$60*1000)+(N171*Q$60*1000))*1000,0) -> 6836008027 | AE10: =AC10/AD10 -> 5.6053182e-06 | AF10: =ROUND(AD10/$B$64,3) -> 245018.21 | AG10: =ROUND(W10*$AC$29,0) -> 38318 | AH10: =AG10/AD10 -> 5.6053182e-06 | AI10: =AC10-AG10 -> 0 | AJ10: =AH10*10000 -> 0.056053182
A11: R&M Supplies and Service | B11: =$H$179 -> 0.0043010753 | C11: 0.0052601959 | D11: 0.006 | E11: =$H$179 -> 0.0043010753 | F11: 0.0051242876 | G11: 0.0086705202 | I11: 0.023215913 | J11: 0.0099121126 | K11: =$H$179 -> 0.0043010753 | L11: 0.026688594 | M11: 0.0086705202 | O11: 0 | P11: 0 | R11: 0.016241103 | S11: 0.0086705202 | V11: =($B11*$B$29+$E11*$E$29+$H11*$H$29+$K11*$K$29+$N11*$N$29+$Q11*$Q$29+$B42*$B$60+$E42*$E$60+$H42*$H$60+$K42*$K$60+$N42*$N$60+$Q42*$Q$60)/$B$64 -> 0.0043010753 | W11: =V11 -> 0.0043010753 | X11: =V11-W11 -> 0 | AA11: lb | AB11: RMS01 | AC11: =ROUND(G179,0) -> 120000 | AD11: =$B$64*1000 -> 27900000 | AE11: =AC11/AD11 -> 0.0043010753 | AF11: =ROUND(AD11/$B$64,3) -> 1000 | AG11: =ROUND(W11*$AC$29,0) -> 120000 | AH11: =AG11/AD11 -> 0.0043010753 | AI11: =AC11-AG11 -> 0 | AJ11: =AH11*10000 -> 43.010753
A12: Manufacturing Supplies | B12: =$H$182 -> 0.00035842294 | C12: 0.00028145605 | D12: 0.002 | E12: =$H$182 -> 0.00035842294 | F12: 0.0001613237 | G12: 0.00043352601 | I12: 0.00076914757 | J12: 0.00049560563 | K12: =$H$182 -> 0.00035842294 | L12: 0.0013365915 | M12: 0.00043352601 | O12: 0 | P12: 0 | R12: 0.00053366327 | S12: 0.00043352601 | V12: =($B12*$B$29+$E12*$E$29+$H12*$H$29+$K12*$K$29+$N12*$N$29+$Q12*$Q$29+$B43*$B$60+$E43*$E$60+$H43*$H$60+$K43*$K$60+$N43*$N$60+$Q43*$Q$60)/$B$64 -> 0.00035842294 | W12: =V12 -> 0.00035842294 | X12: =V12-W12 -> 0 | AA12: lb | AB12: MFG01 | AC12: =ROUND(G182,0) -> 10000 | AD12: =$B$64*1000 -> 27900000 | AE12: =AC12/AD12 -> 0.00035842294 | AF12: =ROUND(AD12/$B$64,3) -> 1000 | AG12: =ROUND(W12*$AC$29,0) -> 10000 | AH12: =AG12/AD12 -> 0.00035842294 | AI12: =AC12-AG12 -> 0 | AJ12: =AH12*10000 -> 3.5842294
A13: Other variable | B13: =$H$185 -> 0.0053763441 | C13: 0.005539271 | D13: 0.006 | E13: =$H$185 -> 0.0053763441 | F13: 0.0047523717 | G13: 0.0057803468 | I13: 0.017048253 | J13: 0.0066080751 | K13: =$H$185 -> 0.0053763441 | L13: 0.026821614 | M13: 0.0057803468 | O13: 0 | P13: 0 | R13: 0.0059964109 | S13: 0.0057803468 | V13: =($B13*$B$29+$E13*$E$29+$H13*$H$29+$K13*$K$29+$N13*$N$29+$Q13*$Q$29+$B44*$B$60+$E44*$E$60+$H44*$H$60+$K44*$K$60+$N44*$N$60+$Q44*$Q$60)/$B$64 -> 0.0053763441 | W13: =V13 -> 0.0053763441 | X13: =V13-W13 -> 0 | AA13: lb | AB13: VAR01 | AC13: =ROUND(G185,0) -> 150000 | AD13: =$B$64*1000 -> 27900000 | AE13: =AC13/AD13 -> 0.0053763441 | AF13: =ROUND(AD13/$B$64,3) -> 1000 | AG13: =ROUND(W13*$AC$29,0) -> 150000 | AH13: =AG13/AD13 -> 0.0053763441 | AI13: =AC13-AG13 -> 0 | AJ13: =AH13*10000 -> 53.763441
A14: Total Variable Costs | B14: =SUM(B6:B13) -> 0.24807858 | C14: =SUM(C6:C13) -> 0.23258747 | D14: =SUM(D6:D13) -> 0.22326468 | E14: =SUM(E6:E13) -> 0.26900501 | F14: =SUM(F6:F13) -> 0.23029767 | G14: 0.30559917 | I14: =SUM(I6:I13) -> 0.42180018 | J14: =SUM(J6:J13) -> 0.5824108 | K14: =SUM(K6:K13) -> 0.28698646 | L14: =SUM(L6:L13) -> 0.3301731 | M14: 0.43366311 | O14: =SUM(O6:O13) -> 0 | P14: =SUM(P6:P13) -> 0 | R14: =SUM(R6:R13) -> 0.26290735 | S14: 0.33373539 | V14: =SUM(V6:V13) -> 0.30009703 | W14: =SUM(W6:W13) -> 0.30009703 | X14: =SUM(X6:X13) -> 0 | AC14: =SUM(AC9:AC13) -> 560190 | AG14: =SUM(AG9:AG13) -> 560190 | AI14: =SUM(AI9:AI13) -> 0
A16: Production Labor | B16: =$D$216/$B$64/1000 -> 0.023140287 | C16: 0.018200142 | D16: 0.035940795 | E16: =$D$216/$B$64/1000 -> 0.023140287 | F16: 0.020063713 | G16: 0.011741675 | I16: 0.012521635 | J16: 0.014552451 | K16: =$D$216/$B$64/1000 -> 0.023140287 | L16: 0.032785827 | M16: 0.011741675 | O16: 0 | P16: 0 | R16: 0.013727223 | S16: 0.011741675 | V16: =($B16*$B$29+$E16*$E$29+$H16*$H$29+$K16*$K$29+$N16*$N$29+$Q16*$Q$29+$B47*$B$60+$E47*$E$60+$H47*$H$60+$K47*$K$60+$N47*$N$60+$Q47*$Q$60)/$B$64 -> 0.023140287 | W16: =+W24-W14 -> 0.029721496 | X16: =V16-W16 -> -0.0065812083 | AA16: hr | AB16: DLAB01 | AC16: =ROUND(D214,0) -> 670220 | AD16: =ROUND(B214,0) -> 22000 | AE16: =AC16/AD16 -> 30.464545 | AF16: =ROUND(AD16/$B$64,3) -> 0.789 | AG16: =ROUND(W16*$AC$29,0) -> 829230 | AH16: =AG16/AD16 -> 37.692273 | AI16: =AC16-AG16 -> -159010 | AJ16: =AH16*10000 -> 376922.73
A17: Repairs & Maintenance Labor | B17: =$G$216/$B$64/1000 -> 0.0055727599 | C17: 0.0048304191 | D17: 0.0113712 | E17: =$G$216/$B$64/1000 -> 0.0055727599 | F17: 0.0044471791 | G17: 0.0041080925 | I17: 0.0044303098 | J17: 0.004696359 | K17: =$G$216/$B$64/1000 -> 0.0055727599 | L17: 0.0088578354 | M17: 0.0041080925 | O17: 0 | P17: 0 | R17: 0.0016693747 | S17: 0.0041080925 | V17: =($B17*$B$29+$E17*$E$29+$H17*$H$29+$K17*$K$29+$N17*$N$29+$Q17*$Q$29+$B48*$B$60+$E48*$E$60+$H48*$H$60+$K48*$K$60+$N48*$N$60+$Q48*$Q$60)/$B$64 -> 0.0055727599 | W17: 0 | X17: =V17-W17 -> 0.0055727599 | AA17: hr | AB17: MLAB01 | AC17: =ROUND(G214,0) -> 155480 | AD17: =ROUND(E214,0) -> 4400 | AE17: =AC17/AD17 -> 35.336364 | AF17: =ROUND(AD17/$B$64,3) -> 0.158 | AG17: =ROUND(W17*$AC$29,0) -> 0 | AH17: =AG17/AD17 -> 0 | AI17: =AC17-AG17 -> 155480 | AJ17: =AH17*10000 -> 0
A18: Indirect Payroll Costs (Benefits) | B18: =$J$216/$B$64/1000 -> 0.010221704 | C18: 0.0068508297 | D18: 0.014188877 | E18: =$J$216/$B$64/1000 -> 0.010221704 | F18: 0.0059757405 | G18: 0.0072598437 | I18: 0.014238166 | J18: 0.008765191 | K18: =$J$216/$B$64/1000 -> 0.010221704 | L18: 0.038686584 | M18: 0.0072598437 | O18: 0 | P18: 0 | R18: 0.0056633179 | S18: 0.0072598437 | V18: =($B18*$B$29+$E18*$E$29+$H18*$H$29+$K18*$K$29+$N18*$N$29+$Q18*$Q$29+$B49*$B$60+$E49*$E$60+$H49*$H$60+$K49*$K$60+$N49*$N$60+$Q49*$Q$60)/$B$64 -> 0.010221704 | W18: 0 | X18: =V18-W18 -> 0.010221704 | AA18: hr | AB18: IPC01 | AC18: =ROUND(J214,0) -> 294186 | AD18: =ROUND(H214,0) -> 26400 | AE18: =AC18/AD18 -> 11.143409 | AF18: =ROUND(AD18/$B$64,3) -> 0.946 | AG18: =ROUND(W18*$AC$29,0) -> 0 | AH18: =AG18/AD18 -> 0 | AI18: =AC18-AG18 -> 294186 | AJ18: =AH18*10000 -> 0
A19: Supervision | B19: =$E$243 -> 0.0055526882 | C19: 0.0022776301 | D19: 0 | E19: =$E$243 -> 0.0055526882 | F19: 0.0019225049 | G19: 0.002449852 | I19: 0.0092721693 | J19: 0.0028006635 | K19: =$E$243 -> 0.0055526882 | L19: 0.01254166 | M19: 0.002449852 | O19: 0 | P19: 0 | R19: 0.0023710733 | S19: 0.002449852 | V19: =($B19*$B$29+$E19*$E$29+$H19*$H$29+$K19*$K$29+$N19*$N$29+$Q19*$Q$29+$B50*$B$60+$E50*$E$60+$H50*$H$60+$K50*$K$60+$N50*$N$60+$Q50*$Q$60)/$B$64 -> 0.0055526882 | W19: 0 | X19: =V19-W19 -> 0.0055526882 | AA19: lb | AB19: SUP01 | AC19: =ROUND(C243,0) -> 154920 | AD19: =$B$64*1000 -> 27900000 | AE19: =AC19/AD19 -> 0.0055526882 | AF19: =ROUND(AD19/$B$64,3) -> 1000 | AG19: =ROUND(W19*$AC$29,0) -> 0 | AH19: =AG19/AD19 -> 0 | AI19: =AC19-AG19 -> 154920 | AJ19: =AH19*10000 -> 0
A20: Depreciation | B20: =$E$244 -> 0.0040172043 | C20: 0.061012872 | D20: 0.01039048 | E20: =$E$244 -> 0.0040172043 | F20: 0.051498884 | G20: 0.06367052 | I20: 0.24870656 | J20: 0.072787947 | K20: =$E$244 -> 0.0040172043 | L20: 0.34045176 | M20: 0.06367052 | O20: 0 | P20: 0 | R20: 0.064182394 | S20: 0.06367052 | V20: =($B20*$B$29+$E20*$E$29+$H20*$H$29+$K20*$K$29+$N20*$N$29+$Q20*$Q$29+$B51*$B$60+$E51*$E$60+$H51*$H$60+$K51*$K$60+$N51*$N$60+$Q51*$Q$60)/$B$64 -> 0.0040172043 | W20: =W24-W14-W16-W17-W18-W19-W21 -> 0 | X20: =V20-W20 -> 0.0040172043 | AA20: lb | AB20: DEP01 | AC20: =ROUND(C244,0) -> 112080 | AD20: =($B$29+$E$29+$H$29+$K$29+$N$29+B60+E60+H60+K60+N60)*1000 -> 27900000 | AE20: =AC20/AD20 -> 0.0040172043 | AF20: =ROUND(AD20/($B$29+$E$29+$H$29+$K$29+$N$29+B60+E60+H60+K60+N60),3) -> 1000 | AG20: =ROUND(W20*$AC$29,0) -> 0 | AH20: =AG20/AD20 -> 0 | AI20: =AC20-AG20 -> 112080 | AJ20: =AH20*10000 -> 0
A21: Insurance & Taxes | B21: =$E$245 -> 0.020176344 | C21: 0.01547789 | D21: 0.03763008 | E21: =$E$245 -> 0.020176344 | F21: 0.012959419 | G21: 0.014046243 | I21: 0.064467032 | J21: 0.018172206 | K21: =$E$245 -> 0.020176344 | L21: 0.083528141 | M21: 0.014046243 | O21: 0 | P21: 0 | R21: 0.015675972 | S21: 0.014046243 | V21: =($B21*$B$29+$E21*$E$29+$H21*$H$29+$K21*$K$29+$N21*$N$29+$Q21*$Q$29+$B52*$B$60+$E52*$E$60+$H52*$H$60+$K52*$K$60+$N52*$N$60+$Q52*$Q$60)/$B$64 -> 0.020176344 | W21: =W24-W14-W16-W17-W18-W19 -> 0 | X21: =V21-W21 -> 0.020176344 | AA21: lb | AB21: INS01 | AC21: =ROUND(C245,0) -> 562920 | AD21: =$B$64*1000 -> 27900000 | AE21: =AC21/AD21 -> 0.020176344 | AF21: =ROUND(AD21/$B$64,3) -> 1000 | AG21: =ROUND(W21*$AC$29,0) -> 0 | AH21: =AG21/AD21 -> 0 | AI21: =AC21-AG21 -> 562920 | AJ21: =AH21*10000 -> 0
A22: Total Fixed Costs | B22: =SUM(B16:B21) -> 0.068680988 | C22: =SUM(C16:C21) -> 0.10864978 | D22: =SUM(D16:D21) -> 0.10952143 | E22: =SUM(E16:E21) -> 0.068680988 | F22: =SUM(F16:F21) -> 0.09686744 | G22: 0.10327623 | I22: =SUM(I16:I21) -> 0.35363588 | J22: =SUM(J16:J21) -> 0.12177482 | K22: =SUM(K16:K21) -> 0.068680988 | L22: =SUM(L16:L21) -> 0.51685181 | M22: 0.10327623 | O22: =SUM(O16:O21) -> 0 | P22: =SUM(P16:P21) -> 0 | R22: =SUM(R16:R21) -> 0.10328935 | S22: 0.10327623 | V22: =SUM(V16:V21) -> 0.068680988 | W22: =SUM(W16:W21) -> 0.029721496 | X22: =SUM(X16:X21) -> 0.038959493 | AC22: =SUM(AC16:AC21) -> 1949806 | AG22: =SUM(AG16:AG21) -> 829230 | AI22: =SUM(AI16:AI21) -> 1120576
AA23: Activity Cost | AC23: =AC14+AC22 -> 2509996 | AG23: =AG14+AG22 -> 1389420 | AI23: =AI14+AI22 -> 1120576
A24: Total Cost per Pound at Gross | B24: =B14+B22 -> 0.31675957 | C24: =C14+C22 -> 0.34123726 | D24: =D14+D22 -> 0.33278611 | E24: =E14+E22 -> 0.337686 | F24: =F14+F22 -> 0.32716511 | G24: =G14+G22 -> 0.40887539 | H24: =H14+H22 -> 0 | I24: =I14+I22 -> 0.77543605 | ... S24: =S14+S22 -> 0.43701161 | V24: =V14+V22 -> 0.36877801 | W24: =0.0498+V6+V7+V8 -> 0.32981852 | X24: =X14+X22 -> 0.038959493 | AA24: $/lb excl matl | AC24: =ROUND(AC23/AC29,5) -> 0.08996 | AG24: =ROUND(AG23/AC29,5) -> 0.0498 | AI24: =ROUND(AI23/AC29,5) -> 0.04016
A25: Less: Substrate Plant Under-absorption | B25: =-B7 -> 0 | D25: 0 | E25: =-E7 -> 0 | G25: -0.02807392 | H25: =-H7 -> 0 | J25: -0.22562455 | K25: =-K7 -> 0 | M25: -0.02886962 | N25: =-N7 -> 0 | Q25: =-Q7 -> 0 | S25: -0.027061741 | V25: 0
A26: Less: RC Under-absorption | B26: =IF(B9+B10+B11+B12+B13+B22>0.0498,0.0498-B9-B10-B11-B12-B13-B22,0) -> -0.039199457 | C26: -0.079184632 | D26: -0.081 | E26: =IF(E9+E10+E11+E12+E13+E22>0.0498,0.0498-E9-E10-E11-E12-E13-E22,0) -> -0.039026693 | F26: =IF(F9+F10+F11+F12+F13+F22>0.0498,0.0498-F9-F10-F11-F12-F13-F22,0) -> -0.064407031 | G26: =IF(G9+G10+G11+G12+G13+G22>0.0498,0.0498-G9-G10-G11-G12-G13-G22,0) -> -0.079620814 | H26: =IF(H9+H10+H11+H12+H13+H22>0.0498,0.0498-H9-H10-H11-H12-H13-H22,0) -> 0 | I26: -0.36723743 | J26: =IF(J9+J10+J11+J12+J13+J22>0.0498,0.0498-J9-J10-J11-J12-J13-J22,0) -> -0.10097661 | K26: =IF(K9+K10+K11+K12+K13+K22>0.0498,0.0498-K9-K10-K11-K12-K13-K22,0) -> -0.039199457 | L26: =IF(L9+L10+L11+L12+L13+L22>0.0498,0.0498-L9-L10-L11-L12-L13-L22,0) -> -0.54222065 | M26: =IF(M9+M10+M11+M12+M13+M22>0.0498,0.0498-M9-M10-M11-M12-M13-M22,0) -> -0.079620814 | N26: =IF(N9+N10+N11+N12+N13+N22>0.0498,0.0498-N9-N10-N11-N12-N13-N22,0) -> 0 | O26: =IF(O9+O10+O11+O12+O13+O22>0.0498,0.0498-O9-O10-O11-O12-O13-O22,0) -> 0 | P26: =IF(P9+P10+P11+P12+P13+P22>0.0498,0.0498-P9-P10-P11-P12-P13-P22,0) -> 0 | Q26: =IF(Q9+Q10+Q11+Q12+Q13+Q22>0.0498,0.0498-Q9-Q10-Q11-Q12-Q13-Q22,0) -> 0 | ... S26: =IF(S9+S10+S11+S12+S13+S22>0.0498,0.0498-S9-S10-S11-S12-S13-S22,0) -> -0.079620814 | V26: =($B26*$B$29+$E26*$E$29+$H26*$H$29+$K26*$K$29+$N26*$N$29+$Q26*$Q$29+$B57*$B$60+$E57*$E$60+$H57*$H$60+$K57*$K$60+$N57*$N$60+$Q57*$Q$60)/$B$64 -> -0.038959493
A27: Net Cost per Pound Absorbed | B27: =SUM(B24:B26) -> 0.27756011 | C27: =SUM(C24:C26) -> 0.26205262 | D27: =SUM(D24:D26) -> 0.25178611 | E27: =SUM(E24:E26) -> 0.29865931 | F27: =SUM(F24:F26) -> 0.26275808 | G27: =SUM(G24:G26) -> 0.30118066 | H27: =SUM(H24:H26) -> 0 | I27: =SUM(I24:I26) -> 0.40819862 | ... S27: =SUM(S24:S26) -> 0.33032906 | V27: =SUM(V24:V26) -> 0.32981852
AA28: $/lb incl matl | AC28: =ROUND((AC24+(B8*B29+E8*E29+H8*H29+K8*K29+N8*N29+Q8*Q29+B39*B60+E39*E60+H39*H60)/B64),5) -> 0.14926 | AG28: =ROUND(AG24+W8,5) -> 0.1091 | AI28: =ROUND(AI24+X8,5) -> 0.04016
A29: Total Production (000 lbs) | B29: 0 | C29: 15431 | D29: 3000 | E29: 21000 | F29: 9412 | G29: 10000 | H29: 0 | I29: 74 | J29: 0 | K29: =+B84 -> 0 | L29: 254 | M29: 1000 | N29: =$B$85 -> 0 | O29: 0 | P29: 0 | Q29: 0 | R29: 3647.15 | S29: 1300 | V29: =B29+E29+H29+K29+N29+Q29+B60+E60+H60+K60+N60+Q60 -> 27900 | AA29: Prod lbs | AC29: =ROUND($B$64*1000,0) -> 27900000
B34: Fusion | E34: ScaleGuard II CL | H34: KSXT | K34: ScaleGuard II KSHD (H) | N34: XX | Q34: XX
B35: =+E4 -> 22 Standard | C35: 19 Actual | D35: =+D4 -> 21 Standard | E35: =+E4 -> 22 Standard | F35: 19 Actual | G35: =+D4 -> 21 Standard | H35: =+E4 -> 22 Standard | I35: 19 Actual | J35: =+D4 -> 21 Standard | K35: =+B4 -> 21 Standard | L35: 19 Actual | M35: =+D4 -> 21 Standard | N35: =+B4 -> 21 Standard | O35: 19 Actual | P35: =+D4 -> 21 Standard | Q35: =+B4 -> 21 Standard | R35: 19 Actual | S35: =+D4 -> 21 Standard
C36: (Jan-Sept) | F36: (Jan-Sept) | I36: (Jan-Sept) | L36: (Jan-Sept)
A37: Materials - Substrate | B37: =E150 -> 0.21326582 | C37: 0.34054143 | D37: 0.22007722 | E37: =G150 -> 0.51387049 | F37: 0.4105 | G37: 0.41282107 | H37: =I150 -> 0.41122404 | I37: 0.26541432 | J37: 0.28800984 | L37: 0 | M37: 1.8829093 | O37: 0 | P37: 0 | R37: 0 | S37: 0
A38: Materials - Substrate Under-Absorption | B38: =$C136*D136 -> 0 | D38: 0 | E38: =$C134*F134 -> 0 | G38: 0.046029189 | H38: =$C131*H131 -> 0 | J38: 0.09332723 | M38: 0.16177979 | P38: 0 | S38: 0
A39: Materials - Resin & Chemicals | B39: =E151+E152 -> 0.067925472 | C39: 0.093737947 | D39: 0.0467607 | E39: =G151+G152 -> 0.04253052 | F39: 0.043894371 | G39: 0.04221848 | H39: =I151+I152 -> 0.0059336936 | I39: 0.04843802 | J39: 0.008758525 | L39: 0 | M39: 0.042578635 | O39: 0 | P39: 0 | R39: 0 | S39: 0
A40: Electricity | B40: =E170 -> 0.009641779 | C40: 0.026041382 | D40: 0.0059095494 | E40: =G170 -> 0.0058784926 | F40: 0.014645894 | G40: 0.0059095494 | H40: =I170 -> 0.0074721126 | I40: 0.010462455 | J40: 0.0059095494 | L40: 0 | M40: 0.010135435 | O40: 0 | P40: 0 | R40: 0 | S40: 0
A41: Gas | B41: =E171 -> 0.001670337 | C41: 0.0016828037 | D41: 0.0013242333 | E41: =G171 -> 0.0011484202 | F41: 0.0055474856 | G41: 0.0013242333 | H41: =I171 -> 0.0013633362 | I41: 0.00084305984 | J41: 0.0013242333 | L41: 0 | M41: 0.0011247591 | O41: 0 | P41: 0 | R41: 0 | S41: 0
A42: R&M Supplies and Service | B42: =$H$179 -> 0.0043010753 | C42: 0.019710326 | D42: 0.006 | E42: =$H$179 -> 0.0043010753 | F42: 0.012018642 | G42: 0.006 | H42: =$H$179 -> 0.0043010753 | I42: 0.0073389729 | J42: 0.006 | L42: 0 | M42: 0.0086705202 | O42: 0 | P42: 0 | R42: 0 | S42: 0
A43: Manufacturing Supplies | B43: =$H$182 -> 0.00035842294 | C43: 0.0024000594 | D43: 0.002 | E43: =$H$182 -> 0.00035842294 | F43: 0.0007808962 | G43: 0.002 | H43: =$H$182 -> 0.00035842294 | I43: 0.00063205421 | J43: 0.002 | L43: 0 | M43: 0.00043352601 | O43: 0 | P43: 0 | R43: 0 | S43: 0
A44: Other variable | B44: =$H$185 -> 0.0053763441 | C44: 0.026652312 | D44: 0.006 | E44: =$H$185 -> 0.0053763441 | F44: 0.026473851 | G44: 0.006 | H44: =$H$185 -> 0.0053763441 | I44: 0.0094086246 | J44: 0.006 | L44: 0 | M44: 0.0057803468 | O44: 0 | P44: 0 | R44: 0 | S44: 0
A45: Total Variable Costs | B45: =SUM(B37:B44) -> 0.30253925 | C45: =SUM(C37:C44) -> 0.51076626 | D45: =SUM(D37:D44) -> 0.2880717 | E45: =SUM(E37:E44) -> 0.57346377 | F45: =SUM(F37:F44) -> 0.51386114 | G45: =SUM(G37:G44) -> 0.52230252 | H45: =SUM(H37:H44) -> 0.43602903 | I45: =SUM(I37:I44) -> 0.34253751 | J45: =SUM(J37:J44) -> 0.41132937 | L45: =SUM(L37:L44) -> 0 | M45: 2.1134123 | O45: =SUM(O37:O44) -> 0 | P45: =SUM(P37:P44) -> 0 | R45: =SUM(R37:R44) -> 0 | S45: =SUM(S37:S44) -> 0
A47: Production Labor | B47: =$D$216/$B$64/1000 -> 0.023140287 | C47: 0.02099802 | D47: 0.035940795 | E47: =$D$216/$B$64/1000 -> 0.023140287 | F47: 0.020095412 | G47: 0.035940795 | H47: =$D$216/$B$64/1000 -> 0.023140287 | I47: 0.017675634 | J47: 0.035940795 | L47: 0 | M47: 0.011741675 | O47: 0 | P47: 0 | R47: 0 | S47: 0
A48: Repairs & Maintenance Labor | B48: =$G$216/$B$64/1000 -> 0.0055727599 | C48: 0.010055044 | D48: 0.0113712 | E48: =$G$216/$B$64/1000 -> 0.0055727599 | F48: 0.0031155542 | G48: 0.0113712 | H48: =$G$216/$B$64/1000 -> 0.0055727599 | I48: 0.0047406695 | J48: 0.0113712 | L48: 0 | M48: 0.0041080925 | O48: 0 | P48: 0 | R48: 0 | S48: 0
A49: Indirect Payroll Costs (Benefits) | B49: =$J$216/$B$64/1000 -> 0.010221704 | C49: 0.020373428 | D49: 0.014188877 | E49: =$J$216/$B$64/1000 -> 0.010221704 | F49: 0.01913635 | G49: 0.014188877 | H49: =$J$216/$B$64/1000 -> 0.010221704 | I49: 0.0076540782 | J49: 0.014188877 | L49: 0 | M49: 0.0072598437 | O49: 0 | P49: 0 | R49: 0 | S49: 0
A50: Supervision | B50: =$E$243 -> 0.0055526882 | C50: 0.0068127908 | D50: 0 | E50: =$E$243 -> 0.0055526882 | F50: 0.0082982662 | G50: 0 | H50: =$E$243 -> 0.0055526882 | I50: 0.0028565151 | J50: 0 | L50: 0 | M50: 0.002449852 | O50: 0 | P50: 0 | R50: 0 | S50: 0
A51: Depreciation | B51: =$E$244 -> 0.0040172043 | C51: 0.18195763 | D51: 0.01039048 | E51: =$E$244 -> 0.0040172043 | F51: 0.22264847 | G51: 0.01039048 | H51: =$E$244 -> 0.0040172043 | I51: 0.07640353 | J51: 0.01039048 | L51: 0 | M51: 0.06367052 | O51: 0 | P51: 0 | R51: 0 | S51: 0
A52: Insurance & Taxes | B52: =$E$245 -> 0.020176344 | C52: 0.045121869 | D52: 0.03763008 | E52: =$E$245 -> 0.020176344 | F52: 0.064601784 | G52: 0.03763008 | H52: =$E$245 -> 0.020176344 | I52: 0.019244874 | J52: 0.03763008 | L52: 0 | M52: 0.014046243 | O52: 0 | P52: 0 | R52: 0 | S52: 0
A53: Total Fixed Costs | B53: =SUM(B47:B52) -> 0.068680988 | C53: =SUM(C47:C52) -> 0.28531878 | D53: =SUM(D47:D52) -> 0.10952143 | E53: =SUM(E47:E52) -> 0.068680988 | F53: =SUM(F47:F52) -> 0.33789584 | G53: =SUM(G47:G52) -> 0.10952143 | H53: =SUM(H47:H52) -> 0.068680988 | I53: =SUM(I47:I52) -> 0.1285753 | J53: =SUM(J47:J52) -> 0.10952143 | L53: =SUM(L47:L52) -> 0 | M53: 0.10327623 | O53: =SUM(O47:O52) -> 0 | P53: =SUM(P47:P52) -> 0 | R53: =SUM(R47:R52) -> 0 | S53: =SUM(S47:S52) -> 0
A55: Total Cost per Pound at Gross | B55: =B45+B53 -> 0.37122024 | C55: =C45+C53 -> 0.79608504 | D55: =D45+D53 -> 0.39759313 | E55: =E45+E53 -> 0.64214476 | F55: =F45+F53 -> 0.85175698 | G55: =G45+G53 -> 0.63182396 | H55: =H45+H53 -> 0.50471001 | I55: =I45+I53 -> 0.47111281 | ... S55: =S45+S53 -> 0
A56: Less: Substrate Plant Under-absorption | B56: =-B38 -> 0 | C56: =-C38 -> 0 | D56: 0 | E56: =-E38 -> 0 | G56: -0.046 | H56: =-H38 -> 0 | J56: -0.09332723 | K56: =-K38 -> 0 | M56: -0.0074705959 | N56: =-N38 -> 0 | P56: 0 | Q56: =-Q38 -> 0
A57: Less: RC Under-absorption | B57: =IF(B40+B41+B42+B43+B44+B53>0.0498,0.0498-B40-B41-B42-B43-B44-B53,0) -> -0.040228947 | C57: -0.31205821 | D57: =IF(D40+D41+D42+D43+D44+D53>0.0498,0.0498-D40-D41-D42-D43-D44-D53,0) -> -0.080955215 | E57: =IF(E40+E41+E42+E43+E44+E53>0.0498,0.0498-E40-E41-E42-E43-E44-E53,0) -> -0.035943744 | F57: =IF(F40+F41+F42+F43+F44+F53>0.0498,0.0498-F40-F41-F42-F43-F44-F53,0) -> -0.34756261 | G57: =IF(G40+G41+G42+G43+G44+G53>0.0498,0.0498-G40-G41-G42-G43-G44-G53,0) -> -0.080955215 | H57: =IF(H40+H41+H42+H43+H44+H53>0.0498,0.0498-H40-H41-H42-H43-H44-H53,0) -> -0.037752279 | I57: =IF(I40+I41+I42+I43+I44+I53>0.0498,0.0498-I40-I41-I42-I43-I44-I53,0) -> -0.10746047 | J57: -0.080955215 | K57: =IF(K40+K41+K42+K43+K44+K53>0.0498,0.0498-K40-K41-K42-K43-K44-K53,0) -> 0 | L57: =IF(L40+L41+L42+L43+L44+L53>0.0498,0.0498-L40-L41-L42-L43-L44-L53,0) -> 0 | M57: =IF(M40+M41+M42+M43+M44+M53>0.0498,0.0498-M40-M41-M42-M43-M44-M53,0) -> -0.079620814 | N57: =IF(N40+N41+N42+N43+N44+N53>0.0498,0.0498-N40-N41-N42-N43-N44-N53,0) -> 0 | O57: 0 | P57: =IF(P40+P41+P42+P43+P44+P53>0.0498,0.0498-P40-P41-P42-P43-P44-P53,0) -> 0 | Q57: =IF(Q40+Q41+Q42+Q43+Q44+Q53>0.0498,0.0498-Q40-Q41-Q42-Q43-Q44-Q53,0) -> 0 | R57: 0 | S57: =IF(S40+S41+S42+S43+S44+S53>0.0498,0.0498-S40-S41-S42-S43-S44-S53,0) -> 0
A58: Net Cost per Pound Absorbed | B58: =SUM(B55:B57) -> 0.3309913 | C58: =SUM(C55:C57) -> 0.48402683 | D58: =SUM(D55:D57) -> 0.31663792 | E58: =SUM(E55:E57) -> 0.60620101 | F58: =SUM(F55:F57) -> 0.50419437 | G58: =SUM(G55:G57) -> 0.50486874 | H58: =SUM(H55:H57) -> 0.46695773 | I58: =SUM(I55:I57) -> 0.36365234 | ... S58: =SUM(S55:S57) -> 0
A60: Total Production (000 lbs) | B60: =+B87 -> 4400 | C60: 101 | D60: 1100 | E60: =+B88 -> 2200 | F60: 979 | G60: 1700 | H60: =+B92 -> 300 | I60: 2743 | J60: 5500 | K60: =+B90 -> 0 | L60: 0 | M60: 100 | N60: 0 | O60: 0 | P60: 0 | Q60: 0 | R60: 0 | S60: 0
A64: Total Plant Production (000 lbs) | B64: =B29+E29+H29+K29+N29+Q29+B60+E60+H60+K60+N60+Q60 -> 27900 | C64: =C29+F29+I29+L29+O29+R29+C60+F60+I60+L60+O60+R60 -> 32641.15 | D64: =D29+G29+J29+M29+P29+S29+D60+G60+J60+M60+P60+S60 -> 23700
V65: 2078820 | W65: 2289955 | AC65: 1.102 | AD65: 0.099 | AE65: =+AC65-AD65 -> 1.003
V66: 22566 | W66: 22313 | AC66: 0.989 | AD66: 0 | AE66: =+AC66-AD66 -> 0.989
B67: Total | C67: Variable | D67: Fixed | V67: 469400 | W67: 521591 | AC67: 1.111 | AD67: 0.07 | AE67: =+AC67-AD67 -> 1.041
A68: Cost Summary: | B68: ($ in 000s) | V68: 514675 | W68: 642354 | AC68: 1.248 | AD68: 0.015 | AE68: =+AC68-AD68 -> 1.233
A69: Absorbed by Production | B69: =SUM(C69:D69) -> 9201.9368 | C69: =W14*$V$29 -> 8372.707 | D69: =W22*$V$29 -> 829.22973 | V69: 62400 | W69: 68640 | AC69: 1.1 | AD69: 0.158 | AE69: =+AC69-AD69 -> 0.942
A70: Underabsorption Expensed | B70: =SUM(C70:D70) -> 1086.9698 | C70: =X14*$V$29 -> 0 | D70: =X22*$V$29 -> 1086.9698 | V70: 22275 | W70: 27844 | AC70: 1.25 | AD70: 0 | AE70: =+AC70-AD70 -> 1.25
A71: Loss on Excess Gas Net Settled | B71: =SUM(C71:D71) -> 0 | C71: 0 | D71: 0 | V71: 10980 | W71: 13725 | AC71: 1.25 | AD71: 0 | AE71: =+AC71-AD71 -> 1.25
A72: Total Cost | B72: =SUM(B69:B71) -> 10288.907 | C72: =SUM(C69:C71) -> 8372.707 | D72: =SUM(D69:D71) -> 1916.1996 | AE72: =AVERAGE(AE65:AE71) -> 1.1011429
A73: Less: Non-Cash | B73: =SUM(C73:D73) -> -112.08 | C73: 0 | D73: =-V20*V29 -> -112.08 | V73: =SUM(V65:V72) -> 3181116 | W73: =SUM(W65:W72) -> 3586422
A74: Cash Cost | B74: =SUM(B72:B73) -> 10176.827 | C74: =SUM(C72:C73) -> 8372.707 | D74: =SUM(D72:D73) -> 1804.1196 | V74: 3233726 | W74: 1569174 | X74: =+W74/V74 -> 0.48525262
V75: =+V73-V74 -> -52610 | W75: =+W73-W74 -> 2017248
B79: Quantity | C79: Rate
A80: Production Plan | B80: (000 lbs) | C80: (000 lbs/day) | D80: Prodn Days | E80: % Split
A81: CB Lite | B81: 21000 | C81: 350 | D81: =IF(C81<>0,B81/C81,0) -> 60 | E81: =IF($D$93<>0,D81/$D$93,0) -> 0.75268817
A82: CB HSP | B82: 0 | C82: =350 -> 350 | D82: =IF(C82<>0,B82/C82,0) -> 0 | E82: =IF($D$93<>0,D82/$D$93,0) -> 0
A83: CB KSLD | B83: 0 | C83: =350 -> 350 | D83: =IF(C83<>0,B83/C83,0) -> 0 | E83: =IF($D$93<>0,D83/$D$93,0) -> 0
A84: RPM Lite / NP LWC | B84: 0 | C84: =350 -> 350 | D84: =IF(C84<>0,B84/C84,0) -> 0 | E84: =IF($D$93<>0,D84/$D$93,0) -> 0
A85: RPM CP / NP ISP | B85: 0 | C85: =350 -> 350 | D85: =IF(C85<>0,B85/C85,0) -> 0 | E85: =IF($D$93<>0,D85/$D$93,0) -> 0
A86: Air | B86: 0 | C86: =350 -> 350 | D86: =IF(C86<>0,B86/C86,0) -> 0 | E86: =IF($D$93<>0,D86/$D$93,0) -> 0
A87: Fusion (#998, 999, 1025) | B87: 4400 | C87: =350 -> 350 | D87: =IF(C87<>0,B87/C87,0) -> 12.571429 | E87: =IF($D$93<>0,D87/$D$93,0) -> 0.15770609
A88: SG II CL | B88: 2200 | C88: =350 -> 350 | D88: =IF(C88<>0,B88/C88,0) -> 6.2857143 | E88: =IF($D$93<>0,D88/$D$93,0) -> 0.078853047
A89: SG II Ultra CL | B89: 0 | C89: =350 -> 350 | D89: =IF(C89<>0,B89/C89,0) -> 0 | E89: =IF($D$93<>0,D89/$D$93,0) -> 0
A90: SG II KSHD (H) | B90: 0 | C90: =350 -> 350 | D90: =IF(C90<>0,B90/C90,0) -> 0 | E90: =IF($D$93<>0,D90/$D$93,0) -> 0
A91: SaltGuard (FDP-806) | B91: 0 | C91: =350 -> 350 | D91: =IF(C91<>0,B91/C91,0) -> 0 | E91: =IF($D$93<>0,D91/$D$93,0) -> 0
A92: KSXT | B92: 300 | C92: =350 -> 350 | D92: =IF(C92<>0,B92/C92,0) -> 0.85714286 | E92: =IF($D$93<>0,D92/$D$93,0) -> 0.010752688
A93: Total | B93: =SUM(B81:B92) -> 27900 | C93: =B93/D93 -> 350 | D93: =SUM(D81:D92) -> 79.714286 | E93: =IF($D$93<>0,D93/$D$93,0) -> 1
A96: Variable Costs - Material
D98: CB Lite | F98: CB Lite EU | H98: CB KSLD | J98: RPM Lite / NP LWC | L98: XX | N98: Air | AF98: CBL | AH98: CBL (EU) | AJ98: RPM | AL98: AIR
A99: Materials Cost: | B99: Price ($/lb) | C99: Source plant under-absorb | D99: BOM Use/lb | E99: Standard Cost | F99: BOM Use/lb | G99: Standard Cost | H99: BOM Use/lb | I99: Standard Cost | J99: BOM Use/lb | K99: Standard Cost | L99: BOM Use/lb | M99: Standard Cost | N99: BOM Use/lb | O99: Standard Cost | AB99: material | AE99: plan price 1 | AF99: cost BOM | AG99: plan price 1 | AH99: cost BOM | AI99: plan price 1 | AJ99: cost BOM | AK99: plan price 1 | AL99: cost BOM
A100: CARBO LITE (32, 36, 115) | B100: =0.1586+0.032-C100 -> 0.1906 | C100: 0 | D100: 0.96442882 | E100: =$B100*D100 -> 0.18382013 | F100: 0.99078514 | G100: =$B100*F100 -> 0.18884365 | H100: 0 | I100: =$B100*H100 -> 0 | J100: 1.0310579 | K100: =$B100*J100 -> 0.19651963 | L100: 0 | M100: =$B100*L100 -> 0 | N100: 0 | O100: =$B100*N100 -> 0 | AB100: CL | AE100: =B100*1000 -> 190.6 | AF100: =E100/B100*1000 -> 964.42882 | AH100: =G100/B100*1000 -> 990.78514 | AJ100: =K100/B100*1000 -> 1031.0579
A101: CARBOAIR UL (861, 938) | B101: =0.1586+0.032-C101 -> 0.1906 | C101: 0 | D101: 0 | E101: =$B101*D101 -> 0 | F101: 0 | G101: =$B101*F101 -> 0 | H101: 0 | I101: =$B101*H101 -> 0 | J101: 0 | K101: =$B101*J101 -> 0 | L101: 0 | M101: =$B101*L101 -> 0 | N101: 0.96649076 | O101: =$B101*N101 -> 0.18421314 | AL101: =O101/B101*1000 -> 966.49076
A102: KRYPTOSPHERE LD (976) | B102: =0.378+0.032-C102 -> 0.41 | C102: 0 | D102: 0 | E102: =$B102*D102 -> 0 | F102: 0 | G102: =$B102*F102 -> 0 | H102: 0 | I102: =$B102*H102 -> 0 | J102: 0 | K102: =$B102*J102 -> 0 | L102: 0 | M102: =$B102*L102 -> 0 | N102: 0 | O102: =$B102*N102 -> 0
A103: CARBO HSP (19) | B103: =0.2+0.032-C103 -> 0.232 | C103: 0 | D103: 0 | E103: =$B103*D103 -> 0 | F103: 0 | G103: =$B103*F103 -> 0 | H103: 0 | I103: =$B103*H103 -> 0 | J103: 0 | K103: =$B103*J103 -> 0 | L103: 0 | M103: =$B103*L103 -> 0 | N103: 0 | O103: =$B103*N103 -> 0
A104: CARBOPROP (50) | B104: 0 | C104: 0 | D104: 0 | E104: =$B104*D104 -> 0 | F104: 0 | G104: =$B104*F104 -> 0 | H104: 0 | I104: =$B104*H104 -> 0 | J104: 0 | K104: =$B104*J104 -> 0 | L104: 0 | M104: =$B104*L104 -> 0 | N104: 0 | O104: =$B104*N104 -> 0
A105: SCALEGUARD I CL (812, 951) | B105: =0.5084-C105 -> 0.5084 | C105: 0 | D105: 0 | E105: =$B105*D105 -> 0 | F105: 0 | G105: =$B105*F105 -> 0 | H105: 0 | I105: =$B105*H105 -> 0 | J105: 0 | K105: =$B105*J105 -> 0 | L105: 0 | M105: =$B105*L105 -> 0 | N105: 0 | O105: =$B105*N105 -> 0
A106: SCALEGUARD I KSHD (H) | B106: =1.9036-C106 -> 1.9036 | C106: 0 | D106: 0 | E106: =$B106*D106 -> 0 | F106: 0 | G106: =$B106*F106 -> 0 | H106: 0 | I106: =$B106*H106 -> 0 | J106: 0 | K106: =$B106*J106 -> 0 | L106: 0 | M106: =$B106*L106 -> 0 | N106: 0 | O106: =$B106*N106 -> 0
A107: CL FUSION SUBSTRATE (994) | B107: =0.1586+0.032-C107+0.02 -> 0.2106 | C107: 0 | D107: 0 | E107: =$B107*D107 -> 0 | F107: 0 | G107: =$B107*F107 -> 0 | H107: 0 | I107: =$B107*H107 -> 0 | J107: 0 | K107: =$B107*J107 -> 0 | L107: 0 | M107: =$B107*L107 -> 0 | N107: 0 | O107: =$B107*N107 -> 0
A108: Plenco Resin (30090) | B108: =1506/1000 -> 1.506 | C108: 0 | D108: 0 | E108: =$B108*D108 -> 0 | F108: 0.030157074 | G108: =$B108*F108 -> 0.045416554 | H108: 0 | I108: =$B108*H108 -> 0 | J108: 0 | K108: =$B108*J108 -> 0 | L108: 0 | M108: =$B108*L108 -> 0 | N108: 0.040703571 | O108: =$B108*N108 -> 0.061299578 | AB108: 30090 | AE108: =B108*1000 -> 1506 | AF108: =E108/B108*1000 -> 0 | AL108: =O108/B108*1000 -> 40.703571
A109: Bimex Resin-EU (30120) | B109: 1.262 | C109: 0 | D109: 0.0317 | E109: =$B109*D109 -> 0.0400054 | F109: 0.0052246952 | G109: =$B109*F109 -> 0.0065935654 | H109: 0 | I109: =$B109*H109 -> 0 | J109: 0 | K109: =$B109*J109 -> 0 | L109: 0 | M109: =$B109*L109 -> 0 | N109: 0 | O109: =$B109*N109 -> 0 | AB109: 30120 | AE109: =B109*1000 -> 1262 | AF109: =E109/B109*1000 -> 31.7 | AH109: =G109/B109*1000 -> 5.2246952
A110: HEXA-EU (30362) | B110: 0.78833 | C110: 0 | D110: 0.0044 | E110: =$B110*D110 -> 0.003468652 | F110: 0.0061505935 | G110: =$B110*F110 -> 0.0048486974 | H110: 0 | I110: =$B110*H110 -> 0 | J110: 0 | K110: =$B110*J110 -> 0 | L110: 0 | M110: =$B110*L110 -> 0 | N110: 0 | O110: =$B110*N110 -> 0 | AB110: 30362 | AE110: =B110*1000 -> 788.33 | AF110: =E110/B110*1000 -> 4.4 | AH110: =G110/B110*1000 -> 6.1505935
A111: Silane-EU (30360) | B111: 4.46 | C111: 0 | D111: 0 | E111: =$B111*D111 -> 0 | F111: 0.00052718059 | G111: =$B111*F111 -> 0.0023512255 | H111: 0 | I111: =$B111*H111 -> 0 | J111: 0 | K111: =$B111*J111 -> 0 | L111: 0 | M111: =$B111*L111 -> 0 | N111: 8.2256008e-06 | O111: =$B111*N111 -> 3.668618e-05 | AB111: 30360 | AH111: =G111/B111*1000 -> 0.52718059 | AL111: =O111/B111*1000 -> 0.0082256008
A112: Surfactant-EU (30361) | B112: =1449.8/1000 -> 1.4498 | C112: 0 | D112: 0 | E112: =$B112*D112 -> 0 | F112: 0.00055567684 | G112: =$B112*F112 -> 0.00080562029 | H112: 0 | I112: =$B112*H112 -> 0 | J112: 0 | K112: =$B112*J112 -> 0 | L112: 0 | M112: =$B112*L112 -> 0 | N112: 3.1805656e-05 | O112: =$B112*N112 -> 4.6111841e-05 | AB112: 30361 | AH112: =G112/B112*1000 -> 0.55567684 | AL112: =O112/B112*1000 -> 0.031805656
A113: Surfactant (30054) | B113: =1164.82/1000 -> 1.16482 | C113: 0 | D113: 0.0004 | E113: =$B113*D113 -> 0.000465928 | F113: 0 | G113: =$B113*F113 -> 0 | H113: 0 | I113: =$B113*H113 -> 0 | J113: 0 | K113: =$B113*J113 -> 0 | L113: 0 | M113: =$B113*L113 -> 0 | N113: 0.0015403808 | O113: =$B113*N113 -> 0.0017942664 | AB113: 30054 | AE113: =B113*1000 -> 1164.82 | AF113: =E113/B113*1000 -> 0.4 | AL113: =O113/B113*1000 -> 1.5403808
A114: Hexamine (30055) | B114: =1096.46/1000 -> 1.09646 | C114: 0 | D114: 0 | E114: =$B114*D114 -> 0 | F114: 0 | G114: =$B114*F114 -> 0 | H114: 0 | I114: =$B114*H114 -> 0 | J114: 0 | K114: =$B114*J114 -> 0 | L114: 0 | M114: =$B114*L114 -> 0 | N114: 0.0053356402 | O114: =$B114*N114 -> 0.005850316 | AB114: 30055 | AE114: =B114*1000 -> 1096.46 | AF114: =E114/B114*1000 -> 0 | AL114: =O114/B114*1000 -> 5.3356402
A115: Silane (30058) | B115: =4019.96/1000 -> 4.01996 | C115: 0 | D115: 0 | E115: =$B115*D115 -> 0 | F115: 0 | G115: =$B115*F115 -> 0 | H115: 0 | I115: =$B115*H115 -> 0 | J115: 0 | K115: =$B115*J115 -> 0 | L115: 0 | M115: =$B115*L115 -> 0 | N115: 0.0010131198 | O115: =$B115*N115 -> 0.0040727012 | AB115: 30058 | AE115: =B115*1000 -> 4019.96 | AF115: =E115/B115*1000 -> 0 | AL115: =O115/B115*1000 -> 1.0131198
A116: WB Concentrate (30454) | B116: 16.504 | C116: 0 | D116: 0 | E116: =$B116*D116 -> 0 | F116: 0 | G116: =$B116*F116 -> 0 | H116: 0 | I116: =$B116*H116 -> 0 | J116: 0 | K116: =$B116*J116 -> 0 | L116: 0 | M116: =$B116*L116 -> 0 | N116: 0 | O116: =$B116*N116 -> 0 | AB116: 30454 | AJ116: =K116/B116*1000 -> 0
A117: PST100 (30116) | B117: =8993.38/1000 -> 8.99338 | J117: 0.0078 | K117: =$B117*J117 -> 0.070148364
...

Sheet NI RC 2021 Std
A1: New Iberia Resin Coating | AB1: Activity | AC1: 10001005 | AD1: 10001005 | AE1: Gross | AF1: Qty/1000 | AG1: 10001005 | AH1: Absorbed | AI1: 10001005 | AJ1: Abs Cost
A2: 2021 STANDARDS | AA2: Unit | AB2: Type | AC2: Total Cost | AD2: Total Qty | AE2: Unit Cost | AF2: Prod lbs | AG2: Absorption | AH2: Unit Cost | AI2: Underabs | AJ2: per 10000
B3: CARBOBond Lite | E3: CARBOBond Lite EU | H3: CARBOBond KSLD | K3: RPM LITE / NEUTRAPROP LWC | N3: XX | Q3: CARBO AIR
B4: 21 Standard | C4: 19 Actual | D4: 20 Standard | E4: =+B4 -> 21 Standard | F4: 19 Actual | G4: =+D4 -> 20 Standard | H4: =+B4 -> 21 Standard | I4: =+C4 -> 19 Actual | J4: =+D4 -> 20 Standard | K4: =+B4 -> 21 Standard | L4: 18 Actual | M4: =+D4 -> 20 Standard | N4: =+B4 -> 21 Standard | O4: 19 Actual | P4: =+D4 -> 20 Standard | Q4: =+B4 -> 21 Standard | R4: 18 Actual | S4: =+D4 -> 20 Standard | V4: Composite | W4: Absorb | X4: Underabsorb
C5: (Jan-Sept) | F5: (Jan-Sept) | I5: =+C5 -> (Jan-Sept) | L5: (Jan-Nov) | R5: (Jan-Oct)
A6: Materials - Substrate | B6: =E121 -> 0.1639529 | C6: 0.16092998 | D6: 0.14369989 | E6: =G121 -> 0.15970957 | F6: 0.15896741 | G6: 0.13998074 | I6: 0.30191317 | J6: 0.28067655 | K6: =K121 -> 0.17527984 | L6: 0.18307969 | M6: 0.15362762 | O6: 0 | P6: 0 | R6: 0.15968841 | S6: 0.14400712 | V6: =($B6*$B$29+$E6*$E$29+$H6*$H$29+$K6*$K$29+$N6*$N$29+$Q6*$Q$29+$B37*$B$60+$E37*$E$60+$H37*$H$60+$K37*$K$60+$N37*$N$60+$Q37*$Q$60)/$B$64 -> 0.25841035 | W6: =V6 -> 0.25841035
A7: Materials - Substrate Under-Absorption | B7: =$C100*D100 -> 0 | D7: 0.088727451 | E7: =$C100*F100 -> 0 | G7: 0.08643106 | J7: 0.22562455 | K7: =$C100*J100 -> 0 | M7: 0.094857323 | P7: 0 | S7: 0.08891715 | V7: 0 | W7: 0
A8: Materials - Resin & Chemicals | B8: =E122+E123 -> 0.038078 | C8: 0.051903794 | D8: 0.049388695 | E8: =G122+G123 -> 0.047521438 | F8: 0.053990671 | G8: 0.053042779 | I8: 0.05384576 | J8: 0.0471079 | K8: =K122+K123 -> 0.073985808 | L8: 0.071924563 | M8: 0.15903358 | O8: 0 | P8: 0 | R8: 0.072759577 | S8: 0.074666525 | V8: =($B8*$B$29+$E8*$E$29+$H8*$H$29+$K8*$K$29+$N8*$N$29+$Q8*$Q$29+$B39*$B$60+$E39*$E$60+$H39*$H$60+$K39*$K$60+$N39*$N$60+$Q39*$Q$60)/$B$64 -> 0.029951763 | W8: =V8 -> 0.029951763 | X8: =V8-W8 -> 0
A9: Electricity | B9: =E163 -> 0.0059095494 | C9: 0.0077075348 | D9: 0.010135435 | E9: =G163 -> 0.0059095494 | F9: 0.0064153677 | G9: 0.010135435 | I9: 0.023850562 | J9: 0.010726 | K9: =K163 -> 0.0059095494 | L9: 0.019218863 | M9: 0.010135435 | O9: 0 | P9: 0 | R9: 0.006525594 | S9: 0.010135435 | V9: =($B9*$B$29+$E9*$E$29+$H9*$H$29+$K9*$K$29+$N9*$N$29+$Q9*$Q$29+$B40*$B$60+$E40*$E$60+$H40*$H$60+$K40*$K$60+$N40*$N$60+$Q40*$Q$60)/$B$64 -> 0.0059095494 | W9: =V9 -> 0.0059095494 | X9: =V9-W9 -> 0 | AA9: kwh | AB9: ELE01 | AC9: =ROUND(((D163*B$29*1000)+(F163*E$29*1000)+(H163*H$29*1000)+(J163*K$29*1000)+(L163*N$29*1000)+(N163*Q$29*1000)+(D170*B$60*1000)+(F170*E$60*1000)+(H170*H$60*1000)+(J170*K$60*1000)+(L170*N$60*1000)+(N170*Q$60*1000))*$B163,0) -> 73869 | AD9: =ROUND((D163*B$29*1000)+(F163*E$29*1000)+(H163*H$29*1000)+(J163*K$29*1000)+(L163*N$29*1000)+(N163*Q$29*1000)+(D170*B$60*1000)+(F170*E$60*1000)+(H170*H$60*1000)+(J170*K$60*1000)+(L170*N$60*1000)+(N170*Q$60*1000),0) -> 540273 | AE9: =AC9/AD9 -> 0.13672532 | AF9: =ROUND(AD9/$B$64,3) -> 43.222 | AG9: =ROUND(W9*$AC$29,0) -> 73869 | AH9: =AG9/AD9 -> 0.13672532 | AI9: =AC9-AG9 -> 0 | AJ9: =AH9*10000 -> 1367.2532
A10: Gas | B10: =E164 -> 0.0013242333 | C10: 0.00096524487 | D10: 0.0011247591 | E10: =G164 -> 0.0013242333 | F10: 0.00088623983 | G10: 0.0011247591 | I10: 0.0011573683 | J10: 0.00126 | K10: =K164 -> 0.0013242333 | L10: 0.0011031846 | M10: 0.0011247591 | O10: 0 | P10: 0 | R10: 0.0011625955 | S10: 0.0011247591 | V10: =($B10*$B$29+$E10*$E$29+$H10*$H$29+$K10*$K$29+$N10*$N$29+$Q10*$Q$29+$B41*$B$60+$E41*$E$60+$H41*$H$60+$K41*$K$60+$N41*$N$60+$Q41*$Q$60)/$B$64 -> 0.0013242333 | W10: =V10 -> 0.0013242333 | X10: =V10-W10 -> 0 | AA10: mbtu | AB10: GAS01 | AC10: =ROUND(((D164*B$29*1000)+(F164*E$29*1000)+(H164*H$29*1000)+(J164*K$29*1000)+(L164*N$29*1000)+(N164*Q$29*1000)+(D171*B$60*1000)+(F171*E$60*1000)+(H171*H$60*1000)+(J171*K$60*1000)+(L171*N$60*1000)+(N171*Q$60*1000))*$B164,0) -> 16553 | AD10: =ROUND(((D164*B$29*1000)+(F164*E$29*1000)+(H164*H$29*1000)+(J164*K$29*1000)+(L164*N$29*1000)+(N164*Q$29*1000)+(D171*B$60*1000)+(F171*E$60*1000)+(H171*H$60*1000)+(J171*K$60*1000)+(L171*N$60*1000)+(N171*Q$60*1000))*1000,0) -> 3678426 | AE10: =AC10/AD10 -> 0.0045000226 | AF10: =ROUND(AD10/$B$64,3) -> 294.274 | AG10: =ROUND(W10*$AC$29,0) -> 16553 | AH10: =AG10/AD10 -> 0.0045000226 | AI10: =AC10-AG10 -> 0 | AJ10: =AH10*10000 -> 45.000226
A11: R&M Supplies and Service | B11: =$H$179 -> 0.006 | C11: 0.0052601959 | D11: 0.0086705202 | E11: =$H$179 -> 0.006 | F11: 0.0051242876 | G11: 0.0086705202 | I11: 0.023215913 | J11: 0.0099121126 | K11: =$H$179 -> 0.006 | L11: 0.026688594 | M11: 0.0086705202 | O11: 0 | P11: 0 | R11: 0.016241103 | S11: 0.0086705202 | V11: =($B11*$B$29+$E11*$E$29+$H11*$H$29+$K11*$K$29+$N11*$N$29+$Q11*$Q$29+$B42*$B$60+$E42*$E$60+$H42*$H$60+$K42*$K$60+$N42*$N$60+$Q42*$Q$60)/$B$64 -> 0.006 | W11: =V11 -> 0.006 | X11: =V11-W11 -> 0 | AA11: lb | AB11: RMS01 | AC11: =ROUND(G179,0) -> 75000 | AD11: =$B$64*1000 -> 12500000 | AE11: =AC11/AD11 -> 0.006 | AF11: =ROUND(AD11/$B$64,3) -> 1000 | AG11: =ROUND(W11*$AC$29,0) -> 75000 | AH11: =AG11/AD11 -> 0.006 | AI11: =AC11-AG11 -> 0 | AJ11: =AH11*10000 -> 60
A12: Manufacturing Supplies | B12: =$H$182 -> 0.002 | C12: 0.00028145605 | D12: 0.00043352601 | E12: =$H$182 -> 0.002 | F12: 0.0001613237 | G12: 0.00043352601 | I12: 0.00076914757 | J12: 0.00049560563 | K12: =$H$182 -> 0.002 | L12: 0.0013365915 | M12: 0.00043352601 | O12: 0 | P12: 0 | R12: 0.00053366327 | S12: 0.00043352601 | V12: =($B12*$B$29+$E12*$E$29+$H12*$H$29+$K12*$K$29+$N12*$N$29+$Q12*$Q$29+$B43*$B$60+$E43*$E$60+$H43*$H$60+$K43*$K$60+$N43*$N$60+$Q43*$Q$60)/$B$64 -> 0.002 | W12: =V12 -> 0.002 | X12: =V12-W12 -> 0 | AA12: lb | AB12: MFG01 | AC12: =ROUND(G182,0) -> 25000 | AD12: =$B$64*1000 -> 12500000 | AE12: =AC12/AD12 -> 0.002 | AF12: =ROUND(AD12/$B$64,3) -> 1000 | AG12: =ROUND(W12*$AC$29,0) -> 25000 | AH12: =AG12/AD12 -> 0.002 | AI12: =AC12-AG12 -> 0 | AJ12: =AH12*10000 -> 20
A13: Other variable | B13: =$H$185 -> 0.006 | C13: 0.005539271 | D13: 0.0057803468 | E13: =$H$185 -> 0.006 | F13: 0.0047523717 | G13: 0.0057803468 | I13: 0.017048253 | J13: 0.0066080751 | K13: =$H$185 -> 0.006 | L13: 0.026821614 | M13: 0.0057803468 | O13: 0 | P13: 0 | R13: 0.0059964109 | S13: 0.0057803468 | V13: =($B13*$B$29+$E13*$E$29+$H13*$H$29+$K13*$K$29+$N13*$N$29+$Q13*$Q$29+$B44*$B$60+$E44*$E$60+$H44*$H$60+$K44*$K$60+$N44*$N$60+$Q44*$Q$60)/$B$64 -> 0.006 | W13: =V13 -> 0.006 | X13: =V13-W13 -> 0 | AA13: lb | AB13: VAR01 | AC13: =ROUND(G185,0) -> 75000 | AD13: =$B$64*1000 -> 12500000 | AE13: =AC13/AD13 -> 0.006 | AF13: =ROUND(AD13/$B$64,3) -> 1000 | AG13: =ROUND(W13*$AC$29,0) -> 75000 | AH13: =AG13/AD13 -> 0.006 | AI13: =AC13-AG13 -> 0 | AJ13: =AH13*10000 -> 60
A14: Total Variable Costs | B14: =SUM(B6:B13) -> 0.22326468 | C14: =SUM(C6:C13) -> 0.23258747 | D14: 0.30796063 | E14: =SUM(E6:E13) -> 0.22846479 | F14: =SUM(F6:F13) -> 0.23029767 | G14: 0.30559917 | I14: =SUM(I6:I13) -> 0.42180018 | J14: =SUM(J6:J13) -> 0.5824108 | K14: =SUM(K6:K13) -> 0.27049943 | L14: =SUM(L6:L13) -> 0.3301731 | M14: 0.43366311 | O14: =SUM(O6:O13) -> 0 | P14: =SUM(P6:P13) -> 0 | R14: =SUM(R6:R13) -> 0.26290735 | S14: 0.33373539 | V14: =SUM(V6:V13) -> 0.3095959 | W14: =SUM(W6:W13) -> 0.3095959 | X14: =SUM(X6:X13) -> 0 | AC14: =SUM(AC9:AC13) -> 265422 | AG14: =SUM(AG9:AG13) -> 265422 | AI14: =SUM(AI9:AI13) -> 0
A16: Production Labor | B16: =$D$216/$B$64/1000 -> 0.035940795 | C16: 0.018200142 | D16: 0.011741675 | E16: =$D$216/$B$64/1000 -> 0.035940795 | F16: 0.020063713 | G16: 0.011741675 | I16: 0.012521635 | J16: 0.014552451 | K16: =$D$216/$B$64/1000 -> 0.035940795 | L16: 0.032785827 | M16: 0.011741675 | O16: 0 | P16: 0 | R16: 0.013727223 | S16: 0.011741675 | V16: =($B16*$B$29+$E16*$E$29+$H16*$H$29+$K16*$K$29+$N16*$N$29+$Q16*$Q$29+$B47*$B$60+$E47*$E$60+$H47*$H$60+$K47*$K$60+$N47*$N$60+$Q47*$Q$60)/$B$64 -> 0.035940795 | W16: =+W24-W14 -> 0.028566217 | X16: =V16-W16 -> 0.0073745775 | AA16: hr | AB16: DLAB01 | AC16: =ROUND(D214,0) -> 460178 | AD16: =ROUND(B214,0) -> 15400 | AE16: =AC16/AD16 -> 29.881688 | AF16: =ROUND(AD16/$B$64,3) -> 1.232 | AG16: =ROUND(W16*$AC$29,0) -> 357078 | AH16: =AG16/AD16 -> 23.186883 | AI16: =AC16-AG16 -> 103100 | AJ16: =AH16*10000 -> 231868.83
A17: Repairs & Maintenance Labor | B17: =$G$216/$B$64/1000 -> 0.0113712 | C17: 0.0048304191 | D17: 0.0041080925 | E17: =$G$216/$B$64/1000 -> 0.0113712 | F17: 0.0044471791 | G17: 0.0041080925 | I17: 0.0044303098 | J17: 0.004696359 | K17: =$G$216/$B$64/1000 -> 0.0113712 | L17: 0.0088578354 | M17: 0.0041080925 | O17: 0 | P17: 0 | R17: 0.0016693747 | S17: 0.0041080925 | V17: =($B17*$B$29+$E17*$E$29+$H17*$H$29+$K17*$K$29+$N17*$N$29+$Q17*$Q$29+$B48*$B$60+$E48*$E$60+$H48*$H$60+$K48*$K$60+$N48*$N$60+$Q48*$Q$60)/$B$64 -> 0.0113712 | W17: 0 | X17: =V17-W17 -> 0.0113712 | AA17: hr | AB17: MLAB01 | AC17: =ROUND(G214,0) -> 142140 | AD17: =ROUND(E214,0) -> 4400 | AE17: =AC17/AD17 -> 32.304545 | AF17: =ROUND(AD17/$B$64,3) -> 0.352 | AG17: =ROUND(W17*$AC$29,0) -> 0 | AH17: =AG17/AD17 -> 0 | AI17: =AC17-AG17 -> 142140 | AJ17: =AH17*10000 -> 0
A18: Indirect Payroll Costs (Benefits) | B18: =$J$216/$B$64/1000 -> 0.014188877 | C18: 0.0068508297 | D18: 0.0072598437 | E18: =$J$216/$B$64/1000 -> 0.014188877 | F18: 0.0059757405 | G18: 0.0072598437 | I18: 0.014238166 | J18: 0.008765191 | K18: =$J$216/$B$64/1000 -> 0.014188877 | L18: 0.038686584 | M18: 0.0072598437 | O18: 0 | P18: 0 | R18: 0.0056633179 | S18: 0.0072598437 | V18: =($B18*$B$29+$E18*$E$29+$H18*$H$29+$K18*$K$29+$N18*$N$29+$Q18*$Q$29+$B49*$B$60+$E49*$E$60+$H49*$H$60+$K49*$K$60+$N49*$N$60+$Q49*$Q$60)/$B$64 -> 0.014188877 | W18: 0 | X18: =V18-W18 -> 0.014188877 | AA18: hr | AB18: IPC01 | AC18: =ROUND(J214,0) -> 180695 | AD18: =ROUND(H214,0) -> 19800 | AE18: =AC18/AD18 -> 9.1260101 | AF18: =ROUND(AD18/$B$64,3) -> 1.584 | AG18: =ROUND(W18*$AC$29,0) -> 0 | AH18: =AG18/AD18 -> 0 | AI18: =AC18-AG18 -> 180695 | AJ18: =AH18*10000 -> 0
A19: Supervision | B19: =$E$243 -> 0 | C19: 0.0022776301 | D19: 0.002449852 | E19: =$E$243 -> 0 | F19: 0.0019225049 | G19: 0.002449852 | I19: 0.0092721693 | J19: 0.0028006635 | K19: =$E$243 -> 0 | L19: 0.01254166 | M19: 0.002449852 | O19: 0 | P19: 0 | R19: 0.0023710733 | S19: 0.002449852 | V19: =($B19*$B$29+$E19*$E$29+$H19*$H$29+$K19*$K$29+$N19*$N$29+$Q19*$Q$29+$B50*$B$60+$E50*$E$60+$H50*$H$60+$K50*$K$60+$N50*$N$60+$Q50*$Q$60)/$B$64 -> 0 | W19: 0 | X19: =V19-W19 -> 0 | AA19: lb | AB19: SUP01 | AC19: =ROUND(C243,0) -> 0 | AD19: =$B$64*1000 -> 12500000 | AE19: =AC19/AD19 -> 0 | AF19: =ROUND(AD19/$B$64,3) -> 1000 | AG19: =ROUND(W19*$AC$29,0) -> 0 | AH19: =AG19/AD19 -> 0 | AI19: =AC19-AG19 -> 0 | AJ19: =AH19*10000 -> 0
A20: Depreciation | B20: =$E$244 -> 0.01039048 | C20: 0.061012872 | D20: 0.06367052 | E20: =$E$244 -> 0.01039048 | F20: 0.051498884 | G20: 0.06367052 | I20: 0.24870656 | J20: 0.072787947 | K20: =$E$244 -> 0.01039048 | L20: 0.34045176 | M20: 0.06367052 | O20: 0 | P20: 0 | R20: 0.064182394 | S20: 0.06367052 | V20: =($B20*$B$29+$E20*$E$29+$H20*$H$29+$K20*$K$29+$N20*$N$29+$Q20*$Q$29+$B51*$B$60+$E51*$E$60+$H51*$H$60+$K51*$K$60+$N51*$N$60+$Q51*$Q$60)/$B$64 -> 0.01039048 | W20: =W24-W14-W16-W17-W18-W19-W21 -> 0 | X20: =V20-W20 -> 0.01039048 | AA20: lb | AB20: DEP01 | AC20: =ROUND(C244,0) -> 129881 | AD20: =($B$29+$E$29+$H$29+$K$29+$N$29+B60+E60+H60+K60+N60)*1000 -> 12500000 | AE20: =AC20/AD20 -> 0.01039048 | AF20: =ROUND(AD20/($B$29+$E$29+$H$29+$K$29+$N$29+B60+E60+H60+K60+N60),3) -> 1000 | AG20: =ROUND(W20*$AC$29,0) -> 0 | AH20: =AG20/AD20 -> 0 | AI20: =AC20-AG20 -> 129881 | AJ20: =AH20*10000 -> 0
A21: Insurance & Taxes | B21: =$E$245 -> 0.03763008 | C21: 0.01547789 | D21: 0.014046243 | E21: =$E$245 -> 0.03763008 | F21: 0.012959419 | G21: 0.014046243 | I21: 0.064467032 | J21: 0.018172206 | K21: =$E$245 -> 0.03763008 | L21: 0.083528141 | M21: 0.014046243 | O21: 0 | P21: 0 | R21: 0.015675972 | S21: 0.014046243 | V21: =($B21*$B$29+$E21*$E$29+$H21*$H$29+$K21*$K$29+$N21*$N$29+$Q21*$Q$29+$B52*$B$60+$E52*$E$60+$H52*$H$60+$K52*$K$60+$N52*$N$60+$Q52*$Q$60)/$B$64 -> 0.03763008 | W21: =W24-W14-W16-W17-W18-W19 -> 0 | X21: =V21-W21 -> 0.03763008 | AA21: lb | AB21: INS01 | AC21: =ROUND(C245,0) -> 470376 | AD21: =$B$64*1000 -> 12500000 | AE21: =AC21/AD21 -> 0.03763008 | AF21: =ROUND(AD21/$B$64,3) -> 1000 | AG21: =ROUND(W21*$AC$29,0) -> 0 | AH21: =AG21/AD21 -> 0 | AI21: =AC21-AG21 -> 470376 | AJ21: =AH21*10000 -> 0
A22: Total Fixed Costs | B22: =SUM(B16:B21) -> 0.10952143 | C22: =SUM(C16:C21) -> 0.10864978 | D22: 0.10327623 | E22: =SUM(E16:E21) -> 0.10952143 | F22: =SUM(F16:F21) -> 0.09686744 | G22: 0.10327623 | I22: =SUM(I16:I21) -> 0.35363588 | J22: =SUM(J16:J21) -> 0.12177482 | K22: =SUM(K16:K21) -> 0.10952143 | L22: =SUM(L16:L21) -> 0.51685181 | M22: 0.10327623 | O22: =SUM(O16:O21) -> 0 | P22: =SUM(P16:P21) -> 0 | R22: =SUM(R16:R21) -> 0.10328935 | S22: 0.10327623 | V22: =SUM(V16:V21) -> 0.10952143 | W22: =SUM(W16:W21) -> 0.028566217 | X22: =SUM(X16:X21) -> 0.080955215 | AC22: =SUM(AC16:AC21) -> 1383270 | AG22: =SUM(AG16:AG21) -> 357078 | AI22: =SUM(AI16:AI21) -> 1026192
AA23: Activity Cost | AC23: =AC14+AC22 -> 1648692 | AG23: =AG14+AG22 -> 622500 | AI23: =AI14+AI22 -> 1026192
A24: Total Cost per Pound at Gross | B24: =B14+B22 -> 0.33278611 | C24: =C14+C22 -> 0.34123726 | D24: =D14+D22 -> 0.41123685 | E24: =E14+E22 -> 0.33798622 | F24: =F14+F22 -> 0.32716511 | G24: =G14+G22 -> 0.40887539 | H24: =H14+H22 -> 0 | I24: =I14+I22 -> 0.77543605 | ... S24: =S14+S22 -> 0.43701161 | V24: =V14+V22 -> 0.41911733 | W24: =0.0498+V6+V7+V8 -> 0.33816211 | X24: =X14+X22 -> 0.080955215 | AA24: $/lb excl matl | AC24: =ROUND(AC23/AC29,5) -> 0.1319 | AG24: =ROUND(AG23/AC29,5) -> 0.0498 | AI24: =ROUND(AI23/AC29,5) -> 0.0821
A25: Less: Substrate Plant Under-absorption | B25: =-B7 -> 0 | D25: -0.02807392 | E25: =-E7 -> 0 | G25: -0.02807392 | H25: =-H7 -> 0 | J25: -0.22562455 | K25: =-K7 -> 0 | M25: -0.02886962 | N25: =-N7 -> 0 | Q25: =-Q7 -> 0 | S25: -0.027061741 | V25: 0
A26: Less: RC Under-absorption | B26: =IF(B9+B10+B11+B12+B13+B22>0.0498,0.0498-B9-B10-B11-B12-B13-B22,0) -> -0.080955215 | C26: -0.079184632 | D26: =IF(D9+D10+D11+D12+D13+D22>0.0498,0.0498-D9-D10-D11-D12-D13-D22,0) -> -0.079620814 | E26: =IF(E9+E10+E11+E12+E13+E22>0.0498,0.0498-E9-E10-E11-E12-E13-E22,0) -> -0.080955215 | F26: =IF(F9+F10+F11+F12+F13+F22>0.0498,0.0498-F9-F10-F11-F12-F13-F22,0) -> -0.064407031 | G26: =IF(G9+G10+G11+G12+G13+G22>0.0498,0.0498-G9-G10-G11-G12-G13-G22,0) -> -0.079620814 | H26: =IF(H9+H10+H11+H12+H13+H22>0.0498,0.0498-H9-H10-H11-H12-H13-H22,0) -> 0 | I26: -0.36723743 | J26: =IF(J9+J10+J11+J12+J13+J22>0.0498,0.0498-J9-J10-J11-J12-J13-J22,0) -> -0.10097661 | K26: =IF(K9+K10+K11+K12+K13+K22>0.0498,0.0498-K9-K10-K11-K12-K13-K22,0) -> -0.080955215 | L26: =IF(L9+L10+L11+L12+L13+L22>0.0498,0.0498-L9-L10-L11-L12-L13-L22,0) -> -0.54222065 | M26: =IF(M9+M10+M11+M12+M13+M22>0.0498,0.0498-M9-M10-M11-M12-M13-M22,0) -> -0.079620814 | N26: =IF(N9+N10+N11+N12+N13+N22>0.0498,0.0498-N9-N10-N11-N12-N13-N22,0) -> 0 | O26: =IF(O9+O10+O11+O12+O13+O22>0.0498,0.0498-O9-O10-O11-O12-O13-O22,0) -> 0 | P26: =IF(P9+P10+P11+P12+P13+P22>0.0498,0.0498-P9-P10-P11-P12-P13-P22,0) -> 0 | Q26: =IF(Q9+Q10+Q11+Q12+Q13+Q22>0.0498,0.0498-Q9-Q10-Q11-Q12-Q13-Q22,0) -> 0 | ... S26: =IF(S9+S10+S11+S12+S13+S22>0.0498,0.0498-S9-S10-S11-S12-S13-S22,0) -> -0.079620814 | V26: =($B26*$B$29+$E26*$E$29+$H26*$H$29+$K26*$K$29+$N26*$N$29+$Q26*$Q$29+$B57*$B$60+$E57*$E$60+$H57*$H$60+$K57*$K$60+$N57*$N$60+$Q57*$Q$60)/$B$64 -> -0.080955215
A27: Net Cost per Pound Absorbed | B27: =SUM(B24:B26) -> 0.2518309 | C27: =SUM(C24:C26) -> 0.26205262 | D27: =SUM(D24:D26) -> 0.30354212 | E27: =SUM(E24:E26) -> 0.25703101 | F27: =SUM(F24:F26) -> 0.26275808 | G27: =SUM(G24:G26) -> 0.30118066 | H27: =SUM(H24:H26) -> 0 | I27: =SUM(I24:I26) -> 0.40819862 | ... S27: =SUM(S24:S26) -> 0.33032906 | V27: =SUM(V24:V26) -> 0.33816211
AA28: $/lb incl matl | AC28: =ROUND((AC24+(B8*B29+E8*E29+H8*H29+K8*K29+N8*N29+Q8*Q29+B39*B60+E39*E60+H39*H60)/B64),5) -> 0.16185 | AG28: =ROUND(AG24+W8,5) -> 0.07975 | AI28: =ROUND(AI24+X8,5) -> 0.0821
A29: Total Production (000 lbs) | B29: =+B81 -> 3000 | C29: 15431 | D29: 10000 | E29: 0 | F29: 9412 | G29: 10000 | H29: 0 | I29: 74 | J29: 0 | K29: =+B84 -> 1200 | L29: 254 | M29: 1000 | N29: =$B$85 -> 0 | O29: 0 | P29: 0 | Q29: 0 | R29: 3647.15 | S29: 1300 | V29: =B29+E29+H29+K29+N29+Q29+B60+E60+H60+K60+N60+Q60 -> 12500 | AA29: Prod lbs | AC29: =ROUND($B$64*1000,0) -> 12500000
B34: Fusion | E34: ScaleGuard II CL | H34: KSXT | K34: ScaleGuard II KSHD (H) | N34: XX | Q34: XX
B35: =+B4 -> 21 Standard | C35: 19 Actual | D35: =+D4 -> 20 Standard | E35: =+B4 -> 21 Standard | F35: 19 Actual | G35: =+D4 -> 20 Standard | H35: =+B4 -> 21 Standard | I35: 19 Actual | J35: =+D4 -> 20 Standard | K35: =+B4 -> 21 Standard | L35: 19 Actual | M35: =+D4 -> 20 Standard | N35: =+B4 -> 21 Standard | O35: 19 Actual | P35: =+D4 -> 20 Standard | Q35: =+B4 -> 21 Standard | R35: 19 Actual | S35: =+D4 -> 20 Standard
C36: (Jan-Sept) | F36: (Jan-Sept) | I36: (Jan-Sept) | L36: (Jan-Sept)
A37: Materials - Substrate | B37: =E150 -> 0.22007722 | C37: 0.34054143 | D37: 0.19598456 | E37: =G150 -> 0.41282107 | F37: 0.4105 | G37: 0.41539541 | H37: =I150 -> 0.28800984 | I37: 0.26541432 | J37: 0.29172286 | L37: 0 | M37: 1.8829093 | O37: 0 | P37: 0 | R37: 0 | S37: 0
A38: Materials - Substrate Under-Absorption | B38: =$C136*D136 -> 0 | D38: 0.10656371 | E38: =$C134*F134 -> 0.046029189 | G38: 0.11759583 | H38: =$C131*H131 -> 0.09332723 | J38: 0.18665446 | M38: 0.16177979 | P38: 0 | S38: 0
A39: Materials - Resin & Chemicals | B39: =E151+E152 -> 0.0467607 | C39: 0.093737947 | D39: 0.086815916 | E39: =G151+G152 -> 0.04221848 | F39: 0.043894371 | G39: 0.044288616 | H39: =I151+I152 -> 0.008758525 | I39: 0.04843802 | J39: 0.10420358 | L39: 0 | M39: 0.042578635 | O39: 0 | P39: 0 | R39: 0 | S39: 0
A40: Electricity | B40: =E170 -> 0.0059095494 | C40: 0.026041382 | D40: 0.010135435 | E40: =G170 -> 0.0059095494 | F40: 0.014645894 | G40: 0.010135435 | H40: =I170 -> 0.0059095494 | I40: 0.010462455 | J40: 0.010135435 | L40: 0 | M40: 0.010135435 | O40: 0 | P40: 0 | R40: 0 | S40: 0
A41: Gas | B41: =E171 -> 0.0013242333 | C41: 0.0016828037 | D41: 0.0011247591 | E41: =G171 -> 0.0013242333 | F41: 0.0055474856 | G41: 0.0011247591 | H41: =I171 -> 0.0013242333 | I41: 0.00084305984 | J41: 0.0011247591 | L41: 0 | M41: 0.0011247591 | O41: 0 | P41: 0 | R41: 0 | S41: 0
A42: R&M Supplies and Service | B42: =$H$179 -> 0.006 | C42: 0.019710326 | D42: 0.0086705202 | E42: =$H$179 -> 0.006 | F42: 0.012018642 | G42: 0.0086705202 | H42: =$H$179 -> 0.006 | I42: 0.0073389729 | J42: 0.0086705202 | L42: 0 | M42: 0.0086705202 | O42: 0 | P42: 0 | R42: 0 | S42: 0
A43: Manufacturing Supplies | B43: =$H$182 -> 0.002 | C43: 0.0024000594 | D43: 0.00043352601 | E43: =$H$182 -> 0.002 | F43: 0.0007808962 | G43: 0.00043352601 | H43: =$H$182 -> 0.002 | I43: 0.00063205421 | J43: 0.00043352601 | L43: 0 | M43: 0.00043352601 | O43: 0 | P43: 0 | R43: 0 | S43: 0
A44: Other variable | B44: =$H$185 -> 0.006 | C44: 0.026652312 | D44: 0.0057803468 | E44: =$H$185 -> 0.006 | F44: 0.026473851 | G44: 0.0057803468 | H44: =$H$185 -> 0.006 | I44: 0.0094086246 | J44: 0.0057803468 | L44: 0 | M44: 0.0057803468 | O44: 0 | P44: 0 | R44: 0 | S44: 0
A45: Total Variable Costs | B45: =SUM(B37:B44) -> 0.2880717 | C45: =SUM(C37:C44) -> 0.51076626 | D45: 0.41550877 | E45: =SUM(E37:E44) -> 0.52230252 | F45: =SUM(F37:F44) -> 0.51386114 | G45: 0.60342444 | H45: =SUM(H37:H44) -> 0.41132937 | I45: =SUM(I37:I44) -> 0.34253751 | J45: 0.60872548 | L45: =SUM(L37:L44) -> 0 | M45: 2.1134123 | O45: =SUM(O37:O44) -> 0 | P45: =SUM(P37:P44) -> 0 | R45: =SUM(R37:R44) -> 0 | S45: =SUM(S37:S44) -> 0
A47: Production Labor | B47: =$D$216/$B$64/1000 -> 0.035940795 | C47: 0.02099802 | D47: 0.011741675 | E47: =$D$216/$B$64/1000 -> 0.035940795 | F47: 0.020095412 | G47: 0.011741675 | H47: =$D$216/$B$64/1000 -> 0.035940795 | I47: 0.017675634 | J47: 0.011741675 | L47: 0 | M47: 0.011741675 | O47: 0 | P47: 0 | R47: 0 | S47: 0
A48: Repairs & Maintenance Labor | B48: =$G$216/$B$64/1000 -> 0.0113712 | C48: 0.010055044 | D48: 0.0041080925 | E48: =$G$216/$B$64/1000 -> 0.0113712 | F48: 0.0031155542 | G48: 0.0041080925 | H48: =$G$216/$B$64/1000 -> 0.0113712 | I48: 0.0047406695 | J48: 0.0041080925 | L48: 0 | M48: 0.0041080925 | O48: 0 | P48: 0 | R48: 0 | S48: 0
A49: Indirect Payroll Costs (Benefits) | B49: =$J$216/$B$64/1000 -> 0.014188877 | C49: 0.020373428 | D49: 0.0072598437 | E49: =$J$216/$B$64/1000 -> 0.014188877 | F49: 0.01913635 | G49: 0.0072598437 | H49: =$J$216/$B$64/1000 -> 0.014188877 | I49: 0.0076540782 | J49: 0.0072598437 | L49: 0 | M49: 0.0072598437 | O49: 0 | P49: 0 | R49: 0 | S49: 0
A50: Supervision | B50: =$E$243 -> 0 | C50: 0.0068127908 | D50: 0.002449852 | E50: =$E$243 -> 0 | F50: 0.0082982662 | G50: 0.002449852 | H50: =$E$243 -> 0 | I50: 0.0028565151 | J50: 0.002449852 | L50: 0 | M50: 0.002449852 | O50: 0 | P50: 0 | R50: 0 | S50: 0
A51: Depreciation | B51: =$E$244 -> 0.01039048 | C51: 0.18195763 | D51: 0.06367052 | E51: =$E$244 -> 0.01039048 | F51: 0.22264847 | G51: 0.06367052 | H51: =$E$244 -> 0.01039048 | I51: 0.07640353 | J51: 0.06367052 | L51: 0 | M51: 0.06367052 | O51: 0 | P51: 0 | R51: 0 | S51: 0
A52: Insurance & Taxes | B52: =$E$245 -> 0.03763008 | C52: 0.045121869 | D52: 0.014046243 | E52: =$E$245 -> 0.03763008 | F52: 0.064601784 | G52: 0.014046243 | H52: =$E$245 -> 0.03763008 | I52: 0.019244874 | J52: 0.014046243 | L52: 0 | M52: 0.014046243 | O52: 0 | P52: 0 | R52: 0 | S52: 0
A53: Total Fixed Costs | B53: =SUM(B47:B52) -> 0.10952143 | C53: =SUM(C47:C52) -> 0.28531878 | D53: 0.10327623 | E53: =SUM(E47:E52) -> 0.10952143 | F53: =SUM(F47:F52) -> 0.33789584 | G53: 0.10327623 | H53: =SUM(H47:H52) -> 0.10952143 | I53: =SUM(I47:I52) -> 0.1285753 | J53: 0.10327623 | L53: =SUM(L47:L52) -> 0 | M53: 0.10327623 | O53: =SUM(O47:O52) -> 0 | P53: =SUM(P47:P52) -> 0 | R53: =SUM(R47:R52) -> 0 | S53: =SUM(S47:S52) -> 0
A55: Total Cost per Pound at Gross | B55: =B45+B53 -> 0.39759313 | C55: =C45+C53 -> 0.79608504 | D55: =D45+D53 -> 0.51878499 | E55: =E45+E53 -> 0.63182396 | F55: =F45+F53 -> 0.85175698 | G55: =G45+G53 -> 0.70670067 | H55: =H45+H53 -> 0.52085081 | I55: =I45+I53 -> 0.47111281 | ... S55: =S45+S53 -> 0
A56: Less: Substrate Plant Under-absorption | B56: =-B38 -> 0 | C56: =-C38 -> 0 | D56: -0.14908529 | E56: =-E38 -> -0.046029189 | G56: -0.034805886 | H56: =-H38 -> -0.09332723 | K56: =-K38 -> 0 | M56: -0.0074705959 | N56: =-N38 -> 0 | P56: 0 | Q56: =-Q38 -> 0
A57: Less: RC Under-absorption | B57: =IF(B40+B41+B42+B43+B44+B53>0.0498,0.0498-B40-B41-B42-B43-B44-B53,0) -> -0.080955215 | C57: -0.31205821 | D57: =IF(D40+D41+D42+D43+D44+D53>0.0498,0.0498-D40-D41-D42-D43-D44-D53,0) -> -0.079620814 | E57: =IF(E40+E41+E42+E43+E44+E53>0.0498,0.0498-E40-E41-E42-E43-E44-E53,0) -> -0.080955215 | F57: =IF(F40+F41+F42+F43+F44+F53>0.0498,0.0498-F40-F41-F42-F43-F44-F53,0) -> -0.34756261 | G57: =IF(G40+G41+G42+G43+G44+G53>0.0498,0.0498-G40-G41-G42-G43-G44-G53,0) -> -0.079620814 | H57: =IF(H40+H41+H42+H43+H44+H53>0.0498,0.0498-H40-H41-H42-H43-H44-H53,0) -> -0.080955215 | I57: =IF(I40+I41+I42+I43+I44+I53>0.0498,0.0498-I40-I41-I42-I43-I44-I53,0) -> -0.10746047 | J57: =IF(J40+J41+J42+J43+J44+J53>0.0498,0.0498-J40-J41-J42-J43-J44-J53,0) -> -0.079620814 | K57: =IF(K40+K41+K42+K43+K44+K53>0.0498,0.0498-K40-K41-K42-K43-K44-K53,0) -> 0 | ... N57: =IF(N40+N41+N42+N43+N44+N53>0.0498,0.0498-N40-N41-N42-N43-N44-N53,0) -> 0 | O57: 0 | P57: =IF(P40+P41+P42+P43+P44+P53>0.0498,0.0498-P40-P41-P42-P43-P44-P53,0) -> 0 | Q57: =IF(Q40+Q41+Q42+Q43+Q44+Q53>0.0498,0.0498-Q40-Q41-Q42-Q43-Q44-Q53,0) -> 0 | R57: 0 | S57: =IF(S40+S41+S42+S43+S44+S53>0.0498,0.0498-S40-S41-S42-S43-S44-S53,0) -> 0
A58: Net Cost per Pound Absorbed | B58: =SUM(B55:B57) -> 0.31663792 | C58: =SUM(C55:C57) -> 0.48402683 | D58: =SUM(D55:D57) -> 0.29007889 | E58: =SUM(E55:E57) -> 0.50483955 | F58: =SUM(F55:F57) -> 0.50419437 | G58: =SUM(G55:G57) -> 0.59227397 | H58: =SUM(H55:H57) -> 0.34656836 | I58: =SUM(I55:I57) -> 0.36365234 | ... S58: =SUM(S55:S57) -> 0
A60: Total Production (000 lbs) | B60: =+B87 -> 1100 | C60: 101 | D60: 1300 | E60: =+B88 -> 1700 | F60: 979 | G60: 3900 | H60: =+B92 -> 5500 | I60: 2743 | J60: 7000 | K60: =+B90 -> 0 | L60: 0 | M60: 100 | N60: 0 | O60: 0 | P60: 0 | Q60: 0 | R60: 0 | S60: 0
A64: Total Plant Production (000 lbs) | B64: =B29+E29+H29+K29+N29+Q29+B60+E60+H60+K60+N60+Q60 -> 12500 | C64: =C29+F29+I29+L29+O29+R29+C60+F60+I60+L60+O60+R60 -> 32641.15 | D64: =D29+G29+J29+M29+P29+S29+D60+G60+J60+M60+P60+S60 -> 34600
V65: 2078820 | W65: 2289955 | AC65: 1.102 | AD65: 0.099 | AE65: =+AC65-AD65 -> 1.003
V66: 22566 | W66: 22313 | AC66: 0.989 | AD66: 0 | AE66: =+AC66-AD66 -> 0.989
B67: Total | C67: Variable | D67: Fixed | V67: 469400 | W67: 521591 | AC67: 1.111 | AD67: 0.07 | AE67: =+AC67-AD67 -> 1.041
A68: Cost Summary: | B68: ($ in 000s) | V68: 514675 | W68: 642354 | AC68: 1.248 | AD68: 0.015 | AE68: =+AC68-AD68 -> 1.233
A69: Absorbed by Production | B69: =SUM(C69:D69) -> 4227.0264 | C69: =W14*$V$29 -> 3869.9487 | D69: =W22*$V$29 -> 357.07772 | V69: 62400 | W69: 68640 | AC69: 1.1 | AD69: 0.158 | AE69: =+AC69-AD69 -> 0.942
A70: Underabsorption Expensed | B70: =SUM(C70:D70) -> 1011.9402 | C70: =X14*$V$29 -> 0 | D70: =X22*$V$29 -> 1011.9402 | V70: 22275 | W70: 27844 | AC70: 1.25 | AD70: 0 | AE70: =+AC70-AD70 -> 1.25
A71: Loss on Excess Gas Net Settled | B71: =SUM(C71:D71) -> 0 | C71: 0 | D71: 0 | V71: 10980 | W71: 13725 | AC71: 1.25 | AD71: 0 | AE71: =+AC71-AD71 -> 1.25
A72: Total Cost | B72: =SUM(B69:B71) -> 5238.9666 | C72: =SUM(C69:C71) -> 3869.9487 | D72: =SUM(D69:D71) -> 1369.0179 | AE72: =AVERAGE(AE65:AE71) -> 1.1011429
A73: Less: Non-Cash | B73: =SUM(C73:D73) -> -129.881 | C73: 0 | D73: =-V20*V29 -> -129.881 | V73: =SUM(V65:V72) -> 3181116 | W73: =SUM(W65:W72) -> 3586422
A74: Cash Cost | B74: =SUM(B72:B73) -> 5109.0856 | C74: =SUM(C72:C73) -> 3869.9487 | D74: =SUM(D72:D73) -> 1239.1369 | V74: 3233726 | W74: 1569174 | X74: =+W74/V74 -> 0.48525262
V75: =+V73-V74 -> -52610 | W75: =+W73-W74 -> 2017248
B79: Quantity | C79: Rate
A80: Production Plan | B80: (000 lbs) | C80: (000 lbs/day) | D80: Prodn Days | E80: % Split
A81: CB Lite | B81: 3000 | C81: 350 | D81: =IF(C81<>0,B81/C81,0) -> 8.5714286 | E81: =IF($D$93<>0,D81/$D$93,0) -> 0.24
A82: CB HSP | B82: 0 | C82: =350 -> 350 | D82: =IF(C82<>0,B82/C82,0) -> 0 | E82: =IF($D$93<>0,D82/$D$93,0) -> 0
A83: CB KSLD | B83: 0 | C83: =350 -> 350 | D83: =IF(C83<>0,B83/C83,0) -> 0 | E83: =IF($D$93<>0,D83/$D$93,0) -> 0
A84: RPM Lite / NP LWC | B84: 1200 | C84: =350 -> 350 | D84: =IF(C84<>0,B84/C84,0) -> 3.4285714 | E84: =IF($D$93<>0,D84/$D$93,0) -> 0.096
A85: RPM CP / NP ISP | B85: 0 | C85: =350 -> 350 | D85: =IF(C85<>0,B85/C85,0) -> 0 | E85: =IF($D$93<>0,D85/$D$93,0) -> 0
A86: Air | B86: 0 | C86: =350 -> 350 | D86: =IF(C86<>0,B86/C86,0) -> 0 | E86: =IF($D$93<>0,D86/$D$93,0) -> 0
A87: Fusion (#998, 999, 1025) | B87: 1100 | C87: =350 -> 350 | D87: =IF(C87<>0,B87/C87,0) -> 3.1428571 | E87: =IF($D$93<>0,D87/$D$93,0) -> 0.088
A88: SG II CL | B88: 1700 | C88: =350 -> 350 | D88: =IF(C88<>0,B88/C88,0) -> 4.8571429 | E88: =IF($D$93<>0,D88/$D$93,0) -> 0.136
A89: SG II Ultra CL | B89: 0 | C89: =350 -> 350 | D89: =IF(C89<>0,B89/C89,0) -> 0 | E89: =IF($D$93<>0,D89/$D$93,0) -> 0
A90: SG II KSHD (H) | B90: 0 | C90: =350 -> 350 | D90: =IF(C90<>0,B90/C90,0) -> 0 | E90: =IF($D$93<>0,D90/$D$93,0) -> 0
A91: SaltGuard (FDP-806) | B91: 0 | C91: =350 -> 350 | D91: =IF(C91<>0,B91/C91,0) -> 0 | E91: =IF($D$93<>0,D91/$D$93,0) -> 0
A92: KSXT | B92: 5500 | C92: =350 -> 350 | D92: =IF(C92<>0,B92/C92,0) -> 15.714286 | E92: =IF($D$93<>0,D92/$D$93,0) -> 0.44
A93: Total | B93: =SUM(B81:B92) -> 12500 | C93: =B93/D93 -> 350 | D93: =SUM(D81:D92) -> 35.714286 | E93: =IF($D$93<>0,D93/$D$93,0) -> 1
A96: Variable Costs - Material
D98: CB Lite | F98: CB Lite EU | H98: CB KSLD | J98: RPM Lite / NP LWC | L98: XX | N98: Air | AF98: CBL | AH98: CBL (EU) | AJ98: RPM | AL98: AIR
A99: Materials Cost: | B99: Price ($/lb) | C99: Source plant under-absorb | D99: BOM Use/lb | E99: Standard Cost | F99: BOM Use/lb | G99: Standard Cost | H99: BOM Use/lb | I99: Standard Cost | J99: BOM Use/lb | K99: Standard Cost | L99: BOM Use/lb | M99: Standard Cost | N99: BOM Use/lb | O99: Standard Cost | AB99: material | AE99: plan price 1 | AF99: cost BOM | AG99: plan price 1 | AH99: cost BOM | AI99: plan price 1 | AJ99: cost BOM | AK99: plan price 1 | AL99: cost BOM
A100: CARBO LITE (32, 36, 115) | B100: =0.138+0.032-C100 -> 0.17 | C100: 0 | D100: 0.96442882 | E100: =$B100*D100 -> 0.1639529 | F100: 0.93946805 | G100: =$B100*F100 -> 0.15970957 | H100: 0 | I100: =$B100*H100 -> 0 | J100: 1.0310579 | K100: =$B100*J100 -> 0.17527984 | L100: 0 | M100: =$B100*L100 -> 0 | N100: 0 | O100: =$B100*N100 -> 0 | AB100: CL | AE100: =B100*1000 -> 170 | AF100: =E100/B100*1000 -> 964.42882 | AH100: =G100/B100*1000 -> 939.46805 | AJ100: =K100/B100*1000 -> 1031.0579
A101: CARBOAIR UL (861, 938) | B101: =0.138+0.032-C101 -> 0.17 | C101: 0 | D101: 0 | E101: =$B101*D101 -> 0 | F101: 0 | G101: =$B101*F101 -> 0 | H101: 0 | I101: =$B101*H101 -> 0 | J101: 0 | K101: =$B101*J101 -> 0 | L101: 0 | M101: =$B101*L101 -> 0 | N101: 0.96649076 | O101: =$B101*N101 -> 0.16430343 | AL101: =O101/B101*1000 -> 966.49076
A102: KRYPTOSPHERE LD (976) | B102: =0.348+0.032-C102 -> 0.287 | C102: 0.093 | D102: 0 | E102: =$B102*D102 -> 0 | F102: 0 | G102: =$B102*F102 -> 0 | H102: 0 | I102: =$B102*H102 -> 0 | J102: 0 | K102: =$B102*J102 -> 0 | L102: 0 | M102: =$B102*L102 -> 0 | N102: 0 | O102: =$B102*N102 -> 0
A103: CARBO HSP (19) | B103: =0.205+0.032-C103 -> 0.237 | C103: 0 | D103: 0 | E103: =$B103*D103 -> 0 | F103: 0 | G103: =$B103*F103 -> 0 | H103: 0 | I103: =$B103*H103 -> 0 | J103: 0 | K103: =$B103*J103 -> 0 | L103: 0 | M103: =$B103*L103 -> 0 | N103: 0 | O103: =$B103*N103 -> 0
A104: CARBOPROP (50) | B104: 0 | C104: 0 | D104: 0 | E104: =$B104*D104 -> 0 | F104: 0 | G104: =$B104*F104 -> 0 | H104: 0 | I104: =$B104*H104 -> 0 | J104: 0 | K104: =$B104*J104 -> 0 | L104: 0 | M104: =$B104*L104 -> 0 | N104: 0 | O104: =$B104*N104 -> 0
A105: SCALEGUARD I CL (812, 951) | B105: =0.4456-C105 -> 0.4009 | C105: =0.0447+0 -> 0.0447 | D105: 0 | E105: =$B105*D105 -> 0 | F105: 0 | G105: =$B105*F105 -> 0 | H105: 0 | I105: =$B105*H105 -> 0 | J105: 0 | K105: =$B105*J105 -> 0 | L105: 0 | M105: =$B105*L105 -> 0 | N105: 0 | O105: =$B105*N105 -> 0
A106: SCALEGUARD I KSHD (H) | B106: =1.9036-C106 -> 1.74 | C106: =0.0552+0.1084 -> 0.1636 | D106: 0 | E106: =$B106*D106 -> 0 | F106: 0 | G106: =$B106*F106 -> 0 | H106: 0 | I106: =$B106*H106 -> 0 | J106: 0 | K106: =$B106*J106 -> 0 | L106: 0 | M106: =$B106*L106 -> 0 | N106: 0 | O106: =$B106*N106 -> 0
A107: CL FUSION SUBSTRATE (994) | B107: =0.138+0.032-C107+0.02 -> 0.19 | C107: 0 | D107: 0 | E107: =$B107*D107 -> 0 | F107: 0 | G107: =$B107*F107 -> 0 | H107: 0 | I107: =$B107*H107 -> 0 | J107: 0 | K107: =$B107*J107 -> 0 | L107: 0 | M107: =$B107*L107 -> 0 | N107: 0 | O107: =$B107*N107 -> 0
A108: Plenco Resin (30090) | B108: =1094.68/1000 -> 1.09468 | C108: 0 | D108: 0 | E108: =$B108*D108 -> 0 | F108: 0 | G108: =$B108*F108 -> 0 | H108: 0 | I108: =$B108*H108 -> 0 | J108: 0 | K108: =$B108*J108 -> 0 | L108: 0 | M108: =$B108*L108 -> 0 | N108: 0.040703571 | O108: =$B108*N108 -> 0.044557385 | AB108: 30090 | AE108: =B108*1000 -> 1094.68 | AF108: =E108/B108*1000 -> 0 | AL108: =O108/B108*1000 -> 40.703571
A109: Bimex Resin-EU (30120) | B109: 1.06 | C109: 0 | D109: 0.0317 | E109: =$B109*D109 -> 0.033602 | F109: 0.035855511 | G109: =$B109*F109 -> 0.038006842 | H109: 0 | I109: =$B109*H109 -> 0 | J109: 0 | K109: =$B109*J109 -> 0 | L109: 0 | M109: =$B109*L109 -> 0 | N109: 0 | O109: =$B109*N109 -> 0 | AB109: 30120 | AE109: =B109*1000 -> 1060 | AF109: =E109/B109*1000 -> 31.7 | AH109: =G109/B109*1000 -> 35.855511
A110: HEXA-EU (30362) | B110: 0.9 | C110: 0 | D110: 0.0044 | E110: =$B110*D110 -> 0.00396 | F110: 0.0047245684 | G110: =$B110*F110 -> 0.0042521116 | H110: 0 | I110: =$B110*H110 -> 0 | J110: 0 | K110: =$B110*J110 -> 0 | L110: 0 | M110: =$B110*L110 -> 0 | N110: 0 | O110: =$B110*N110 -> 0 | AB110: 30362 | AE110: =B110*1000 -> 900 | AF110: =E110/B110*1000 -> 4.4 | AH110: =G110/B110*1000 -> 4.7245684
A111: Silane-EU (30360) | B111: 4.83 | C111: 0 | D111: 0 | E111: =$B111*D111 -> 0 | F111: 0.00095981301 | G111: =$B111*F111 -> 0.0046358969 | H111: 0 | I111: =$B111*H111 -> 0 | J111: 0 | K111: =$B111*J111 -> 0 | L111: 0 | M111: =$B111*L111 -> 0 | N111: 8.2256008e-06 | O111: =$B111*N111 -> 3.9729652e-05 | AB111: 30360 | AH111: =G111/B111*1000 -> 0.95981301 | AL111: =O111/B111*1000 -> 0.0082256008
A112: Surfactant-EU (30361) | B112: 0.88 | C112: 0 | D112: 0 | E112: =$B112*D112 -> 0 | F112: 0.00071203187 | G112: =$B112*F112 -> 0.00062658805 | H112: 0 | I112: =$B112*H112 -> 0 | J112: 0 | K112: =$B112*J112 -> 0 | L112: 0 | M112: =$B112*L112 -> 0 | N112: 3.1805656e-05 | O112: =$B112*N112 -> 2.7988978e-05 | AB112: 30361 | AH112: =G112/B112*1000 -> 0.71203187 | AL112: =O112/B112*1000 -> 0.031805656
A113: Surfactant (30054) | B113: 1.29 | C113: 0 | D113: 0.0004 | E113: =$B113*D113 -> 0.000516 | F113: 0 | G113: =$B113*F113 -> 0 | H113: 0 | I113: =$B113*H113 -> 0 | J113: 0 | K113: =$B113*J113 -> 0 | L113: 0 | M113: =$B113*L113 -> 0 | N113: 0.0015403808 | O113: =$B113*N113 -> 0.0019870913 | AB113: 30054 | AE113: =B113*1000 -> 1290 | AF113: =E113/B113*1000 -> 0.4 | AL113: =O113/B113*1000 -> 1.5403808
A114: Hexamine (30055) | B114: 1 | C114: 0 | D114: 0 | E114: =$B114*D114 -> 0 | F114: 0 | G114: =$B114*F114 -> 0 | H114: 0 | I114: =$B114*H114 -> 0 | J114: 0 | K114: =$B114*J114 -> 0 | L114: 0 | M114: =$B114*L114 -> 0 | N114: 0.0053356402 | O114: =$B114*N114 -> 0.0053356402 | AB114: 30055 | AE114: =B114*1000 -> 1000 | AF114: =E114/B114*1000 -> 0 | AL114: =O114/B114*1000 -> 5.3356402
A115: Silane (30058) | B115: 3.94 | C115: 0 | D115: 0 | E115: =$B115*D115 -> 0 | F115: 0 | G115: =$B115*F115 -> 0 | H115: 0 | I115: =$B115*H115 -> 0 | J115: 0 | K115: =$B115*J115 -> 0 | L115: 0 | M115: =$B115*L115 -> 0 | N115: 0.0010131198 | O115: =$B115*N115 -> 0.0039916921 | AB115: 30058 | AE115: =B115*1000 -> 3940 | AF115: =E115/B115*1000 -> 0 | AL115: =O115/B115*1000 -> 1.0131198
A116: WB Concentrate (30454) | B116: =13699.7/1000 -> 13.6997 | C116: 0 | D116: 0 | E116: =$B116*D116 -> 0 | F116: 0 | G116: =$B116*F116 -> 0 | H116: 0 | I116: =$B116*H116 -> 0 | J116: 0 | K116: =$B116*J116 -> 0 | L116: 0 | M116: =$B116*L116 -> 0 | N116: 0 | O116: =$B116*N116 -> 0 | AB116: 30454 | AJ116: =K116/B116*1000 -> 0
A117: PST100 (30116) | B117: =9485.36/1000 -> 9.48536 | J117: 0.0078 | K117: =$B117*J117 -> 0.073985808
...

Sheet NI RC 2020 Std
A1: New Iberia Resin Coating | AB1: Activity | AC1: 10001005 | AD1: 10001005 | AE1: Gross | AF1: Qty/1000 | AG1: 10001005 | AH1: Absorbed | AI1: 10001005 | AJ1: Abs Cost
A2: 2020 STANDARDS | AA2: Unit | AB2: Type | AC2: Total Cost | AD2: Total Qty | AE2: Unit Cost | AF2: Prod lbs | AG2: Absorption | AH2: Unit Cost | AI2: Underabs | AJ2: per 10000
B3: CARBOBond Lite | E3: CARBOBond Lite EU | H3: CARBOBond KSLD | K3: RPM LITE / NEUTRAPROP LWC | N3: XX | Q3: CARBO AIR
B4: 20 Standard | C4: 19 Actual | D4: 19 Standard | E4: =+B4 -> 20 Standard | F4: 19 Actual | G4: =+D4 -> 19 Standard | H4: =+B4 -> 20 Standard | I4: =+C4 -> 19 Actual | J4: =+D4 -> 19 Standard | K4: =+B4 -> 20 Standard | L4: 18 Actual | M4: =+D4 -> 19 Standard | N4: =+B4 -> 20 Standard | O4: 19 Actual | P4: =+D4 -> 19 Standard | Q4: =+B4 -> 20 Standard | R4: 18 Actual | S4: =+D4 -> 19 Standard | V4: Composite | W4: Absorb | X4: Underabsorb
C5: (Jan-Sept) | F5: (Jan-Sept) | I5: =+C5 -> (Jan-Sept) | L5: (Jan-Nov) | R5: (Jan-Oct)
A6: Materials - Substrate | B6: =E120 -> 0.14369989 | C6: 0.16092998 | D6: 0.17245408 | E6: =G120 -> 0.13998074 | F6: 0.15896741 | G6: 0.17245408 | H6: =I120 -> 0 | I6: 0.30191317 | J6: 0.28067655 | K6: =K120 -> 0.15362762 | L6: 0.18307969 | M6: 0.17734195 | N6: =M120 -> 0 | O6: 0 | P6: 0 | Q6: =O120 -> 0.14400712 | R6: 0.15968841 | S6: 0.16623641 | V6: =($B6*$B$29+$E6*$E$29+$H6*$H$29+$K6*$K$29+$N6*$N$29+$Q6*$Q$29+$B37*$B$60+$E37*$E$60+$H37*$H$60+$K37*$K$60+$N37*$N$60+$Q37*$Q$60)/$B$64 -> 0.21048602 | W6: =V6 -> 0.21048602
A7: Materials - Substrate Under-Absorption | B7: =$C100*D100 -> 0.088727451 | D7: 0.02807392 | E7: =$C100*F100 -> 0.08643106 | G7: 0.02807392 | H7: =C102*H102 -> 0 | J7: 0.22562455 | K7: =$C100*J100 -> 0.094857323 | M7: 0.02886962 | N7: =C104*L104 -> 0 | P7: 0 | Q7: =$C101*N101 -> 0.08891715 | S7: 0.027061741 | V7: 0 | W7: 0
A8: Materials - Resin & Chemicals | B8: =E121+E122 -> 0.049388695 | C8: 0.051903794 | D8: 0.05510658 | E8: =G121+G122 -> 0.053042779 | F8: 0.053990671 | G8: 0.05510658 | H8: =I121+I122 -> 0 | I8: 0.05384576 | J8: 0.0471079 | K8: =K121+K122 -> 0.15903358 | L8: 0.071924563 | M8: 0.0979032 | N8: =M121+M122 -> 0 | O8: 0 | P8: 0 | Q8: =O121+O122 -> 0.074666525 | R8: 0.072759577 | S8: 0.078307486 | V8: =($B8*$B$29+$E8*$E$29+$H8*$H$29+$K8*$K$29+$N8*$N$29+$Q8*$Q$29+$B39*$B$60+$E39*$E$60+$H39*$H$60+$K39*$K$60+$N39*$N$60+$Q39*$Q$60)/$B$64 -> 0.066464855 | W8: =V8 -> 0.066464855 | X8: =V8-W8 -> 0
A9: Electricity | B9: =E161 -> 0.010135435 | C9: 0.0077075348 | D9: 0.010726 | E9: =G161 -> 0.010135435 | F9: 0.0064153677 | G9: 0.010726 | H9: =I161 -> 0.010135435 | I9: 0.023850562 | J9: 0.010726 | K9: =K161 -> 0.010135435 | L9: 0.019218863 | M9: 0.010726 | N9: =M161 -> 0.010135435 | O9: 0 | P9: 0 | Q9: =O161 -> 0.010135435 | R9: 0.006525594 | S9: 0.010726 | V9: =($B9*$B$29+$E9*$E$29+$H9*$H$29+$K9*$K$29+$N9*$N$29+$Q9*$Q$29+$B40*$B$60+$E40*$E$60+$H40*$H$60+$K40*$K$60+$N40*$N$60+$Q40*$Q$60)/$B$64 -> 0.010135435 | W9: =V9 -> 0.010135435 | X9: =V9-W9 -> 0 | AA9: kwh | AB9: ELE01 | AC9: =ROUND(((D161*B$29*1000)+(F161*E$29*1000)+(H161*H$29*1000)+(J161*K$29*1000)+(L161*N$29*1000)+(N161*Q$29*1000)+(D168*B$60*1000)+(F168*E$60*1000)+(H168*H$60*1000)+(J168*K$60*1000)+(L168*N$60*1000)+(N168*Q$60*1000))*$B161,0) -> 350686 | AD9: =ROUND((D161*B$29*1000)+(F161*E$29*1000)+(H161*H$29*1000)+(J161*K$29*1000)+(L161*N$29*1000)+(N161*Q$29*1000)+(D168*B$60*1000)+(F168*E$60*1000)+(H168*H$60*1000)+(J168*K$60*1000)+(L168*N$60*1000)+(N168*Q$60*1000),0) -> 2040058 | AE9: =AC9/AD9 -> 0.17190001 | AF9: =ROUND(AD9/$B$64,3) -> 58.961 | AG9: =ROUND(W9*$AC$29,0) -> 350686 | AH9: =AG9/AD9 -> 0.17190001 | AI9: =AC9-AG9 -> 0 | AJ9: =AH9*10000 -> 1719.0001
A10: Gas | B10: =E162 -> 0.0011247591 | C10: 0.00096524487 | D10: 0.00126 | E10: =G162 -> 0.0011247591 | F10: 0.00088623983 | G10: 0.00126 | H10: =I162 -> 0.0011247591 | I10: 0.0011573683 | J10: 0.00126 | K10: =K162 -> 0.0011247591 | L10: 0.0011031846 | M10: 0.00126 | N10: =M162 -> 0.0011247591 | O10: 0 | P10: 0 | Q10: =O162 -> 0.0011247591 | R10: 0.0011625955 | S10: 0.00126 | V10: =($B10*$B$29+$E10*$E$29+$H10*$H$29+$K10*$K$29+$N10*$N$29+$Q10*$Q$29+$B41*$B$60+$E41*$E$60+$H41*$H$60+$K41*$K$60+$N41*$N$60+$Q41*$Q$60)/$B$64 -> 0.0011247591 | W10: =V10 -> 0.0011247591 | X10: =V10-W10 -> 0 | AA10: mbtu | AB10: GAS01 | AC10: =ROUND(((D162*B$29*1000)+(F162*E$29*1000)+(H162*H$29*1000)+(J162*K$29*1000)+(L162*N$29*1000)+(N162*Q$29*1000)+(D169*B$60*1000)+(F169*E$60*1000)+(H169*H$60*1000)+(J169*K$60*1000)+(L169*N$60*1000)+(N169*Q$60*1000))*$B162,0) -> 38917 | AD10: =ROUND(((D162*B$29*1000)+(F162*E$29*1000)+(H162*H$29*1000)+(J162*K$29*1000)+(L162*N$29*1000)+(N162*Q$29*1000)+(D169*B$60*1000)+(F169*E$60*1000)+(H169*H$60*1000)+(J169*K$60*1000)+(L169*N$60*1000)+(N169*Q$60*1000))*1000,0) -> 11280193 | AE10: =AC10/AD10 -> 0.0034500296 | AF10: =ROUND(AD10/$B$64,3) -> 326.017 | AG10: =ROUND(W10*$AC$29,0) -> 38917 | AH10: =AG10/AD10 -> 0.0034500296 | AI10: =AC10-AG10 -> 0 | AJ10: =AH10*10000 -> 34.500296
A11: R&M Supplies and Service | B11: =$H$177 -> 0.0086705202 | C11: 0.0052601959 | D11: 0.0099121126 | E11: =$H$177 -> 0.0086705202 | F11: 0.0051242876 | G11: 0.0099121126 | H11: =$H$177 -> 0.0086705202 | I11: 0.023215913 | J11: 0.0099121126 | K11: =$H$177 -> 0.0086705202 | L11: 0.026688594 | M11: 0.0099121126 | N11: =$H$177 -> 0.0086705202 | O11: 0 | P11: 0 | Q11: =$H$177 -> 0.0086705202 | R11: 0.016241103 | S11: 0.0099121126 | V11: =($B11*$B$29+$E11*$E$29+$H11*$H$29+$K11*$K$29+$N11*$N$29+$Q11*$Q$29+$B42*$B$60+$E42*$E$60+$H42*$H$60+$K42*$K$60+$N42*$N$60+$Q42*$Q$60)/$B$64 -> 0.0086705202 | W11: =V11 -> 0.0086705202 | X11: =V11-W11 -> 0 | AA11: lb | AB11: RMS01 | AC11: =ROUND(G177,0) -> 300000 | AD11: =$B$64*1000 -> 34600000 | AE11: =AC11/AD11 -> 0.0086705202 | AF11: =ROUND(AD11/$B$64,3) -> 1000 | AG11: =ROUND(W11*$AC$29,0) -> 300000 | AH11: =AG11/AD11 -> 0.0086705202 | AI11: =AC11-AG11 -> 0 | AJ11: =AH11*10000 -> 86.705202
A12: Manufacturing Supplies | B12: =$H$180 -> 0.00043352601 | C12: 0.00028145605 | D12: 0.00049560563 | E12: =$H$180 -> 0.00043352601 | F12: 0.0001613237 | G12: 0.00049560563 | H12: =$H$180 -> 0.00043352601 | I12: 0.00076914757 | J12: 0.00049560563 | K12: =$H$180 -> 0.00043352601 | L12: 0.0013365915 | M12: 0.00049560563 | N12: =$H$180 -> 0.00043352601 | O12: 0 | P12: 0 | Q12: =$H$180 -> 0.00043352601 | R12: 0.00053366327 | S12: 0.00049560563 | V12: =($B12*$B$29+$E12*$E$29+$H12*$H$29+$K12*$K$29+$N12*$N$29+$Q12*$Q$29+$B43*$B$60+$E43*$E$60+$H43*$H$60+$K43*$K$60+$N43*$N$60+$Q43*$Q$60)/$B$64 -> 0.00043352601 | W12: =V12 -> 0.00043352601 | X12: =V12-W12 -> 0 | AA12: lb | AB12: MFG01 | AC12: =ROUND(G180,0) -> 15000 | AD12: =$B$64*1000 -> 34600000 | AE12: =AC12/AD12 -> 0.00043352601 | AF12: =ROUND(AD12/$B$64,3) -> 1000 | AG12: =ROUND(W12*$AC$29,0) -> 15000 | AH12: =AG12/AD12 -> 0.00043352601 | AI12: =AC12-AG12 -> 0 | AJ12: =AH12*10000 -> 4.3352601
A13: Other variable | B13: =$H$183 -> 0.0057803468 | C13: 0.005539271 | D13: 0.0066080751 | E13: =$H$183 -> 0.0057803468 | F13: 0.0047523717 | G13: 0.0066080751 | H13: =$H$183 -> 0.0057803468 | I13: 0.017048253 | J13: 0.0066080751 | K13: =$H$183 -> 0.0057803468 | L13: 0.026821614 | M13: 0.0066080751 | N13: =$H$183 -> 0.0057803468 | O13: 0 | P13: 0 | Q13: =$H$183 -> 0.0057803468 | R13: 0.0059964109 | S13: 0.0066080751 | V13: =($B13*$B$29+$E13*$E$29+$H13*$H$29+$K13*$K$29+$N13*$N$29+$Q13*$Q$29+$B44*$B$60+$E44*$E$60+$H44*$H$60+$K44*$K$60+$N44*$N$60+$Q44*$Q$60)/$B$64 -> 0.0057803468 | W13: =V13 -> 0.0057803468 | X13: =V13-W13 -> 0 | AA13: lb | AB13: VAR01 | AC13: =ROUND(G183,0) -> 200000 | AD13: =$B$64*1000 -> 34600000 | AE13: =AC13/AD13 -> 0.0057803468 | AF13: =ROUND(AD13/$B$64,3) -> 1000 | AG13: =ROUND(W13*$AC$29,0) -> 200000 | AH13: =AG13/AD13 -> 0.0057803468 | AI13: =AC13-AG13 -> 0 | AJ13: =AH13*10000 -> 57.803468
A14: Total Variable Costs | B14: =SUM(B6:B13) -> 0.30796063 | C14: =SUM(C6:C13) -> 0.23258747 | D14: =SUM(D6:D13) -> 0.28463637 | E14: =SUM(E6:E13) -> 0.30559917 | F14: =SUM(F6:F13) -> 0.23029767 | G14: =SUM(G6:G13) -> 0.28463637 | H14: =SUM(H6:H13) -> 0.026144587 | I14: =SUM(I6:I13) -> 0.42180018 | ... S14: =SUM(S6:S13) -> 0.30060743 | V14: =SUM(V6:V13) -> 0.30309546 | W14: =SUM(W6:W13) -> 0.30309546 | X14: =SUM(X6:X13) -> 0 | AC14: =SUM(AC9:AC13) -> 904603 | AG14: =SUM(AG9:AG13) -> 904603 | AI14: =SUM(AI9:AI13) -> 0
A16: Production Labor | B16: =$D$214/$B$64/1000 -> 0.011741675 | C16: 0.018200142 | D16: 0.014552451 | E16: =$D$214/$B$64/1000 -> 0.011741675 | F16: 0.020063713 | G16: 0.014552451 | H16: =$D$214/$B$64/1000 -> 0.011741675 | I16: 0.012521635 | J16: 0.014552451 | K16: =$D$214/$B$64/1000 -> 0.011741675 | L16: 0.032785827 | M16: 0.014552451 | N16: =$D$214/$B$64/1000 -> 0.011741675 | O16: 0 | P16: 0 | Q16: =$D$214/$B$64/1000 -> 0.011741675 | R16: 0.013727223 | S16: 0.014552451 | V16: =($B16*$B$29+$E16*$E$29+$H16*$H$29+$K16*$K$29+$N16*$N$29+$Q16*$Q$29+$B47*$B$60+$E47*$E$60+$H47*$H$60+$K47*$K$60+$N47*$N$60+$Q47*$Q$60)/$B$64 -> 0.011741675 | W16: =V16 -> 0.011741675 | X16: =V16-W16 -> 0 | AA16: hr | AB16: DLAB01 | AC16: =ROUND(D212,0) -> 434475 | AD16: =ROUND(B212,0) -> 15400 | AE16: =AC16/AD16 -> 28.212662 | AF16: =ROUND(AD16/$B$64,3) -> 0.445 | AG16: =ROUND(W16*$AC$29,0) -> 406262 | AH16: =AG16/AD16 -> 26.380649 | AI16: =AC16-AG16 -> 28213 | AJ16: =AH16*10000 -> 263806.49
A17: Repairs & Maintenance Labor | B17: =$G$214/$B$64/1000 -> 0.0041080925 | C17: 0.0048304191 | D17: 0.004696359 | E17: =$G$214/$B$64/1000 -> 0.0041080925 | F17: 0.0044471791 | G17: 0.004696359 | H17: =$G$214/$B$64/1000 -> 0.0041080925 | I17: 0.0044303098 | J17: 0.004696359 | K17: =$G$214/$B$64/1000 -> 0.0041080925 | L17: 0.0088578354 | M17: 0.004696359 | N17: =$G$214/$B$64/1000 -> 0.0041080925 | O17: 0 | P17: 0 | Q17: =$G$214/$B$64/1000 -> 0.0041080925 | R17: 0.0016693747 | S17: 0.004696359 | V17: =($B17*$B$29+$E17*$E$29+$H17*$H$29+$K17*$K$29+$N17*$N$29+$Q17*$Q$29+$B48*$B$60+$E48*$E$60+$H48*$H$60+$K48*$K$60+$N48*$N$60+$Q48*$Q$60)/$B$64 -> 0.0041080925 | W17: =V17 -> 0.0041080925 | X17: =V17-W17 -> 0 | AA17: hr | AB17: MLAB01 | AC17: =ROUND(G212,0) -> 142140 | AD17: =ROUND(E212,0) -> 4400 | AE17: =AC17/AD17 -> 32.304545 | AF17: =ROUND(AD17/$B$64,3) -> 0.127 | AG17: =ROUND(W17*$AC$29,0) -> 142140 | AH17: =AG17/AD17 -> 32.304545 | AI17: =AC17-AG17 -> 0 | AJ17: =AH17*10000 -> 323045.45
A18: Indirect Payroll Costs (Benefits) | B18: =$J$214/$B$64/1000 -> 0.0072598437 | C18: 0.0068508297 | D18: 0.008765191 | E18: =$J$214/$B$64/1000 -> 0.0072598437 | F18: 0.0059757405 | G18: 0.008765191 | H18: =$J$214/$B$64/1000 -> 0.0072598437 | I18: 0.014238166 | J18: 0.008765191 | K18: =$J$214/$B$64/1000 -> 0.0072598437 | L18: 0.038686584 | M18: 0.008765191 | N18: =$J$214/$B$64/1000 -> 0.0072598437 | O18: 0 | P18: 0 | Q18: =$J$214/$B$64/1000 -> 0.0072598437 | R18: 0.0056633179 | S18: 0.008765191 | V18: =($B18*$B$29+$E18*$E$29+$H18*$H$29+$K18*$K$29+$N18*$N$29+$Q18*$Q$29+$B49*$B$60+$E49*$E$60+$H49*$H$60+$K49*$K$60+$N49*$N$60+$Q49*$Q$60)/$B$64 -> 0.0072598437 | W18: =+V18 -> 0.0072598437 | X18: =V18-W18 -> 0 | AA18: hr | AB18: IPC01 | AC18: =ROUND(J212,0) -> 264552 | AD18: =ROUND(H212,0) -> 19800 | AE18: =AC18/AD18 -> 13.361212 | AF18: =ROUND(AD18/$B$64,3) -> 0.572 | AG18: =ROUND(W18*$AC$29,0) -> 251191 | AH18: =AG18/AD18 -> 12.686414 | AI18: =AC18-AG18 -> 13361 | AJ18: =AH18*10000 -> 126864.14
A19: Supervision | B19: =$E$241 -> 0.002449852 | C19: 0.0022776301 | D19: 0.0028006635 | E19: =$E$241 -> 0.002449852 | F19: 0.0019225049 | G19: 0.0028006635 | H19: =$E$241 -> 0.002449852 | I19: 0.0092721693 | J19: 0.0028006635 | K19: =$E$241 -> 0.002449852 | L19: 0.01254166 | M19: 0.0028006635 | N19: =$E$241 -> 0.002449852 | O19: 0 | P19: 0 | Q19: =$E$241 -> 0.002449852 | R19: 0.0023710733 | S19: 0.0028006635 | V19: =($B19*$B$29+$E19*$E$29+$H19*$H$29+$K19*$K$29+$N19*$N$29+$Q19*$Q$29+$B50*$B$60+$E50*$E$60+$H50*$H$60+$K50*$K$60+$N50*$N$60+$Q50*$Q$60)/$B$64 -> 0.002449852 | W19: =W24-W14-W16-W17-W18 -> 0.00054580138 | X19: =V19-W19 -> 0.0019040506 | AA19: lb | AB19: SUP01 | AC19: =ROUND(C241,0) -> 84765 | AD19: =$B$64*1000 -> 34600000 | AE19: =AC19/AD19 -> 0.0024498555 | AF19: =ROUND(AD19/$B$64,3) -> 1000 | AG19: =ROUND(W19*$AC$29,0) -> 18885 | AH19: =AG19/AD19 -> 0.00054580925 | AI19: =AC19-AG19 -> 65880 | AJ19: =AH19*10000 -> 5.4580925
A20: Depreciation | B20: =$E$242 -> 0.06367052 | C20: 0.061012872 | D20: 0.072787947 | E20: =$E$242 -> 0.06367052 | F20: 0.051498884 | G20: 0.072787947 | H20: =$E$242 -> 0.06367052 | I20: 0.24870656 | J20: 0.072787947 | K20: =$E$242 -> 0.06367052 | L20: 0.34045176 | M20: 0.072787947 | N20: =$E$242 -> 0.06367052 | O20: 0 | P20: 0 | Q20: =$E$242 -> 0.06367052 | R20: 0.064182394 | S20: 0.072787947 | V20: =($B20*$B$29+$E20*$E$29+$H20*$H$29+$K20*$K$29+$N20*$N$29+$Q20*$Q$29+$B51*$B$60+$E51*$E$60+$H51*$H$60+$K51*$K$60+$N51*$N$60+$Q51*$Q$60)/$B$64 -> 0.06367052 | W20: =W24-W14-W16-W17-W18-W19-W21 -> 0 | X20: =V20-W20 -> 0.06367052 | AA20: lb | AB20: DEP01 | AC20: =ROUND(C242,0) -> 2203000 | AD20: =($B$29+$E$29+$H$29+$K$29+$N$29)*1000 -> 21000000 | AE20: =AC20/AD20 -> 0.10490476 | AF20: =ROUND(AD20/($B$29+$E$29+$H$29+$K$29+$N$29),3) -> 1000 | AG20: =ROUND(W20*$AC$29,0) -> 0 | AH20: =AG20/AD20 -> 0 | AI20: =AC20-AG20 -> 2203000 | AJ20: =AH20*10000 -> 0
A21: Insurance & Taxes | B21: =$E$243 -> 0.014046243 | C21: 0.01547789 | D21: 0.018172206 | E21: =$E$243 -> 0.014046243 | F21: 0.012959419 | G21: 0.018172206 | H21: =$E$243 -> 0.014046243 | I21: 0.064467032 | J21: 0.018172206 | K21: =$E$243 -> 0.014046243 | L21: 0.083528141 | M21: 0.018172206 | N21: =$E$243 -> 0.014046243 | O21: 0 | P21: 0 | Q21: =$E$243 -> 0.014046243 | R21: 0.015675972 | S21: 0.018172206 | V21: =($B21*$B$29+$E21*$E$29+$H21*$H$29+$K21*$K$29+$N21*$N$29+$Q21*$Q$29+$B52*$B$60+$E52*$E$60+$H52*$H$60+$K52*$K$60+$N52*$N$60+$Q52*$Q$60)/$B$64 -> 0.014046243 | W21: =W24-W14-W16-W17-W18-W19 -> 0 | X21: =V21-W21 -> 0.014046243 | AA21: lb | AB21: INS01 | AC21: =ROUND(C243,0) -> 486000 | AD21: =$B$64*1000 -> 34600000 | AE21: =AC21/AD21 -> 0.014046243 | AF21: =ROUND(AD21/$B$64,3) -> 1000 | AG21: =ROUND(W21*$AC$29,0) -> 0 | AH21: =AG21/AD21 -> 0 | AI21: =AC21-AG21 -> 486000 | AJ21: =AH21*10000 -> 0
A22: Total Fixed Costs | B22: =SUM(B16:B21) -> 0.10327623 | C22: =SUM(C16:C21) -> 0.10864978 | D22: =SUM(D16:D21) -> 0.12177482 | E22: =SUM(E16:E21) -> 0.10327623 | F22: =SUM(F16:F21) -> 0.09686744 | G22: =SUM(G16:G21) -> 0.12177482 | H22: =SUM(H16:H21) -> 0.10327623 | I22: =SUM(I16:I21) -> 0.35363588 | ... S22: =SUM(S16:S21) -> 0.12177482 | V22: =SUM(V16:V21) -> 0.10327623 | W22: =SUM(W16:W21) -> 0.023655413 | X22: =SUM(X16:X21) -> 0.079620814 | AC22: =SUM(AC16:AC21) -> 3614932 | AG22: =SUM(AG16:AG21) -> 818478 | AI22: =SUM(AI16:AI21) -> 2796454
AA23: Activity Cost | AC23: =AC14+AC22 -> 4519535 | AG23: =AG14+AG22 -> 1723081 | AI23: =AI14+AI22 -> 2796454
A24: Total Cost per Pound at Gross | B24: =B14+B22 -> 0.41123685 | C24: =C14+C22 -> 0.34123726 | D24: =D14+D22 -> 0.40641119 | E24: =E14+E22 -> 0.40887539 | F24: =F14+F22 -> 0.32716511 | G24: =G14+G22 -> 0.40641119 | H24: =H14+H22 -> 0.12942081 | I24: =I14+I22 -> 0.77543605 | ... S24: =S14+S22 -> 0.42238225 | V24: =V14+V22 -> 0.40637169 | W24: =0.0498+V6+V7+V8 -> 0.32675087 | X24: =X14+X22 -> 0.079620814 | AA24: $/lb excl matl | AC24: =ROUND(AC23/AC29,5) -> 0.13062 | AG24: =ROUND(AG23/AC29,5) -> 0.0498 | AI24: =ROUND(AI23/AC29,5) -> 0.08082
A25: Less: Substrate Plant Under-absorption | B25: =-B7 -> -0.088727451 | D25: -0.02807392 | E25: =-E7 -> -0.08643106 | G25: -0.02807392 | H25: =-H7 -> 0 | J25: -0.22562455 | K25: =-K7 -> -0.094857323 | M25: -0.02886962 | N25: =-N7 -> 0 | Q25: =-Q7 -> -0.08891715 | S25: -0.027061741 | V25: 0
A26: Less: RC Under-absorption | B26: =IF(B9+B10+B11+B12+B13+B22>0.0498,0.0498-B9-B10-B11-B12-B13-B22,0) -> -0.079620814 | C26: -0.079184632 | D26: =IF(D9+D10+D11+D12+D13+D22>0.0498,0.0498-D9-D10-D11-D12-D13-D22,0) -> -0.10097661 | E26: =IF(E9+E10+E11+E12+E13+E22>0.0498,0.0498-E9-E10-E11-E12-E13-E22,0) -> -0.079620814 | F26: =IF(F9+F10+F11+F12+F13+F22>0.0498,0.0498-F9-F10-F11-F12-F13-F22,0) -> -0.064407031 | G26: =IF(G9+G10+G11+G12+G13+G22>0.0498,0.0498-G9-G10-G11-G12-G13-G22,0) -> -0.10097661 | H26: =IF(H9+H10+H11+H12+H13+H22>0.0498,0.0498-H9-H10-H11-H12-H13-H22,0) -> -0.079620814 | I26: -0.36723743 | J26: =IF(J9+J10+J11+J12+J13+J22>0.0498,0.0498-J9-J10-J11-J12-J13-J22,0) -> -0.10097661 | K26: =IF(K9+K10+K11+K12+K13+K22>0.0498,0.0498-K9-K10-K11-K12-K13-K22,0) -> -0.079620814 | L26: =IF(L9+L10+L11+L12+L13+L22>0.0498,0.0498-L9-L10-L11-L12-L13-L22,0) -> -0.54222065 | M26: =IF(M9+M10+M11+M12+M13+M22>0.0498,0.0498-M9-M10-M11-M12-M13-M22,0) -> -0.10097661 | N26: =IF(N9+N10+N11+N12+N13+N22>0.0498,0.0498-N9-N10-N11-N12-N13-N22,0) -> -0.079620814 | O26: =IF(O9+O10+O11+O12+O13+O22>0.0498,0.0498-O9-O10-O11-O12-O13-O22,0) -> 0 | P26: =IF(P9+P10+P11+P12+P13+P22>0.0498,0.0498-P9-P10-P11-P12-P13-P22,0) -> 0 | Q26: =IF(Q9+Q10+Q11+Q12+Q13+Q22>0.0498,0.0498-Q9-Q10-Q11-Q12-Q13-Q22,0) -> -0.079620814 | ... S26: =IF(S9+S10+S11+S12+S13+S22>0.0498,0.0498-S9-S10-S11-S12-S13-S22,0) -> -0.10097661 | V26: =($B26*$B$29+$E26*$E$29+$H26*$H$29+$K26*$K$29+$N26*$N$29+$Q26*$Q$29+$B57*$B$60+$E57*$E$60+$H57*$H$60+$K57*$K$60+$N57*$N$60+$Q57*$Q$60)/$B$64 -> -0.079620814
A27: Net Cost per Pound Absorbed | B27: =SUM(B24:B26) -> 0.24288859 | C27: =SUM(C24:C26) -> 0.26205262 | D27: =SUM(D24:D26) -> 0.27736066 | E27: =SUM(E24:E26) -> 0.24282352 | F27: =SUM(F24:F26) -> 0.26275808 | G27: =SUM(G24:G26) -> 0.27736066 | H27: =SUM(H24:H26) -> 0.0498 | I27: =SUM(I24:I26) -> 0.40819862 | ... S27: =SUM(S24:S26) -> 0.2943439 | V27: =SUM(V24:V26) -> 0.32675087
AA28: $/lb incl matl | AC28: =ROUND((AC24+(B8*B29+E8*E29+H8*H29+K8*K29+N8*N29+Q8*Q29)/B64),5) -> 0.16763 | AG28: =ROUND(AG24+W8,5) -> 0.11626 | AI28: =ROUND(AI24+X8,5) -> 0.08082
A29: Total Production (000 lbs) | B29: 10000 | C29: 15431 | D29: 8700 | E29: 10000 | F29: 9412 | H29: 0 | I29: 74 | J29: 600 | K29: 1000 | L29: 254 | M29: 2664 | N29: =$B$85 -> 0 | O29: 0 | P29: 0 | Q29: 1300 | R29: 3647.15 | S29: 11002 | V29: =B29+E29+H29+K29+N29+Q29+B60+E60+H60+K60+N60+Q60 -> 34600 | AA29: Prod lbs | AC29: =ROUND($B$64*1000,0) -> 34600000
B34: Fusion | E34: ScaleGuard II CL | H34: KSXT | K34: ScaleGuard II KSHD (H) | N34: XX | Q34: XX
B35: =+B4 -> 20 Standard | C35: 19 Actual | D35: =+D4 -> 19 Standard | E35: =+B4 -> 20 Standard | F35: 19 Actual | G35: =+D4 -> 19 Standard | H35: =+B4 -> 20 Standard | I35: 19 Actual | J35: =+D4 -> 19 Standard | K35: =+B4 -> 20 Standard | L35: 19 Actual | M35: =+D4 -> 19 Standard | N35: =+B4 -> 20 Standard | O35: 19 Actual | P35: =+D4 -> 19 Standard | Q35: =+B4 -> 20 Standard | R35: 19 Actual | S35: =+D4 -> 19 Standard
C36: (Jan-Sept) | F36: (Jan-Sept) | I36: (Jan-Sept) | L36: (Jan-Sept)
A37: Materials - Substrate | B37: =E148 -> 0.19598456 | C37: 0.34054143 | D37: 0.24705272 | E37: =G148 -> 0.41539541 | F37: 0.4105 | G37: 0.41971568 | H37: =I148 -> 0.29172286 | I37: 0.26541432 | J37: 0 | K37: =K148 -> 1.8829093 | L37: 0 | M37: 1.8876071 | N37: =M148 -> 0 | O37: 0 | P37: 0 | Q37: =O148 -> 0 | R37: 0 | S37: 0
A38: Materials - Substrate Under-Absorption | B38: =$C135*D135 -> 0.10656371 | D38: 0.14908529 | E38: =$C133*F133 -> 0.11759583 | G38: 0.034805886 | H38: =$C130*H130 -> 0.18665446 | J38: 0 | K38: =$C134*J134 -> 0.16177979 | M38: 0.0074705959 | N38: 0 | P38: 0 | Q38: 0 | S38: 0
A39: Materials - Resin & Chemicals | B39: =E149+E150 -> 0.086815916 | C39: 0.093737947 | D39: 0.054021222 | E39: =G149+G150 -> 0.044288616 | F39: 0.043894371 | G39: 0.037426675 | H39: =I149+I150 -> 0.10420358 | I39: 0.04843802 | J39: 0 | K39: =K149+K150 -> 0.042578635 | L39: 0 | M39: 0.044929537 | N39: =M149+M150 -> 0 | O39: 0 | P39: 0 | Q39: =O149 -> 0 | R39: 0 | S39: 0
A40: Electricity | B40: =E168 -> 0.010135435 | C40: 0.026041382 | D40: 0.010726 | E40: =G168 -> 0.010135435 | F40: 0.014645894 | G40: 0.010726 | H40: =I168 -> 0.010135435 | I40: 0.010462455 | J40: 0 | K40: =K168 -> 0.010135435 | L40: 0 | M40: 0.010726 | N40: =M168 -> 0 | O40: 0 | P40: 0 | Q40: =O168 -> 0 | R40: 0 | S40: 0
A41: Gas | B41: =E169 -> 0.0011247591 | C41: 0.0016828037 | D41: 0.00126 | E41: =G169 -> 0.0011247591 | F41: 0.0055474856 | G41: 0.00126 | H41: =I169 -> 0.0011247591 | I41: 0.00084305984 | J41: 0 | K41: =K169 -> 0.0011247591 | L41: 0 | M41: 0.00126 | N41: =M169 -> 0 | O41: 0 | P41: 0 | Q41: =O169 -> 0 | R41: 0 | S41: 0
A42: R&M Supplies and Service | B42: =$H$177 -> 0.0086705202 | C42: 0.019710326 | D42: 0.0099121126 | E42: =$H$177 -> 0.0086705202 | F42: 0.012018642 | G42: 0.0099121126 | H42: =$H$177 -> 0.0086705202 | I42: 0.0073389729 | J42: 0 | K42: =$H$177 -> 0.0086705202 | L42: 0 | M42: 0.0099121126 | N42: =$H$177 -> 0.0086705202 | O42: 0 | P42: 0 | Q42: =$H$177 -> 0.0086705202 | R42: 0 | S42: 0
A43: Manufacturing Supplies | B43: =$H$180 -> 0.00043352601 | C43: 0.0024000594 | D43: 0.00049560563 | E43: =$H$180 -> 0.00043352601 | F43: 0.0007808962 | G43: 0.00049560563 | H43: =$H$180 -> 0.00043352601 | I43: 0.00063205421 | J43: 0 | K43: =$H$180 -> 0.00043352601 | L43: 0 | M43: 0.00049560563 | N43: =$H$180 -> 0.00043352601 | O43: 0 | P43: 0 | Q43: =$H$180 -> 0.00043352601 | R43: 0 | S43: 0
A44: Other variable | B44: =$H$183 -> 0.0057803468 | C44: 0.026652312 | D44: 0.0066080751 | E44: =$H$183 -> 0.0057803468 | F44: 0.026473851 | G44: 0.0066080751 | H44: =$H$183 -> 0.0057803468 | I44: 0.0094086246 | J44: 0 | K44: =$H$183 -> 0.0057803468 | L44: 0 | M44: 0.0066080751 | N44: =$H$183 -> 0.0057803468 | O44: 0 | P44: 0 | Q44: =$H$183 -> 0.0057803468 | R44: 0 | S44: 0
A45: Total Variable Costs | B45: =SUM(B37:B44) -> 0.41550877 | C45: =SUM(C37:C44) -> 0.51076626 | D45: =SUM(D37:D44) -> 0.47916103 | E45: =SUM(E37:E44) -> 0.60342444 | F45: =SUM(F37:F44) -> 0.51386114 | G45: =SUM(G37:G44) -> 0.52095004 | H45: =SUM(H37:H44) -> 0.60872548 | I45: =SUM(I37:I44) -> 0.34253751 | ... S45: =SUM(S37:S44) -> 0
A47: Production Labor | B47: =$D$214/$B$64/1000 -> 0.011741675 | C47: 0.02099802 | D47: 0.014552451 | E47: =$D$214/$B$64/1000 -> 0.011741675 | F47: 0.020095412 | G47: 0.014552451 | H47: =$D$214/$B$64/1000 -> 0.011741675 | I47: 0.017675634 | J47: 0 | K47: =$D$214/$B$64/1000 -> 0.011741675 | L47: 0 | M47: 0.014552451 | N47: =$D$214/$B$64/1000 -> 0.011741675 | O47: 0 | P47: 0 | Q47: =$D$214/$B$64/1000 -> 0.011741675 | R47: 0 | S47: 0
A48: Repairs & Maintenance Labor | B48: =$G$214/$B$64/1000 -> 0.0041080925 | C48: 0.010055044 | D48: 0.004696359 | E48: =$G$214/$B$64/1000 -> 0.0041080925 | F48: 0.0031155542 | G48: 0.004696359 | H48: =$G$214/$B$64/1000 -> 0.0041080925 | I48: 0.0047406695 | J48: 0 | K48: =$G$214/$B$64/1000 -> 0.0041080925 | L48: 0 | M48: 0.004696359 | N48: =$G$214/$B$64/1000 -> 0.0041080925 | O48: 0 | P48: 0 | Q48: =$G$214/$B$64/1000 -> 0.0041080925 | R48: 0 | S48: 0
A49: Indirect Payroll Costs (Benefits) | B49: =$J$214/$B$64/1000 -> 0.0072598437 | C49: 0.020373428 | D49: 0.008765191 | E49: =$J$214/$B$64/1000 -> 0.0072598437 | F49: 0.01913635 | G49: 0.008765191 | H49: =$J$214/$B$64/1000 -> 0.0072598437 | I49: 0.0076540782 | J49: 0 | K49: =$J$214/$B$64/1000 -> 0.0072598437 | L49: 0 | M49: 0.008765191 | N49: =$J$214/$B$64/1000 -> 0.0072598437 | O49: 0 | P49: 0 | Q49: =$J$214/$B$64/1000 -> 0.0072598437 | R49: 0 | S49: 0
A50: Supervision | B50: =$E$241 -> 0.002449852 | C50: 0.0068127908 | D50: 0.0028006635 | E50: =$E$241 -> 0.002449852 | F50: 0.0082982662 | G50: 0.0028006635 | H50: =$E$241 -> 0.002449852 | I50: 0.0028565151 | J50: 0 | K50: =$E$241 -> 0.002449852 | L50: 0 | M50: 0.0028006635 | N50: =$E$241 -> 0.002449852 | O50: 0 | P50: 0 | Q50: =$E$241 -> 0.002449852 | R50: 0 | S50: 0
A51: Depreciation | B51: =$E$242 -> 0.06367052 | C51: 0.18195763 | D51: 0.072787947 | E51: =$E$242 -> 0.06367052 | F51: 0.22264847 | G51: 0.072787947 | H51: =$E$242 -> 0.06367052 | I51: 0.07640353 | J51: 0 | K51: =$E$242 -> 0.06367052 | L51: 0 | M51: 0.072787947 | N51: =$E$242 -> 0.06367052 | O51: 0 | P51: 0 | Q51: =$E$242 -> 0.06367052 | R51: 0 | S51: 0
A52: Insurance & Taxes | B52: =$E$243 -> 0.014046243 | C52: 0.045121869 | D52: 0.018172206 | E52: =$E$243 -> 0.014046243 | F52: 0.064601784 | G52: 0.018172206 | H52: =$E$243 -> 0.014046243 | I52: 0.019244874 | J52: 0 | K52: =$E$243 -> 0.014046243 | L52: 0 | M52: 0.018172206 | N52: =$E$243 -> 0.014046243 | O52: 0 | P52: 0 | Q52: =$E$243 -> 0.014046243 | R52: 0 | S52: 0
A53: Total Fixed Costs | B53: =SUM(B47:B52) -> 0.10327623 | C53: =SUM(C47:C52) -> 0.28531878 | D53: =SUM(D47:D52) -> 0.12177482 | E53: =SUM(E47:E52) -> 0.10327623 | F53: =SUM(F47:F52) -> 0.33789584 | G53: =SUM(G47:G52) -> 0.12177482 | H53: =SUM(H47:H52) -> 0.10327623 | I53: =SUM(I47:I52) -> 0.1285753 | ... S53: =SUM(S47:S52) -> 0
A55: Total Cost per Pound at Gross | B55: =B45+B53 -> 0.51878499 | C55: =C45+C53 -> 0.79608504 | D55: =D45+D53 -> 0.60093585 | E55: =E45+E53 -> 0.70670067 | F55: =F45+F53 -> 0.85175698 | G55: =G45+G53 -> 0.64272486 | H55: =H45+H53 -> 0.7120017 | I55: =I45+I53 -> 0.47111281 | ... S55: =S45+S53 -> 0
A56: Less: Substrate Plant Under-absorption | B56: =-B38 -> -0.10656371 | C56: =-C38 -> 0 | D56: -0.14908529 | E56: =-E38 -> -0.11759583 | G56: -0.034805886 | H56: =-H38 -> -0.18665446 | K56: =-K38 -> -0.16177979 | M56: -0.0074705959 | N56: =-N38 -> 0 | P56: 0 | Q56: =-Q38 -> 0
A57: Less: RC Under-absorption | B57: =IF(B40+B41+B42+B43+B44+B53>0.0498,0.0498-B40-B41-B42-B43-B44-B53,0) -> -0.079620814 | C57: -0.31205821 | D57: =IF(D40+D41+D42+D43+D44+D53>0.0498,0.0498-D40-D41-D42-D43-D44-D53,0) -> -0.10097661 | E57: =IF(E40+E41+E42+E43+E44+E53>0.0498,0.0498-E40-E41-E42-E43-E44-E53,0) -> -0.079620814 | F57: =IF(F40+F41+F42+F43+F44+F53>0.0498,0.0498-F40-F41-F42-F43-F44-F53,0) -> -0.34756261 | G57: =IF(G40+G41+G42+G43+G44+G53>0.0498,0.0498-G40-G41-G42-G43-G44-G53,0) -> -0.10097661 | H57: =IF(H40+H41+H42+H43+H44+H53>0.0498,0.0498-H40-H41-H42-H43-H44-H53,0) -> -0.079620814 | I57: =IF(I40+I41+I42+I43+I44+I53>0.0498,0.0498-I40-I41-I42-I43-I44-I53,0) -> -0.10746047 | J57: =IF(J40+J41+J42+J43+J44+J53>0.0498,0.0498-J40-J41-J42-J43-J44-J53,0) -> 0 | K57: =IF(K40+K41+K42+K43+K44+K53>0.0498,0.0498-K40-K41-K42-K43-K44-K53,0) -> -0.079620814 | ... N57: =IF(N40+N41+N42+N43+N44+N53>0.0498,0.0498-N40-N41-N42-N43-N44-N53,0) -> -0.068360619 | O57: 0 | P57: =IF(P40+P41+P42+P43+P44+P53>0.0498,0.0498-P40-P41-P42-P43-P44-P53,0) -> 0 | Q57: =IF(Q40+Q41+Q42+Q43+Q44+Q53>0.0498,0.0498-Q40-Q41-Q42-Q43-Q44-Q53,0) -> -0.068360619 | R57: 0 | S57: =IF(S40+S41+S42+S43+S44+S53>0.0498,0.0498-S40-S41-S42-S43-S44-S53,0) -> 0
A58: Net Cost per Pound Absorbed | B58: =SUM(B55:B57) -> 0.33260047 | C58: =SUM(C55:C57) -> 0.48402683 | D58: =SUM(D55:D57) -> 0.35087395 | E58: =SUM(E55:E57) -> 0.50948403 | F58: =SUM(F55:F57) -> 0.50419437 | G58: =SUM(G55:G57) -> 0.50694236 | H58: =SUM(H55:H57) -> 0.44572643 | I58: =SUM(I55:I57) -> 0.36365234 | ... S58: =SUM(S55:S57) -> 0
A60: Total Production (000 lbs) | B60: 1300 | C60: 101 | D60: 400 | E60: 3900 | F60: 979 | G60: 5800 | H60: 7000 | I60: 2743 | J60: 0 | K60: 100 | L60: 0 | M60: 0 | N60: 0 | O60: 0 | P60: 0 | Q60: 0 | R60: 0 | S60: 0
A64: Total Plant Production (000 lbs) | B64: =B29+E29+H29+K29+N29+Q29+B60+E60+H60+K60+N60+Q60 -> 34600 | C64: =C29+F29+I29+L29+O29+R29+C60+F60+I60+L60+O60+R60 -> 32641.15 | D64: =D29+G29+J29+M29+P29+S29+D60+G60+J60+M60+P60+S60 -> 29166
V65: 2078820 | W65: 2289955 | AC65: 1.102 | AD65: 0.099 | AE65: =+AC65-AD65 -> 1.003
V66: 22566 | W66: 22313 | AC66: 0.989 | AD66: 0 | AE66: =+AC66-AD66 -> 0.989
B67: Total | C67: Variable | D67: Fixed | V67: 469400 | W67: 521591 | AC67: 1.111 | AD67: 0.07 | AE67: =+AC67-AD67 -> 1.041
A68: Cost Summary: | B68: ($ in 000s) | V68: 514675 | W68: 642354 | AC68: 1.248 | AD68: 0.015 | AE68: =+AC68-AD68 -> 1.233
A69: Absorbed by Production | B69: =SUM(C69:D69) -> 11305.58 | C69: =W14*$V$29 -> 10487.103 | D69: =W22*$V$29 -> 818.47728 | V69: 62400 | W69: 68640 | AC69: 1.1 | AD69: 0.158 | AE69: =+AC69-AD69 -> 0.942
A70: Underabsorption Expensed | B70: =SUM(C70:D70) -> 2754.8802 | C70: =X14*$V$29 -> 0 | D70: =X22*$V$29 -> 2754.8802 | V70: 22275 | W70: 27844 | AC70: 1.25 | AD70: 0 | AE70: =+AC70-AD70 -> 1.25
A71: Loss on Excess Gas Net Settled | B71: =SUM(C71:D71) -> 0 | C71: 0 | D71: 0 | V71: 10980 | W71: 13725 | AC71: 1.25 | AD71: 0 | AE71: =+AC71-AD71 -> 1.25
A72: Total Cost | B72: =SUM(B69:B71) -> 14060.46 | C72: =SUM(C69:C71) -> 10487.103 | D72: =SUM(D69:D71) -> 3573.3574 | AE72: =AVERAGE(AE65:AE71) -> 1.1011429
A73: Less: Non-Cash | B73: =SUM(C73:D73) -> -2203 | C73: 0 | D73: =-V20*V29 -> -2203 | V73: =SUM(V65:V72) -> 3181116 | W73: =SUM(W65:W72) -> 3586422
A74: Cash Cost | B74: =SUM(B72:B73) -> 11857.46 | C74: =SUM(C72:C73) -> 10487.103 | D74: =SUM(D72:D73) -> 1370.3574 | V74: 3233726 | W74: 1569174 | X74: =+W74/V74 -> 0.48525262
V75: =+V73-V74 -> -52610 | W75: =+W73-W74 -> 2017248
B79: Quantity | C79: Rate
A80: Production Plan | B80: (000 lbs) | C80: (000 lbs/day) | D80: Prodn Days | E80: % Split
A81: CB Lite | B81: 20000 | C81: =350 -> 350 | D81: =IF(C81<>0,B81/C81,0) -> 57.142857 | E81: =IF($D$93<>0,D81/$D$93,0) -> 0.57803468
A82: CB HSP | B82: 0 | C82: =350 -> 350 | D82: =IF(C82<>0,B82/C82,0) -> 0 | E82: =IF($D$93<>0,D82/$D$93,0) -> 0
A83: CB KSLD | B83: 0 | C83: =350 -> 350 | D83: =IF(C83<>0,B83/C83,0) -> 0 | E83: =IF($D$93<>0,D83/$D$93,0) -> 0
A84: RPM Lite / NP LWC | B84: 1000 | C84: =350 -> 350 | D84: =IF(C84<>0,B84/C84,0) -> 2.8571429 | E84: =IF($D$93<>0,D84/$D$93,0) -> 0.028901734
A85: RPM CP / NP ISP | B85: 0 | C85: =350 -> 350 | D85: =IF(C85<>0,B85/C85,0) -> 0 | E85: =IF($D$93<>0,D85/$D$93,0) -> 0
A86: Air | B86: 1300 | C86: =350 -> 350 | D86: =IF(C86<>0,B86/C86,0) -> 3.7142857 | E86: =IF($D$93<>0,D86/$D$93,0) -> 0.037572254
A87: Fusion (#998, 999, 1025) | B87: 1300 | C87: =350 -> 350 | D87: =IF(C87<>0,B87/C87,0) -> 3.7142857 | E87: =IF($D$93<>0,D87/$D$93,0) -> 0.037572254
A88: SG II CL | B88: 3900 | C88: =350 -> 350 | D88: =IF(C88<>0,B88/C88,0) -> 11.142857 | E88: =IF($D$93<>0,D88/$D$93,0) -> 0.11271676
A89: SG II Ultra CL | B89: 0 | C89: =350 -> 350 | D89: =IF(C89<>0,B89/C89,0) -> 0 | E89: =IF($D$93<>0,D89/$D$93,0) -> 0
A90: SG II KSHD (H) | B90: 100 | C90: =350 -> 350 | D90: =IF(C90<>0,B90/C90,0) -> 0.28571429 | E90: =IF($D$93<>0,D90/$D$93,0) -> 0.0028901734
A91: SaltGuard (FDP-806) | B91: 0 | C91: =350 -> 350 | D91: =IF(C91<>0,B91/C91,0) -> 0 | E91: =IF($D$93<>0,D91/$D$93,0) -> 0
A92: KSXT | B92: 7000 | C92: =350 -> 350 | D92: =IF(C92<>0,B92/C92,0) -> 20 | E92: =IF($D$93<>0,D92/$D$93,0) -> 0.20231214
A93: Total | B93: =SUM(B81:B92) -> 34600 | C93: =B93/D93 -> 350 | D93: =SUM(D81:D92) -> 98.857143 | E93: =IF($D$93<>0,D93/$D$93,0) -> 1
A96: Variable Costs - Material
D98: CB Lite | F98: CB Lite EU | H98: CB KSLD | J98: RPM Lite / NP LWC | L98: XX | N98: Air | AF98: CBL | AH98: CBL (EU) | AJ98: RPM | AL98: AIR
A99: Materials Cost: | B99: Price ($/lb) | C99: Source plant under-absorb | D99: BOM Use/lb | E99: Standard Cost | F99: BOM Use/lb | G99: Standard Cost | H99: BOM Use/lb | I99: Standard Cost | J99: BOM Use/lb | K99: Standard Cost | L99: BOM Use/lb | M99: Standard Cost | N99: BOM Use/lb | O99: Standard Cost | AB99: material | AE99: plan price 1 | AF99: cost BOM | AG99: plan price 1 | AH99: cost BOM | AI99: plan price 1 | AJ99: cost BOM | AK99: plan price 1 | AL99: cost BOM
A100: CARBO LITE (32, 36, 115) | B100: =0.209+0.032-C100 -> 0.149 | C100: 0.092 | D100: 0.96442882 | E100: =$B100*D100 -> 0.14369989 | F100: 0.93946805 | G100: =$B100*F100 -> 0.13998074 | H100: 0 | I100: =$B100*H100 -> 0 | J100: 1.0310579 | K100: =$B100*J100 -> 0.15362762 | L100: 0 | M100: =$B100*L100 -> 0 | N100: 0 | O100: =$B100*N100 -> 0 | AB100: CL | AE100: =B100*1000 -> 149 | AF100: =E100/B100*1000 -> 964.42882 | AH100: =G100/B100*1000 -> 939.46805 | AJ100: =K100/B100*1000 -> 1031.0579
A101: CARBOAIR UL (861, 938) | B101: =0.209+0.032-C101 -> 0.149 | C101: 0.092 | D101: 0 | E101: =$B101*D101 -> 0 | F101: 0 | G101: =$B101*F101 -> 0 | H101: 0 | I101: =$B101*H101 -> 0 | J101: 0 | K101: =$B101*J101 -> 0 | L101: 0 | M101: =$B101*L101 -> 0 | N101: 0.96649076 | O101: =$B101*N101 -> 0.14400712 | AL101: =O101/B101*1000 -> 966.49076
A102: KRYPTOSPHERE LD (976) | B102: =0.4447+0.032-C102 -> 0.2907 | C102: 0.186 | D102: 0 | E102: =$B102*D102 -> 0 | F102: 0 | G102: =$B102*F102 -> 0 | H102: 0 | I102: =$B102*H102 -> 0 | J102: 0 | K102: =$B102*J102 -> 0 | L102: 0 | M102: =$B102*L102 -> 0 | N102: 0 | O102: =$B102*N102 -> 0
A103: CARBO HSP (19) | B103: =0.225+0.032-C103 -> 0.257 | C103: 0 | D103: 0 | E103: =$B103*D103 -> 0 | F103: 0 | G103: =$B103*F103 -> 0 | H103: 0 | I103: =$B103*H103 -> 0 | J103: 0 | K103: =$B103*J103 -> 0 | L103: 0 | M103: =$B103*L103 -> 0 | N103: 0 | O103: =$B103*N103 -> 0
A104: CARBOPROP (50) | B104: =0.22+0.032-C104 -> 0.252 | C104: 0 | D104: 0 | E104: =$B104*D104 -> 0 | F104: 0 | G104: =$B104*F104 -> 0 | H104: 0 | I104: =$B104*H104 -> 0 | J104: 0 | K104: =$B104*J104 -> 0 | L104: 0 | M104: =$B104*L104 -> 0 | N104: 0 | O104: =$B104*N104 -> 0
A105: SCALEGUARD I CL (812, 951) | B105: =0.5176-C105 -> 0.4034 | C105: =0.049+0.0652 -> 0.1142 | D105: 0 | E105: =$B105*D105 -> 0 | F105: 0 | G105: =$B105*F105 -> 0 | H105: 0 | I105: =$B105*H105 -> 0 | J105: 0 | K105: =$B105*J105 -> 0 | L105: 0 | M105: =$B105*L105 -> 0 | N105: 0 | O105: =$B105*N105 -> 0
A106: SCALEGUARD I KSHD (H) | B106: =2.05-C106 -> 1.8878 | C106: =0.049+0.1132 -> 0.1622 | D106: 0 | E106: =$B106*D106 -> 0 | F106: 0 | G106: =$B106*F106 -> 0 | H106: 0 | I106: =$B106*H106 -> 0 | J106: 0 | K106: =$B106*J106 -> 0 | L106: 0 | M106: =$B106*L106 -> 0 | N106: 0 | O106: =$B106*N106 -> 0
A107: CL FUSION SUBSTRATE (994) | B107: =0.2292+0.032-C107 -> 0.1692 | C107: 0.092 | D107: 0 | E107: =$B107*D107 -> 0 | F107: 0 | G107: =$B107*F107 -> 0 | H107: 0 | I107: =$B107*H107 -> 0 | J107: 0 | K107: =$B107*J107 -> 0 | L107: 0 | M107: =$B107*L107 -> 0 | N107: 0 | O107: =$B107*N107 -> 0
A108: Plenco Resin (30090) | B108: =1118.2/1000 -> 1.1182 | C108: 0 | D108: 0.029759013 | E108: =$B108*D108 -> 0.033276528 | F108: 0 | G108: =$B108*F108 -> 0 | H108: 0 | I108: =$B108*H108 -> 0 | J108: 0 | K108: =$B108*J108 -> 0 | L108: 0 | M108: =$B108*L108 -> 0 | N108: 0.040703571 | O108: =$B108*N108 -> 0.045514733 | AB108: 30090 | AE108: =B108*1000 -> 1118.2 | AF108: =E108/B108*1000 -> 29.759013 | AL108: =O108/B108*1000 -> 40.703571
A109: Bimex Resin-EU (30120) | B109: =1217.55/1000 -> 1.21755 | C109: 0 | D109: 0.0063885501 | E109: =$B109*D109 -> 0.0077783792 | F109: 0.035855511 | G109: =$B109*F109 -> 0.043655878 | H109: 0 | I109: =$B109*H109 -> 0 | J109: 0 | K109: =$B109*J109 -> 0 | L109: 0 | M109: =$B109*L109 -> 0 | N109: 0 | O109: =$B109*N109 -> 0 | AB109: 30120 | AE109: =B109*1000 -> 1217.55 | AF109: =E109/B109*1000 -> 6.3885501 | AH109: =G109/B109*1000 -> 35.855511
A110: HEXA-EU (30362) | B110: =945.41/1000 -> 0.94541 | C110: 0 | D110: 0.0048857039 | E110: =$B110*D110 -> 0.0046189934 | F110: 0.0047245684 | G110: =$B110*F110 -> 0.0044666542 | H110: 0 | I110: =$B110*H110 -> 0 | J110: 0 | K110: =$B110*J110 -> 0 | L110: 0 | M110: =$B110*L110 -> 0 | N110: 0 | O110: =$B110*N110 -> 0 | AB110: 30362 | AE110: =B110*1000 -> 945.41 | AF110: =E110/B110*1000 -> 4.8857039 | AH110: =G110/B110*1000 -> 4.7245684
A111: Silane-EU (30360) | B111: =4458.01/1000 -> 4.45801 | C111: 0 | D111: 0 | E111: =$B111*D111 -> 0 | F111: 0.00095981301 | G111: =$B111*F111 -> 0.004278856 | H111: 0 | I111: =$B111*H111 -> 0 | J111: 0 | K111: =$B111*J111 -> 0 | L111: 0 | M111: =$B111*L111 -> 0 | N111: 8.2256008e-06 | O111: =$B111*N111 -> 3.6669811e-05 | AB111: 30360 | AH111: =G111/B111*1000 -> 0.95981301 | AL111: =O111/B111*1000 -> 0.0082256008
A112: Surfactant-EU (30361) | B112: =900.79/1000 -> 0.90079 | C112: 0 | D112: 0 | E112: =$B112*D112 -> 0 | F112: 0.00071203187 | G112: =$B112*F112 -> 0.00064139119 | H112: 0 | I112: =$B112*H112 -> 0 | J112: 0 | K112: =$B112*J112 -> 0 | L112: 0 | M112: =$B112*L112 -> 0 | N112: 3.1805656e-05 | O112: =$B112*N112 -> 2.8650217e-05 | AB112: 30361 | AH112: =G112/B112*1000 -> 0.71203187 | AL112: =O112/B112*1000 -> 0.031805656
A113: Surfactant (30054) | B113: =1249.29/1000 -> 1.24929 | C113: 0 | D113: 0.0005757172 | E113: =$B113*D113 -> 0.00071923774 | F113: 0 | G113: =$B113*F113 -> 0 | H113: 0 | I113: =$B113*H113 -> 0 | J113: 0 | K113: =$B113*J113 -> 0 | L113: 0 | M113: =$B113*L113 -> 0 | N113: 0.0015403808 | O113: =$B113*N113 -> 0.0019243824 | AB113: 30054 | AE113: =B113*1000 -> 1249.29 | AF113: =E113/B113*1000 -> 0.5757172 | AL113: =O113/B113*1000 -> 1.5403808
