Workbook

Sheet 2025 Summary
D4: Ceramics | E4: HA | G4: Ceramics | H4: HA
C5: Nov | D5: 0 | G5: =#REF! -> #REF! | H5: =#REF! -> #REF!
C6: Dec | G6: =#REF! -> #REF! | H6: =#REF! -> #REF!
C7: Jan | D7: 30000 | E7: 4900 | G7: =Jan!$B$22 -> 0.13768507 | H7: =Jan!$E$45 -> 0.23615711
C8: Feb | D8: 0 | E8: 4900 | G8: =Feb!$B$22 -> 0 | H8: =Feb!$E$45 -> 0.25135472
C9: Mar | D9: 0 | E9: 4900 | G9: =Mar!$B$22 -> 0 | H9: =Mar!$E$45 -> 0.25135472
C10: Apr | D10: 30000 | E10: 4900 | G10: =Apr!$B$22 -> 0.13768507 | H10: =Apr!$E$45 -> 0.24615711
C11: May | E11: 4900 | G11: =May!$B$22 -> 0 | H11: =May!$E$45 -> 0.25135472
C12: Jun | D12: 0 | E12: 4900 | G12: =Jun!$B$22 -> 0 | H12: =Jun!$E$45 -> 0.25135472
C13: Jul | D13: 0 | E13: 4900 | G13: =Jul!$B$22 -> 0 | H13: =Jul!$E$45 -> 0.25135472
C14: Aug | D14: 0 | E14: 4900 | G14: =Aug!$B$22 -> 0 | H14: =Aug!$E$45 -> 0.25135472
C15: Sep | D15: 0 | E15: 4900 | G15: =Sep!$B$22 -> 0 | H15: =Sep!$E$45 -> 0.25135472
C16: Oct | D16: 11000 | E16: 4900 | G16: =Oct!$B$22 -> 0.19735191 | H16: =Oct!$E$45 -> 0.24717157
C17: Nov | E17: 4900 | G17: =Nov!$B$22 -> 0 | H17: =Nov!$E$45 -> 0.25135472
C18: Dec | E18: 4900 | G18: =Dec!$B$22 -> 0 | H18: =Dec!$E$45 -> 0.25135472
C20: Total | D20: =SUM(D4:D18) -> 71000 | E20: =SUM(E5:E18) -> 58800

Sheet Jan
A1: TOOMSBORO STANDARD 2025
B3: CERAMICS | E3: CG 280 | H3: CG 300
B4: 25 Standard | C4: 23 Actual | D4: 20 Standard | E4: =$B$4 -> 25 Standard | F4: =+C4 -> 23 Actual | G4: =+D4 -> 20 Standard | H4: =+B4 -> 25 Standard | I4: =+C4 -> 23 Actual | J4: =+D4 -> 20 Standard
C5: (Jan-Sept) | F5: (Jan-Sept) | I5: (Jan-Sept)
A6: Materials | B6: =IF(B24<>0,$D$82,0) -> 0.065965818 | C6: 0.0585 | D6: 0.04156581 | E6: =+H82 -> 0 | F6: 0 | G6: 0 | H6: =+D96 -> 0 | I6: 0 | J6: 0
A7: Electricity | B7: =IF(B24<>0,$D$163,0) -> 0.0101288 | C7: 0.0105 | D7: 0.020277329 | E7: =G163 -> 0.0198372 | F7: 0 | G7: 0 | H7: =J163 -> 0.0198372 | I7: 0 | J7: 0
A8: Gas | B8: =IF(B24<>0,$D$164,0) -> 0.026 | C8: 0.0156 | D8: 0.014965 | E8: =G164 -> 0.0171 | F8: 0 | G8: 0 | H8: =J164 -> 0.0171 | I8: 0 | J8: 0
A9: R&M Supplies and Service | B9: =IF(B24<>0,$J$177,0) -> 0.011766667 | C9: 0.0192 | D9: 0.015915789 | E9: =$H$177 -> 0.03 | F9: 0 | G9: 0 | H9: =$H$177 -> 0.03 | I9: 0 | J9: 0
A10: Manufacturing Supplies | B10: =IF(B24<>0,$J$181,0) -> 0.0025 | C10: 0.0008 | D10: 0.0026315789 | E10: =$H$181 -> 0.0055102041 | F10: 0 | G10: 0 | H10: =$H$181 -> 0.0055102041 | I10: 0 | J10: 0
A11: Other variable | B11: =IF(B24<>0,$J$184,0) -> 0.0019 | C11: 0.0058 | D11: 0.0094736842 | E11: =$H$184 -> 0.01122449 | F11: 0 | G11: 0 | H11: =$H$184 -> 0.01122449 | I11: 0 | J11: 0
A12: Total Variable Costs | B12: =SUM(B6:B11) -> 0.11826128 | C12: =SUM(C6:C11) -> 0.1104 | D12: =SUM(D6:D11) -> 0.10482919 | E12: =SUM(E6:E11) -> 0.083671894 | F12: =SUM(F6:F11) -> 0 | G12: =SUM(G6:G11) -> 0 | H12: =SUM(H6:H11) -> 0.083671894 | I12: =SUM(I6:I11) -> 0 | J12: =SUM(J6:J11) -> 0
A14: Production Labor | B14: =IF($B$24<>0,$F$152/B24/1000,0) -> 0.008496223 | C14: 0.0246 | D14: 0.0073599375 | E14: =$D$124*$E$108/$B$49/1000 -> 0.00013061064 | F14: 0 | G14: 0 | H14: =$D$124*$E$108/$B$49/1000 -> 0.00013061064 | I14: 0 | J14: 0
A15: Repairs & Maintenance Labor | B15: =IF($B$24<>0,$F$153/$B$24/1000,0) -> 0.0035945559 | C15: 0.009 | D15: 0.0042419375 | E15: =$H$124*$E$108/$B$49/1000 -> 0 | F15: 0 | G15: 0 | H15: =$H$124*$E$108/$B$49/1000 -> 0 | I15: 0 | J15: 0
A16: Indirect Payroll Costs (Benefits) | B16: =IF($B$24<>0,$F$155/$B$24/1000,0) -> 0.0036987737 | C16: 0.0079 | D16: 0.0053897125 | E16: =$D$131*$E$108/$B$49/1000 -> 0 | F16: 0 | G16: 0 | H16: =$D$131*$E$108/$B$49/1000 -> 0 | I16: 0 | J16: 0
A17: Supervision | B17: =IF($B$24<>0,$F$154/$B$24/1000,0) -> 0.00023846667 | C17: 0 | D17: 0.0026778947 | E17: =$F$194 -> 0 | F17: 0 | G17: 0 | H17: =$F$194 -> 0 | I17: 0 | J17: 0
A18: Depreciation | B18: =IF($B$24<>0,$B$196/$B$49/1000,0) -> 0.00065364613 | C18: 0.0027 | D18: 0.1672 | E18: =$F$196 -> 0.0078437536 | F18: 0 | G18: 0 | H18: =$F$196 -> 0.0078437536 | I18: 0 | J18: 0
A19: Insurance & Taxes | B19: =IF($B$24<>0,$B$195/$B$49/1000,0) -> 0.0027421203 | C19: 0.012 | D19: 0.012884211 | E19: =$F$195 -> 0.032905444 | F19: 0 | G19: 0 | H19: =$F$195 -> 0.032905444 | I19: 0 | J19: 0
A20: Total Fixed Costs | B20: =SUM(B14:B19) -> 0.019423786 | C20: =SUM(C14:C19) -> 0.0562 | D20: =SUM(D14:D19) -> 0.19975369 | E20: =SUM(E14:E19) -> 0.040879808 | F20: =SUM(F14:F19) -> 0 | G20: =SUM(G14:G19) -> 0 | H20: =SUM(H14:H19) -> 0.040879808 | I20: =SUM(I14:I19) -> 0 | J20: =SUM(J14:J19) -> 0
A22: TOTAL COSTS PER POUND | B22: =B12+B20 -> 0.13768507 | C22: =C12+C20 -> 0.1666 | D22: =D12+D20 -> 0.30458288 | E22: =E12+E20 -> 0.1245517 | F22: =F12+F20 -> 0 | G22: =G12+G20 -> 0 | H22: =H12+H20 -> 0.1245517 | I22: =I12+I20 -> 0 | J22: =J12+J20 -> 0
A24: PRODUCTION ( in 000 lbs ) | B24: =+B54 -> 30000 | C24: 0 | D24: 80000 | E24: =+B55 -> 0 | F24: 0 | G24: 0 | H24: =+B56 -> 0 | I24: 0 | J24: 0
B26: XXX | E26: HA PELLETS
B27: =$B$4 -> 25 Standard | C27: =+C4 -> 23 Actual | D27: =+D4 -> 20 Standard | E27: 24 Standard | F27: 23 Actual | G27: 22 Standard | H27: =+B27 -> 25 Standard | I27: =+C27 -> 23 Actual | J27: =+D27 -> 20 Standard
C28: (Jan-Sept) | F28: (Jan-Aug)
A29: Materials | B29: =D82 -> 0.065965818 | C29: 0 | D29: 0 | E29: =IF(E47<>0,$L$96,0) -> 0.070852832 | F29: 0.078 | G29: 0.06025968 | H29: 0 | I29: 0 | J29: 0
A30: Electricity | B30: =D169 -> 0 | C30: 0 | D30: 0 | E30: =IF(E47<>0,$G$169,0)-0.01 -> 0.033918811 | F30: 0.0432 | G30: 0.026879418 | H30: 0 | I30: 0 | J30: 0
A31: Gas | B31: =D170 -> 0 | C31: 0 | D31: 0 | E31: =IF(E47<>0,$G$170,0) -> 0.026 | F31: 0.019 | G31: 0.028567 | H31: =J170 -> 0 | I31: 0 | J31: 0
A32: R&M Supplies and Service | B32: =IF($B$47<>0,$H$177,0) -> 0 | C32: 0 | D32: 0 | E32: =IF(E47<>0,$H$177,0) -> 0.03 | F32: 0.0298 | G32: 0.027777778 | H32: 0 | I32: 0 | J32: 0
A33: Manufacturing Supplies | B33: =IF($B$47<>0,$H$181,0) -> 0 | C33: 0 | D33: 0 | E33: =IF(E47<>0,$H$181,0) -> 0.0055102041 | F33: 0.0012 | G33: 0.0069444444 | H33: 0 | I33: 0 | J33: 0
A34: Other variable | B34: =IF($B$47<>0,$H$184,0) -> 0 | C34: 0 | D34: 0 | E34: =IF(E47<>0,$H$184,0) -> 0.01122449 | F34: 0.0139 | G34: 0.0125 | H34: 0 | I34: 0 | J34: 0
A35: Total Variable Costs | B35: =SUM(B29:B34) -> 0.065965818 | C35: =SUM(C29:C34) -> 0 | D35: =SUM(D29:D34) -> 0 | E35: =SUM(E29:E34) -> 0.17750634 | F35: =SUM(F29:F34) -> 0.1851 | G35: =SUM(G29:G34) -> 0.16292832 | H35: =SUM(H29:H34) -> 0 | I35: =SUM(I29:I34) -> 0 | J35: =SUM(J29:J34) -> 0
A37: Production Labor | B37: =$D$124*$E$108/$B$49/1000 -> 0.00013061064 | C37: 0 | D37: 0 | E37: =IF($E$47<>0,$F$127/$E$47/1000,0) -> 0.040001507 | F37: 0.0353 | G37: 0.02156921 | H37: 0 | I37: 0 | J37: 0
A38: Repairs & Maintenance Labor | B38: =$H$124*$E$108/$B$49/1000 -> 0 | C38: 0 | D38: 0 | E38: =IF($E$47<>0,$F$128/$E$47/1000,0) -> 0.0048061173 | F38: 0.0067 | G38: 0.0051700857 | H38: 0 | I38: 0 | J38: 0
A39: Indirect Payroll Costs (Benefits) | B39: =$D$131*$E$108/$B$49/1000 -> 0 | C39: 0 | D39: 0 | E39: =IF($E$47<>0,$F$130/$E$47/1000,0) -> 0.012994211 | F39: 0.0112 | G39: 0.0080162316 | H39: 0 | I39: 0 | J39: 0
A40: Supervision | B40: =IF($B$49<>0,$F$194,0) -> 0 | C40: 0 | D40: 0 | E40: =IF($E$47<>0,$F$129/$E$47/1000,0) -> 0 | F40: 0 | G40: 0.00047638889 | H40: 0 | I40: 0 | J40: 0
A41: Depreciation | B41: =IF($B$49<>0,$F$196,0) -> 0.0078437536 | C41: 0 | D41: 0 | E41: =IF($E$47<>0,$B$196/$B$49/1000/4,0) -> 0.00016341153 | F41: 0.0085 | G41: 0.0056777778 | H41: 0 | I41: 0 | J41: 0
A42: Insurance & Taxes | B42: =IF($B$49<>0,$F$195,0) -> 0.032905444 | C42: 0 | D42: 0 | E42: =IF($E$47<>0,$B$195/$B$49/1000/4,0) -> 0.00068553009 | F42: 0.0362 | G42: 0.025861111 | H42: 0 | I42: 0 | J42: 0
A43: Total Fixed Costs | B43: =SUM(B37:B42) -> 0.040879808 | C43: =SUM(C37:C42) -> 0 | D43: =SUM(D37:D42) -> 0 | E43: =SUM(E37:E42) -> 0.058650778 | F43: =SUM(F37:F42) -> 0.0979 | G43: =SUM(G37:G42) -> 0.066770805 | H43: =SUM(H37:H42) -> 0 | I43: =SUM(I37:I42) -> 0 | J43: =SUM(J37:J42) -> 0
A44: Excess Costs | F44: -0.0455
A45: TOTAL COSTS PER POUND | B45: =B35+B43 -> 0.10684563 | C45: =C35+C43 -> 0 | D45: 0.19962946 | E45: =E35+E43+E44 -> 0.23615711 | F45: =F35+F43+F44 -> 0.2375 | G45: =+G35+G43 -> 0.22969913 | H45: =H35+H43 -> 0 | I45: =I35+I43 -> 0 | J45: =J35+J43 -> 0
A47: PRODUCTION ( in 000 lbs ) | B47: =+B57 -> 0 | C47: 0 | D47: 0 | E47: =+B58 -> 4900 | F47: 15776 | G47: 36000 | H47: =+B59 -> 0 | I47: 0 | J47: 0
A49: TOTAL PLANT PRODUCTION ( in 000 lbs) | B49: =B24+E24+H24+B47+E47+H47 -> 34900 | C49: =C24+F24+I24+C47+F47+I47 -> 15776 | D49: =D24+G24+J24+D47+G47+J47 -> 116000
A51: Variable Costs - Material | B51: Purchase Price/lb * Yield Factor * Scrap Factor * Mix = Std. Cost Contribution
A53: Production Plan: | B53: Pounds (000) | C53: Product Split
A54: Ceramics | B54: ='2025 Summary'!$D$7 -> 30000 | C54: =B54/$B$60 -> 0.85959885 | E54: =9*400000*7 -> 25200000
A55: CG280 | B55: 0 | C55: =B55/$B$60 -> 0
A56: CG300 | B56: 0 | C56: =B56/$B$60 -> 0
A57: XXX | B57: 0 | C57: =B57/$B$60 -> 0
A58: HA PELLETS | B58: ='2025 Summary'!$E$7 -> 4900 | C58: =B58/$B$60 -> 0.14040115
B59: 0 | C59: =B59/$B$60 -> 0
A60: Total | B60: =SUM(B54:B59) -> 34900 | C60: =B60/$B$60 -> 1
C62: Yield Factor | G62: Mix %
A63: Local Kaolin | B63: Price ($/Ton) | C63: Ceramics | D63: CG280 | E63: CG300 | F63: XXX | G63: HA Pellets | H63: Ceramics | I63: CG280 | J63: CG300 | K63: XXX | L63: HA Pellets
A64: Arcilla (local kaolin) 30012 | B64: =11.89*2 -> 23.78 | C64: =$C$76*H64 -> 0 | D64: =$C$86*I64 -> 0 | E64: =$G$86*J64 -> 0 | F64: =$K$86*K64 -> 0 | G64: =$K$86*L64 -> 0 | H64: 0 | I64: 0 | J64: 0 | K64: 0 | L64: 0
B65: 0 | C65: =$C$76*H65 -> 0 | D65: =$C$86*I65 -> 0 | E65: =$G$86*J65 -> 0 | F65: =$K$86*K65 -> 0 | G65: =$K$86*L65 -> 0 | H65: 0 | I65: 0 | J65: 0 | K65: 0 | L65: 0
C66: =SUM(C64:C65) -> 0 | D66: =SUM(D64:D65) -> 0 | E66: =SUM(E64:E65) -> 0 | F66: =SUM(F64:F65) -> 0 | G66: =SUM(G64:G65) -> 0
A67: Bauxite:
A68: Rusal (30008) | B68: 0 | C68: =$C$77*H68 -> 0 | D68: =$C$87*I68 -> 0 | E68: =$G$87*J68 -> 0 | F68: =$K$87*K68 -> 0 | G68: =$K$87*L68 -> 0 | H68: 0 | I68: 0 | J68: 0 | K68: 0 | L68: 0
A69: Kaolin - CE Calcined (30060) | B69: =116.72*2 -> 233.44 | C69: =$C$77*H69 -> 0 | D69: =$C$87*I69 -> 0 | E69: =$G$87*J69 -> 0 | F69: =$K$87*K69 -> 0 | G69: =$K$87*L69 -> 0 | H69: 0 | I69: 0 | J69: 0 | K69: 0 | L69: 0
B70: 0 | C70: 0 | D70: =$C$87*I70 -> 0 | E70: =$G$87*J70 -> 0 | F70: =$K$87*K70 -> 0 | G70: =$K$87*L70 -> 0 | H70: 0 | I70: 0 | J70: 0 | K70: 0 | L70: 0
B71: 0 | C71: 0 | D71: =$C$87*I71 -> 0 | E71: =$G$87*J71 -> 0 | F71: =$K$87*K71 -> 0 | G71: =$K$87*L71 -> 0 | H71: 0 | I71: 0 | J71: 0 | K71: 0 | L71: 0
C72: =SUM(C68:C71) -> 0 | D72: =SUM(D68:D71) -> 0 | E72: =SUM(E68:E71) -> 0 | F72: =SUM(F68:F71) -> 0 | G72: =SUM(G68:G71) -> 0
B74: Ceramics | F74: CG280
B75: Price ($/lb) | C75: Yield Factor | D75: Std $ Contrib | F75: Price ($/lb) | G75: Yield Factor | H75: Std $ Contrib
A76: Local Kaolin | B76: =0.011 -> 0.011 | C76: =AVERAGE(3.6826,3.5997, 2.6808) -> 3.3210333 | D76: =B76*C76 -> 0.036531367 | F76: 0 | G76: 0 | H76: =F76*G76 -> 0
A77: Bauxite | B77: =($B$68*$H$68+$B$69*$H$69+$B$70*$H$70+$B$71*$H$71)/2000 -> 0 | C77: 0 | D77: =B77*C77 -> 0 | F77: =($B$68*$L$68+$B$69*$L$69+$B$70*$L$70+$B$71*$L$71)/2000 -> 0 | G77: 0 | H77: =F77*G77 -> 0
A78: PVA (30017) | B78: 1.838 | C78: 0.0081 | D78: =B78*C78 -> 0.0148878 | F78: =+B78 -> 1.838 | G78: 0 | H78: =F78*G78 -> 0
A79: Dispersant (30011) | B79: =750/1000 -> 0.75 | C79: 0.0161 | D79: =B79*C79 -> 0.012075 | F79: =+B79 -> 0.75 | G79: 0
A80: Ammonia (30000) | B80: =157.43/1000 -> 0.15743 | C80: 0.0157 | D80: =B80*C80 -> 0.002471651 | F80: =+B80 -> 0.15743 | G80: 0 | H80: 0
A82: Total Material Cost Per Pound | D82: =SUM(D76:D80) -> 0.065965818 | H82: =SUM(H76:H80) -> 0
B84: CG300 | F84: XXX | J84: HA Pellets
B85: Price ($/lb) | C85: Yield Factor/BOM | D85: Std $ Contrib | F85: Price ($/lb) | G85: Yield Factor | H85: Std $ Contrib | J85: Price ($/lb) | K85: Yield Factor | L85: Std $ Contrib
A86: Local kaolin | B86: =($B$64*$I$64+$B$65*$I$65)/2000 -> 0 | C86: 0 | D86: =B86*C86 -> 0 | F86: =($B$64*$J$64+$B$65*$J$65)/2000 -> 0 | G86: 0 | H86: =F86*G86 -> 0 | J86: =($B$64*$K$64+$B$65*$K$65)/2000 -> 0 | K86: 0 | L86: =J86*K86 -> 0
A87: Bauxite | B87: =($B$68*$I$68+$B$69*$I$69+$B$70*$I$70+$B$71*$I$71)/2000 -> 0 | C87: 0 | D87: =B87*C87 -> 0 | F87: =($B$68*$J$68+$B$69*$J$69+$B$70*$J$70+$B$71*$J$71)/2000 -> 0 | G87: 0 | H87: =F87*G87 -> 0 | J87: =($B$68*$K$68+$B$69*$K$69+$B$70*$K$70+$B$71*$K$71)/2000 -> 0 | K87: 0 | L87: =J87*K87 -> 0
A88: PVA (30017) | B88: 2.54 | C88: 0 | D88: =B88*C88 -> 0 | F88: =+B88 -> 2.54 | G88: 0 | H88: =F88*G88 -> 0 | J88: 1.964 | K88: 0.020848164 | L88: =J88*K88 -> 0.040945794
A89: Dispersant (30011) | B89: =750/1000 -> 0.75 | C89: 0 | D89: =B89*C89 -> 0 | F89: =+B89 -> 0.75 | G89: 0 | H89: =F89*G89 -> 0 | J89: 0.591 | K89: 0.0031014518 | L89: =J89*K89 -> 0.001832958
A90: Ammonia (30000) | B90: =157.43/1000 -> 0.15743 | C90: 0 | D90: =B90*C90 -> 0 | F90: =+B90 -> 0.15743 | G90: 0 | H90: =F90*G90 -> 0 | J90: 0.105 | K90: 0.1 | L90: =J90*K90 -> 0.0105
A91: Defoamer (30010) | C91: 0 | D91: =B91*C91 -> 0 | F91: =+B91 -> 0 | G91: 0 | H91: =F91*G91 -> 0 | J91: 1.027 | K91: 0.0021752348 | L91: =J91*K91 -> 0.0022339662
A92: Ultrasurf (30341) | C92: 0 | D92: =B92*C92 -> 0 | F92: =+B92 -> 0 | G92: 0 | H92: =F92*G92 -> 0 | J92: 1.389 | K92: 0.0023312553 | L92: =J92*K92 -> 0.0032381137
A93: HA Pallets (30350) | J93: 18.84 | K93: 0.0006 | L93: =J93*K93 -> 0.011304
A94: HA Bag Protectors (30342) | J94: 1.33 | K94: 0.0006 | L94: =J94*K94 -> 0.000798
D95: 0 | H95: 0 | L95: 0
A96: Total Material Cost Per Pound | D96: =SUM(D86:D95) -> 0 | H96: =SUM(H86:H95) -> 0 | L96: =SUM(L86:L95) -> 0.070852832
A98: Variable Cost - Production/R&M Labor & Benefits
F99: W&S Carve Out of Production Labor
A100: Labor Split:
B101: Prod. Plan (000) | C101: Rate (000 lbs/day) | D101: Kiln Days | E101: % Split | F101: 1 | G101: <--EEs | Hrs--> | H101: =(F101*C202*C204)+((F101*C202*C204*D113)) -> 345498296
A102: Ceramics | B102: =B54 -> 30000 | C102: 550 | D102: =B102/C102 -> 54.545455 | E102: =D102/D$108 -> 0.55045872 | F102: =(F101*C202*C204*C116)+((F101*C202*C204*D113)*C118) -> 18643341 | G102: Payroll | H102: =F102/$H$101 -> 0.053960732 | I102: Rate will be dependant on prodcut size
A103: CG280 | B103: =B55 -> 0 | C103: 0 | D103: 0 | E103: =D103/D$108 -> 0 | F103: =F102*C206 -> 5593002.3 | G103: IPC | H103: =F103/$H$101 -> 0.01618822
A104: CG300 | B104: =B56 -> 0 | C104: 0 | D104: 0 | E104: =D104/D$108 -> 0
A105: XXX | B105: =B57 -> 0 | C105: 0 | D105: 0 | E105: =D105/D$108 -> 0
A106: HA PELLETS | B106: =B58 -> 4900 | C106: 110 | D106: =B106/C106 -> 44.545455 | E106: =D106/D$108 -> 0.44954128 | I106: Reduced daily rate to 110 vs. 150
B107: =B59 -> 0 | C107: 0 | D107: 0 | E107: =D107/D$108 -> 0
B108: =SUM(B102:B107) -> 34900 | C108: =B108/D108 -> 352.20183 | D108: =SUM(D102:D107) -> 99.090909 | E108: =D108/D$108 -> 1
A109: HA Group
B112: Jan | C112: Feb | D112: Mar | E112: Apr | F112: May | G112: Jun | H112: Jul
A113: Production Labor | B113: 119702.77 | C113: 140371.43 | D113: 166103.95 | E113: 166766.86 | F113: 105842.43 | G113: 147383.65 | H113: 163283.07
A114: R & M Labor | B114: 15222.93 | C114: 23913.55 | D114: 19670.79 | E114: 41336.57 | F114: 23672.31 | G114: 9419.99 | H114: 18308.82
A115: IPC | B115: 11228.99 | C115: 10794.51 | D115: 10146.4 | E115: 8112.73 | F115: -1917.2 | G115: 49379.56 | H115: 50660.85
A116: Supervision | B116: 3928.57 | C116: -3928.57 | D116: 0 | E116: -1311.46 | F116: 841.1 | G116: 0 | H116: 0
A117: Temp | B117: 37953 | C117: 21274 | D117: 55365 | E117: 3960 | F117: 26641 | G117: 11698 | H117: 35168
...

Sheet Feb
A1: TOOMSBORO STANDARD 2025
B3: CERAMICS | E3: CG 280 | H3: CG 300
B4: 25 Standard | C4: 23 Actual | D4: 20 Standard | E4: =$B$4 -> 25 Standard | F4: =+C4 -> 23 Actual | G4: =+D4 -> 20 Standard | H4: =+B4 -> 25 Standard | I4: =+C4 -> 23 Actual | J4: =+D4 -> 20 Standard
C5: (Jan-Sept) | F5: (Jan-Sept) | I5: (Jan-Sept)
A6: Materials | B6: =IF(B24<>0,$D$82,0) -> 0 | C6: 0.0585 | D6: 0.04156581 | E6: =+H82 -> 0 | F6: 0 | G6: 0 | H6: =+D96 -> 0 | I6: 0 | J6: 0
A7: Electricity | B7: =IF(B24<>0,$D$163,0) -> 0 | C7: 0.0105 | D7: 0.020277329 | E7: =G163 -> 0.0198372 | F7: 0 | G7: 0 | H7: =J163 -> 0.0198372 | I7: 0 | J7: 0
A8: Gas | B8: =IF(B24<>0,$D$164,0) -> 0 | C8: 0.0156 | D8: 0.014965 | E8: =G164 -> 0.0171 | F8: 0 | G8: 0 | H8: =J164 -> 0.0171 | I8: 0 | J8: 0
A9: R&M Supplies and Service | B9: =IF(B24<>0,$J$177,0) -> 0 | C9: 0.0192 | D9: 0.015915789 | E9: =$H$177 -> 0.03 | F9: 0 | G9: 0 | H9: =$H$177 -> 0.03 | I9: 0 | J9: 0
A10: Manufacturing Supplies | B10: =IF(B24<>0,$J$181,0) -> 0 | C10: 0.0008 | D10: 0.0026315789 | E10: =$H$181 -> 0.0055102041 | F10: 0 | G10: 0 | H10: =$H$181 -> 0.0055102041 | I10: 0 | J10: 0
A11: Other variable | B11: =IF(B24<>0,$J$184,0) -> 0 | C11: 0.0058 | D11: 0.0094736842 | E11: =$H$184 -> 0.01122449 | F11: 0 | G11: 0 | H11: =$H$184 -> 0.01122449 | I11: 0 | J11: 0
A12: Total Variable Costs | B12: =SUM(B6:B11) -> 0 | C12: =SUM(C6:C11) -> 0.1104 | D12: =SUM(D6:D11) -> 0.10482919 | E12: =SUM(E6:E11) -> 0.083671894 | F12: =SUM(F6:F11) -> 0 | G12: =SUM(G6:G11) -> 0 | H12: =SUM(H6:H11) -> 0.083671894 | I12: =SUM(I6:I11) -> 0 | J12: =SUM(J6:J11) -> 0
A14: Production Labor | B14: =IF($B$24<>0,$F$152/B24/1000,0) -> 0 | C14: 0.0246 | D14: 0.0073599375 | E14: =$D$124*$E$108/$B$49/1000 -> 0.00093026761 | F14: 0 | G14: 0 | H14: =$D$124*$E$108/$B$49/1000 -> 0.00093026761 | I14: 0 | J14: 0
A15: Repairs & Maintenance Labor | B15: =IF($B$24<>0,$F$153/$B$24/1000,0) -> 0 | C15: 0.009 | D15: 0.0042419375 | E15: =$H$124*$E$108/$B$49/1000 -> 0 | F15: 0 | G15: 0 | H15: =$H$124*$E$108/$B$49/1000 -> 0 | I15: 0 | J15: 0
A16: Indirect Payroll Costs (Benefits) | B16: =IF($B$24<>0,$F$155/$B$24/1000,0) -> 0 | C16: 0.0079 | D16: 0.0053897125 | E16: =$D$131*$E$108/$B$49/1000 -> 0 | F16: 0 | G16: 0 | H16: =$D$131*$E$108/$B$49/1000 -> 0 | I16: 0 | J16: 0
A17: Supervision | B17: =IF($B$24<>0,$F$154/$B$24/1000,0) -> 0 | C17: 0 | D17: 0.0026778947 | E17: =$F$194 -> 0 | F17: 0 | G17: 0 | H17: =$F$194 -> 0 | I17: 0 | J17: 0
A18: Depreciation | B18: =IF($B$24<>0,$B$196/$B$49/1000,0) -> 0 | C18: 0.0027 | D18: 0.1672 | E18: =$F$196 -> 0.055866735 | F18: 0 | G18: 0 | H18: =$F$196 -> 0.055866735 | I18: 0 | J18: 0
A19: Insurance & Taxes | B19: =IF($B$24<>0,$B$195/$B$49/1000,0) -> 0 | C19: 0.012 | D19: 0.012884211 | E19: =$F$195 -> 0.23436735 | F19: 0 | G19: 0 | H19: =$F$195 -> 0.23436735 | I19: 0 | J19: 0
A20: Total Fixed Costs | B20: =SUM(B14:B19) -> 0 | C20: =SUM(C14:C19) -> 0.0562 | D20: =SUM(D14:D19) -> 0.19975369 | E20: =SUM(E14:E19) -> 0.29116435 | F20: =SUM(F14:F19) -> 0 | G20: =SUM(G14:G19) -> 0 | H20: =SUM(H14:H19) -> 0.29116435 | I20: =SUM(I14:I19) -> 0 | J20: =SUM(J14:J19) -> 0
A22: TOTAL COSTS PER POUND | B22: =B12+B20 -> 0 | C22: =C12+C20 -> 0.1666 | D22: =D12+D20 -> 0.30458288 | E22: =E12+E20 -> 0.37483624 | F22: =F12+F20 -> 0 | G22: =G12+G20 -> 0 | H22: =H12+H20 -> 0.37483624 | I22: =I12+I20 -> 0 | J22: =J12+J20 -> 0
A24: PRODUCTION ( in 000 lbs ) | B24: =+B54 -> 0 | C24: 0 | D24: 80000 | E24: =+B55 -> 0 | F24: 0 | G24: 0 | H24: =+B56 -> 0 | I24: 0 | J24: 0
B26: XXX | E26: HA PELLETS
B27: =$B$4 -> 25 Standard | C27: =+C4 -> 23 Actual | D27: =+D4 -> 20 Standard | E27: 24 Standard | F27: 23 Actual | G27: 22 Standard | H27: =+B27 -> 25 Standard | I27: =+C27 -> 23 Actual | J27: =+D27 -> 20 Standard
C28: (Jan-Sept) | F28: (Jan-Aug)
A29: Materials | B29: =D82 -> 0.065965818 | C29: 0 | D29: 0 | E29: =IF(E47<>0,$L$96,0) -> 0.070852832 | F29: 0.078 | G29: 0.06025968 | H29: 0 | I29: 0 | J29: 0
A30: Electricity | B30: =D169 -> 0 | C30: 0 | D30: 0 | E30: =IF(E47<>0,$G$169,0) -> 0.043918811 | F30: 0.0432 | G30: 0.026879418 | H30: 0 | I30: 0 | J30: 0
A31: Gas | B31: =D170 -> 0 | C31: 0 | D31: 0 | E31: =IF(E47<>0,$G$170,0) -> 0.026 | F31: 0.019 | G31: 0.028567 | H31: =J170 -> 0 | I31: 0 | J31: 0
A32: R&M Supplies and Service | B32: =IF($B$47<>0,$H$177,0) -> 0 | C32: 0 | D32: 0 | E32: =IF(E47<>0,$H$177,0) -> 0.03 | F32: 0.0298 | G32: 0.027777778 | H32: 0 | I32: 0 | J32: 0
A33: Manufacturing Supplies | B33: =IF($B$47<>0,$H$181,0) -> 0 | C33: 0 | D33: 0 | E33: =IF(E47<>0,$H$181,0) -> 0.0055102041 | F33: 0.0012 | G33: 0.0069444444 | H33: 0 | I33: 0 | J33: 0
A34: Other variable | B34: =IF($B$47<>0,$H$184,0) -> 0 | C34: 0 | D34: 0 | E34: =IF(E47<>0,$H$184,0) -> 0.01122449 | F34: 0.0139 | G34: 0.0125 | H34: 0 | I34: 0 | J34: 0
A35: Total Variable Costs | B35: =SUM(B29:B34) -> 0.065965818 | C35: =SUM(C29:C34) -> 0 | D35: =SUM(D29:D34) -> 0 | E35: =SUM(E29:E34) -> 0.18750634 | F35: =SUM(F29:F34) -> 0.1851 | G35: =SUM(G29:G34) -> 0.16292832 | H35: =SUM(H29:H34) -> 0 | I35: =SUM(I29:I34) -> 0 | J35: =SUM(J29:J34) -> 0
A37: Production Labor | B37: =$D$124*$E$108/$B$49/1000 -> 0.00093026761 | C37: 0 | D37: 0 | E37: =IF($E$47<>0,$F$127/$E$47/1000,0) -> 0.040001507 | F37: 0.0353 | G37: 0.02156921 | H37: 0 | I37: 0 | J37: 0
A38: Repairs & Maintenance Labor | B38: =$H$124*$E$108/$B$49/1000 -> 0 | C38: 0 | D38: 0 | E38: =IF($E$47<>0,$F$128/$E$47/1000,0) -> 0.0048061173 | F38: 0.0067 | G38: 0.0051700857 | H38: 0 | I38: 0 | J38: 0
A39: Indirect Payroll Costs (Benefits) | B39: =$D$131*$E$108/$B$49/1000 -> 0 | C39: 0 | D39: 0 | E39: =IF($E$47<>0,$F$130/$E$47/1000,0) -> 0.012994211 | F39: 0.0112 | G39: 0.0080162316 | H39: 0 | I39: 0 | J39: 0
A40: Supervision | B40: =IF($B$49<>0,$F$194,0) -> 0 | C40: 0 | D40: 0 | E40: =IF($E$47<>0,$F$129/$E$47/1000,0) -> 0 | F40: 0 | G40: 0.00047638889 | H40: 0 | I40: 0 | J40: 0
A41: Depreciation | B41: =IF($B$49<>0,$F$196,0) -> 0.055866735 | C41: 0 | D41: 0 | E41: =IF($E$47<>0,$B$196/$B$49/1000/4,0) -> 0.0011638903 | F41: 0.0085 | G41: 0.0056777778 | H41: 0 | I41: 0 | J41: 0
A42: Insurance & Taxes | B42: =IF($B$49<>0,$F$195,0) -> 0.23436735 | C42: 0 | D42: 0 | E42: =IF($E$47<>0,$B$195/$B$49/1000/4,0) -> 0.0048826531 | F42: 0.0362 | G42: 0.025861111 | H42: 0 | I42: 0 | J42: 0
A43: Total Fixed Costs | B43: =SUM(B37:B42) -> 0.29116435 | C43: =SUM(C37:C42) -> 0 | D43: =SUM(D37:D42) -> 0 | E43: =SUM(E37:E42) -> 0.063848379 | F43: =SUM(F37:F42) -> 0.0979 | G43: =SUM(G37:G42) -> 0.066770805 | H43: =SUM(H37:H42) -> 0 | I43: =SUM(I37:I42) -> 0 | J43: =SUM(J37:J42) -> 0
A44: Excess Costs | F44: -0.0455
A45: TOTAL COSTS PER POUND | B45: =B35+B43 -> 0.35713017 | C45: =C35+C43 -> 0 | D45: 0.19962946 | E45: =E35+E43+E44 -> 0.25135472 | F45: =F35+F43+F44 -> 0.2375 | G45: =+G35+G43 -> 0.22969913 | H45: =H35+H43 -> 0 | I45: =I35+I43 -> 0 | J45: =J35+J43 -> 0
A47: PRODUCTION ( in 000 lbs ) | B47: =+B57 -> 0 | C47: 0 | D47: 0 | E47: =+B58 -> 4900 | F47: 15776 | G47: 36000 | H47: =+B59 -> 0 | I47: 0 | J47: 0
A49: TOTAL PLANT PRODUCTION ( in 000 lbs) | B49: =B24+E24+H24+B47+E47+H47 -> 4900 | C49: =C24+F24+I24+C47+F47+I47 -> 15776 | D49: =D24+G24+J24+D47+G47+J47 -> 116000
A51: Variable Costs - Material | B51: Purchase Price/lb * Yield Factor * Scrap Factor * Mix = Std. Cost Contribution
A53: Production Plan: | B53: Pounds (000) | C53: Product Split
A54: Ceramics | B54: ='2025 Summary'!$D$8 -> 0 | C54: =B54/$B$60 -> 0 | E54: =9*400000*7 -> 25200000
A55: CG280 | B55: 0 | C55: =B55/$B$60 -> 0
A56: CG300 | B56: 0 | C56: =B56/$B$60 -> 0
A57: XXX | B57: 0 | C57: =B57/$B$60 -> 0
A58: HA PELLETS | B58: ='2025 Summary'!$E$8 -> 4900 | C58: =B58/$B$60 -> 1
B59: 0 | C59: =B59/$B$60 -> 0
A60: Total | B60: =SUM(B54:B59) -> 4900 | C60: =B60/$B$60 -> 1
C62: Yield Factor | G62: Mix %
A63: Local Kaolin | B63: Price ($/Ton) | C63: Ceramics | D63: CG280 | E63: CG300 | F63: XXX | G63: HA Pellets | H63: Ceramics | I63: CG280 | J63: CG300 | K63: XXX | L63: HA Pellets
A64: Arcilla (local kaolin) 30012 | B64: =11.89*2 -> 23.78 | C64: =$C$76*H64 -> 0 | D64: =$C$86*I64 -> 0 | E64: =$G$86*J64 -> 0 | F64: =$K$86*K64 -> 0 | G64: =$K$86*L64 -> 0 | H64: 0 | I64: 0 | J64: 0 | K64: 0 | L64: 0
B65: 0 | C65: =$C$76*H65 -> 0 | D65: =$C$86*I65 -> 0 | E65: =$G$86*J65 -> 0 | F65: =$K$86*K65 -> 0 | G65: =$K$86*L65 -> 0 | H65: 0 | I65: 0 | J65: 0 | K65: 0 | L65: 0
C66: =SUM(C64:C65) -> 0 | D66: =SUM(D64:D65) -> 0 | E66: =SUM(E64:E65) -> 0 | F66: =SUM(F64:F65) -> 0 | G66: =SUM(G64:G65) -> 0
A67: Bauxite:
A68: Rusal (30008) | B68: 0 | C68: =$C$77*H68 -> 0 | D68: =$C$87*I68 -> 0 | E68: =$G$87*J68 -> 0 | F68: =$K$87*K68 -> 0 | G68: =$K$87*L68 -> 0 | H68: 0 | I68: 0 | J68: 0 | K68: 0 | L68: 0
A69: Kaolin - CE Calcined (30060) | B69: =116.72*2 -> 233.44 | C69: =$C$77*H69 -> 0 | D69: =$C$87*I69 -> 0 | E69: =$G$87*J69 -> 0 | F69: =$K$87*K69 -> 0 | G69: =$K$87*L69 -> 0 | H69: 0 | I69: 0 | J69: 0 | K69: 0 | L69: 0
B70: 0 | C70: 0 | D70: =$C$87*I70 -> 0 | E70: =$G$87*J70 -> 0 | F70: =$K$87*K70 -> 0 | G70: =$K$87*L70 -> 0 | H70: 0 | I70: 0 | J70: 0 | K70: 0 | L70: 0
B71: 0 | C71: 0 | D71: =$C$87*I71 -> 0 | E71: =$G$87*J71 -> 0 | F71: =$K$87*K71 -> 0 | G71: =$K$87*L71 -> 0 | H71: 0 | I71: 0 | J71: 0 | K71: 0 | L71: 0
C72: =SUM(C68:C71) -> 0 | D72: =SUM(D68:D71) -> 0 | E72: =SUM(E68:E71) -> 0 | F72: =SUM(F68:F71) -> 0 | G72: =SUM(G68:G71) -> 0
B74: Ceramics | F74: CG280
B75: Price ($/lb) | C75: Yield Factor | D75: Std $ Contrib | F75: Price ($/lb) | G75: Yield Factor | H75: Std $ Contrib
A76: Local Kaolin | B76: =0.011 -> 0.011 | C76: =AVERAGE(3.6826,3.5997, 2.6808) -> 3.3210333 | D76: =B76*C76 -> 0.036531367 | F76: 0 | G76: 0 | H76: =F76*G76 -> 0
A77: Bauxite | B77: =($B$68*$H$68+$B$69*$H$69+$B$70*$H$70+$B$71*$H$71)/2000 -> 0 | C77: 0 | D77: =B77*C77 -> 0 | F77: =($B$68*$L$68+$B$69*$L$69+$B$70*$L$70+$B$71*$L$71)/2000 -> 0 | G77: 0 | H77: =F77*G77 -> 0
A78: PVA (30017) | B78: 1.838 | C78: 0.0081 | D78: =B78*C78 -> 0.0148878 | F78: =+B78 -> 1.838 | G78: 0 | H78: =F78*G78 -> 0
A79: Dispersant (30011) | B79: =750/1000 -> 0.75 | C79: 0.0161 | D79: =B79*C79 -> 0.012075 | F79: =+B79 -> 0.75 | G79: 0
A80: Ammonia (30000) | B80: =157.43/1000 -> 0.15743 | C80: 0.0157 | D80: =B80*C80 -> 0.002471651 | F80: =+B80 -> 0.15743 | G80: 0 | H80: 0
A82: Total Material Cost Per Pound | D82: =SUM(D76:D80) -> 0.065965818 | H82: =SUM(H76:H80) -> 0
B84: CG300 | F84: XXX | J84: HA Pellets
B85: Price ($/lb) | C85: Yield Factor/BOM | D85: Std $ Contrib | F85: Price ($/lb) | G85: Yield Factor | H85: Std $ Contrib | J85: Price ($/lb) | K85: Yield Factor | L85: Std $ Contrib
A86: Local kaolin | B86: =($B$64*$I$64+$B$65*$I$65)/2000 -> 0 | C86: 0 | D86: =B86*C86 -> 0 | F86: =($B$64*$J$64+$B$65*$J$65)/2000 -> 0 | G86: 0 | H86: =F86*G86 -> 0 | J86: =($B$64*$K$64+$B$65*$K$65)/2000 -> 0 | K86: 0 | L86: =J86*K86 -> 0
A87: Bauxite | B87: =($B$68*$I$68+$B$69*$I$69+$B$70*$I$70+$B$71*$I$71)/2000 -> 0 | C87: 0 | D87: =B87*C87 -> 0 | F87: =($B$68*$J$68+$B$69*$J$69+$B$70*$J$70+$B$71*$J$71)/2000 -> 0 | G87: 0 | H87: =F87*G87 -> 0 | J87: =($B$68*$K$68+$B$69*$K$69+$B$70*$K$70+$B$71*$K$71)/2000 -> 0 | K87: 0 | L87: =J87*K87 -> 0
A88: PVA (30017) | B88: 2.54 | C88: 0 | D88: =B88*C88 -> 0 | F88: =+B88 -> 2.54 | G88: 0 | H88: =F88*G88 -> 0 | J88: 1.964 | K88: 0.020848164 | L88: =J88*K88 -> 0.040945794
A89: Dispersant (30011) | B89: =750/1000 -> 0.75 | C89: 0 | D89: =B89*C89 -> 0 | F89: =+B89 -> 0.75 | G89: 0 | H89: =F89*G89 -> 0 | J89: 0.591 | K89: 0.0031014518 | L89: =J89*K89 -> 0.001832958
A90: Ammonia (30000) | B90: =157.43/1000 -> 0.15743 | C90: 0 | D90: =B90*C90 -> 0 | F90: =+B90 -> 0.15743 | G90: 0 | H90: =F90*G90 -> 0 | J90: 0.105 | K90: 0.1 | L90: =J90*K90 -> 0.0105
A91: Defoamer (30010) | C91: 0 | D91: =B91*C91 -> 0 | F91: =+B91 -> 0 | G91: 0 | H91: =F91*G91 -> 0 | J91: 1.027 | K91: 0.0021752348 | L91: =J91*K91 -> 0.0022339662
A92: Ultrasurf (30341) | C92: 0 | D92: =B92*C92 -> 0 | F92: =+B92 -> 0 | G92: 0 | H92: =F92*G92 -> 0 | J92: 1.389 | K92: 0.0023312553 | L92: =J92*K92 -> 0.0032381137
A93: HA Pallets (30350) | J93: 18.84 | K93: 0.0006 | L93: =J93*K93 -> 0.011304
A94: HA Bag Protectors (30342) | J94: 1.33 | K94: 0.0006 | L94: =J94*K94 -> 0.000798
D95: 0 | H95: 0 | L95: 0
A96: Total Material Cost Per Pound | D96: =SUM(D86:D95) -> 0 | H96: =SUM(H86:H95) -> 0 | L96: =SUM(L86:L95) -> 0.070852832
A98: Variable Cost - Production/R&M Labor & Benefits
F99: W&S Carve Out of Production Labor
A100: Labor Split:
B101: Prod. Plan (000) | C101: Rate (000 lbs/day) | D101: Kiln Days | E101: % Split | F101: 1 | G101: <--EEs | Hrs--> | H101: =(F101*C202*C204)+((F101*C202*C204*D113)) -> 345498296
A102: Ceramics | B102: =B54 -> 0 | C102: 550 | D102: =B102/C102 -> 0 | E102: =D102/D$108 -> 0 | F102: =(F101*C202*C204*C116)+((F101*C202*C204*D113)*C118) -> 18643341 | G102: Payroll | H102: =F102/$H$101 -> 0.053960732 | I102: Rate will be dependant on prodcut size
A103: CG280 | B103: =B55 -> 0 | C103: 0 | D103: 0 | E103: =D103/D$108 -> 0 | F103: =F102*C206 -> 5593002.3 | G103: IPC | H103: =F103/$H$101 -> 0.01618822
A104: CG300 | B104: =B56 -> 0 | C104: 0 | D104: 0 | E104: =D104/D$108 -> 0
A105: XXX | B105: =B57 -> 0 | C105: 0 | D105: 0 | E105: =D105/D$108 -> 0
A106: HA PELLETS | B106: =B58 -> 4900 | C106: 110 | D106: =B106/C106 -> 44.545455 | E106: =D106/D$108 -> 1 | I106: Reduced daily rate to 110 vs. 150
B107: =B59 -> 0 | C107: 0 | D107: 0 | E107: =D107/D$108 -> 0
B108: =SUM(B102:B107) -> 4900 | C108: =B108/D108 -> 110 | D108: =SUM(D102:D107) -> 44.545455 | E108: =D108/D$108 -> 1
A109: HA Group
B112: Jan | C112: Feb | D112: Mar | E112: Apr | F112: May | G112: Jun | H112: Jul
A113: Production Labor | B113: 119702.77 | C113: 140371.43 | D113: 166103.95 | E113: 166766.86 | F113: 105842.43 | G113: 147383.65 | H113: 163283.07
A114: R & M Labor | B114: 15222.93 | C114: 23913.55 | D114: 19670.79 | E114: 41336.57 | F114: 23672.31 | G114: 9419.99 | H114: 18308.82
A115: IPC | B115: 11228.99 | C115: 10794.51 | D115: 10146.4 | E115: 8112.73 | F115: -1917.2 | G115: 49379.56 | H115: 50660.85
A116: Supervision | B116: 3928.57 | C116: -3928.57 | D116: 0 | E116: -1311.46 | F116: 841.1 | G116: 0 | H116: 0
A117: Temp | B117: 37953 | C117: 21274 | D117: 55365 | E117: 3960 | F117: 26641 | G117: 11698 | H117: 35168
...

Sheet Mar
A1: TOOMSBORO STANDARD 2025
B3: CERAMICS | E3: CG 280 | H3: CG 300
B4: 25 Standard | C4: 23 Actual | D4: 20 Standard | E4: =$B$4 -> 25 Standard | F4: =+C4 -> 23 Actual | G4: =+D4 -> 20 Standard | H4: =+B4 -> 25 Standard | I4: =+C4 -> 23 Actual | J4: =+D4 -> 20 Standard
C5: (Jan-Sept) | F5: (Jan-Sept) | I5: (Jan-Sept)
A6: Materials | B6: =IF(B24<>0,$D$82,0) -> 0 | C6: 0.0585 | D6: 0.04156581 | E6: =+H82 -> 0 | F6: 0 | G6: 0 | H6: =+D96 -> 0 | I6: 0 | J6: 0
A7: Electricity | B7: =IF(B24<>0,$D$163,0) -> 0 | C7: 0.0105 | D7: 0.020277329 | E7: =G163 -> 0.0198372 | F7: 0 | G7: 0 | H7: =J163 -> 0.0198372 | I7: 0 | J7: 0
A8: Gas | B8: =IF(B24<>0,$D$164,0) -> 0 | C8: 0.0156 | D8: 0.014965 | E8: =G164 -> 0.0171 | F8: 0 | G8: 0 | H8: =J164 -> 0.0171 | I8: 0 | J8: 0
A9: R&M Supplies and Service | B9: =IF(B24<>0,$J$177,0) -> 0 | C9: 0.0192 | D9: 0.015915789 | E9: =$H$177 -> 0.03 | F9: 0 | G9: 0 | H9: =$H$177 -> 0.03 | I9: 0 | J9: 0
A10: Manufacturing Supplies | B10: =IF(B24<>0,$J$181,0) -> 0 | C10: 0.0008 | D10: 0.0026315789 | E10: =$H$181 -> 0.0055102041 | F10: 0 | G10: 0 | H10: =$H$181 -> 0.0055102041 | I10: 0 | J10: 0
A11: Other variable | B11: =IF(B24<>0,$J$184,0) -> 0 | C11: 0.0058 | D11: 0.0094736842 | E11: =$H$184 -> 0.01122449 | F11: 0 | G11: 0 | H11: =$H$184 -> 0.01122449 | I11: 0 | J11: 0
A12: Total Variable Costs | B12: =SUM(B6:B11) -> 0 | C12: =SUM(C6:C11) -> 0.1104 | D12: =SUM(D6:D11) -> 0.10482919 | E12: =SUM(E6:E11) -> 0.083671894 | F12: =SUM(F6:F11) -> 0 | G12: =SUM(G6:G11) -> 0 | H12: =SUM(H6:H11) -> 0.083671894 | I12: =SUM(I6:I11) -> 0 | J12: =SUM(J6:J11) -> 0
A14: Production Labor | B14: =IF($B$24<>0,$F$152/B24/1000,0) -> 0 | C14: 0.0246 | D14: 0.0073599375 | E14: =$D$124*$E$108/$B$49/1000 -> 0.00093026761 | F14: 0 | G14: 0 | H14: =$D$124*$E$108/$B$49/1000 -> 0.00093026761 | I14: 0 | J14: 0
A15: Repairs & Maintenance Labor | B15: =IF($B$24<>0,$F$153/$B$24/1000,0) -> 0 | C15: 0.009 | D15: 0.0042419375 | E15: =$H$124*$E$108/$B$49/1000 -> 0 | F15: 0 | G15: 0 | H15: =$H$124*$E$108/$B$49/1000 -> 0 | I15: 0 | J15: 0
A16: Indirect Payroll Costs (Benefits) | B16: =IF($B$24<>0,$F$155/$B$24/1000,0) -> 0 | C16: 0.0079 | D16: 0.0053897125 | E16: =$D$131*$E$108/$B$49/1000 -> 0 | F16: 0 | G16: 0 | H16: =$D$131*$E$108/$B$49/1000 -> 0 | I16: 0 | J16: 0
A17: Supervision | B17: =IF($B$24<>0,$F$154/$B$24/1000,0) -> 0 | C17: 0 | D17: 0.0026778947 | E17: =$F$194 -> 0 | F17: 0 | G17: 0 | H17: =$F$194 -> 0 | I17: 0 | J17: 0
A18: Depreciation | B18: =IF($B$24<>0,$B$196/$B$49/1000,0) -> 0 | C18: 0.0027 | D18: 0.1672 | E18: =$F$196 -> 0.055866735 | F18: 0 | G18: 0 | H18: =$F$196 -> 0.055866735 | I18: 0 | J18: 0
A19: Insurance & Taxes | B19: =IF($B$24<>0,$B$195/$B$49/1000,0) -> 0 | C19: 0.012 | D19: 0.012884211 | E19: =$F$195 -> 0.23436735 | F19: 0 | G19: 0 | H19: =$F$195 -> 0.23436735 | I19: 0 | J19: 0
A20: Total Fixed Costs | B20: =SUM(B14:B19) -> 0 | C20: =SUM(C14:C19) -> 0.0562 | D20: =SUM(D14:D19) -> 0.19975369 | E20: =SUM(E14:E19) -> 0.29116435 | F20: =SUM(F14:F19) -> 0 | G20: =SUM(G14:G19) -> 0 | H20: =SUM(H14:H19) -> 0.29116435 | I20: =SUM(I14:I19) -> 0 | J20: =SUM(J14:J19) -> 0
A22: TOTAL COSTS PER POUND | B22: =B12+B20 -> 0 | C22: =C12+C20 -> 0.1666 | D22: =D12+D20 -> 0.30458288 | E22: =E12+E20 -> 0.37483624 | F22: =F12+F20 -> 0 | G22: =G12+G20 -> 0 | H22: =H12+H20 -> 0.37483624 | I22: =I12+I20 -> 0 | J22: =J12+J20 -> 0
A24: PRODUCTION ( in 000 lbs ) | B24: =+B54 -> 0 | C24: 0 | D24: 80000 | E24: =+B55 -> 0 | F24: 0 | G24: 0 | H24: =+B56 -> 0 | I24: 0 | J24: 0
B26: XXX | E26: HA PELLETS
B27: =$B$4 -> 25 Standard | C27: =+C4 -> 23 Actual | D27: =+D4 -> 20 Standard | E27: 24 Standard | F27: 23 Actual | G27: 22 Standard | H27: =+B27 -> 25 Standard | I27: =+C27 -> 23 Actual | J27: =+D27 -> 20 Standard
C28: (Jan-Sept) | F28: (Jan-Aug)
A29: Materials | B29: =D82 -> 0.065965818 | C29: 0 | D29: 0 | E29: =IF(E47<>0,$L$96,0) -> 0.070852832 | F29: 0.078 | G29: 0.06025968 | H29: 0 | I29: 0 | J29: 0
A30: Electricity | B30: =D169 -> 0 | C30: 0 | D30: 0 | E30: =IF(E47<>0,$G$169,0) -> 0.043918811 | F30: 0.0432 | G30: 0.026879418 | H30: 0 | I30: 0 | J30: 0
A31: Gas | B31: =D170 -> 0 | C31: 0 | D31: 0 | E31: =IF(E47<>0,$G$170,0) -> 0.026 | F31: 0.019 | G31: 0.028567 | H31: =J170 -> 0 | I31: 0 | J31: 0
A32: R&M Supplies and Service | B32: =IF($B$47<>0,$H$177,0) -> 0 | C32: 0 | D32: 0 | E32: =IF(E47<>0,$H$177,0) -> 0.03 | F32: 0.0298 | G32: 0.027777778 | H32: 0 | I32: 0 | J32: 0
A33: Manufacturing Supplies | B33: =IF($B$47<>0,$H$181,0) -> 0 | C33: 0 | D33: 0 | E33: =IF(E47<>0,$H$181,0) -> 0.0055102041 | F33: 0.0012 | G33: 0.0069444444 | H33: 0 | I33: 0 | J33: 0
A34: Other variable | B34: =IF($B$47<>0,$H$184,0) -> 0 | C34: 0 | D34: 0 | E34: =IF(E47<>0,$H$184,0) -> 0.01122449 | F34: 0.0139 | G34: 0.0125 | H34: 0 | I34: 0 | J34: 0
A35: Total Variable Costs | B35: =SUM(B29:B34) -> 0.065965818 | C35: =SUM(C29:C34) -> 0 | D35: =SUM(D29:D34) -> 0 | E35: =SUM(E29:E34) -> 0.18750634 | F35: =SUM(F29:F34) -> 0.1851 | G35: =SUM(G29:G34) -> 0.16292832 | H35: =SUM(H29:H34) -> 0 | I35: =SUM(I29:I34) -> 0 | J35: =SUM(J29:J34) -> 0
A37: Production Labor | B37: =$D$124*$E$108/$B$49/1000 -> 0.00093026761 | C37: 0 | D37: 0 | E37: =IF($E$47<>0,$F$127/$E$47/1000,0) -> 0.040001507 | F37: 0.0353 | G37: 0.02156921 | H37: 0 | I37: 0 | J37: 0
A38: Repairs & Maintenance Labor | B38: =$H$124*$E$108/$B$49/1000 -> 0 | C38: 0 | D38: 0 | E38: =IF($E$47<>0,$F$128/$E$47/1000,0) -> 0.0048061173 | F38: 0.0067 | G38: 0.0051700857 | H38: 0 | I38: 0 | J38: 0
A39: Indirect Payroll Costs (Benefits) | B39: =$D$131*$E$108/$B$49/1000 -> 0 | C39: 0 | D39: 0 | E39: =IF($E$47<>0,$F$130/$E$47/1000,0) -> 0.012994211 | F39: 0.0112 | G39: 0.0080162316 | H39: 0 | I39: 0 | J39: 0
A40: Supervision | B40: =IF($B$49<>0,$F$194,0) -> 0 | C40: 0 | D40: 0 | E40: =IF($E$47<>0,$F$129/$E$47/1000,0) -> 0 | F40: 0 | G40: 0.00047638889 | H40: 0 | I40: 0 | J40: 0
A41: Depreciation | B41: =IF($B$49<>0,$F$196,0) -> 0.055866735 | C41: 0 | D41: 0 | E41: =IF($E$47<>0,$B$196/$B$49/1000/4,0) -> 0.0011638903 | F41: 0.0085 | G41: 0.0056777778 | H41: 0 | I41: 0 | J41: 0
A42: Insurance & Taxes | B42: =IF($B$49<>0,$F$195,0) -> 0.23436735 | C42: 0 | D42: 0 | E42: =IF($E$47<>0,$B$195/$B$49/1000/4,0) -> 0.0048826531 | F42: 0.0362 | G42: 0.025861111 | H42: 0 | I42: 0 | J42: 0
A43: Total Fixed Costs | B43: =SUM(B37:B42) -> 0.29116435 | C43: =SUM(C37:C42) -> 0 | D43: =SUM(D37:D42) -> 0 | E43: =SUM(E37:E42) -> 0.063848379 | F43: =SUM(F37:F42) -> 0.0979 | G43: =SUM(G37:G42) -> 0.066770805 | H43: =SUM(H37:H42) -> 0 | I43: =SUM(I37:I42) -> 0 | J43: =SUM(J37:J42) -> 0
A44: Excess Costs | F44: -0.0455
A45: TOTAL COSTS PER POUND | B45: =B35+B43 -> 0.35713017 | C45: =C35+C43 -> 0 | D45: 0.19962946 | E45: =E35+E43+E44 -> 0.25135472 | F45: =F35+F43+F44 -> 0.2375 | G45: =+G35+G43 -> 0.22969913 | H45: =H35+H43 -> 0 | I45: =I35+I43 -> 0 | J45: =J35+J43 -> 0 | L45: =E45-0.245 -> 0.0063547165 | M45: =E47*1000*L45 -> 31138.111
M46: =M45/12 -> 2594.8426
A47: PRODUCTION ( in 000 lbs ) | B47: =+B57 -> 0 | C47: 0 | D47: 0 | E47: =+B58 -> 4900 | F47: 15776 | G47: 36000 | H47: =+B59 -> 0 | I47: 0 | J47: 0
A49: TOTAL PLANT PRODUCTION ( in 000 lbs) | B49: =B24+E24+H24+B47+E47+H47 -> 4900 | C49: =C24+F24+I24+C47+F47+I47 -> 15776 | D49: =D24+G24+J24+D47+G47+J47 -> 116000
A51: Variable Costs - Material | B51: Purchase Price/lb * Yield Factor * Scrap Factor * Mix = Std. Cost Contribution
A53: Production Plan: | B53: Pounds (000) | C53: Product Split
A54: Ceramics | B54: ='2025 Summary'!$D$9 -> 0 | C54: =B54/$B$60 -> 0 | E54: =9*400000*7 -> 25200000
A55: CG280 | B55: 0 | C55: =B55/$B$60 -> 0
A56: CG300 | B56: 0 | C56: =B56/$B$60 -> 0
A57: XXX | B57: 0 | C57: =B57/$B$60 -> 0
A58: HA PELLETS | B58: ='2025 Summary'!$E$9 -> 4900 | C58: =B58/$B$60 -> 1
B59: 0 | C59: =B59/$B$60 -> 0
A60: Total | B60: =SUM(B54:B59) -> 4900 | C60: =B60/$B$60 -> 1
C62: Yield Factor | G62: Mix %
A63: Local Kaolin | B63: Price ($/Ton) | C63: Ceramics | D63: CG280 | E63: CG300 | F63: XXX | G63: HA Pellets | H63: Ceramics | I63: CG280 | J63: CG300 | K63: XXX | L63: HA Pellets
A64: Arcilla (local kaolin) 30012 | B64: =11.89*2 -> 23.78 | C64: =$C$76*H64 -> 0 | D64: =$C$86*I64 -> 0 | E64: =$G$86*J64 -> 0 | F64: =$K$86*K64 -> 0 | G64: =$K$86*L64 -> 0 | H64: 0 | I64: 0 | J64: 0 | K64: 0 | L64: 0
B65: 0 | C65: =$C$76*H65 -> 0 | D65: =$C$86*I65 -> 0 | E65: =$G$86*J65 -> 0 | F65: =$K$86*K65 -> 0 | G65: =$K$86*L65 -> 0 | H65: 0 | I65: 0 | J65: 0 | K65: 0 | L65: 0
C66: =SUM(C64:C65) -> 0 | D66: =SUM(D64:D65) -> 0 | E66: =SUM(E64:E65) -> 0 | F66: =SUM(F64:F65) -> 0 | G66: =SUM(G64:G65) -> 0
A67: Bauxite:
A68: Rusal (30008) | B68: 0 | C68: =$C$77*H68 -> 0 | D68: =$C$87*I68 -> 0 | E68: =$G$87*J68 -> 0 | F68: =$K$87*K68 -> 0 | G68: =$K$87*L68 -> 0 | H68: 0 | I68: 0 | J68: 0 | K68: 0 | L68: 0
A69: Kaolin - CE Calcined (30060) | B69: =116.72*2 -> 233.44 | C69: =$C$77*H69 -> 0 | D69: =$C$87*I69 -> 0 | E69: =$G$87*J69 -> 0 | F69: =$K$87*K69 -> 0 | G69: =$K$87*L69 -> 0 | H69: 0 | I69: 0 | J69: 0 | K69: 0 | L69: 0
B70: 0 | C70: 0 | D70: =$C$87*I70 -> 0 | E70: =$G$87*J70 -> 0 | F70: =$K$87*K70 -> 0 | G70: =$K$87*L70 -> 0 | H70: 0 | I70: 0 | J70: 0 | K70: 0 | L70: 0
B71: 0 | C71: 0 | D71: =$C$87*I71 -> 0 | E71: =$G$87*J71 -> 0 | F71: =$K$87*K71 -> 0 | G71: =$K$87*L71 -> 0 | H71: 0 | I71: 0 | J71: 0 | K71: 0 | L71: 0
C72: =SUM(C68:C71) -> 0 | D72: =SUM(D68:D71) -> 0 | E72: =SUM(E68:E71) -> 0 | F72: =SUM(F68:F71) -> 0 | G72: =SUM(G68:G71) -> 0
B74: Ceramics | F74: CG280
B75: Price ($/lb) | C75: Yield Factor | D75: Std $ Contrib | F75: Price ($/lb) | G75: Yield Factor | H75: Std $ Contrib
A76: Local Kaolin | B76: =0.011 -> 0.011 | C76: =AVERAGE(3.6826,3.5997, 2.6808) -> 3.3210333 | D76: =B76*C76 -> 0.036531367 | F76: 0 | G76: 0 | H76: =F76*G76 -> 0
A77: Bauxite | B77: =($B$68*$H$68+$B$69*$H$69+$B$70*$H$70+$B$71*$H$71)/2000 -> 0 | C77: 0 | D77: =B77*C77 -> 0 | F77: =($B$68*$L$68+$B$69*$L$69+$B$70*$L$70+$B$71*$L$71)/2000 -> 0 | G77: 0 | H77: =F77*G77 -> 0
A78: PVA (30017) | B78: 1.838 | C78: 0.0081 | D78: =B78*C78 -> 0.0148878 | F78: =+B78 -> 1.838 | G78: 0 | H78: =F78*G78 -> 0
A79: Dispersant (30011) | B79: =750/1000 -> 0.75 | C79: 0.0161 | D79: =B79*C79 -> 0.012075 | F79: =+B79 -> 0.75 | G79: 0
A80: Ammonia (30000) | B80: =157.43/1000 -> 0.15743 | C80: 0.0157 | D80: =B80*C80 -> 0.002471651 | F80: =+B80 -> 0.15743 | G80: 0 | H80: 0
A82: Total Material Cost Per Pound | D82: =SUM(D76:D80) -> 0.065965818 | H82: =SUM(H76:H80) -> 0
B84: CG300 | F84: XXX | J84: HA Pellets
B85: Price ($/lb) | C85: Yield Factor/BOM | D85: Std $ Contrib | F85: Price ($/lb) | G85: Yield Factor | H85: Std $ Contrib | J85: Price ($/lb) | K85: Yield Factor | L85: Std $ Contrib
A86: Local kaolin | B86: =($B$64*$I$64+$B$65*$I$65)/2000 -> 0 | C86: 0 | D86: =B86*C86 -> 0 | F86: =($B$64*$J$64+$B$65*$J$65)/2000 -> 0 | G86: 0 | H86: =F86*G86 -> 0 | J86: =($B$64*$K$64+$B$65*$K$65)/2000 -> 0 | K86: 0 | L86: =J86*K86 -> 0
A87: Bauxite | B87: =($B$68*$I$68+$B$69*$I$69+$B$70*$I$70+$B$71*$I$71)/2000 -> 0 | C87: 0 | D87: =B87*C87 -> 0 | F87: =($B$68*$J$68+$B$69*$J$69+$B$70*$J$70+$B$71*$J$71)/2000 -> 0 | G87: 0 | H87: =F87*G87 -> 0 | J87: =($B$68*$K$68+$B$69*$K$69+$B$70*$K$70+$B$71*$K$71)/2000 -> 0 | K87: 0 | L87: =J87*K87 -> 0
A88: PVA (30017) | B88: 2.54 | C88: 0 | D88: =B88*C88 -> 0 | F88: =+B88 -> 2.54 | G88: 0 | H88: =F88*G88 -> 0 | J88: 1.964 | K88: 0.020848164 | L88: =J88*K88 -> 0.040945794
A89: Dispersant (30011) | B89: =750/1000 -> 0.75 | C89: 0 | D89: =B89*C89 -> 0 | F89: =+B89 -> 0.75 | G89: 0 | H89: =F89*G89 -> 0 | J89: 0.591 | K89: 0.0031014518 | L89: =J89*K89 -> 0.001832958
A90: Ammonia (30000) | B90: =157.43/1000 -> 0.15743 | C90: 0 | D90: =B90*C90 -> 0 | F90: =+B90 -> 0.15743 | G90: 0 | H90: =F90*G90 -> 0 | J90: 0.105 | K90: 0.1 | L90: =J90*K90 -> 0.0105
A91: Defoamer (30010) | C91: 0 | D91: =B91*C91 -> 0 | F91: =+B91 -> 0 | G91: 0 | H91: =F91*G91 -> 0 | J91: 1.027 | K91: 0.0021752348 | L91: =J91*K91 -> 0.0022339662
A92: Ultrasurf (30341) | C92: 0 | D92: =B92*C92 -> 0 | F92: =+B92 -> 0 | G92: 0 | H92: =F92*G92 -> 0 | J92: 1.389 | K92: 0.0023312553 | L92: =J92*K92 -> 0.0032381137
A93: HA Pallets (30350) | J93: 18.84 | K93: 0.0006 | L93: =J93*K93 -> 0.011304
A94: HA Bag Protectors (30342) | J94: 1.33 | K94: 0.0006 | L94: =J94*K94 -> 0.000798
D95: 0 | H95: 0 | L95: 0
A96: Total Material Cost Per Pound | D96: =SUM(D86:D95) -> 0 | H96: =SUM(H86:H95) -> 0 | L96: =SUM(L86:L95) -> 0.070852832
A98: Variable Cost - Production/R&M Labor & Benefits
F99: W&S Carve Out of Production Labor
A100: Labor Split:
B101: Prod. Plan (000) | C101: Rate (000 lbs/day) | D101: Kiln Days | E101: % Split | F101: 1 | G101: <--EEs | Hrs--> | H101: =(F101*C202*C204)+((F101*C202*C204*D113)) -> 345498296
A102: Ceramics | B102: =B54 -> 0 | C102: 550 | D102: =B102/C102 -> 0 | E102: =D102/D$108 -> 0 | F102: =(F101*C202*C204*C116)+((F101*C202*C204*D113)*C118) -> 18643341 | G102: Payroll | H102: =F102/$H$101 -> 0.053960732 | I102: Rate will be dependant on prodcut size
A103: CG280 | B103: =B55 -> 0 | C103: 0 | D103: 0 | E103: =D103/D$108 -> 0 | F103: =F102*C206 -> 5593002.3 | G103: IPC | H103: =F103/$H$101 -> 0.01618822
A104: CG300 | B104: =B56 -> 0 | C104: 0 | D104: 0 | E104: =D104/D$108 -> 0
A105: XXX | B105: =B57 -> 0 | C105: 0 | D105: 0 | E105: =D105/D$108 -> 0
A106: HA PELLETS | B106: =B58 -> 4900 | C106: 110 | D106: =B106/C106 -> 44.545455 | E106: =D106/D$108 -> 1 | I106: Reduced daily rate to 110 vs. 150
B107: =B59 -> 0 | C107: 0 | D107: 0 | E107: =D107/D$108 -> 0
B108: =SUM(B102:B107) -> 4900 | C108: =B108/D108 -> 110 | D108: =SUM(D102:D107) -> 44.545455 | E108: =D108/D$108 -> 1
A109: HA Group
B110: =SUM(B113:B116) -> 150083.26 | C110: =SUM(C113:C116) -> 171150.92 | D110: =SUM(D113:D116) -> 195921.14 | E110: =SUM(E113:E116) -> 214904.7 | F110: =SUM(F113:F116) -> 128438.64 | G110: =SUM(G113:G116) -> 206183.2 | H110: =SUM(H113:H116) -> 232252.74
B112: Jan | C112: Feb | D112: Mar | E112: Apr | F112: May | G112: Jun | H112: Jul
A113: Production Labor | B113: 119702.77 | C113: 140371.43 | D113: 166103.95 | E113: 166766.86 | F113: 105842.43 | G113: 147383.65 | H113: 163283.07
A114: R & M Labor | B114: 15222.93 | C114: 23913.55 | D114: 19670.79 | E114: 41336.57 | F114: 23672.31 | G114: 9419.99 | H114: 18308.82
A115: IPC | B115: 11228.99 | C115: 10794.51 | D115: 10146.4 | E115: 8112.73 | F115: -1917.2 | G115: 49379.56 | H115: 50660.85
...

Sheet Apr
A1: TOOMSBORO STANDARD 2025
B3: CERAMICS | E3: CG 280 | H3: CG 300
B4: 25 Standard | C4: 23 Actual | D4: 20 Standard | E4: =$B$4 -> 25 Standard | F4: =+C4 -> 23 Actual | G4: =+D4 -> 20 Standard | H4: =+B4 -> 25 Standard | I4: =+C4 -> 23 Actual | J4: =+D4 -> 20 Standard
C5: (Jan-Sept) | F5: (Jan-Sept) | I5: (Jan-Sept)
A6: Materials | B6: =IF(B24<>0,$D$82,0) -> 0.065965818 | C6: 0.0585 | D6: 0.04156581 | E6: =+H82 -> 0 | F6: 0 | G6: 0 | H6: =+D96 -> 0 | I6: 0 | J6: 0
A7: Electricity | B7: =IF(B24<>0,$D$163,0) -> 0.0101288 | C7: 0.0105 | D7: 0.020277329 | E7: =G163 -> 0.0198372 | F7: 0 | G7: 0 | H7: =J163 -> 0.0198372 | I7: 0 | J7: 0
A8: Gas | B8: =IF(B24<>0,$D$164,0) -> 0.026 | C8: 0.0156 | D8: 0.014965 | E8: =G164 -> 0.0171 | F8: 0 | G8: 0 | H8: =J164 -> 0.0171 | I8: 0 | J8: 0
A9: R&M Supplies and Service | B9: =IF(B24<>0,$J$177,0) -> 0.011766667 | C9: 0.0192 | D9: 0.015915789 | E9: =$H$177 -> 0.03 | F9: 0 | G9: 0 | H9: =$H$177 -> 0.03 | I9: 0 | J9: 0
A10: Manufacturing Supplies | B10: =IF(B24<>0,$J$181,0) -> 0.0025 | C10: 0.0008 | D10: 0.0026315789 | E10: =$H$181 -> 0.0055102041 | F10: 0 | G10: 0 | H10: =$H$181 -> 0.0055102041 | I10: 0 | J10: 0
A11: Other variable | B11: =IF(B24<>0,$J$184,0) -> 0.0019 | C11: 0.0058 | D11: 0.0094736842 | E11: =$H$184 -> 0.01122449 | F11: 0 | G11: 0 | H11: =$H$184 -> 0.01122449 | I11: 0 | J11: 0
A12: Total Variable Costs | B12: =SUM(B6:B11) -> 0.11826128 | C12: =SUM(C6:C11) -> 0.1104 | D12: =SUM(D6:D11) -> 0.10482919 | E12: =SUM(E6:E11) -> 0.083671894 | F12: =SUM(F6:F11) -> 0 | G12: =SUM(G6:G11) -> 0 | H12: =SUM(H6:H11) -> 0.083671894 | I12: =SUM(I6:I11) -> 0 | J12: =SUM(J6:J11) -> 0
A14: Production Labor | B14: =IF($B$24<>0,$F$152/B24/1000,0) -> 0.008496223 | C14: 0.0246 | D14: 0.0073599375 | E14: =$D$124*$E$108/$B$49/1000 -> 0.00013061064 | F14: 0 | G14: 0 | H14: =$D$124*$E$108/$B$49/1000 -> 0.00013061064 | I14: 0 | J14: 0
A15: Repairs & Maintenance Labor | B15: =IF($B$24<>0,$F$153/$B$24/1000,0) -> 0.0035945559 | C15: 0.009 | D15: 0.0042419375 | E15: =$H$124*$E$108/$B$49/1000 -> 0 | F15: 0 | G15: 0 | H15: =$H$124*$E$108/$B$49/1000 -> 0 | I15: 0 | J15: 0
A16: Indirect Payroll Costs (Benefits) | B16: =IF($B$24<>0,$F$155/$B$24/1000,0) -> 0.0036987737 | C16: 0.0079 | D16: 0.0053897125 | E16: =$D$131*$E$108/$B$49/1000 -> 0 | F16: 0 | G16: 0 | H16: =$D$131*$E$108/$B$49/1000 -> 0 | I16: 0 | J16: 0
A17: Supervision | B17: =IF($B$24<>0,$F$154/$B$24/1000,0) -> 0.00023846667 | C17: 0 | D17: 0.0026778947 | E17: =$F$194 -> 0 | F17: 0 | G17: 0 | H17: =$F$194 -> 0 | I17: 0 | J17: 0
A18: Depreciation | B18: =IF($B$24<>0,$B$196/$B$49/1000,0) -> 0.00065364613 | C18: 0.0027 | D18: 0.1672 | E18: =$F$196 -> 0.0078437536 | F18: 0 | G18: 0 | H18: =$F$196 -> 0.0078437536 | I18: 0 | J18: 0
A19: Insurance & Taxes | B19: =IF($B$24<>0,$B$195/$B$49/1000,0) -> 0.0027421203 | C19: 0.012 | D19: 0.012884211 | E19: =$F$195 -> 0.032905444 | F19: 0 | G19: 0 | H19: =$F$195 -> 0.032905444 | I19: 0 | J19: 0
A20: Total Fixed Costs | B20: =SUM(B14:B19) -> 0.019423786 | C20: =SUM(C14:C19) -> 0.0562 | D20: =SUM(D14:D19) -> 0.19975369 | E20: =SUM(E14:E19) -> 0.040879808 | F20: =SUM(F14:F19) -> 0 | G20: =SUM(G14:G19) -> 0 | H20: =SUM(H14:H19) -> 0.040879808 | I20: =SUM(I14:I19) -> 0 | J20: =SUM(J14:J19) -> 0
A22: TOTAL COSTS PER POUND | B22: =B12+B20 -> 0.13768507 | C22: =C12+C20 -> 0.1666 | D22: =D12+D20 -> 0.30458288 | E22: =E12+E20 -> 0.1245517 | F22: =F12+F20 -> 0 | G22: =G12+G20 -> 0 | H22: =H12+H20 -> 0.1245517 | I22: =I12+I20 -> 0 | J22: =J12+J20 -> 0
A24: PRODUCTION ( in 000 lbs ) | B24: =+B54 -> 30000 | C24: 0 | D24: 80000 | E24: =+B55 -> 0 | F24: 0 | G24: 0 | H24: =+B56 -> 0 | I24: 0 | J24: 0
B26: XXX | E26: HA PELLETS
B27: =$B$4 -> 25 Standard | C27: =+C4 -> 23 Actual | D27: =+D4 -> 20 Standard | E27: 24 Standard | F27: 23 Actual | G27: 22 Standard | H27: =+B27 -> 25 Standard | I27: =+C27 -> 23 Actual | J27: =+D27 -> 20 Standard
C28: (Jan-Sept) | F28: (Jan-Aug)
A29: Materials | B29: =D82 -> 0.065965818 | C29: 0 | D29: 0 | E29: =IF(E47<>0,$L$96,0) -> 0.070852832 | F29: 0.078 | G29: 0.06025968 | H29: 0 | I29: 0 | J29: 0
A30: Electricity | B30: =D169 -> 0 | C30: 0 | D30: 0 | E30: =IF(E47<>0,$G$169,0) -> 0.043918811 | F30: 0.0432 | G30: 0.026879418 | H30: 0 | I30: 0 | J30: 0
A31: Gas | B31: =D170 -> 0 | C31: 0 | D31: 0 | E31: =IF(E47<>0,$G$170,0) -> 0.026 | F31: 0.019 | G31: 0.028567 | H31: =J170 -> 0 | I31: 0 | J31: 0
A32: R&M Supplies and Service | B32: =IF($B$47<>0,$H$177,0) -> 0 | C32: 0 | D32: 0 | E32: =IF(E47<>0,$H$177,0) -> 0.03 | F32: 0.0298 | G32: 0.027777778 | H32: 0 | I32: 0 | J32: 0
A33: Manufacturing Supplies | B33: =IF($B$47<>0,$H$181,0) -> 0 | C33: 0 | D33: 0 | E33: =IF(E47<>0,$H$181,0) -> 0.0055102041 | F33: 0.0012 | G33: 0.0069444444 | H33: 0 | I33: 0 | J33: 0
A34: Other variable | B34: =IF($B$47<>0,$H$184,0) -> 0 | C34: 0 | D34: 0 | E34: =IF(E47<>0,$H$184,0) -> 0.01122449 | F34: 0.0139 | G34: 0.0125 | H34: 0 | I34: 0 | J34: 0
A35: Total Variable Costs | B35: =SUM(B29:B34) -> 0.065965818 | C35: =SUM(C29:C34) -> 0 | D35: =SUM(D29:D34) -> 0 | E35: =SUM(E29:E34) -> 0.18750634 | F35: =SUM(F29:F34) -> 0.1851 | G35: =SUM(G29:G34) -> 0.16292832 | H35: =SUM(H29:H34) -> 0 | I35: =SUM(I29:I34) -> 0 | J35: =SUM(J29:J34) -> 0
A37: Production Labor | B37: =$D$124*$E$108/$B$49/1000 -> 0.00013061064 | C37: 0 | D37: 0 | E37: =IF($E$47<>0,$F$127/$E$47/1000,0) -> 0.040001507 | F37: 0.0353 | G37: 0.02156921 | H37: 0 | I37: 0 | J37: 0
A38: Repairs & Maintenance Labor | B38: =$H$124*$E$108/$B$49/1000 -> 0 | C38: 0 | D38: 0 | E38: =IF($E$47<>0,$F$128/$E$47/1000,0) -> 0.0048061173 | F38: 0.0067 | G38: 0.0051700857 | H38: 0 | I38: 0 | J38: 0
A39: Indirect Payroll Costs (Benefits) | B39: =$D$131*$E$108/$B$49/1000 -> 0 | C39: 0 | D39: 0 | E39: =IF($E$47<>0,$F$130/$E$47/1000,0) -> 0.012994211 | F39: 0.0112 | G39: 0.0080162316 | H39: 0 | I39: 0 | J39: 0
A40: Supervision | B40: =IF($B$49<>0,$F$194,0) -> 0 | C40: 0 | D40: 0 | E40: =IF($E$47<>0,$F$129/$E$47/1000,0) -> 0 | F40: 0 | G40: 0.00047638889 | H40: 0 | I40: 0 | J40: 0
A41: Depreciation | B41: =IF($B$49<>0,$F$196,0) -> 0.0078437536 | C41: 0 | D41: 0 | E41: =IF($E$47<>0,$B$196/$B$49/1000/4,0) -> 0.00016341153 | F41: 0.0085 | G41: 0.0056777778 | H41: 0 | I41: 0 | J41: 0
A42: Insurance & Taxes | B42: =IF($B$49<>0,$F$195,0) -> 0.032905444 | C42: 0 | D42: 0 | E42: =IF($E$47<>0,$B$195/$B$49/1000/4,0) -> 0.00068553009 | F42: 0.0362 | G42: 0.025861111 | H42: 0 | I42: 0 | J42: 0
A43: Total Fixed Costs | B43: =SUM(B37:B42) -> 0.040879808 | C43: =SUM(C37:C42) -> 0 | D43: =SUM(D37:D42) -> 0 | E43: =SUM(E37:E42) -> 0.058650778 | F43: =SUM(F37:F42) -> 0.0979 | G43: =SUM(G37:G42) -> 0.066770805 | H43: =SUM(H37:H42) -> 0 | I43: =SUM(I37:I42) -> 0 | J43: =SUM(J37:J42) -> 0
A44: Excess Costs | F44: -0.0455
A45: TOTAL COSTS PER POUND | B45: =B35+B43 -> 0.10684563 | C45: =C35+C43 -> 0 | D45: 0.19962946 | E45: =E35+E43+E44 -> 0.24615711 | F45: =F35+F43+F44 -> 0.2375 | G45: =+G35+G43 -> 0.22969913 | H45: =H35+H43 -> 0 | I45: =I35+I43 -> 0 | J45: =J35+J43 -> 0 | L45: =E45-0.245 -> 0.0011571148 | M45: =E47*1000*L45 -> 5669.8624
M46: =M45/12 -> 472.48853
A47: PRODUCTION ( in 000 lbs ) | B47: =+B57 -> 0 | C47: 0 | D47: 0 | E47: =+B58 -> 4900 | F47: 15776 | G47: 36000 | H47: =+B59 -> 0 | I47: 0 | J47: 0
A49: TOTAL PLANT PRODUCTION ( in 000 lbs) | B49: =B24+E24+H24+B47+E47+H47 -> 34900 | C49: =C24+F24+I24+C47+F47+I47 -> 15776 | D49: =D24+G24+J24+D47+G47+J47 -> 116000
A51: Variable Costs - Material | B51: Purchase Price/lb * Yield Factor * Scrap Factor * Mix = Std. Cost Contribution
A53: Production Plan: | B53: Pounds (000) | C53: Product Split
A54: Ceramics | B54: ='2025 Summary'!$D$10 -> 30000 | C54: =B54/$B$60 -> 0.85959885 | E54: =9*400000*7 -> 25200000
A55: CG280 | B55: 0 | C55: =B55/$B$60 -> 0
A56: CG300 | B56: 0 | C56: =B56/$B$60 -> 0
A57: XXX | B57: 0 | C57: =B57/$B$60 -> 0
A58: HA PELLETS | B58: ='2025 Summary'!$E$10 -> 4900 | C58: =B58/$B$60 -> 0.14040115
B59: 0 | C59: =B59/$B$60 -> 0
A60: Total | B60: =SUM(B54:B59) -> 34900 | C60: =B60/$B$60 -> 1
C62: Yield Factor | G62: Mix %
A63: Local Kaolin | B63: Price ($/Ton) | C63: Ceramics | D63: CG280 | E63: CG300 | F63: XXX | G63: HA Pellets | H63: Ceramics | I63: CG280 | J63: CG300 | K63: XXX | L63: HA Pellets
A64: Arcilla (local kaolin) 30012 | B64: =11.89*2 -> 23.78 | C64: =$C$76*H64 -> 0 | D64: =$C$86*I64 -> 0 | E64: =$G$86*J64 -> 0 | F64: =$K$86*K64 -> 0 | G64: =$K$86*L64 -> 0 | H64: 0 | I64: 0 | J64: 0 | K64: 0 | L64: 0
B65: 0 | C65: =$C$76*H65 -> 0 | D65: =$C$86*I65 -> 0 | E65: =$G$86*J65 -> 0 | F65: =$K$86*K65 -> 0 | G65: =$K$86*L65 -> 0 | H65: 0 | I65: 0 | J65: 0 | K65: 0 | L65: 0
C66: =SUM(C64:C65) -> 0 | D66: =SUM(D64:D65) -> 0 | E66: =SUM(E64:E65) -> 0 | F66: =SUM(F64:F65) -> 0 | G66: =SUM(G64:G65) -> 0
A67: Bauxite:
A68: Rusal (30008) | B68: 0 | C68: =$C$77*H68 -> 0 | D68: =$C$87*I68 -> 0 | E68: =$G$87*J68 -> 0 | F68: =$K$87*K68 -> 0 | G68: =$K$87*L68 -> 0 | H68: 0 | I68: 0 | J68: 0 | K68: 0 | L68: 0
A69: Kaolin - CE Calcined (30060) | B69: =116.72*2 -> 233.44 | C69: =$C$77*H69 -> 0 | D69: =$C$87*I69 -> 0 | E69: =$G$87*J69 -> 0 | F69: =$K$87*K69 -> 0 | G69: =$K$87*L69 -> 0 | H69: 0 | I69: 0 | J69: 0 | K69: 0 | L69: 0
B70: 0 | C70: 0 | D70: =$C$87*I70 -> 0 | E70: =$G$87*J70 -> 0 | F70: =$K$87*K70 -> 0 | G70: =$K$87*L70 -> 0 | H70: 0 | I70: 0 | J70: 0 | K70: 0 | L70: 0
B71: 0 | C71: 0 | D71: =$C$87*I71 -> 0 | E71: =$G$87*J71 -> 0 | F71: =$K$87*K71 -> 0 | G71: =$K$87*L71 -> 0 | H71: 0 | I71: 0 | J71: 0 | K71: 0 | L71: 0
C72: =SUM(C68:C71) -> 0 | D72: =SUM(D68:D71) -> 0 | E72: =SUM(E68:E71) -> 0 | F72: =SUM(F68:F71) -> 0 | G72: =SUM(G68:G71) -> 0
B74: Ceramics | F74: CG280
B75: Price ($/lb) | C75: Yield Factor | D75: Std $ Contrib | F75: Price ($/lb) | G75: Yield Factor | H75: Std $ Contrib
A76: Local Kaolin | B76: =0.011 -> 0.011 | C76: =AVERAGE(3.6826,3.5997, 2.6808) -> 3.3210333 | D76: =B76*C76 -> 0.036531367 | F76: 0 | G76: 0 | H76: =F76*G76 -> 0
A77: Bauxite | B77: =($B$68*$H$68+$B$69*$H$69+$B$70*$H$70+$B$71*$H$71)/2000 -> 0 | C77: 0 | D77: =B77*C77 -> 0 | F77: =($B$68*$L$68+$B$69*$L$69+$B$70*$L$70+$B$71*$L$71)/2000 -> 0 | G77: 0 | H77: =F77*G77 -> 0
A78: PVA (30017) | B78: 1.838 | C78: 0.0081 | D78: =B78*C78 -> 0.0148878 | F78: =+B78 -> 1.838 | G78: 0 | H78: =F78*G78 -> 0
A79: Dispersant (30011) | B79: =750/1000 -> 0.75 | C79: 0.0161 | D79: =B79*C79 -> 0.012075 | F79: =+B79 -> 0.75 | G79: 0
A80: Ammonia (30000) | B80: =157.43/1000 -> 0.15743 | C80: 0.0157 | D80: =B80*C80 -> 0.002471651 | F80: =+B80 -> 0.15743 | G80: 0 | H80: 0
A82: Total Material Cost Per Pound | D82: =SUM(D76:D80) -> 0.065965818 | H82: =SUM(H76:H80) -> 0
B84: CG300 | F84: XXX | J84: HA Pellets
B85: Price ($/lb) | C85: Yield Factor/BOM | D85: Std $ Contrib | F85: Price ($/lb) | G85: Yield Factor | H85: Std $ Contrib | J85: Price ($/lb) | K85: Yield Factor | L85: Std $ Contrib
A86: Local kaolin | B86: =($B$64*$I$64+$B$65*$I$65)/2000 -> 0 | C86: 0 | D86: =B86*C86 -> 0 | F86: =($B$64*$J$64+$B$65*$J$65)/2000 -> 0 | G86: 0 | H86: =F86*G86 -> 0 | J86: =($B$64*$K$64+$B$65*$K$65)/2000 -> 0 | K86: 0 | L86: =J86*K86 -> 0
A87: Bauxite | B87: =($B$68*$I$68+$B$69*$I$69+$B$70*$I$70+$B$71*$I$71)/2000 -> 0 | C87: 0 | D87: =B87*C87 -> 0 | F87: =($B$68*$J$68+$B$69*$J$69+$B$70*$J$70+$B$71*$J$71)/2000 -> 0 | G87: 0 | H87: =F87*G87 -> 0 | J87: =($B$68*$K$68+$B$69*$K$69+$B$70*$K$70+$B$71*$K$71)/2000 -> 0 | K87: 0 | L87: =J87*K87 -> 0
A88: PVA (30017) | B88: 2.54 | C88: 0 | D88: =B88*C88 -> 0 | F88: =+B88 -> 2.54 | G88: 0 | H88: =F88*G88 -> 0 | J88: 1.964 | K88: 0.020848164 | L88: =J88*K88 -> 0.040945794
A89: Dispersant (30011) | B89: =750/1000 -> 0.75 | C89: 0 | D89: =B89*C89 -> 0 | F89: =+B89 -> 0.75 | G89: 0 | H89: =F89*G89 -> 0 | J89: 0.591 | K89: 0.0031014518 | L89: =J89*K89 -> 0.001832958
A90: Ammonia (30000) | B90: =157.43/1000 -> 0.15743 | C90: 0 | D90: =B90*C90 -> 0 | F90: =+B90 -> 0.15743 | G90: 0 | H90: =F90*G90 -> 0 | J90: 0.105 | K90: 0.1 | L90: =J90*K90 -> 0.0105
A91: Defoamer (30010) | C91: 0 | D91: =B91*C91 -> 0 | F91: =+B91 -> 0 | G91: 0 | H91: =F91*G91 -> 0 | J91: 1.027 | K91: 0.0021752348 | L91: =J91*K91 -> 0.0022339662
A92: Ultrasurf (30341) | C92: 0 | D92: =B92*C92 -> 0 | F92: =+B92 -> 0 | G92: 0 | H92: =F92*G92 -> 0 | J92: 1.389 | K92: 0.0023312553 | L92: =J92*K92 -> 0.0032381137
A93: HA Pallets (30350) | J93: 18.84 | K93: 0.0006 | L93: =J93*K93 -> 0.011304
A94: HA Bag Protectors (30342) | J94: 1.33 | K94: 0.0006 | L94: =J94*K94 -> 0.000798
D95: 0 | H95: 0 | L95: 0
A96: Total Material Cost Per Pound | D96: =SUM(D86:D95) -> 0 | H96: =SUM(H86:H95) -> 0 | L96: =SUM(L86:L95) -> 0.070852832
A98: Variable Cost - Production/R&M Labor & Benefits
F99: W&S Carve Out of Production Labor
A100: Labor Split:
B101: Prod. Plan (000) | C101: Rate (000 lbs/day) | D101: Kiln Days | E101: % Split | F101: 1 | G101: <--EEs | Hrs--> | H101: =(F101*C202*C204)+((F101*C202*C204*D113)) -> 345498296
A102: Ceramics | B102: =B54 -> 30000 | C102: 550 | D102: =B102/C102 -> 54.545455 | E102: =D102/D$108 -> 0.55045872 | F102: =(F101*C202*C204*C116)+((F101*C202*C204*D113)*C118) -> 18643341 | G102: Payroll | H102: =F102/$H$101 -> 0.053960732 | I102: Rate will be dependant on prodcut size
A103: CG280 | B103: =B55 -> 0 | C103: 0 | D103: 0 | E103: =D103/D$108 -> 0 | F103: =F102*C206 -> 5593002.3 | G103: IPC | H103: =F103/$H$101 -> 0.01618822
A104: CG300 | B104: =B56 -> 0 | C104: 0 | D104: 0 | E104: =D104/D$108 -> 0
A105: XXX | B105: =B57 -> 0 | C105: 0 | D105: 0 | E105: =D105/D$108 -> 0
A106: HA PELLETS | B106: =B58 -> 4900 | C106: 110 | D106: =B106/C106 -> 44.545455 | E106: =D106/D$108 -> 0.44954128 | I106: Reduced daily rate to 110 vs. 150
B107: =B59 -> 0 | C107: 0 | D107: 0 | E107: =D107/D$108 -> 0
B108: =SUM(B102:B107) -> 34900 | C108: =B108/D108 -> 352.20183 | D108: =SUM(D102:D107) -> 99.090909 | E108: =D108/D$108 -> 1
A109: HA Group
B112: Jan | C112: Feb | D112: Mar | E112: Apr | F112: May | G112: Jun | H112: Jul
A113: Production Labor | B113: 119702.77 | C113: 140371.43 | D113: 166103.95 | E113: 166766.86 | F113: 105842.43 | G113: 147383.65 | H113: 163283.07
A114: R & M Labor | B114: 15222.93 | C114: 23913.55 | D114: 19670.79 | E114: 41336.57 | F114: 23672.31 | G114: 9419.99 | H114: 18308.82
A115: IPC | B115: 11228.99 | C115: 10794.51 | D115: 10146.4 | E115: 8112.73 | F115: -1917.2 | G115: 49379.56 | H115: 50660.85
A116: Supervision | B116: 3928.57 | C116: -3928.57 | D116: 0 | E116: -1311.46 | F116: 841.1 | G116: 0 | H116: 0
...

Sheet May
A1: TOOMSBORO STANDARD 2025
B3: CERAMICS | E3: CG 280 | H3: CG 300
B4: 25 Standard | C4: 23 Actual | D4: 20 Standard | E4: =$B$4 -> 25 Standard | F4: =+C4 -> 23 Actual | G4: =+D4 -> 20 Standard | H4: =+B4 -> 25 Standard | I4: =+C4 -> 23 Actual | J4: =+D4 -> 20 Standard
C5: (Jan-Sept) | F5: (Jan-Sept) | I5: (Jan-Sept)
A6: Materials | B6: =IF(B24<>0,$D$82,0) -> 0 | C6: 0.0585 | D6: 0.04156581 | E6: =+H82 -> 0 | F6: 0 | G6: 0 | H6: =+D96 -> 0 | I6: 0 | J6: 0
A7: Electricity | B7: =IF(B24<>0,$D$163,0) -> 0 | C7: 0.0105 | D7: 0.020277329 | E7: =G163 -> 0.0198372 | F7: 0 | G7: 0 | H7: =J163 -> 0.0198372 | I7: 0 | J7: 0
A8: Gas | B8: =IF(B24<>0,$D$164,0) -> 0 | C8: 0.0156 | D8: 0.014965 | E8: =G164 -> 0.0171 | F8: 0 | G8: 0 | H8: =J164 -> 0.0171 | I8: 0 | J8: 0
A9: R&M Supplies and Service | B9: =IF(B24<>0,$J$177,0) -> 0 | C9: 0.0192 | D9: 0.015915789 | E9: =$H$177 -> 0.03 | F9: 0 | G9: 0 | H9: =$H$177 -> 0.03 | I9: 0 | J9: 0
A10: Manufacturing Supplies | B10: =IF(B24<>0,$J$181,0) -> 0 | C10: 0.0008 | D10: 0.0026315789 | E10: =$H$181 -> 0.0055102041 | F10: 0 | G10: 0 | H10: =$H$181 -> 0.0055102041 | I10: 0 | J10: 0
A11: Other variable | B11: =IF(B24<>0,$J$184,0) -> 0 | C11: 0.0058 | D11: 0.0094736842 | E11: =$H$184 -> 0.01122449 | F11: 0 | G11: 0 | H11: =$H$184 -> 0.01122449 | I11: 0 | J11: 0
A12: Total Variable Costs | B12: =SUM(B6:B11) -> 0 | C12: =SUM(C6:C11) -> 0.1104 | D12: =SUM(D6:D11) -> 0.10482919 | E12: =SUM(E6:E11) -> 0.083671894 | F12: =SUM(F6:F11) -> 0 | G12: =SUM(G6:G11) -> 0 | H12: =SUM(H6:H11) -> 0.083671894 | I12: =SUM(I6:I11) -> 0 | J12: =SUM(J6:J11) -> 0
A14: Production Labor | B14: =IF($B$24<>0,$F$152/B24/1000,0) -> 0 | C14: 0.0246 | D14: 0.0073599375 | E14: =$D$124*$E$108/$B$49/1000 -> 0.00093026761 | F14: 0 | G14: 0 | H14: =$D$124*$E$108/$B$49/1000 -> 0.00093026761 | I14: 0 | J14: 0
A15: Repairs & Maintenance Labor | B15: =IF($B$24<>0,$F$153/$B$24/1000,0) -> 0 | C15: 0.009 | D15: 0.0042419375 | E15: =$H$124*$E$108/$B$49/1000 -> 0 | F15: 0 | G15: 0 | H15: =$H$124*$E$108/$B$49/1000 -> 0 | I15: 0 | J15: 0
A16: Indirect Payroll Costs (Benefits) | B16: =IF($B$24<>0,$F$155/$B$24/1000,0) -> 0 | C16: 0.0079 | D16: 0.0053897125 | E16: =$D$131*$E$108/$B$49/1000 -> 0 | F16: 0 | G16: 0 | H16: =$D$131*$E$108/$B$49/1000 -> 0 | I16: 0 | J16: 0
A17: Supervision | B17: =IF($B$24<>0,$F$154/$B$24/1000,0) -> 0 | C17: 0 | D17: 0.0026778947 | E17: =$F$194 -> 0 | F17: 0 | G17: 0 | H17: =$F$194 -> 0 | I17: 0 | J17: 0
A18: Depreciation | B18: =IF($B$24<>0,$B$196/$B$49/1000,0) -> 0 | C18: 0.0027 | D18: 0.1672 | E18: =$F$196 -> 0.055866735 | F18: 0 | G18: 0 | H18: =$F$196 -> 0.055866735 | I18: 0 | J18: 0
A19: Insurance & Taxes | B19: =IF($B$24<>0,$B$195/$B$49/1000,0) -> 0 | C19: 0.012 | D19: 0.012884211 | E19: =$F$195 -> 0.23436735 | F19: 0 | G19: 0 | H19: =$F$195 -> 0.23436735 | I19: 0 | J19: 0
A20: Total Fixed Costs | B20: =SUM(B14:B19) -> 0 | C20: =SUM(C14:C19) -> 0.0562 | D20: =SUM(D14:D19) -> 0.19975369 | E20: =SUM(E14:E19) -> 0.29116435 | F20: =SUM(F14:F19) -> 0 | G20: =SUM(G14:G19) -> 0 | H20: =SUM(H14:H19) -> 0.29116435 | I20: =SUM(I14:I19) -> 0 | J20: =SUM(J14:J19) -> 0
A22: TOTAL COSTS PER POUND | B22: =B12+B20 -> 0 | C22: =C12+C20 -> 0.1666 | D22: =D12+D20 -> 0.30458288 | E22: =E12+E20 -> 0.37483624 | F22: =F12+F20 -> 0 | G22: =G12+G20 -> 0 | H22: =H12+H20 -> 0.37483624 | I22: =I12+I20 -> 0 | J22: =J12+J20 -> 0
A24: PRODUCTION ( in 000 lbs ) | B24: =+B54 -> 0 | C24: 0 | D24: 80000 | E24: =+B55 -> 0 | F24: 0 | G24: 0 | H24: =+B56 -> 0 | I24: 0 | J24: 0
B26: XXX | E26: HA PELLETS
B27: =$B$4 -> 25 Standard | C27: =+C4 -> 23 Actual | D27: =+D4 -> 20 Standard | E27: 24 Standard | F27: 23 Actual | G27: 22 Standard | H27: =+B27 -> 25 Standard | I27: =+C27 -> 23 Actual | J27: =+D27 -> 20 Standard
C28: (Jan-Sept) | F28: (Jan-Aug)
A29: Materials | B29: =D82 -> 0.065965818 | C29: 0 | D29: 0 | E29: =IF(E47<>0,$L$96,0) -> 0.070852832 | F29: 0.078 | G29: 0.06025968 | H29: 0 | I29: 0 | J29: 0
A30: Electricity | B30: =D169 -> 0 | C30: 0 | D30: 0 | E30: =IF(E47<>0,$G$169,0) -> 0.043918811 | F30: 0.0432 | G30: 0.026879418 | H30: 0 | I30: 0 | J30: 0
A31: Gas | B31: =D170 -> 0 | C31: 0 | D31: 0 | E31: =IF(E47<>0,$G$170,0) -> 0.026 | F31: 0.019 | G31: 0.028567 | H31: =J170 -> 0 | I31: 0 | J31: 0
A32: R&M Supplies and Service | B32: =IF($B$47<>0,$H$177,0) -> 0 | C32: 0 | D32: 0 | E32: =IF(E47<>0,$H$177,0) -> 0.03 | F32: 0.0298 | G32: 0.027777778 | H32: 0 | I32: 0 | J32: 0
A33: Manufacturing Supplies | B33: =IF($B$47<>0,$H$181,0) -> 0 | C33: 0 | D33: 0 | E33: =IF(E47<>0,$H$181,0) -> 0.0055102041 | F33: 0.0012 | G33: 0.0069444444 | H33: 0 | I33: 0 | J33: 0
A34: Other variable | B34: =IF($B$47<>0,$H$184,0) -> 0 | C34: 0 | D34: 0 | E34: =IF(E47<>0,$H$184,0) -> 0.01122449 | F34: 0.0139 | G34: 0.0125 | H34: 0 | I34: 0 | J34: 0
A35: Total Variable Costs | B35: =SUM(B29:B34) -> 0.065965818 | C35: =SUM(C29:C34) -> 0 | D35: =SUM(D29:D34) -> 0 | E35: =SUM(E29:E34) -> 0.18750634 | F35: =SUM(F29:F34) -> 0.1851 | G35: =SUM(G29:G34) -> 0.16292832 | H35: =SUM(H29:H34) -> 0 | I35: =SUM(I29:I34) -> 0 | J35: =SUM(J29:J34) -> 0
A37: Production Labor | B37: =$D$124*$E$108/$B$49/1000 -> 0.00093026761 | C37: 0 | D37: 0 | E37: =IF($E$47<>0,$F$127/$E$47/1000,0) -> 0.040001507 | F37: 0.0353 | G37: 0.02156921 | H37: 0 | I37: 0 | J37: 0
A38: Repairs & Maintenance Labor | B38: =$H$124*$E$108/$B$49/1000 -> 0 | C38: 0 | D38: 0 | E38: =IF($E$47<>0,$F$128/$E$47/1000,0) -> 0.0048061173 | F38: 0.0067 | G38: 0.0051700857 | H38: 0 | I38: 0 | J38: 0
A39: Indirect Payroll Costs (Benefits) | B39: =$D$131*$E$108/$B$49/1000 -> 0 | C39: 0 | D39: 0 | E39: =IF($E$47<>0,$F$130/$E$47/1000,0) -> 0.012994211 | F39: 0.0112 | G39: 0.0080162316 | H39: 0 | I39: 0 | J39: 0
A40: Supervision | B40: =IF($B$49<>0,$F$194,0) -> 0 | C40: 0 | D40: 0 | E40: =IF($E$47<>0,$F$129/$E$47/1000,0) -> 0 | F40: 0 | G40: 0.00047638889 | H40: 0 | I40: 0 | J40: 0
A41: Depreciation | B41: =IF($B$49<>0,$F$196,0) -> 0.055866735 | C41: 0 | D41: 0 | E41: =IF($E$47<>0,$B$196/$B$49/1000/4,0) -> 0.0011638903 | F41: 0.0085 | G41: 0.0056777778 | H41: 0 | I41: 0 | J41: 0
A42: Insurance & Taxes | B42: =IF($B$49<>0,$F$195,0) -> 0.23436735 | C42: 0 | D42: 0 | E42: =IF($E$47<>0,$B$195/$B$49/1000/4,0) -> 0.0048826531 | F42: 0.0362 | G42: 0.025861111 | H42: 0 | I42: 0 | J42: 0
A43: Total Fixed Costs | B43: =SUM(B37:B42) -> 0.29116435 | C43: =SUM(C37:C42) -> 0 | D43: =SUM(D37:D42) -> 0 | E43: =SUM(E37:E42) -> 0.063848379 | F43: =SUM(F37:F42) -> 0.0979 | G43: =SUM(G37:G42) -> 0.066770805 | H43: =SUM(H37:H42) -> 0 | I43: =SUM(I37:I42) -> 0 | J43: =SUM(J37:J42) -> 0
A44: Excess Costs | F44: -0.0455
A45: TOTAL COSTS PER POUND | B45: =B35+B43 -> 0.35713017 | C45: =C35+C43 -> 0 | D45: 0.19962946 | E45: =E35+E43+E44 -> 0.25135472 | F45: =F35+F43+F44 -> 0.2375 | G45: =+G35+G43 -> 0.22969913 | H45: =H35+H43 -> 0 | I45: =I35+I43 -> 0 | J45: =J35+J43 -> 0 | L45: =E45-0.245 -> 0.0063547165 | M45: =E47*1000*L45 -> 31138.111
M46: =M45/12 -> 2594.8426
A47: PRODUCTION ( in 000 lbs ) | B47: =+B57 -> 0 | C47: 0 | D47: 0 | E47: =+B58 -> 4900 | F47: 15776 | G47: 36000 | H47: =+B59 -> 0 | I47: 0 | J47: 0
A49: TOTAL PLANT PRODUCTION ( in 000 lbs) | B49: =B24+E24+H24+B47+E47+H47 -> 4900 | C49: =C24+F24+I24+C47+F47+I47 -> 15776 | D49: =D24+G24+J24+D47+G47+J47 -> 116000
A51: Variable Costs - Material | B51: Purchase Price/lb * Yield Factor * Scrap Factor * Mix = Std. Cost Contribution
A53: Production Plan: | B53: Pounds (000) | C53: Product Split
A54: Ceramics | B54: ='2025 Summary'!$D$11 -> 0 | C54: =B54/$B$60 -> 0 | E54: =9*400000*7 -> 25200000
A55: CG280 | B55: 0 | C55: =B55/$B$60 -> 0
A56: CG300 | B56: 0 | C56: =B56/$B$60 -> 0
A57: XXX | B57: 0 | C57: =B57/$B$60 -> 0
A58: HA PELLETS | B58: ='2025 Summary'!$E$11 -> 4900 | C58: =B58/$B$60 -> 1
B59: 0 | C59: =B59/$B$60 -> 0
A60: Total | B60: =SUM(B54:B59) -> 4900 | C60: =B60/$B$60 -> 1
C62: Yield Factor | G62: Mix %
A63: Local Kaolin | B63: Price ($/Ton) | C63: Ceramics | D63: CG280 | E63: CG300 | F63: XXX | G63: HA Pellets | H63: Ceramics | I63: CG280 | J63: CG300 | K63: XXX | L63: HA Pellets
A64: Arcilla (local kaolin) 30012 | B64: =11.89*2 -> 23.78 | C64: =$C$76*H64 -> 0 | D64: =$C$86*I64 -> 0 | E64: =$G$86*J64 -> 0 | F64: =$K$86*K64 -> 0 | G64: =$K$86*L64 -> 0 | H64: 0 | I64: 0 | J64: 0 | K64: 0 | L64: 0
B65: 0 | C65: =$C$76*H65 -> 0 | D65: =$C$86*I65 -> 0 | E65: =$G$86*J65 -> 0 | F65: =$K$86*K65 -> 0 | G65: =$K$86*L65 -> 0 | H65: 0 | I65: 0 | J65: 0 | K65: 0 | L65: 0
C66: =SUM(C64:C65) -> 0 | D66: =SUM(D64:D65) -> 0 | E66: =SUM(E64:E65) -> 0 | F66: =SUM(F64:F65) -> 0 | G66: =SUM(G64:G65) -> 0
A67: Bauxite:
A68: Rusal (30008) | B68: 0 | C68: =$C$77*H68 -> 0 | D68: =$C$87*I68 -> 0 | E68: =$G$87*J68 -> 0 | F68: =$K$87*K68 -> 0 | G68: =$K$87*L68 -> 0 | H68: 0 | I68: 0 | J68: 0 | K68: 0 | L68: 0
A69: Kaolin - CE Calcined (30060) | B69: =116.72*2 -> 233.44 | C69: =$C$77*H69 -> 0 | D69: =$C$87*I69 -> 0 | E69: =$G$87*J69 -> 0 | F69: =$K$87*K69 -> 0 | G69: =$K$87*L69 -> 0 | H69: 0 | I69: 0 | J69: 0 | K69: 0 | L69: 0
B70: 0 | C70: 0 | D70: =$C$87*I70 -> 0 | E70: =$G$87*J70 -> 0 | F70: =$K$87*K70 -> 0 | G70: =$K$87*L70 -> 0 | H70: 0 | I70: 0 | J70: 0 | K70: 0 | L70: 0
B71: 0 | C71: 0 | D71: =$C$87*I71 -> 0 | E71: =$G$87*J71 -> 0 | F71: =$K$87*K71 -> 0 | G71: =$K$87*L71 -> 0 | H71: 0 | I71: 0 | J71: 0 | K71: 0 | L71: 0
C72: =SUM(C68:C71) -> 0 | D72: =SUM(D68:D71) -> 0 | E72: =SUM(E68:E71) -> 0 | F72: =SUM(F68:F71) -> 0 | G72: =SUM(G68:G71) -> 0
B74: Ceramics | F74: CG280
B75: Price ($/lb) | C75: Yield Factor | D75: Std $ Contrib | F75: Price ($/lb) | G75: Yield Factor | H75: Std $ Contrib
A76: Local Kaolin | B76: =0.011 -> 0.011 | C76: =AVERAGE(3.6826,3.5997, 2.6808) -> 3.3210333 | D76: =B76*C76 -> 0.036531367 | F76: 0 | G76: 0 | H76: =F76*G76 -> 0
A77: Bauxite | B77: =($B$68*$H$68+$B$69*$H$69+$B$70*$H$70+$B$71*$H$71)/2000 -> 0 | C77: 0 | D77: =B77*C77 -> 0 | F77: =($B$68*$L$68+$B$69*$L$69+$B$70*$L$70+$B$71*$L$71)/2000 -> 0 | G77: 0 | H77: =F77*G77 -> 0
A78: PVA (30017) | B78: 1.838 | C78: 0.0081 | D78: =B78*C78 -> 0.0148878 | F78: =+B78 -> 1.838 | G78: 0 | H78: =F78*G78 -> 0
A79: Dispersant (30011) | B79: =750/1000 -> 0.75 | C79: 0.0161 | D79: =B79*C79 -> 0.012075 | F79: =+B79 -> 0.75 | G79: 0
A80: Ammonia (30000) | B80: =157.43/1000 -> 0.15743 | C80: 0.0157 | D80: =B80*C80 -> 0.002471651 | F80: =+B80 -> 0.15743 | G80: 0 | H80: 0
A82: Total Material Cost Per Pound | D82: =SUM(D76:D80) -> 0.065965818 | H82: =SUM(H76:H80) -> 0
B84: CG300 | F84: XXX | J84: HA Pellets
B85: Price ($/lb) | C85: Yield Factor/BOM | D85: Std $ Contrib | F85: Price ($/lb) | G85: Yield Factor | H85: Std $ Contrib | J85: Price ($/lb) | K85: Yield Factor | L85: Std $ Contrib
A86: Local kaolin | B86: =($B$64*$I$64+$B$65*$I$65)/2000 -> 0 | C86: 0 | D86: =B86*C86 -> 0 | F86: =($B$64*$J$64+$B$65*$J$65)/2000 -> 0 | G86: 0 | H86: =F86*G86 -> 0 | J86: =($B$64*$K$64+$B$65*$K$65)/2000 -> 0 | K86: 0 | L86: =J86*K86 -> 0
A87: Bauxite | B87: =($B$68*$I$68+$B$69*$I$69+$B$70*$I$70+$B$71*$I$71)/2000 -> 0 | C87: 0 | D87: =B87*C87 -> 0 | F87: =($B$68*$J$68+$B$69*$J$69+$B$70*$J$70+$B$71*$J$71)/2000 -> 0 | G87: 0 | H87: =F87*G87 -> 0 | J87: =($B$68*$K$68+$B$69*$K$69+$B$70*$K$70+$B$71*$K$71)/2000 -> 0 | K87: 0 | L87: =J87*K87 -> 0
A88: PVA (30017) | B88: 2.54 | C88: 0 | D88: =B88*C88 -> 0 | F88: =+B88 -> 2.54 | G88: 0 | H88: =F88*G88 -> 0 | J88: 1.964 | K88: 0.020848164 | L88: =J88*K88 -> 0.040945794
A89: Dispersant (30011) | B89: =750/1000 -> 0.75 | C89: 0 | D89: =B89*C89 -> 0 | F89: =+B89 -> 0.75 | G89: 0 | H89: =F89*G89 -> 0 | J89: 0.591 | K89: 0.0031014518 | L89: =J89*K89 -> 0.001832958
A90: Ammonia (30000) | B90: =157.43/1000 -> 0.15743 | C90: 0 | D90: =B90*C90 -> 0 | F90: =+B90 -> 0.15743 | G90: 0 | H90: =F90*G90 -> 0 | J90: 0.105 | K90: 0.1 | L90: =J90*K90 -> 0.0105
A91: Defoamer (30010) | C91: 0 | D91: =B91*C91 -> 0 | F91: =+B91 -> 0 | G91: 0 | H91: =F91*G91 -> 0 | J91: 1.027 | K91: 0.0021752348 | L91: =J91*K91 -> 0.0022339662
A92: Ultrasurf (30341) | C92: 0 | D92: =B92*C92 -> 0 | F92: =+B92 -> 0 | G92: 0 | H92: =F92*G92 -> 0 | J92: 1.389 | K92: 0.0023312553 | L92: =J92*K92 -> 0.0032381137
A93: HA Pallets (30350) | J93: 18.84 | K93: 0.0006 | L93: =J93*K93 -> 0.011304
A94: HA Bag Protectors (30342) | J94: 1.33 | K94: 0.0006 | L94: =J94*K94 -> 0.000798
D95: 0 | H95: 0 | L95: 0
A96: Total Material Cost Per Pound | D96: =SUM(D86:D95) -> 0 | H96: =SUM(H86:H95) -> 0 | L96: =SUM(L86:L95) -> 0.070852832
A98: Variable Cost - Production/R&M Labor & Benefits
F99: W&S Carve Out of Production Labor
A100: Labor Split:
B101: Prod. Plan (000) | C101: Rate (000 lbs/day) | D101: Kiln Days | E101: % Split | F101: 1 | G101: <--EEs | Hrs--> | H101: =(F101*C202*C204)+((F101*C202*C204*D113)) -> 345498296
A102: Ceramics | B102: =B54 -> 0 | C102: 550 | D102: =B102/C102 -> 0 | E102: =D102/D$108 -> 0 | F102: =(F101*C202*C204*C116)+((F101*C202*C204*D113)*C118) -> 18643341 | G102: Payroll | H102: =F102/$H$101 -> 0.053960732 | I102: Rate will be dependant on prodcut size
A103: CG280 | B103: =B55 -> 0 | C103: 0 | D103: 0 | E103: =D103/D$108 -> 0 | F103: =F102*C206 -> 5593002.3 | G103: IPC | H103: =F103/$H$101 -> 0.01618822
A104: CG300 | B104: =B56 -> 0 | C104: 0 | D104: 0 | E104: =D104/D$108 -> 0
A105: XXX | B105: =B57 -> 0 | C105: 0 | D105: 0 | E105: =D105/D$108 -> 0
A106: HA PELLETS | B106: =B58 -> 4900 | C106: 110 | D106: =B106/C106 -> 44.545455 | E106: =D106/D$108 -> 1 | I106: Reduced daily rate to 110 vs. 150
B107: =B59 -> 0 | C107: 0 | D107: 0 | E107: =D107/D$108 -> 0
B108: =SUM(B102:B107) -> 4900 | C108: =B108/D108 -> 110 | D108: =SUM(D102:D107) -> 44.545455 | E108: =D108/D$108 -> 1
A109: HA Group
B112: Jan | C112: Feb | D112: Mar | E112: Apr | F112: May | G112: Jun | H112: Jul
A113: Production Labor | B113: 119702.77 | C113: 140371.43 | D113: 166103.95 | E113: 166766.86 | F113: 105842.43 | G113: 147383.65 | H113: 163283.07
A114: R & M Labor | B114: 15222.93 | C114: 23913.55 | D114: 19670.79 | E114: 41336.57 | F114: 23672.31 | G114: 9419.99 | H114: 18308.82
A115: IPC | B115: 11228.99 | C115: 10794.51 | D115: 10146.4 | E115: 8112.73 | F115: -1917.2 | G115: 49379.56 | H115: 50660.85
A116: Supervision | B116: 3928.57 | C116: -3928.57 | D116: 0 | E116: -1311.46 | F116: 841.1 | G116: 0 | H116: 0
...

Sheet Jun
A1: TOOMSBORO STANDARD 2025
B3: CERAMICS | E3: CG 280 | H3: CG 300
B4: 25 Standard | C4: 23 Actual | D4: 20 Standard | E4: =$B$4 -> 25 Standard | F4: =+C4 -> 23 Actual | G4: =+D4 -> 20 Standard | H4: =+B4 -> 25 Standard | I4: =+C4 -> 23 Actual | J4: =+D4 -> 20 Standard
C5: (Jan-Sept) | F5: (Jan-Sept) | I5: (Jan-Sept)
A6: Materials | B6: =IF(B24<>0,$D$82,0) -> 0 | C6: 0.0585 | D6: 0.04156581 | E6: =+H82 -> 0 | F6: 0 | G6: 0 | H6: =+D96 -> 0 | I6: 0 | J6: 0
A7: Electricity | B7: =IF(B24<>0,$D$163,0) -> 0 | C7: 0.0105 | D7: 0.020277329 | E7: =G163 -> 0.0198372 | F7: 0 | G7: 0 | H7: =J163 -> 0.0198372 | I7: 0 | J7: 0
A8: Gas | B8: =IF(B24<>0,$D$164,0) -> 0 | C8: 0.0156 | D8: 0.014965 | E8: =G164 -> 0.0171 | F8: 0 | G8: 0 | H8: =J164 -> 0.0171 | I8: 0 | J8: 0
A9: R&M Supplies and Service | B9: =IF(B24<>0,$J$177,0) -> 0 | C9: 0.0192 | D9: 0.015915789 | E9: =$H$177 -> 0.03 | F9: 0 | G9: 0 | H9: =$H$177 -> 0.03 | I9: 0 | J9: 0
A10: Manufacturing Supplies | B10: =IF(B24<>0,$J$181,0) -> 0 | C10: 0.0008 | D10: 0.0026315789 | E10: =$H$181 -> 0.0055102041 | F10: 0 | G10: 0 | H10: =$H$181 -> 0.0055102041 | I10: 0 | J10: 0
A11: Other variable | B11: =IF(B24<>0,$J$184,0) -> 0 | C11: 0.0058 | D11: 0.0094736842 | E11: =$H$184 -> 0.01122449 | F11: 0 | G11: 0 | H11: =$H$184 -> 0.01122449 | I11: 0 | J11: 0
A12: Total Variable Costs | B12: =SUM(B6:B11) -> 0 | C12: =SUM(C6:C11) -> 0.1104 | D12: =SUM(D6:D11) -> 0.10482919 | E12: =SUM(E6:E11) -> 0.083671894 | F12: =SUM(F6:F11) -> 0 | G12: =SUM(G6:G11) -> 0 | H12: =SUM(H6:H11) -> 0.083671894 | I12: =SUM(I6:I11) -> 0 | J12: =SUM(J6:J11) -> 0
A14: Production Labor | B14: =IF($B$24<>0,$F$152/B24/1000,0) -> 0 | C14: 0.0246 | D14: 0.0073599375 | E14: =$D$124*$E$108/$B$49/1000 -> 0.00093026761 | F14: 0 | G14: 0 | H14: =$D$124*$E$108/$B$49/1000 -> 0.00093026761 | I14: 0 | J14: 0
A15: Repairs & Maintenance Labor | B15: =IF($B$24<>0,$F$153/$B$24/1000,0) -> 0 | C15: 0.009 | D15: 0.0042419375 | E15: =$H$124*$E$108/$B$49/1000 -> 0 | F15: 0 | G15: 0 | H15: =$H$124*$E$108/$B$49/1000 -> 0 | I15: 0 | J15: 0
A16: Indirect Payroll Costs (Benefits) | B16: =IF($B$24<>0,$F$155/$B$24/1000,0) -> 0 | C16: 0.0079 | D16: 0.0053897125 | E16: =$D$131*$E$108/$B$49/1000 -> 0 | F16: 0 | G16: 0 | H16: =$D$131*$E$108/$B$49/1000 -> 0 | I16: 0 | J16: 0
A17: Supervision | B17: =IF($B$24<>0,$F$154/$B$24/1000,0) -> 0 | C17: 0 | D17: 0.0026778947 | E17: =$F$194 -> 0 | F17: 0 | G17: 0 | H17: =$F$194 -> 0 | I17: 0 | J17: 0
A18: Depreciation | B18: =IF($B$24<>0,$B$196/$B$49/1000,0) -> 0 | C18: 0.0027 | D18: 0.1672 | E18: =$F$196 -> 0.055866735 | F18: 0 | G18: 0 | H18: =$F$196 -> 0.055866735 | I18: 0 | J18: 0
A19: Insurance & Taxes | B19: =IF($B$24<>0,$B$195/$B$49/1000,0) -> 0 | C19: 0.012 | D19: 0.012884211 | E19: =$F$195 -> 0.23436735 | F19: 0 | G19: 0 | H19: =$F$195 -> 0.23436735 | I19: 0 | J19: 0
A20: Total Fixed Costs | B20: =SUM(B14:B19) -> 0 | C20: =SUM(C14:C19) -> 0.0562 | D20: =SUM(D14:D19) -> 0.19975369 | E20: =SUM(E14:E19) -> 0.29116435 | F20: =SUM(F14:F19) -> 0 | G20: =SUM(G14:G19) -> 0 | H20: =SUM(H14:H19) -> 0.29116435 | I20: =SUM(I14:I19) -> 0 | J20: =SUM(J14:J19) -> 0
A22: TOTAL COSTS PER POUND | B22: =B12+B20 -> 0 | C22: =C12+C20 -> 0.1666 | D22: =D12+D20 -> 0.30458288 | E22: =E12+E20 -> 0.37483624 | F22: =F12+F20 -> 0 | G22: =G12+G20 -> 0 | H22: =H12+H20 -> 0.37483624 | I22: =I12+I20 -> 0 | J22: =J12+J20 -> 0
A24: PRODUCTION ( in 000 lbs ) | B24: =+B54 -> 0 | C24: 0 | D24: 80000 | E24: =+B55 -> 0 | F24: 0 | G24: 0 | H24: =+B56 -> 0 | I24: 0 | J24: 0
B26: XXX | E26: HA PELLETS
B27: =$B$4 -> 25 Standard | C27: =+C4 -> 23 Actual | D27: =+D4 -> 20 Standard | E27: 24 Standard | F27: 23 Actual | G27: 22 Standard | H27: =+B27 -> 25 Standard | I27: =+C27 -> 23 Actual | J27: =+D27 -> 20 Standard
C28: (Jan-Sept) | F28: (Jan-Aug)
A29: Materials | B29: =D82 -> 0.065965818 | C29: 0 | D29: 0 | E29: =IF(E47<>0,$L$96,0) -> 0.070852832 | F29: 0.078 | G29: 0.06025968 | H29: 0 | I29: 0 | J29: 0
A30: Electricity | B30: =D169 -> 0 | C30: 0 | D30: 0 | E30: =IF(E47<>0,$G$169,0) -> 0.043918811 | F30: 0.0432 | G30: 0.026879418 | H30: 0 | I30: 0 | J30: 0
A31: Gas | B31: =D170 -> 0 | C31: 0 | D31: 0 | E31: =IF(E47<>0,$G$170,0) -> 0.026 | F31: 0.019 | G31: 0.028567 | H31: =J170 -> 0 | I31: 0 | J31: 0
A32: R&M Supplies and Service | B32: =IF($B$47<>0,$H$177,0) -> 0 | C32: 0 | D32: 0 | E32: =IF(E47<>0,$H$177,0) -> 0.03 | F32: 0.0298 | G32: 0.027777778 | H32: 0 | I32: 0 | J32: 0
A33: Manufacturing Supplies | B33: =IF($B$47<>0,$H$181,0) -> 0 | C33: 0 | D33: 0 | E33: =IF(E47<>0,$H$181,0) -> 0.0055102041 | F33: 0.0012 | G33: 0.0069444444 | H33: 0 | I33: 0 | J33: 0
A34: Other variable | B34: =IF($B$47<>0,$H$184,0) -> 0 | C34: 0 | D34: 0 | E34: =IF(E47<>0,$H$184,0) -> 0.01122449 | F34: 0.0139 | G34: 0.0125 | H34: 0 | I34: 0 | J34: 0
A35: Total Variable Costs | B35: =SUM(B29:B34) -> 0.065965818 | C35: =SUM(C29:C34) -> 0 | D35: =SUM(D29:D34) -> 0 | E35: =SUM(E29:E34) -> 0.18750634 | F35: =SUM(F29:F34) -> 0.1851 | G35: =SUM(G29:G34) -> 0.16292832 | H35: =SUM(H29:H34) -> 0 | I35: =SUM(I29:I34) -> 0 | J35: =SUM(J29:J34) -> 0
A37: Production Labor | B37: =$D$124*$E$108/$B$49/1000 -> 0.00093026761 | C37: 0 | D37: 0 | E37: =IF($E$47<>0,$F$127/$E$47/1000,0) -> 0.040001507 | F37: 0.0353 | G37: 0.02156921 | H37: 0 | I37: 0 | J37: 0
A38: Repairs & Maintenance Labor | B38: =$H$124*$E$108/$B$49/1000 -> 0 | C38: 0 | D38: 0 | E38: =IF($E$47<>0,$F$128/$E$47/1000,0) -> 0.0048061173 | F38: 0.0067 | G38: 0.0051700857 | H38: 0 | I38: 0 | J38: 0
A39: Indirect Payroll Costs (Benefits) | B39: =$D$131*$E$108/$B$49/1000 -> 0 | C39: 0 | D39: 0 | E39: =IF($E$47<>0,$F$130/$E$47/1000,0) -> 0.012994211 | F39: 0.0112 | G39: 0.0080162316 | H39: 0 | I39: 0 | J39: 0
A40: Supervision | B40: =IF($B$49<>0,$F$194,0) -> 0 | C40: 0 | D40: 0 | E40: =IF($E$47<>0,$F$129/$E$47/1000,0) -> 0 | F40: 0 | G40: 0.00047638889 | H40: 0 | I40: 0 | J40: 0
A41: Depreciation | B41: =IF($B$49<>0,$F$196,0) -> 0.055866735 | C41: 0 | D41: 0 | E41: =IF($E$47<>0,$B$196/$B$49/1000/4,0) -> 0.0011638903 | F41: 0.0085 | G41: 0.0056777778 | H41: 0 | I41: 0 | J41: 0
A42: Insurance & Taxes | B42: =IF($B$49<>0,$F$195,0) -> 0.23436735 | C42: 0 | D42: 0 | E42: =IF($E$47<>0,$B$195/$B$49/1000/4,0) -> 0.0048826531 | F42: 0.0362 | G42: 0.025861111 | H42: 0 | I42: 0 | J42: 0
A43: Total Fixed Costs | B43: =SUM(B37:B42) -> 0.29116435 | C43: =SUM(C37:C42) -> 0 | D43: =SUM(D37:D42) -> 0 | E43: =SUM(E37:E42) -> 0.063848379 | F43: =SUM(F37:F42) -> 0.0979 | G43: =SUM(G37:G42) -> 0.066770805 | H43: =SUM(H37:H42) -> 0 | I43: =SUM(I37:I42) -> 0 | J43: =SUM(J37:J42) -> 0
A44: Excess Costs | F44: -0.0455
A45: TOTAL COSTS PER POUND | B45: =B35+B43 -> 0.35713017 | C45: =C35+C43 -> 0 | D45: 0.19962946 | E45: =E35+E43+E44 -> 0.25135472 | F45: =F35+F43+F44 -> 0.2375 | G45: =+G35+G43 -> 0.22969913 | H45: =H35+H43 -> 0 | I45: =I35+I43 -> 0 | J45: =J35+J43 -> 0 | L45: =E45-0.245 -> 0.0063547165 | M45: =E47*1000*L45 -> 31138.111
M46: =M45/12 -> 2594.8426
A47: PRODUCTION ( in 000 lbs ) | B47: =+B57 -> 0 | C47: 0 | D47: 0 | E47: =+B58 -> 4900 | F47: 15776 | G47: 36000 | H47: =+B59 -> 0 | I47: 0 | J47: 0
A49: TOTAL PLANT PRODUCTION ( in 000 lbs) | B49: =B24+E24+H24+B47+E47+H47 -> 4900 | C49: =C24+F24+I24+C47+F47+I47 -> 15776 | D49: =D24+G24+J24+D47+G47+J47 -> 116000
A51: Variable Costs - Material | B51: Purchase Price/lb * Yield Factor * Scrap Factor * Mix = Std. Cost Contribution
A53: Production Plan: | B53: Pounds (000) | C53: Product Split
A54: Ceramics | B54: ='2025 Summary'!$D$12 -> 0 | C54: =B54/$B$60 -> 0 | E54: =9*400000*7 -> 25200000
A55: CG280 | B55: 0 | C55: =B55/$B$60 -> 0
A56: CG300 | B56: 0 | C56: =B56/$B$60 -> 0
A57: XXX | B57: 0 | C57: =B57/$B$60 -> 0
A58: HA PELLETS | B58: ='2025 Summary'!$E$12 -> 4900 | C58: =B58/$B$60 -> 1
B59: 0 | C59: =B59/$B$60 -> 0
A60: Total | B60: =SUM(B54:B59) -> 4900 | C60: =B60/$B$60 -> 1
C62: Yield Factor | G62: Mix %
A63: Local Kaolin | B63: Price ($/Ton) | C63: Ceramics | D63: CG280 | E63: CG300 | F63: XXX | G63: HA Pellets | H63: Ceramics | I63: CG280 | J63: CG300 | K63: XXX | L63: HA Pellets
A64: Arcilla (local kaolin) 30012 | B64: =11.89*2 -> 23.78 | C64: =$C$76*H64 -> 0 | D64: =$C$86*I64 -> 0 | E64: =$G$86*J64 -> 0 | F64: =$K$86*K64 -> 0 | G64: =$K$86*L64 -> 0 | H64: 0 | I64: 0 | J64: 0 | K64: 0 | L64: 0
B65: 0 | C65: =$C$76*H65 -> 0 | D65: =$C$86*I65 -> 0 | E65: =$G$86*J65 -> 0 | F65: =$K$86*K65 -> 0 | G65: =$K$86*L65 -> 0 | H65: 0 | I65: 0 | J65: 0 | K65: 0 | L65: 0
C66: =SUM(C64:C65) -> 0 | D66: =SUM(D64:D65) -> 0 | E66: =SUM(E64:E65) -> 0 | F66: =SUM(F64:F65) -> 0 | G66: =SUM(G64:G65) -> 0
A67: Bauxite:
A68: Rusal (30008) | B68: 0 | C68: =$C$77*H68 -> 0 | D68: =$C$87*I68 -> 0 | E68: =$G$87*J68 -> 0 | F68: =$K$87*K68 -> 0 | G68: =$K$87*L68 -> 0 | H68: 0 | I68: 0 | J68: 0 | K68: 0 | L68: 0
A69: Kaolin - CE Calcined (30060) | B69: =116.72*2 -> 233.44 | C69: =$C$77*H69 -> 0 | D69: =$C$87*I69 -> 0 | E69: =$G$87*J69 -> 0 | F69: =$K$87*K69 -> 0 | G69: =$K$87*L69 -> 0 | H69: 0 | I69: 0 | J69: 0 | K69: 0 | L69: 0
B70: 0 | C70: 0 | D70: =$C$87*I70 -> 0 | E70: =$G$87*J70 -> 0 | F70: =$K$87*K70 -> 0 | G70: =$K$87*L70 -> 0 | H70: 0 | I70: 0 | J70: 0 | K70: 0 | L70: 0
B71: 0 | C71: 0 | D71: =$C$87*I71 -> 0 | E71: =$G$87*J71 -> 0 | F71: =$K$87*K71 -> 0 | G71: =$K$87*L71 -> 0 | H71: 0 | I71: 0 | J71: 0 | K71: 0 | L71: 0
C72: =SUM(C68:C71) -> 0 | D72: =SUM(D68:D71) -> 0 | E72: =SUM(E68:E71) -> 0 | F72: =SUM(F68:F71) -> 0 | G72: =SUM(G68:G71) -> 0
B74: Ceramics | F74: CG280
B75: Price ($/lb) | C75: Yield Factor | D75: Std $ Contrib | F75: Price ($/lb) | G75: Yield Factor | H75: Std $ Contrib
A76: Local Kaolin | B76: =0.011 -> 0.011 | C76: =AVERAGE(3.6826,3.5997, 2.6808) -> 3.3210333 | D76: =B76*C76 -> 0.036531367 | F76: 0 | G76: 0 | H76: =F76*G76 -> 0
A77: Bauxite | B77: =($B$68*$H$68+$B$69*$H$69+$B$70*$H$70+$B$71*$H$71)/2000 -> 0 | C77: 0 | D77: =B77*C77 -> 0 | F77: =($B$68*$L$68+$B$69*$L$69+$B$70*$L$70+$B$71*$L$71)/2000 -> 0 | G77: 0 | H77: =F77*G77 -> 0
A78: PVA (30017) | B78: 1.838 | C78: 0.0081 | D78: =B78*C78 -> 0.0148878 | F78: =+B78 -> 1.838 | G78: 0 | H78: =F78*G78 -> 0
A79: Dispersant (30011) | B79: =750/1000 -> 0.75 | C79: 0.0161 | D79: =B79*C79 -> 0.012075 | F79: =+B79 -> 0.75 | G79: 0
A80: Ammonia (30000) | B80: =157.43/1000 -> 0.15743 | C80: 0.0157 | D80: =B80*C80 -> 0.002471651 | F80: =+B80 -> 0.15743 | G80: 0 | H80: 0
A82: Total Material Cost Per Pound | D82: =SUM(D76:D80) -> 0.065965818 | H82: =SUM(H76:H80) -> 0
B84: CG300 | F84: XXX | J84: HA Pellets
B85: Price ($/lb) | C85: Yield Factor/BOM | D85: Std $ Contrib | F85: Price ($/lb) | G85: Yield Factor | H85: Std $ Contrib | J85: Price ($/lb) | K85: Yield Factor | L85: Std $ Contrib
A86: Local kaolin | B86: =($B$64*$I$64+$B$65*$I$65)/2000 -> 0 | C86: 0 | D86: =B86*C86 -> 0 | F86: =($B$64*$J$64+$B$65*$J$65)/2000 -> 0 | G86: 0 | H86: =F86*G86 -> 0 | J86: =($B$64*$K$64+$B$65*$K$65)/2000 -> 0 | K86: 0 | L86: =J86*K86 -> 0
A87: Bauxite | B87: =($B$68*$I$68+$B$69*$I$69+$B$70*$I$70+$B$71*$I$71)/2000 -> 0 | C87: 0 | D87: =B87*C87 -> 0 | F87: =($B$68*$J$68+$B$69*$J$69+$B$70*$J$70+$B$71*$J$71)/2000 -> 0 | G87: 0 | H87: =F87*G87 -> 0 | J87: =($B$68*$K$68+$B$69*$K$69+$B$70*$K$70+$B$71*$K$71)/2000 -> 0 | K87: 0 | L87: =J87*K87 -> 0
A88: PVA (30017) | B88: 2.54 | C88: 0 | D88: =B88*C88 -> 0 | F88: =+B88 -> 2.54 | G88: 0 | H88: =F88*G88 -> 0 | J88: 1.964 | K88: 0.020848164 | L88: =J88*K88 -> 0.040945794
A89: Dispersant (30011) | B89: =750/1000 -> 0.75 | C89: 0 | D89: =B89*C89 -> 0 | F89: =+B89 -> 0.75 | G89: 0 | H89: =F89*G89 -> 0 | J89: 0.591 | K89: 0.0031014518 | L89: =J89*K89 -> 0.001832958
A90: Ammonia (30000) | B90: =157.43/1000 -> 0.15743 | C90: 0 | D90: =B90*C90 -> 0 | F90: =+B90 -> 0.15743 | G90: 0 | H90: =F90*G90 -> 0 | J90: 0.105 | K90: 0.1 | L90: =J90*K90 -> 0.0105
A91: Defoamer (30010) | C91: 0 | D91: =B91*C91 -> 0 | F91: =+B91 -> 0 | G91: 0 | H91: =F91*G91 -> 0 | J91: 1.027 | K91: 0.0021752348 | L91: =J91*K91 -> 0.0022339662
A92: Ultrasurf (30341) | C92: 0 | D92: =B92*C92 -> 0 | F92: =+B92 -> 0 | G92: 0 | H92: =F92*G92 -> 0 | J92: 1.389 | K92: 0.0023312553 | L92: =J92*K92 -> 0.0032381137
A93: HA Pallets (30350) | J93: 18.84 | K93: 0.0006 | L93: =J93*K93 -> 0.011304
A94: HA Bag Protectors (30342) | J94: 1.33 | K94: 0.0006 | L94: =J94*K94 -> 0.000798
D95: 0 | H95: 0 | L95: 0
A96: Total Material Cost Per Pound | D96: =SUM(D86:D95) -> 0 | H96: =SUM(H86:H95) -> 0 | L96: =SUM(L86:L95) -> 0.070852832
A98: Variable Cost - Production/R&M Labor & Benefits
F99: W&S Carve Out of Production Labor
A100: Labor Split:
B101: Prod. Plan (000) | C101: Rate (000 lbs/day) | D101: Kiln Days | E101: % Split | F101: 1 | G101: <--EEs | Hrs--> | H101: =(F101*C202*C204)+((F101*C202*C204*D113)) -> 345498296
A102: Ceramics | B102: =B54 -> 0 | C102: 550 | D102: =B102/C102 -> 0 | E102: =D102/D$108 -> 0 | F102: =(F101*C202*C204*C116)+((F101*C202*C204*D113)*C118) -> 18643341 | G102: Payroll | H102: =F102/$H$101 -> 0.053960732 | I102: Rate will be dependant on prodcut size
A103: CG280 | B103: =B55 -> 0 | C103: 0 | D103: 0 | E103: =D103/D$108 -> 0 | F103: =F102*C206 -> 5593002.3 | G103: IPC | H103: =F103/$H$101 -> 0.01618822
A104: CG300 | B104: =B56 -> 0 | C104: 0 | D104: 0 | E104: =D104/D$108 -> 0
A105: XXX | B105: =B57 -> 0 | C105: 0 | D105: 0 | E105: =D105/D$108 -> 0
A106: HA PELLETS | B106: =B58 -> 4900 | C106: 110 | D106: =B106/C106 -> 44.545455 | E106: =D106/D$108 -> 1 | I106: Reduced daily rate to 110 vs. 150
B107: =B59 -> 0 | C107: 0 | D107: 0 | E107: =D107/D$108 -> 0
B108: =SUM(B102:B107) -> 4900 | C108: =B108/D108 -> 110 | D108: =SUM(D102:D107) -> 44.545455 | E108: =D108/D$108 -> 1
A109: HA Group
B112: Jan | C112: Feb | D112: Mar | E112: Apr | F112: May | G112: Jun | H112: Jul
A113: Production Labor | B113: 119702.77 | C113: 140371.43 | D113: 166103.95 | E113: 166766.86 | F113: 105842.43 | G113: 147383.65 | H113: 163283.07
A114: R & M Labor | B114: 15222.93 | C114: 23913.55 | D114: 19670.79 | E114: 41336.57 | F114: 23672.31 | G114: 9419.99 | H114: 18308.82
A115: IPC | B115: 11228.99 | C115: 10794.51 | D115: 10146.4 | E115: 8112.73 | F115: -1917.2 | G115: 49379.56 | H115: 50660.85
A116: Supervision | B116: 3928.57 | C116: -3928.57 | D116: 0 | E116: -1311.46 | F116: 841.1 | G116: 0 | H116: 0
...

Sheet Jul
A1: TOOMSBORO STANDARD 2025
B3: CERAMICS | E3: CG 280 | H3: CG 300
B4: 25 Standard | C4: 23 Actual | D4: 20 Standard | E4: =$B$4 -> 25 Standard | F4: =+C4 -> 23 Actual | G4: =+D4 -> 20 Standard | H4: =+B4 -> 25 Standard | I4: =+C4 -> 23 Actual | J4: =+D4 -> 20 Standard
C5: (Jan-Sept) | F5: (Jan-Sept) | I5: (Jan-Sept)
A6: Materials | B6: =IF(B24<>0,$D$82,0) -> 0 | C6: 0.0585 | D6: 0.04156581 | E6: =+H82 -> 0 | F6: 0 | G6: 0 | H6: =+D96 -> 0 | I6: 0 | J6: 0
A7: Electricity | B7: =IF(B24<>0,$D$163,0) -> 0 | C7: 0.0105 | D7: 0.020277329 | E7: =G163 -> 0.0198372 | F7: 0 | G7: 0 | H7: =J163 -> 0.0198372 | I7: 0 | J7: 0
A8: Gas | B8: =IF(B24<>0,$D$164,0) -> 0 | C8: 0.0156 | D8: 0.014965 | E8: =G164 -> 0.0171 | F8: 0 | G8: 0 | H8: =J164 -> 0.0171 | I8: 0 | J8: 0
A9: R&M Supplies and Service | B9: =IF(B24<>0,$J$177,0) -> 0 | C9: 0.0192 | D9: 0.015915789 | E9: =$H$177 -> 0.03 | F9: 0 | G9: 0 | H9: =$H$177 -> 0.03 | I9: 0 | J9: 0
A10: Manufacturing Supplies | B10: =IF(B24<>0,$J$181,0) -> 0 | C10: 0.0008 | D10: 0.0026315789 | E10: =$H$181 -> 0.0055102041 | F10: 0 | G10: 0 | H10: =$H$181 -> 0.0055102041 | I10: 0 | J10: 0
A11: Other variable | B11: =IF(B24<>0,$J$184,0) -> 0 | C11: 0.0058 | D11: 0.0094736842 | E11: =$H$184 -> 0.01122449 | F11: 0 | G11: 0 | H11: =$H$184 -> 0.01122449 | I11: 0 | J11: 0
A12: Total Variable Costs | B12: =SUM(B6:B11) -> 0 | C12: =SUM(C6:C11) -> 0.1104 | D12: =SUM(D6:D11) -> 0.10482919 | E12: =SUM(E6:E11) -> 0.083671894 | F12: =SUM(F6:F11) -> 0 | G12: =SUM(G6:G11) -> 0 | H12: =SUM(H6:H11) -> 0.083671894 | I12: =SUM(I6:I11) -> 0 | J12: =SUM(J6:J11) -> 0
A14: Production Labor | B14: =IF($B$24<>0,$F$152/B24/1000,0) -> 0 | C14: 0.0246 | D14: 0.0073599375 | E14: =$D$124*$E$108/$B$49/1000 -> 0.00093026761 | F14: 0 | G14: 0 | H14: =$D$124*$E$108/$B$49/1000 -> 0.00093026761 | I14: 0 | J14: 0
A15: Repairs & Maintenance Labor | B15: =IF($B$24<>0,$F$153/$B$24/1000,0) -> 0 | C15: 0.009 | D15: 0.0042419375 | E15: =$H$124*$E$108/$B$49/1000 -> 0 | F15: 0 | G15: 0 | H15: =$H$124*$E$108/$B$49/1000 -> 0 | I15: 0 | J15: 0
A16: Indirect Payroll Costs (Benefits) | B16: =IF($B$24<>0,$F$155/$B$24/1000,0) -> 0 | C16: 0.0079 | D16: 0.0053897125 | E16: =$D$131*$E$108/$B$49/1000 -> 0 | F16: 0 | G16: 0 | H16: =$D$131*$E$108/$B$49/1000 -> 0 | I16: 0 | J16: 0
A17: Supervision | B17: =IF($B$24<>0,$F$154/$B$24/1000,0) -> 0 | C17: 0 | D17: 0.0026778947 | E17: =$F$194 -> 0 | F17: 0 | G17: 0 | H17: =$F$194 -> 0 | I17: 0 | J17: 0
A18: Depreciation | B18: =IF($B$24<>0,$B$196/$B$49/1000,0) -> 0 | C18: 0.0027 | D18: 0.1672 | E18: =$F$196 -> 0.055866735 | F18: 0 | G18: 0 | H18: =$F$196 -> 0.055866735 | I18: 0 | J18: 0
A19: Insurance & Taxes | B19: =IF($B$24<>0,$B$195/$B$49/1000,0) -> 0 | C19: 0.012 | D19: 0.012884211 | E19: =$F$195 -> 0.23436735 | F19: 0 | G19: 0 | H19: =$F$195 -> 0.23436735 | I19: 0 | J19: 0
A20: Total Fixed Costs | B20: =SUM(B14:B19) -> 0 | C20: =SUM(C14:C19) -> 0.0562 | D20: =SUM(D14:D19) -> 0.19975369 | E20: =SUM(E14:E19) -> 0.29116435 | F20: =SUM(F14:F19) -> 0 | G20: =SUM(G14:G19) -> 0 | H20: =SUM(H14:H19) -> 0.29116435 | I20: =SUM(I14:I19) -> 0 | J20: =SUM(J14:J19) -> 0
A22: TOTAL COSTS PER POUND | B22: =B12+B20 -> 0 | C22: =C12+C20 -> 0.1666 | D22: =D12+D20 -> 0.30458288 | E22: =E12+E20 -> 0.37483624 | F22: =F12+F20 -> 0 | G22: =G12+G20 -> 0 | H22: =H12+H20 -> 0.37483624 | I22: =I12+I20 -> 0 | J22: =J12+J20 -> 0
A24: PRODUCTION ( in 000 lbs ) | B24: =+B54 -> 0 | C24: 0 | D24: 80000 | E24: =+B55 -> 0 | F24: 0 | G24: 0 | H24: =+B56 -> 0 | I24: 0 | J24: 0
B26: XXX | E26: HA PELLETS
B27: =$B$4 -> 25 Standard | C27: =+C4 -> 23 Actual | D27: =+D4 -> 20 Standard | E27: 24 Standard | F27: 23 Actual | G27: 22 Standard | H27: =+B27 -> 25 Standard | I27: =+C27 -> 23 Actual | J27: =+D27 -> 20 Standard
C28: (Jan-Sept) | F28: (Jan-Aug)
A29: Materials | B29: =D82 -> 0.065965818 | C29: 0 | D29: 0 | E29: =IF(E47<>0,$L$96,0) -> 0.070852832 | F29: 0.078 | G29: 0.06025968 | H29: 0 | I29: 0 | J29: 0
A30: Electricity | B30: =D169 -> 0 | C30: 0 | D30: 0 | E30: =IF(E47<>0,$G$169,0) -> 0.043918811 | F30: 0.0432 | G30: 0.026879418 | H30: 0 | I30: 0 | J30: 0
A31: Gas | B31: =D170 -> 0 | C31: 0 | D31: 0 | E31: =IF(E47<>0,$G$170,0) -> 0.026 | F31: 0.019 | G31: 0.028567 | H31: =J170 -> 0 | I31: 0 | J31: 0
A32: R&M Supplies and Service | B32: =IF($B$47<>0,$H$177,0) -> 0 | C32: 0 | D32: 0 | E32: =IF(E47<>0,$H$177,0) -> 0.03 | F32: 0.0298 | G32: 0.027777778 | H32: 0 | I32: 0 | J32: 0
A33: Manufacturing Supplies | B33: =IF($B$47<>0,$H$181,0) -> 0 | C33: 0 | D33: 0 | E33: =IF(E47<>0,$H$181,0) -> 0.0055102041 | F33: 0.0012 | G33: 0.0069444444 | H33: 0 | I33: 0 | J33: 0
A34: Other variable | B34: =IF($B$47<>0,$H$184,0) -> 0 | C34: 0 | D34: 0 | E34: =IF(E47<>0,$H$184,0) -> 0.01122449 | F34: 0.0139 | G34: 0.0125 | H34: 0 | I34: 0 | J34: 0
A35: Total Variable Costs | B35: =SUM(B29:B34) -> 0.065965818 | C35: =SUM(C29:C34) -> 0 | D35: =SUM(D29:D34) -> 0 | E35: =SUM(E29:E34) -> 0.18750634 | F35: =SUM(F29:F34) -> 0.1851 | G35: =SUM(G29:G34) -> 0.16292832 | H35: =SUM(H29:H34) -> 0 | I35: =SUM(I29:I34) -> 0 | J35: =SUM(J29:J34) -> 0
A37: Production Labor | B37: =$D$124*$E$108/$B$49/1000 -> 0.00093026761 | C37: 0 | D37: 0 | E37: =IF($E$47<>0,$F$127/$E$47/1000,0) -> 0.040001507 | F37: 0.0353 | G37: 0.02156921 | H37: 0 | I37: 0 | J37: 0
A38: Repairs & Maintenance Labor | B38: =$H$124*$E$108/$B$49/1000 -> 0 | C38: 0 | D38: 0 | E38: =IF($E$47<>0,$F$128/$E$47/1000,0) -> 0.0048061173 | F38: 0.0067 | G38: 0.0051700857 | H38: 0 | I38: 0 | J38: 0
A39: Indirect Payroll Costs (Benefits) | B39: =$D$131*$E$108/$B$49/1000 -> 0 | C39: 0 | D39: 0 | E39: =IF($E$47<>0,$F$130/$E$47/1000,0) -> 0.012994211 | F39: 0.0112 | G39: 0.0080162316 | H39: 0 | I39: 0 | J39: 0
A40: Supervision | B40: =IF($B$49<>0,$F$194,0) -> 0 | C40: 0 | D40: 0 | E40: =IF($E$47<>0,$F$129/$E$47/1000,0) -> 0 | F40: 0 | G40: 0.00047638889 | H40: 0 | I40: 0 | J40: 0
A41: Depreciation | B41: =IF($B$49<>0,$F$196,0) -> 0.055866735 | C41: 0 | D41: 0 | E41: =IF($E$47<>0,$B$196/$B$49/1000/4,0) -> 0.0011638903 | F41: 0.0085 | G41: 0.0056777778 | H41: 0 | I41: 0 | J41: 0
A42: Insurance & Taxes | B42: =IF($B$49<>0,$F$195,0) -> 0.23436735 | C42: 0 | D42: 0 | E42: =IF($E$47<>0,$B$195/$B$49/1000/4,0) -> 0.0048826531 | F42: 0.0362 | G42: 0.025861111 | H42: 0 | I42: 0 | J42: 0
A43: Total Fixed Costs | B43: =SUM(B37:B42) -> 0.29116435 | C43: =SUM(C37:C42) -> 0 | D43: =SUM(D37:D42) -> 0 | E43: =SUM(E37:E42) -> 0.063848379 | F43: =SUM(F37:F42) -> 0.0979 | G43: =SUM(G37:G42) -> 0.066770805 | H43: =SUM(H37:H42) -> 0 | I43: =SUM(I37:I42) -> 0 | J43: =SUM(J37:J42) -> 0
A44: Excess Costs | F44: -0.0455
A45: TOTAL COSTS PER POUND | B45: =B35+B43 -> 0.35713017 | C45: =C35+C43 -> 0 | D45: 0.19962946 | E45: =E35+E43+E44 -> 0.25135472 | F45: =F35+F43+F44 -> 0.2375 | G45: =+G35+G43 -> 0.22969913 | H45: =H35+H43 -> 0 | I45: =I35+I43 -> 0 | J45: =J35+J43 -> 0 | L45: =E45-0.245 -> 0.0063547165 | M45: =E47*1000*L45 -> 31138.111
M46: =M45/12 -> 2594.8426
A47: PRODUCTION ( in 000 lbs ) | B47: =+B57 -> 0 | C47: 0 | D47: 0 | E47: =+B58 -> 4900 | F47: 15776 | G47: 36000 | H47: =+B59 -> 0 | I47: 0 | J47: 0
A49: TOTAL PLANT PRODUCTION ( in 000 lbs) | B49: =B24+E24+H24+B47+E47+H47 -> 4900 | C49: =C24+F24+I24+C47+F47+I47 -> 15776 | D49: =D24+G24+J24+D47+G47+J47 -> 116000
A51: Variable Costs - Material | B51: Purchase Price/lb * Yield Factor * Scrap Factor * Mix = Std. Cost Contribution
A53: Production Plan: | B53: Pounds (000) | C53: Product Split
A54: Ceramics | B54: ='2025 Summary'!$D$13 -> 0 | C54: =B54/$B$60 -> 0 | E54: =9*400000*7 -> 25200000
A55: CG280 | B55: 0 | C55: =B55/$B$60 -> 0
A56: CG300 | B56: 0 | C56: =B56/$B$60 -> 0
A57: XXX | B57: 0 | C57: =B57/$B$60 -> 0
A58: HA PELLETS | B58: ='2025 Summary'!$E$13 -> 4900 | C58: =B58/$B$60 -> 1
B59: 0 | C59: =B59/$B$60 -> 0
A60: Total | B60: =SUM(B54:B59) -> 4900 | C60: =B60/$B$60 -> 1
C62: Yield Factor | G62: Mix %
A63: Local Kaolin | B63: Price ($/Ton) | C63: Ceramics | D63: CG280 | E63: CG300 | F63: XXX | G63: HA Pellets | H63: Ceramics | I63: CG280 | J63: CG300 | K63: XXX | L63: HA Pellets
A64: Arcilla (local kaolin) 30012 | B64: =11.89*2 -> 23.78 | C64: =$C$76*H64 -> 0 | D64: =$C$86*I64 -> 0 | E64: =$G$86*J64 -> 0 | F64: =$K$86*K64 -> 0 | G64: =$K$86*L64 -> 0 | H64: 0 | I64: 0 | J64: 0 | K64: 0 | L64: 0
B65: 0 | C65: =$C$76*H65 -> 0 | D65: =$C$86*I65 -> 0 | E65: =$G$86*J65 -> 0 | F65: =$K$86*K65 -> 0 | G65: =$K$86*L65 -> 0 | H65: 0 | I65: 0 | J65: 0 | K65: 0 | L65: 0
C66: =SUM(C64:C65) -> 0 | D66: =SUM(D64:D65) -> 0 | E66: =SUM(E64:E65) -> 0 | F66: =SUM(F64:F65) -> 0 | G66: =SUM(G64:G65) -> 0
A67: Bauxite:
A68: Rusal (30008) | B68: 0 | C68: =$C$77*H68 -> 0 | D68: =$C$87*I68 -> 0 | E68: =$G$87*J68 -> 0 | F68: =$K$87*K68 -> 0 | G68: =$K$87*L68 -> 0 | H68: 0 | I68: 0 | J68: 0 | K68: 0 | L68: 0
A69: Kaolin - CE Calcined (30060) | B69: =116.72*2 -> 233.44 | C69: =$C$77*H69 -> 0 | D69: =$C$87*I69 -> 0 | E69: =$G$87*J69 -> 0 | F69: =$K$87*K69 -> 0 | G69: =$K$87*L69 -> 0 | H69: 0 | I69: 0 | J69: 0 | K69: 0 | L69: 0
B70: 0 | C70: 0 | D70: =$C$87*I70 -> 0 | E70: =$G$87*J70 -> 0 | F70: =$K$87*K70 -> 0 | G70: =$K$87*L70 -> 0 | H70: 0 | I70: 0 | J70: 0 | K70: 0 | L70: 0
B71: 0 | C71: 0 | D71: =$C$87*I71 -> 0 | E71: =$G$87*J71 -> 0 | F71: =$K$87*K71 -> 0 | G71: =$K$87*L71 -> 0 | H71: 0 | I71: 0 | J71: 0 | K71: 0 | L71: 0
C72: =SUM(C68:C71) -> 0 | D72: =SUM(D68:D71) -> 0 | E72: =SUM(E68:E71) -> 0 | F72: =SUM(F68:F71) -> 0 | G72: =SUM(G68:G71) -> 0
B74: Ceramics | F74: CG280
B75: Price ($/lb) | C75: Yield Factor | D75: Std $ Contrib | F75: Price ($/lb) | G75: Yield Factor | H75: Std $ Contrib
A76: Local Kaolin | B76: =0.011 -> 0.011 | C76: =AVERAGE(3.6826,3.5997, 2.6808) -> 3.3210333 | D76: =B76*C76 -> 0.036531367 | F76: 0 | G76: 0 | H76: =F76*G76 -> 0
A77: Bauxite | B77: =($B$68*$H$68+$B$69*$H$69+$B$70*$H$70+$B$71*$H$71)/2000 -> 0 | C77: 0 | D77: =B77*C77 -> 0 | F77: =($B$68*$L$68+$B$69*$L$69+$B$70*$L$70+$B$71*$L$71)/2000 -> 0 | G77: 0 | H77: =F77*G77 -> 0
A78: PVA (30017) | B78: 1.838 | C78: 0.0081 | D78: =B78*C78 -> 0.0148878 | F78: =+B78 -> 1.838 | G78: 0 | H78: =F78*G78 -> 0
A79: Dispersant (30011) | B79: =750/1000 -> 0.75 | C79: 0.0161 | D79: =B79*C79 -> 0.012075 | F79: =+B79 -> 0.75 | G79: 0
A80: Ammonia (30000) | B80: =157.43/1000 -> 0.15743 | C80: 0.0157 | D80: =B80*C80 -> 0.002471651 | F80: =+B80 -> 0.15743 | G80: 0 | H80: 0
A82: Total Material Cost Per Pound | D82: =SUM(D76:D80) -> 0.065965818 | H82: =SUM(H76:H80) -> 0
B84: CG300 | F84: XXX | J84: HA Pellets
B85: Price ($/lb) | C85: Yield Factor/BOM | D85: Std $ Contrib | F85: Price ($/lb) | G85: Yield Factor | H85: Std $ Contrib | J85: Price ($/lb) | K85: Yield Factor | L85: Std $ Contrib
A86: Local kaolin | B86: =($B$64*$I$64+$B$65*$I$65)/2000 -> 0 | C86: 0 | D86: =B86*C86 -> 0 | F86: =($B$64*$J$64+$B$65*$J$65)/2000 -> 0 | G86: 0 | H86: =F86*G86 -> 0 | J86: =($B$64*$K$64+$B$65*$K$65)/2000 -> 0 | K86: 0 | L86: =J86*K86 -> 0
A87: Bauxite | B87: =($B$68*$I$68+$B$69*$I$69+$B$70*$I$70+$B$71*$I$71)/2000 -> 0 | C87: 0 | D87: =B87*C87 -> 0 | F87: =($B$68*$J$68+$B$69*$J$69+$B$70*$J$70+$B$71*$J$71)/2000 -> 0 | G87: 0 | H87: =F87*G87 -> 0 | J87: =($B$68*$K$68+$B$69*$K$69+$B$70*$K$70+$B$71*$K$71)/2000 -> 0 | K87: 0 | L87: =J87*K87 -> 0
A88: PVA (30017) | B88: 2.54 | C88: 0 | D88: =B88*C88 -> 0 | F88: =+B88 -> 2.54 | G88: 0 | H88: =F88*G88 -> 0 | J88: 1.964 | K88: 0.020848164 | L88: =J88*K88 -> 0.040945794
A89: Dispersant (30011) | B89: =750/1000 -> 0.75 | C89: 0 | D89: =B89*C89 -> 0 | F89: =+B89 -> 0.75 | G89: 0 | H89: =F89*G89 -> 0 | J89: 0.591 | K89: 0.0031014518 | L89: =J89*K89 -> 0.001832958
A90: Ammonia (30000) | B90: =157.43/1000 -> 0.15743 | C90: 0 | D90: =B90*C90 -> 0 | F90: =+B90 -> 0.15743 | G90: 0 | H90: =F90*G90 -> 0 | J90: 0.105 | K90: 0.1 | L90: =J90*K90 -> 0.0105
A91: Defoamer (30010) | C91: 0 | D91: =B91*C91 -> 0 | F91: =+B91 -> 0 | G91: 0 | H91: =F91*G91 -> 0 | J91: 1.027 | K91: 0.0021752348 | L91: =J91*K91 -> 0.0022339662
A92: Ultrasurf (30341) | C92: 0 | D92: =B92*C92 -> 0 | F92: =+B92 -> 0 | G92: 0 | H92: =F92*G92 -> 0 | J92: 1.389 | K92: 0.0023312553 | L92: =J92*K92 -> 0.0032381137
A93: HA Pallets (30350) | J93: 18.84 | K93: 0.0006 | L93: =J93*K93 -> 0.011304
A94: HA Bag Protectors (30342) | J94: 1.33 | K94: 0.0006 | L94: =J94*K94 -> 0.000798
D95: 0 | H95: 0 | L95: 0
A96: Total Material Cost Per Pound | D96: =SUM(D86:D95) -> 0 | H96: =SUM(H86:H95) -> 0 | L96: =SUM(L86:L95) -> 0.070852832
A98: Variable Cost - Production/R&M Labor & Benefits
F99: W&S Carve Out of Production Labor
A100: Labor Split:
B101: Prod. Plan (000) | C101: Rate (000 lbs/day) | D101: Kiln Days | E101: % Split | F101: 1 | G101: <--EEs | Hrs--> | H101: =(F101*C202*C204)+((F101*C202*C204*D113)) -> 345498296
A102: Ceramics | B102: =B54 -> 0 | C102: 550 | D102: =B102/C102 -> 0 | E102: =D102/D$108 -> 0 | F102: =(F101*C202*C204*C116)+((F101*C202*C204*D113)*C118) -> 18643341 | G102: Payroll | H102: =F102/$H$101 -> 0.053960732 | I102: Rate will be dependant on prodcut size
A103: CG280 | B103: =B55 -> 0 | C103: 0 | D103: 0 | E103: =D103/D$108 -> 0 | F103: =F102*C206 -> 5593002.3 | G103: IPC | H103: =F103/$H$101 -> 0.01618822
A104: CG300 | B104: =B56 -> 0 | C104: 0 | D104: 0 | E104: =D104/D$108 -> 0
A105: XXX | B105: =B57 -> 0 | C105: 0 | D105: 0 | E105: =D105/D$108 -> 0
A106: HA PELLETS | B106: =B58 -> 4900 | C106: 110 | D106: =B106/C106 -> 44.545455 | E106: =D106/D$108 -> 1 | I106: Reduced daily rate to 110 vs. 150
B107: =B59 -> 0 | C107: 0 | D107: 0 | E107: =D107/D$108 -> 0
B108: =SUM(B102:B107) -> 4900 | C108: =B108/D108 -> 110 | D108: =SUM(D102:D107) -> 44.545455 | E108: =D108/D$108 -> 1
A109: HA Group
B112: Jan | C112: Feb | D112: Mar | E112: Apr | F112: May | G112: Jun | H112: Jul
A113: Production Labor | B113: 119702.77 | C113: 140371.43 | D113: 166103.95 | E113: 166766.86 | F113: 105842.43 | G113: 147383.65 | H113: 163283.07
A114: R & M Labor | B114: 15222.93 | C114: 23913.55 | D114: 19670.79 | E114: 41336.57 | F114: 23672.31 | G114: 9419.99 | H114: 18308.82
A115: IPC | B115: 11228.99 | C115: 10794.51 | D115: 10146.4 | E115: 8112.73 | F115: -1917.2 | G115: 49379.56 | H115: 50660.85
A116: Supervision | B116: 3928.57 | C116: -3928.57 | D116: 0 | E116: -1311.46 | F116: 841.1 | G116: 0 | H116: 0
...

Sheet Aug
A1: TOOMSBORO STANDARD 2025
B3: CERAMICS | E3: CG 280 | H3: CG 300
B4: 25 Standard | C4: 23 Actual | D4: 20 Standard | E4: =$B$4 -> 25 Standard | F4: =+C4 -> 23 Actual | G4: =+D4 -> 20 Standard | H4: =+B4 -> 25 Standard | I4: =+C4 -> 23 Actual | J4: =+D4 -> 20 Standard
C5: (Jan-Sept) | F5: (Jan-Sept) | I5: (Jan-Sept)
A6: Materials | B6: =IF(B24<>0,$D$82,0) -> 0 | C6: 0.0585 | D6: 0.04156581 | E6: =+H82 -> 0 | F6: 0 | G6: 0 | H6: =+D96 -> 0 | I6: 0 | J6: 0
A7: Electricity | B7: =IF(B24<>0,$D$163,0) -> 0 | C7: 0.0105 | D7: 0.020277329 | E7: =G163 -> 0.0198372 | F7: 0 | G7: 0 | H7: =J163 -> 0.0198372 | I7: 0 | J7: 0
A8: Gas | B8: =IF(B24<>0,$D$164,0) -> 0 | C8: 0.0156 | D8: 0.014965 | E8: =G164 -> 0.0171 | F8: 0 | G8: 0 | H8: =J164 -> 0.0171 | I8: 0 | J8: 0
A9: R&M Supplies and Service | B9: =IF(B24<>0,$J$177,0) -> 0 | C9: 0.0192 | D9: 0.015915789 | E9: =$H$177 -> 0.03 | F9: 0 | G9: 0 | H9: =$H$177 -> 0.03 | I9: 0 | J9: 0
A10: Manufacturing Supplies | B10: =IF(B24<>0,$J$181,0) -> 0 | C10: 0.0008 | D10: 0.0026315789 | E10: =$H$181 -> 0.0055102041 | F10: 0 | G10: 0 | H10: =$H$181 -> 0.0055102041 | I10: 0 | J10: 0
A11: Other variable | B11: =IF(B24<>0,$J$184,0) -> 0 | C11: 0.0058 | D11: 0.0094736842 | E11: =$H$184 -> 0.01122449 | F11: 0 | G11: 0 | H11: =$H$184 -> 0.01122449 | I11: 0 | J11: 0
A12: Total Variable Costs | B12: =SUM(B6:B11) -> 0 | C12: =SUM(C6:C11) -> 0.1104 | D12: =SUM(D6:D11) -> 0.10482919 | E12: =SUM(E6:E11) -> 0.083671894 | F12: =SUM(F6:F11) -> 0 | G12: =SUM(G6:G11) -> 0 | H12: =SUM(H6:H11) -> 0.083671894 | I12: =SUM(I6:I11) -> 0 | J12: =SUM(J6:J11) -> 0
A14: Production Labor | B14: =IF($B$24<>0,$F$152/B24/1000,0) -> 0 | C14: 0.0246 | D14: 0.0073599375 | E14: =$D$124*$E$108/$B$49/1000 -> 0.00093026761 | F14: 0 | G14: 0 | H14: =$D$124*$E$108/$B$49/1000 -> 0.00093026761 | I14: 0 | J14: 0
A15: Repairs & Maintenance Labor | B15: =IF($B$24<>0,$F$153/$B$24/1000,0) -> 0 | C15: 0.009 | D15: 0.0042419375 | E15: =$H$124*$E$108/$B$49/1000 -> 0 | F15: 0 | G15: 0 | H15: =$H$124*$E$108/$B$49/1000 -> 0 | I15: 0 | J15: 0
A16: Indirect Payroll Costs (Benefits) | B16: =IF($B$24<>0,$F$155/$B$24/1000,0) -> 0 | C16: 0.0079 | D16: 0.0053897125 | E16: =$D$131*$E$108/$B$49/1000 -> 0 | F16: 0 | G16: 0 | H16: =$D$131*$E$108/$B$49/1000 -> 0 | I16: 0 | J16: 0
A17: Supervision | B17: =IF($B$24<>0,$F$154/$B$24/1000,0) -> 0 | C17: 0 | D17: 0.0026778947 | E17: =$F$194 -> 0 | F17: 0 | G17: 0 | H17: =$F$194 -> 0 | I17: 0 | J17: 0
A18: Depreciation | B18: =IF($B$24<>0,$B$196/$B$49/1000,0) -> 0 | C18: 0.0027 | D18: 0.1672 | E18: =$F$196 -> 0.055866735 | F18: 0 | G18: 0 | H18: =$F$196 -> 0.055866735 | I18: 0 | J18: 0
A19: Insurance & Taxes | B19: =IF($B$24<>0,$B$195/$B$49/1000,0) -> 0 | C19: 0.012 | D19: 0.012884211 | E19: =$F$195 -> 0.23436735 | F19: 0 | G19: 0 | H19: =$F$195 -> 0.23436735 | I19: 0 | J19: 0
A20: Total Fixed Costs | B20: =SUM(B14:B19) -> 0 | C20: =SUM(C14:C19) -> 0.0562 | D20: =SUM(D14:D19) -> 0.19975369 | E20: =SUM(E14:E19) -> 0.29116435 | F20: =SUM(F14:F19) -> 0 | G20: =SUM(G14:G19) -> 0 | H20: =SUM(H14:H19) -> 0.29116435 | I20: =SUM(I14:I19) -> 0 | J20: =SUM(J14:J19) -> 0
A22: TOTAL COSTS PER POUND | B22: =B12+B20 -> 0 | C22: =C12+C20 -> 0.1666 | D22: =D12+D20 -> 0.30458288 | E22: =E12+E20 -> 0.37483624 | F22: =F12+F20 -> 0 | G22: =G12+G20 -> 0 | H22: =H12+H20 -> 0.37483624 | I22: =I12+I20 -> 0 | J22: =J12+J20 -> 0
A24: PRODUCTION ( in 000 lbs ) | B24: =+B54 -> 0 | C24: 0 | D24: 80000 | E24: =+B55 -> 0 | F24: 0 | G24: 0 | H24: =+B56 -> 0 | I24: 0 | J24: 0
B26: XXX | E26: HA PELLETS
B27: =$B$4 -> 25 Standard | C27: =+C4 -> 23 Actual | D27: =+D4 -> 20 Standard | E27: 24 Standard | F27: 23 Actual | G27: 22 Standard | H27: =+B27 -> 25 Standard | I27: =+C27 -> 23 Actual | J27: =+D27 -> 20 Standard
C28: (Jan-Sept) | F28: (Jan-Aug)
A29: Materials | B29: =D82 -> 0.065965818 | C29: 0 | D29: 0 | E29: =IF(E47<>0,$L$96,0) -> 0.070852832 | F29: 0.078 | G29: 0.06025968 | H29: 0 | I29: 0 | J29: 0
A30: Electricity | B30: =D169 -> 0 | C30: 0 | D30: 0 | E30: =IF(E47<>0,$G$169,0) -> 0.043918811 | F30: 0.0432 | G30: 0.026879418 | H30: 0 | I30: 0 | J30: 0
A31: Gas | B31: =D170 -> 0 | C31: 0 | D31: 0 | E31: =IF(E47<>0,$G$170,0) -> 0.026 | F31: 0.019 | G31: 0.028567 | H31: =J170 -> 0 | I31: 0 | J31: 0
A32: R&M Supplies and Service | B32: =IF($B$47<>0,$H$177,0) -> 0 | C32: 0 | D32: 0 | E32: =IF(E47<>0,$H$177,0) -> 0.03 | F32: 0.0298 | G32: 0.027777778 | H32: 0 | I32: 0 | J32: 0
A33: Manufacturing Supplies | B33: =IF($B$47<>0,$H$181,0) -> 0 | C33: 0 | D33: 0 | E33: =IF(E47<>0,$H$181,0) -> 0.0055102041 | F33: 0.0012 | G33: 0.0069444444 | H33: 0 | I33: 0 | J33: 0
A34: Other variable | B34: =IF($B$47<>0,$H$184,0) -> 0 | C34: 0 | D34: 0 | E34: =IF(E47<>0,$H$184,0) -> 0.01122449 | F34: 0.0139 | G34: 0.0125 | H34: 0 | I34: 0 | J34: 0
A35: Total Variable Costs | B35: =SUM(B29:B34) -> 0.065965818 | C35: =SUM(C29:C34) -> 0 | D35: =SUM(D29:D34) -> 0 | E35: =SUM(E29:E34) -> 0.18750634 | F35: =SUM(F29:F34) -> 0.1851 | G35: =SUM(G29:G34) -> 0.16292832 | H35: =SUM(H29:H34) -> 0 | I35: =SUM(I29:I34) -> 0 | J35: =SUM(J29:J34) -> 0
A37: Production Labor | B37: =$D$124*$E$108/$B$49/1000 -> 0.00093026761 | C37: 0 | D37: 0 | E37: =IF($E$47<>0,$F$127/$E$47/1000,0) -> 0.040001507 | F37: 0.0353 | G37: 0.02156921 | H37: 0 | I37: 0 | J37: 0
A38: Repairs & Maintenance Labor | B38: =$H$124*$E$108/$B$49/1000 -> 0 | C38: 0 | D38: 0 | E38: =IF($E$47<>0,$F$128/$E$47/1000,0) -> 0.0048061173 | F38: 0.0067 | G38: 0.0051700857 | H38: 0 | I38: 0 | J38: 0
A39: Indirect Payroll Costs (Benefits) | B39: =$D$131*$E$108/$B$49/1000 -> 0 | C39: 0 | D39: 0 | E39: =IF($E$47<>0,$F$130/$E$47/1000,0) -> 0.012994211 | F39: 0.0112 | G39: 0.0080162316 | H39: 0 | I39: 0 | J39: 0
A40: Supervision | B40: =IF($B$49<>0,$F$194,0) -> 0 | C40: 0 | D40: 0 | E40: =IF($E$47<>0,$F$129/$E$47/1000,0) -> 0 | F40: 0 | G40: 0.00047638889 | H40: 0 | I40: 0 | J40: 0
A41: Depreciation | B41: =IF($B$49<>0,$F$196,0) -> 0.055866735 | C41: 0 | D41: 0 | E41: =IF($E$47<>0,$B$196/$B$49/1000/4,0) -> 0.0011638903 | F41: 0.0085 | G41: 0.0056777778 | H41: 0 | I41: 0 | J41: 0
A42: Insurance & Taxes | B42: =IF($B$49<>0,$F$195,0) -> 0.23436735 | C42: 0 | D42: 0 | E42: =IF($E$47<>0,$B$195/$B$49/1000/4,0) -> 0.0048826531 | F42: 0.0362 | G42: 0.025861111 | H42: 0 | I42: 0 | J42: 0
A43: Total Fixed Costs | B43: =SUM(B37:B42) -> 0.29116435 | C43: =SUM(C37:C42) -> 0 | D43: =SUM(D37:D42) -> 0 | E43: =SUM(E37:E42) -> 0.063848379 | F43: =SUM(F37:F42) -> 0.0979 | G43: =SUM(G37:G42) -> 0.066770805 | H43: =SUM(H37:H42) -> 0 | I43: =SUM(I37:I42) -> 0 | J43: =SUM(J37:J42) -> 0
A44: Excess Costs | F44: -0.0455
A45: TOTAL COSTS PER POUND | B45: =B35+B43 -> 0.35713017 | C45: =C35+C43 -> 0 | D45: 0.19962946 | E45: =E35+E43+E44 -> 0.25135472 | F45: =F35+F43+F44 -> 0.2375 | G45: =+G35+G43 -> 0.22969913 | H45: =H35+H43 -> 0 | I45: =I35+I43 -> 0 | J45: =J35+J43 -> 0 | L45: =E45-0.245 -> 0.0063547165 | M45: =E47*1000*L45 -> 31138.111
M46: =M45/12 -> 2594.8426
A47: PRODUCTION ( in 000 lbs ) | B47: =+B57 -> 0 | C47: 0 | D47: 0 | E47: =+B58 -> 4900 | F47: 15776 | G47: 36000 | H47: =+B59 -> 0 | I47: 0 | J47: 0
A49: TOTAL PLANT PRODUCTION ( in 000 lbs) | B49: =B24+E24+H24+B47+E47+H47 -> 4900 | C49: =C24+F24+I24+C47+F47+I47 -> 15776 | D49: =D24+G24+J24+D47+G47+J47 -> 116000
A51: Variable Costs - Material | B51: Purchase Price/lb * Yield Factor * Scrap Factor * Mix = Std. Cost Contribution
A53: Production Plan: | B53: Pounds (000) | C53: Product Split
A54: Ceramics | B54: ='2025 Summary'!$D$14 -> 0 | C54: =B54/$B$60 -> 0 | E54: =9*400000*7 -> 25200000
A55: CG280 | B55: 0 | C55: =B55/$B$60 -> 0
A56: CG300 | B56: 0 | C56: =B56/$B$60 -> 0
A57: XXX | B57: 0 | C57: =B57/$B$60 -> 0
A58: HA PELLETS | B58: ='2025 Summary'!$E$14 -> 4900 | C58: =B58/$B$60 -> 1
B59: 0 | C59: =B59/$B$60 -> 0
A60: Total | B60: =SUM(B54:B59) -> 4900 | C60: =B60/$B$60 -> 1
C62: Yield Factor | G62: Mix %
A63: Local Kaolin | B63: Price ($/Ton) | C63: Ceramics | D63: CG280 | E63: CG300 | F63: XXX | G63: HA Pellets | H63: Ceramics | I63: CG280 | J63: CG300 | K63: XXX | L63: HA Pellets
A64: Arcilla (local kaolin) 30012 | B64: =11.89*2 -> 23.78 | C64: =$C$76*H64 -> 0 | D64: =$C$86*I64 -> 0 | E64: =$G$86*J64 -> 0 | F64: =$K$86*K64 -> 0 | G64: =$K$86*L64 -> 0 | H64: 0 | I64: 0 | J64: 0 | K64: 0 | L64: 0
B65: 0 | C65: =$C$76*H65 -> 0 | D65: =$C$86*I65 -> 0 | E65: =$G$86*J65 -> 0 | F65: =$K$86*K65 -> 0 | G65: =$K$86*L65 -> 0 | H65: 0 | I65: 0 | J65: 0 | K65: 0 | L65: 0
C66: =SUM(C64:C65) -> 0 | D66: =SUM(D64:D65) -> 0 | E66: =SUM(E64:E65) -> 0 | F66: =SUM(F64:F65) -> 0 | G66: =SUM(G64:G65) -> 0
A67: Bauxite:
A68: Rusal (30008) | B68: 0 | C68: =$C$77*H68 -> 0 | D68: =$C$87*I68 -> 0 | E68: =$G$87*J68 -> 0 | F68: =$K$87*K68 -> 0 | G68: =$K$87*L68 -> 0 | H68: 0 | I68: 0 | J68: 0 | K68: 0 | L68: 0
A69: Kaolin - CE Calcined (30060) | B69: =116.72*2 -> 233.44 | C69: =$C$77*H69 -> 0 | D69: =$C$87*I69 -> 0 | E69: =$G$87*J69 -> 0 | F69: =$K$87*K69 -> 0 | G69: =$K$87*L69 -> 0 | H69: 0 | I69: 0 | J69: 0 | K69: 0 | L69: 0
B70: 0 | C70: 0 | D70: =$C$87*I70 -> 0 | E70: =$G$87*J70 -> 0 | F70: =$K$87*K70 -> 0 | G70: =$K$87*L70 -> 0 | H70: 0 | I70: 0 | J70: 0 | K70: 0 | L70: 0
B71: 0 | C71: 0 | D71: =$C$87*I71 -> 0 | E71: =$G$87*J71 -> 0 | F71: =$K$87*K71 -> 0 | G71: =$K$87*L71 -> 0 | H71: 0 | I71: 0 | J71: 0 | K71: 0 | L71: 0
C72: =SUM(C68:C71) -> 0 | D72: =SUM(D68:D71) -> 0 | E72: =SUM(E68:E71) -> 0 | F72: =SUM(F68:F71) -> 0 | G72: =SUM(G68:G71) -> 0
B74: Ceramics | F74: CG280
B75: Price ($/lb) | C75: Yield Factor | D75: Std $ Contrib | F75: Price ($/lb) | G75: Yield Factor | H75: Std $ Contrib
A76: Local Kaolin | B76: =0.011 -> 0.011 | C76: =AVERAGE(3.6826,3.5997, 2.6808) -> 3.3210333 | D76: =B76*C76 -> 0.036531367 | F76: 0 | G76: 0 | H76: =F76*G76 -> 0
A77: Bauxite | B77: =($B$68*$H$68+$B$69*$H$69+$B$70*$H$70+$B$71*$H$71)/2000 -> 0 | C77: 0 | D77: =B77*C77 -> 0 | F77: =($B$68*$L$68+$B$69*$L$69+$B$70*$L$70+$B$71*$L$71)/2000 -> 0 | G77: 0 | H77: =F77*G77 -> 0
A78: PVA (30017) | B78: 1.838 | C78: 0.0081 | D78: =B78*C78 -> 0.0148878 | F78: =+B78 -> 1.838 | G78: 0 | H78: =F78*G78 -> 0
A79: Dispersant (30011) | B79: =750/1000 -> 0.75 | C79: 0.0161 | D79: =B79*C79 -> 0.012075 | F79: =+B79 -> 0.75 | G79: 0
A80: Ammonia (30000) | B80: =157.43/1000 -> 0.15743 | C80: 0.0157 | D80: =B80*C80 -> 0.002471651 | F80: =+B80 -> 0.15743 | G80: 0 | H80: 0
A82: Total Material Cost Per Pound | D82: =SUM(D76:D80) -> 0.065965818 | H82: =SUM(H76:H80) -> 0
B84: CG300 | F84: XXX | J84: HA Pellets
B85: Price ($/lb) | C85: Yield Factor/BOM | D85: Std $ Contrib | F85: Price ($/lb) | G85: Yield Factor | H85: Std $ Contrib | J85: Price ($/lb) | K85: Yield Factor | L85: Std $ Contrib
A86: Local kaolin | B86: =($B$64*$I$64+$B$65*$I$65)/2000 -> 0 | C86: 0 | D86: =B86*C86 -> 0 | F86: =($B$64*$J$64+$B$65*$J$65)/2000 -> 0 | G86: 0 | H86: =F86*G86 -> 0 | J86: =($B$64*$K$64+$B$65*$K$65)/2000 -> 0 | K86: 0 | L86: =J86*K86 -> 0
A87: Bauxite | B87: =($B$68*$I$68+$B$69*$I$69+$B$70*$I$70+$B$71*$I$71)/2000 -> 0 | C87: 0 | D87: =B87*C87 -> 0 | F87: =($B$68*$J$68+$B$69*$J$69+$B$70*$J$70+$B$71*$J$71)/2000 -> 0 | G87: 0 | H87: =F87*G87 -> 0 | J87: =($B$68*$K$68+$B$69*$K$69+$B$70*$K$70+$B$71*$K$71)/2000 -> 0 | K87: 0 | L87: =J87*K87 -> 0
A88: PVA (30017) | B88: 2.54 | C88: 0 | D88: =B88*C88 -> 0 | F88: =+B88 -> 2.54 | G88: 0 | H88: =F88*G88 -> 0 | J88: 1.964 | K88: 0.020848164 | L88: =J88*K88 -> 0.040945794
A89: Dispersant (30011) | B89: =750/1000 -> 0.75 | C89: 0 | D89: =B89*C89 -> 0 | F89: =+B89 -> 0.75 | G89: 0 | H89: =F89*G89 -> 0 | J89: 0.591 | K89: 0.0031014518 | L89: =J89*K89 -> 0.001832958
A90: Ammonia (30000) | B90: =157.43/1000 -> 0.15743 | C90: 0 | D90: =B90*C90 -> 0 | F90: =+B90 -> 0.15743 | G90: 0 | H90: =F90*G90 -> 0 | J90: 0.105 | K90: 0.1 | L90: =J90*K90 -> 0.0105
A91: Defoamer (30010) | C91: 0 | D91: =B91*C91 -> 0 | F91: =+B91 -> 0 | G91: 0 | H91: =F91*G91 -> 0 | J91: 1.027 | K91: 0.0021752348 | L91: =J91*K91 -> 0.0022339662
A92: Ultrasurf (30341) | C92: 0 | D92: =B92*C92 -> 0 | F92: =+B92 -> 0 | G92: 0 | H92: =F92*G92 -> 0 | J92: 1.389 | K92: 0.0023312553 | L92: =J92*K92 -> 0.0032381137
A93: HA Pallets (30350) | J93: 18.84 | K93: 0.0006 | L93: =J93*K93 -> 0.011304
A94: HA Bag Protectors (30342) | J94: 1.33 | K94: 0.0006 | L94: =J94*K94 -> 0.000798
D95: 0 | H95: 0 | L95: 0
A96: Total Material Cost Per Pound | D96: =SUM(D86:D95) -> 0 | H96: =SUM(H86:H95) -> 0 | L96: =SUM(L86:L95) -> 0.070852832
A98: Variable Cost - Production/R&M Labor & Benefits
F99: W&S Carve Out of Production Labor
A100: Labor Split:
B101: Prod. Plan (000) | C101: Rate (000 lbs/day) | D101: Kiln Days | E101: % Split | F101: 1 | G101: <--EEs | Hrs--> | H101: =(F101*C202*C204)+((F101*C202*C204*D113)) -> 345498296
A102: Ceramics | B102: =B54 -> 0 | C102: 550 | D102: =B102/C102 -> 0 | E102: =D102/D$108 -> 0 | F102: =(F101*C202*C204*C116)+((F101*C202*C204*D113)*C118) -> 18643341 | G102: Payroll | H102: =F102/$H$101 -> 0.053960732 | I102: Rate will be dependant on prodcut size
A103: CG280 | B103: =B55 -> 0 | C103: 0 | D103: 0 | E103: =D103/D$108 -> 0 | F103: =F102*C206 -> 5593002.3 | G103: IPC | H103: =F103/$H$101 -> 0.01618822
A104: CG300 | B104: =B56 -> 0 | C104: 0 | D104: 0 | E104: =D104/D$108 -> 0
A105: XXX | B105: =B57 -> 0 | C105: 0 | D105: 0 | E105: =D105/D$108 -> 0
A106: HA PELLETS | B106: =B58 -> 4900 | C106: 110 | D106: =B106/C106 -> 44.545455 | E106: =D106/D$108 -> 1 | I106: Reduced daily rate to 110 vs. 150
B107: =B59 -> 0 | C107: 0 | D107: 0 | E107: =D107/D$108 -> 0
B108: =SUM(B102:B107) -> 4900 | C108: =B108/D108 -> 110 | D108: =SUM(D102:D107) -> 44.545455 | E108: =D108/D$108 -> 1
A109: HA Group
B112: Jan | C112: Feb | D112: Mar | E112: Apr | F112: May | G112: Jun | H112: Jul
A113: Production Labor | B113: 119702.77 | C113: 140371.43 | D113: 166103.95 | E113: 166766.86 | F113: 105842.43 | G113: 147383.65 | H113: 163283.07
A114: R & M Labor | B114: 15222.93 | C114: 23913.55 | D114: 19670.79 | E114: 41336.57 | F114: 23672.31 | G114: 9419.99 | H114: 18308.82
A115: IPC | B115: 11228.99 | C115: 10794.51 | D115: 10146.4 | E115: 8112.73 | F115: -1917.2 | G115: 49379.56 | H115: 50660.85
A116: Supervision | B116: 3928.57 | C116: -3928.57 | D116: 0 | E116: -1311.46 | F116: 841.1 | G116: 0 | H116: 0
...

Sheet Sep
A1: TOOMSBORO STANDARD 2025
B3: CERAMICS | E3: CG 280 | H3: CG 300
B4: 25 Standard | C4: 23 Actual | D4: 20 Standard | E4: =$B$4 -> 25 Standard | F4: =+C4 -> 23 Actual | G4: =+D4 -> 20 Standard | H4: =+B4 -> 25 Standard | I4: =+C4 -> 23 Actual | J4: =+D4 -> 20 Standard
C5: (Jan-Sept) | F5: (Jan-Sept) | I5: (Jan-Sept)
A6: Materials | B6: =IF(B24<>0,$D$82,0) -> 0 | C6: 0.0585 | D6: 0.04156581 | E6: =+H82 -> 0 | F6: 0 | G6: 0 | H6: =+D96 -> 0 | I6: 0 | J6: 0
A7: Electricity | B7: =IF(B24<>0,$D$163,0) -> 0 | C7: 0.0105 | D7: 0.020277329 | E7: =G163 -> 0.0198372 | F7: 0 | G7: 0 | H7: =J163 -> 0.0198372 | I7: 0 | J7: 0
A8: Gas | B8: =IF(B24<>0,$D$164,0) -> 0 | C8: 0.0156 | D8: 0.014965 | E8: =G164 -> 0.0171 | F8: 0 | G8: 0 | H8: =J164 -> 0.0171 | I8: 0 | J8: 0
A9: R&M Supplies and Service | B9: =IF(B24<>0,$J$177,0) -> 0 | C9: 0.0192 | D9: 0.015915789 | E9: =$H$177 -> 0.03 | F9: 0 | G9: 0 | H9: =$H$177 -> 0.03 | I9: 0 | J9: 0
A10: Manufacturing Supplies | B10: =IF(B24<>0,$J$181,0) -> 0 | C10: 0.0008 | D10: 0.0026315789 | E10: =$H$181 -> 0.0055102041 | F10: 0 | G10: 0 | H10: =$H$181 -> 0.0055102041 | I10: 0 | J10: 0
A11: Other variable | B11: =IF(B24<>0,$J$184,0) -> 0 | C11: 0.0058 | D11: 0.0094736842 | E11: =$H$184 -> 0.01122449 | F11: 0 | G11: 0 | H11: =$H$184 -> 0.01122449 | I11: 0 | J11: 0
A12: Total Variable Costs | B12: =SUM(B6:B11) -> 0 | C12: =SUM(C6:C11) -> 0.1104 | D12: =SUM(D6:D11) -> 0.10482919 | E12: =SUM(E6:E11) -> 0.083671894 | F12: =SUM(F6:F11) -> 0 | G12: =SUM(G6:G11) -> 0 | H12: =SUM(H6:H11) -> 0.083671894 | I12: =SUM(I6:I11) -> 0 | J12: =SUM(J6:J11) -> 0
A14: Production Labor | B14: =IF($B$24<>0,$F$152/B24/1000,0) -> 0 | C14: 0.0246 | D14: 0.0073599375 | E14: =$D$124*$E$108/$B$49/1000 -> 0.00093026761 | F14: 0 | G14: 0 | H14: =$D$124*$E$108/$B$49/1000 -> 0.00093026761 | I14: 0 | J14: 0
A15: Repairs & Maintenance Labor | B15: =IF($B$24<>0,$F$153/$B$24/1000,0) -> 0 | C15: 0.009 | D15: 0.0042419375 | E15: =$H$124*$E$108/$B$49/1000 -> 0 | F15: 0 | G15: 0 | H15: =$H$124*$E$108/$B$49/1000 -> 0 | I15: 0 | J15: 0
A16: Indirect Payroll Costs (Benefits) | B16: =IF($B$24<>0,$F$155/$B$24/1000,0) -> 0 | C16: 0.0079 | D16: 0.0053897125 | E16: =$D$131*$E$108/$B$49/1000 -> 0 | F16: 0 | G16: 0 | H16: =$D$131*$E$108/$B$49/1000 -> 0 | I16: 0 | J16: 0
A17: Supervision | B17: =IF($B$24<>0,$F$154/$B$24/1000,0) -> 0 | C17: 0 | D17: 0.0026778947 | E17: =$F$194 -> 0 | F17: 0 | G17: 0 | H17: =$F$194 -> 0 | I17: 0 | J17: 0
A18: Depreciation | B18: =IF($B$24<>0,$B$196/$B$49/1000,0) -> 0 | C18: 0.0027 | D18: 0.1672 | E18: =$F$196 -> 0.055866735 | F18: 0 | G18: 0 | H18: =$F$196 -> 0.055866735 | I18: 0 | J18: 0
A19: Insurance & Taxes | B19: =IF($B$24<>0,$B$195/$B$49/1000,0) -> 0 | C19: 0.012 | D19: 0.012884211 | E19: =$F$195 -> 0.23436735 | F19: 0 | G19: 0 | H19: =$F$195 -> 0.23436735 | I19: 0 | J19: 0
A20: Total Fixed Costs | B20: =SUM(B14:B19) -> 0 | C20: =SUM(C14:C19) -> 0.0562 | D20: =SUM(D14:D19) -> 0.19975369 | E20: =SUM(E14:E19) -> 0.29116435 | F20: =SUM(F14:F19) -> 0 | G20: =SUM(G14:G19) -> 0 | H20: =SUM(H14:H19) -> 0.29116435 | I20: =SUM(I14:I19) -> 0 | J20: =SUM(J14:J19) -> 0
A22: TOTAL COSTS PER POUND | B22: =B12+B20 -> 0 | C22: =C12+C20 -> 0.1666 | D22: =D12+D20 -> 0.30458288 | E22: =E12+E20 -> 0.37483624 | F22: =F12+F20 -> 0 | G22: =G12+G20 -> 0 | H22: =H12+H20 -> 0.37483624 | I22: =I12+I20 -> 0 | J22: =J12+J20 -> 0
A24: PRODUCTION ( in 000 lbs ) | B24: =+B54 -> 0 | C24: 0 | D24: 80000 | E24: =+B55 -> 0 | F24: 0 | G24: 0 | H24: =+B56 -> 0 | I24: 0 | J24: 0
B26: XXX | E26: HA PELLETS
B27: =$B$4 -> 25 Standard | C27: =+C4 -> 23 Actual | D27: =+D4 -> 20 Standard | E27: 24 Standard | F27: 23 Actual | G27: 22 Standard | H27: =+B27 -> 25 Standard | I27: =+C27 -> 23 Actual | J27: =+D27 -> 20 Standard
C28: (Jan-Sept) | F28: (Jan-Aug)
A29: Materials | B29: =D82 -> 0.065965818 | C29: 0 | D29: 0 | E29: =IF(E47<>0,$L$96,0) -> 0.070852832 | F29: 0.078 | G29: 0.06025968 | H29: 0 | I29: 0 | J29: 0
A30: Electricity | B30: =D169 -> 0 | C30: 0 | D30: 0 | E30: =IF(E47<>0,$G$169,0) -> 0.043918811 | F30: 0.0432 | G30: 0.026879418 | H30: 0 | I30: 0 | J30: 0
A31: Gas | B31: =D170 -> 0 | C31: 0 | D31: 0 | E31: =IF(E47<>0,$G$170,0) -> 0.026 | F31: 0.019 | G31: 0.028567 | H31: =J170 -> 0 | I31: 0 | J31: 0
A32: R&M Supplies and Service | B32: =IF($B$47<>0,$H$177,0) -> 0 | C32: 0 | D32: 0 | E32: =IF(E47<>0,$H$177,0) -> 0.03 | F32: 0.0298 | G32: 0.027777778 | H32: 0 | I32: 0 | J32: 0
A33: Manufacturing Supplies | B33: =IF($B$47<>0,$H$181,0) -> 0 | C33: 0 | D33: 0 | E33: =IF(E47<>0,$H$181,0) -> 0.0055102041 | F33: 0.0012 | G33: 0.0069444444 | H33: 0 | I33: 0 | J33: 0
A34: Other variable | B34: =IF($B$47<>0,$H$184,0) -> 0 | C34: 0 | D34: 0 | E34: =IF(E47<>0,$H$184,0) -> 0.01122449 | F34: 0.0139 | G34: 0.0125 | H34: 0 | I34: 0 | J34: 0
A35: Total Variable Costs | B35: =SUM(B29:B34) -> 0.065965818 | C35: =SUM(C29:C34) -> 0 | D35: =SUM(D29:D34) -> 0 | E35: =SUM(E29:E34) -> 0.18750634 | F35: =SUM(F29:F34) -> 0.1851 | G35: =SUM(G29:G34) -> 0.16292832 | H35: =SUM(H29:H34) -> 0 | I35: =SUM(I29:I34) -> 0 | J35: =SUM(J29:J34) -> 0
A37: Production Labor | B37: =$D$124*$E$108/$B$49/1000 -> 0.00093026761 | C37: 0 | D37: 0 | E37: =IF($E$47<>0,$F$127/$E$47/1000,0) -> 0.040001507 | F37: 0.0353 | G37: 0.02156921 | H37: 0 | I37: 0 | J37: 0
A38: Repairs & Maintenance Labor | B38: =$H$124*$E$108/$B$49/1000 -> 0 | C38: 0 | D38: 0 | E38: =IF($E$47<>0,$F$128/$E$47/1000,0) -> 0.0048061173 | F38: 0.0067 | G38: 0.0051700857 | H38: 0 | I38: 0 | J38: 0
A39: Indirect Payroll Costs (Benefits) | B39: =$D$131*$E$108/$B$49/1000 -> 0 | C39: 0 | D39: 0 | E39: =IF($E$47<>0,$F$130/$E$47/1000,0) -> 0.012994211 | F39: 0.0112 | G39: 0.0080162316 | H39: 0 | I39: 0 | J39: 0
A40: Supervision | B40: =IF($B$49<>0,$F$194,0) -> 0 | C40: 0 | D40: 0 | E40: =IF($E$47<>0,$F$129/$E$47/1000,0) -> 0 | F40: 0 | G40: 0.00047638889 | H40: 0 | I40: 0 | J40: 0
A41: Depreciation | B41: =IF($B$49<>0,$F$196,0) -> 0.055866735 | C41: 0 | D41: 0 | E41: =IF($E$47<>0,$B$196/$B$49/1000/4,0) -> 0.0011638903 | F41: 0.0085 | G41: 0.0056777778 | H41: 0 | I41: 0 | J41: 0
A42: Insurance & Taxes | B42: =IF($B$49<>0,$F$195,0) -> 0.23436735 | C42: 0 | D42: 0 | E42: =IF($E$47<>0,$B$195/$B$49/1000/4,0) -> 0.0048826531 | F42: 0.0362 | G42: 0.025861111 | H42: 0 | I42: 0 | J42: 0
A43: Total Fixed Costs | B43: =SUM(B37:B42) -> 0.29116435 | C43: =SUM(C37:C42) -> 0 | D43: =SUM(D37:D42) -> 0 | E43: =SUM(E37:E42) -> 0.063848379 | F43: =SUM(F37:F42) -> 0.0979 | G43: =SUM(G37:G42) -> 0.066770805 | H43: =SUM(H37:H42) -> 0 | I43: =SUM(I37:I42) -> 0 | J43: =SUM(J37:J42) -> 0
A44: Excess Costs | F44: -0.0455
A45: TOTAL COSTS PER POUND | B45: =B35+B43 -> 0.35713017 | C45: =C35+C43 -> 0 | D45: 0.19962946 | E45: =E35+E43+E44 -> 0.25135472 | F45: =F35+F43+F44 -> 0.2375 | G45: =+G35+G43 -> 0.22969913 | H45: =H35+H43 -> 0 | I45: =I35+I43 -> 0 | J45: =J35+J43 -> 0 | L45: =E45-0.245 -> 0.0063547165 | M45: =E47*1000*L45 -> 31138.111
M46: =M45/12 -> 2594.8426
A47: PRODUCTION ( in 000 lbs ) | B47: =+B57 -> 0 | C47: 0 | D47: 0 | E47: =+B58 -> 4900 | F47: 15776 | G47: 36000 | H47: =+B59 -> 0 | I47: 0 | J47: 0
A49: TOTAL PLANT PRODUCTION ( in 000 lbs) | B49: =B24+E24+H24+B47+E47+H47 -> 4900 | C49: =C24+F24+I24+C47+F47+I47 -> 15776 | D49: =D24+G24+J24+D47+G47+J47 -> 116000
A51: Variable Costs - Material | B51: Purchase Price/lb * Yield Factor * Scrap Factor * Mix = Std. Cost Contribution
A53: Production Plan: | B53: Pounds (000) | C53: Product Split
A54: Ceramics | B54: ='2025 Summary'!$D$15 -> 0 | C54: =B54/$B$60 -> 0 | E54: =9*400000*7 -> 25200000
A55: CG280 | B55: 0 | C55: =B55/$B$60 -> 0
A56: CG300 | B56: 0 | C56: =B56/$B$60 -> 0
A57: XXX | B57: 0 | C57: =B57/$B$60 -> 0
A58: HA PELLETS | B58: ='2025 Summary'!$E$15 -> 4900 | C58: =B58/$B$60 -> 1
B59: 0 | C59: =B59/$B$60 -> 0
A60: Total | B60: =SUM(B54:B59) -> 4900 | C60: =B60/$B$60 -> 1
C62: Yield Factor | G62: Mix %
A63: Local Kaolin | B63: Price ($/Ton) | C63: Ceramics | D63: CG280 | E63: CG300 | F63: XXX | G63: HA Pellets | H63: Ceramics | I63: CG280 | J63: CG300 | K63: XXX | L63: HA Pellets
A64: Arcilla (local kaolin) 30012 | B64: =11.89*2 -> 23.78 | C64: =$C$76*H64 -> 0 | D64: =$C$86*I64 -> 0 | E64: =$G$86*J64 -> 0 | F64: =$K$86*K64 -> 0 | G64: =$K$86*L64 -> 0 | H64: 0 | I64: 0 | J64: 0 | K64: 0 | L64: 0
B65: 0 | C65: =$C$76*H65 -> 0 | D65: =$C$86*I65 -> 0 | E65: =$G$86*J65 -> 0 | F65: =$K$86*K65 -> 0 | G65: =$K$86*L65 -> 0 | H65: 0 | I65: 0 | J65: 0 | K65: 0 | L65: 0
C66: =SUM(C64:C65) -> 0 | D66: =SUM(D64:D65) -> 0 | E66: =SUM(E64:E65) -> 0 | F66: =SUM(F64:F65) -> 0 | G66: =SUM(G64:G65) -> 0
A67: Bauxite:
A68: Rusal (30008) | B68: 0 | C68: =$C$77*H68 -> 0 | D68: =$C$87*I68 -> 0 | E68: =$G$87*J68 -> 0 | F68: =$K$87*K68 -> 0 | G68: =$K$87*L68 -> 0 | H68: 0 | I68: 0 | J68: 0 | K68: 0 | L68: 0
A69: Kaolin - CE Calcined (30060) | B69: =116.72*2 -> 233.44 | C69: =$C$77*H69 -> 0 | D69: =$C$87*I69 -> 0 | E69: =$G$87*J69 -> 0 | F69: =$K$87*K69 -> 0 | G69: =$K$87*L69 -> 0 | H69: 0 | I69: 0 | J69: 0 | K69: 0 | L69: 0
B70: 0 | C70: 0 | D70: =$C$87*I70 -> 0 | E70: =$G$87*J70 -> 0 | F70: =$K$87*K70 -> 0 | G70: =$K$87*L70 -> 0 | H70: 0 | I70: 0 | J70: 0 | K70: 0 | L70: 0
B71: 0 | C71: 0 | D71: =$C$87*I71 -> 0 | E71: =$G$87*J71 -> 0 | F71: =$K$87*K71 -> 0 | G71: =$K$87*L71 -> 0 | H71: 0 | I71: 0 | J71: 0 | K71: 0 | L71: 0
C72: =SUM(C68:C71) -> 0 | D72: =SUM(D68:D71) -> 0 | E72: =SUM(E68:E71) -> 0 | F72: =SUM(F68:F71) -> 0 | G72: =SUM(G68:G71) -> 0
B74: Ceramics | F74: CG280
B75: Price ($/lb) | C75: Yield Factor | D75: Std $ Contrib | F75: Price ($/lb) | G75: Yield Factor | H75: Std $ Contrib
A76: Local Kaolin | B76: =0.011 -> 0.011 | C76: =AVERAGE(3.6826,3.5997, 2.6808) -> 3.3210333 | D76: =B76*C76 -> 0.036531367 | F76: 0 | G76: 0 | H76: =F76*G76 -> 0
A77: Bauxite | B77: =($B$68*$H$68+$B$69*$H$69+$B$70*$H$70+$B$71*$H$71)/2000 -> 0 | C77: 0 | D77: =B77*C77 -> 0 | F77: =($B$68*$L$68+$B$69*$L$69+$B$70*$L$70+$B$71*$L$71)/2000 -> 0 | G77: 0 | H77: =F77*G77 -> 0
A78: PVA (30017) | B78: 1.838 | C78: 0.0081 | D78: =B78*C78 -> 0.0148878 | F78: =+B78 -> 1.838 | G78: 0 | H78: =F78*G78 -> 0
A79: Dispersant (30011) | B79: =750/1000 -> 0.75 | C79: 0.0161 | D79: =B79*C79 -> 0.012075 | F79: =+B79 -> 0.75 | G79: 0
A80: Ammonia (30000) | B80: =157.43/1000 -> 0.15743 | C80: 0.0157 | D80: =B80*C80 -> 0.002471651 | F80: =+B80 -> 0.15743 | G80: 0 | H80: 0
A82: Total Material Cost Per Pound | D82: =SUM(D76:D80) -> 0.065965818 | H82: =SUM(H76:H80) -> 0
B84: CG300 | F84: XXX | J84: HA Pellets
B85: Price ($/lb) | C85: Yield Factor/BOM | D85: Std $ Contrib | F85: Price ($/lb) | G85: Yield Factor | H85: Std $ Contrib | J85: Price ($/lb) | K85: Yield Factor | L85: Std $ Contrib
A86: Local kaolin | B86: =($B$64*$I$64+$B$65*$I$65)/2000 -> 0 | C86: 0 | D86: =B86*C86 -> 0 | F86: =($B$64*$J$64+$B$65*$J$65)/2000 -> 0 | G86: 0 | H86: =F86*G86 -> 0 | J86: =($B$64*$K$64+$B$65*$K$65)/2000 -> 0 | K86: 0 | L86: =J86*K86 -> 0
A87: Bauxite | B87: =($B$68*$I$68+$B$69*$I$69+$B$70*$I$70+$B$71*$I$71)/2000 -> 0 | C87: 0 | D87: =B87*C87 -> 0 | F87: =($B$68*$J$68+$B$69*$J$69+$B$70*$J$70+$B$71*$J$71)/2000 -> 0 | G87: 0 | H87: =F87*G87 -> 0 | J87: =($B$68*$K$68+$B$69*$K$69+$B$70*$K$70+$B$71*$K$71)/2000 -> 0 | K87: 0 | L87: =J87*K87 -> 0
A88: PVA (30017) | B88: 2.54 | C88: 0 | D88: =B88*C88 -> 0 | F88: =+B88 -> 2.54 | G88: 0 | H88: =F88*G88 -> 0 | J88: 1.964 | K88: 0.020848164 | L88: =J88*K88 -> 0.040945794
A89: Dispersant (30011) | B89: =750/1000 -> 0.75 | C89: 0 | D89: =B89*C89 -> 0 | F89: =+B89 -> 0.75 | G89: 0 | H89: =F89*G89 -> 0 | J89: 0.591 | K89: 0.0031014518 | L89: =J89*K89 -> 0.001832958
A90: Ammonia (30000) | B90: =157.43/1000 -> 0.15743 | C90: 0 | D90: =B90*C90 -> 0 | F90: =+B90 -> 0.15743 | G90: 0 | H90: =F90*G90 -> 0 | J90: 0.105 | K90: 0.1 | L90: =J90*K90 -> 0.0105
A91: Defoamer (30010) | C91: 0 | D91: =B91*C91 -> 0 | F91: =+B91 -> 0 | G91: 0 | H91: =F91*G91 -> 0 | J91: 1.027 | K91: 0.0021752348 | L91: =J91*K91 -> 0.0022339662
A92: Ultrasurf (30341) | C92: 0 | D92: =B92*C92 -> 0 | F92: =+B92 -> 0 | G92: 0 | H92: =F92*G92 -> 0 | J92: 1.389 | K92: 0.0023312553 | L92: =J92*K92 -> 0.0032381137
A93: HA Pallets (30350) | J93: 18.84 | K93: 0.0006 | L93: =J93*K93 -> 0.011304
A94: HA Bag Protectors (30342) | J94: 1.33 | K94: 0.0006 | L94: =J94*K94 -> 0.000798
D95: 0 | H95: 0 | L95: 0
A96: Total Material Cost Per Pound | D96: =SUM(D86:D95) -> 0 | H96: =SUM(H86:H95) -> 0 | L96: =SUM(L86:L95) -> 0.070852832
A98: Variable Cost - Production/R&M Labor & Benefits
F99: W&S Carve Out of Production Labor
A100: Labor Split:
B101: Prod. Plan (000) | C101: Rate (000 lbs/day) | D101: Kiln Days | E101: % Split | F101: 1 | G101: <--EEs | Hrs--> | H101: =(F101*C202*C204)+((F101*C202*C204*D113)) -> 345498296
A102: Ceramics | B102: =B54 -> 0 | C102: 550 | D102: =B102/C102 -> 0 | E102: =D102/D$108 -> 0 | F102: =(F101*C202*C204*C116)+((F101*C202*C204*D113)*C118) -> 18643341 | G102: Payroll | H102: =F102/$H$101 -> 0.053960732 | I102: Rate will be dependant on prodcut size
A103: CG280 | B103: =B55 -> 0 | C103: 0 | D103: 0 | E103: =D103/D$108 -> 0 | F103: =F102*C206 -> 5593002.3 | G103: IPC | H103: =F103/$H$101 -> 0.01618822
A104: CG300 | B104: =B56 -> 0 | C104: 0 | D104: 0 | E104: =D104/D$108 -> 0
A105: XXX | B105: =B57 -> 0 | C105: 0 | D105: 0 | E105: =D105/D$108 -> 0
A106: HA PELLETS | B106: =B58 -> 4900 | C106: 110 | D106: =B106/C106 -> 44.545455 | E106: =D106/D$108 -> 1 | I106: Reduced daily rate to 110 vs. 150
B107: =B59 -> 0 | C107: 0 | D107: 0 | E107: =D107/D$108 -> 0
B108: =SUM(B102:B107) -> 4900 | C108: =B108/D108 -> 110 | D108: =SUM(D102:D107) -> 44.545455 | E108: =D108/D$108 -> 1
A109: HA Group
B112: Jan | C112: Feb | D112: Mar | E112: Apr | F112: May | G112: Jun | H112: Jul
A113: Production Labor | B113: 119702.77 | C113: 140371.43 | D113: 166103.95 | E113: 166766.86 | F113: 105842.43 | G113: 147383.65 | H113: 163283.07
A114: R & M Labor | B114: 15222.93 | C114: 23913.55 | D114: 19670.79 | E114: 41336.57 | F114: 23672.31 | G114: 9419.99 | H114: 18308.82
A115: IPC | B115: 11228.99 | C115: 10794.51 | D115: 10146.4 | E115: 8112.73 | F115: -1917.2 | G115: 49379.56 | H115: 50660.85
A116: Supervision | B116: 3928.57 | C116: -3928.57 | D116: 0 | E116: -1311.46 | F116: 841.1 | G116: 0 | H116: 0
...

Sheet Oct
A1: TOOMSBORO STANDARD 2025
B3: CERAMICS | E3: CG 280 | H3: CG 300
B4: 25 Standard | C4: 23 Actual | D4: 20 Standard | E4: =$B$4 -> 25 Standard | F4: =+C4 -> 23 Actual | G4: =+D4 -> 20 Standard | H4: =+B4 -> 25 Standard | I4: =+C4 -> 23 Actual | J4: =+D4 -> 20 Standard
C5: (Jan-Sept) | F5: (Jan-Sept) | I5: (Jan-Sept)
A6: Materials | B6: =IF(B24<>0,$D$82,0) -> 0.065965818 | C6: 0.0585 | D6: 0.04156581 | E6: =+H82 -> 0 | F6: 0 | G6: 0 | H6: =+D96 -> 0 | I6: 0 | J6: 0
A7: Electricity | B7: =IF(B24<>0,$D$163,0) -> 0.0101288 | C7: 0.0105 | D7: 0.020277329 | E7: =G163 -> 0.0198372 | F7: 0 | G7: 0 | H7: =J163 -> 0.0198372 | I7: 0 | J7: 0
A8: Gas | B8: =IF(B24<>0,$D$164,0) -> 0.026 | C8: 0.0156 | D8: 0.014965 | E8: =G164 -> 0.0171 | F8: 0 | G8: 0 | H8: =J164 -> 0.0171 | I8: 0 | J8: 0
A9: R&M Supplies and Service | B9: =IF(B24<>0,$J$177,0) -> 0.032090909 | C9: 0.0192 | D9: 0.015915789 | E9: =$H$177 -> 0.03 | F9: 0 | G9: 0 | H9: =$H$177 -> 0.03 | I9: 0 | J9: 0
A10: Manufacturing Supplies | B10: =IF(B24<>0,$J$181,0) -> 0.0068181818 | C10: 0.0008 | D10: 0.0026315789 | E10: =$H$181 -> 0.0055102041 | F10: 0 | G10: 0 | H10: =$H$181 -> 0.0055102041 | I10: 0 | J10: 0
A11: Other variable | B11: =IF(B24<>0,$J$184,0) -> 0.0051818182 | C11: 0.0058 | D11: 0.0094736842 | E11: =$H$184 -> 0.01122449 | F11: 0 | G11: 0 | H11: =$H$184 -> 0.01122449 | I11: 0 | J11: 0
A12: Total Variable Costs | B12: =SUM(B6:B11) -> 0.14618553 | C12: =SUM(C6:C11) -> 0.1104 | D12: =SUM(D6:D11) -> 0.10482919 | E12: =SUM(E6:E11) -> 0.083671894 | F12: =SUM(F6:F11) -> 0 | G12: =SUM(G6:G11) -> 0 | H12: =SUM(H6:H11) -> 0.083671894 | I12: =SUM(I6:I11) -> 0 | J12: =SUM(J6:J11) -> 0
A14: Production Labor | B14: =IF($B$24<>0,$F$152/B24/1000,0) -> 0.023171517 | C14: 0.0246 | D14: 0.0073599375 | E14: =$D$124*$E$108/$B$49/1000 -> 0.00028668625 | F14: 0 | G14: 0 | H14: =$D$124*$E$108/$B$49/1000 -> 0.00028668625 | I14: 0 | J14: 0
A15: Repairs & Maintenance Labor | B15: =IF($B$24<>0,$F$153/$B$24/1000,0) -> 0.0098033342 | C15: 0.009 | D15: 0.0042419375 | E15: =$H$124*$E$108/$B$49/1000 -> 0 | F15: 0 | G15: 0 | H15: =$H$124*$E$108/$B$49/1000 -> 0 | I15: 0 | J15: 0
A16: Indirect Payroll Costs (Benefits) | B16: =IF($B$24<>0,$F$155/$B$24/1000,0) -> 0.010087565 | C16: 0.0079 | D16: 0.0053897125 | E16: =$D$131*$E$108/$B$49/1000 -> 0 | F16: 0 | G16: 0 | H16: =$D$131*$E$108/$B$49/1000 -> 0 | I16: 0 | J16: 0
A17: Supervision | B17: =IF($B$24<>0,$F$154/$B$24/1000,0) -> 0.00065036364 | C17: 0 | D17: 0.0026778947 | E17: =$F$194 -> 0 | F17: 0 | G17: 0 | H17: =$F$194 -> 0 | I17: 0 | J17: 0
A18: Depreciation | B18: =IF($B$24<>0,$B$196/$B$49/1000,0) -> 0.0014347327 | C18: 0.0027 | D18: 0.1672 | E18: =$F$196 -> 0.017216792 | F18: 0 | G18: 0 | H18: =$F$196 -> 0.017216792 | I18: 0 | J18: 0
A19: Insurance & Taxes | B19: =IF($B$24<>0,$B$195/$B$49/1000,0) -> 0.0060188679 | C19: 0.012 | D19: 0.012884211 | E19: =$F$195 -> 0.072226415 | F19: 0 | G19: 0 | H19: =$F$195 -> 0.072226415 | I19: 0 | J19: 0
A20: Total Fixed Costs | B20: =SUM(B14:B19) -> 0.05116638 | C20: =SUM(C14:C19) -> 0.0562 | D20: =SUM(D14:D19) -> 0.19975369 | E20: =SUM(E14:E19) -> 0.089729894 | F20: =SUM(F14:F19) -> 0 | G20: =SUM(G14:G19) -> 0 | H20: =SUM(H14:H19) -> 0.089729894 | I20: =SUM(I14:I19) -> 0 | J20: =SUM(J14:J19) -> 0
A22: TOTAL COSTS PER POUND | B22: =B12+B20 -> 0.19735191 | C22: =C12+C20 -> 0.1666 | D22: =D12+D20 -> 0.30458288 | E22: =E12+E20 -> 0.17340179 | F22: =F12+F20 -> 0 | G22: =G12+G20 -> 0 | H22: =H12+H20 -> 0.17340179 | I22: =I12+I20 -> 0 | J22: =J12+J20 -> 0
A24: PRODUCTION ( in 000 lbs ) | B24: =+B54 -> 11000 | C24: 0 | D24: 80000 | E24: =+B55 -> 0 | F24: 0 | G24: 0 | H24: =+B56 -> 0 | I24: 0 | J24: 0
B26: XXX | E26: HA PELLETS
B27: =$B$4 -> 25 Standard | C27: =+C4 -> 23 Actual | D27: =+D4 -> 20 Standard | E27: 24 Standard | F27: 23 Actual | G27: 22 Standard | H27: =+B27 -> 25 Standard | I27: =+C27 -> 23 Actual | J27: =+D27 -> 20 Standard
C28: (Jan-Sept) | F28: (Jan-Aug)
A29: Materials | B29: =D82 -> 0.065965818 | C29: 0 | D29: 0 | E29: =IF(E47<>0,$L$96,0) -> 0.070852832 | F29: 0.078 | G29: 0.06025968 | H29: 0 | I29: 0 | J29: 0
A30: Electricity | B30: =D169 -> 0 | C30: 0 | D30: 0 | E30: =IF(E47<>0,$G$169,0) -> 0.043918811 | F30: 0.0432 | G30: 0.026879418 | H30: 0 | I30: 0 | J30: 0
A31: Gas | B31: =D170 -> 0 | C31: 0 | D31: 0 | E31: =IF(E47<>0,$G$170,0) -> 0.026 | F31: 0.019 | G31: 0.028567 | H31: =J170 -> 0 | I31: 0 | J31: 0
A32: R&M Supplies and Service | B32: =IF($B$47<>0,$H$177,0) -> 0 | C32: 0 | D32: 0 | E32: =IF(E47<>0,$H$177,0) -> 0.03 | F32: 0.0298 | G32: 0.027777778 | H32: 0 | I32: 0 | J32: 0
A33: Manufacturing Supplies | B33: =IF($B$47<>0,$H$181,0) -> 0 | C33: 0 | D33: 0 | E33: =IF(E47<>0,$H$181,0) -> 0.0055102041 | F33: 0.0012 | G33: 0.0069444444 | H33: 0 | I33: 0 | J33: 0
A34: Other variable | B34: =IF($B$47<>0,$H$184,0) -> 0 | C34: 0 | D34: 0 | E34: =IF(E47<>0,$H$184,0) -> 0.01122449 | F34: 0.0139 | G34: 0.0125 | H34: 0 | I34: 0 | J34: 0
A35: Total Variable Costs | B35: =SUM(B29:B34) -> 0.065965818 | C35: =SUM(C29:C34) -> 0 | D35: =SUM(D29:D34) -> 0 | E35: =SUM(E29:E34) -> 0.18750634 | F35: =SUM(F29:F34) -> 0.1851 | G35: =SUM(G29:G34) -> 0.16292832 | H35: =SUM(H29:H34) -> 0 | I35: =SUM(I29:I34) -> 0 | J35: =SUM(J29:J34) -> 0
A37: Production Labor | B37: =$D$124*$E$108/$B$49/1000 -> 0.00028668625 | C37: 0 | D37: 0 | E37: =IF($E$47<>0,$F$127/$E$47/1000,0) -> 0.040001507 | F37: 0.0353 | G37: 0.02156921 | H37: 0 | I37: 0 | J37: 0
A38: Repairs & Maintenance Labor | B38: =$H$124*$E$108/$B$49/1000 -> 0 | C38: 0 | D38: 0 | E38: =IF($E$47<>0,$F$128/$E$47/1000,0) -> 0.0048061173 | F38: 0.0067 | G38: 0.0051700857 | H38: 0 | I38: 0 | J38: 0
A39: Indirect Payroll Costs (Benefits) | B39: =$D$131*$E$108/$B$49/1000 -> 0 | C39: 0 | D39: 0 | E39: =IF($E$47<>0,$F$130/$E$47/1000,0) -> 0.012994211 | F39: 0.0112 | G39: 0.0080162316 | H39: 0 | I39: 0 | J39: 0
A40: Supervision | B40: =IF($B$49<>0,$F$194,0) -> 0 | C40: 0 | D40: 0 | E40: =IF($E$47<>0,$F$129/$E$47/1000,0) -> 0 | F40: 0 | G40: 0.00047638889 | H40: 0 | I40: 0 | J40: 0
A41: Depreciation | B41: =IF($B$49<>0,$F$196,0) -> 0.017216792 | C41: 0 | D41: 0 | E41: =IF($E$47<>0,$B$196/$B$49/1000/4,0) -> 0.00035868318 | F41: 0.0085 | G41: 0.0056777778 | H41: 0 | I41: 0 | J41: 0
A42: Insurance & Taxes | B42: =IF($B$49<>0,$F$195,0) -> 0.072226415 | C42: 0 | D42: 0 | E42: =IF($E$47<>0,$B$195/$B$49/1000/4,0) -> 0.001504717 | F42: 0.0362 | G42: 0.025861111 | H42: 0 | I42: 0 | J42: 0
A43: Total Fixed Costs | B43: =SUM(B37:B42) -> 0.089729894 | C43: =SUM(C37:C42) -> 0 | D43: =SUM(D37:D42) -> 0 | E43: =SUM(E37:E42) -> 0.059665236 | F43: =SUM(F37:F42) -> 0.0979 | G43: =SUM(G37:G42) -> 0.066770805 | H43: =SUM(H37:H42) -> 0 | I43: =SUM(I37:I42) -> 0 | J43: =SUM(J37:J42) -> 0
A44: Excess Costs | F44: -0.0455
A45: TOTAL COSTS PER POUND | B45: =B35+B43 -> 0.15569571 | C45: =C35+C43 -> 0 | D45: 0.19962946 | E45: =E35+E43+E44 -> 0.24717157 | F45: =F35+F43+F44 -> 0.2375 | G45: =+G35+G43 -> 0.22969913 | H45: =H35+H43 -> 0 | I45: =I35+I43 -> 0 | J45: =J35+J43 -> 0 | L45: =E45-0.245 -> 0.0021715733 | M45: =E47*1000*L45 -> 10640.709
M46: =M45/12 -> 886.72577
A47: PRODUCTION ( in 000 lbs ) | B47: =+B57 -> 0 | C47: 0 | D47: 0 | E47: =+B58 -> 4900 | F47: 15776 | G47: 36000 | H47: =+B59 -> 0 | I47: 0 | J47: 0
A49: TOTAL PLANT PRODUCTION ( in 000 lbs) | B49: =B24+E24+H24+B47+E47+H47 -> 15900 | C49: =C24+F24+I24+C47+F47+I47 -> 15776 | D49: =D24+G24+J24+D47+G47+J47 -> 116000
A51: Variable Costs - Material | B51: Purchase Price/lb * Yield Factor * Scrap Factor * Mix = Std. Cost Contribution
A53: Production Plan: | B53: Pounds (000) | C53: Product Split
A54: Ceramics | B54: ='2025 Summary'!$D$16 -> 11000 | C54: =B54/$B$60 -> 0.6918239 | E54: =9*400000*7 -> 25200000
A55: CG280 | B55: 0 | C55: =B55/$B$60 -> 0
A56: CG300 | B56: 0 | C56: =B56/$B$60 -> 0
A57: XXX | B57: 0 | C57: =B57/$B$60 -> 0
A58: HA PELLETS | B58: ='2025 Summary'!$E$16 -> 4900 | C58: =B58/$B$60 -> 0.3081761
B59: 0 | C59: =B59/$B$60 -> 0
A60: Total | B60: =SUM(B54:B59) -> 15900 | C60: =B60/$B$60 -> 1
C62: Yield Factor | G62: Mix %
A63: Local Kaolin | B63: Price ($/Ton) | C63: Ceramics | D63: CG280 | E63: CG300 | F63: XXX | G63: HA Pellets | H63: Ceramics | I63: CG280 | J63: CG300 | K63: XXX | L63: HA Pellets
A64: Arcilla (local kaolin) 30012 | B64: =11.89*2 -> 23.78 | C64: =$C$76*H64 -> 0 | D64: =$C$86*I64 -> 0 | E64: =$G$86*J64 -> 0 | F64: =$K$86*K64 -> 0 | G64: =$K$86*L64 -> 0 | H64: 0 | I64: 0 | J64: 0 | K64: 0 | L64: 0
B65: 0 | C65: =$C$76*H65 -> 0 | D65: =$C$86*I65 -> 0 | E65: =$G$86*J65 -> 0 | F65: =$K$86*K65 -> 0 | G65: =$K$86*L65 -> 0 | H65: 0 | I65: 0 | J65: 0 | K65: 0 | L65: 0
C66: =SUM(C64:C65) -> 0 | D66: =SUM(D64:D65) -> 0 | E66: =SUM(E64:E65) -> 0 | F66: =SUM(F64:F65) -> 0 | G66: =SUM(G64:G65) -> 0
A67: Bauxite:
A68: Rusal (30008) | B68: 0 | C68: =$C$77*H68 -> 0 | D68: =$C$87*I68 -> 0 | E68: =$G$87*J68 -> 0 | F68: =$K$87*K68 -> 0 | G68: =$K$87*L68 -> 0 | H68: 0 | I68: 0 | J68: 0 | K68: 0 | L68: 0
A69: Kaolin - CE Calcined (30060) | B69: =116.72*2 -> 233.44 | C69: =$C$77*H69 -> 0 | D69: =$C$87*I69 -> 0 | E69: =$G$87*J69 -> 0 | F69: =$K$87*K69 -> 0 | G69: =$K$87*L69 -> 0 | H69: 0 | I69: 0 | J69: 0 | K69: 0 | L69: 0
B70: 0 | C70: 0 | D70: =$C$87*I70 -> 0 | E70: =$G$87*J70 -> 0 | F70: =$K$87*K70 -> 0 | G70: =$K$87*L70 -> 0 | H70: 0 | I70: 0 | J70: 0 | K70: 0 | L70: 0
B71: 0 | C71: 0 | D71: =$C$87*I71 -> 0 | E71: =$G$87*J71 -> 0 | F71: =$K$87*K71 -> 0 | G71: =$K$87*L71 -> 0 | H71: 0 | I71: 0 | J71: 0 | K71: 0 | L71: 0
C72: =SUM(C68:C71) -> 0 | D72: =SUM(D68:D71) -> 0 | E72: =SUM(E68:E71) -> 0 | F72: =SUM(F68:F71) -> 0 | G72: =SUM(G68:G71) -> 0
B74: Ceramics | F74: CG280
B75: Price ($/lb) | C75: Yield Factor | D75: Std $ Contrib | F75: Price ($/lb) | G75: Yield Factor | H75: Std $ Contrib
A76: Local Kaolin | B76: =0.011 -> 0.011 | C76: =AVERAGE(3.6826,3.5997, 2.6808) -> 3.3210333 | D76: =B76*C76 -> 0.036531367 | F76: 0 | G76: 0 | H76: =F76*G76 -> 0
A77: Bauxite | B77: =($B$68*$H$68+$B$69*$H$69+$B$70*$H$70+$B$71*$H$71)/2000 -> 0 | C77: 0 | D77: =B77*C77 -> 0 | F77: =($B$68*$L$68+$B$69*$L$69+$B$70*$L$70+$B$71*$L$71)/2000 -> 0 | G77: 0 | H77: =F77*G77 -> 0
A78: PVA (30017) | B78: 1.838 | C78: 0.0081 | D78: =B78*C78 -> 0.0148878 | F78: =+B78 -> 1.838 | G78: 0 | H78: =F78*G78 -> 0
A79: Dispersant (30011) | B79: =750/1000 -> 0.75 | C79: 0.0161 | D79: =B79*C79 -> 0.012075 | F79: =+B79 -> 0.75 | G79: 0
A80: Ammonia (30000) | B80: =157.43/1000 -> 0.15743 | C80: 0.0157 | D80: =B80*C80 -> 0.002471651 | F80: =+B80 -> 0.15743 | G80: 0 | H80: 0
A82: Total Material Cost Per Pound | D82: =SUM(D76:D80) -> 0.065965818 | H82: =SUM(H76:H80) -> 0
B84: CG300 | F84: XXX | J84: HA Pellets
B85: Price ($/lb) | C85: Yield Factor/BOM | D85: Std $ Contrib | F85: Price ($/lb) | G85: Yield Factor | H85: Std $ Contrib | J85: Price ($/lb) | K85: Yield Factor | L85: Std $ Contrib
A86: Local kaolin | B86: =($B$64*$I$64+$B$65*$I$65)/2000 -> 0 | C86: 0 | D86: =B86*C86 -> 0 | F86: =($B$64*$J$64+$B$65*$J$65)/2000 -> 0 | G86: 0 | H86: =F86*G86 -> 0 | J86: =($B$64*$K$64+$B$65*$K$65)/2000 -> 0 | K86: 0 | L86: =J86*K86 -> 0
A87: Bauxite | B87: =($B$68*$I$68+$B$69*$I$69+$B$70*$I$70+$B$71*$I$71)/2000 -> 0 | C87: 0 | D87: =B87*C87 -> 0 | F87: =($B$68*$J$68+$B$69*$J$69+$B$70*$J$70+$B$71*$J$71)/2000 -> 0 | G87: 0 | H87: =F87*G87 -> 0 | J87: =($B$68*$K$68+$B$69*$K$69+$B$70*$K$70+$B$71*$K$71)/2000 -> 0 | K87: 0 | L87: =J87*K87 -> 0
A88: PVA (30017) | B88: 2.54 | C88: 0 | D88: =B88*C88 -> 0 | F88: =+B88 -> 2.54 | G88: 0 | H88: =F88*G88 -> 0 | J88: 1.964 | K88: 0.020848164 | L88: =J88*K88 -> 0.040945794
A89: Dispersant (30011) | B89: =750/1000 -> 0.75 | C89: 0 | D89: =B89*C89 -> 0 | F89: =+B89 -> 0.75 | G89: 0 | H89: =F89*G89 -> 0 | J89: 0.591 | K89: 0.0031014518 | L89: =J89*K89 -> 0.001832958
A90: Ammonia (30000) | B90: =157.43/1000 -> 0.15743 | C90: 0 | D90: =B90*C90 -> 0 | F90: =+B90 -> 0.15743 | G90: 0 | H90: =F90*G90 -> 0 | J90: 0.105 | K90: 0.1 | L90: =J90*K90 -> 0.0105
A91: Defoamer (30010) | C91: 0 | D91: =B91*C91 -> 0 | F91: =+B91 -> 0 | G91: 0 | H91: =F91*G91 -> 0 | J91: 1.027 | K91: 0.0021752348 | L91: =J91*K91 -> 0.0022339662
A92: Ultrasurf (30341) | C92: 0 | D92: =B92*C92 -> 0 | F92: =+B92 -> 0 | G92: 0 | H92: =F92*G92 -> 0 | J92: 1.389 | K92: 0.0023312553 | L92: =J92*K92 -> 0.0032381137
A93: HA Pallets (30350) | J93: 18.84 | K93: 0.0006 | L93: =J93*K93 -> 0.011304
A94: HA Bag Protectors (30342) | J94: 1.33 | K94: 0.0006 | L94: =J94*K94 -> 0.000798
D95: 0 | H95: 0 | L95: 0
A96: Total Material Cost Per Pound | D96: =SUM(D86:D95) -> 0 | H96: =SUM(H86:H95) -> 0 | L96: =SUM(L86:L95) -> 0.070852832
A98: Variable Cost - Production/R&M Labor & Benefits
F99: W&S Carve Out of Production Labor
A100: Labor Split:
B101: Prod. Plan (000) | C101: Rate (000 lbs/day) | D101: Kiln Days | E101: % Split | F101: 1 | G101: <--EEs | Hrs--> | H101: =(F101*C202*C204)+((F101*C202*C204*D113)) -> 345498296
A102: Ceramics | B102: =B54 -> 11000 | C102: 550 | D102: =B102/C102 -> 20 | E102: =D102/D$108 -> 0.30985915 | F102: =(F101*C202*C204*C116)+((F101*C202*C204*D113)*C118) -> 18643341 | G102: Payroll | H102: =F102/$H$101 -> 0.053960732 | I102: Rate will be dependant on prodcut size
A103: CG280 | B103: =B55 -> 0 | C103: 0 | D103: 0 | E103: =D103/D$108 -> 0 | F103: =F102*C206 -> 5593002.3 | G103: IPC | H103: =F103/$H$101 -> 0.01618822
A104: CG300 | B104: =B56 -> 0 | C104: 0 | D104: 0 | E104: =D104/D$108 -> 0
A105: XXX | B105: =B57 -> 0 | C105: 0 | D105: 0 | E105: =D105/D$108 -> 0
A106: HA PELLETS | B106: =B58 -> 4900 | C106: 110 | D106: =B106/C106 -> 44.545455 | E106: =D106/D$108 -> 0.69014085 | I106: Reduced daily rate to 110 vs. 150
B107: =B59 -> 0 | C107: 0 | D107: 0 | E107: =D107/D$108 -> 0
B108: =SUM(B102:B107) -> 15900 | C108: =B108/D108 -> 246.33803 | D108: =SUM(D102:D107) -> 64.545455 | E108: =D108/D$108 -> 1
A109: HA Group
B112: Jan | C112: Feb | D112: Mar | E112: Apr | F112: May | G112: Jun | H112: Jul
A113: Production Labor | B113: 119702.77 | C113: 140371.43 | D113: 166103.95 | E113: 166766.86 | F113: 105842.43 | G113: 147383.65 | H113: 163283.07
A114: R & M Labor | B114: 15222.93 | C114: 23913.55 | D114: 19670.79 | E114: 41336.57 | F114: 23672.31 | G114: 9419.99 | H114: 18308.82
A115: IPC | B115: 11228.99 | C115: 10794.51 | D115: 10146.4 | E115: 8112.73 | F115: -1917.2 | G115: 49379.56 | H115: 50660.85
A116: Supervision | B116: 3928.57 | C116: -3928.57 | D116: 0 | E116: -1311.46 | F116: 841.1 | G116: 0 | H116: 0
...

Sheet Nov
A1: TOOMSBORO STANDARD 2025
B3: CERAMICS | E3: CG 280 | H3: CG 300
B4: 25 Standard | C4: 23 Actual | D4: 20 Standard | E4: =$B$4 -> 25 Standard | F4: =+C4 -> 23 Actual | G4: =+D4 -> 20 Standard | H4: =+B4 -> 25 Standard | I4: =+C4 -> 23 Actual | J4: =+D4 -> 20 Standard
C5: (Jan-Sept) | F5: (Jan-Sept) | I5: (Jan-Sept)
A6: Materials | B6: =IF(B24<>0,$D$82,0) -> 0 | C6: 0.0585 | D6: 0.04156581 | E6: =+H82 -> 0 | F6: 0 | G6: 0 | H6: =+D96 -> 0 | I6: 0 | J6: 0
A7: Electricity | B7: =IF(B24<>0,$D$163,0) -> 0 | C7: 0.0105 | D7: 0.020277329 | E7: =G163 -> 0.0198372 | F7: 0 | G7: 0 | H7: =J163 -> 0.0198372 | I7: 0 | J7: 0
A8: Gas | B8: =IF(B24<>0,$D$164,0) -> 0 | C8: 0.0156 | D8: 0.014965 | E8: =G164 -> 0.0171 | F8: 0 | G8: 0 | H8: =J164 -> 0.0171 | I8: 0 | J8: 0
A9: R&M Supplies and Service | B9: =IF(B24<>0,$J$177,0) -> 0 | C9: 0.0192 | D9: 0.015915789 | E9: =$H$177 -> 0.03 | F9: 0 | G9: 0 | H9: =$H$177 -> 0.03 | I9: 0 | J9: 0
A10: Manufacturing Supplies | B10: =IF(B24<>0,$J$181,0) -> 0 | C10: 0.0008 | D10: 0.0026315789 | E10: =$H$181 -> 0.0055102041 | F10: 0 | G10: 0 | H10: =$H$181 -> 0.0055102041 | I10: 0 | J10: 0
A11: Other variable | B11: =IF(B24<>0,$J$184,0) -> 0 | C11: 0.0058 | D11: 0.0094736842 | E11: =$H$184 -> 0.01122449 | F11: 0 | G11: 0 | H11: =$H$184 -> 0.01122449 | I11: 0 | J11: 0
A12: Total Variable Costs | B12: =SUM(B6:B11) -> 0 | C12: =SUM(C6:C11) -> 0.1104 | D12: =SUM(D6:D11) -> 0.10482919 | E12: =SUM(E6:E11) -> 0.083671894 | F12: =SUM(F6:F11) -> 0 | G12: =SUM(G6:G11) -> 0 | H12: =SUM(H6:H11) -> 0.083671894 | I12: =SUM(I6:I11) -> 0 | J12: =SUM(J6:J11) -> 0
A14: Production Labor | B14: =IF($B$24<>0,$F$152/B24/1000,0) -> 0 | C14: 0.0246 | D14: 0.0073599375 | E14: =$D$124*$E$108/$B$49/1000 -> 0.00093026761 | F14: 0 | G14: 0 | H14: =$D$124*$E$108/$B$49/1000 -> 0.00093026761 | I14: 0 | J14: 0
A15: Repairs & Maintenance Labor | B15: =IF($B$24<>0,$F$153/$B$24/1000,0) -> 0 | C15: 0.009 | D15: 0.0042419375 | E15: =$H$124*$E$108/$B$49/1000 -> 0 | F15: 0 | G15: 0 | H15: =$H$124*$E$108/$B$49/1000 -> 0 | I15: 0 | J15: 0
A16: Indirect Payroll Costs (Benefits) | B16: =IF($B$24<>0,$F$155/$B$24/1000,0) -> 0 | C16: 0.0079 | D16: 0.0053897125 | E16: =$D$131*$E$108/$B$49/1000 -> 0 | F16: 0 | G16: 0 | H16: =$D$131*$E$108/$B$49/1000 -> 0 | I16: 0 | J16: 0
A17: Supervision | B17: =IF($B$24<>0,$F$154/$B$24/1000,0) -> 0 | C17: 0 | D17: 0.0026778947 | E17: =$F$194 -> 0 | F17: 0 | G17: 0 | H17: =$F$194 -> 0 | I17: 0 | J17: 0
A18: Depreciation | B18: =IF($B$24<>0,$B$196/$B$49/1000,0) -> 0 | C18: 0.0027 | D18: 0.1672 | E18: =$F$196 -> 0.055866735 | F18: 0 | G18: 0 | H18: =$F$196 -> 0.055866735 | I18: 0 | J18: 0
A19: Insurance & Taxes | B19: =IF($B$24<>0,$B$195/$B$49/1000,0) -> 0 | C19: 0.012 | D19: 0.012884211 | E19: =$F$195 -> 0.23436735 | F19: 0 | G19: 0 | H19: =$F$195 -> 0.23436735 | I19: 0 | J19: 0
A20: Total Fixed Costs | B20: =SUM(B14:B19) -> 0 | C20: =SUM(C14:C19) -> 0.0562 | D20: =SUM(D14:D19) -> 0.19975369 | E20: =SUM(E14:E19) -> 0.29116435 | F20: =SUM(F14:F19) -> 0 | G20: =SUM(G14:G19) -> 0 | H20: =SUM(H14:H19) -> 0.29116435 | I20: =SUM(I14:I19) -> 0 | J20: =SUM(J14:J19) -> 0
A22: TOTAL COSTS PER POUND | B22: =B12+B20 -> 0 | C22: =C12+C20 -> 0.1666 | D22: =D12+D20 -> 0.30458288 | E22: =E12+E20 -> 0.37483624 | F22: =F12+F20 -> 0 | G22: =G12+G20 -> 0 | H22: =H12+H20 -> 0.37483624 | I22: =I12+I20 -> 0 | J22: =J12+J20 -> 0
A24: PRODUCTION ( in 000 lbs ) | B24: =+B54 -> 0 | C24: 0 | D24: 80000 | E24: =+B55 -> 0 | F24: 0 | G24: 0 | H24: =+B56 -> 0 | I24: 0 | J24: 0
B26: XXX | E26: HA PELLETS
B27: =$B$4 -> 25 Standard | C27: =+C4 -> 23 Actual | D27: =+D4 -> 20 Standard | E27: 24 Standard | F27: 23 Actual | G27: 22 Standard | H27: =+B27 -> 25 Standard | I27: =+C27 -> 23 Actual | J27: =+D27 -> 20 Standard
C28: (Jan-Sept) | F28: (Jan-Aug)
A29: Materials | B29: =D82 -> 0.065965818 | C29: 0 | D29: 0 | E29: =IF(E47<>0,$L$96,0) -> 0.070852832 | F29: 0.078 | G29: 0.06025968 | H29: 0 | I29: 0 | J29: 0
A30: Electricity | B30: =D169 -> 0 | C30: 0 | D30: 0 | E30: =IF(E47<>0,$G$169,0) -> 0.043918811 | F30: 0.0432 | G30: 0.026879418 | H30: 0 | I30: 0 | J30: 0
A31: Gas | B31: =D170 -> 0 | C31: 0 | D31: 0 | E31: =IF(E47<>0,$G$170,0) -> 0.026 | F31: 0.019 | G31: 0.028567 | H31: =J170 -> 0 | I31: 0 | J31: 0
A32: R&M Supplies and Service | B32: =IF($B$47<>0,$H$177,0) -> 0 | C32: 0 | D32: 0 | E32: =IF(E47<>0,$H$177,0) -> 0.03 | F32: 0.0298 | G32: 0.027777778 | H32: 0 | I32: 0 | J32: 0
A33: Manufacturing Supplies | B33: =IF($B$47<>0,$H$181,0) -> 0 | C33: 0 | D33: 0 | E33: =IF(E47<>0,$H$181,0) -> 0.0055102041 | F33: 0.0012 | G33: 0.0069444444 | H33: 0 | I33: 0 | J33: 0
A34: Other variable | B34: =IF($B$47<>0,$H$184,0) -> 0 | C34: 0 | D34: 0 | E34: =IF(E47<>0,$H$184,0) -> 0.01122449 | F34: 0.0139 | G34: 0.0125 | H34: 0 | I34: 0 | J34: 0
A35: Total Variable Costs | B35: =SUM(B29:B34) -> 0.065965818 | C35: =SUM(C29:C34) -> 0 | D35: =SUM(D29:D34) -> 0 | E35: =SUM(E29:E34) -> 0.18750634 | F35: =SUM(F29:F34) -> 0.1851 | G35: =SUM(G29:G34) -> 0.16292832 | H35: =SUM(H29:H34) -> 0 | I35: =SUM(I29:I34) -> 0 | J35: =SUM(J29:J34) -> 0
A37: Production Labor | B37: =$D$124*$E$108/$B$49/1000 -> 0.00093026761 | C37: 0 | D37: 0 | E37: =IF($E$47<>0,$F$127/$E$47/1000,0) -> 0.040001507 | F37: 0.0353 | G37: 0.02156921 | H37: 0 | I37: 0 | J37: 0
A38: Repairs & Maintenance Labor | B38: =$H$124*$E$108/$B$49/1000 -> 0 | C38: 0 | D38: 0 | E38: =IF($E$47<>0,$F$128/$E$47/1000,0) -> 0.0048061173 | F38: 0.0067 | G38: 0.0051700857 | H38: 0 | I38: 0 | J38: 0
A39: Indirect Payroll Costs (Benefits) | B39: =$D$131*$E$108/$B$49/1000 -> 0 | C39: 0 | D39: 0 | E39: =IF($E$47<>0,$F$130/$E$47/1000,0) -> 0.012994211 | F39: 0.0112 | G39: 0.0080162316 | H39: 0 | I39: 0 | J39: 0
A40: Supervision | B40: =IF($B$49<>0,$F$194,0) -> 0 | C40: 0 | D40: 0 | E40: =IF($E$47<>0,$F$129/$E$47/1000,0) -> 0 | F40: 0 | G40: 0.00047638889 | H40: 0 | I40: 0 | J40: 0
A41: Depreciation | B41: =IF($B$49<>0,$F$196,0) -> 0.055866735 | C41: 0 | D41: 0 | E41: =IF($E$47<>0,$B$196/$B$49/1000/4,0) -> 0.0011638903 | F41: 0.0085 | G41: 0.0056777778 | H41: 0 | I41: 0 | J41: 0
A42: Insurance & Taxes | B42: =IF($B$49<>0,$F$195,0) -> 0.23436735 | C42: 0 | D42: 0 | E42: =IF($E$47<>0,$B$195/$B$49/1000/4,0) -> 0.0048826531 | F42: 0.0362 | G42: 0.025861111 | H42: 0 | I42: 0 | J42: 0
A43: Total Fixed Costs | B43: =SUM(B37:B42) -> 0.29116435 | C43: =SUM(C37:C42) -> 0 | D43: =SUM(D37:D42) -> 0 | E43: =SUM(E37:E42) -> 0.063848379 | F43: =SUM(F37:F42) -> 0.0979 | G43: =SUM(G37:G42) -> 0.066770805 | H43: =SUM(H37:H42) -> 0 | I43: =SUM(I37:I42) -> 0 | J43: =SUM(J37:J42) -> 0
A44: Excess Costs | F44: -0.0455
A45: TOTAL COSTS PER POUND | B45: =B35+B43 -> 0.35713017 | C45: =C35+C43 -> 0 | D45: 0.19962946 | E45: =E35+E43+E44 -> 0.25135472 | F45: =F35+F43+F44 -> 0.2375 | G45: =+G35+G43 -> 0.22969913 | H45: =H35+H43 -> 0 | I45: =I35+I43 -> 0 | J45: =J35+J43 -> 0 | L45: =E45-0.245 -> 0.0063547165 | M45: =E47*1000*L45 -> 31138.111
M46: =M45/12 -> 2594.8426
A47: PRODUCTION ( in 000 lbs ) | B47: =+B57 -> 0 | C47: 0 | D47: 0 | E47: =+B58 -> 4900 | F47: 15776 | G47: 36000 | H47: =+B59 -> 0 | I47: 0 | J47: 0
A49: TOTAL PLANT PRODUCTION ( in 000 lbs) | B49: =B24+E24+H24+B47+E47+H47 -> 4900 | C49: =C24+F24+I24+C47+F47+I47 -> 15776 | D49: =D24+G24+J24+D47+G47+J47 -> 116000
A51: Variable Costs - Material | B51: Purchase Price/lb * Yield Factor * Scrap Factor * Mix = Std. Cost Contribution
A53: Production Plan: | B53: Pounds (000) | C53: Product Split
A54: Ceramics | B54: ='2025 Summary'!$D$17 -> 0 | C54: =B54/$B$60 -> 0 | E54: =9*400000*7 -> 25200000
A55: CG280 | B55: 0 | C55: =B55/$B$60 -> 0
A56: CG300 | B56: 0 | C56: =B56/$B$60 -> 0
A57: XXX | B57: 0 | C57: =B57/$B$60 -> 0
A58: HA PELLETS | B58: ='2025 Summary'!$E$17 -> 4900 | C58: =B58/$B$60 -> 1
B59: 0 | C59: =B59/$B$60 -> 0
A60: Total | B60: =SUM(B54:B59) -> 4900 | C60: =B60/$B$60 -> 1
C62: Yield Factor | G62: Mix %
A63: Local Kaolin | B63: Price ($/Ton) | C63: Ceramics | D63: CG280 | E63: CG300 | F63: XXX | G63: HA Pellets | H63: Ceramics | I63: CG280 | J63: CG300 | K63: XXX | L63: HA Pellets
A64: Arcilla (local kaolin) 30012 | B64: =11.89*2 -> 23.78 | C64: =$C$76*H64 -> 0 | D64: =$C$86*I64 -> 0 | E64: =$G$86*J64 -> 0 | F64: =$K$86*K64 -> 0 | G64: =$K$86*L64 -> 0 | H64: 0 | I64: 0 | J64: 0 | K64: 0 | L64: 0
B65: 0 | C65: =$C$76*H65 -> 0 | D65: =$C$86*I65 -> 0 | E65: =$G$86*J65 -> 0 | F65: =$K$86*K65 -> 0 | G65: =$K$86*L65 -> 0 | H65: 0 | I65: 0 | J65: 0 | K65: 0 | L65: 0
C66: =SUM(C64:C65) -> 0 | D66: =SUM(D64:D65) -> 0 | E66: =SUM(E64:E65) -> 0 | F66: =SUM(F64:F65) -> 0 | G66: =SUM(G64:G65) -> 0
A67: Bauxite:
A68: Rusal (30008) | B68: 0 | C68: =$C$77*H68 -> 0 | D68: =$C$87*I68 -> 0 | E68: =$G$87*J68 -> 0 | F68: =$K$87*K68 -> 0 | G68: =$K$87*L68 -> 0 | H68: 0 | I68: 0 | J68: 0 | K68: 0 | L68: 0
A69: Kaolin - CE Calcined (30060) | B69: =116.72*2 -> 233.44 | C69: =$C$77*H69 -> 0 | D69: =$C$87*I69 -> 0 | E69: =$G$87*J69 -> 0 | F69: =$K$87*K69 -> 0 | G69: =$K$87*L69 -> 0 | H69: 0 | I69: 0 | J69: 0 | K69: 0 | L69: 0
B70: 0 | C70: 0 | D70: =$C$87*I70 -> 0 | E70: =$G$87*J70 -> 0 | F70: =$K$87*K70 -> 0 | G70: =$K$87*L70 -> 0 | H70: 0 | I70: 0 | J70: 0 | K70: 0 | L70: 0
B71: 0 | C71: 0 | D71: =$C$87*I71 -> 0 | E71: =$G$87*J71 -> 0 | F71: =$K$87*K71 -> 0 | G71: =$K$87*L71 -> 0 | H71: 0 | I71: 0 | J71: 0 | K71: 0 | L71: 0
C72: =SUM(C68:C71) -> 0 | D72: =SUM(D68:D71) -> 0 | E72: =SUM(E68:E71) -> 0 | F72: =SUM(F68:F71) -> 0 | G72: =SUM(G68:G71) -> 0
B74: Ceramics | F74: CG280
B75: Price ($/lb) | C75: Yield Factor | D75: Std $ Contrib | F75: Price ($/lb) | G75: Yield Factor | H75: Std $ Contrib
A76: Local Kaolin | B76: =0.011 -> 0.011 | C76: =AVERAGE(3.6826,3.5997, 2.6808) -> 3.3210333 | D76: =B76*C76 -> 0.036531367 | F76: 0 | G76: 0 | H76: =F76*G76 -> 0
A77: Bauxite | B77: =($B$68*$H$68+$B$69*$H$69+$B$70*$H$70+$B$71*$H$71)/2000 -> 0 | C77: 0 | D77: =B77*C77 -> 0 | F77: =($B$68*$L$68+$B$69*$L$69+$B$70*$L$70+$B$71*$L$71)/2000 -> 0 | G77: 0 | H77: =F77*G77 -> 0
A78: PVA (30017) | B78: 1.838 | C78: 0.0081 | D78: =B78*C78 -> 0.0148878 | F78: =+B78 -> 1.838 | G78: 0 | H78: =F78*G78 -> 0
A79: Dispersant (30011) | B79: =750/1000 -> 0.75 | C79: 0.0161 | D79: =B79*C79 -> 0.012075 | F79: =+B79 -> 0.75 | G79: 0
A80: Ammonia (30000) | B80: =157.43/1000 -> 0.15743 | C80: 0.0157 | D80: =B80*C80 -> 0.002471651 | F80: =+B80 -> 0.15743 | G80: 0 | H80: 0
A82: Total Material Cost Per Pound | D82: =SUM(D76:D80) -> 0.065965818 | H82: =SUM(H76:H80) -> 0
B84: CG300 | F84: XXX | J84: HA Pellets
B85: Price ($/lb) | C85: Yield Factor/BOM | D85: Std $ Contrib | F85: Price ($/lb) | G85: Yield Factor | H85: Std $ Contrib | J85: Price ($/lb) | K85: Yield Factor | L85: Std $ Contrib
A86: Local kaolin | B86: =($B$64*$I$64+$B$65*$I$65)/2000 -> 0 | C86: 0 | D86: =B86*C86 -> 0 | F86: =($B$64*$J$64+$B$65*$J$65)/2000 -> 0 | G86: 0 | H86: =F86*G86 -> 0 | J86: =($B$64*$K$64+$B$65*$K$65)/2000 -> 0 | K86: 0 | L86: =J86*K86 -> 0
A87: Bauxite | B87: =($B$68*$I$68+$B$69*$I$69+$B$70*$I$70+$B$71*$I$71)/2000 -> 0 | C87: 0 | D87: =B87*C87 -> 0 | F87: =($B$68*$J$68+$B$69*$J$69+$B$70*$J$70+$B$71*$J$71)/2000 -> 0 | G87: 0 | H87: =F87*G87 -> 0 | J87: =($B$68*$K$68+$B$69*$K$69+$B$70*$K$70+$B$71*$K$71)/2000 -> 0 | K87: 0 | L87: =J87*K87 -> 0
A88: PVA (30017) | B88: 2.54 | C88: 0 | D88: =B88*C88 -> 0 | F88: =+B88 -> 2.54 | G88: 0 | H88: =F88*G88 -> 0 | J88: 1.964 | K88: 0.020848164 | L88: =J88*K88 -> 0.040945794
A89: Dispersant (30011) | B89: =750/1000 -> 0.75 | C89: 0 | D89: =B89*C89 -> 0 | F89: =+B89 -> 0.75 | G89: 0 | H89: =F89*G89 -> 0 | J89: 0.591 | K89: 0.0031014518 | L89: =J89*K89 -> 0.001832958
A90: Ammonia (30000) | B90: =157.43/1000 -> 0.15743 | C90: 0 | D90: =B90*C90 -> 0 | F90: =+B90 -> 0.15743 | G90: 0 | H90: =F90*G90 -> 0 | J90: 0.105 | K90: 0.1 | L90: =J90*K90 -> 0.0105
A91: Defoamer (30010) | C91: 0 | D91: =B91*C91 -> 0 | F91: =+B91 -> 0 | G91: 0 | H91: =F91*G91 -> 0 | J91: 1.027 | K91: 0.0021752348 | L91: =J91*K91 -> 0.0022339662
A92: Ultrasurf (30341) | C92: 0 | D92: =B92*C92 -> 0 | F92: =+B92 -> 0 | G92: 0 | H92: =F92*G92 -> 0 | J92: 1.389 | K92: 0.0023312553 | L92: =J92*K92 -> 0.0032381137
A93: HA Pallets (30350) | J93: 18.84 | K93: 0.0006 | L93: =J93*K93 -> 0.011304
A94: HA Bag Protectors (30342) | J94: 1.33 | K94: 0.0006 | L94: =J94*K94 -> 0.000798
D95: 0 | H95: 0 | L95: 0
A96: Total Material Cost Per Pound | D96: =SUM(D86:D95) -> 0 | H96: =SUM(H86:H95) -> 0 | L96: =SUM(L86:L95) -> 0.070852832
A98: Variable Cost - Production/R&M Labor & Benefits
F99: W&S Carve Out of Production Labor
A100: Labor Split:
B101: Prod. Plan (000) | C101: Rate (000 lbs/day) | D101: Kiln Days | E101: % Split | F101: 1 | G101: <--EEs | Hrs--> | H101: =(F101*C202*C204)+((F101*C202*C204*D113)) -> 345498296
A102: Ceramics | B102: =B54 -> 0 | C102: 550 | D102: =B102/C102 -> 0 | E102: =D102/D$108 -> 0 | F102: =(F101*C202*C204*C116)+((F101*C202*C204*D113)*C118) -> 18643341 | G102: Payroll | H102: =F102/$H$101 -> 0.053960732 | I102: Rate will be dependant on prodcut size
A103: CG280 | B103: =B55 -> 0 | C103: 0 | D103: 0 | E103: =D103/D$108 -> 0 | F103: =F102*C206 -> 5593002.3 | G103: IPC | H103: =F103/$H$101 -> 0.01618822
A104: CG300 | B104: =B56 -> 0 | C104: 0 | D104: 0 | E104: =D104/D$108 -> 0
A105: XXX | B105: =B57 -> 0 | C105: 0 | D105: 0 | E105: =D105/D$108 -> 0
A106: HA PELLETS | B106: =B58 -> 4900 | C106: 110 | D106: =B106/C106 -> 44.545455 | E106: =D106/D$108 -> 1 | I106: Reduced daily rate to 110 vs. 150
B107: =B59 -> 0 | C107: 0 | D107: 0 | E107: =D107/D$108 -> 0
B108: =SUM(B102:B107) -> 4900 | C108: =B108/D108 -> 110 | D108: =SUM(D102:D107) -> 44.545455 | E108: =D108/D$108 -> 1
A109: HA Group
B112: Jan | C112: Feb | D112: Mar | E112: Apr | F112: May | G112: Jun | H112: Jul
A113: Production Labor | B113: 119702.77 | C113: 140371.43 | D113: 166103.95 | E113: 166766.86 | F113: 105842.43 | G113: 147383.65 | H113: 163283.07
A114: R & M Labor | B114: 15222.93 | C114: 23913.55 | D114: 19670.79 | E114: 41336.57 | F114: 23672.31 | G114: 9419.99 | H114: 18308.82
A115: IPC | B115: 11228.99 | C115: 10794.51 | D115: 10146.4 | E115: 8112.73 | F115: -1917.2 | G115: 49379.56 | H115: 50660.85
A116: Supervision | B116: 3928.57 | C116: -3928.57 | D116: 0 | E116: -1311.46 | F116: 841.1 | G116: 0 | H116: 0
...

Sheet Dec
A1: TOOMSBORO STANDARD 2025
B3: CERAMICS | E3: CG 280 | H3: CG 300
B4: 25 Standard | C4: 23 Actual | D4: 20 Standard | E4: =$B$4 -> 25 Standard | F4: =+C4 -> 23 Actual | G4: =+D4 -> 20 Standard | H4: =+B4 -> 25 Standard | I4: =+C4 -> 23 Actual | J4: =+D4 -> 20 Standard
C5: (Jan-Sept) | F5: (Jan-Sept) | I5: (Jan-Sept)
A6: Materials | B6: =IF(B24<>0,$D$82,0) -> 0 | C6: 0.0585 | D6: 0.04156581 | E6: =+H82 -> 0 | F6: 0 | G6: 0 | H6: =+D96 -> 0 | I6: 0 | J6: 0
A7: Electricity | B7: =IF(B24<>0,$D$163,0) -> 0 | C7: 0.0105 | D7: 0.020277329 | E7: =G163 -> 0.0198372 | F7: 0 | G7: 0 | H7: =J163 -> 0.0198372 | I7: 0 | J7: 0
A8: Gas | B8: =IF(B24<>0,$D$164,0) -> 0 | C8: 0.0156 | D8: 0.014965 | E8: =G164 -> 0.0171 | F8: 0 | G8: 0 | H8: =J164 -> 0.0171 | I8: 0 | J8: 0
A9: R&M Supplies and Service | B9: =IF(B24<>0,$J$177,0) -> 0 | C9: 0.0192 | D9: 0.015915789 | E9: =$H$177 -> 0.03 | F9: 0 | G9: 0 | H9: =$H$177 -> 0.03 | I9: 0 | J9: 0
A10: Manufacturing Supplies | B10: =IF(B24<>0,$J$181,0) -> 0 | C10: 0.0008 | D10: 0.0026315789 | E10: =$H$181 -> 0.0055102041 | F10: 0 | G10: 0 | H10: =$H$181 -> 0.0055102041 | I10: 0 | J10: 0
A11: Other variable | B11: =IF(B24<>0,$J$184,0) -> 0 | C11: 0.0058 | D11: 0.0094736842 | E11: =$H$184 -> 0.01122449 | F11: 0 | G11: 0 | H11: =$H$184 -> 0.01122449 | I11: 0 | J11: 0
A12: Total Variable Costs | B12: =SUM(B6:B11) -> 0 | C12: =SUM(C6:C11) -> 0.1104 | D12: =SUM(D6:D11) -> 0.10482919 | E12: =SUM(E6:E11) -> 0.083671894 | F12: =SUM(F6:F11) -> 0 | G12: =SUM(G6:G11) -> 0 | H12: =SUM(H6:H11) -> 0.083671894 | I12: =SUM(I6:I11) -> 0 | J12: =SUM(J6:J11) -> 0
A14: Production Labor | B14: =IF($B$24<>0,$F$152/B24/1000,0) -> 0 | C14: 0.0246 | D14: 0.0073599375 | E14: =$D$124*$E$108/$B$49/1000 -> 0.00093026761 | F14: 0 | G14: 0 | H14: =$D$124*$E$108/$B$49/1000 -> 0.00093026761 | I14: 0 | J14: 0
A15: Repairs & Maintenance Labor | B15: =IF($B$24<>0,$F$153/$B$24/1000,0) -> 0 | C15: 0.009 | D15: 0.0042419375 | E15: =$H$124*$E$108/$B$49/1000 -> 0 | F15: 0 | G15: 0 | H15: =$H$124*$E$108/$B$49/1000 -> 0 | I15: 0 | J15: 0
A16: Indirect Payroll Costs (Benefits) | B16: =IF($B$24<>0,$F$155/$B$24/1000,0) -> 0 | C16: 0.0079 | D16: 0.0053897125 | E16: =$D$131*$E$108/$B$49/1000 -> 0 | F16: 0 | G16: 0 | H16: =$D$131*$E$108/$B$49/1000 -> 0 | I16: 0 | J16: 0
A17: Supervision | B17: =IF($B$24<>0,$F$154/$B$24/1000,0) -> 0 | C17: 0 | D17: 0.0026778947 | E17: =$F$194 -> 0 | F17: 0 | G17: 0 | H17: =$F$194 -> 0 | I17: 0 | J17: 0
A18: Depreciation | B18: =IF($B$24<>0,$B$196/$B$49/1000,0) -> 0 | C18: 0.0027 | D18: 0.1672 | E18: =$F$196 -> 0.055866735 | F18: 0 | G18: 0 | H18: =$F$196 -> 0.055866735 | I18: 0 | J18: 0
A19: Insurance & Taxes | B19: =IF($B$24<>0,$B$195/$B$49/1000,0) -> 0 | C19: 0.012 | D19: 0.012884211 | E19: =$F$195 -> 0.23436735 | F19: 0 | G19: 0 | H19: =$F$195 -> 0.23436735 | I19: 0 | J19: 0
A20: Total Fixed Costs | B20: =SUM(B14:B19) -> 0 | C20: =SUM(C14:C19) -> 0.0562 | D20: =SUM(D14:D19) -> 0.19975369 | E20: =SUM(E14:E19) -> 0.29116435 | F20: =SUM(F14:F19) -> 0 | G20: =SUM(G14:G19) -> 0 | H20: =SUM(H14:H19) -> 0.29116435 | I20: =SUM(I14:I19) -> 0 | J20: =SUM(J14:J19) -> 0
A22: TOTAL COSTS PER POUND | B22: =B12+B20 -> 0 | C22: =C12+C20 -> 0.1666 | D22: =D12+D20 -> 0.30458288 | E22: =E12+E20 -> 0.37483624 | F22: =F12+F20 -> 0 | G22: =G12+G20 -> 0 | H22: =H12+H20 -> 0.37483624 | I22: =I12+I20 -> 0 | J22: =J12+J20 -> 0
A24: PRODUCTION ( in 000 lbs ) | B24: =+B54 -> 0 | C24: 0 | D24: 80000 | E24: =+B55 -> 0 | F24: 0 | G24: 0 | H24: =+B56 -> 0 | I24: 0 | J24: 0
B26: XXX | E26: HA PELLETS
B27: =$B$4 -> 25 Standard | C27: =+C4 -> 23 Actual | D27: =+D4 -> 20 Standard | E27: 24 Standard | F27: 23 Actual | G27: 22 Standard | H27: =+B27 -> 25 Standard | I27: =+C27 -> 23 Actual | J27: =+D27 -> 20 Standard
C28: (Jan-Sept) | F28: (Jan-Aug)
A29: Materials | B29: =D82 -> 0.065965818 | C29: 0 | D29: 0 | E29: =IF(E47<>0,$L$96,0) -> 0.070852832 | F29: 0.078 | G29: 0.06025968 | H29: 0 | I29: 0 | J29: 0
A30: Electricity | B30: =D169 -> 0 | C30: 0 | D30: 0 | E30: =IF(E47<>0,$G$169,0) -> 0.043918811 | F30: 0.0432 | G30: 0.026879418 | H30: 0 | I30: 0 | J30: 0
A31: Gas | B31: =D170 -> 0 | C31: 0 | D31: 0 | E31: =IF(E47<>0,$G$170,0) -> 0.026 | F31: 0.019 | G31: 0.028567 | H31: =J170 -> 0 | I31: 0 | J31: 0
A32: R&M Supplies and Service | B32: =IF($B$47<>0,$H$177,0) -> 0 | C32: 0 | D32: 0 | E32: =IF(E47<>0,$H$177,0) -> 0.03 | F32: 0.0298 | G32: 0.027777778 | H32: 0 | I32: 0 | J32: 0
A33: Manufacturing Supplies | B33: =IF($B$47<>0,$H$181,0) -> 0 | C33: 0 | D33: 0 | E33: =IF(E47<>0,$H$181,0) -> 0.0055102041 | F33: 0.0012 | G33: 0.0069444444 | H33: 0 | I33: 0 | J33: 0
A34: Other variable | B34: =IF($B$47<>0,$H$184,0) -> 0 | C34: 0 | D34: 0 | E34: =IF(E47<>0,$H$184,0) -> 0.01122449 | F34: 0.0139 | G34: 0.0125 | H34: 0 | I34: 0 | J34: 0
A35: Total Variable Costs | B35: =SUM(B29:B34) -> 0.065965818 | C35: =SUM(C29:C34) -> 0 | D35: =SUM(D29:D34) -> 0 | E35: =SUM(E29:E34) -> 0.18750634 | F35: =SUM(F29:F34) -> 0.1851 | G35: =SUM(G29:G34) -> 0.16292832 | H35: =SUM(H29:H34) -> 0 | I35: =SUM(I29:I34) -> 0 | J35: =SUM(J29:J34) -> 0
A37: Production Labor | B37: =$D$124*$E$108/$B$49/1000 -> 0.00093026761 | C37: 0 | D37: 0 | E37: =IF($E$47<>0,$F$127/$E$47/1000,0) -> 0.040001507 | F37: 0.0353 | G37: 0.02156921 | H37: 0 | I37: 0 | J37: 0
A38: Repairs & Maintenance Labor | B38: =$H$124*$E$108/$B$49/1000 -> 0 | C38: 0 | D38: 0 | E38: =IF($E$47<>0,$F$128/$E$47/1000,0) -> 0.0048061173 | F38: 0.0067 | G38: 0.0051700857 | H38: 0 | I38: 0 | J38: 0
A39: Indirect Payroll Costs (Benefits) | B39: =$D$131*$E$108/$B$49/1000 -> 0 | C39: 0 | D39: 0 | E39: =IF($E$47<>0,$F$130/$E$47/1000,0) -> 0.012994211 | F39: 0.0112 | G39: 0.0080162316 | H39: 0 | I39: 0 | J39: 0
A40: Supervision | B40: =IF($B$49<>0,$F$194,0) -> 0 | C40: 0 | D40: 0 | E40: =IF($E$47<>0,$F$129/$E$47/1000,0) -> 0 | F40: 0 | G40: 0.00047638889 | H40: 0 | I40: 0 | J40: 0
A41: Depreciation | B41: =IF($B$49<>0,$F$196,0) -> 0.055866735 | C41: 0 | D41: 0 | E41: =IF($E$47<>0,$B$196/$B$49/1000/4,0) -> 0.0011638903 | F41: 0.0085 | G41: 0.0056777778 | H41: 0 | I41: 0 | J41: 0
A42: Insurance & Taxes | B42: =IF($B$49<>0,$F$195,0) -> 0.23436735 | C42: 0 | D42: 0 | E42: =IF($E$47<>0,$B$195/$B$49/1000/4,0) -> 0.0048826531 | F42: 0.0362 | G42: 0.025861111 | H42: 0 | I42: 0 | J42: 0
A43: Total Fixed Costs | B43: =SUM(B37:B42) -> 0.29116435 | C43: =SUM(C37:C42) -> 0 | D43: =SUM(D37:D42) -> 0 | E43: =SUM(E37:E42) -> 0.063848379 | F43: =SUM(F37:F42) -> 0.0979 | G43: =SUM(G37:G42) -> 0.066770805 | H43: =SUM(H37:H42) -> 0 | I43: =SUM(I37:I42) -> 0 | J43: =SUM(J37:J42) -> 0
A44: Excess Costs | F44: -0.0455
A45: TOTAL COSTS PER POUND | B45: =B35+B43 -> 0.35713017 | C45: =C35+C43 -> 0 | D45: 0.19962946 | E45: =E35+E43+E44 -> 0.25135472 | F45: =F35+F43+F44 -> 0.2375 | G45: =+G35+G43 -> 0.22969913 | H45: =H35+H43 -> 0 | I45: =I35+I43 -> 0 | J45: =J35+J43 -> 0 | L45: =E45-0.245 -> 0.0063547165 | M45: =E47*1000*L45 -> 31138.111
M46: =M45/12 -> 2594.8426
A47: PRODUCTION ( in 000 lbs ) | B47: =+B57 -> 0 | C47: 0 | D47: 0 | E47: =+B58 -> 4900 | F47: 15776 | G47: 36000 | H47: =+B59 -> 0 | I47: 0 | J47: 0
A49: TOTAL PLANT PRODUCTION ( in 000 lbs) | B49: =B24+E24+H24+B47+E47+H47 -> 4900 | C49: =C24+F24+I24+C47+F47+I47 -> 15776 | D49: =D24+G24+J24+D47+G47+J47 -> 116000
A51: Variable Costs - Material | B51: Purchase Price/lb * Yield Factor * Scrap Factor * Mix = Std. Cost Contribution
A53: Production Plan: | B53: Pounds (000) | C53: Product Split
A54: Ceramics | B54: ='2025 Summary'!$D$18 -> 0 | C54: =B54/$B$60 -> 0 | E54: =9*400000*7 -> 25200000
A55: CG280 | B55: 0 | C55: =B55/$B$60 -> 0
A56: CG300 | B56: 0 | C56: =B56/$B$60 -> 0
A57: XXX | B57: 0 | C57: =B57/$B$60 -> 0
A58: HA PELLETS | B58: ='2025 Summary'!$E$18 -> 4900 | C58: =B58/$B$60 -> 1
B59: 0 | C59: =B59/$B$60 -> 0
A60: Total | B60: =SUM(B54:B59) -> 4900 | C60: =B60/$B$60 -> 1
C62: Yield Factor | G62: Mix %
A63: Local Kaolin | B63: Price ($/Ton) | C63: Ceramics | D63: CG280 | E63: CG300 | F63: XXX | G63: HA Pellets | H63: Ceramics | I63: CG280 | J63: CG300 | K63: XXX | L63: HA Pellets
A64: Arcilla (local kaolin) 30012 | B64: =11.89*2 -> 23.78 | C64: =$C$76*H64 -> 0 | D64: =$C$86*I64 -> 0 | E64: =$G$86*J64 -> 0 | F64: =$K$86*K64 -> 0 | G64: =$K$86*L64 -> 0 | H64: 0 | I64: 0 | J64: 0 | K64: 0 | L64: 0
B65: 0 | C65: =$C$76*H65 -> 0 | D65: =$C$86*I65 -> 0 | E65: =$G$86*J65 -> 0 | F65: =$K$86*K65 -> 0 | G65: =$K$86*L65 -> 0 | H65: 0 | I65: 0 | J65: 0 | K65: 0 | L65: 0
C66: =SUM(C64:C65) -> 0 | D66: =SUM(D64:D65) -> 0 | E66: =SUM(E64:E65) -> 0 | F66: =SUM(F64:F65) -> 0 | G66: =SUM(G64:G65) -> 0
A67: Bauxite:
A68: Rusal (30008) | B68: 0 | C68: =$C$77*H68 -> 0 | D68: =$C$87*I68 -> 0 | E68: =$G$87*J68 -> 0 | F68: =$K$87*K68 -> 0 | G68: =$K$87*L68 -> 0 | H68: 0 | I68: 0 | J68: 0 | K68: 0 | L68: 0
A69: Kaolin - CE Calcined (30060) | B69: =116.72*2 -> 233.44 | C69: =$C$77*H69 -> 0 | D69: =$C$87*I69 -> 0 | E69: =$G$87*J69 -> 0 | F69: =$K$87*K69 -> 0 | G69: =$K$87*L69 -> 0 | H69: 0 | I69: 0 | J69: 0 | K69: 0 | L69: 0
B70: 0 | C70: 0 | D70: =$C$87*I70 -> 0 | E70: =$G$87*J70 -> 0 | F70: =$K$87*K70 -> 0 | G70: =$K$87*L70 -> 0 | H70: 0 | I70: 0 | J70: 0 | K70: 0 | L70: 0
B71: 0 | C71: 0 | D71: =$C$87*I71 -> 0 | E71: =$G$87*J71 -> 0 | F71: =$K$87*K71 -> 0 | G71: =$K$87*L71 -> 0 | H71: 0 | I71: 0 | J71: 0 | K71: 0 | L71: 0
C72: =SUM(C68:C71) -> 0 | D72: =SUM(D68:D71) -> 0 | E72: =SUM(E68:E71) -> 0 | F72: =SUM(F68:F71) -> 0 | G72: =SUM(G68:G71) -> 0
B74: Ceramics | F74: CG280
B75: Price ($/lb) | C75: Yield Factor | D75: Std $ Contrib | F75: Price ($/lb) | G75: Yield Factor | H75: Std $ Contrib
A76: Local Kaolin | B76: =0.011 -> 0.011 | C76: =AVERAGE(3.6826,3.5997, 2.6808) -> 3.3210333 | D76: =B76*C76 -> 0.036531367 | F76: 0 | G76: 0 | H76: =F76*G76 -> 0
A77: Bauxite | B77: =($B$68*$H$68+$B$69*$H$69+$B$70*$H$70+$B$71*$H$71)/2000 -> 0 | C77: 0 | D77: =B77*C77 -> 0 | F77: =($B$68*$L$68+$B$69*$L$69+$B$70*$L$70+$B$71*$L$71)/2000 -> 0 | G77: 0 | H77: =F77*G77 -> 0
A78: PVA (30017) | B78: 1.838 | C78: 0.0081 | D78: =B78*C78 -> 0.0148878 | F78: =+B78 -> 1.838 | G78: 0 | H78: =F78*G78 -> 0
A79: Dispersant (30011) | B79: =750/1000 -> 0.75 | C79: 0.0161 | D79: =B79*C79 -> 0.012075 | F79: =+B79 -> 0.75 | G79: 0
A80: Ammonia (30000) | B80: =157.43/1000 -> 0.15743 | C80: 0.0157 | D80: =B80*C80 -> 0.002471651 | F80: =+B80 -> 0.15743 | G80: 0 | H80: 0
A82: Total Material Cost Per Pound | D82: =SUM(D76:D80) -> 0.065965818 | H82: =SUM(H76:H80) -> 0
B84: CG300 | F84: XXX | J84: HA Pellets
B85: Price ($/lb) | C85: Yield Factor/BOM | D85: Std $ Contrib | F85: Price ($/lb) | G85: Yield Factor | H85: Std $ Contrib | J85: Price ($/lb) | K85: Yield Factor | L85: Std $ Contrib
A86: Local kaolin | B86: =($B$64*$I$64+$B$65*$I$65)/2000 -> 0 | C86: 0 | D86: =B86*C86 -> 0 | F86: =($B$64*$J$64+$B$65*$J$65)/2000 -> 0 | G86: 0 | H86: =F86*G86 -> 0 | J86: =($B$64*$K$64+$B$65*$K$65)/2000 -> 0 | K86: 0 | L86: =J86*K86 -> 0
A87: Bauxite | B87: =($B$68*$I$68+$B$69*$I$69+$B$70*$I$70+$B$71*$I$71)/2000 -> 0 | C87: 0 | D87: =B87*C87 -> 0 | F87: =($B$68*$J$68+$B$69*$J$69+$B$70*$J$70+$B$71*$J$71)/2000 -> 0 | G87: 0 | H87: =F87*G87 -> 0 | J87: =($B$68*$K$68+$B$69*$K$69+$B$70*$K$70+$B$71*$K$71)/2000 -> 0 | K87: 0 | L87: =J87*K87 -> 0
A88: PVA (30017) | B88: 2.54 | C88: 0 | D88: =B88*C88 -> 0 | F88: =+B88 -> 2.54 | G88: 0 | H88: =F88*G88 -> 0 | J88: 1.964 | K88: 0.020848164 | L88: =J88*K88 -> 0.040945794
A89: Dispersant (30011) | B89: =750/1000 -> 0.75 | C89: 0 | D89: =B89*C89 -> 0 | F89: =+B89 -> 0.75 | G89: 0 | H89: =F89*G89 -> 0 | J89: 0.591 | K89: 0.0031014518 | L89: =J89*K89 -> 0.001832958
A90: Ammonia (30000) | B90: =157.43/1000 -> 0.15743 | C90: 0 | D90: =B90*C90 -> 0 | F90: =+B90 -> 0.15743 | G90: 0 | H90: =F90*G90 -> 0 | J90: 0.105 | K90: 0.1 | L90: =J90*K90 -> 0.0105
A91: Defoamer (30010) | C91: 0 | D91: =B91*C91 -> 0 | F91: =+B91 -> 0 | G91: 0 | H91: =F91*G91 -> 0 | J91: 1.027 | K91: 0.0021752348 | L91: =J91*K91 -> 0.0022339662
A92: Ultrasurf (30341) | C92: 0 | D92: =B92*C92 -> 0 | F92: =+B92 -> 0 | G92: 0 | H92: =F92*G92 -> 0 | J92: 1.389 | K92: 0.0023312553 | L92: =J92*K92 -> 0.0032381137
A93: HA Pallets (30350) | J93: 18.84 | K93: 0.0006 | L93: =J93*K93 -> 0.011304
A94: HA Bag Protectors (30342) | J94: 1.33 | K94: 0.0006 | L94: =J94*K94 -> 0.000798
D95: 0 | H95: 0 | L95: 0
A96: Total Material Cost Per Pound | D96: =SUM(D86:D95) -> 0 | H96: =SUM(H86:H95) -> 0 | L96: =SUM(L86:L95) -> 0.070852832
A98: Variable Cost - Production/R&M Labor & Benefits
F99: W&S Carve Out of Production Labor
A100: Labor Split:
B101: Prod. Plan (000) | C101: Rate (000 lbs/day) | D101: Kiln Days | E101: % Split | F101: 1 | G101: <--EEs | Hrs--> | H101: =(F101*C202*C204)+((F101*C202*C204*D113)) -> 345498296
A102: Ceramics | B102: =B54 -> 0 | C102: 550 | D102: =B102/C102 -> 0 | E102: =D102/D$108 -> 0 | F102: =(F101*C202*C204*C116)+((F101*C202*C204*D113)*C118) -> 18643341 | G102: Payroll | H102: =F102/$H$101 -> 0.053960732 | I102: Rate will be dependant on prodcut size
A103: CG280 | B103: =B55 -> 0 | C103: 0 | D103: 0 | E103: =D103/D$108 -> 0 | F103: =F102*C206 -> 5593002.3 | G103: IPC | H103: =F103/$H$101 -> 0.01618822
A104: CG300 | B104: =B56 -> 0 | C104: 0 | D104: 0 | E104: =D104/D$108 -> 0
A105: XXX | B105: =B57 -> 0 | C105: 0 | D105: 0 | E105: =D105/D$108 -> 0
A106: HA PELLETS | B106: =B58 -> 4900 | C106: 110 | D106: =B106/C106 -> 44.545455 | E106: =D106/D$108 -> 1 | I106: Reduced daily rate to 110 vs. 150
B107: =B59 -> 0 | C107: 0 | D107: 0 | E107: =D107/D$108 -> 0
B108: =SUM(B102:B107) -> 4900 | C108: =B108/D108 -> 110 | D108: =SUM(D102:D107) -> 44.545455 | E108: =D108/D$108 -> 1
A109: HA Group
B112: Jan | C112: Feb | D112: Mar | E112: Apr | F112: May | G112: Jun | H112: Jul
A113: Production Labor | B113: 119702.77 | C113: 140371.43 | D113: 166103.95 | E113: 166766.86 | F113: 105842.43 | G113: 147383.65 | H113: 163283.07
A114: R & M Labor | B114: 15222.93 | C114: 23913.55 | D114: 19670.79 | E114: 41336.57 | F114: 23672.31 | G114: 9419.99 | H114: 18308.82
A115: IPC | B115: 11228.99 | C115: 10794.51 | D115: 10146.4 | E115: 8112.73 | F115: -1917.2 | G115: 49379.56 | H115: 50660.85
A116: Supervision | B116: 3928.57 | C116: -3928.57 | D116: 0 | E116: -1311.46 | F116: 841.1 | G116: 0 | H116: 0
...
