Workbook

Sheet 18 Std v1 (Recap)
B1: 2018 Standards | G1: Reference
B2: 100.1M LB Scenario | E2: 140.1M LB Scenario | G2: Jan-Oct 2017 Actual | J2: 2017 Standard
B3: LBS in 000s | C3: $/LB | E3: LBS in 000s | F3: $/LB | G3: LBS in 000s | H3: $/LB | J3: LBS in 000s | K3: $/LB
A4: NIRO:
A5: CEP/CL/HP/CARBOBEAD | B5: ='18 Std (v1)'!$B$24 -> 50100 | C5: ='18 Std (v1)'!$B$22 -> 0.20646543 | E5: ='18 Std v1 (140.1M)'!$B$24 -> 90100 | F5: ='18 Std v1 (140.1M)'!$B$22 -> 0.1661563 | G5: ='18 Std (v1)'!C24 -> 121112.43 | H5: ='18 Std (v1)'!C22 -> 0.16329172 | J5: ='18 Std (v1)'!D24 -> 190000 | K5: ='18 Std (v1)'!D22 -> 0.11902659
A6: NRT/FUSION | B6: ='18 Std (v1)'!$K$24 -> 0 | C6: ='18 Std (v1)'!$K$22 -> 0.43673061 | E6: ='18 Std v1 (140.1M)'!$K$24 -> 0 | F6: ='18 Std v1 (140.1M)'!$K$22 -> 0.39642148 | G6: ='18 Std (v1)'!L24 -> 630.366 | H6: ='18 Std (v1)'!L22 -> 0.39939454 | J6: ='18 Std (v1)'!M24 -> 0 | K6: ='18 Std (v1)'!M22 -> 0
A7: CARBOGRIND | B7: ='18 Std (v1)'!$N$24 -> 0 | C7: ='18 Std (v1)'!$N$22 -> 0.30703664 | E7: ='18 Std v1 (140.1M)'!$N$24 -> 0 | F7: ='18 Std v1 (140.1M)'!$N$22 -> 0.30469592 | G7: ='18 Std (v1)'!O24 -> 1071.4 | H7: ='18 Std (v1)'!O22 -> 0.31298551 | J7: ='18 Std (v1)'!P24 -> 0 | K7: ='18 Std (v1)'!P22 -> 0
A8: NIRO TOTAL | B8: =SUM(B5:B7) -> 50100 | E8: =SUM(E5:E7) -> 90100 | G8: =SUM(G5:G7) -> 122814.2 | J8: =SUM(J5:J7) -> 190000
A10: KS:
A11: KSLD/KRYPTOCAST | B11: ='18 Std (v1)'!$E$24 -> 35000 | C11: ='18 Std (v1)'!$E$22 -> 0.40829992 | E11: ='18 Std v1 (140.1M)'!$E$24 -> 35000 | F11: ='18 Std v1 (140.1M)'!$E$22 -> 0.37065519 | G11: ='18 Std (v1)'!F24 -> 8379.436 | H11: ='18 Std (v1)'!F22 -> 0.36206859 | J11: ='18 Std (v1)'!G24 -> 40000 | K11: ='18 Std (v1)'!G22 -> 0.25987429
A12: KSHD | B12: ='18 Std (v1)'!$H$24 -> 15000 | C12: ='18 Std (v1)'!$H$22 -> 0.8438075 | E12: ='18 Std v1 (140.1M)'!$H$24 -> 15000 | F12: ='18 Std v1 (140.1M)'!$H$22 -> 0.80616277 | G12: ='18 Std (v1)'!I24 -> 15451 | H12: ='18 Std (v1)'!I22 -> 0.77540423 | J12: ='18 Std (v1)'!J24 -> 6000 | K12: ='18 Std (v1)'!J22 -> 0.79889817
A13: KS TOTAL | B13: =SUM(B11:B12) -> 50000 | E13: =SUM(E11:E12) -> 50000 | G13: =SUM(G11:G12) -> 23830.436 | J13: =SUM(J11:J12) -> 46000
A15: GRAND TOTAL | B15: =B8+B13 -> 100100 | E15: =E8+E13 -> 140100 | G15: =G8+G13 -> 146644.64 | J15: =J8+J13 -> 236000

Sheet 18 Std v1 (140.1M)
A1: EUFAULA PLANT STANDARDS | W1: Cost Center 10001002 Total | AF1: Cost Center 10001002 Bulk Production | AO1: CEP/CL | AP1: KSLD | AQ1: KSHD | AR1: Total | AS1: CEP/CL | AT1: KSLD | AU1: KSHD
W2: Production | X2: Bagging | Y2: Total Cost | Z2: Unit Qty | AA2: Unit Price | AB2: UOM | AC2: Activity/Matl | AD2: Account | AE2: Acct % | AF2: CEP/CL | AG2: KSLD | AH2: KSHD | AI2: Total Cost | AJ2: CEP/CL Qty | AK2: KSLD Qty | AL2: KSHD Qty | AM2: Total Qty | AN2: Unit Price | AO2: Qty/1000 lbs | AP2: Qty/1000 lbs | AQ2: Qty/1000 lbs | AR2: Under-Abs | AS2: Under-Abs | AT2: Under-Abs | AU2: Under-Abs
B3: CEP/CL/HP/CARBOBEAD (NIRO) | E3: KSLD | H3: KSHD | K3: NRT/FUSION (NIRO) | N3: CARBOGRIND (NIRO) | R3: COMPOSITE
B4: 18 Std | C4: 17 Act | D4: 17 Std | E4: 18 Std | F4: 17 Act | G4: 17 Std | H4: 18 Std | I4: 17 Act | J4: 17 Std | K4: 18 Std | L4: 17 Act | M4: 17 Std | N4: 18 Std | O4: 17 Act | P4: 17 Std | R4: 18 Std | S4: Absorb Limit | T4: 18 Absorb | U4: 18 Underabs
C5: (Jan-Oct) | F5: (Jan-Oct) | I5: (Jan-Oct) | L5: (Jan-Oct) | O5: (Jan-Oct)
A6: Materials | B6: =IF($B$24<>0,$D$56,0) -> 0.046284643 | C6: 0.04891789 | D6: 0.037383237 | E6: =$F$56 -> 0.14603303 | F6: 0.14828624 | G6: 0.10706625 | H6: =IF($H$24<>0,$H$56,0) -> 0.58154061 | I6: 0.58125835 | J6: 0.50666479 | K6: =J56 -> 0.27654982 | L6: 0.28027625 | M6: 0 | N6: =L56 -> 0.18482427 | O6: 0.18504975 | P6: 0 | R6: =(B6*B$24+E6*E$24+H6*H$24+K6*K$24+N6*N$24)/R$24 -> 0.12851186 | S6: =R6 -> 0.12851186 | T6: =R6 -> 0.12851186 | U6: =R6-T6 -> 0 | V6: =R6*$R$24 -> 18004.511
A7: Electricity | B7: =IF($B$24<>0,$D$104,0) -> 0.0061759711 | C7: 0.0067184367 | D7: 0.0056445202 | E7: =$H$104 -> 0.0538927 | F7: 0.053032975 | G7: 0.046359529 | H7: =IF($H$24<>0,$H$104,0) -> 0.0538927 | I7: 0.0550883 | J7: 0.051146 | K7: =B7 -> 0.0061759711 | L7: 0.0045711698 | M7: 0 | N7: =B7 -> 0.0061759711 | O7: 0.0047608363 | P7: 0 | R7: =(B7*B$24+E7*E$24+H7*H$24+K7*K$24+N7*N$24)/R$24 -> 0.023205496 | S7: 0.0065396807 | T7: =IF($R$22<$S$22,R7,IF($R$12<$S$12,R7,IF(AND($R$12>$S$12,$R$20<$S$20),(($S$7+$S$8+$S$9+$S$10+$S$11)+($S$20-$R$20))/($R$7+$R$8+$R$9+$R$10+$R$11)*R7,R7/($R$7+$R$8+$R$9+$R$10+$R$11)*($S$7+$S$8+$S$9+$S$10+$S$11)))) -> 0.016526343 | U7: =R7-T7 -> 0.0066791526 | V7: =R7*$R$24 -> 3251.09 | W7: =ROUND($G$98*$H$98,0) -> 3251090 | X7: 0 | Y7: =SUM(W7:X7) -> 3251090 | Z7: =G98 -> 44218400 | AA7: =Y7/Z7 -> 0.073523465 | AB7: kwh | AC7: ELE01 | AD7: 630010 | AE7: 1 | AF7: =ROUND($B$104*$C$104*$B$24*1000,0) -> 556455 | AG7: =ROUND($F$104*$G$104*$E$24*1000,0) -> 1886245 | AH7: =ROUND($F$104*$G$104*$H$24*1000,0) -> 808391 | AI7: =SUM(AF7:AH7) -> 3251091 | AJ7: =$B$104*$B$24*1000 -> 7568400 | AK7: =$F$104*$E$24*1000 -> 25655000 | AL7: =$F$104*$H$24*1000 -> 10995000 | AM7: =SUM(AJ7:AL7) -> 44218400 | AN7: =AI7/AM7 -> 0.073523488 | AO7: =ROUND(AJ7/$B$24,3) -> 84 | AP7: =ROUND(AK7/$E$24,3) -> 733 | AQ7: =IF($H$24<>0,ROUND(AL7/$H$24,3),0) -> 733 | AR7: =U7*$R$24 -> 935.74928 | AS7: =$AR7/$AM7*AJ7 -> 160.1624 | AT7: =$AR7/$AM7*AK7 -> 542.91082 | AU7: =$AR7/$AM7*AL7 -> 232.67607
A8: Gas | B8: =IF($B$24<>0,$D$109,0) -> 0.01909316 | C8: 0.023250696 | D8: 0.017573111 | E8: =$H$109 -> 0.010739902 | F8: 0.014393442 | G8: 0.010073294 | H8: =IF($H$24<>0,$H$109,0) -> 0.010739902 | I8: 0.012985865 | J8: 0.0124745 | K8: =B8 -> 0.01909316 | L8: 0.031930815 | M8: 0 | N8: =B8 -> 0.01909316 | O8: 0.020645268 | P8: 0 | R8: =(B8*B$24+E8*E$24+H8*H$24+K8*K$24+N8*N$24)/R$24 -> 0.016111983 | S8: 0.029646433 | T8: =IF($R$22<$S$22,R8,IF($R$12<$S$12,R8,IF(AND($R$12>$S$12,$R$20<$S$20),(($S$7+$S$8+$S$9+$S$10+$S$11)+($S$20-$R$20))/($R$7+$R$8+$R$9+$R$10+$R$11)*R8,R8/($R$7+$R$8+$R$9+$R$10+$R$11)*($S$7+$S$8+$S$9+$S$10+$S$11)))) -> 0.01147453 | U8: =R8-T8 -> 0.0046374528 | V8: =R8*$R$24 -> 2257.2888 | W8: =ROUND($D$98*$C$98,0) -> 2257289 | X8: 0 | Y8: =SUM(W8:X8) -> 2257289 | Z8: =C98*1000 -> 5.6748e+08 | AA8: =Y8/Z8 -> 0.0039777419 | AB8: mbtu | AC8: GAS01 | AD8: 630015 | AE8: 1 | AF8: =ROUND($B$109*$C$109*$B$24*1000,0) -> 1720294 | AG8: =ROUND($F$109*$G$109*$E$24*1000,0) -> 375897 | AH8: =ROUND($F$109*$G$109*$H$24*1000,0) -> 161099 | AI8: =SUM(AF8:AH8) -> 2257290 | AJ8: =$B$109*$B$24*1000*1000 -> 4.3248e+08 | AK8: =$F$109*$E$24*1000*1000 -> 94500000 | AL8: =$F$109*$H$24*1000*1000 -> 40500000 | AM8: =SUM(AJ8:AL8) -> 5.6748e+08 | AN8: =AI8/AM8 -> 0.0039777437 | AO8: =ROUND(AJ8/$B$24,3) -> 4800 | AP8: =ROUND(AK8/$E$24,3) -> 2700 | AQ8: =IF($H$24<>0,ROUND(AL8/$H$24,3),0) -> 2700 | AR8: =U8*$R$24 -> 649.70714 | AS8: =$AR8/$AM8*AJ8 -> 495.14581 | AT8: =$AR8/$AM8*AK8 -> 108.19293 | AU8: =$AR8/$AM8*AL8 -> 46.368399
A9: R&M Supplies and Service | B9: =IF($B$24<>0,$H$119,0) -> 0.025695933 | C9: 0.020888729 | D9: 0.0091201588 | E9: =$H$119 -> 0.025695933 | F9: 0.021258138 | G9: 0.0093875756 | H9: =IF($H$24<>0,$H$119,0) -> 0.025695933 | I9: 0.015830358 | J9: 0.031944443 | K9: =B9 -> 0.025695933 | L9: 0.01877303 | M9: 0 | N9: =B9 -> 0.025695933 | O9: 0.024556496 | P9: 0 | R9: =(B9*B$24+E9*E$24+H9*H$24+K9*K$24+N9*N$24)/R$24 -> 0.025695933 | S9: 0.014439611 | T9: =IF($R$22<$S$22,R9,IF($R$12<$S$12,R9,IF(AND($R$12>$S$12,$R$20<$S$20),(($S$7+$S$8+$S$9+$S$10+$S$11)+($S$20-$R$20))/($R$7+$R$8+$R$9+$R$10+$R$11)*R9,R9/($R$7+$R$8+$R$9+$R$10+$R$11)*($S$7+$S$8+$S$9+$S$10+$S$11)))) -> 0.018299967 | U9: =R9-T9 -> 0.0073959658 | V9: =R9*$R$24 -> 3600.0001 | W9: =ROUND($G$119,0) -> 3600000 | X9: 0 | Y9: =SUM(W9:X9) -> 3600000 | Z9: =$B$25*1000 -> 140100000 | AA9: =Y9/Z9 -> 0.025695931 | AB9: lb | AC9: RMS01 | AD9: 630000 | AE9: 1 | AF9: =$H$119*$B$24*1000 -> 2315203.5 | AG9: =$H$119*$E$24*1000 -> 899357.64 | AH9: =$H$119*$H$24*1000 -> 385438.99 | AI9: =SUM(AF9:AH9) -> 3600000.1 | AJ9: =$B$24*1000 -> 90100000 | AK9: =$E$24*1000 -> 35000000 | AL9: =$H$24*1000 -> 15000000 | AM9: =SUM(AJ9:AL9) -> 140100000 | AN9: =AI9/AM9 -> 0.025695933 | AO9: =ROUND(AJ9/$B$24,3) -> 1000 | AP9: =ROUND(AK9/$E$24,3) -> 1000 | AQ9: =IF($H$24<>0,ROUND(AL9/$H$24,3),0) -> 1000 | AR9: =U9*$R$24 -> 1036.1748 | AS9: =$AR9/$AM9*AJ9 -> 666.37652 | AT9: =$AR9/$AM9*AK9 -> 258.8588 | AU9: =$AR9/$AM9*AL9 -> 110.93949
A10: Manufacturing Supplies | B10: =IF($B$24<>0,$H$123,0) -> 0.0034261242 | C10: 0.0025984533 | D10: 0.00079305734 | E10: =$H$123 -> 0.0034261242 | F10: 0.0020231732 | G10: 0.00081631098 | H10: =IF($H$24<>0,$H$123,0) -> 0.0034261242 | I10: 0.0035917746 | J10: 0.0027777778 | K10: =B10 -> 0.0034261242 | L10: 0.0021372028 | M10: 0 | N10: =B10 -> 0.0034261242 | O10: 0.0016521561 | P10: 0 | R10: =(B10*B$24+E10*E$24+H10*H$24+K10*K$24+N10*N$24)/R$24 -> 0.0034261242 | S10: 0.0011089115 | T10: =IF($R$22<$S$22,R10,IF($R$12<$S$12,R10,IF(AND($R$12>$S$12,$R$20<$S$20),(($S$7+$S$8+$S$9+$S$10+$S$11)+($S$20-$R$20))/($R$7+$R$8+$R$9+$R$10+$R$11)*R10,R10/($R$7+$R$8+$R$9+$R$10+$R$11)*($S$7+$S$8+$S$9+$S$10+$S$11)))) -> 0.0024399955 | U10: =R10-T10 -> 0.00098612873 | V10: =R10*$R$24 -> 480 | W10: =ROUND($G$123,0) -> 480000 | X10: 0 | Y10: =SUM(W10:X10) -> 480000 | Z10: =$B$25*1000 -> 140100000 | AA10: =Y10/Z10 -> 0.0034261242 | AB10: lb | AC10: MFG01 | AD10: 631050 | AE10: 1 | AF10: =$H$123*$B$24*1000 -> 308693.79 | AG10: =$H$123*$E$24*1000 -> 119914.35 | AH10: =$H$123*$H$24*1000 -> 51391.863 | AI10: =SUM(AF10:AH10) -> 480000 | AJ10: =$B$24*1000 -> 90100000 | AK10: =$E$24*1000 -> 35000000 | AL10: =$H$24*1000 -> 15000000 | AM10: =SUM(AJ10:AL10) -> 140100000 | AN10: =AI10/AM10 -> 0.0034261242 | AO10: =ROUND(AJ10/$B$24,3) -> 1000 | AP10: =ROUND(AK10/$E$24,3) -> 1000 | AQ10: =IF($H$24<>0,ROUND(AL10/$H$24,3),0) -> 1000 | AR10: =U10*$R$24 -> 138.15664 | AS10: =$AR10/$AM10*AJ10 -> 88.850199 | AT10: =$AR10/$AM10*AK10 -> 34.514506 | AU10: =$AR10/$AM10*AL10 -> 14.791931
A11: Other variable | B11: =IF($B$24<>0,$H$126,0) -> 0.0085653105 | C11: 0.0071261242 | D11: 0.002973965 | E11: =$H$126 -> 0.0085653105 | F11: 0.008722241 | G11: 0.0030611662 | H11: =IF($H$24<>0,$H$126,0) -> 0.0085653105 | I11: 0.0068701845 | J11: 0.010416667 | K11: =B11 -> 0.0085653105 | L11: 0.0078377165 | M11: 0 | N11: =B11 -> 0.0085653105 | O11: 0.011616427 | P11: 0 | R11: =(B11*B$24+E11*E$24+H11*H$24+K11*K$24+N11*N$24)/R$24 -> 0.0085653105 | S11: 0.0031061887 | T11: =IF($R$22<$S$22,R11,IF($R$12<$S$12,R11,IF(AND($R$12>$S$12,$R$20<$S$20),(($S$7+$S$8+$S$9+$S$10+$S$11)+($S$20-$R$20))/($R$7+$R$8+$R$9+$R$10+$R$11)*R11,R11/($R$7+$R$8+$R$9+$R$10+$R$11)*($S$7+$S$8+$S$9+$S$10+$S$11)))) -> 0.0060999887 | U11: =R11-T11 -> 0.0024653218 | V11: =R11*$R$24 -> 1200 | W11: =ROUND($G$126,0) -> 1200000 | X11: 0 | Y11: =SUM(W11:X11) -> 1200000 | Z11: =$B$25*1000 -> 140100000 | AA11: =Y11/Z11 -> 0.0085653105 | AB11: lb | AC11: VAR01 | AD11: see below | AE11: see below | AF11: =$H$126*$B$24*1000 -> 771734.48 | AG11: =$H$126*$E$24*1000 -> 299785.87 | AH11: =$H$126*$H$24*1000 -> 128479.66 | AI11: =SUM(AF11:AH11) -> 1200000 | AJ11: =$B$24*1000 -> 90100000 | AK11: =$E$24*1000 -> 35000000 | AL11: =$H$24*1000 -> 15000000 | AM11: =SUM(AJ11:AL11) -> 140100000 | AN11: =AI11/AM11 -> 0.0085653105 | AO11: =ROUND(AJ11/$B$24,3) -> 1000 | AP11: =ROUND(AK11/$E$24,3) -> 1000 | AQ11: =IF($H$24<>0,ROUND(AL11/$H$24,3),0) -> 1000 | AR11: =U11*$R$24 -> 345.39159 | AS11: =$AR11/$AM11*AJ11 -> 222.1255 | AT11: =$AR11/$AM11*AK11 -> 86.286264 | AU11: =$AR11/$AM11*AL11 -> 36.979827
A12: Total Variable Costs | B12: =SUM(B6:B11) -> 0.10924114 | C12: =SUM(C6:C11) -> 0.10950033 | D12: =SUM(D6:D11) -> 0.073488049 | E12: =SUM(E6:E11) -> 0.248353 | F12: =SUM(F6:F11) -> 0.24771621 | G12: =SUM(G6:G11) -> 0.17676413 | H12: =SUM(H6:H11) -> 0.68386058 | I12: =SUM(I6:I11) -> 0.67562483 | ... P12: =SUM(P6:P11) -> 0 | R12: =SUM(R6:R11) -> 0.2055167 | S12: =SUM(S6:S11) -> 0.18335268 | T12: =SUM(T6:T11) -> 0.18335268 | U12: =SUM(U6:U11) -> 0.022164022 | V12: =SUM(V7:V11) -> 10788.379 | W12: =SUM(W7:W11) -> 10788379 | X12: =SUM(X7:X11) -> 0 | Y12: =SUM(Y7:Y11) -> 10788379 | AF12: =SUM(AF7:AF11) -> 5672380.8 | AG12: =SUM(AG7:AG11) -> 3581199.9 | AH12: =SUM(AH7:AH11) -> 1534800.5 | AI12: =SUM(AI7:AI11) -> 10788381 | AR12: =SUM(AR7:AR11) -> 3105.1794 | AS12: =SUM(AS7:AS11) -> 1632.6604 | AT12: =SUM(AT7:AT11) -> 1030.7633 | AU12: =SUM(AU7:AU11) -> 441.75571
A14: Production Labor | B14: =IF($B$24<>0,$F$89/$B$24/1000,0) -> 0.021671575 | C14: 0.0130835 | D14: 0.015388494 | E14: =$H$89/($E$24+$H$24)/1000 -> 0.021671575 | F14: 0.015315616 | G14: 0.015854474 | H14: =IF($H$24<>0,$H$89/($E$24+$H$24)/1000,0) -> 0.021671575 | I14: 0.035737987 | J14: 0.055160288 | K14: =B14 -> 0.021671575 | L14: 0.014090322 | M14: 0 | N14: =B14 -> 0.021671575 | O14: 0.013746771 | P14: 0 | R14: =(B14*B$24+E14*E$24+H14*H$24+K14*K$24+N14*N$24)/R$24 -> 0.021671575 | S14: 0.011308447 | T14: =R14 -> 0.021671575 | U14: =R14-T14 -> 0 | V14: =R14*$R$24 -> 3036.1876 | W14: =ROUND($D$78,0) -> 3036188 | X14: =ROUND($D$77,0) -> 68408 | Y14: =SUM(W14:X14) -> 3104596 | Z14: =$B$76 -> 99348 | AA14: =Y14/Z14 -> 31.249708 | AB14: hr | AC14: DLAB01 | AD14: see below | AE14: see below | AF14: =$F89 -> 1952608.9 | AG14: =$H89/($E$24+$H$24)*E24 -> 758505.12 | AH14: =$H89/($E$24+$H$24)*H24 -> 325073.62 | AI14: =SUM(AF14:AH14) -> 3036187.6 | AJ14: =$E89 -> 62484.085 | AK14: =$G89/($E$24+$H$24)*E24 -> 24272.397 | AL14: =$G89/($E$24+$H$24)*H24 -> 10402.456 | AM14: =SUM(AJ14:AL14) -> 97158.938 | AN14: =AI14/AM14 -> 31.2497 | AO14: =ROUND(AJ14/$B$24,3) -> 0.693 | AP14: =ROUND(AK14/$E$24,3) -> 0.693 | AQ14: =IF($H$24<>0,ROUND(AL14/$H$24,3),0) -> 0.693 | AR14: =U14*$R$24 -> 0 | AS14: =$AR14/$AM14*AJ14 -> 0 | AT14: =$AR14/$AM14*AK14 -> 0 | AU14: =$AR14/$AM14*AL14 -> 0
A15: Repairs & Maintenance Labor | B15: =IF($B$24<>0,$F$90/$B$24/1000,0) -> 0.0086067633 | C15: 0.0055430533 | D15: 0.0054755569 | E15: =$H$90/($E$24+$H$24)/1000 -> 0.0086067633 | F15: 0.0064201194 | G15: 0.0056361085 | H15: =IF($H$24<>0,$H$90/($E$24+$H$24)/1000,0) -> 0.0086067633 | I15: 0.014775811 | J15: 0.01917879 | K15: =B15 -> 0.0086067633 | L15: 0.0061446049 | M15: 0 | N15: =B15 -> 0.0086067633 | O15: 0.0062273101 | P15: 0 | R15: =(B15*B$24+E15*E$24+H15*H$24+K15*K$24+N15*N$24)/R$24 -> 0.0086067633 | S15: 0.0052712801 | T15: =S22-T12-T14 -> 0.01699873 | U15: =R15-T15 -> -0.0083919666 | V15: =R15*$R$24 -> 1205.8075 | W15: =ROUND($H$76,0) -> 1205808 | X15: 0 | Y15: =SUM(W15:X15) -> 1205808 | Z15: =$F$76 -> 36691.2 | AA15: =Y15/Z15 -> 32.863684 | AB15: hr | AC15: MLAB01 | AD15: see below | AE15: see below | AF15: =$F90 -> 775469.38 | AG15: =$H90/($E$24+$H$24)*E24 -> 301236.72 | AH15: =$H90/($E$24+$H$24)*H24 -> 129101.45 | AI15: =SUM(AF15:AH15) -> 1205807.5 | AJ15: =$E90 -> 23596.553 | AK15: =$G90/($E$24+$H$24)*E24 -> 9166.2527 | AL15: =$G90/($E$24+$H$24)*H24 -> 3928.394 | AM15: =SUM(AJ15:AL15) -> 36691.2 | AN15: =AI15/AM15 -> 32.863671 | AO15: =ROUND(AJ15/$B$24,3) -> 0.262 | AP15: =ROUND(AK15/$E$24,3) -> 0.262 | AQ15: =IF($H$24<>0,ROUND(AL15/$H$24,3),0) -> 0.262 | AR15: =U15*$R$24 -> -1175.7145 | AS15: =$AR15/$AM15*AJ15 -> -756.11619 | AT15: =$AR15/$AM15*AK15 -> -293.71883 | AU15: =$AR15/$AM15*AL15 -> -125.8795
A16: Indirect Payroll Costs (Benefits) | B16: =IF($B$24<>0,$F$91/$B$24/1000,0) -> 0.012035476 | C16: 0.0071493219 | D16: 0.0093107449 | E16: =$H$91/($E$24+$H$24)/1000 -> 0.012035476 | F16: 0.0082509873 | G16: 0.0095926839 | H16: =IF($H$24<>0,$H$91/($E$24+$H$24)/1000,0) -> 0.012035476 | I16: 0.019322727 | J16: 0.033374504 | K16: =B16 -> 0.012035476 | L16: 0.0080163112 | M16: 0 | N16: =B16 -> 0.012035476 | O16: 0.0074639164 | P16: 0 | R16: =(B16*B$24+E16*E$24+H16*H$24+K16*K$24+N16*N$24)/R$24 -> 0.012035476 | S16: 0.0080958839 | T16: =S22-T12-T14-T15 -> 0 | U16: =R16-T16 -> 0.012035476 | V16: =R16*$R$24 -> 1686.1702 | W16: =ROUND($D$86,0) -> 1686170 | X16: =ROUND($D$85,0) -> 37991 | Y16: =SUM(W16:X16) -> 1724161 | Z16: =$B$84 -> 99348 | AA16: =Y16/Z16 -> 17.354763 | AB16: hr | AC16: IPC01 | AD16: see below | AE16: see below | AF16: =$F91 -> 1084396.4 | AG16: =$H91/($E$24+$H$24)*E24 -> 421241.67 | AH16: =$H91/($E$24+$H$24)*H24 -> 180532.14 | AI16: =SUM(AF16:AH16) -> 1686170.2 | AJ16: =$E91 -> 62484.085 | AK16: =$G91/($E$24+$H$24)*E24 -> 24272.397 | AL16: =$G91/($E$24+$H$24)*H24 -> 10402.456 | AM16: =SUM(AJ16:AL16) -> 97158.937 | AN16: =AI16/AM16 -> 17.354762 | AO16: =ROUND(AJ16/$B$24,3) -> 0.693 | AP16: =ROUND(AK16/$E$24,3) -> 0.693 | AQ16: =IF($H$24<>0,ROUND(AL16/$H$24,3),0) -> 0.693 | AR16: =U16*$R$24 -> 1686.1702 | AS16: =$AR16/$AM16*AJ16 -> 1084.3964 | AT16: =$AR16/$AM16*AK16 -> 421.24167 | AU16: =$AR16/$AM16*AL16 -> 180.53214
A17: Supervision | B17: =IF($B$24<>0,$D$136,0) -> 0.0027052106 | C17: 0.0020941539 | D17: 0.0014661648 | E17: =$E$136 -> 0.0027052106 | F17: 0.002255474 | G17: 0.0015091549 | H17: =IF($H$24<>0,$E$136,0) -> 0.0027052106 | I17: 0.0019750709 | J17: 0.0051354167 | K17: =B17 -> 0.0027052106 | L17: 0.0024827481 | M17: 0 | N17: =B17 -> 0.0027052106 | O17: 0.0025772821 | P17: 0 | R17: =(B17*B$24+E17*E$24+H17*H$24+K17*K$24+N17*N$24)/R$24 -> 0.0027052106 | S17: 0.0020913266 | T17: =S22-T12-T14-T15-T16 -> 0 | U17: =R17-T17 -> 0.0027052106 | V17: =R17*$R$24 -> 379 | W17: =ROUND($C$136,0) -> 379000 | X17: 0 | Y17: =SUM(W17:X17) -> 379000 | Z17: =$B$25*1000 -> 140100000 | AA17: =Y17/Z17 -> 0.0027052106 | AB17: lb | AC17: SUP01 | AD17: 611000 | AE17: 1 | AF17: =$D$136*$B$24*1000 -> 243739.47 | AG17: =$E$136*$E$24*1000 -> 94682.37 | AH17: =$E$136*$H$24*1000 -> 40578.158 | AI17: =SUM(AF17:AH17) -> 379000 | AJ17: =ROUND(AF17/$AA17,0) -> 90100000 | AK17: =ROUND(AG17/$AA17,0) -> 35000000 | AL17: =ROUND(AH17/$AA17,0) -> 15000000 | AM17: =SUM(AJ17:AL17) -> 140100000 | AN17: =AI17/AM17 -> 0.0027052106 | AO17: =ROUND(AJ17/$B$24,3) -> 1000 | AP17: =ROUND(AK17/$E$24,3) -> 1000 | AQ17: =IF($H$24<>0,ROUND(AL17/$H$24,3),0) -> 1000 | AR17: =U17*$R$24 -> 379 | AS17: =$AR17/$AM17*AJ17 -> 243.73947 | AT17: =$AR17/$AM17*AK17 -> 94.68237 | AU17: =$AR17/$AM17*AL17 -> 40.578158
A18: Insurance & Taxes | B18: =IF($B$24<>0,$D$137,0) -> 0.0028551035 | C18: 0.0022245575 | D18: 0.0011301067 | E18: =$E$137 -> 0.0028551035 | F18: 0.0025373784 | G18: 0.0011632431 | H18: =IF($H$24<>0,$E$137,0) -> 0.0028551035 | I18: 0.0017392298 | J18: 0.0039583333 | K18: =B18 -> 0.0028551035 | L18: 0.0021055704 | M18: 0 | N18: =B18 -> 0.0028551035 | O18: 0.0042373717 | P18: 0 | R18: =(B18*B$24+E18*E$24+H18*H$24+K18*K$24+N18*N$24)/R$24 -> 0.0028551035 | S18: 0.0031981538 | T18: =S22-T12-T14-T15-T16-T17 -> 0 | U18: =R18-T18 -> 0.0028551035 | V18: =R18*$R$24 -> 400 | W18: =ROUND($C$137,0) -> 400000 | X18: 0 | Y18: =SUM(W18:X18) -> 400000 | Z18: =$B$25*1000 -> 140100000 | AA18: =Y18/Z18 -> 0.0028551035 | AB18: lb | AC18: INS01 | AD18: see below | AE18: see below | AF18: =$D$137*$B$24*1000 -> 257244.83 | AG18: =$E$137*$E$24*1000 -> 99928.622 | AH18: =$E$137*$H$24*1000 -> 42826.552 | AI18: =SUM(AF18:AH18) -> 400000 | AJ18: =ROUND(AF18/$AA18,0) -> 90100000 | AK18: =ROUND(AG18/$AA18,0) -> 35000000 | AL18: =ROUND(AH18/$AA18,0) -> 15000000 | AM18: =SUM(AJ18:AL18) -> 140100000 | AN18: =AI18/AM18 -> 0.0028551035 | AO18: =ROUND(AJ18/$B$24,3) -> 1000 | AP18: =ROUND(AK18/$E$24,3) -> 1000 | AQ18: =IF($H$24<>0,ROUND(AL18/$H$24,3),0) -> 1000 | AR18: =U18*$R$24 -> 400 | AS18: =$AR18/$AM18*AJ18 -> 257.24483 | AT18: =$AR18/$AM18*AK18 -> 99.928622 | AU18: =$AR18/$AM18*AL18 -> 42.826552
A19: Depreciation | B19: =IF($B$24<>0,$D$138,0) -> 0.009041029 | C19: 0.023696807 | D19: 0.012767474 | E19: =$E$138 -> 0.074428066 | F19: 0.079572807 | G19: 0.049354497 | H19: =IF($H$24<>0,$E$138,0) -> 0.074428066 | I19: 0.026228572 | J19: 0.066666667 | K19: =B19 -> 0.009041029 | L19: 0.021028799 | M19: 0 | N19: =B19 -> 0.009041029 | O19: 0.030451932 | P19: 0 | R19: =(B19*B$24+E19*E$24+H19*H$24+K19*K$24+N19*N$24)/R$24 -> 0.032376874 | S19: 0.0087052134 | T19: =S22-T12-T14-T15-T16-T17-T18 -> 0 | U19: =R19-T19 -> 0.032376874 | V19: =R19*$R$24 -> 4536 | W19: =ROUND($C$138,0) -> 4536000 | X19: 0 | Y19: =SUM(W19:X19) -> 4536000 | Z19: =$B$25*1000 -> 140100000 | AA19: =Y19/Z19 -> 0.032376874 | AB19: lb | AC19: DEP01 | AD19: see below | AE19: see below | AF19: =$D$138*$B$24*1000 -> 814596.72 | AG19: =$E$138*$E$24*1000 -> 2604982.3 | AH19: =$E$138*$H$24*1000 -> 1116421 | AI19: =SUM(AF19:AH19) -> 4536000 | AJ19: =AF19/$AA19 -> 25159832 | AK19: =AG19/$AA19 -> 80458117 | AL19: =AH19/$AA19 -> 34482050 | AM19: =SUM(AJ19:AL19) -> 140100000 | AN19: =AI19/AM19 -> 0.032376874 | AO19: =ROUND(AJ19/$B$24,3) -> 279.243 | AP19: =ROUND(AK19/$E$24,3) -> 2298.803 | AQ19: =IF($H$24<>0,ROUND(AL19/$H$24,3),0) -> 2298.803 | AR19: =U19*$R$24 -> 4536 | AS19: =$AR19/$AM19*AJ19 -> 814.59672 | AT19: =$AR19/$AM19*AK19 -> 2604.9823 | AU19: =$AR19/$AM19*AL19 -> 1116.421
A20: Total Fixed Costs | B20: =SUM(B14:B19) -> 0.056915158 | C20: =SUM(C14:C19) -> 0.053791393 | D20: =SUM(D14:D19) -> 0.045538542 | E20: =SUM(E14:E19) -> 0.12230219 | F20: =SUM(F14:F19) -> 0.11435238 | G20: =SUM(G14:G19) -> 0.083110161 | H20: =SUM(H14:H19) -> 0.12230219 | I20: =SUM(I14:I19) -> 0.099779397 | ... P20: =SUM(P14:P19) -> 0 | R20: =SUM(R14:R19) -> 0.080251002 | S20: =SUM(S14:S19) -> 0.038670305 | T20: =SUM(T14:T19) -> 0.038670305 | U20: =SUM(U14:U19) -> 0.041580697 | V20: =SUM(V14:V19) -> 11243.165 | W20: =SUM(W14:W19) -> 11243166 | X20: =SUM(X14:X19) -> 106399 | Y20: =SUM(Y14:Y19) -> 11349565 | AF20: =SUM(AF14:AF19) -> 5128055.7 | AG20: =SUM(AG14:AG19) -> 4280576.8 | AH20: =SUM(AH14:AH19) -> 1834532.9 | AI20: =SUM(AI14:AI19) -> 11243165 | AR20: =SUM(AR14:AR19) -> 5825.4557 | AS20: =SUM(AS14:AS19) -> 1643.8612 | AT20: =SUM(AT14:AT19) -> 2927.1161 | AU20: =SUM(AU14:AU19) -> 1254.4783
V21: =V12+V20 -> 22031.544 | W21: =W12+W20 -> 22031545 | X21: =X12+X20 -> 106399 | Y21: =Y12+Y20 -> 22137944 | AF21: =AF12+AF20 -> 10800436 | AG21: =AG12+AG20 -> 7861776.6 | AH21: =AH12+AH20 -> 3369333.4 | AI21: =AI12+AI20 -> 22031547 | AR21: =AR12+AR20 -> 8930.6352 | AS21: =AS12+AS20 -> 3276.5216 | AT21: =AT12+AT20 -> 3957.8795 | AU21: =AU12+AU20 -> 1696.2341
A22: TOTAL COST PER POUND | B22: =B12+B20 -> 0.1661563 | C22: =C12+C20 -> 0.16329172 | D22: =D12+D20 -> 0.11902659 | E22: =E12+E20 -> 0.37065519 | F22: =F12+F20 -> 0.36206859 | G22: =G12+G20 -> 0.25987429 | H22: =H12+H20 -> 0.80616277 | I22: =I12+I20 -> 0.77540423 | ... P22: =P12+P20 -> 0 | R22: =R12+R20 -> 0.28576771 | S22: =S12+S20 -> 0.22202299 | T22: =T12+T20 -> 0.22202299 | U22: =U12+U20 -> 0.063744719 | V22: =V6+V21 -> 40036.056 | AD22: Excl. Raw Matl | AF22: =ROUND(AF21/AF24,5) -> 0.11987 | AG22: =ROUND(AG21/AG24,5) -> 0.22462 | AH22: =IF(AH24<>0,ROUND(AH21/AH24,5),0) -> 0.22462 | AI22: =ROUND(AI21/AI24,5) -> 0.15726
AD23: Incl. Raw Matl | AF23: =ROUND(AF22+B6,5) -> 0.16615 | AG23: =ROUND(AG22+E6,5) -> 0.37065 | AH23: =IF(AH24<>0,ROUND(AH22+H6,5),0) -> 0.80616 | AI23: =ROUND(AI22+(B6*B24+E6*E24+H6*H24)/B25,5) -> 0.28577
A24: TOTAL PRODUCTION (000 lbs) | B24: =$B$30+$B$31 -> 90100 | C24: 121112.43 | D24: 190000 | E24: =$B$32 -> 35000 | F24: 8379.436 | G24: 40000 | H24: =$B$33 -> 15000 | I24: 15451 | J24: 6000 | K24: 0 | L24: 630.366 | M24: 0 | N24: 0 | O24: 1071.4 | P24: 0 | R24: =B25 -> 140100 | AD24: Bulk Prodn lbs | AF24: =ROUND(B24*1000,0) -> 90100000 | AG24: =ROUND(E24*1000,0) -> 35000000 | AH24: =ROUND(H24*1000,0) -> 15000000 | AI24: =SUM(AF24:AH24) -> 140100000
A25: TOTAL PLANT PRODUCTION (000 lbs) | B25: =B24+E24+H24+K24+N24 -> 140100 | C25: =C24+F24+I24+L24+O24 -> 146644.64 | D25: =D24+G24+J24+M24+P24 -> 236000
A27: Variable Costs - Material | B27: Purchase Price/lb * Yield Factor * Scrap Factor * Mix = Std. Cost Contribution | S27: Total | T27: Variable | U27: Fixed
R28: 18 Annual: | S28: ($ in 000s)
A29: Production Plan: | B29: Pounds (000) | C29: Product Split | R29: Abs by Prodn | S29: =SUM(T29:U29) -> 31105.421 | T29: =T12*$R$24 -> 25687.711 | U29: =T20*$R$24 -> 5417.7097
A30: CARBO EconoProp | B30: =36000+40000 -> 76000 | C30: =+B30/$B$34 -> 0.54246966 | R30: Under-abs Exp | S30: =SUM(T30:U30) -> 8930.6352 | T30: =U12*R24 -> 3105.1794 | U30: =U20*R24 -> 5825.4557
A31: CARBO Lite | B31: =17500+4600-8000 -> 14100 | C31: =+B31/$B$34 -> 0.1006424 | R31: Gas Net Settled | S31: =SUM(T31:U31) -> 0 | T31: =IF(C97<>0,0,(((((D96/1.06564)-0.33)*0.974)-D97)*(240000-C96))/1000) -> 0 | U31: 0
A32: Kryptosphere LD | B32: =35000 -> 35000 | C32: =+B32/$B$34 -> 0.24982156 | R32: Total Cost | S32: =SUM(S29:S31) -> 40036.056 | T32: =SUM(T29:T31) -> 28792.89 | U32: =SUM(U29:U31) -> 11243.165
A33: Kryptosphere HD | B33: =15000 -> 15000 | C33: =+B33/$B$34 -> 0.10706638 | R33: Less: Non-cash | S33: =SUM(T33:U33) -> -4536 | T33: 0 | U33: =-R19*R24 -> -4536
A34: Total | B34: =SUM(B30:B33) -> 140100 | C34: =SUM(C30:C33) -> 1 | R34: Cash | S34: =SUM(S32:S33) -> 35500.056 | T34: =SUM(T32:T33) -> 28792.89 | U34: =SUM(U32:U33) -> 6707.1654
C36: CEP/CL/HP | E36: KSLD | G36: KSHD | I36: NRT/FUSION | K36: CARBOGRIND | R36: 18 Monthly:
A37: Raw Material: | B37: Price ($/NT) | C37: Ratio/Mix | E37: Ratio/Mix | G37: Ratio/Mix | I37: Ratio/Mix | K37: Ratio/Mix | R37: Abs by Prodn | S37: =SUM(T37:U37) -> 2592.1184 | T37: =T29/12 -> 2140.6426 | U37: =U29/12 -> 451.47581
A38: Arcilla | B38: =13.3*2 -> 26.6 | C38: 0.5 | E38: 0.5 | G38: 0 | I38: 0.5 | K38: 0.5 | R38: Under-abs Exp | S38: =SUM(T38:U38) -> 744.2196 | T38: =T30/12 -> 258.76495 | U38: =U30/12 -> 485.45464
A39: CARBO | B39: =12.41*2 -> 24.82 | C39: 0.5 | E39: 0.5 | G39: 0 | I39: 0.5 | K39: 0.5 | R39: Gas Net Settled | S39: =SUM(T39:U39) -> 0 | T39: =T31/12 -> 0 | U39: =U31/12 -> 0
A40: Weighted Average (LW) | B40: =+B38*C38+B39*C39 -> 25.71 | C40: =SUM(C38:C39) -> 1 | E40: =SUM(E38:E39) -> 1 | G40: =SUM(G38:G39) -> 0 | I40: =SUM(I38:I39) -> 1 | K40: =SUM(K38:K39) -> 1 | R40: Total Cost | S40: =SUM(S37:S39) -> 3336.338 | T40: =SUM(T37:T39) -> 2399.4075 | U40: =SUM(U37:U39) -> 936.93045
R41: Less: Non-cash | S41: =SUM(T41:U41) -> -378 | T41: =T33/12 -> 0 | U41: =U33/12 -> -378
A42: Materials: | B42: Price ($/lb) | C42: Usage Factor | D42: Std $ Contrib | E42: Usage Factor | F42: Std $ Contrib | G42: Usage Factor | H42: Std $ Contrib | I42: Usage Factor | J42: Std $ Contrib | K42: Usage Factor | L42: Std $ Contrib | R42: Cash | S42: =SUM(S40:S41) -> 2958.338 | T42: =SUM(T40:T41) -> 2399.4075 | U42: =SUM(U40:U41) -> 558.93045 | AR42: lbs required | AS42: 10/31/16 Inv | AT42: % of requ | AU42: cost per lb
A43: Clay/Kaolin (30015) | B43: =$B$40/2000 -> 0.012855 | C43: 2.1972328 | D43: =B43*C43 -> 0.028245428 | E43: 2.4102522 | F43: =B43*E43 -> 0.030983792 | G43: 0 | H43: =$B43*G43 -> 0 | I43: 2.6302429 | J43: =$B43*I43 -> 0.033811772 | K43: 1.4950065 | L43: =$B43*K43 -> 0.019218309 | AA43: =B43*1000 -> 12.855 | AB43: lb | AC43: 30015/U102 | AO43: =IF(B43<>0,D43/B43*1000,0) -> 2197.2328 | AP43: =IF(B43<>0,F43/B43*1000,0) -> 2410.2522 | AQ43: =IF(B43<>0,H43/B43*1000,0) -> 0 | AR43: =AO43*$B$24+AP43*$E$24+AQ43*$H$24 -> 2.823295e+08 | AS43: 202343432 | AT43: =AS43/AR43 -> 0.71669248 | AU43: =343597.02/24291676.299 -> 0.01414464
A44: Rusal Slurry (30301) | B44: 0.13442 | C44: 0 | D44: =B44*C44 -> 0 | E44: 0 | F44: =B44*E44 -> 0 | G44: 3.4975597 | H44: =$B44*G44 -> 0.47014198 | I44: 0 | J44: =$B44*I44 -> 0 | K44: 0 | L44: =$B44*K44 -> 0 | AA44: =B44*1000 -> 134.42 | AB44: lb | AC44: 30282/U102 | AO44: =IF(B44<>0,D44/B44*1000,0) -> 0 | AP44: =IF(B44<>0,F44/B44*1000,0) -> 0 | AQ44: =IF(B44<>0,H44/B44*1000,0) -> 3497.5597 | AR44: =AO44*$B$24+AP44*$E$24+AQ44*$H$24 -> 52463396 | AS44: 0 | AT44: =AS44/AR44 -> 0 | AU44: 0.06274
A45: CarboGrind 280 - Green (70160) | B45: 0.30571 | C45: 0 | D45: =B45*C45 -> 0 | E45: 0 | F45: =B45*E45 -> 0 | G45: 0 | H45: =$B45*G45 -> 0 | I45: 0 | J45: =$B45*I45 -> 0 | K45: 0.50149804 | L45: =$B45*K45 -> 0.15331297
A46: PVA (30017) | B46: 1.3657 | C46: 0.0099558259 | D46: =B46*C46 -> 0.013596671 | E46: 0 | F46: =B46*E46 -> 0 | G46: 0 | H46: =$B46*G46 -> 0 | I46: 0.010031902 | J46: =$B46*I46 -> 0.013700569 | K46: 0.0066058428 | L46: =$B46*K46 -> 0.0090215995 | AA46: =B46*1000 -> 1365.7 | AB46: lb | AC46: 30017/U102 | AO46: =IF(B46<>0,D46/B46*1000,0) -> 9.9558259 | AP46: =IF(B46<>0,F46/B46*1000,0) -> 0 | AQ46: =IF(B46<>0,H46/B46*1000,0) -> 0 | AR46: =AO46*$B$24+AP46*$E$24+AQ46*$H$24 -> 897019.91 | AS46: 101933 | AT46: =AS46/AR46 -> 0.11363516 | AU46: =143105.19/AS46 -> 1.4039142
A47: Dispersant (30011) | B47: 0.46 | C47: 0.0083656485 | D47: =B47*C47 -> 0.0038481983 | E47: 0.010556001 | F47: =B47*E47 -> 0.0048557605 | G47: 0.0052729258 | H47: =$B47*G47 -> 0.0024255459 | I47: 0.0058781279 | J47: =$B47*I47 -> 0.0027039389 | K47: 0.0062581669 | L47: =$B47*K47 -> 0.0028787568 | AA47: =B47*1000 -> 460 | AB47: lb | AC47: 30011/U102 | AO47: =IF(B47<>0,D47/B47*1000,0) -> 8.3656485 | AP47: =IF(B47<>0,F47/B47*1000,0) -> 10.556001 | AQ47: =IF(B47<>0,H47/B47*1000,0) -> 5.2729258 | AR47: =AO47*$B$24+AP47*$E$24+AQ47*$H$24 -> 1202298.9 | AS47: 84108 | AT47: =AS47/AR47 -> 0.069955984 | AU47: =38613.79/AS47 -> 0.45909771
A48: Ammonia (30000) | B48: 0.06274 | C48: 0.0094731409 | D48: =B48*C48 -> 0.00059434486 | E48: 0.013838363 | F48: =B48*E48 -> 0.00086821889 | G48: 0.00045626976 | H48: =$B48*G48 -> 2.8626364e-05 | I48: 0.014843042 | J48: =$B48*I48 -> 0.00093125245 | K48: 0.0062581669 | L48: =$B48*K48 -> 0.00039263739 | AA48: =B48*1000 -> 62.74 | AB48: lb | AC48: 30000/U102 | AO48: =IF(B48<>0,D48/B48*1000,0) -> 9.4731409 | AP48: =IF(B48<>0,F48/B48*1000,0) -> 13.838363 | AQ48: =IF(B48<>0,H48/B48*1000,0) -> 0.45626976 | AR48: =AO48*$B$24+AP48*$E$24+AQ48*$H$24 -> 1344716.7 | AS48: 47388 | AT48: =AS48/AR48 -> 0.035240135 | AU48: =2705.86/AS48 -> 0.05710011
A49: CaCL (30114) | B49: 0.08677 | C49: 0 | D49: =B49*C49 -> 0 | E49: 0.35728908 | F49: =B49*E49 -> 0.031001974 | G49: 0.27359571 | H49: =$B49*G49 -> 0.023739899 | I49: 0 | J49: =$B49*I49 -> 0 | K49: 0 | L49: =$B49*K49 -> 0 | AA49: =B49*1000 -> 86.77 | AB49: lb | AC49: 30114/U102 | AO49: =IF(B49<>0,D49/B49*1000,0) -> 0 | AP49: =IF(B49<>0,F49/B49*1000,0) -> 357.28908 | AQ49: =IF(B49<>0,H49/B49*1000,0) -> 273.59571 | AR49: =AO49*$B$24+AP49*$E$24+AQ49*$H$24 -> 16609054 | AS49: 560786 | AT49: =AS49/AR49 -> 0.033763875 | AU49: =49077.4/AS49 -> 0.08751538
A50: Algenate (30170) | B50: 6.13644 | C50: 0 | D50: =B50*C50 -> 0 | E50: 0.012763636 | F50: =B50*E50 -> 0.078323284 | G50: 0.013885015 | H50: =$B50*G50 -> 0.085204559 | I50: 0 | J50: =$B50*I50 -> 0 | K50: 0 | L50: =$B50*K50 -> 0 | AA50: =B50*1000 -> 6136.44 | AB50: lb | AC50: 30170/U102 | AO50: =IF(B50<>0,D50/B50*1000,0) -> 0 | AP50: =IF(B50<>0,F50/B50*1000,0) -> 12.763636 | AQ50: =IF(B50<>0,H50/B50*1000,0) -> 13.885015 | AR50: =AO50*$B$24+AP50*$E$24+AQ50*$H$24 -> 655002.47 | AS50: 208883 | AT50: =AS50/AR50 -> 0.31890414 | AU50: =1269211.15/AS50 -> 6.0761821
A51: Taggant (30021) | B51: 11.52 | C51: 0 | D51: =B51*C51 -> 0 | E51: 0 | F51: =B51*E51 -> 0 | G51: 0 | H51: =$B51*G51 -> 0 | I51: 0.019566171 | J51: =$B51*I51 -> 0.22540229 | K51: 0 | L51: =$B51*K51 -> 0 | AA51: =B51*1000 -> 11520 | AB51: lb | AC51: 30021/U102 | AO51: =IF(B51<>0,D51/B51*1000,0) -> 0 | AP51: =IF(B51<>0,F51/B51*1000,0) -> 0 | AQ51: =IF(B51<>0,H51/B51*1000,0) -> 0 | AR51: =AO51*$B$24+AP51*$E$24+AQ51*$H$24 -> 0
A53: Standard Cost Contribution | D53: $/lb | F53: $/lb | H53: $/lb | J53: $/lb | L53: $/lb
A54: Clay/Bauxite | D54: =D43+D44+D45 -> 0.028245428 | F54: =F43+F44+F45 -> 0.030983792 | H54: =H43+H44+H45 -> 0.47014198 | J54: =J43+J44+J45 -> 0.033811772 | L54: =L43+L44+L45 -> 0.17253127
A55: Chemical | D55: =SUM(D46:D51) -> 0.018039215 | F55: =SUM(F46:F51) -> 0.11504924 | H55: =SUM(H46:H51) -> 0.11139863 | J55: =SUM(J46:J51) -> 0.24273805 | L55: =SUM(L46:L51) -> 0.012292994
A56: Total Material Cost Per Pound | D56: =SUM(D54:D55) -> 0.046284643 | F56: =SUM(F54:F55) -> 0.14603303 | H56: =SUM(H54:H55) -> 0.58154061 | J56: =SUM(J54:J55) -> 0.27654982 | L56: =SUM(L54:L55) -> 0.18482427
A60: Variable Cost - Labor & Benefits - 12 hour shift | B60: Production Labor | F60: R&M Labor | AF60: Alternate DLAB01 Allocation per Product Line
B61: NIRO | C61: KS | D61: Total | F61: NIRO | G61: KS | H61: Total | Y61: =$Y$14*$AE61 -> 2794136.4 | AC61: DLAB01 (s/t) | AD61: 611030 | AE61: =100%-D64 -> 0.9 | AI61: NIRO | AJ61: =($B$68+$B$70+$B$72+$B$75-$B$77)/$B$25*$B$24 -> 31583.836 | AK61: =($B$68+$B$70+$B$72+$B$75-$B$77)/$B$25*($E$24+$H$24) -> 17527.101 | AM61: =SUM(AJ61:AK61) -> 49110.938
A62: Full Time Employees | B62: =33-8 -> 25 | C62: 20 | D62: =SUM(B62:C62) -> 45 | F62: =11+1 -> 12 | G62: 4 | H62: =SUM(F62:G62) -> 16 | Y62: =$Y$14*$AE62 -> 310459.6 | AC62: DLAB01 (o/t) | AD62: 610210 | AE62: =D64 -> 0.1 | AI62: KS | AJ62: 0 | AK62: =($B$69+$B$71+$B$73)/$E$24*($E$24+$H$24) -> 68640 | AM62: =SUM(AJ62:AK62) -> 68640
A63: Labor Rate | B63: =28.6*(1+$F$150) -> 29.172 | C63: =28.6*(1+$F$150) -> 29.172 | D63: =($B$62*B63+$C$62*C63)/$D$62 -> 29.172 | F63: =31.47*(1+$F$150) -> 32.0994 | G63: =31.47*(1+$F$150) -> 32.0994 | H63: =($F$62*F63+$G$62*G63)/$H$62 -> 32.0994 | Y63: =SUM(Y61:Y62) -> 3104596 | AB63: hr | AC63: DLAB01 | AD63: Total | AF63: =$AN$63*AO63*$B$24 -> 986985.41 | AG63: =$AN$63*AP63*($E$24+$H$24) -> 2692696 | AI63: =SUM(AF63:AG63) -> 3679681.5 | AJ63: =SUM(AJ61:AJ62) -> 31583.836 | AK63: =SUM(AK61:AK62) -> 86167.101 | AM63: =SUM(AM61:AM62) -> 117750.94 | AN63: =$AN$14 -> 31.2497 | AO63: =AJ63/$B$24 -> 0.35054202 | AP63: =AK63/($E$24+$H$24) -> 1.723342
A64: Overtime | B64: 0.1 | C64: 0.1 | D64: =($B$62*B64+$C$62*C64)/$D$62 -> 0.1 | F64: 0.05 | G64: 0.05 | H64: =($F$62*F64+$G$62*G64)/$H$62 -> 0.05 | AF64: Alternate MLAB01 Allocation per Product Line
Y65: =$Y$15*$AE65 -> 1145517.6 | AC65: MLAB01 (s/t) | AD65: 611040 | AE65: =100%-H64 -> 0.95 | AI65: NIRO | AJ65: =($F$68+$F$70+$F$72+$F$75-$F$77)/$B$25*$B$24 -> 17697.415 | AK65: =($F$68+$F$70+$F$72+$F$75-$F$77)/$B$25*($E$24+$H$24) -> 9820.985 | AM65: =SUM(AJ65:AK65) -> 27518.4
B66: Production Labor | F66: R & M Labor | Y66: =$Y$15*$AE66 -> 60290.4 | AC66: MLAB01 (o/t) | AD66: 610215 | AE66: =H64 -> 0.05 | AI66: KS | AJ66: 0 | AK66: =($F$69+$F$71+$F$73)/$E$24*($E$24+$H$24) -> 13104 | AM66: =SUM(AJ66:AK66) -> 13104
B67: Equiv. Hrs. | C67: Rates | D67: Gross Pay | F67: Equiv. Hrs. | G67: Rates | H67: Gross Pay | Y67: =SUM(Y65:Y66) -> 1205808 | AB67: hr | AC67: MLAB01 | AD67: Total | AF67: =$AN$67*AO67*$B$24 -> 581602.03 | AG67: =$AN$67*AP67*($E$24+$H$24) -> 753399.17 | AI67: =SUM(AF67:AG67) -> 1335001.2 | AJ67: =SUM(AJ65:AJ66) -> 17697.415 | AK67: =SUM(AK65:AK66) -> 22924.985 | AM67: =SUM(AM65:AM66) -> 40622.4 | AN67: =$AN$15 -> 32.863671 | AO67: =AJ67/$B$24 -> 0.1964197 | AP67: =AK67/($E$24+$H$24) -> 0.4584997
A68: Straight Time Pay (NIRO) | B68: =$D$150*$D$151*B$62 -> 54600 | C68: =B$63 -> 29.172 | D68: =B68*C68 -> 1592791.2 | F68: =$D$150*$D$151*F$62 -> 26208 | G68: =F$63 -> 32.0994 | H68: =F68*G68 -> 841261.08 | AF68: Nov16 Ytd
A69: Straight Time Pay (KS) | B69: =$D$150*$D$151*C$62 -> 43680 | C69: =C$63 -> 29.172 | D69: =B69*C69 -> 1274233 | F69: =$D$150*$D$151*G$62 -> 8736 | G69: =G$63 -> 32.0994 | H69: =F69*G69 -> 280420.36 | Y69: =$Y$16*$AE69 -> 152927 | AC69: IPC01 (vac) | AD69: 610220 | AE69: =AF69/$AF$75 -> 0.088696471 | AF69: 113854.1
A70: Overtime Pay (NIRO) | B70: =B68*B64 -> 5460 | C70: =B63*D152 -> 43.758 | D70: =B70*C70 -> 238918.68 | F70: =F68*F64 -> 1310.4 | G70: =F63*D152 -> 48.1491 | H70: =F70*G70 -> 63094.581 | Y70: =$Y$16*$AE70 -> 143396.26 | AC70: IPC01 (hol) | AD70: 610510 | AE70: =AF70/$AF$75 -> 0.083168718 | AF70: 106758.47
A71: Overtime Pay (KS) | B71: =B69*C64 -> 4368 | C71: =C63*D152 -> 43.758 | D71: =B71*C71 -> 191134.94 | F71: =F69*G64 -> 436.8 | G71: =G63*D152 -> 48.1491 | H71: =F71*G71 -> 21031.527 | Y71: =$Y$16*$AE71 -> 142313.83 | AC71: IPC01 (401k) | AD71: 610600 | AE71: =AF71/$AF$75 -> 0.082540916 | AF71: 105952.6
A72: Additional OIC Pay (NIRO) | B72: 0 | D72: =96*(35.78*1.02)*12*1.5 -> 63064.397 | F72: 0 | H72: 0 | Y72: =$Y$16*$AE72 -> 860260.64 | AC72: IPC01 (ins) | AD72: 610610 | AE72: =AF72/$AF$75 -> 0.4989445 | AF72: 640463.77
A73: Additional OIC Pay (KS) | B73: 0 | D73: 0 | F73: 0 | H73: 0 | Y73: =$Y$16*$AE73 -> 393466.13 | AC73: IPC01 (tax) | AD73: 612000 | AE73: =AF73/$AF$75 -> 0.2282073 | AF73: 292935.41
A74: Total Gross Pay | B74: =SUM(B68:B73) -> 108108 | C74: =D74/B74 -> 31.081346 | D74: =SUM(D68:D73) -> 3360142.2 | F74: =SUM(F68:F73) -> 36691.2 | G74: =H74/F74 -> 32.863671 | H74: =SUM(H68:H73) -> 1205807.5 | Y74: =$Y$16*$AE74 -> 31797.139 | AC74: IPC01 (w/c) | AD74: 612100 | AE74: =AF74/$AF$75 -> 0.018442094 | AF74: 23672.96
A75: Less: Gross Pay (NIRO) Allocated to Shipping | B75: =-H84 -> -8760 | C75: =D75/B75 -> 29.172032 | D75: =ROUND(B75*B63,0) -> -255547 | F75: 0 | H75: 0 | Y75: =SUM(Y69:Y74) -> 1724161 | AB75: hr | AC75: IPC01 | AD75: Total | AE75: =SUM(AE69:AE74) -> 1 | AF75: =SUM(AF69:AF74) -> 1283637.3
A76: Gross Pay Alloc to Production (Bulk & Bag) | B76: =SUM(B74:B75) -> 99348 | C76: =D76/B76 -> 31.2497 | D76: =SUM(D74:D75) -> 3104595.2 | F76: =SUM(F74:F75) -> 36691.2 | G76: =H76/F76 -> 32.863671 | H76: =SUM(H74:H75) -> 1205807.5
A77: Gross Pay Alloc to Bag Production | B77: =H85 -> 2189.0625 | D77: =B77*C76 -> 68407.546 | F77: 0 | H77: =F77*G76 -> 0
A78: Gross Pay Alloc to Bulk Production | B78: =B76-B77 -> 97158.938 | D78: =B78*C76 -> 3036187.6 | F78: =F76-F77 -> 36691.2 | H78: =F78*G76 -> 1205807.5
A80: =CONCATENATE("Indirect Payroll Cost (IPC) at ",$D$153*100,"% (NIRO)") -> Indirect Payroll Cost (IPC) at 40% (NIRO) | B80: =B68+B70+B72 -> 60060 | C80: =D80/B80 -> 18.642224 | D80: =((D68+D70+D72)*$D$153)+((H68+H70+H72)*$D$153) -> 1119652 | E80: Shipping & Bagging Labor per D. Kessler Formula: | H80: =B63*(1+D153)*H83 -> 447168.47 | AF80: Alternate IPC01 Allocation per Product Line
A81: =CONCATENATE("Indirect Payroll Cost (IPC) at ",$D$153*100,"% (KS)") -> Indirect Payroll Cost (IPC) at 40% (KS) | B81: =B69+B71+B73 -> 48048 | C81: =D81/B81 -> 14.708789 | D81: =((D69+D71+D73)*$D$153)+((H69+H71+H73)*$D$153) -> 706727.92 | E81: Bagging % & lbs | G81: 0.2 | H81: =B25*G81*1000 -> 28020000 | AI81: NIRO | AJ81: =($B$68+$B$70+$B$72+$B$75-$B$77)/$B$25*$B$24 -> 31583.836 | AK81: =($B$68+$B$70+$B$72+$B$75-$B$77)/$B$25*($E$24+$H$24) -> 17527.101 | AM81: =SUM(AJ81:AK81) -> 49110.938
A82: =CONCATENATE("Total IPC at ",$D$153*100,"% (KS)") -> Total IPC at 40% (KS) | B82: =SUM(B80:B81) -> 108108 | C82: =D82/B82 -> 16.894031 | D82: =SUM(D80:D81) -> 1826379.9 | E82: ($ at S/T rate) | F82: Gross Pay | G82: Benefits | H82: Hours | AI82: KS | AJ82: 0 | AK82: =($B$69+$B$71+$B$73)/($E$24+$H$24)*($E$24+$H$24) -> 48048 | AM82: =SUM(AJ82:AK82) -> 48048
A83: Less: IPC Allocated to Shipping (NIRO) | B83: =B75 -> -8760 | C83: =D83/B83 -> 11.668836 | D83: =ROUND(B83*$B$63*D153,0) -> -102219 | E83: Ttl Ship & Bag | F83: =SUM(F84:F85) -> 323954.27 | G83: =SUM(G84:G85) -> 140209.35 | H83: =SUM(H84:H85) -> 10949.062 | AF83: =$AN$83*AO83*$B$24 -> 548129.96 | AG83: =$AN$83*AP83*($E$24+$H$24) -> 1138040.3 | AI83: =SUM(AF83:AG83) -> 1686170.2 | AJ83: =SUM(AJ81:AJ82) -> 31583.836 | AK83: =SUM(AK81:AK82) -> 65575.101 | AM83: =SUM(AM81:AM82) -> 97158.938 | AN83: =$AN$16 -> 17.354762 | AO83: =AJ83/$B$24 -> 0.35054202 | AP83: =AK83/($E$24+$H$24) -> 1.311502
A84: IPC Allocated to Production (Bulk & Bag) | B84: =SUM(B82:B83) -> 99348 | C84: =D84/B84 -> 17.354762 | D84: =SUM(D82:D83) -> 1724160.9 | E84: Shipping | F84: =$H84*$B$63 -> 255546.72 | G84: =$H84*$B$63*$D$153 -> 102218.69 | H84: =1*365*24 -> 8760
A85: IPC Allocated to Bag Production | B85: =H85 -> 2189.0625 | D85: =B85*C84 -> 37990.659 | E85: Bagging | F85: =$H85*$C$76 -> 68407.546 | G85: =$H85*$C$84 -> 37990.659 | H85: =H81/12800 -> 2189.0625
A86: IPC Allocated to Bulk Production | B86: =B84-B85 -> 97158.938 | D86: =B86*C84 -> 1686170.2
E87: NIRO (CEP/CL/NRT/FUSION/CG) | G87: KRYPTOSPHERE (LD & HD)
E88: Hours | F88: Cost | G88: Hours | H88: Cost
A89: Production Labor Allocation by Product | E89: =IF(AND($B$132<>0,$C$132<>0),$B$78/$D$132*$B$132,IF(AND($B$132<>0,$C$132=0),$B$78,0)) -> 62484.085 | F89: =E89*$C$76 -> 1952608.9 | G89: =IF(AND($B$132<>0,$C$132<>0),$B$78/$D$132*$C$132,IF(AND($B$132=0,$C$132<>0),$B$78,0)) -> 34674.853 | H89: =G89*$C$76 -> 1083578.7
A90: Maintenance Labor Allocation by Product | E90: =IF(AND($B$132<>0,$C$132<>0),$F$78/$D$132*$B$132,IF(AND($B$132<>0,$C$132=0),$F$78,0)) -> 23596.553 | F90: =E90*$G$76 -> 775469.38 | G90: =IF(AND($B$132<>0,$C$132<>0),$F$78/$D$132*$C$132,IF(AND($B$132=0,$C$132<>0),$F$78,0)) -> 13094.647 | H90: =G90*$G$76 -> 430338.17
A91: Indirect Payroll Costs Allocation by Product | E91: =(E89+E90)/($B$78+$F$78)*$B$86 -> 62484.085 | F91: =E91*$C$84 -> 1084396.4 | G91: =(G89+G90)/($B$78+$F$78)*$B$86 -> 34674.853 | H91: =G91*$C$84 -> 601773.82
A94: Variable Costs - Utilities
B95: Gas | C95: mmbtu | D95: price/mmbtu | F95: Electricity | G95: kwh | H95: price/kwh
B96: Contract | C96: =IF(($B$109*$B$24+$F$109*$E$24+$F$109*$H$24)*1000<=240000,($B$109*$B$24+$F$109*$E$24+$F$109*$H$24)*1000,240000) -> 240000 | D96: 5.23 | F96: NIRO | G96: =(B102*$B$24+F102*$E$24+F102*$H$24)*1000 -> 10768400 | H96: 0.1
B97: Spot | C97: =IF(C96>=240000,(((B106+B107+B108)*$B$24*1000)+((F106+F107+F108)*($E$24+$H$24)*1000))-240000,0) -> 327480 | D97: 3.06 | F97: KS | G97: =(B103*$B$24+F103*$E$24+F103*$H$24)*1000 -> 33450000 | H97: 0.065
C98: =SUM(C96:C97) -> 567480 | D98: =(C96*D96+C97*D97)/C98 -> 3.9777416 | G98: =SUM(G96:G97) -> 44218400 | H98: =(G96*H96+G97*H97)/G98 -> 0.073523465
B100: CEP/CL | F100: KRYPTOSPHERE LD/HD
B101: Usage (Unit/lb) | C101: Unit Price | D101: Std. Cost Contribution | F101: Usage (Unit/lb) | G101: Unit Price | H101: Std. Cost Contribution
A102: Electricity (kwh) - NIRO | B102: 0.084 | C102: =$H$98 -> 0.073523465 | D102: =B102*C102 -> 0.0061759711 | F102: =0.064 -> 0.064 | G102: =$H$98 -> 0.073523465 | H102: =F102*G102 -> 0.0047055018
A103: Electricity (kwh) - KS | B103: 0 | C103: =$H$98 -> 0.073523465 | D103: =B103*C103 -> 0 | F103: =0.669 -> 0.669 | G103: =$H$98 -> 0.073523465 | H103: =F103*G103 -> 0.049187198
A104: Total Electricity | B104: =SUM(B102:B103) -> 0.084 | C104: =D104/B104 -> 0.073523465 | D104: =SUM(D102:D103) -> 0.0061759711 | F104: =SUM(F102:F103) -> 0.733 | G104: =H104/F104 -> 0.073523465 | H104: =SUM(H102:H103) -> 0.0538927
A106: Gas (mmbtu) - Kiln | B106: 0.0024 | C106: =$D$98 -> 3.9777416 | D106: =B106*C106 -> 0.0095465798 | F106: 0.0024 | G106: =$D$98 -> 3.9777416 | H106: =F106*G106 -> 0.0095465798
A107: Gas (mmbtu) - NIRO | B107: 0.0024 | C107: =$D$98 -> 3.9777416 | D107: =B107*C107 -> 0.0095465798 | F107: 0 | G107: =$D$98 -> 3.9777416 | H107: =F107*G107 -> 0
A108: Gas (mmbtu) - Fluid Bed | B108: 0 | C108: =$D$98 -> 3.9777416 | D108: =B108*C108 -> 0 | F108: 0.0003 | G108: =$D$98 -> 3.9777416 | H108: =F108*G108 -> 0.0011933225
A109: Total Gas | B109: =SUM(B106:B108) -> 0.0048 | C109: =D109/B109 -> 3.9777416 | D109: =SUM(D106:D108) -> 0.01909316 | F109: =SUM(F106:F108) -> 0.0027 | G109: =H109/F109 -> 3.9777416 | H109: =SUM(H106:H108) -> 0.010739902
A111: Total Utilities | D111: =D104+D109 -> 0.025269131 | H111: =H104+H109 -> 0.064632602
A115: Variable Costs - R&M Supplies, Mfg. Supplies & Other
B116: Total | C116: Pre-KS Plant | D116: KS Line 1
...

Sheet Comparative
B1: EP/CL | E1: KSLD | H1: KSHD | K1: NRT/FUSION | N1: NRT+ | Q1: NRT KSLD | T1: CG280 | W1: CG300
B2: 19 Std (2) | C2: 19 Std | D2: Diff | E2: 19 Std (2) | F2: 19 Std | G2: Diff | H2: 19 Std (2) | I2: 19 Std | J2: Diff | K2: 19 Std (2) | L2: 19 Std | M2: Diff | N2: 19 Std (2) | O2: 19 Std | P2: Diff | Q2: 19 Std (2) | R2: 19 Std | S2: Diff | T2: 19 Std (2) | U2: 19 Std | V2: Diff | W2: 19 Std (2) | X2: 19 Std | Y2: Diff
A4: Materials | B4: 0.052442084 | C4: 0.052442084 | D4: =B4-C4 -> 0 | E4: 0.11900853 | F4: 0.11900853 | G4: =E4-F4 -> 0 | H4: 0.42313082 | I4: 0.42313082 | J4: =H4-I4 -> 0 | K4: 0.12711514 | L4: 0.12711514 | M4: =K4-L4 -> 0 | N4: 1.9292536 | O4: 1.9292536 | P4: =N4-O4 -> 0 | Q4: 0.21033033 | R4: 0.21033033 | S4: =Q4-R4 -> 0 | T4: 0.11317584 | U4: 0.11317584 | V4: =T4-U4 -> 0 | W4: 0.28172044 | X4: 0.28172044 | Y4: =W4-X4 -> 0
A5: Electricity | B5: 0.0098763951 | C5: 0.0098763951 | D5: =B5-C5 -> 0 | E5: 0.055687674 | F5: 0.055687674 | G5: =E5-F5 -> 0 | H5: 0.055687674 | I5: 0.055687674 | J5: =H5-I5 -> 0 | K5: 0.0098763951 | L5: 0.0098763951 | M5: =K5-L5 -> 0 | N5: 0.0098763951 | O5: 0.0098763951 | P5: =N5-O5 -> 0 | Q5: 0.055687674 | R5: 0.055687674 | S5: =Q5-R5 -> 0 | T5: 0.0098763951 | U5: 0.0098763951 | V5: =T5-U5 -> 0 | W5: 0.0098763951 | X5: 0.0098763951 | Y5: =W5-X5 -> 0
A6: Gas | B6: 0.0168 | C6: 0.0168 | D6: =B6-C6 -> 0 | E6: 0.0098 | F6: 0.0098 | G6: =E6-F6 -> 0 | H6: 0.0098 | I6: 0.0098 | J6: =H6-I6 -> 0 | K6: 0.0168 | L6: 0.0168 | M6: =K6-L6 -> 0 | N6: 0.0168 | O6: 0.0168 | P6: =N6-O6 -> 0 | Q6: 0.0098 | R6: 0.0098 | S6: =Q6-R6 -> 0 | T6: 0.0168 | U6: 0.0168 | V6: =T6-U6 -> 0 | W6: 0.0168 | X6: 0.0168 | Y6: =W6-X6 -> 0
A7: R&M Supplies and Service | B7: 0.02718869 | C7: 0.02718869 | D7: =B7-C7 -> 0 | E7: 0.02718869 | F7: 0.02718869 | G7: =E7-F7 -> 0 | H7: 0.02718869 | I7: 0.02718869 | J7: =H7-I7 -> 0 | K7: 0.02718869 | L7: 0.02718869 | M7: =K7-L7 -> 0 | N7: 0.02718869 | O7: 0.02718869 | P7: =N7-O7 -> 0 | Q7: 0.02718869 | R7: 0.02718869 | S7: =Q7-R7 -> 0 | T7: 0.02718869 | U7: 0.02718869 | V7: =T7-U7 -> 0 | W7: 0.02718869 | X7: 0.02718869 | Y7: =W7-X7 -> 0
A8: Manufacturing Supplies | B8: 0.0043501903 | C8: 0.0043501903 | D8: =B8-C8 -> 0 | E8: 0.0043501903 | F8: 0.0043501903 | G8: =E8-F8 -> 0 | H8: 0.0043501903 | I8: 0.0043501903 | J8: =H8-I8 -> 0 | K8: 0.0043501903 | L8: 0.0043501903 | M8: =K8-L8 -> 0 | N8: 0.0043501903 | O8: 0.0043501903 | P8: =N8-O8 -> 0 | Q8: 0.0043501903 | R8: 0.0043501903 | S8: =Q8-R8 -> 0 | T8: 0.0043501903 | U8: 0.0043501903 | V8: =T8-U8 -> 0 | W8: 0.0043501903 | X8: 0.0043501903 | Y8: =W8-X8 -> 0
A9: Other variable | B9: 0.010875476 | C9: 0.010875476 | D9: =B9-C9 -> 0 | E9: 0.010875476 | F9: 0.010875476 | G9: =E9-F9 -> 0 | H9: 0.010875476 | I9: 0.010875476 | J9: =H9-I9 -> 0 | K9: 0.010875476 | L9: 0.010875476 | M9: =K9-L9 -> 0 | N9: 0.010875476 | O9: 0.010875476 | P9: =N9-O9 -> 0 | Q9: 0.010875476 | R9: 0.010875476 | S9: =Q9-R9 -> 0 | T9: 0.010875476 | U9: 0.010875476 | V9: =T9-U9 -> 0 | W9: 0.010875476 | X9: 0.010875476 | Y9: =W9-X9 -> 0
A10: Total Variable Costs | B10: =SUM(B4:B9) -> 0.12153283 | C10: =SUM(C4:C9) -> 0.12153283 | D10: =SUM(D4:D9) -> 0 | E10: =SUM(E4:E9) -> 0.22691056 | F10: =SUM(F4:F9) -> 0.22691056 | G10: =SUM(G4:G9) -> 0 | H10: =SUM(H4:H9) -> 0.53103284 | I10: =SUM(I4:I9) -> 0.53103284 | ... Y10: =SUM(Y4:Y9) -> 0
A12: Production Labor | B12: 0.038989507 | C12: 0.049677855 | D12: =B12-C12 -> -0.010688348 | E12: 0.038989507 | F12: 0.049677855 | G12: =E12-F12 -> -0.010688348 | H12: 0.038989507 | I12: 0.049677855 | J12: =H12-I12 -> -0.010688348 | K12: 0.038989507 | L12: 0.049677855 | M12: =K12-L12 -> -0.010688348 | N12: 0.038989507 | O12: 0.049677855 | P12: =N12-O12 -> -0.010688348 | Q12: 0.038989507 | R12: 0.049677855 | S12: =Q12-R12 -> -0.010688348 | T12: 0.038989507 | U12: 0.049677855 | V12: =T12-U12 -> -0.010688348 | W12: 0.038989507 | X12: 0.049677855 | Y12: =W12-X12 -> -0.010688348
A13: Repairs & Maintenance Labor | B13: 0.020329845 | C13: 0.025902946 | D13: =B13-C13 -> -0.0055731008 | E13: 0.020329845 | F13: 0.025902946 | G13: =E13-F13 -> -0.0055731008 | H13: 0.020329845 | I13: 0.025902946 | J13: =H13-I13 -> -0.0055731008 | K13: 0.020329845 | L13: 0.025902946 | M13: =K13-L13 -> -0.0055731008 | N13: 0.020329845 | O13: 0.025902946 | P13: =N13-O13 -> -0.0055731008 | Q13: 0.020329845 | R13: 0.025902946 | S13: =Q13-R13 -> -0.0055731008 | T13: 0.020329845 | U13: 0.025902946 | V13: =T13-U13 -> -0.0055731008 | W13: 0.020329845 | X13: 0.025902946 | Y13: =W13-X13 -> -0.0055731008
A14: Indirect Payroll Costs (Benefits) | B14: 0.026450178 | C14: 0.03370107 | D14: =B14-C14 -> -0.0072508918 | E14: 0.026450178 | F14: 0.03370107 | G14: =E14-F14 -> -0.0072508918 | H14: 0.026450178 | I14: 0.03370107 | J14: =H14-I14 -> -0.0072508918 | K14: 0.026450178 | L14: 0.03370107 | M14: =K14-L14 -> -0.0072508918 | N14: 0.026450178 | O14: 0.03370107 | P14: =N14-O14 -> -0.0072508918 | Q14: 0.026450178 | R14: 0.03370107 | S14: =Q14-R14 -> -0.0072508918 | T14: 0.026450178 | U14: 0.03370107 | V14: =T14-U14 -> -0.0072508918 | W14: 0.026450178 | X14: 0.03370107 | Y14: =W14-X14 -> -0.0072508918
A15: Supervision | B15: 0.0068776509 | C15: 0.0087630485 | D15: =B15-C15 -> -0.0018853976 | E15: 0.0068776509 | F15: 0.0087630485 | G15: =E15-F15 -> -0.0018853976 | H15: 0.0068776509 | I15: 0.0087630485 | J15: =H15-I15 -> -0.0018853976 | K15: 0.0068776509 | L15: 0.0087630485 | M15: =K15-L15 -> -0.0018853976 | N15: 0.0068776509 | O15: 0.0087630485 | P15: =N15-O15 -> -0.0018853976 | Q15: 0.0068776509 | R15: 0.0087630485 | S15: =Q15-R15 -> -0.0018853976 | T15: 0.0068776509 | U15: 0.0087630485 | V15: =T15-U15 -> -0.0018853976 | W15: 0.0068776509 | X15: 0.0087630485 | Y15: =W15-X15 -> -0.0018853976
A16: Depreciation | B16: 0.021572981 | C16: 0.0289071 | D16: =B16-C16 -> -0.0073341183 | E16: 0.11680294 | F16: 0.12232835 | G16: =E16-F16 -> -0.0055254115 | H16: 0.11680294 | I16: 0.12232835 | J16: =H16-I16 -> -0.0055254115 | K16: 0.021572981 | L16: 0.0289071 | M16: =K16-L16 -> -0.0073341183 | N16: 0.021572981 | O16: 0.0289071 | P16: =N16-O16 -> -0.0073341183 | Q16: 0.11680294 | R16: 0.12232835 | S16: =Q16-R16 -> -0.0055254115 | T16: 0.021572981 | U16: 0.0289071 | V16: =T16-U16 -> -0.0073341183 | W16: 0.021572981 | X16: 0.0289071 | Y16: =W16-X16 -> -0.0073341183
A17: Insurance & Taxes | B17: 0.012688055 | C17: 0.016166282 | D17: =B17-C17 -> -0.0034782267 | E17: 0.012688055 | F17: 0.016166282 | G17: =E17-F17 -> -0.0034782267 | H17: 0.012688055 | I17: 0.016166282 | J17: =H17-I17 -> -0.0034782267 | K17: 0.012688055 | L17: 0.016166282 | M17: =K17-L17 -> -0.0034782267 | N17: 0.012688055 | O17: 0.016166282 | P17: =N17-O17 -> -0.0034782267 | Q17: 0.012688055 | R17: 0.016166282 | S17: =Q17-R17 -> -0.0034782267 | T17: 0.012688055 | U17: 0.016166282 | V17: =T17-U17 -> -0.0034782267 | W17: 0.012688055 | X17: 0.016166282 | Y17: =W17-X17 -> -0.0034782267
A18: Total Fixed Costs | B18: =SUM(B12:B17) -> 0.12690822 | C18: =SUM(C12:C17) -> 0.1631183 | D18: =SUM(D12:D17) -> -0.036210083 | E18: =SUM(E12:E17) -> 0.22213818 | F18: =SUM(F12:F17) -> 0.25653955 | G18: =SUM(G12:G17) -> -0.034401376 | H18: =SUM(H12:H17) -> 0.22213818 | I18: =SUM(I12:I17) -> 0.25653955 | ... Y18: =SUM(Y12:Y17) -> -0.036210083
A20: TOTAL COST PER POUND | B20: =B10+B18 -> 0.24844105 | C20: =C10+C18 -> 0.28465114 | D20: =D10+D18 -> -0.036210083 | E20: =E10+E18 -> 0.44904874 | F20: =F10+F18 -> 0.48345012 | G20: =G10+G18 -> -0.034401376 | H20: =H10+H18 -> 0.75317102 | I20: =I10+I18 -> 0.7875724 | ... Y20: =Y10+Y18 -> -0.036210083
A21: LESS: EXCESS FIXED COSTS | B21: -0.11199897 | C21: -0.14820909 | D21: =B21-C21 -> 0.036210124 | E21: -0.19604021 | F21: -0.23044158 | G21: =E21-F21 -> 0.034401376 | H21: -0.13204021 | I21: -0.16644158 | J21: =H21-I21 -> 0.034401376 | K21: -0.11199897 | L21: -0.14820905 | M21: =K21-L21 -> 0.036210083 | N21: -0.11199897 | O21: -0.14820905 | P21: =N21-O21 -> 0.036210083 | Q21: -0.19604021 | R21: -0.23044158 | S21: =Q21-R21 -> 0.034401376 | T21: -0.11199897 | U21: -0.14820905 | V21: =T21-U21 -> 0.036210083 | W21: -0.11199897 | X21: -0.14820905 | Y21: =W21-X21 -> 0.036210083
A22: ABSORBED COST PER POUND | B22: =SUM(B20:B21) -> 0.13644208 | C22: =SUM(C20:C21) -> 0.13644204 | D22: =SUM(D20:D21) -> 4.0784653e-08 | E22: =SUM(E20:E21) -> 0.25300853 | F22: =SUM(F20:F21) -> 0.25300853 | G22: =SUM(G20:G21) -> 0 | H22: =SUM(H20:H21) -> 0.62113082 | I22: =SUM(I20:I21) -> 0.62113082 | ... Y22: =SUM(Y20:Y21) -> 0

Sheet 19 Std (2)
A1: EUFAULA PLANT STANDARDS | AF1: Cost Center 10001002 Total | AO1: Cost Center 10001002 Bulk Production | BH1: CEP/CL | BI1: KSLD | BJ1: KSHD | BK1: NRT/Fusion | BL1: NRT+ | BM1: NRT KSLD | BN1: CG280 | BO1: CG300 | BP1: Total | BQ1: CEP/CL | BR1: KSLD | BS1: KSHD | BT1: NRT/Fusion | BU1: NRT+ | BV1: NRT KSLD | BW1: CG280 | BX1: CG300
AF2: Production | AG2: Bagging | AH2: Total Cost | AI2: Unit Qty | AJ2: Unit Price | AK2: UOM | AL2: Activity/Matl | AM2: Account | AN2: Acct % | AO2: EP/CL | AP2: KSLD | AQ2: KSHD | AR2: NRT/Fusion | AS2: NRT+ | AT2: NRT KSLD | AU2: CG280 | AV2: CG300 | AW2: Total Cost | AX2: EP/CL Qty | AY2: KSLD Qty | AZ2: KSHD Qty | BA2: NRT/Fusion Qty | BB2: NRT+ Qty | BC2: NRT KSLD Qty | BD2: CG280 Qty | BE2: CG300 Qty | BF2: Total Qty | BG2: Unit Price | BH2: Qty/1000 lbs | BI2: Qty/1000 lbs | BJ2: Qty/1000 lbs | BK2: Qty/1000 lbs | BL2: Qty/1000 lbs | BM2: Qty/1000 lbs | BN2: Qty/1000 lbs | BO2: Qty/1000 lbs | BP2: Under-Abs | BQ2: Under-Abs | BR2: Under-Abs | BS2: Under-Abs | BT2: Under-Abs | BU2: Under-Abs | BV2: Under-Abs | BW2: Under-Abs | BX2: Under-Abs
B3: CEP/CL/HP | E3: KSLD | H3: KSHD | K3: NRT/FUSION | N3: NRT+ | Q3: NRT KSLD | T3: CG280 | W3: CG300 | AA3: COMPOSITE | AO3: B | AP3: E | AQ3: H | AR3: K | AS3: N | AT3: Q | AU3: T | AV3: W | AX3: B | AY3: E | AZ3: H | BA3: K | BB3: N | BC3: Q | BD3: T | BE3: W | BQ3: B | BR3: E | BS3: H | BT3: K | BU3: N | BV3: Q | BW3: T | BX3: W
B4: 19 Std | C4: 18 Act | D4: 18 Std | E4: 19 Std | F4: 18 Act | G4: 18 Std | H4: 19 Std | I4: 18 Act | J4: 18 Std | K4: 19 Std | L4: 18 Act | M4: 18 Std | N4: 19 Std | O4: 18 Act | P4: 18 Std | Q4: 19 Std | R4: 18 Act | S4: 18 Std | T4: 19 Std | U4: 18 Act | V4: 18 Std | W4: 19 Std | X4: 18 Act | Y4: 18 Std | AA4: 19 Std | AB4: 19 Absorb | AC4: 19 Underabs
C5: (Jan-Oct) | F5: (Jan-Oct) | I5: (Jan-Oct) | L5: (Jan-Oct) | O5: (Jan-Oct) | R5: (Jan-Oct) | U5: (Jan-Oct) | X5: (Jan-Oct)
A6: Materials | B6: =$D$66 -> 0.052442084 | C6: 0.052476066 | D6: 0.046284643 | E6: =$F$66 -> 0.11900853 | F6: 0.11639619 | G6: 0.14603303 | H6: =$H$66 -> 0.42313082 | I6: 0.41696458 | J6: 0.58154061 | K6: =$J$66 -> 0.12711514 | L6: 0.12044521 | M6: 0.27654982 | N6: =$L$66 -> 1.9292536 | O6: 1.8366354 | P6: 0 | Q6: =$N$66 -> 0.21033033 | R6: 0.19631709 | S6: 0.2134758 | T6: =$P$66 -> 0.11317584 | U6: 0.26903053 | V6: 0.14685585 | W6: =$R$66 -> 0.28172044 | X6: 0.41772519 | Y6: 0.14685585 | AA6: =(B6*B$26+E6*E$26+H6*H$26+K6*K$26+N6*N$26+Q6*Q$26+T6*T$26+W6*W$26)/AA$26 -> 0.17383503 | AB6: =AA6 -> 0.17383503 | AC6: =AA6-AB6 -> 0 | AE6: =AA6*$AA$26 -> 9590.4786
A7: Electricity | B7: =$D$114 -> 0.0098763951 | C7: 0.013296851 | D7: 0.0058460609 | E7: =$H$114 -> 0.055687674 | F7: 0.0503476 | G7: 0.051013841 | H7: =$H$114 -> 0.055687674 | I7: 0.063041198 | J7: 0.051013841 | K7: =$D$114 -> 0.0098763951 | L7: 0.0043388439 | M7: 0.0058460609 | N7: =$D$114 -> 0.0098763951 | O7: 0.0051273333 | P7: 0 | Q7: =$H$114 -> 0.055687674 | R7: 0.074619382 | S7: 0.051013841 | T7: =$D$114 -> 0.0098763951 | U7: 0.0084103379 | V7: 0.0058460609 | W7: =$D$114 -> 0.0098763951 | X7: 0.0054841618 | Y7: 0.0058460609 | AA7: =(B7*B$26+E7*E$26+H7*H$26+K7*K$26+N7*N$26+Q7*Q$26+T7*T$26+W7*W$26)/AA$26 -> 0.038108831 | AB7: =AA7 -> 0.038108831 | AC7: =AA7-AB7 -> 0 | AE7: =AA7*$AA$26 -> 2102.4642 | AF7: =ROUND($G$108*$H$108,0) -> 2102464 | AG7: 0 | AH7: =SUM(AF7:AG7) -> 2102464 | AI7: =G108 -> 27674100 | AJ7: =AH7/AI7 -> 0.075972263 | AK7: kwh | AL7: ELE01 | AM7: 630010 | AN7: 1 | AO7: =ROUND($B$114*$C$114*$B$26*1000,0) -> 91850 | AP7: =ROUND($F$114*$G$114*$E$26*1000,0) -> 1336504 | AQ7: =ROUND($F$114*$G$114*$H$26*1000,0) -> 556877 | AR7: =ROUND($B$114*$C$114*$K$26*1000,0) -> 46123 | AS7: =ROUND($B$114*$C$114*$N$26*1000,0) -> 0 | AT7: =ROUND($F$114*$G$114*$Q$26*1000,0) -> 0 | AU7: =ROUND($B$114*$C$114*$T$26*1000,0) -> 35555 | AV7: =ROUND($B$114*$C$114*$W$26*1000,0) -> 35555 | AW7: =SUM(AO7:AV7) -> 2102464 | AX7: =$B$114*$B$26*1000 -> 1209000 | AY7: =$F$114*$E$26*1000 -> 17592000 | AZ7: =$F$114*$H$26*1000 -> 7330000 | BA7: =$B$114*$K$26*1000 -> 607100 | BB7: =$B$114*$N$26*1000 -> 0 | BC7: =$F$114*$Q$26*1000 -> 0 | BD7: =$B$114*$T$26*1000 -> 468000 | BE7: =$B$114*$W$26*1000 -> 468000 | BF7: =SUM(AX7:BE7) -> 27674100 | BG7: =AW7/BF7 -> 0.075972263 | BH7: =IF(AO$26<>0,ROUND(AX7/AO$26*1000,3),0) -> 130 | BI7: =IF(AP$26<>0,ROUND(AY7/AP$26*1000,3),0) -> 733 | BJ7: =IF(AQ$26<>0,ROUND(AZ7/AQ$26*1000,3),0) -> 733 | BK7: =IF(AR$26<>0,ROUND(BA7/AR$26*1000,3),0) -> 130 | BL7: =IF(AS$26<>0,ROUND(BB7/AS$26*1000,3),BH7) -> 130 | BM7: =IF(AT$26<>0,ROUND(BC7/AT$26*1000,3),BI7) -> 733 | BN7: =IF(AU$26<>0,ROUND(BD7/AU$26*1000,3),0) -> 130 | BO7: =IF(AV$26<>0,ROUND(BE7/AV$26*1000,3),0) -> 130 | BP7: =AC7*$AA$26 -> 0 | BQ7: =$AC7*AO$26/1000 -> 0 | BR7: =$AC7*AP$26/1000 -> 0 | BS7: =$AC7*AQ$26/1000 -> 0 | BT7: =$AC7*AR$26/1000 -> 0 | BU7: =$AC7*AS$26/1000 -> 0 | BV7: =$AC7*AT$26/1000 -> 0 | BW7: =$AC7*AU$26/1000 -> 0 | BX7: =$AC7*AV$26/1000 -> 0
A8: Gas | B8: =$D$119 -> 0.0168 | C8: 0.023514844 | D8: 0.025057338 | E8: =$H$119 -> 0.0098 | F8: 0.020991938 | G8: 0.014094753 | H8: =$H$119 -> 0.0098 | I8: 0.015002511 | J8: 0.014094753 | K8: =$D$119 -> 0.0168 | L8: 0.025939135 | M8: 0.025057338 | N8: =$D$119 -> 0.0168 | O8: 0.02896025 | P8: 0 | Q8: =$H$119 -> 0.0098 | R8: 0.015185188 | S8: 0.014094753 | T8: =$D$119 -> 0.0168 | U8: 0.011419925 | V8: 0.025057338 | W8: =$D$119 -> 0.0168 | X8: 0.01214861 | Y8: 0.025057338 | AA8: =(B8*B$26+E8*E$26+H8*H$26+K8*K$26+N8*N$26+Q8*Q$26+T8*T$26+W8*W$26)/AA$26 -> 0.012486061 | AB8: =AA8 -> 0.012486061 | AC8: =AA8-AB8 -> 0 | AE8: =AA8*$AA$26 -> 688.856 | AF8: =ROUND($D$108*$C$108,0) -> 688856 | AG8: 0 | AH8: =SUM(AF8:AG8) -> 688856 | AI8: =C108*1000 -> 1.96816e+08 | AJ8: =AH8/AI8 -> 0.0035 | AK8: mbtu | AL8: GAS01 | AM8: 630015 | AN8: 1 | AO8: =ROUND($B$119*$C$119*$B$26*1000,0) -> 156240 | AP8: =ROUND($F$119*$G$119*$E$26*1000,0) -> 235200 | AQ8: =ROUND($F$119*$G$119*$H$26*1000,0) -> 98000 | AR8: =ROUND($B$119*$C$119*$K$26*1000,0) -> 78456 | AS8: =ROUND($B$119*$C$119*$N$26*1000,0) -> 0 | AT8: =ROUND($F$119*$G$119*$Q$26*1000,0) -> 0 | AU8: =ROUND($B$119*$C$119*$T$26*1000,0) -> 60480 | AV8: =ROUND($B$119*$C$119*$W$26*1000,0) -> 60480 | AW8: =SUM(AO8:AV8) -> 688856 | AX8: =$B$119*$B$26*1000*1000 -> 44640000 | AY8: =$F$119*$E$26*1000*1000 -> 67200000 | AZ8: =$F$119*$H$26*1000*1000 -> 28000000 | BA8: =$B$119*$K$26*1000*1000 -> 22416000 | BB8: =$B$119*$N$26*1000*1000 -> 0 | BC8: =$F$119*$Q$26*1000*1000 -> 0 | BD8: =$B$119*$T$26*1000*1000 -> 17280000 | BE8: =$B$119*$W$26*1000*1000 -> 17280000 | BF8: =SUM(AX8:BE8) -> 1.96816e+08 | BG8: =AW8/BF8 -> 0.0035 | BH8: =IF(AO$26<>0,ROUND(AX8/AO$26*1000,3),0) -> 4800 | BI8: =IF(AP$26<>0,ROUND(AY8/AP$26*1000,3),0) -> 2800 | BJ8: =IF(AQ$26<>0,ROUND(AZ8/AQ$26*1000,3),0) -> 2800 | BK8: =IF(AR$26<>0,ROUND(BA8/AR$26*1000,3),0) -> 4800 | BL8: =IF(AS$26<>0,ROUND(BB8/AS$26*1000,3),BH8) -> 4800 | BM8: =IF(AT$26<>0,ROUND(BC8/AT$26*1000,3),BI8) -> 2800 | BN8: =IF(AU$26<>0,ROUND(BD8/AU$26*1000,3),0) -> 4800 | BO8: =IF(AV$26<>0,ROUND(BE8/AV$26*1000,3),0) -> 4800 | BP8: =AC8*$AA$26 -> 0 | BQ8: =$AC8*AO$26/1000 -> 0 | BR8: =$AC8*AP$26/1000 -> 0 | BS8: =$AC8*AQ$26/1000 -> 0 | BT8: =$AC8*AR$26/1000 -> 0 | BU8: =$AC8*AS$26/1000 -> 0 | BV8: =$AC8*AT$26/1000 -> 0 | BW8: =$AC8*AU$26/1000 -> 0 | BX8: =$AC8*AV$26/1000 -> 0
A9: R&M Supplies and Service | B9: =$H$129 -> 0.02718869 | C9: 0.022502448 | D9: 0.049930654 | E9: =$H$129 -> 0.02718869 | F9: 0.034492916 | G9: 0.049930654 | H9: =$H$129 -> 0.02718869 | I9: 0.033203792 | J9: 0.049930654 | K9: =$H$129 -> 0.02718869 | L9: 0.025464135 | M9: 0.049930654 | N9: =$H$129 -> 0.02718869 | O9: 0.03200775 | P9: 0 | Q9: =$H$129 -> 0.02718869 | R9: 0.012887626 | S9: 0.049930654 | T9: =$H$129 -> 0.02718869 | U9: 0.027627116 | V9: 0.049930654 | W9: =$H$129 -> 0.02718869 | X9: 0.034060431 | Y9: 0.049930654 | AA9: =(B9*B$26+E9*E$26+H9*H$26+K9*K$26+N9*N$26+Q9*Q$26+T9*T$26+W9*W$26)/AA$26 -> 0.02718869 | AB9: =AA9 -> 0.02718869 | AC9: =AA9-AB9 -> 0 | AE9: =AA9*$AA$26 -> 1500 | AF9: =ROUND($G$129,0) -> 1500000 | AG9: 0 | AH9: =SUM(AF9:AG9) -> 1500000 | AI9: =$B$28*1000 -> 55170000 | AJ9: =AH9/AI9 -> 0.02718869 | AK9: lb | AL9: RMS01 | AM9: 630000 | AN9: 1 | AO9: =$H$129*$B$26*1000 -> 252854.81 | AP9: =$H$129*$E$26*1000 -> 652528.55 | AQ9: =$H$129*$H$26*1000 -> 271886.9 | AR9: =$H$129*$K$26*1000 -> 126971.18 | AS9: =$H$129*$N$26*1000 -> 0 | AT9: =$H$129*$Q$26*1000 -> 0 | AU9: =$H$129*$T$26*1000 -> 97879.282 | AV9: =$H$129*$W$26*1000 -> 97879.282 | AW9: =SUM(AO9:AV9) -> 1500000 | AX9: =$B$26*1000 -> 9300000 | AY9: =$E$26*1000 -> 24000000 | AZ9: =$H$26*1000 -> 10000000 | BA9: =$K$26*1000 -> 4670000 | BB9: =$N$26*1000 -> 0 | BC9: =$Q$26*1000 -> 0 | BD9: =$T$26*1000 -> 3600000 | BE9: =$W$26*1000 -> 3600000 | BF9: =SUM(AX9:BE9) -> 55170000 | BG9: =AW9/BF9 -> 0.02718869 | BH9: =IF(AO$26<>0,ROUND(AX9/AO$26*1000,3),0) -> 1000 | BI9: =IF(AP$26<>0,ROUND(AY9/AP$26*1000,3),0) -> 1000 | BJ9: =IF(AQ$26<>0,ROUND(AZ9/AQ$26*1000,3),0) -> 1000 | BK9: =IF(AR$26<>0,ROUND(BA9/AR$26*1000,3),0) -> 1000 | BL9: =IF(AS$26<>0,ROUND(BB9/AS$26*1000,3),BH9) -> 1000 | BM9: =IF(AT$26<>0,ROUND(BC9/AT$26*1000,3),BI9) -> 1000 | BN9: =IF(AU$26<>0,ROUND(BD9/AU$26*1000,3),0) -> 1000 | BO9: =IF(AV$26<>0,ROUND(BE9/AV$26*1000,3),0) -> 1000 | BP9: =AC9*$AA$26 -> 0 | BQ9: =$AC9*AO$26/1000 -> 0 | BR9: =$AC9*AP$26/1000 -> 0 | BS9: =$AC9*AQ$26/1000 -> 0 | BT9: =$AC9*AR$26/1000 -> 0 | BU9: =$AC9*AS$26/1000 -> 0 | BV9: =$AC9*AT$26/1000 -> 0 | BW9: =$AC9*AU$26/1000 -> 0 | BX9: =$AC9*AV$26/1000 -> 0
A10: Manufacturing Supplies | B10: =$H$133 -> 0.0043501903 | C10: 0.0023760034 | D10: 0.0066574202 | E10: =$H$133 -> 0.0043501903 | F10: 0.010081949 | G10: 0.0066574202 | H10: =$H$133 -> 0.0043501903 | I10: 0.0057492015 | J10: 0.0066574202 | K10: =$H$133 -> 0.0043501903 | L10: 0.0074659488 | M10: 0.0066574202 | N10: =$H$133 -> 0.0043501903 | O10: 2.4083333e-05 | P10: 0 | Q10: =$H$133 -> 0.0043501903 | R10: 0.0062434068 | S10: 0.0066574202 | T10: =$H$133 -> 0.0043501903 | U10: 0.0028120484 | V10: 0.0066574202 | W10: =$H$133 -> 0.0043501903 | X10: 0.0040891998 | Y10: 0.0066574202 | AA10: =(B10*B$26+E10*E$26+H10*H$26+K10*K$26+N10*N$26+Q10*Q$26+T10*T$26+W10*W$26)/AA$26 -> 0.0043501903 | AB10: =AA10 -> 0.0043501903 | AC10: =AA10-AB10 -> 0 | AE10: =AA10*$AA$26 -> 240 | AF10: =ROUND($G$133,0) -> 240000 | AG10: 0 | AH10: =SUM(AF10:AG10) -> 240000 | AI10: =$B$28*1000 -> 55170000 | AJ10: =AH10/AI10 -> 0.0043501903 | AK10: lb | AL10: MFG01 | AM10: 631050 | AN10: 1 | AO10: =$H$133*$B$26*1000 -> 40456.77 | AP10: =$H$133*$E$26*1000 -> 104404.57 | AQ10: =$H$133*$H$26*1000 -> 43501.903 | AR10: =$H$133*$K$26*1000 -> 20315.389 | AS10: =$H$133*$N$26*1000 -> 0 | AT10: =$H$133*$Q$26*1000 -> 0 | AU10: =$H$133*$T$26*1000 -> 15660.685 | AV10: =$H$133*$W$26*1000 -> 15660.685 | AW10: =SUM(AO10:AV10) -> 240000 | AX10: =$B$26*1000 -> 9300000 | AY10: =$E$26*1000 -> 24000000 | AZ10: =$H$26*1000 -> 10000000 | BA10: =$K$26*1000 -> 4670000 | BB10: =$N$26*1000 -> 0 | BC10: =$Q$26*1000 -> 0 | BD10: =$T$26*1000 -> 3600000 | BE10: =$W$26*1000 -> 3600000 | BF10: =SUM(AX10:BE10) -> 55170000 | BG10: =AW10/BF10 -> 0.0043501903 | BH10: =IF(AO$26<>0,ROUND(AX10/AO$26*1000,3),0) -> 1000 | BI10: =IF(AP$26<>0,ROUND(AY10/AP$26*1000,3),0) -> 1000 | BJ10: =IF(AQ$26<>0,ROUND(AZ10/AQ$26*1000,3),0) -> 1000 | BK10: =IF(AR$26<>0,ROUND(BA10/AR$26*1000,3),0) -> 1000 | BL10: =IF(AS$26<>0,ROUND(BB10/AS$26*1000,3),BH10) -> 1000 | BM10: =IF(AT$26<>0,ROUND(BC10/AT$26*1000,3),BI10) -> 1000 | BN10: =IF(AU$26<>0,ROUND(BD10/AU$26*1000,3),0) -> 1000 | BO10: =IF(AV$26<>0,ROUND(BE10/AV$26*1000,3),0) -> 1000 | BP10: =AC10*$AA$26 -> 0 | BQ10: =$AC10*AO$26/1000 -> 0 | BR10: =$AC10*AP$26/1000 -> 0 | BS10: =$AC10*AQ$26/1000 -> 0 | BT10: =$AC10*AR$26/1000 -> 0 | BU10: =$AC10*AS$26/1000 -> 0 | BV10: =$AC10*AT$26/1000 -> 0 | BW10: =$AC10*AU$26/1000 -> 0 | BX10: =$AC10*AV$26/1000 -> 0
A11: Other variable | B11: =$H$136 -> 0.010875476 | C11: 0.0084782467 | D11: 0.016643551 | E11: =$H$136 -> 0.010875476 | F11: 0.013888916 | G11: 0.016643551 | H11: =$H$136 -> 0.010875476 | I11: 0.017367487 | J11: 0.016643551 | K11: =$H$136 -> 0.010875476 | L11: 0.003624579 | M11: 0.016643551 | N11: =$H$136 -> 0.010875476 | O11: 0.013958 | P11: 0 | Q11: =$H$136 -> 0.010875476 | R11: 0.013900072 | S11: 0.016643551 | T11: =$H$136 -> 0.010875476 | U11: 0.013435556 | V11: 0.016643551 | W11: =$H$136 -> 0.010875476 | X11: 0.018878704 | Y11: 0.016643551 | AA11: =(B11*B$26+E11*E$26+H11*H$26+K11*K$26+N11*N$26+Q11*Q$26+T11*T$26+W11*W$26)/AA$26 -> 0.010875476 | AB11: =AA11 -> 0.010875476 | AC11: =AA11-AB11 -> 0 | AE11: =AA11*$AA$26 -> 600 | AF11: =ROUND($G$136,0) -> 600000 | AG11: 0 | AH11: =SUM(AF11:AG11) -> 600000 | AI11: =$B$28*1000 -> 55170000 | AJ11: =AH11/AI11 -> 0.010875476 | AK11: lb | AL11: VAR01 | AM11: see below | AN11: see below | AO11: =$H$136*$B$26*1000 -> 101141.92 | AP11: =$H$136*$E$26*1000 -> 261011.42 | AQ11: =$H$136*$H$26*1000 -> 108754.76 | AR11: =$H$136*$K$26*1000 -> 50788.472 | AS11: =$H$136*$N$26*1000 -> 0 | AT11: =$H$136*$Q$26*1000 -> 0 | AU11: =$H$136*$T$26*1000 -> 39151.713 | AV11: =$H$136*$W$26*1000 -> 39151.713 | AW11: =SUM(AO11:AV11) -> 600000 | AX11: =$B$26*1000 -> 9300000 | AY11: =$E$26*1000 -> 24000000 | AZ11: =$H$26*1000 -> 10000000 | BA11: =$K$26*1000 -> 4670000 | BB11: =$N$26*1000 -> 0 | BC11: =$Q$26*1000 -> 0 | BD11: =$T$26*1000 -> 3600000 | BE11: =$W$26*1000 -> 3600000 | BF11: =SUM(AX11:BE11) -> 55170000 | BG11: =AW11/BF11 -> 0.010875476 | BH11: =IF(AO$26<>0,ROUND(AX11/AO$26*1000,3),0) -> 1000 | BI11: =IF(AP$26<>0,ROUND(AY11/AP$26*1000,3),0) -> 1000 | BJ11: =IF(AQ$26<>0,ROUND(AZ11/AQ$26*1000,3),0) -> 1000 | BK11: =IF(AR$26<>0,ROUND(BA11/AR$26*1000,3),0) -> 1000 | BL11: =IF(AS$26<>0,ROUND(BB11/AS$26*1000,3),BH11) -> 1000 | BM11: =IF(AT$26<>0,ROUND(BC11/AT$26*1000,3),BI11) -> 1000 | BN11: =IF(AU$26<>0,ROUND(BD11/AU$26*1000,3),0) -> 1000 | BO11: =IF(AV$26<>0,ROUND(BE11/AV$26*1000,3),0) -> 1000 | BP11: =AC11*$AA$26 -> 0 | BQ11: =$AC11*AO$26/1000 -> 0 | BR11: =$AC11*AP$26/1000 -> 0 | BS11: =$AC11*AQ$26/1000 -> 0 | BT11: =$AC11*AR$26/1000 -> 0 | BU11: =$AC11*AS$26/1000 -> 0 | BV11: =$AC11*AT$26/1000 -> 0 | BW11: =$AC11*AU$26/1000 -> 0 | BX11: =$AC11*AV$26/1000 -> 0
A12: Total Variable Costs | B12: =SUM(B6:B11) -> 0.12153283 | C12: =SUM(C6:C11) -> 0.12264446 | D12: =SUM(D6:D11) -> 0.15041967 | E12: =SUM(E6:E11) -> 0.22691056 | F12: =SUM(F6:F11) -> 0.24619951 | G12: =SUM(G6:G11) -> 0.28437325 | H12: =SUM(H6:H11) -> 0.53103284 | I12: =SUM(I6:I11) -> 0.55132877 | ... Y12: =SUM(Y6:Y11) -> 0.25099088 | AA12: =SUM(AA6:AA11) -> 0.26684428 | AB12: =SUM(AB6:AB11) -> 0.26684428 | AC12: =SUM(AC6:AC11) -> 0 | AE12: =SUM(AE7:AE11) -> 5131.3202 | AF12: =SUM(AF7:AF11) -> 5131320 | AG12: =SUM(AG7:AG11) -> 0 | AH12: =SUM(AH7:AH11) -> 5131320 | AO12: =SUM(AO7:AO11) -> 642543.51 | AP12: =SUM(AP7:AP11) -> 2589648.5 | AQ12: =SUM(AQ7:AQ11) -> 1079020.6 | AW12: =SUM(AW7:AW11) -> 5131320 | BP12: =SUM(BP7:BP11) -> 0 | BQ12: =SUM(BQ7:BQ11) -> 0 | BR12: =SUM(BR7:BR11) -> 0 | BS12: =SUM(BS7:BS11) -> 0 | BT12: =SUM(BT7:BT11) -> 0 | BU12: =SUM(BU7:BU11) -> 0 | BV12: =SUM(BV7:BV11) -> 0 | BW12: =SUM(BW7:BW11) -> 0 | BX12: =SUM(BX7:BX11) -> 0
A14: Production Labor | B14: =IF($B$142<>0,$F99/$B$142/1000,0) -> 0.038989507 | C14: 0.018989996 | D14: 0.042571296 | E14: =IF($C$142<>0,$H99/$C$142/1000,0) -> 0.038989507 | F14: 0.028644278 | G14: 0.042571296 | H14: =IF($C$142<>0,$H99/$C$142/1000,0) -> 0.038989507 | I14: 0.055686215 | J14: 0.042571296 | K14: =IF($B$142<>0,$F99/$B$142/1000,0) -> 0.038989507 | L14: 0.014388196 | M14: 0.042571296 | N14: =IF($B$142<>0,$F99/$B$142/1000,0) -> 0.038989507 | O14: 0.029732 | P14: 0 | Q14: =IF($C$142<>0,$H99/$C$142/1000,0) -> 0.038989507 | R14: 0.020196803 | S14: 0.042571296 | T14: =IF($B$142<>0,$F99/$B$142/1000,0) -> 0.038989507 | U14: 0.0016157561 | V14: 0.042571296 | W14: =IF($B$142<>0,$F99/$B$142/1000,0) -> 0.038989507 | X14: 0.0014495359 | Y14: 0.042571296 | AA14: =(B14*B$26+E14*E$26+H14*H$26+K14*K$26+N14*N$26+Q14*Q$26+T14*T$26+W14*W$26)/AA$26 -> 0.038989507 | AB14: =AB22-AB12 -> 0.033405108 | AC14: =AA14-AB14 -> 0.0055843995 | AE14: =AA14*$AA$26 -> 2151.0511 | AF14: =ROUND($D$88,0) -> 2151051 | AG14: =ROUND($D$87,0) -> 29082 | AH14: =SUM(AF14:AG14) -> 2180133 | AI14: =$B$86 -> 64622.4 | AJ14: =AH14/AI14 -> 33.736491 | AK14: hr | AL14: DLAB01 | AM14: see below | AN14: see below | AO14: =$F99/$B$142*B$26 -> 362602.42 | AP14: =$H99/$C$142*E$26 -> 935748.18 | AQ14: =$H99/$C$142*H$26 -> 389895.07 | AR14: =$F99/$B$142*K$26 -> 182081 | AS14: =$F99/$B$142*N$26 -> 0 | AT14: =$H99/$C$142*Q$26 -> 0 | AU14: =$F99/$B$142*T$26 -> 140362.23 | AV14: =$F99/$B$142*W$26 -> 140362.23 | AW14: =SUM(AO14:AV14) -> 2151051.1 | AX14: =$E99/$B$142*B$26 -> 10748.077 | AY14: =$G99/$C$142*E$26 -> 27736.974 | AZ14: =$G99/$C$142*H$26 -> 11557.072 | BA14: =$E99/$B$142*K$26 -> 5397.1528 | BB14: =$E99/$B$142*N$26 -> 0 | BC14: =$G99/$C$142*Q$26 -> 0 | BD14: =$E99/$B$142*T$26 -> 4160.5461 | BE14: =$E99/$B$142*W$26 -> 4160.5461 | BF14: =SUM(AX14:BE14) -> 63760.369 | BG14: =AW14/BF14 -> 33.736491 | BH14: =IF(AO$26<>0,ROUND(AX14/AO$26*1000,3),0) -> 1.156 | BI14: =IF(AP$26<>0,ROUND(AY14/AP$26*1000,3),0) -> 1.156 | BJ14: =IF(AQ$26<>0,ROUND(AZ14/AQ$26*1000,3),0) -> 1.156 | BK14: =IF(AR$26<>0,ROUND(BA14/AR$26*1000,3),0) -> 1.156 | BL14: =IF(AS$26<>0,ROUND(BB14/AS$26*1000,3),BH14) -> 1.156 | BM14: =IF(AT$26<>0,ROUND(BC14/AT$26*1000,3),BI14) -> 1.156 | BN14: =IF(AU$26<>0,ROUND(BD14/AU$26*1000,3),0) -> 1.156 | BO14: =IF(AV$26<>0,ROUND(BE14/AV$26*1000,3),0) -> 1.156 | BP14: =AC14*$AA$26 -> 308.09132 | BQ14: =$AC14*AO$26/1000 -> 51.934916 | BR14: =$AC14*AP$26/1000 -> 134.02559 | BS14: =$AC14*AQ$26/1000 -> 55.843995 | BT14: =$AC14*AR$26/1000 -> 26.079146 | BU14: =$AC14*AS$26/1000 -> 0 | BV14: =$AC14*AT$26/1000 -> 0 | BW14: =$AC14*AU$26/1000 -> 20.103838 | BX14: =$AC14*AV$26/1000 -> 20.103838
A15: Repairs & Maintenance Labor | B15: =IF($B$142<>0,$F100/$B$142/1000,0) -> 0.020329845 | C15: 0.010091097 | D15: 0.016724099 | E15: =IF($C$142<>0,$H100/$C$142/1000,0) -> 0.020329845 | F15: 0.015211939 | G15: 0.016724099 | H15: =IF($C$142<>0,$H100/$C$142/1000,0) -> 0.020329845 | I15: 0.021872855 | J15: 0.016724099 | K15: =IF($B$142<>0,$F100/$B$142/1000,0) -> 0.020329845 | L15: 0.0051394268 | M15: 0.016724099 | N15: =IF($B$142<>0,$F100/$B$142/1000,0) -> 0.020329845 | O15: 0.01789125 | P15: 0 | Q15: =IF($C$142<>0,$H100/$C$142/1000,0) -> 0.020329845 | R15: 0.0086290824 | S15: 0.016724099 | T15: =IF($B$142<>0,$F100/$B$142/1000,0) -> 0.020329845 | U15: 0.00092575296 | V15: 0.016724099 | W15: =IF($B$142<>0,$F100/$B$142/1000,0) -> 0.020329845 | X15: 0.00073897059 | Y15: 0.016724099 | AA15: =(B15*B$26+E15*E$26+H15*H$26+K15*K$26+N15*N$26+Q15*Q$26+T15*T$26+W15*W$26)/AA$26 -> 0.020329845 | AB15: =AB22-AB12-AB14 -> 0 | AC15: =AA15-AB15 -> 0.020329845 | AE15: =AA15*$AA$26 -> 1121.5976 | AF15: =ROUND($H$86,0) -> 1121598 | AG15: 0 | AH15: =SUM(AF15:AG15) -> 1121598 | AI15: =$F$86 -> 31449.6 | AJ15: =AH15/AI15 -> 35.663347 | AK15: hr | AL15: MLAB01 | AM15: see below | AN15: see below | AO15: =$F100/$B$142*B$26 -> 189067.56 | AP15: =$H100/$C$142*E$26 -> 487916.29 | AQ15: =$H100/$C$142*H$26 -> 203298.45 | AR15: =$F100/$B$142*K$26 -> 94940.378 | AS15: =$F100/$B$142*N$26 -> 0 | AT15: =$H100/$C$142*Q$26 -> 0 | AU15: =$F100/$B$142*T$26 -> 73187.443 | AV15: =$F100/$B$142*W$26 -> 73187.443 | AW15: =SUM(AO15:AV15) -> 1121597.6 | AX15: =$E100/$B$142*B$26 -> 5301.4551 | AY15: =$G100/$C$142*E$26 -> 13681.175 | AZ15: =$G100/$C$142*H$26 -> 5700.4894 | BA15: =$E100/$B$142*K$26 -> 2662.1285 | BB15: =$E100/$B$142*N$26 -> 0 | BC15: =$G100/$C$142*Q$26 -> 0 | BD15: =$E100/$B$142*T$26 -> 2052.1762 | BE15: =$E100/$B$142*W$26 -> 2052.1762 | BF15: =SUM(AX15:BE15) -> 31449.6 | BG15: =AW15/BF15 -> 35.663333 | BH15: =IF(AO$26<>0,ROUND(AX15/AO$26*1000,3),0) -> 0.57 | BI15: =IF(AP$26<>0,ROUND(AY15/AP$26*1000,3),0) -> 0.57 | BJ15: =IF(AQ$26<>0,ROUND(AZ15/AQ$26*1000,3),0) -> 0.57 | BK15: =IF(AR$26<>0,ROUND(BA15/AR$26*1000,3),0) -> 0.57 | BL15: =IF(AS$26<>0,ROUND(BB15/AS$26*1000,3),BH15) -> 0.57 | BM15: =IF(AT$26<>0,ROUND(BC15/AT$26*1000,3),BI15) -> 0.57 | BN15: =IF(AU$26<>0,ROUND(BD15/AU$26*1000,3),0) -> 0.57 | BO15: =IF(AV$26<>0,ROUND(BE15/AV$26*1000,3),0) -> 0.57 | BP15: =AC15*$AA$26 -> 1121.5976 | BQ15: =$AC15*AO$26/1000 -> 189.06756 | BR15: =$AC15*AP$26/1000 -> 487.91629 | BS15: =$AC15*AQ$26/1000 -> 203.29845 | BT15: =$AC15*AR$26/1000 -> 94.940378 | BU15: =$AC15*AS$26/1000 -> 0 | BV15: =$AC15*AT$26/1000 -> 0 | BW15: =$AC15*AU$26/1000 -> 73.187443 | BX15: =$AC15*AV$26/1000 -> 73.187443
A16: Indirect Payroll Costs (Benefits) | B16: =IF($B$142<>0,$F101/$B$142/1000,0) -> 0.026450178 | C16: 0.014602185 | D16: 0.023642298 | E16: =IF($C$142<>0,$H101/$C$142/1000,0) -> 0.026450178 | F16: 0.019376157 | G16: 0.023642298 | H16: =IF($C$142<>0,$H101/$C$142/1000,0) -> 0.026450178 | I16: 0.033118009 | J16: 0.023642298 | K16: =IF($B$142<>0,$F101/$B$142/1000,0) -> 0.026450178 | L16: 0.0067939767 | M16: 0.023642298 | N16: =IF($B$142<>0,$F101/$B$142/1000,0) -> 0.026450178 | O16: 0.0179385 | P16: 0 | Q16: =IF($C$142<>0,$H101/$C$142/1000,0) -> 0.026450178 | R16: 0.011299855 | S16: 0.023642298 | T16: =IF($B$142<>0,$F101/$B$142/1000,0) -> 0.026450178 | U16: 0.0012972166 | V16: 0.023642298 | W16: =IF($B$142<>0,$F101/$B$142/1000,0) -> 0.026450178 | X16: 0.0009368989 | Y16: 0.023642298 | AA16: =(B16*B$26+E16*E$26+H16*H$26+K16*K$26+N16*N$26+Q16*Q$26+T16*T$26+W16*W$26)/AA$26 -> 0.026450178 | AB16: =AB22-AB12-AB14-AB15 -> 0 | AC16: =AA16-AB16 -> 0.026450178 | AE16: =AA16*$AA$26 -> 1459.2563 | AF16: =ROUND($D$96,0) -> 1459256 | AG16: =ROUND($D$95,0) -> 13212 | AH16: =SUM(AF16:AG16) -> 1472468 | AI16: =$B$94 -> 96072 | AJ16: =AH16/AI16 -> 15.326713 | AK16: hr | AL16: IPC01 | AM16: see below | AN16: see below | AO16: =$F101/$B$142*B$26 -> 245986.66 | AP16: =$H101/$C$142*E$26 -> 634804.28 | AQ16: =$H101/$C$142*H$26 -> 264501.78 | AR16: =$F101/$B$142*K$26 -> 123522.33 | AS16: =$F101/$B$142*N$26 -> 0 | AT16: =$H101/$C$142*Q$26 -> 0 | AU16: =$F101/$B$142*T$26 -> 95220.641 | AV16: =$F101/$B$142*W$26 -> 95220.641 | AW16: =SUM(AO16:AV16) -> 1459256.3 | AX16: =$E101/$B$142*B$26 -> 16049.533 | AY16: =$G101/$C$142*E$26 -> 41418.148 | AZ16: =$G101/$C$142*H$26 -> 17257.562 | BA16: =$E101/$B$142*K$26 -> 8059.2814 | BB16: =$E101/$B$142*N$26 -> 0 | BC16: =$G101/$C$142*Q$26 -> 0 | BD16: =$E101/$B$142*T$26 -> 6212.7223 | BE16: =$E101/$B$142*W$26 -> 6212.7223 | BF16: =SUM(AX16:BE16) -> 95209.969 | BG16: =AW16/BF16 -> 15.326718 | BH16: =IF(AO$26<>0,ROUND(AX16/AO$26*1000,3),0) -> 1.726 | BI16: =IF(AP$26<>0,ROUND(AY16/AP$26*1000,3),0) -> 1.726 | BJ16: =IF(AQ$26<>0,ROUND(AZ16/AQ$26*1000,3),0) -> 1.726 | BK16: =IF(AR$26<>0,ROUND(BA16/AR$26*1000,3),0) -> 1.726 | BL16: =IF(AS$26<>0,ROUND(BB16/AS$26*1000,3),BH16) -> 1.726 | BM16: =IF(AT$26<>0,ROUND(BC16/AT$26*1000,3),BI16) -> 1.726 | BN16: =IF(AU$26<>0,ROUND(BD16/AU$26*1000,3),0) -> 1.726 | BO16: =IF(AV$26<>0,ROUND(BE16/AV$26*1000,3),0) -> 1.726 | BP16: =AC16*$AA$26 -> 1459.2563 | BQ16: =$AC16*AO$26/1000 -> 245.98666 | BR16: =$AC16*AP$26/1000 -> 634.80428 | BS16: =$AC16*AQ$26/1000 -> 264.50178 | BT16: =$AC16*AR$26/1000 -> 123.52233 | BU16: =$AC16*AS$26/1000 -> 0 | BV16: =$AC16*AT$26/1000 -> 0 | BW16: =$AC16*AU$26/1000 -> 95.220641 | BX16: =$AC16*AV$26/1000 -> 95.220641
A17: Supervision | B17: =$D$146 -> 0.0068776509 | C17: 0.0039713733 | D17: 0.0052565881 | E17: =$E$146 -> 0.0068776509 | F17: 0.0064783865 | G17: 0.0052565881 | H17: =$E$146 -> 0.0068776509 | I17: 0.0050193276 | J17: 0.0052565881 | K17: =$D$146 -> 0.0068776509 | L17: 0.0047005019 | M17: 0.0052565881 | N17: =$D$146 -> 0.0068776509 | O17: 0.0058318333 | P17: 0 | Q17: =$E$146 -> 0.0068776509 | R17: 0.0059811055 | S17: 0.0052565881 | T17: =$D$146 -> 0.0068776509 | U17: 0.0043047836 | V17: 0.0052565881 | W17: =$D$146 -> 0.0068776509 | X17: 0.0050072551 | Y17: 0.0052565881 | AA17: =(B17*B$26+E17*E$26+H17*H$26+K17*K$26+N17*N$26+Q17*Q$26+T17*T$26+W17*W$26)/AA$26 -> 0.0068776509 | AB17: =AB22-AB12-AB14-AB15-AB16 -> 0 | AC17: =AA17-AB17 -> 0.0068776509 | AE17: =AA17*$AA$26 -> 379.44 | AF17: =ROUND($C$146,0) -> 379440 | AG17: 0 | AH17: =SUM(AF17:AG17) -> 379440 | AI17: =$B$28*1000 -> 55170000 | AJ17: =AH17/AI17 -> 0.0068776509 | AK17: lb | AL17: SUP01 | AM17: 611000 | AN17: 1 | AO17: =$D$146*$B$26*1000 -> 63962.153 | AP17: =$E$146*$E$26*1000 -> 165063.62 | AQ17: =$E$146*$H$26*1000 -> 68776.509 | AR17: =$D$146*$K$26*1000 -> 32118.63 | AS17: =$D$146*$N$26*1000 -> 0 | AT17: =$E$146*$N$26*1000 -> 0 | AU17: =$D$146*$T$26*1000 -> 24759.543 | AV17: =$D$146*$W$26*1000 -> 24759.543 | AW17: =SUM(AO17:AV17) -> 379440 | AX17: =ROUND(AO17/$AJ17,0) -> 9300000 | AY17: =ROUND(AP17/$AJ17,0) -> 24000000 | AZ17: =ROUND(AQ17/$AJ17,0) -> 10000000 | BA17: =ROUND(AR17/$AJ17,0) -> 4670000 | BB17: =ROUND(AS17/$AJ17,0) -> 0 | BC17: =ROUND(AT17/$AJ17,0) -> 0 | BD17: =ROUND(AU17/$AJ17,0) -> 3600000 | BE17: =ROUND(AV17/$AJ17,0) -> 3600000 | BF17: =SUM(AX17:BE17) -> 55170000 | BG17: =AW17/BF17 -> 0.0068776509 | BH17: =IF(AO$26<>0,ROUND(AX17/AO$26*1000,3),0) -> 1000 | BI17: =IF(AP$26<>0,ROUND(AY17/AP$26*1000,3),0) -> 1000 | BJ17: =IF(AQ$26<>0,ROUND(AZ17/AQ$26*1000,3),0) -> 1000 | BK17: =IF(AR$26<>0,ROUND(BA17/AR$26*1000,3),0) -> 1000 | BL17: =IF(AS$26<>0,ROUND(BB17/AS$26*1000,3),BH17) -> 1000 | BM17: =IF(AT$26<>0,ROUND(BC17/AT$26*1000,3),BI17) -> 1000 | BN17: =IF(AU$26<>0,ROUND(BD17/AU$26*1000,3),0) -> 1000 | BO17: =IF(AV$26<>0,ROUND(BE17/AV$26*1000,3),0) -> 1000 | BP17: =AC17*$AA$26 -> 379.44 | BQ17: =$AC17*AO$26/1000 -> 63.962153 | BR17: =$AC17*AP$26/1000 -> 165.06362 | BS17: =$AC17*AQ$26/1000 -> 68.776509 | BT17: =$AC17*AR$26/1000 -> 32.11863 | BU17: =$AC17*AS$26/1000 -> 0 | BV17: =$AC17*AT$26/1000 -> 0 | BW17: =$AC17*AU$26/1000 -> 24.759543 | BX17: =$AC17*AV$26/1000 -> 24.759543
A18: Depreciation | B18: =$D$148 -> 0.021572981 | C18: 0.037538559 | D18: 0.018278409 | E18: =$E$148 -> 0.11680294 | F18: 0.083846122 | G18: 0.082640943 | H18: =$E$148 -> 0.11680294 | I18: 0.11292119 | J18: 0.082640943 | K18: =$D$148 -> 0.021572981 | L18: 0.044091321 | M18: 0.018278409 | N18: =$D$148 -> 0.021572981 | O18: 0.076417417 | P18: 0 | Q18: =$E$148 -> 0.11680294 | R18: 0.14234028 | S18: 0.082640943 | T18: =$D$148 -> 0.021572981 | U18: 0.050070513 | V18: 0.018278409 | W18: =$D$148 -> 0.021572981 | X18: 0.048014874 | Y18: 0.018278409 | AA18: =(B18*B$26+E18*E$26+H18*H$26+K18*K$26+N18*N$26+Q18*Q$26+T18*T$26+W18*W$26)/AA$26 -> 0.080261011 | AB18: =AB22-AB12-AB14-AB15-AB16-AB17-AB19 -> 0 | AC18: =AA18-AB18 -> 0.080261011 | AE18: =AA18*$AA$26 -> 4428 | AF18: =ROUND($C$148,0) -> 4428000 | AG18: 0 | AH18: =SUM(AF18:AG18) -> 4428000 | AI18: =$B$28*1000 -> 55170000 | AJ18: =AH18/AI18 -> 0.080261011 | AK18: lb | AL18: DEP01 | AM18: see below | AN18: see below | AO18: =$D$148*$B$26*1000 -> 200628.73 | AP18: =$E$148*$E$26*1000 -> 2803270.6 | AQ18: =$E$148*$H$26*1000 -> 1168029.4 | AR18: =$D$148*$K$26*1000 -> 100745.82 | AS18: =$D$148*$N$26*1000 -> 0 | AT18: =$E$148*$N$26*1000 -> 0 | AU18: =$D$148*$T$26*1000 -> 77662.733 | AV18: =$D$148*$W$26*1000 -> 77662.733 | AW18: =SUM(AO18:AV18) -> 4428000 | AX18: =AO18/$AJ18 -> 2499703.5 | AY18: =AP18/$AJ18 -> 34926928 | AZ18: =AQ18/$AJ18 -> 14552887 | BA18: =AR18/$AJ18 -> 1255227.4 | BB18: =AS18/$AJ18 -> 0 | BC18: =AT18/$AJ18 -> 0 | BD18: =AU18/$AJ18 -> 967627.15 | BE18: =AV18/$AJ18 -> 967627.15 | BF18: =SUM(AX18:BE18) -> 55170000 | BG18: =AW18/BF18 -> 0.080261011 | BH18: =IF(AO$26<>0,ROUND(AX18/AO$26*1000,3),0) -> 268.785 | BI18: =IF(AP$26<>0,ROUND(AY18/AP$26*1000,3),0) -> 1455.289 | BJ18: =IF(AQ$26<>0,ROUND(AZ18/AQ$26*1000,3),0) -> 1455.289 | BK18: =IF(AR$26<>0,ROUND(BA18/AR$26*1000,3),0) -> 268.785 | BL18: =IF(AS$26<>0,ROUND(BB18/AS$26*1000,3),BH18) -> 268.785 | BM18: =IF(AT$26<>0,ROUND(BC18/AT$26*1000,3),BI18) -> 1455.289 | BN18: =IF(AU$26<>0,ROUND(BD18/AU$26*1000,3),0) -> 268.785 | BO18: =IF(AV$26<>0,ROUND(BE18/AV$26*1000,3),0) -> 268.785 | BP18: =AC18*$AA$26 -> 4428 | BQ18: =BQ22-BQ19-BQ14-BQ15-BQ16-BQ17 -> 372.64021 | BR18: =BR22-BR19-BR14-BR15-BR16-BR17 -> 2978.6419 | BS18: =BS22-BS19-BS14-BS15-BS16-BS17 -> 601.10078 | BT18: =BT22-BT19-BT14-BT15-BT16-BT17 -> 187.12148 | BU18: =BU22-BU19-BU14-BU15-BU16-BU17 -> 0 | BV18: =BV22-BV19-BV14-BV15-BV16-BV17 -> 0 | BW18: =BW22-BW19-BW14-BW15-BW16-BW17 -> 144.24782 | BX18: =BX22-BX19-BX14-BX15-BX16-BX17 -> 144.24782
A19: Insurance & Taxes | B19: =$D$147 -> 0.012688055 | C19: 0.0079989152 | D19: 0.0055478502 | E19: =$E$147 -> 0.012688055 | F19: 0.013458145 | G19: 0.0055478502 | H19: =$E$147 -> 0.012688055 | I19: 0.0082880219 | J19: 0.0055478502 | K19: =$D$147 -> 0.012688055 | L19: 0.0091534812 | M19: 0.0055478502 | N19: =$D$147 -> 0.012688055 | O19: 0.0121375 | P19: 0 | Q19: =$E$147 -> 0.012688055 | R19: 0.011672598 | S19: 0.0055478502 | T19: =$D$147 -> 0.012688055 | U19: 0.006389349 | V19: 0.0055478502 | W19: =$D$147 -> 0.012688055 | X19: 0.0066758555 | Y19: 0.0055478502 | AA19: =(B19*B$26+E19*E$26+H19*H$26+K19*K$26+N19*N$26+Q19*Q$26+T19*T$26+W19*W$26)/AA$26 -> 0.012688055 | AB19: =AB22-AB12-AB14-AB15-AB16-AB17 -> 0 | AC19: =AA19-AB19 -> 0.012688055 | AE19: =AA19*$AA$26 -> 700 | AF19: =ROUND($C$147,0) -> 700000 | AG19: 0 | AH19: =SUM(AF19:AG19) -> 700000 | AI19: =$B$28*1000 -> 55170000 | AJ19: =AH19/AI19 -> 0.012688055 | AK19: lb | AL19: INS01 | AM19: see below | AN19: see below | AO19: =$D$147*$B$26*1000 -> 117998.91 | AP19: =$E$147*$E$26*1000 -> 304513.32 | AQ19: =$E$147*$H$26*1000 -> 126880.55 | AR19: =$D$147*$K$26*1000 -> 59253.217 | AS19: =$D$147*$N$26*1000 -> 0 | AT19: =$E$147*$N$26*1000 -> 0 | AU19: =$D$147*$T$26*1000 -> 45676.998 | AV19: =$D$147*$W$26*1000 -> 45676.998 | AW19: =SUM(AO19:AV19) -> 700000 | AX19: =ROUND(AO19/$AJ19,0) -> 9300000 | AY19: =ROUND(AP19/$AJ19,0) -> 24000000 | AZ19: =ROUND(AQ19/$AJ19,0) -> 10000000 | BA19: =ROUND(AR19/$AJ19,0) -> 4670000 | BB19: =ROUND(AS19/$AJ19,0) -> 0 | BC19: =ROUND(AT19/$AJ19,0) -> 0 | BD19: =ROUND(AU19/$AJ19,0) -> 3600000 | BE19: =ROUND(AV19/$AJ19,0) -> 3600000 | BF19: =SUM(AX19:BE19) -> 55170000 | BG19: =AW19/BF19 -> 0.012688055 | BH19: =IF(AO$26<>0,ROUND(AX19/AO$26*1000,3),0) -> 1000 | BI19: =IF(AP$26<>0,ROUND(AY19/AP$26*1000,3),0) -> 1000 | BJ19: =IF(AQ$26<>0,ROUND(AZ19/AQ$26*1000,3),0) -> 1000 | BK19: =IF(AR$26<>0,ROUND(BA19/AR$26*1000,3),0) -> 1000 | BL19: =IF(AS$26<>0,ROUND(BB19/AS$26*1000,3),BH19) -> 1000 | BM19: =IF(AT$26<>0,ROUND(BC19/AT$26*1000,3),BI19) -> 1000 | BN19: =IF(AU$26<>0,ROUND(BD19/AU$26*1000,3),0) -> 1000 | BO19: =IF(AV$26<>0,ROUND(BE19/AV$26*1000,3),0) -> 1000 | BP19: =AC19*$AA$26 -> 700 | BQ19: =$AC19*AO$26/1000 -> 117.99891 | BR19: =$AC19*AP$26/1000 -> 304.51332 | BS19: =$AC19*AQ$26/1000 -> 126.88055 | BT19: =$AC19*AR$26/1000 -> 59.253217 | BU19: =$AC19*AS$26/1000 -> 0 | BV19: =$AC19*AT$26/1000 -> 0 | BW19: =$AC19*AU$26/1000 -> 45.676998 | BX19: =$AC19*AV$26/1000 -> 45.676998
A20: Total Fixed Costs | B20: =SUM(B14:B19) -> 0.12690822 | C20: =SUM(C14:C19) -> 0.093192125 | D20: =SUM(D14:D19) -> 0.11202054 | E20: =SUM(E14:E19) -> 0.22213818 | F20: =SUM(F14:F19) -> 0.16701503 | G20: =SUM(G14:G19) -> 0.17638307 | H20: =SUM(H14:H19) -> 0.22213818 | I20: =SUM(I14:I19) -> 0.23690561 | ... Y20: =SUM(Y14:Y19) -> 0.11202054 | AA20: =SUM(AA14:AA19) -> 0.18559625 | AB20: =SUM(AB14:AB19) -> 0.033405108 | AC20: =SUM(AC14:AC19) -> 0.15219114 | AE20: =SUM(AE14:AE19) -> 10239.345 | AF20: =SUM(AF14:AF19) -> 10239345 | AG20: =SUM(AG14:AG19) -> 42294 | AH20: =SUM(AH14:AH19) -> 10281639 | AO20: =SUM(AO14:AO19) -> 1180246.4 | AP20: =SUM(AP14:AP19) -> 5331316.3 | AQ20: =SUM(AQ14:AQ19) -> 2221381.8 | AR20: =SUM(AR14:AR19) -> 592661.38 | AS20: =SUM(AS14:AS19) -> 0 | AT20: =SUM(AT14:AT19) -> 0 | AU20: =SUM(AU14:AU19) -> 456869.59 | AV20: =SUM(AV14:AV19) -> 456869.59 | AW20: =SUM(AW14:AW19) -> 10239345 | BP20: =SUM(BP14:BP19) -> 8396.3852 | BQ20: =SUM(BQ14:BQ19) -> 1041.5904 | BR20: =SUM(BR14:BR19) -> 4704.965 | BS20: =SUM(BS14:BS19) -> 1320.4021 | BT20: =SUM(BT14:BT19) -> 523.03519 | BU20: =SUM(BU14:BU19) -> 0 | BV20: =SUM(BV14:BV19) -> 0 | BW20: =SUM(BW14:BW19) -> 403.19629 | BX20: =SUM(BX14:BX19) -> 403.19629
AE21: =AE12+AE20 -> 15370.665 | AF21: =AF12+AF20 -> 15370665 | AG21: =AG12+AG20 -> 42294 | AH21: =AH12+AH20 -> 15412959 | AO21: =AO12+AO20 -> 1822789.9 | AP21: =AP12+AP20 -> 7920964.8 | AQ21: =AQ12+AQ20 -> 3300402.3 | AR21: =AR12+AR20 -> 592661.38 | AS21: =AS12+AS20 -> 0 | AT21: =AT12+AT20 -> 0 | AU21: =AU12+AU20 -> 456869.59 | AV21: =AV12+AV20 -> 456869.59 | AW21: =AW12+AW20 -> 15370665 | BP21: =BP12+BP20 -> 8396.3852 | BQ21: =BQ12+BQ20 -> 1041.5904 | BR21: =BR12+BR20 -> 4704.965 | BS21: =BS12+BS20 -> 1320.4021 | BT21: =BT12+BT20 -> 523.03519 | BU21: =BU12+BU20 -> 0 | BV21: =BV12+BV20 -> 0 | BW21: =BW12+BW20 -> 403.19629 | BX21: =BX12+BX20 -> 403.19629
A22: TOTAL COST PER POUND | B22: =B12+B20 -> 0.24844105 | C22: =C12+C20 -> 0.21583658 | D22: =D12+D20 -> 0.26244021 | E22: =E12+E20 -> 0.44904874 | F22: =F12+F20 -> 0.41321454 | G22: =G12+G20 -> 0.46075632 | H22: =H12+H20 -> 0.75317102 | I22: =I12+I20 -> 0.78823438 | ... Y22: =Y12+Y20 -> 0.36301142 | AA22: =AA12+AA20 -> 0.45244053 | AB22: =AB6+((0.084*(B26+K26+N26+T26+W26))+(0.134*(E26+Q26))+(0.198*H26))/B28 -> 0.30024939 | AC22: =AC12+AC20 -> 0.15219114 | AE22: =AE6+AE21 -> 24961.144 | AM22: Excl. Raw Matl | AO22: =ROUND(AO21/AO26,5) -> 0.196 | AP22: =ROUND(AP21/AP26,5) -> 0.33004 | AQ22: =IF(AQ26<>0,ROUND(AQ21/AQ26,5),0) -> 0.33004 | AR22: =IF(AR26<>0,ROUND(AR21/AR26,5),0) -> 0.12691 | AS22: =IF(AS26<>0,ROUND(AS21/AS26,5),0) -> 0 | AT22: =IF(AT26<>0,ROUND(AT21/AT26,5),0) -> 0 | AU22: =IF(AU26<>0,ROUND(AU21/AU26,5),0) -> 0.12691 | AV22: =IF(AV26<>0,ROUND(AV21/AV26,5),0) -> 0.12691 | AW22: =ROUND(AW21/AW26,5) -> 0.27861 | BP22: =SUM(BQ22:BX22) -> 8396.3852 | BQ22: =(B22-B24)*B26 -> 1041.5904 | BR22: =(E22-E24)*E26 -> 4704.965 | BS22: =(H22-H24)*H26 -> 1320.4021 | BT22: =(K22-K24)*K26 -> 523.03519 | BU22: =(N22-N24)*N26 -> 0 | BV22: =(Q22-Q24)*Q26 -> 0 | BW22: =(T22-T24)*T26 -> 403.19629 | BX22: =(W22-W24)*W26 -> 403.19629
A23: LESS: EXCESS FIXED COSTS | B23: =B24-B22 -> -0.11199897 | E23: =E24-E22 -> -0.19604021 | H23: =H24-H22 -> -0.13204021 | K23: =K24-K22 -> -0.11199897 | N23: =N24-N22 -> -0.11199897 | Q23: =Q24-Q22 -> -0.19604021 | T23: =T24-T22 -> -0.11199897 | W23: =W24-W22 -> -0.11199897 | AA23: =AA24-AA22 -> -0.15219114 | AM23: Incl. Raw Matl | AO23: =ROUND(AO22+B6,5) -> 0.24844 | AP23: =ROUND(AP22+E6,5) -> 0.44905 | AQ23: =IF(AQ26<>0,ROUND(AQ22+H6,5),0) -> 0.75317 | AR23: =IF(AR26<>0,ROUND(AR22+I6,5),0) -> 0.54387 | AS23: =IF(AS26<>0,ROUND(AS22+J6,5),0) -> 0 | AT23: =IF(AT26<>0,ROUND(AT22+K6,5),0) -> 0 | AU23: =IF(AU26<>0,ROUND(AU22+L6,5),0) -> 0.24736 | AV23: =IF(AV26<>0,ROUND(AV22+M6,5),0) -> 0.40346 | AW23: =ROUND(AW22+(AA6*AA26)/B28,5) -> 0.45245
A24: ABSORBED COST PER POUND | B24: =IF(B7+B8+B9+B10+B11+B20<0.084,B22,B6+0.084) -> 0.13644208 | E24: =IF(E7+E8+E9+E10+E11+E20<0.134,E22,E6+0.134) -> 0.25300853 | H24: =IF(H7+H8+H9+H10+H11+H20<0.198,H22,H6+0.198) -> 0.62113082 | K24: =IF(K7+K8+K9+K10+K11+K20<0.084,K22,K6+0.084) -> 0.21111514 | N24: =IF(N7+N8+N9+N10+N11+N20<0.084,N22,N6+0.084) -> 2.0132536 | Q24: =IF(Q7+Q8+Q9+Q10+Q11+Q20<0.134,Q22,Q6+0.134) -> 0.34433033 | T24: =IF(T7+T8+T9+T10+T11+T20<0.084,T22,T6+0.084) -> 0.19717584 | W24: =IF(W7+W8+W9+W10+W11+W20<0.084,W22,W6+0.084) -> 0.36572044 | AA24: =(B24*B$26+E24*E$26+H24*H$26+K24*K$26+N24*N$26+Q24*Q$26+T24*T$26+W24*W$26)/AA$26 -> 0.30024939
A26: TOTAL PRODUCTION (000 lbs) | B26: =$B$31+$B$32 -> 9300 | C26: 44618.198 | D26: 22100 | E26: =$B$33 -> 24000 | F26: 6373.269 | G26: 35000 | H26: =$B$34 -> 10000 | I26: 12690.11 | J26: 15000 | K26: =$B$35 -> 4670 | L26: 617.6 | M26: 0 | N26: =$B$36 -> 0 | O26: 120 | P26: 0 | Q26: =$B$37 -> 0 | R26: 553.6 | S26: 0 | T26: =$B$38 -> 3600 | U26: 3939.982 | V26: 0 | W26: =$B$39 -> 3600 | X26: 715.36 | Y26: 0 | AA26: =B28 -> 55170 | AM26: Bulk Prodn lbs | AO26: =ROUND(B26*1000,0) -> 9300000 | AP26: =ROUND(E26*1000,0) -> 24000000 | AQ26: =ROUND(H26*1000,0) -> 10000000 | AR26: =ROUND(K26*1000,0) -> 4670000 | AS26: =ROUND(N26*1000,0) -> 0 | AT26: =ROUND(Q26*1000,0) -> 0 | AU26: =ROUND(T26*1000,0) -> 3600000 | AV26: =ROUND(W26*1000,0) -> 3600000 | AW26: =SUM(AO26:AV26) -> 55170000
A28: TOTAL PLANT PRODUCTION (000 lbs) | B28: =B26+E26+H26+K26+N26+Q26+T26+W26 -> 55170 | C28: =C26+F26+I26+L26+R26+U26+X26 -> 69508.119 | D28: =D26+G26+J26+M26+V26 -> 72100
AB29: Total | AC29: Variable | AD29: Fixed
A30: Production Plan: | B30: Pounds (000) | C30: Product Split | AA30: 19 Annual: | AB30: ($ in 000s)
A31: CARBO EconoProp | B31: 0 | C31: =+B31/$B$41 -> 0 | AA31: Abs by Prodn | AB31: =SUM(AC31:AD31) -> 16564.759 | AC31: =AB12*$AA$26 -> 14721.799 | AD31: =AB20*$AA$26 -> 1842.9598
A32: CARBO Lite | B32: =2000+14400/2+ROUND(100*1.013,-1) -> 9300 | C32: =+B32/$B$41 -> 0.16856987 | AA32: Under-abs Exp | AB32: =SUM(AC32:AD32) -> 8396.3852 | AC32: =AC12*AA26 -> 0 | AD32: =AC20*AA26 -> 8396.3852
A33: Kryptosphere LD | B33: 24000 | C33: =+B33/$B$41 -> 0.43501903 | AA33: Gas Net Settled | AB33: =SUM(AC33:AD33) -> 0 | AC33: =IF(C107<>0,0,(((((D106/1.06564)-0.33)*0.974)-D107)*(240000-C106))/1000) -> 0 | AD33: 0
A34: Kryptosphere HD | B34: 10000 | C34: =+B34/$B$41 -> 0.18125793 | AA34: Total Cost | AB34: =SUM(AB31:AB33) -> 24961.144 | AC34: =SUM(AC31:AC33) -> 14721.799 | AD34: =SUM(AD31:AD33) -> 10239.345
A35: NRT / Fusion | B35: 4670 | C35: =+B35/$B$41 -> 0.084647453 | AA35: Less: Non-cash | AB35: =SUM(AC35:AD35) -> -4428 | AC35: 0 | AD35: =-AA18*AA26 -> -4428
A36: NRT+ | B36: 0 | C36: =+B36/$B$41 -> 0 | AA36: Cash | AB36: =SUM(AB34:AB35) -> 20533.144 | AC36: =SUM(AC34:AC35) -> 14721.799 | AD36: =SUM(AD34:AD35) -> 5811.345
A37: NRT KSLD | B37: 0 | C37: =+B37/$B$41 -> 0
A38: CG280 | B38: =14400/4 -> 3600 | C38: =+B38/$B$41 -> 0.065252855 | AA38: 19 Monthly:
A39: CG300 | B39: =14400/4 -> 3600 | C39: =+B39/$B$41 -> 0.065252855 | AA39: Abs by Prodn | AB39: =SUM(AC39:AD39) -> 1380.3966 | AC39: =AC31/12 -> 1226.8166 | AD39: =AD31/12 -> 153.57998
B40: 0 | C40: =+B40/$B$41 -> 0 | AA40: Under-abs Exp | AB40: =SUM(AC40:AD40) -> 699.69877 | AC40: =AC32/12 -> 0 | AD40: =AD32/12 -> 699.69877
A41: Total | B41: =SUM(B31:B40) -> 55170 | C41: =SUM(C31:C40) -> 1 | AA41: Gas Net Settled | AB41: =SUM(AC41:AD41) -> 0 | AC41: =AC33/12 -> 0 | AD41: =AD33/12 -> 0
AA42: Total Cost | AB42: =SUM(AB39:AB41) -> 2080.0953 | AC42: =SUM(AC39:AC41) -> 1226.8166 | AD42: =SUM(AD39:AD41) -> 853.27875
AA43: Less: Non-cash | AB43: =SUM(AC43:AD43) -> -369 | AC43: =AC35/12 -> 0 | AD43: =AD35/12 -> -369
A44: Variable Costs - Material | AA44: Cash | AB44: =SUM(AB42:AB43) -> 1711.0953 | AC44: =SUM(AC42:AC43) -> 1226.8166 | AD44: =SUM(AD42:AD43) -> 484.27875
C45: CEP/CL/HP | E45: KSLD | G45: KSHD | I45: NRT/FUSION | K45: NRT+ | M45: NRT KSLD | O45: CG280 | Q45: CG300
A46: Raw Material: | B46: Price ($/NT) | C46: Ratio/Mix | E46: Ratio/Mix | G46: Ratio/Mix | I46: Ratio/Mix | K46: Ratio/Mix | M46: Ratio/Mix | O46: Ratio/Mix | Q46: Ratio/Mix
A47: Arcilla | B47: =16.84*2 -> 33.68 | C47: 0.6 | E47: 0.6 | G47: 0.6 | I47: 0.6 | K47: 0.6 | M47: 0.6 | O47: 0.6 | Q47: 0.6
A48: CARBO | B48: =13.81*2 -> 27.62 | C48: 0.4 | E48: 0.4 | G48: 0.4 | I48: 0.4 | K48: 0.4 | M48: 0.4 | O48: 0.4 | Q48: 0.4
A49: Weighted Average (LW) | B49: =+B47*C47+B48*C48 -> 31.256 | C49: =SUM(C47:C48) -> 1 | E49: =SUM(E47:E48) -> 1 | G49: =SUM(G47:G48) -> 1 | I49: =SUM(I47:I48) -> 1 | K49: =SUM(K47:K48) -> 1 | M49: =SUM(M47:M48) -> 1 | O49: =SUM(O47:O48) -> 1 | Q49: =SUM(Q47:Q48) -> 1
A51: Materials: | B51: Price ($/lb) | C51: BOM Use/lb | D51: Std $ Contrib | E51: BOM Use/lb | F51: Std $ Contrib | G51: BOM Use/lb | H51: Std $ Contrib | I51: BOM Use/lb | J51: Std $ Contrib | K51: BOM Use/lb | L51: Std $ Contrib | M51: BOM Use/lb | N51: Std $ Contrib | O51: BOM Use/lb | P51: Std $ Contrib | Q51: BOM Use/lb | R51: Std $ Contrib | BP51: lbs required | BQ51: 10/31/16 Inv | BR51: % of requ | BS51: cost per lb | BT51: cost per lb | BV51: cost per lb | BW51: cost per lb | BX51: cost per lb
A52: Clay/Kaolin (30015) | B52: =$B$49/2000 -> 0.015628 | C52: 2.1675264 | D52: =B52*C52 -> 0.033874102 | E52: 2.1341418 | F52: =B52*E52 -> 0.033352367 | G52: 0 | H52: =$B52*G52 -> 0 | I52: 2.4626137 | J52: =$B52*I52 -> 0.038485727 | K52: 2.2880632 | L52: =$B52*K52 -> 0.035757852 | M52: 1.8981586 | N52: =$B52*M52 -> 0.029664422 | O52: 1.8469764 | P52: =$B52*O52 -> 0.028864547 | Q52: 0.69046628 | R52: =$B52*Q52 -> 0.010790607 | AE52: =D52*$B$26+F52*$E$26+H52*$H$26+J52*$K$26+L52*$N$26+N52*$Q$26+P52*$T$26+R52*$W$26 -> 1437.9729 | AJ52: =B52*1000 -> 15.628 | AK52: lb | AL52: 30015/U102 | BH52: =IF(B52<>0,D52/B52*1000,0) -> 2167.5264 | BI52: =IF(B52<>0,F52/B52*1000,0) -> 2134.1418 | BJ52: =IF(B52<>0,H52/B52*1000,0) -> 0 | BP52: =BH52*$B$26+BI52*$E$26+BJ52*$H$26 -> 71377397 | BQ52: 202343432 | BR52: =BQ52/BP52 -> 2.834839 | BS52: =343597.02/24291676.299 -> 0.01414464 | BT52: =343597.02/24291676.299 -> 0.01414464 | BV52: =343597.02/24291676.299 -> 0.01414464 | BW52: =343597.02/24291676.299 -> 0.01414464 | BX52: =343597.02/24291676.299 -> 0.01414464
A53: Bauxite Pellets (30282) | B53: 0.14 | C53: 0 | D53: =B53*C53 -> 0 | E53: 0 | F53: =B53*E53 -> 0 | G53: 2.1733186 | H53: =$B53*G53 -> 0.30426461 | I53: 0 | J53: =$B53*I53 -> 0 | L53: =$B53*K53 -> 0 | M53: 0 | N53: =$B53*M53 -> 0 | O53: 0.51538366 | P53: =$B53*O53 -> 0.072153712 | Q53: 1.8395621 | R53: =$B53*Q53 -> 0.25753869 | AE53: =D53*$B$26+F53*$E$26+H53*$H$26+J53*$K$26+L53*$N$26+N53*$Q$26+P53*$T$26+R53*$W$26 -> 4229.5387 | AJ53: =B53*1000 -> 140 | AK53: lb | AL53: 30282/U102 | BH53: =IF(B53<>0,D53/B53*1000,0) -> 0 | BI53: =IF(B53<>0,F53/B53*1000,0) -> 0 | BJ53: =IF(B53<>0,H53/B53*1000,0) -> 2173.3186 | BP53: =BH53*$B$26+BI53*$E$26+BJ53*$H$26 -> 21733186 | BQ53: 0 | BR53: =BQ53/BP53 -> 0 | BS53: 0.06274 | BT53: 0.06274 | BV53: 0.06274 | BW53: 0.06274 | BX53: 0.06274
A54: CarboGrind 280 - Green (70180) | B54: 0.206 | C54: 0 | D54: =B54*C54 -> 0 | E54: 0 | F54: =B54*E54 -> 0 | G54: 0 | H54: =$B54*G54 -> 0 | I54: 0 | J54: =$B54*I54 -> 0 | L54: =$B54*K54 -> 0 | M54: 0 | N54: =$B54*M54 -> 0 | O54: 0 | P54: =$B54*O54 -> 0 | Q54: 0 | R54: =$B54*Q54 -> 0 | AE54: =D54*$B$26+F54*$E$26+H54*$H$26+J54*$K$26+L54*$N$26+N54*$Q$26+P54*$T$26+R54*$W$26 -> 0 | AJ54: =B54*1000 -> 206 | AK54: lb | AL54: 70180/U102 | BH54: =IF(B54<>0,D54/B54*1000,0) -> 0 | BI54: =IF(B54<>0,F54/B54*1000,0) -> 0 | BJ54: =IF(B54<>0,H54/B54*1000,0) -> 0
A55: CarboGrind 300 - Green (70186) | B55: 0.257 | C55: 0 | D55: =B55*C55 -> 0 | E55: 0 | F55: =B55*E55 -> 0 | G55: 0 | H55: =$B55*G55 -> 0 | I55: 0 | J55: =$B55*I55 -> 0 | L55: =$B55*K55 -> 0 | M55: 0 | N55: =$B55*M55 -> 0 | O55: 0 | P55: =$B55*O55 -> 0 | Q55: 0 | R55: =$B55*Q55 -> 0 | AE55: =D55*$B$26+F55*$E$26+H55*$H$26+J55*$K$26+L55*$N$26+N55*$Q$26+P55*$T$26+R55*$W$26 -> 0 | AJ55: =B55*1000 -> 257 | AK55: lb | AL55: 70186/U102 | BH55: =IF(B55<>0,D55/B55*1000,0) -> 0 | BI55: =IF(B55<>0,F55/B55*1000,0) -> 0 | BJ55: =IF(B55<>0,H55/B55*1000,0) -> 0
A56: PVA (30017) | B56: 1.33 | C56: 0.0094054228 | D56: =B56*C56 -> 0.012509212 | E56: 0 | F56: =B56*E56 -> 0 | G56: 0 | H56: =$B56*G56 -> 0 | I56: 0.014362715 | J56: =$B56*I56 -> 0.019102411 | K56: 0.010276842 | L56: =$B56*K56 -> 0.013668199 | M56: 0 | N56: =$B56*M56 -> 0 | O56: 0.0027255443 | P56: =$B56*O56 -> 0.0036249739 | Q56: 0.0028544754 | R56: =$B56*Q56 -> 0.0037964522 | AE56: =D56*$B$26+F56*$E$26+H56*$H$26+J56*$K$26+L56*$N$26+N56*$Q$26+P56*$T$26+R56*$W$26 -> 232.26107 | AJ56: =B56*1000 -> 1330 | AK56: lb | AL56: 30017/U102 | BH56: =IF(B56<>0,D56/B56*1000,0) -> 9.4054228 | BI56: =IF(B56<>0,F56/B56*1000,0) -> 0 | BJ56: =IF(B56<>0,H56/B56*1000,0) -> 0 | BP56: =BH56*$B$26+BI56*$E$26+BJ56*$H$26 -> 87470.432 | BQ56: 101933 | BR56: =BQ56/BP56 -> 1.1653424 | BS56: =143105.19/BQ56 -> 1.4039142 | BT56: =143105.19/BR56 -> 122800.98 | BV56: =143105.19/BS56 -> 101933 | BW56: =143105.19/BT56 -> 1.1653424 | BX56: =143105.19/BV56 -> 1.4039142
A57: Dispersant (30011) | B57: 0.46 | C57: 0.011178289 | D57: =B57*C57 -> 0.0051420127 | E57: 0.0077979271 | F57: =B57*E57 -> 0.0035870465 | G57: 0.079254917 | H57: =$B57*G57 -> 0.036457262 | I57: 0.014250521 | J57: =$B57*I57 -> 0.0065552398 | K57: 0.0088472583 | L57: =$B57*K57 -> 0.0040697388 | M57: 0.017324837 | N57: =$B57*M57 -> 0.0079694252 | O57: 0.016243267 | P57: =$B57*O57 -> 0.007471903 | Q57: 0.01680158 | R57: =$B57*Q57 -> 0.0077287268 | AE57: =D57*$B$26+F57*$E$26+H57*$H$26+J57*$K$26+L57*$N$26+N57*$Q$26+P57*$T$26+R57*$W$26 -> 583.81769 | AJ57: =B57*1000 -> 460 | AK57: lb | AL57: 30011/U102 | BH57: =IF(B57<>0,D57/B57*1000,0) -> 11.178289 | BI57: =IF(B57<>0,F57/B57*1000,0) -> 7.7979271 | BJ57: =IF(B57<>0,H57/B57*1000,0) -> 79.254917 | BP57: =BH57*$B$26+BI57*$E$26+BJ57*$H$26 -> 1083657.5 | BQ57: 84108 | BR57: =BQ57/BP57 -> 0.077614929 | BS57: =38613.79/BQ57 -> 0.45909771 | BT57: =38613.79/BR57 -> 497504.67 | BV57: =38613.79/BS57 -> 84108 | BW57: =38613.79/BT57 -> 0.077614929 | BX57: =38613.79/BV57 -> 0.45909771
A58: Ammonia (30000) | B58: 0.0793 | C58: 0.011560614 | D58: =B58*C58 -> 0.00091675669 | E58: 0.0088598915 | F58: =B58*E58 -> 0.0007025894 | G58: 0 | H58: =$B58*G58 -> 0 | I58: 0.026576473 | J58: =$B58*I58 -> 0.0021075143 | K58: 0.0098592667 | L58: =$B58*K58 -> 0.00078183985 | M58: 0.010400838 | N58: =$B58*M58 -> 0.00082478647 | O58: 0.013375789 | P58: =$B58*O58 -> 0.0010607001 | Q58: 0.023530496 | R58: =$B58*Q58 -> 0.0018659683 | AE58: =D58*$B$26+F58*$E$26+H58*$H$26+J58*$K$26+L58*$N$26+N58*$Q$26+P58*$T$26+R58*$W$26 -> 45.766081 | AJ58: =B58*1000 -> 79.3 | AK58: lb | AL58: 30000/U102 | BH58: =IF(B58<>0,D58/B58*1000,0) -> 11.560614 | BI58: =IF(B58<>0,F58/B58*1000,0) -> 8.8598915 | BJ58: =IF(B58<>0,H58/B58*1000,0) -> 0 | BP58: =BH58*$B$26+BI58*$E$26+BJ58*$H$26 -> 320151.11 | BQ58: 47388 | BR58: =BQ58/BP58 -> 0.1480176 | BS58: =2705.86/BQ58 -> 0.05710011 | BT58: =2705.86/BR58 -> 18280.663 | BV58: =2705.86/BS58 -> 47388 | BW58: =2705.86/BT58 -> 0.1480176 | BX58: =2705.86/BV58 -> 0.05710011
A59: CaCL (30114) | B59: 0.0875 | C59: 0 | D59: =B59*C59 -> 0 | E59: 0.18495151 | F59: =B59*E59 -> 0.016183257 | G59: 0.20059974 | H59: =$B59*G59 -> 0.017552477 | I59: 0 | J59: =$B59*I59 -> 0 | L59: =$B59*K59 -> 0 | M59: 0.23347453 | N59: =$B59*M59 -> 0.020429021 | O59: 0 | P59: =$B59*O59 -> 0 | Q59: 0 | R59: =$B59*Q59 -> 0 | AE59: =D59*$B$26+F59*$E$26+H59*$H$26+J59*$K$26+L59*$N$26+N59*$Q$26+P59*$T$26+R59*$W$26 -> 563.92294 | AJ59: =B59*1000 -> 87.5 | AK59: lb | AL59: 30114/U102 | BH59: =IF(B59<>0,D59/B59*1000,0) -> 0 | BI59: =IF(B59<>0,F59/B59*1000,0) -> 184.95151 | BJ59: =IF(B59<>0,H59/B59*1000,0) -> 200.59974 | BP59: =BH59*$B$26+BI59*$E$26+BJ59*$H$26 -> 6444833.6 | BQ59: 560786 | BR59: =BQ59/BP59 -> 0.087013263 | BS59: =49077.4/BQ59 -> 0.08751538 | BT59: =49077.4/BR59 -> 564022.06 | BV59: =49077.4/BS59 -> 560786 | BW59: =49077.4/BT59 -> 0.087013263 | BX59: =49077.4/BV59 -> 0.08751538
A60: Algenate (30170) | B60: 6.13644 | C60: 0 | D60: =B60*C60 -> 0 | E60: 0.010622327 | F60: =B60*E60 -> 0.065183272 | G60: 0.010569071 | H60: =$B60*G60 -> 0.064856471 | I60: 0 | J60: =$B60*I60 -> 0 | L60: =$B60*K60 -> 0 | M60: 0.013688703 | N60: =$B60*M60 -> 0.083999905 | O60: 0 | P60: =$B60*O60 -> 0 | Q60: 0 | R60: =$B60*Q60 -> 0 | AE60: =D60*$B$26+F60*$E$26+H60*$H$26+J60*$K$26+L60*$N$26+N60*$Q$26+P60*$T$26+R60*$W$26 -> 2212.9632 | AJ60: =B60*1000 -> 6136.44 | AK60: lb | AL60: 30170/U102 | BH60: =IF(B60<>0,D60/B60*1000,0) -> 0 | BI60: =IF(B60<>0,F60/B60*1000,0) -> 10.622327 | BJ60: =IF(B60<>0,H60/B60*1000,0) -> 10.569071 | BP60: =BH60*$B$26+BI60*$E$26+BJ60*$H$26 -> 360626.56 | BQ60: 208883 | BR60: =BQ60/BP60 -> 0.57922245 | BS60: =1269211.15/BQ60 -> 6.0761821 | BT60: =1269211.15/BR60 -> 2191232.6 | BV60: =1269211.15/BS60 -> 208883 | BW60: =1269211.15/BT60 -> 0.57922245 | BX60: =1269211.15/BV60 -> 6.0761821
A61: Taggant (30021) | B61: 11.52 | C61: 0 | D61: =B61*C61 -> 0 | E61: 0 | F61: =B61*E61 -> 0 | G61: 0 | H61: =$B61*G61 -> 0 | I61: 0.0052833549 | J61: =$B61*I61 -> 0.060864249 | K61: 0.16275833 | L61: =$B61*K61 -> 1.874976 | M61: 0.0058544075 | N61: =$B61*M61 -> 0.067442775 | O61: 0 | P61: =$B61*O61 -> 0 | Q61: 0 | R61: =$B61*Q61 -> 0 | AE61: =D61*$B$26+F61*$E$26+H61*$H$26+J61*$K$26+L61*$N$26+N61*$Q$26+P61*$T$26+R61*$W$26 -> 284.23604 | AJ61: =B61*1000 -> 11520 | AK61: lb | AL61: 30021/U102 | BH61: =IF(B61<>0,D61/B61*1000,0) -> 0 | BI61: =IF(B61<>0,F61/B61*1000,0) -> 0 | BJ61: =IF(B61<>0,H61/B61*1000,0) -> 0 | BP61: =BH61*$B$26+BI61*$E$26+BJ61*$H$26 -> 0
A63: Standard Cost Contribution | D63: $/lb | F63: $/lb | H63: $/lb | J63: $/lb | L63: $/lb | N63: $/lb | P63: $/lb | R63: $/lb
A64: Clay/Bauxite | D64: =D52+D53+D54 -> 0.033874102 | F64: =F52+F53+F54 -> 0.033352367 | H64: =H52+H53+H54 -> 0.30426461 | J64: =J52+J53+J54 -> 0.038485727 | L64: =L52+L53+L54 -> 0.035757852 | N64: =N52+N53+N54 -> 0.029664422 | P64: =P52+P53+P54 -> 0.10101826 | R64: =R52+R53+R54 -> 0.2683293 | AE64: =AE52+AE53+AE54 -> 5667.5116
A65: Chemical | D65: =SUM(D56:D61) -> 0.018567982 | F65: =SUM(F56:F61) -> 0.085656165 | H65: =SUM(H56:H61) -> 0.11886621 | J65: =SUM(J56:J61) -> 0.088629414 | L65: =SUM(L56:L61) -> 1.8934958 | N65: =SUM(N56:N61) -> 0.18066591 | P65: =SUM(P56:P61) -> 0.012157577 | R65: =SUM(R56:R61) -> 0.013391147 | AE65: =SUM(AE56:AE61) -> 3922.9671
A66: Total Material Cost Per Pound | D66: =SUM(D64:D65) -> 0.052442084 | F66: =SUM(F64:F65) -> 0.11900853 | H66: =SUM(H64:H65) -> 0.42313082 | J66: =SUM(J64:J65) -> 0.12711514 | L66: =SUM(L64:L65) -> 1.9292536 | N66: =SUM(N64:N65) -> 0.21033033 | P66: =SUM(P64:P65) -> 0.11317584 | R66: =SUM(R64:R65) -> 0.28172044 | AE66: =SUM(AE64:AE65) -> 9590.4786
A70: Variable Cost - Labor & Benefits - 12 hour shift | B70: Production Labor | F70: R&M Labor | AO70: Alternate DLAB01 Allocation per Product Line
B71: NIRO | C71: KS | D71: Total | F71: NIRO | G71: KS | H71: Total | AH71: =$AH$14*$AN71 -> 1744106.4 | AL71: DLAB01 (s/t) | AM71: 611030 | AN71: =100%-D74 -> 0.8 | AW71: NIRO | AX71: =($B$78+$B$80+$B$82+$B$85-$B$87)/$B$28*$B$26 -> 5446.6222 | AY71: =($B$78+$B$80+$B$82+$B$85-$B$87)/$B$28*($E$26+$H$26) -> 19912.382 | BF71: =SUM(AX71:AY71) -> 25359.005
A72: Full Time Employees | B72: 16 | C72: 12 | D72: =SUM(B72:C72) -> 28 | F72: 8 | G72: 4 | H72: =SUM(F72:G72) -> 12 | AH72: =$AH$14*$AN72 -> 436026.6 | AL72: DLAB01 (o/t) | AM72: 610210 | AN72: =D74 -> 0.2 | AW72: KS | AX72: 0 | AY72: =($B$79+$B$81+$B$83)/$E$26*($E$26+$H$26) -> 44553.6 | BF72: =SUM(AX72:AY72) -> 44553.6
A73: Labor Rate | B73: =ROUND(30.22*(1+$F$160),2) -> 30.82 | C73: =ROUND(30.22*(1+$F$160),2) -> 30.82 | D73: =($B$72*B73+$C$72*C73)/$D$72 -> 30.82 | F73: =ROUND(32.27*(1+$F$160),2) -> 32.92 | G73: =ROUND(32.27*(1+$F$160),2) -> 32.92 | H73: =($F$72*F73+$G$72*G73)/$H$72 -> 32.92 | AH73: =SUM(AH71:AH72) -> 2180133 | AK73: hr | AL73: DLAB01 | AM73: Total | AO73: =$BG$73*BH73*$B$26 -> 183749.92 | AP73: =$BG$73*BI73*($E$26+$H$26) -> 2174856.1 | AW73: =SUM(AO73:AP73) -> 2358606 | AX73: =SUM(AX71:AX72) -> 5446.6222 | AY73: =SUM(AY71:AY72) -> 64465.982 | BF73: =SUM(BF71:BF72) -> 69912.605 | BG73: =$BG$14 -> 33.736491 | BH73: =AX73/$B$26 -> 0.58565831 | BI73: =AY73/($E$26+$H$26) -> 1.8960583
A74: Overtime | B74: 0.2 | C74: 0.2 | D74: =($B$72*B74+$C$72*C74)/$D$72 -> 0.2 | F74: 0.2 | G74: 0.2 | H74: =($F$72*F74+$G$72*G74)/$H$72 -> 0.2 | AO74: Alternate MLAB01 Allocation per Product Line
AH75: =$AH$15*$AN75 -> 897278.4 | AL75: MLAB01 (s/t) | AM75: 611040 | AN75: =100%-H74 -> 0.8 | AW75: NIRO | AX75: =($F$78+$F$80+$F$82+$F$85-$F$87)/$B$28*$B$26 -> 3534.3034 | AY75: =($F$78+$F$80+$F$82+$F$85-$F$87)/$B$28*($E$26+$H$26) -> 12921.109 | BF75: =SUM(AX75:AY75) -> 16455.413
B76: Production Labor | F76: R & M Labor | AH76: =$AH$15*$AN76 -> 224319.6 | AL76: MLAB01 (o/t) | AM76: 610215 | AN76: =H74 -> 0.2 | AW76: KS | AX76: 0 | AY76: =($F$79+$F$81+$F$83)/$E$26*($E$26+$H$26) -> 14851.2 | BF76: =SUM(AX76:AY76) -> 14851.2
B77: Equiv. Hrs. | C77: Rates | D77: Gross Pay | F77: Equiv. Hrs. | G77: Rates | H77: Gross Pay | AH77: =SUM(AH75:AH76) -> 1121598 | AK77: hr | AL77: MLAB01 | AM77: Total | AO77: =$BG$77*BH77*$B$26 -> 126045.04 | AP77: =$BG$77*BI77*($E$26+$H$26) -> 990453.12 | AW77: =SUM(AO77:AP77) -> 1116498.2 | AX77: =SUM(AX75:AX76) -> 3534.3034 | AY77: =SUM(AY75:AY76) -> 27772.309 | BF77: =SUM(BF75:BF76) -> 31306.613 | BG77: =$BG$15 -> 35.663333 | BH77: =AX77/$B$26 -> 0.38003263 | BI77: =AY77/($E$26+$H$26) -> 0.81683263
A78: Straight Time Pay (NIRO) | B78: =$D$160*$D$161*B$72 -> 34944 | C78: =B$73 -> 30.82 | D78: =B78*C78 -> 1076974.1 | F78: =$D$160*$D$161*F$72 -> 17472 | G78: =F$73 -> 32.92 | H78: =F78*G78 -> 575178.24 | AO78: Nov16 Ytd
A79: Straight Time Pay (KS) | B79: =$D$160*$D$161*C$72 -> 26208 | C79: =C$73 -> 30.82 | D79: =B79*C79 -> 807730.56 | F79: =$D$160*$D$161*G$72 -> 8736 | G79: =G$73 -> 32.92 | H79: =F79*G79 -> 287589.12 | AH79: =$AH$16*$AN79 -> 130602.72 | AL79: IPC01 (vac) | AM79: 610220 | AN79: =AO79/$AO$85 -> 0.088696471 | AO79: 113854.1
A80: Overtime Pay (NIRO) | B80: =B78*B74 -> 6988.8 | C80: =B73*D162 -> 46.23 | D80: =B80*C80 -> 323092.22 | F80: =F78*F74 -> 3494.4 | G80: =F73*D162 -> 49.38 | H80: =F80*G80 -> 172553.47 | AH80: =$AH$16*$AN80 -> 122463.28 | AL80: IPC01 (hol) | AM80: 610510 | AN80: =AO80/$AO$85 -> 0.083168718 | AO80: 106758.47
A81: Overtime Pay (KS) | B81: =B79*C74 -> 5241.6 | C81: =C73*D162 -> 46.23 | D81: =B81*C81 -> 242319.17 | F81: =F79*G74 -> 1747.2 | G81: =G73*D162 -> 49.38 | H81: =F81*G81 -> 86276.736 | AH81: =$AH$16*$AN81 -> 121538.86 | AL81: IPC01 (401k) | AM81: 610600 | AN81: =AO81/$AO$85 -> 0.082540916 | AO81: 105952.6
A82: Additional OIC Pay (NIRO) | B82: 0 | D82: =(96*(35.78*1.02)*12*1.5)*0 -> 0 | F82: 0 | H82: 0 | AH82: =$AH$16*$AN82 -> 734679.8 | AL82: IPC01 (ins) | AM82: 610610 | AN82: =AO82/$AO$85 -> 0.4989445 | AO82: 640463.77
A83: Additional OIC Pay (KS) | B83: 0 | D83: 0 | F83: 0 | H83: 0 | AH83: =$AH$16*$AN83 -> 336027.95 | AL83: IPC01 (tax) | AM83: 612000 | AN83: =AO83/$AO$85 -> 0.2282073 | AO83: 292935.41
A84: Total Gross Pay | B84: =SUM(B78:B83) -> 73382.4 | C84: =D84/B84 -> 33.388333 | D84: =SUM(D78:D83) -> 2450116 | F84: =SUM(F78:F83) -> 31449.6 | G84: =H84/F84 -> 35.663333 | H84: =SUM(H78:H83) -> 1121597.6 | AH84: =$AH$16*$AN84 -> 27155.393 | AL84: IPC01 (w/c) | AM84: 612100 | AN84: =AO84/$AO$85 -> 0.018442094 | AO84: 23672.96
A85: Less: Gross Pay (NIRO) Allocated to Shipping | B85: =-H94 -> -8760 | C85: =D85/B85 -> 30.819977 | D85: =ROUND(B85*B73,0) -> -269983 | F85: 0 | H85: 0 | AH85: =SUM(AH79:AH84) -> 1472468 | AK85: hr | AL85: IPC01 | AM85: Total | AN85: =SUM(AN79:AN84) -> 1 | AO85: =SUM(AO79:AO84) -> 1283637.3
A86: Gross Pay Alloc to Production (Bulk & Bag) | B86: =SUM(B84:B85) -> 64622.4 | C86: =D86/B86 -> 33.736491 | D86: =SUM(D84:D85) -> 2180133 | F86: =SUM(F84:F85) -> 31449.6 | G86: =H86/F86 -> 35.663333 | H86: =SUM(H84:H85) -> 1121597.6
A87: Gross Pay Alloc to Bag Production | B87: =H95 -> 862.03125 | D87: =B87*C86 -> 29081.91 | F87: 0 | H87: =F87*G86 -> 0
A88: Gross Pay Alloc to Bulk Production | B88: =B86-B87 -> 63760.369 | D88: =B88*C86 -> 2151051.1 | F88: =F86-F87 -> 31449.6 | H88: =F88*G86 -> 1121597.6
A90: =CONCATENATE("Indirect Payroll Cost (IPC) at ",$D$163*100,"% (NIRO)") -> Indirect Payroll Cost (IPC) at 40% (NIRO) | B90: =(B78+B80+B82)+(F78+F80+F82) -> 62899.2 | C90: =D90/B90 -> 14.865168 | D90: =((D78+D80+D82)*$D$163)+((H78+H80+H82)*$D$163)+($C$146*$D$163/2) -> 935007.21 | E90: Shipping & Bagging Labor calc: | H90: =B73*(1+D163)*H93 -> 415171.4 | AO90: Alternate IPC01 Allocation per Product Line
A91: =CONCATENATE("Indirect Payroll Cost (IPC) at ",$D$163*100,"% (KS)") -> Indirect Payroll Cost (IPC) at 40% (KS) | B91: =(B79+B81+B83)+F79+F81+F83 -> 41932.8 | C91: =D91/B91 -> 15.392586 | D91: =((D79+D81+D83)*$D$163)+((H79+H81+H83)*$D$163)+($C$146*$D$163/2) -> 645454.23 | E91: Bagging % & lbs | G91: 0.2 | H91: =B28*G91*1000 -> 11034000 | AW91: NIRO | AX91: =($B$78+$B$80+$B$82+$B$85-$B$87)/$B$28*$B$26 -> 5446.6222 | AY91: =($B$78+$B$80+$B$82+$B$85-$B$87)/$B$28*($E$26+$H$26) -> 19912.382 | BF91: =SUM(AX91:AY91) -> 25359.005
A92: =CONCATENATE("Total IPC at ",$D$163*100,"% (KS)") -> Total IPC at 40% (KS) | B92: =SUM(B90:B91) -> 104832 | C92: =D92/B92 -> 15.076136 | D92: =SUM(D90:D91) -> 1580461.4 | E92: ($ at S/T rate) | F92: Gross Pay | G92: Benefits | H92: Hours | AW92: KS | AX92: 0 | AY92: =($B$79+$B$81+$B$83)/($E$26+$H$26)*($E$26+$H$26) -> 31449.6 | BF92: =SUM(AX92:AY92) -> 31449.6
A93: Less: IPC Allocated to Shipping (NIRO) | B93: =B85 -> -8760 | C93: =D93/B93 -> 12.327968 | D93: =ROUND(B93*$B$73*D163,0) -> -107993 | E93: Ttl Ship & Bag | F93: =SUM(F94:F95) -> 299065.11 | G93: =SUM(G94:G95) -> 121205.39 | H93: =SUM(H94:H95) -> 9622.0312 | AO93: =$BG$93*BH93*$B$26 -> 83478.843 | AP93: =$BG$93*BI93*($E$26+$H$26) -> 787210.61 | AW93: =SUM(AO93:AP93) -> 870689.46 | AX93: =SUM(AX91:AX92) -> 5446.6222 | AY93: =SUM(AY91:AY92) -> 51361.982 | BF93: =SUM(BF91:BF92) -> 56808.605 | BG93: =$BG$16 -> 15.326718 | BH93: =AX93/$B$26 -> 0.58565831 | BI93: =AY93/($E$26+$H$26) -> 1.5106465
A94: IPC Allocated to Production (Bulk & Bag) | B94: =SUM(B92:B93) -> 96072 | C94: =D94/B94 -> 15.326718 | D94: =SUM(D92:D93) -> 1472468.4 | E94: Shipping | F94: =$H94*$B$73 -> 269983.2 | G94: =$H94*$B$73*$D$163 -> 107993.28 | H94: =1*365*24 -> 8760
A95: IPC Allocated to Bag Production | B95: =H95 -> 862.03125 | D95: =B95*C94 -> 13212.11 | E95: Bagging | F95: =$H95*$C$86 -> 29081.91 | G95: =$H95*$C$94 -> 13212.11 | H95: =H91/12800 -> 862.03125
A96: IPC Allocated to Bulk Production | B96: =B94-B95 -> 95209.969 | D96: =B96*C94 -> 1459256.3
E97: NIRO | G97: KRYPTOSPHERE
E98: Hours | F98: Cost | G98: Hours | H98: Cost
A99: Production Labor Allocation by Product | E99: =IF(AND($B$142<>0,$C$142<>0),$B$88/$D$142*$B$142,IF(AND($B$142<>0,$C$142=0),$B$88,0)) -> 24466.322 | F99: =E99*$C$86 -> 825407.87 | G99: =IF(AND($B$142<>0,$C$142<>0),$B$88/$D$142*$C$142,IF(AND($B$142=0,$C$142<>0),$B$88,0)) -> 39294.046 | H99: =G99*$C$86 -> 1325643.3
A100: Maintenance Labor Allocation by Product | E100: =IF(AND($B$142<>0,$C$142<>0),$F$88/$D$142*$B$142,IF(AND($B$142<>0,$C$142=0),$F$88,0)) -> 12067.936 | F100: =E100*$G$86 -> 430382.83 | G100: =IF(AND($B$142<>0,$C$142<>0),$F$88/$D$142*$C$142,IF(AND($B$142=0,$C$142<>0),$F$88,0)) -> 19381.664 | H100: =G100*$G$86 -> 691214.74
A101: Indirect Payroll Costs Allocation by Product | E101: =(E99+E100)/($B$88+$F$88)*$B$96 -> 36534.258 | F101: =E101*$C$94 -> 559950.27 | G101: =(G99+G100)/($B$88+$F$88)*$B$96 -> 58675.71 | H101: =G101*$C$94 -> 899306.06
A104: Variable Costs - Utilities
B105: Gas | C105: mmbtu | D105: price/mmbtu | F105: Electricity | G105: kwh | H105: price/kwh
B106: Contract | C106: =IF(($B$119*($B$26+$K$26+$T$26+$W$26)+$F$119*($E$26+$H$26+$Q$26))*1000<=0,($B$119*($B$26+$K$26+$T$26+$W$26)+$F$119*($E$26+$H$26+$Q$26))*1000,0) -> 0 | D106: 0 | F106: NIRO | G106: =(B112*$B$142+F112*$C$142)*1000 -> 4928100 | H106: =0.1+0.022 -> 0.122
B107: Spot | C107: =IF(C106>=0,(((B116+B117+B118)*($B$26+$K$26+$T$26+$W$26)*1000)+((F116+F117+F118)*($E$26+$H$26+$Q$26)*1000))-0,0) -> 196816 | D107: 3.5 | F107: KS | G107: =(B113*$B$142+F113*$C$142)*1000 -> 22746000 | H107: =0.065+0.001 -> 0.066
C108: =SUM(C106:C107) -> 196816 | D108: =(C106*D106+C107*D107)/C108 -> 3.5 | G108: =SUM(G106:G107) -> 27674100 | H108: =(G106*H106+G107*H107)/G108 -> 0.07597227
B110: NIRO | F110: KS
B111: Usage (Unit/lb) | C111: Unit Price | D111: Std. Cost Contribution | F111: Usage (Unit/lb) | G111: Unit Price | H111: Std. Cost Contribution
A112: Electricity (kwh) - NIRO | B112: =0.084+0.046 -> 0.13 | C112: =$H$108 -> 0.07597227 | D112: =B112*C112 -> 0.0098763951 | F112: =0.064 -> 0.064 | G112: =$H$108 -> 0.07597227 | H112: =F112*G112 -> 0.0048622253
...

Sheet 2025 Summary
D2: CL/Cbead | E2: KSLD | F2: KSHD | G2: NRT / Fusion | H2: NRT+ | I2: NRT KSLD | J2: CG280 | K2: CG300 | L2: CL/CB $/lb | M2: KSLD $/lb | N2: KSHD $/lb | O2: NRT / Fusion $/lb | P2: NRT+ $/lb | Q2: NRT KSLD $/lb | R2: CG280 $/lb | S2: CG300 $/lb
C3: Nov | L3: =#REF! -> #REF! | M3: =#REF! -> #REF!
C4: Dec | L4: =#REF! -> #REF! | M4: =#REF! -> #REF!
C5: Jan | D5: 15000 | E5: 0 | F5: 0 | G5: 89.6 | H5: 0 | I5: 0 | J5: 0 | L5: =Jan!$B$24 -> 0.17846959 | M5: =Jan!$E$24 -> 0 | N5: =Jan!H24 -> 0 | O5: =Jan!$K$24 -> 0.27590939 | P5: =Jan!$N$24 -> 0 | Q5: =Jan!$Q$24 -> 0 | R5: =Jan!$T$24 -> 0 | S5: =Jan!$W$24 -> 0
C6: Feb | D6: 0 | E6: 1500 | F6: 3000 | G6: 0 | H6: 0 | I6: 0 | J6: 0 | L6: =Feb!B24 -> 0 | M6: =Feb!E24 -> 0.46081023 | N6: =Feb!H24 -> 1.0933601 | O6: =Feb!$K$24 -> 0 | P6: =Feb!$N$24 -> 0 | Q6: =Feb!$Q$24 -> 0 | R6: =Feb!$T$24 -> 0 | S6: =Feb!$W$24 -> 0
C7: Mar | D7: 0 | E7: 4500 | F7: 0 | G7: 0 | H7: 0 | I7: 0 | J7: 0 | L7: =Mar!B24 -> 0 | M7: =Mar!E24 -> 0.46081023 | N7: =Mar!H24 -> 0 | O7: =Mar!$K$24 -> 0 | P7: =Mar!$N$24 -> 0 | Q7: =Mar!$Q$24 -> 0 | R7: =Mar!$T$24 -> 0 | S7: =Mar!$W$24 -> 0
C8: Apr | D8: 0 | E8: 0 | F8: 3000 | G8: 0 | H8: 0 | I8: 900 | J8: 0 | L8: =Apr!B24 -> 0 | M8: =Apr!E24 -> 0 | N8: =Apr!H24 -> 1.1210608 | O8: =Apr!$K$24 -> 0 | P8: =Apr!$N$24 -> 0 | Q8: =Apr!$Q$24 -> 0.39976727 | R8: =Apr!$T$24 -> 0 | S8: =Apr!$W$24 -> 0
C9: May | D9: 0 | E9: 4500 | F9: 0 | G9: 0 | H9: 0 | I9: 0 | J9: 0 | L9: =May!B24 -> 0 | M9: =May!E24 -> 0.46081023 | N9: =May!H24 -> 0 | O9: =May!$K$24 -> 0 | P9: =May!$N$24 -> 0 | Q9: =May!$Q$24 -> 0 | R9: =May!$T$24 -> 0 | S9: =May!$W$24 -> 0
C10: Jun | D10: 0 | E10: 0 | F10: 4500 | G10: 0 | H10: 0 | I10: 0 | J10: 0 | L10: =Jun!B24 -> 0 | M10: =Jun!E24 -> 0 | N10: =Jun!H24 -> 1.0933601 | O10: =Jun!$K$24 -> 0 | P10: =Jun!$N$24 -> 0 | Q10: =Jun!$Q$24 -> 0 | R10: =Jun!$T$24 -> 0 | S10: =Jun!$W$24 -> 0
C11: Jul | D11: 5000 | E11: 0 | F11: 1500 | G11: 0 | H11: 0 | I11: 0 | J11: 1600 | L11: =Jul!B24 -> 0.22480424 | M11: =Jul!E24 -> 0 | N11: =Jul!H24 -> 1.0133359 | O11: =Jul!$K$24 -> 0 | P11: =Jul!$N$24 -> 0 | Q11: =Jul!$Q$24 -> 0 | R11: =Jul!$T$24 -> 0.42250076 | S11: =Jul!$W$24 -> 0
C12: Aug | D12: 15000 | E12: 0 | F12: 0 | G12: 0 | H12: 0 | I12: 0 | J12: 0 | L12: =Aug!B24 -> 0.17879033 | M12: =Aug!E24 -> 0 | N12: =Aug!H24 -> 0 | O12: =Aug!$K$24 -> 0 | P12: =Aug!$N$24 -> 0 | Q12: =Aug!$Q$24 -> 0 | R12: =Aug!$T$24 -> 0 | S12: =Aug!$W$24 -> 0
C13: Sep | D13: 15000 | E13: 0 | F13: 0 | G13: 0 | H13: 0 | I13: 0 | J13: 0 | L13: =Sep!B24 -> 0.17879033 | M13: =Sep!E24 -> 0 | N13: =Sep!H24 -> 0 | O13: =Sep!$K$24 -> 0 | P13: =Sep!$N$24 -> 0 | Q13: =Sep!$Q$24 -> 0 | R13: =Sep!$T$24 -> 0 | S13: =Sep!$W$24 -> 0
C14: Oct | D14: 15000 | E14: 0 | F14: 0 | G14: 0 | H14: 0 | I14: 0 | J14: 0 | L14: =Oct!B24 -> 0.17879033 | M14: =Oct!E24 -> 0 | N14: =Oct!H24 -> 0 | O14: =Oct!$K$24 -> 0 | P14: =Oct!$N$24 -> 0 | Q14: =Oct!$Q$24 -> 0 | R14: =Oct!$T$24 -> 0 | S14: =Oct!$W$24 -> 0
C15: Nov | D15: 0 | E15: 0 | F15: 0 | G15: 0 | H15: 0 | I15: 0 | J15: 0 | L15: =Nov!B24 -> 0 | M15: =Nov!E24 -> 0 | N15: =Nov!H24 -> 0 | O15: =Nov!$K$24 -> 0 | P15: =Nov!$N$24 -> 0 | Q15: =Nov!$Q$24 -> 0 | R15: =Nov!$T$24 -> 0 | S15: =Nov!$W$24 -> 0
C16: Dec | D16: 0 | E16: 0 | F16: 0 | G16: 0 | H16: 0 | I16: 0 | J16: 0 | L16: =Dec!B24 -> 0 | M16: =Dec!E24 -> 0 | N16: =Dec!H24 -> 0 | O16: =Dec!$K$24 -> 0 | P16: =Dec!$N$24 -> 0 | Q16: =Dec!$Q$24 -> 0 | R16: =Dec!$T$24 -> 0 | S16: =Dec!$W$24 -> 0
C18: Total | D18: =SUM(D3:D16) -> 65000 | E18: =SUM(E3:E16) -> 10500 | F18: =SUM(F3:F16) -> 12000 | G18: =SUM(G3:G16) -> 89.6 | H18: =SUM(H3:H16) -> 0 | I18: =SUM(I3:I16) -> 900 | J18: =SUM(J3:J16) -> 1600

Sheet Jan
A1: EUFAULA PLANT STANDARD 2025 | BO1: CG300
BO2: Qty/1000 lbs
B3: CEP/CL/HP | E3: KSLD | H3: KSHD | K3: NRT/FUSION | N3: NRT+ | Q3: NRT KSLD | T3: CG280 | W3: CG300 | AA3: COMPOSITE
B4: 25 Standard | C4: 23 Actual | D4: 22 Standard | E4: =+B4 -> 25 Standard | F4: =+C4 -> 23 Actual | G4: =+D4 -> 22 Standard | H4: =+B4 -> 25 Standard | I4: 22 Actual | J4: =+D4 -> 22 Standard | K4: =+B4 -> 25 Standard | L4: 22 Actual | M4: =+D4 -> 22 Standard | N4: =+B4 -> 25 Standard | O4: 19 Actual | P4: =+D4 -> 22 Standard | Q4: =+B4 -> 25 Standard | R4: 19 Actual | S4: =+D4 -> 22 Standard | T4: =+B4 -> 25 Standard | U4: =+C4 -> 23 Actual | V4: =+D4 -> 22 Standard | W4: =+B4 -> 25 Standard | X4: 19 Actual | Y4: =+D4 -> 22 Standard | AA4: 22 Std | AB4: 22 Absorb | AC4: 22 Underabs
C5: (Jan-Mar) | F5: (Jan-Mar) | I5: (Jan-Aug) | L5: (Jan-Feb) | O5: (Jan-Sept) | R5: (Mar & May) | U5: (Jan-Aug) | X5: (Jan-Sept)
A6: Materials | B6: =IF($B$26<>0,$D$66,0) -> 0.083034 | C6: 0.1339 | D6: 0.079895748 | E6: =IF(E26<>0,$F$66,0) -> 0 | F6: 0.2541 | G6: 0.14867672 | H6: =IF(H26<>0,$H$66,0) -> 0 | I6: 0.59389054 | J6: 0.41403491 | K6: =IF(K26<>0,$J$66,0) -> 0.1804738 | L6: 0.158 | M6: 0.52415863 | N6: =IF(N26<>0,$L$66,0) -> 0 | O6: 1.3654495 | P6: 2.009955 | Q6: =IF(Q26<>0,$N$66,0) -> 0 | R6: 0.3128638 | S6: 0.16351092 | T6: =IF($T$26<>0,$P$66,0) -> 0 | U6: 0 | V6: 0.21393973 | W6: =IF($W$26<>0,$R$66,0) -> 0 | X6: 0.38538493 | Y6: 0.35185707 | AA6: =(B6*B$26+E6*E$26+H6*H$26+K6*K$26+N6*N$26+Q6*Q$26+T6*T$26+W6*W$26)/AA$26 -> 0.083612584 | AB6: =AA6 -> 0.083612584 | AC6: =AA6-AB6 -> 0
A7: Electricity | B7: =IF($B$26<>0,$D$115,0) -> 0.01696 | C7: 0.0199 | D7: 0.017174113 | E7: =IF(E26<>0,$H$115,0) -> 0 | F7: 0.0841 | G7: 0.088307347 | H7: =IF(H26<>0,$H$115,0) -> 0 | I7: 0.068525916 | J7: 0.090176734 | K7: =IF(K26<>0,$D$115,0) -> 0.01696 | L7: 0.0186 | M7: 0.088307347 | N7: =IF(N26<>0,$D$115,0) -> 0 | O7: 0.0073991531 | P7: 0.022101421 | Q7: =IF(Q26<>0,$H$115,0) -> 0 | R7: 0.070627226 | S7: 0.090176734 | T7: =IF($T$26<>0,$D$115,0) -> 0 | U7: 0 | V7: 0.088307347 | W7: =IF($W$26<>0,$D$115,0) -> 0 | X7: 0.0063876044 | Y7: 0.022101421 | AA7: =(B7*B$26+E7*E$26+H7*H$26+K7*K$26+N7*N$26+Q7*Q$26+T7*T$26+W7*W$26)/AA$26 -> 0.01696 | AB7: =AA7 -> 0.01696 | AC7: =AA7-AB7 -> 0 | BH7: =ROUND(AX7/$B$26,3) -> 0 | BI7: =ROUND(AY7/$E$26,3) -> #DIV/0! | BJ7: =IF($H$26<>0,ROUND(AZ7/$H$26,3),0) -> 0 | BK7: =ROUND(BA7/$K$26,3) -> 0 | BN7: =ROUND(BD7/$T$26,3) -> #DIV/0! | BO7: =ROUND(BE7/$W$26,3) -> #DIV/0!
A8: Gas | B8: =IF(B26<>0,$D$120,0) -> 0.02478 | C8: 0.0272 | D8: 0.077202409 | E8: =IF(E26<>0,$H$120,0) -> 0 | F8: 0.0288 | G8: 0.043356204 | H8: =IF($H$26<>0,$H$120,0) -> 0 | I8: 0.06584205 | J8: 0.012775 | K8: =IF(K26<>0,$D$120,0) -> 0.02478 | L8: 0.0275 | M8: 0.043356204 | N8: =IF(N26<>0,$D$120,0) -> 0 | O8: 0.020068106 | P8: 0.020075 | Q8: =IF(Q26<>0,$H$120,0) -> 0 | R8: 0.012631134 | S8: 0.012775 | T8: =IF(T26<>0,$D$120,0) -> 0 | U8: 0 | V8: 0.043356204 | W8: =IF(W26<>0,$D$120,0) -> 0 | X8: 0.010829289 | Y8: 0.020075 | AA8: =(B8*B$26+E8*E$26+H8*H$26+K8*K$26+N8*N$26+Q8*Q$26+T8*T$26+W8*W$26)/AA$26 -> 0.02478 | AB8: =AA8 -> 0.02478 | AC8: =AA8-AB8 -> 0 | BH8: =ROUND(AX8/$B$26,3) -> 0 | BI8: =ROUND(AY8/$E$26,3) -> #DIV/0! | BJ8: =IF($H$26<>0,ROUND(AZ8/$H$26,3),0) -> 0 | BK8: =ROUND(BA8/$K$26,3) -> 0 | BN8: =ROUND(BD8/$T$26,3) -> #DIV/0! | BO8: =ROUND(BE8/$W$26,3) -> #DIV/0!
A9: R&M Supplies and Service | B9: =IF(B26<>0,$B$133/$B$27/1000,0) -> 0.012997603 | C9: 0.0395 | D9: 0.025157233 | E9: =IF(E26<>0,$B$133/$B$27/1000,0) -> 0 | F9: 0.0419 | G9: 0.025157233 | H9: =IF(H26<>0,$B$133/$B$27/1000,0) -> 0 | I9: 0.073013915 | J9: 0.020211742 | K9: =IF(K26<>0,$B$133/$B$27/1000,0) -> 0.012997603 | L9: 0.0431 | M9: 0.025157233 | N9: =IF(N26<>0,$B$133/$B$27/1000,0) -> 0 | O9: 0.029693532 | P9: 0.020211742 | Q9: =IF(Q26<>0,$B$133/$B$27/1000,0) -> 0 | R9: 0.0050277646 | S9: 0.020211742 | T9: =IF(T26<>0,$B$133/$B$27/1000,0) -> 0 | U9: 0 | V9: 0.025157233 | W9: =IF(W26<>0,$B$133/$B$27/1000,0) -> 0 | X9: 0.032578496 | Y9: 0.020211742 | AA9: =(B9*B$26+E9*E$26+H9*H$26+K9*K$26+N9*N$26+Q9*Q$26+T9*T$26+W9*W$26)/AA$26 -> 0.012997603 | AB9: =AA9 -> 0.012997603 | AC9: =AA9-AB9 -> 0 | BH9: =ROUND(AX9/$B$26,3) -> 0 | BI9: =ROUND(AY9/$E$26,3) -> #DIV/0! | BJ9: =IF($H$26<>0,ROUND(AZ9/$H$26,3),0) -> 0 | BK9: =ROUND(BA9/$K$26,3) -> 0 | BN9: =ROUND(BD9/$T$26,3) -> #DIV/0! | BO9: =ROUND(BE9/$W$26,3) -> #DIV/0!
A10: Manufacturing Supplies | B10: =IF(B26<>0,$B$134/$B$27/1000,0) -> 0.0026492841 | C10: 0.0049 | D10: 0.0041928721 | E10: =IF(E26<>0,$B$134/$B$27/1000,0) -> 0 | F10: 0.0041 | G10: 0.0041928721 | H10: =IF(H26<>0,$B$134/$B$27/1000,0) -> 0 | I10: 0.0022798529 | J10: 0.0048123195 | K10: =IF(K26<>0,$B$134/$B$27/1000,0) -> 0.0026492841 | L10: 0.006 | M10: 0.0041928721 | N10: =IF(N26<>0,$B$134/$B$27/1000,0) -> 0 | O10: 0.0077779148 | P10: 0.0048123195 | Q10: =IF(Q26<>0,$B$134/$B$27/1000,0) -> 0 | R10: 0.0023705607 | S10: 0.0048123195 | T10: =IF(T26<>0,$B$134/$B$27/1000,0) -> 0 | U10: 0 | V10: 0.0041928721 | W10: =IF(W26<>0,$B$134/$B$27/1000,0) -> 0 | X10: 0.0047472399 | Y10: 0.0048123195 | AA10: =(B10*B$26+E10*E$26+H10*H$26+K10*K$26+N10*N$26+Q10*Q$26+T10*T$26+W10*W$26)/AA$26 -> 0.0026492841 | AB10: =AA10 -> 0.0026492841 | AC10: =AA10-AB10 -> 0 | BH10: =ROUND(AX10/$B$26,3) -> 0 | BI10: =ROUND(AY10/$E$26,3) -> #DIV/0! | BJ10: =IF($H$26<>0,ROUND(AZ10/$H$26,3),0) -> 0 | BK10: =ROUND(BA10/$K$26,3) -> 0 | BN10: =ROUND(BD10/$T$26,3) -> #DIV/0! | BO10: =ROUND(BE10/$W$26,3) -> #DIV/0!
A11: Other variable | B11: =IF(B26<>0,$B$135/$B$27/1000,0) -> 0.0062581073 | C11: 0.0136 | D11: 0.0083857442 | E11: =IF(E26<>0,$B$135/$B$27/1000,0) -> 0 | F11: 0.0282 | G11: 0.0083857442 | H11: =IF(H26<>0,$B$135/$B$27/1000,0) -> 0 | I11: 0.029140105 | J11: 0.0076997113 | K11: =IF(K26<>0,$B$135/$B$27/1000,0) -> 0.0062581073 | L11: 0.0256 | M11: 0.0083857442 | N11: =IF(N26<>0,$B$135/$B$27/1000,0) -> 0 | O11: 0.012628237 | P11: 0.0076997113 | Q11: =IF(Q26<>0,$B$135/$B$27/1000,0) -> 0 | R11: 0.0093357827 | S11: 0.0076997113 | T11: =IF(T26<>0,$B$135/$B$27/1000,0) -> 0 | U11: 0 | V11: 0.0083857442 | W11: =IF(W26<>0,$B$135/$B$27/1000,0) -> 0 | X11: 0.0096675993 | Y11: 0.0076997113 | AA11: =(B11*B$26+E11*E$26+H11*H$26+K11*K$26+N11*N$26+Q11*Q$26+T11*T$26+W11*W$26)/AA$26 -> 0.0062581073 | AB11: =AA11 -> 0.0062581073 | AC11: =AA11-AB11 -> 0 | BH11: =ROUND(AX11/$B$26,3) -> 0 | BI11: =ROUND(AY11/$E$26,3) -> #DIV/0! | BJ11: =IF($H$26<>0,ROUND(AZ11/$H$26,3),0) -> 0 | BK11: =ROUND(BA11/$K$26,3) -> 0 | BN11: =ROUND(BD11/$T$26,3) -> #DIV/0! | BO11: =ROUND(BE11/$W$26,3) -> #DIV/0!
A12: Total Variable Costs | B12: =SUM(B6:B11) -> 0.14667899 | C12: =SUM(C6:C11) -> 0.239 | D12: 0.21200812 | E12: =SUM(E6:E11) -> 0 | F12: =SUM(F6:F11) -> 0.4412 | G12: 0.31807612 | H12: =SUM(H6:H11) -> 0 | I12: =SUM(I6:I11) -> 0.83269238 | J12: =SUM(J6:J11) -> 0.54971042 | K12: =SUM(K6:K11) -> 0.24411879 | L12: =SUM(L6:L11) -> 0.2788 | M12: 0.69355803 | N12: =SUM(N6:N11) -> 0 | O12: =SUM(O6:O11) -> 1.4430164 | P12: =SUM(P6:P11) -> 2.0848552 | Q12: =SUM(Q6:Q11) -> 0 | R12: =SUM(R6:R11) -> 0.41285626 | S12: =SUM(S6:S11) -> 0.29918642 | T12: =SUM(T6:T11) -> 0 | U12: =SUM(U6:U11) -> 0 | V12: 0.38333913 | W12: =SUM(W6:W11) -> 0 | X12: =SUM(X6:X11) -> 0.44959516 | Y12: =SUM(Y6:Y11) -> 0.42675726 | AA12: =SUM(AA6:AA11) -> 0.14725758 | AB12: =SUM(AB6:AB11) -> 0.14725758 | AC12: =SUM(AC6:AC11) -> 0
A14: Production Labor | B14: =IF(B26<>0,$F$91/$B$27/1000,0) -> 0.016327603 | C14: 0.0477 | D14: 0.01509434 | E14: =IF(E26<>0,$F$91/$B$27/1000,0) -> 0 | F14: 0.0821 | G14: 0.01509434 | H14: =IF(H26<>0,$F$91/$B$27/1000,0) -> 0 | I14: 0.075578634 | J14: 0.020862907 | K14: =IF(K26<>0,$F$91/$B$27/1000,0) -> 0.016327603 | L14: 0.0726 | M14: 0.01509434 | N14: =IF(N26<>0,$F$91/$B$27/1000,0) -> 0 | O14: 0.029535802 | P14: 0.025328546 | Q14: =IF(Q26<>0,$F$91/$B$27/1000,0) -> 0 | R14: 0.039889444 | S14: 0.020862907 | T14: =IF(T26<>0,$F$91/$B$27/1000,0) -> 0 | U14: 0 | V14: 0.01509434 | W14: =IF(W26<>0,$F$91/$B$27/1000,0) -> 0 | X14: 0.0021692465 | Y14: 0.025328546 | AA14: =(B14*B$26+E14*E$26+H14*H$26+K14*K$26+N14*N$26+Q14*Q$26+T14*T$26+W14*W$26)/AA$26 -> 0.016327603 | AB14: =AB22-AB12 -> 0.020355006 | AC14: =AA14-AB14 -> -0.0040274031 | BH14: =ROUND(AX14/$B$26,3) -> 0 | BI14: =ROUND(AY14/$E$26,3) -> #DIV/0! | BJ14: =IF($H$26<>0,ROUND(AZ14/$H$26,3),0) -> 0 | BK14: =ROUND(BA14/$K$26,3) -> 0 | BN14: =ROUND(BD14/$T$26,3) -> #DIV/0! | BO14: =ROUND(BE14/$W$26,3) -> #DIV/0!
A15: Repairs & Maintenance Labor | B15: =IF(B26<>0,$F$92/$B$27/1000,0) -> 0.0055380872 | C15: 0.0134 | D15: 0.0051091399 | E15: =IF(E26<>0,$F$92/$B$27/1000,0) -> 0 | F15: 0.0264 | G15: 0.0051091399 | H15: =IF(H26<>0,$F$92/$B$27/1000,0) -> 0 | I15: 0.014677876 | J15: 0.010844159 | K15: =IF(K26<>0,$F$92/$B$27/1000,0) -> 0.0055380872 | L15: 0.0231 | M15: 0.0051091399 | N15: =IF(N26<>0,$F$92/$B$27/1000,0) -> 0 | O15: 0.011565104 | P15: 0.013165317 | Q15: =IF(Q26<>0,$F$92/$B$27/1000,0) -> 0 | R15: 0.012338214 | S15: 0.010844159 | T15: =IF(T26<>0,$F$92/$B$27/1000,0) -> 0 | U15: 0 | V15: 0.0068056863 | W15: =IF(W26<>0,$F$92/$B$27/1000,0) -> 0 | X15: 0.0012020313 | Y15: 0.013165317 | AA15: =(B15*B$26+E15*E$26+H15*H$26+K15*K$26+N15*N$26+Q15*Q$26+T15*T$26+W15*W$26)/AA$26 -> 0.0055380872 | AB15: =AB22-AB12-AB14 -> 0 | AC15: =AA15-AB15 -> 0.0055380872 | BH15: =ROUND(AX15/$B$26,3) -> 0 | BI15: =ROUND(AY15/$E$26,3) -> #DIV/0! | BJ15: =IF($H$26<>0,ROUND(AZ15/$H$26,3),0) -> 0 | BK15: =ROUND(BA15/$K$26,3) -> 0 | BL15: =ROUND(BB15/$K$26,3) -> 0 | BM15: =ROUND(BC15/$K$26,3) -> 0 | BN15: =ROUND(BD15/$T$26,3) -> #DIV/0! | BO15: =ROUND(BE15/$W$26,3) -> #DIV/0!
A16: Indirect Payroll Costs (Benefits) | B16: =IF(B26<>0,$F$94/$B$27/1000,0) -> 0.0063410501 | C16: 0.0166 | D16: 0.0070087903 | E16: =IF(E26<>0,$F$94/$B$27/1000,0) -> 0 | F16: 0.0296 | G16: 0.0070087903 | H16: =IF(H26<>0,$F$94/$B$27/1000,0) -> 0 | I16: 0.017771004 | J16: 0.014114022 | K16: =IF(K26<>0,$F$94/$B$27/1000,0) -> 0.0063410501 | L16: 0.027 | M16: 0.0070087903 | N16: =IF(N26<>0,$F$94/$B$27/1000,0) -> 0 | O16: 0.016622212 | P16: 0.017135083 | Q16: =IF(Q26<>0,$F$94/$B$27/1000,0) -> 0 | R16: 0.012631134 | S16: 0.014114022 | T16: =IF(T26<>0,$F$94/$B$27/1000,0) -> 0 | U16: 0 | V16: 0.0093361366 | W16: =IF(W26<>0,$F$94/$B$27/1000,0) -> 0 | X16: 0.0011939818 | Y16: 0.017135083 | AA16: =(B16*B$26+E16*E$26+H16*H$26+K16*K$26+N16*N$26+Q16*Q$26+T16*T$26+W16*W$26)/AA$26 -> 0.0063410501 | AB16: =AB22-AB12-AB14-AB15 -> 0 | AC16: =AA16-AB16 -> 0.0063410501 | BH16: =ROUND(AX16/$B$26,3) -> 0 | BI16: =ROUND(AY16/$E$26,3) -> #DIV/0! | BJ16: =IF($H$26<>0,ROUND(AZ16/$H$26,3),0) -> 0 | BK16: =ROUND(BA16/$K$26,3) -> 0 | BN16: =ROUND(BD16/$T$26,3) -> #DIV/0! | BO16: =ROUND(BE16/$W$26,3) -> #DIV/0!
A17: Supervision | B17: 0 | C17: 1.8003774e-05 | D17: 0.0020935849 | E17: 0 | F17: 0.0004720951 | G17: 0.0020935849 | H17: 0 | I17: 0.00015175772 | J17: 0.0036519731 | K17: 0 | L17: 0 | M17: 0.0020935849 | N17: 0 | O17: 0.0042622241 | P17: 0.0036519731 | Q17: 0 | R17: 0.0046532453 | S17: 0.0036519731 | T17: 0 | U17: 0 | V17: 0.0020935849 | W17: 0 | X17: 0.0042504432 | Y17: 0.0036519731 | AA17: =(B17*B$26+E17*E$26+H17*H$26+K17*K$26+N17*N$26+Q17*Q$26+T17*T$26+W17*W$26)/AA$26 -> 0 | AB17: =AB22-AB12-AB14-AB15-AB16 -> 0 | AC17: =AA17-AB17 -> 0 | BH17: =ROUND(AX17/$B$26,3) -> 0 | BI17: =ROUND(AY17/$E$26,3) -> #DIV/0! | BJ17: =IF($H$26<>0,ROUND(AZ17/$H$26,3),0) -> 0 | BK17: =ROUND(BA17/$K$26,3) -> 0 | BN17: =ROUND(BD17/$T$26,3) -> #DIV/0! | BO17: =ROUND(BE17/$W$26,3) -> #DIV/0!
A18: Depreciation | B18: =IF(B26<>0,$B$148/$B$27/1000,0) -> 0.0012574409 | C18: 0.0048 | D18: 0.00099233644 | E18: =IF(E26<>0,$B$148/$B$27/1000,0) -> 0 | F18: 0.0081 | G18: 0.00099233644 | H18: =IF(H26<>0,$B$148/$B$27/1000,0) -> 0 | I18: 0.005932162 | J18: 0.12150298 | K18: =IF(K26<>0,$B$148/$B$27/1000,0) -> 0.0012574409 | L18: 0.0073 | M18: 0.00099233644 | N18: =IF(N26<>0,$B$148/$B$27/1000,0) -> 0 | O18: 0.014490934 | P18: 0.0069002299 | Q18: =IF(Q26<>0,$B$148/$B$27/1000,0) -> 0 | R18: 0.052077013 | S18: 0.12150298 | T18: =IF(T26<>0,$B$148/$B$27/1000,0) -> 0 | U18: 0 | V18: 0.00099233644 | W18: =IF(W26<>0,$B$148/$B$27/1000,0) -> 0 | X18: 0.01440759 | Y18: 0.0069002299 | AA18: =(B18*B$26+E18*E$26+H18*H$26+K18*K$26+N18*N$26+Q18*Q$26+T18*T$26+W18*W$26)/AA$26 -> 0.0012574409 | AB18: =AB22-AB12-AB14-AB15-AB16-AB17-AB19 -> 0 | AC18: =AA18-AB18 -> 0.0012574409 | BH18: =ROUND(AX18/$B$26,3) -> 0 | BI18: =ROUND(AY18/$E$26,3) -> #DIV/0! | BJ18: =IF($H$26<>0,ROUND(AZ18/$H$26,3),0) -> 0 | BK18: =ROUND(BA18/$K$26,3) -> 0 | BL18: =ROUND(BB18/$K$26,3) -> 0 | BM18: =ROUND(BC18/$K$26,3) -> 0 | BN18: =ROUND(BD18/$T$26,3) -> #DIV/0! | BO18: =ROUND(BE18/$W$26,3) -> #DIV/0!
A19: Insurance & Taxes | B19: =IF(B26<>0,$B$149/$B$27/1000,0) -> 0.0023264136 | C19: 0.0078 | D19: 0.0072955975 | E19: =IF(E26<>0,$B$149/$B$27/1000,0) -> 0 | F19: 0.0152 | G19: 0.0072955975 | H19: =IF(H26<>0,$B$149/$B$27/1000,0) -> 0 | I19: 0.0097673443 | J19: 0.0045524543 | K19: =IF(K26<>0,$B$149/$B$27/1000,0) -> 0.0023264136 | L19: 0.0132 | M19: 0.0072955975 | N19: =IF(N26<>0,$B$149/$B$27/1000,0) -> 0 | O19: 0.0079899726 | P19: 0.0045524543 | Q19: =IF(Q26<>0,$B$149/$B$27/1000,0) -> 0 | R19: 0.0077079837 | S19: 0.0045524543 | T19: =IF(T26<>0,$B$149/$B$27/1000,0) -> 0 | U19: 0 | V19: 0.0072955975 | W19: =IF(W26<>0,$B$149/$B$27/1000,0) -> 0 | X19: 0.007303301 | Y19: 0.0045524543 | AA19: =(B19*B$26+E19*E$26+H19*H$26+K19*K$26+N19*N$26+Q19*Q$26+T19*T$26+W19*W$26)/AA$26 -> 0.0023264136 | AB19: =AB22-AB12-AB14-AB15-AB16-AB17 -> 0 | AC19: =AA19-AB19 -> 0.0023264136 | BH19: =ROUND(AX19/$B$26,3) -> 0 | BI19: =ROUND(AY19/$E$26,3) -> #DIV/0! | BJ19: =IF($H$26<>0,ROUND(AZ19/$H$26,3),0) -> 0 | BK19: =ROUND(BA19/$K$26,3) -> 0 | BL19: =ROUND(BB19/$K$26,3) -> 0 | BM19: =ROUND(BC19/$K$26,3) -> 0 | BN19: =ROUND(BD19/$T$26,3) -> #DIV/0! | BO19: =ROUND(BE19/$W$26,3) -> #DIV/0!
A20: Total Fixed Costs | B20: =SUM(B14:B19) -> 0.031790594 | C20: =SUM(C14:C19) -> 0.090318004 | D20: 0.037593789 | E20: =SUM(E14:E19) -> 0 | F20: =SUM(F14:F19) -> 0.1618721 | G20: 0.037593789 | H20: =SUM(H14:H19) -> 0 | I20: =SUM(I14:I19) -> 0.12387878 | J20: =SUM(J14:J19) -> 0.1755285 | K20: =SUM(K14:K19) -> 0.031790594 | L20: =SUM(L14:L19) -> 0.1432 | M20: 0.037593789 | N20: =SUM(N14:N19) -> 0 | O20: =SUM(O14:O19) -> 0.084466248 | P20: =SUM(P14:P19) -> 0.070733603 | Q20: =SUM(Q14:Q19) -> 0 | R20: =SUM(R14:R19) -> 0.12929703 | S20: =SUM(S14:S19) -> 0.1755285 | T20: =SUM(T14:T19) -> 0 | U20: =SUM(U14:U19) -> 0 | V20: 0.041617681 | W20: =SUM(W14:W19) -> 0 | X20: =SUM(X14:X19) -> 0.030526594 | Y20: =SUM(Y14:Y19) -> 0.070733603 | AA20: =SUM(AA14:AA19) -> 0.031790594 | AB20: =SUM(AB14:AB19) -> 0.020355006 | AC20: =SUM(AC14:AC19) -> 0.011435589
A22: TOTAL COST PER POUND | B22: =B12+B20 -> 0.17846959 | C22: =C12+C20 -> 0.329318 | D22: =D12+D20 -> 0.24960191 | E22: =E12+E20 -> 0 | F22: =F12+F20 -> 0.6030721 | G22: =G12+G20 -> 0.35566991 | H22: =H12+H20 -> 0 | I22: =I12+I20 -> 0.95657116 | ... Y22: =Y12+Y20 -> 0.49749086 | AA22: =AA12+AA20 -> 0.17904817 | AB22: =AB6+((0.084*(B26+K26+T26+W26))+(0.134*(E26+Q26))+(0.198*H26))/B27 -> 0.16761258 | AC22: =AC12+AC20 -> 0.011435589
A23: LESS: EXCESS FIXED COSTS | B23: 0 | C23: -0.001395186 | E23: 0 | F23: -0.017495998 | H23: 0 | I23: -0.019688076 | K23: 0 | N23: 0 | Q23: =+Q24-Q22 -> 0 | T23: 0 | U23: 0 | W23: 0 | AA23: =+AA24-AA22 -> 0
A24: ABSORBED COST PER POUND | B24: =+B22+B23 -> 0.17846959 | C24: =+C22+C23 -> 0.32792282 | E24: =+E22+E23 -> 0 | F24: =+F22+F23 -> 0.5855761 | H24: =+H22+H23 -> 0 | I24: =+I22+I23 -> 0.93688308 | K24: =+K22+K23 -> 0.27590939 | L24: =+L22+L23 -> 0.422 | N24: =+N22+N23 -> 0 | Q24: =IF(Q7+Q8+Q9+Q10+Q11+Q20<0.134,Q22,Q6+0.134) -> 0 | T24: =+T22+T23 -> 0 | U24: =+U22+U23 -> 0 | W24: =+W22+W23 -> 0 | AA24: =(B24*B$26+E24*E$26+H24*H$26+K24*K$26+N24*N$26+Q24*Q$26+T24*T$26+W24*W$26)/AA$26 -> 0.17904817
A26: TOTAL PRODUCTION (000 lbs) | B26: =+B32 -> 15000 | C26: 23473 | D26: 17100 | E26: =+B33 -> 0 | F26: 9975 | G26: 10100 | H26: =+B34 -> 0 | I26: 4086 | J26: 7700 | K26: =+B35 -> 89.6 | L26: 354 | M26: 3700 | N26: =+B36 -> 0 | O26: 234 | P26: 0 | Q26: =+B37 -> 0 | R26: 478 | S26: 0 | T26: =+B38 -> 0 | U26: 0 | V26: 9100 | W26: =+B40 -> 0 | X26: 784 | Y26: 0 | AA26: =B27 -> 15089.6
A27: TOTAL PLANT PRODUCTION (000 lbs) | B27: =B26+E26+H26+K26+N26+Q26+T26+W26 -> 15089.6 | C27: =C26+F26+I26+L26+R26+U26+X26 -> 39150 | D27: =D26+G26+J26+M26+V26+P26+S26+Y26 -> 47700 | L27: .
AB29: Total | AC29: Variable | AD29: Fixed
A30: Production Plan: | B30: Pounds (000) | C30: Product Split | D30: Days | E30: Under absorption days | AA30: 22 Annual: | AB30: ($ in 000s)
A31: CARBO EconoProp | B31: ='2025 Summary'!#REF! -> #REF! | C31: =+B31/$B$41 -> #REF! | AA31: Abs by Prodn | AB31: =SUM(AC31:AD31) -> 2529.2069 | AC31: =AB12*$AA$26 -> 2222.058 | AD31: =AB20*$AA$26 -> 307.1489
A32: CARBO Lite | B32: ='2025 Summary'!D5 -> 15000 | C32: =+B32/$B$41 -> #REF! | D32: =B32*1000/600000 -> 25 | AA32: Under-abs Exp | AB32: =SUM(AC32:AD32) -> 172.55846 | AC32: =AC12*AA26 -> 0 | AD32: =AC20*AA26 -> 172.55846
A33: Kryptosphere LD (includes XT) | B33: ='2025 Summary'!E5 -> 0 | C33: =+B33/$B$41 -> #REF! | D33: =B33*1000/150000 -> 0 | AA33: Gas Net Settled | AB33: =SUM(AC33:AD33) -> 0 | AC33: =IF(C108<>0,0,(((((D107/1.06564)-0.33)*0.974)-D108)*(240000-C107))/1000) -> 0 | AD33: 0
A34: Kryptosphere HD | B34: ='2025 Summary'!F5 -> 0 | C34: =+B34/$B$41 -> #REF! | D34: =B34*1000/150000 -> 0 | AA34: Total Cost | AB34: =SUM(AB31:AB33) -> 2701.7653 | AC34: =SUM(AC31:AC33) -> 2222.058 | AD34: =SUM(AD31:AD33) -> 479.70735
A35: NRT / Fusion | B35: ='2025 Summary'!G5 -> 89.6 | C35: =+B35/$B$41 -> #REF! | D35: =B35*1000/175000 -> 0.512 | AA35: Less: Non-cash | AB35: =SUM(AC35:AD35) -> -18.97428 | AC35: 0 | AD35: =-AA18*AA26 -> -18.97428
A36: NRT+ | B36: ='2025 Summary'!H5 -> 0 | C36: =+B36/$B$41 -> #REF! | AA36: Cash | AB36: =SUM(AB34:AB35) -> 2682.791 | AC36: =SUM(AC34:AC35) -> 2222.058 | AD36: =SUM(AD34:AD35) -> 460.73307
A37: NRT KSLD | B37: ='2025 Summary'!I5 -> 0 | C37: =+B37/$B$41 -> #REF! | D37: =B37*1000/150000 -> 0
A38: CG280 | B38: ='2025 Summary'!J5 -> 0 | C38: =+B38/$B$41 -> #REF! | D38: =B38*1000/150000 -> 0 | AA38: 22 Monthly:
A39: CG300 | B39: ='2025 Summary'!K5 -> 0 | C39: =+B39/$B$41 -> #REF! | AA39: Abs by Prodn | AB39: =SUM(AC39:AD39) -> 210.76724 | AC39: =AC31/12 -> 185.1715 | AD39: =AD31/12 -> 25.595741
B40: 0 | C40: =+B40/$B$41 -> #REF! | AA40: Under-abs Exp | AB40: =SUM(AC40:AD40) -> 14.379871 | AC40: =AC32/12 -> 0 | AD40: =AD32/12 -> 14.379871
A41: Total | B41: =SUM(B31:B40) -> #REF! | C41: =SUM(C31:C40) -> #REF! | D41: =SUM(D31:D40) -> 25.512 | E41: =30-D41 -> 4.488 | AA41: Gas Net Settled | AB41: =SUM(AC41:AD41) -> 0 | AC41: =AC33/12 -> 0 | AD41: =AD33/12 -> 0
AA42: Total Cost | AB42: =SUM(AB39:AB41) -> 225.14711 | AC42: =SUM(AC39:AC41) -> 185.1715 | AD42: =SUM(AD39:AD41) -> 39.975613
AA43: Less: Non-cash | AB43: =SUM(AC43:AD43) -> -1.58119 | AC43: =AC35/12 -> 0 | AD43: =AD35/12 -> -1.58119
A44: Variable Costs - Material | AA44: Cash | AB44: =SUM(AB42:AB43) -> 223.56592 | AC44: =SUM(AC42:AC43) -> 185.1715 | AD44: =SUM(AD42:AD43) -> 38.394423
C45: CEP/CL/HP | E45: KSLD | G45: KSHD | I45: NRT/FUSION | K45: NRT+ | M45: NRT KSLD | O45: CG280 | Q45: CG300
A46: Raw Material: | B46: Price ($/NT) | C46: Ratio/Mix | E46: Ratio/Mix | G46: Ratio/Mix | I46: Ratio/Mix | K46: Ratio/Mix | M46: Ratio/Mix | O46: Ratio/Mix | Q46: Ratio/Mix
A47: Arcilla | B47: =40*2 -> 80 | C47: 0.1 | E47: 0.1 | G47: 0.6 | I47: 0.1 | K47: 0.6 | M47: 0.6 | O47: 0.6 | Q47: 0.6
A48: Minerals Manufacturing Co | B48: =36 -> 36 | C48: 0.9 | E48: 0.9 | G48: 0.4 | I48: 0.9 | K48: 0.4 | M48: 0.4 | O48: 0.4 | Q48: 0.4
A49: Weighted Average (LW) | B49: =+B47*C47+B48*C48 -> 40.4 | C49: =SUM(C47:C48) -> 1 | E49: =SUM(E47:E48) -> 1 | G49: =SUM(G47:G48) -> 1 | I49: =SUM(I47:I48) -> 1 | K49: =SUM(K47:K48) -> 1 | M49: =SUM(M47:M48) -> 1 | O49: =SUM(O47:O48) -> 1 | Q49: =SUM(Q47:Q48) -> 1
A51: Materials: | B51: Price ($/lb) | C51: BOM Use/lb | D51: Std $ Contrib | E51: BOM Use/lb | F51: Std $ Contrib | G51: BOM Use/lb | H51: Std $ Contrib | I51: BOM Use/lb | J51: Std $ Contrib | K51: BOM Use/lb | L51: Std $ Contrib | M51: BOM Use/lb | N51: Std $ Contrib | O51: BOM Use/lb | P51: Std $ Contrib | Q51: BOM Use/lb | R51: Std $ Contrib | BP51: lbs required | BQ51: 10/31/16 Inv | BR51: % of requ | BS51: cost per lb | BT51: cost per lb | BV51: cost per lb | BW51: cost per lb | BX51: cost per lb
A52: Clay/Kaolin (30015) | B52: =$B$49/2000 -> 0.0202 | C52: 2.19 | D52: =B52*C52 -> 0.044238 | E52: 2.18 | F52: =B52*E52 -> 0.044036 | G52: 0 | H52: =$B52*G52 -> 0 | I52: 2.2 | J52: =$B52*I52 -> 0.04444 | K52: 2.2880632 | L52: =$B52*K52 -> 0.046218877 | M52: =1781289/745600 -> 2.3890679 | N52: =$B52*M52 -> 0.048259171 | O52: =10229046/4674328 -> 2.1883458 | P52: =$B52*O52 -> 0.044204585 | Q52: =559444.75/783756 -> 0.71379964 | R52: =$B52*Q52 -> 0.014418753 | AE52: =D52*$B$26+F52*$E$26+H52*$H$26+J52*$K$26+L52*$N$26+N52*$Q$26+P52*$T$26+R52*$W$26 -> 667.55182 | AJ52: =B52*1000 -> 20.2 | AK52: lb | AL52: 30015/U102 | BH52: =IF(B52<>0,D52/B52*1000,0) -> 2190 | BI52: =IF(B52<>0,F52/B52*1000,0) -> 2180 | BJ52: =IF($B$52<>0,H52/$B$52*1000,0) -> 0 | BK52: =IF($B$52<>0,J52/$B$52*1000,0) -> 2200 | BN52: =IF($B52<>0,P52/$B52*1000,0) -> 2188.3458 | BO52: =IF($B52<>0,R52/$B52*1000,0) -> 713.79964 | BP52: =BH52*$B$26+BI52*$E$26+BJ52*$H$26 -> 32850000 | BQ52: 202343432 | BR52: =BQ52/BP52 -> 6.1596174 | BS52: =343597.02/24291676.299 -> 0.01414464 | BT52: =343597.02/24291676.299 -> 0.01414464 | BV52: =343597.02/24291676.299 -> 0.01414464 | BW52: =343597.02/24291676.299 -> 0.01414464 | BX52: =343597.02/24291676.299 -> 0.01414464
A53: Bauxite Pellets (30282) | B53: 0.25 | C53: 0 | D53: =B53*C53 -> 0 | E53: 0 | F53: =B53*E53 -> 0 | G53: 2.4 | H53: =$B53*G53 -> 0.6 | I53: 0 | J53: =$B53*I53 -> 0 | L53: =$B53*K53 -> 0 | M53: 0 | N53: =$B53*M53 -> 0 | O53: =3334227/4674328 -> 0.71330617 | P53: =$B53*O53 -> 0.17832654 | Q53: =1729064.25/783756 -> 2.2061257 | R53: =$B53*Q53 -> 0.55153142 | AE53: =D53*$B$26+F53*$E$26+H53*$H$26+J53*$K$26+L53*$N$26+N53*$Q$26+P53*$T$26+R53*$W$26 -> 0 | AJ53: =B53*1000 -> 250 | AK53: lb | AL53: 30282/U102 | BH53: =IF(B53<>0,D53/B53*1000,0) -> 0 | BI53: =IF(B53<>0,F53/B53*1000,0) -> 0 | BJ53: =IF($B$53<>0,H53/$B$53*1000,0) -> 2400 | BK53: =IF($B$53<>0,J53/$B$53*1000,0) -> 0 | BN53: =IF($B53<>0,P53/$B53*1000,0) -> 713.30617 | BO53: =IF($B53<>0,R53/$B53*1000,0) -> 2206.1257 | BP53: =BH53*$B$26+BI53*$E$26+BJ53*$H$26 -> 0 | BQ53: 0 | BR53: =BQ53/BP53 -> #DIV/0! | BS53: 0.06274 | BT53: 0.06274 | BV53: 0.06274 | BW53: 0.06274 | BX53: 0.06274
A54: CarboGrind 280 - Green (70180) | B54: 0 | C54: 0 | D54: =B54*C54 -> 0 | E54: 0 | F54: =B54*E54 -> 0 | G54: 0 | H54: =$B54*G54 -> 0 | I54: 0 | J54: =$B54*I54 -> 0 | L54: =$B54*K54 -> 0 | M54: 0 | N54: =$B54*M54 -> 0 | O54: 0 | P54: =$B54*O54 -> 0 | Q54: 0 | R54: =$B54*Q54 -> 0 | AE54: =D54*$B$26+F54*$E$26+H54*$H$26+J54*$K$26+L54*$N$26+N54*$Q$26+P54*$T$26+R54*$W$26 -> 0 | AJ54: =B54*1000 -> 0 | AK54: lb | AL54: 70180/U102 | BH54: =IF(B54<>0,D54/B54*1000,0) -> 0 | BI54: =IF(B54<>0,F54/B54*1000,0) -> 0 | BJ54: =IF($B$54<>0,H54/$B$54*1000,0) -> 0 | BK54: =IF($B$54<>0,J54/$B$54*1000,0) -> 0 | BN54: =IF($B54<>0,P54/$B54*1000,0) -> 0 | BO54: =IF($B54<>0,R54/$B54*1000,0) -> 0
A55: CarboGrind 300 - Green (70186) | B55: 0 | C55: 0 | D55: =B55*C55 -> 0 | E55: 0 | F55: =B55*E55 -> 0 | G55: 0 | H55: =$B55*G55 -> 0 | I55: 0 | J55: =$B55*I55 -> 0 | L55: =$B55*K55 -> 0 | M55: 0 | N55: =$B55*M55 -> 0 | O55: 0 | P55: =$B55*O55 -> 0 | Q55: 0 | R55: =$B55*Q55 -> 0 | AE55: =D55*$B$26+F55*$E$26+H55*$H$26+J55*$K$26+L55*$N$26+N55*$Q$26+P55*$T$26+R55*$W$26 -> 0 | AJ55: =B55*1000 -> 0 | AK55: lb | AL55: 70186/U102 | BH55: =IF(B55<>0,D55/B55*1000,0) -> 0 | BI55: =IF(B55<>0,F55/B55*1000,0) -> 0 | BJ55: =IF($B$55<>0,H55/$B$55*1000,0) -> 0 | BK55: =IF($B$55<>0,J55/$B$55*1000,0) -> 0 | BN55: =IF($B55<>0,P55/$B55*1000,0) -> 0 | BO55: =IF($B55<>0,R55/$B55*1000,0) -> 0
A56: PVA (30017) | B56: 2.257 | C56: 0.012 | D56: =B56*C56 -> 0.027084 | E56: 0 | F56: =B56*E56 -> 0 | G56: 0 | H56: =$B56*G56 -> 0 | I56: 0.01 | J56: =$B56*I56 -> 0.02257 | K56: 0.010276842 | L56: =$B56*K56 -> 0.023194832 | M56: 0 | N56: =$B56*M56 -> 0 | O56: =69706/4674328 -> 0.014912518 | P56: =$B56*O56 -> 0.033657553 | Q56: =12367.22/783756 -> 0.015779426 | R56: =$B56*Q56 -> 0.035614165 | AE56: =D56*$B$26+F56*$E$26+H56*$H$26+J56*$K$26+L56*$N$26+N56*$Q$26+P56*$T$26+R56*$W$26 -> 408.28227 | AJ56: =B56*1000 -> 2257 | AK56: lb | AL56: 30017/U102 | BH56: =IF(B56<>0,D56/B56*1000,0) -> 12 | BI56: =IF(B56<>0,F56/B56*1000,0) -> 0 | BJ56: =IF($B$56<>0,H56/$B$56*1000,0) -> 0 | BK56: =IF($B$56<>0,J56/$B$56*1000,0) -> 10 | BN56: =IF($B56<>0,P56/$B56*1000,0) -> 14.912518 | BO56: =IF($B56<>0,R56/$B56*1000,0) -> 15.779426 | BP56: =BH56*$B$26+BI56*$E$26+BJ56*$H$26 -> 180000 | BQ56: 101933 | BR56: =BQ56/BP56 -> 0.56629444 | BS56: =143105.19/BQ56 -> 1.4039142 | BT56: =143105.19/BR56 -> 252704.56 | BV56: =143105.19/BS56 -> 101933 | BW56: =143105.19/BT56 -> 0.56629444 | BX56: =143105.19/BV56 -> 1.4039142
A57: Dispersant (30011) | B57: =750/1000 -> 0.75 | C57: 0.012 | D57: =B57*C57 -> 0.009 | E57: 0.013 | F57: =B57*E57 -> 0.00975 | G57: 0.05 | H57: =$B57*G57 -> 0.0375 | I57: 0.013 | J57: =$B57*I57 -> 0.00975 | K57: 0.0088472583 | L57: =$B57*K57 -> 0.0066354438 | M57: =12051.2/745600 -> 0.01616309 | N57: =$B57*M57 -> 0.012122318 | O57: =131000/4674328 -> 0.028025419 | P57: =$B57*O57 -> 0.021019064 | Q57: =11579.528/783756 -> 0.014774404 | R57: =$B57*Q57 -> 0.011080803 | AE57: =D57*$B$26+F57*$E$26+H57*$H$26+J57*$K$26+L57*$N$26+N57*$Q$26+P57*$T$26+R57*$W$26 -> 135.8736 | AJ57: =B57*1000 -> 750 | AK57: lb | AL57: 30011/U102 | BH57: =IF(B57<>0,D57/B57*1000,0) -> 12 | BI57: =IF(B57<>0,F57/B57*1000,0) -> 13 | BJ57: =IF($B$57<>0,H57/$B$57*1000,0) -> 50 | BK57: =IF($B$57<>0,J57/$B$57*1000,0) -> 13 | BN57: =IF($B57<>0,P57/$B57*1000,0) -> 28.025419 | BO57: =IF($B57<>0,R57/$B57*1000,0) -> 14.774404 | BP57: =BH57*$B$26+BI57*$E$26+BJ57*$H$26 -> 180000 | BQ57: 84108 | BR57: =BQ57/BP57 -> 0.46726667 | BS57: =38613.79/BQ57 -> 0.45909771 | BT57: =38613.79/BR57 -> 82637.587 | BV57: =38613.79/BS57 -> 84108 | BW57: =38613.79/BT57 -> 0.46726667 | BX57: =38613.79/BV57 -> 0.45909771
A58: Ammonia (30000) | B58: 0.226 | C58: 0.012 | D58: =B58*C58 -> 0.002712 | E58: 0.012 | F58: =B58*E58 -> 0.002712 | G58: 0 | H58: =$B58*G58 -> 0 | I58: 0.0113 | J58: =$B58*I58 -> 0.0025538 | K58: 0.0098592667 | L58: =$B58*K58 -> 0.0022281943 | M58: =8236.2/745600 -> 0.011046406 | N58: =$B58*M58 -> 0.0024964877 | O58: =72861/4674328 -> 0.015587481 | P58: =$B58*O58 -> 0.0035227708 | Q58: =7307.749/783756 -> 0.0093240103 | R58: =$B58*Q58 -> 0.0021072263 | AE58: =D58*$B$26+F58*$E$26+H58*$H$26+J58*$K$26+L58*$N$26+N58*$Q$26+P58*$T$26+R58*$W$26 -> 40.90882 | AJ58: =B58*1000 -> 226 | AK58: lb | AL58: 30000/U102 | BH58: =IF(B58<>0,D58/B58*1000,0) -> 12 | BI58: =IF(B58<>0,F58/B58*1000,0) -> 12 | BJ58: =IF($B$58<>0,H58/$B$58*1000,0) -> 0 | BK58: =IF($B$58<>0,J58/$B$58*1000,0) -> 11.3 | BN58: =IF($B58<>0,P58/$B58*1000,0) -> 15.587481 | BO58: =IF($B58<>0,R58/$B58*1000,0) -> 9.3240103 | BP58: =BH58*$B$26+BI58*$E$26+BJ58*$H$26 -> 180000 | BQ58: 47388 | BR58: =BQ58/BP58 -> 0.26326667 | BS58: =2705.86/BQ58 -> 0.05710011 | BT58: =2705.86/BR58 -> 10278.02 | BV58: =2705.86/BS58 -> 47388 | BW58: =2705.86/BT58 -> 0.26326667 | BX58: =2705.86/BV58 -> 0.05710011
A59: CaCL (30114) | B59: 0.158 | C59: 0 | D59: =B59*C59 -> 0 | E59: 0.1641 | F59: =B59*E59 -> 0.0259278 | G59: 0.24 | H59: =$B59*G59 -> 0.03792 | I59: 0 | J59: =$B59*I59 -> 0 | L59: =$B59*K59 -> 0 | M59: =127002/745600 -> 0.1703353 | N59: =$B59*M59 -> 0.026912977 | O59: 0 | P59: =$B59*O59 -> 0 | Q59: 0 | R59: =$B59*Q59 -> 0 | AE59: =D59*$B$26+F59*$E$26+H59*$H$26+J59*$K$26+L59*$N$26+N59*$Q$26+P59*$T$26+R59*$W$26 -> 0 | AJ59: =B59*1000 -> 158 | AK59: lb | AL59: 30114/U102 | BH59: =IF(B59<>0,D59/B59*1000,0) -> 0 | BI59: =IF(B59<>0,F59/B59*1000,0) -> 164.1 | BJ59: =IF($B$59<>0,H59/$B$59*1000,0) -> 240 | BK59: =IF($B$59<>0,J59/$B$59*1000,0) -> 0 | BN59: =IF($B59<>0,P59/$B59*1000,0) -> 0 | BO59: =IF($B59<>0,R59/$B59*1000,0) -> 0 | BP59: =BH59*$B$26+BI59*$E$26+BJ59*$H$26 -> 0 | BQ59: 560786 | BR59: =BQ59/BP59 -> #DIV/0! | BS59: =49077.4/BQ59 -> 0.08751538 | BT59: =49077.4/BR59 -> #DIV/0! | BV59: =49077.4/BS59 -> 560786 | BW59: =49077.4/BT59 -> #DIV/0! | BX59: =49077.4/BV59 -> 0.08751538
A60: Algenate (30170) | B60: 9.199 | C60: 0 | D60: =B60*C60 -> 0 | E60: 0.01 | F60: =B60*E60 -> 0.09199 | G60: 0.0143 | H60: =$B60*G60 -> 0.1315457 | I60: 0 | J60: =$B60*I60 -> 0 | L60: =$B60*K60 -> 0 | M60: =4610.8/745600 -> 0.0061840129 | N60: =$B60*M60 -> 0.056886734 | O60: 0 | P60: =$B60*O60 -> 0 | Q60: 0 | R60: =$B60*Q60 -> 0 | AE60: =D60*$B$26+F60*$E$26+H60*$H$26+J60*$K$26+L60*$N$26+N60*$Q$26+P60*$T$26+R60*$W$26 -> 0 | AJ60: =B60*1000 -> 9199 | AK60: lb | AL60: 30170/U102 | BH60: =IF(B60<>0,D60/B60*1000,0) -> 0 | BI60: =IF(B60<>0,F60/B60*1000,0) -> 10 | BJ60: =IF($B$60<>0,H60/$B$60*1000,0) -> 14.3 | BK60: =IF($B$60<>0,J60/$B$60*1000,0) -> 0 | BN60: =IF($B60<>0,P60/$B60*1000,0) -> 0 | BO60: =IF($B60<>0,R60/$B60*1000,0) -> 0 | BP60: =BH60*$B$26+BI60*$E$26+BJ60*$H$26 -> 0 | BQ60: 208883 | BR60: =BQ60/BP60 -> #DIV/0! | BS60: =1269211.15/BQ60 -> 6.0761821 | BT60: =1269211.15/BR60 -> #DIV/0! | BV60: =1269211.15/BS60 -> 208883 | BW60: =1269211.15/BT60 -> #DIV/0! | BX60: =1269211.15/BV60 -> 6.0761821
A61: Taggant (30021) | B61: 25.29 | C61: 0 | D61: =B61*C61 -> 0 | E61: 0 | F61: =B61*E61 -> 0 | G61: 0 | H61: =$B61*G61 -> 0 | I61: 0.004 | J61: =$B61*I61 -> 0.10116 | K61: 0.16275833 | L61: =$B61*K61 -> 4.1161582 | M61: =3511/745600 -> 0.0047089592 | N61: =$B61*M61 -> 0.11908958 | O61: 0 | P61: =$B61*O61 -> 0 | Q61: 0 | R61: =$B61*Q61 -> 0 | AE61: =D61*$B$26+F61*$E$26+H61*$H$26+J61*$K$26+L61*$N$26+N61*$Q$26+P61*$T$26+R61*$W$26 -> 9.063936 | AJ61: =B61*1000 -> 25290 | AK61: lb | AL61: 30021/U102 | BH61: =IF(B61<>0,D61/B61*1000,0) -> 0 | BI61: =IF(B61<>0,F61/B61*1000,0) -> 0 | BJ61: =IF($B$61<>0,H61/$B$61*1000,0) -> 0 | BK61: =IF($B$61<>0,J61/$B$61*1000,0) -> 4 | BN61: =IF($B61<>0,P61/$B61*1000,0) -> 0 | BO61: =IF($B61<>0,R61/$B61*1000,0) -> 0 | BP61: =BH61*$B$26+BI61*$E$26+BJ61*$H$26 -> 0
A63: Standard Cost Contribution | D63: $/lb | F63: $/lb | H63: $/lb | J63: $/lb | L63: $/lb | N63: $/lb | P63: $/lb | R63: $/lb
A64: Clay/Bauxite | D64: =D52+D53+D54 -> 0.044238 | F64: =F52+F53+F54 -> 0.044036 | H64: =H52+H53+H54 -> 0.6 | J64: =J52+J53+J54 -> 0.04444 | L64: =L52+L53+L54 -> 0.046218877 | N64: =N52+N53+N54 -> 0.048259171 | P64: =P52+P53+P54 -> 0.22253113 | R64: =R52+R53+R54 -> 0.56595018 | AE64: =AE52+AE53+AE54 -> 667.55182
A65: Chemical | D65: =SUM(D56:D61) -> 0.038796 | F65: =SUM(F56:F61) -> 0.1303798 | H65: =SUM(H56:H61) -> 0.2069657 | J65: =SUM(J56:J61) -> 0.1360338 | L65: =SUM(L56:L61) -> 4.1482167 | N65: =SUM(N56:N61) -> 0.2175081 | P65: =SUM(P56:P61) -> 0.058199388 | R65: =SUM(R56:R61) -> 0.048802195 | AE65: =SUM(AE56:AE61) -> 594.12863
A66: Total Material Cost Per Pound | D66: =SUM(D64:D65) -> 0.083034 | F66: =SUM(F64:F65) -> 0.1744158 | H66: =SUM(H64:H65) -> 0.8069657 | J66: =SUM(J64:J65) -> 0.1804738 | L66: =SUM(L64:L65) -> 4.1944356 | N66: =SUM(N64:N65) -> 0.26576727 | P66: =SUM(P64:P65) -> 0.28073052 | R66: =SUM(R64:R65) -> 0.61475237 | AE66: =SUM(AE64:AE65) -> 1261.6805
A70: Variable Cost - Labor & Benefits - 12 hour shift | AR70: Alternate DLAB01 Allocation per Product Line
AH71: =$AH$14*$AN71 -> 0 | AL71: DLAB01 (s/t) | AM71: 611030 | AN71: 0.7 | AZ71: NIRO | BA71: =($B$78+$B$80+$B$82+#REF!-$B$88)/$B$27*$B$26 -> #REF! | BB71: =($B$78+$B$80+$B$82+#REF!-$B$88)/$B$27*($E$26+$H$26) -> #REF! | BI71: =SUM(BA71:BB71) -> #REF!
AH72: =$AH$14*$AN72 -> 0 | AL72: DLAB01 (o/t) | AM72: 610210 | AN72: 0.3 | AZ72: KS | BA72: 0 | BB72: =($B$79+$B$81+$B$84)/$E$26*($E$26+$H$26) -> #DIV/0! | BI72: =SUM(BA72:BB72) -> #DIV/0!
AH73: =SUM(AH71:AH72) -> 0 | AK73: hr | AL73: DLAB01 | AM73: Total | AR73: =$BJ$73*BK73*$B$26 -> #REF! | AS73: =$BJ$73*BL73*($E$26+$H$26) -> #REF! | AZ73: =SUM(AR73:AS73) -> #REF! | BA73: =SUM(BA71:BA72) -> #REF! | BB73: =SUM(BB71:BB72) -> #REF! | BI73: =SUM(BI71:BI72) -> #REF! | BJ73: =$BG$14 -> 0 | BK73: =BA73/$B$26 -> #REF! | BL73: =BB73/($E$26+$H$26) -> #REF!
AR74: Alternate MLAB01 Allocation per Product Line
AH75: =$AH$15*$AN75 -> 0 | AL75: MLAB01 (s/t) | AM75: 611040 | AN75: 0.7 | AZ75: NIRO | BA75: =($F$78+$F$80+$F$82+$F$86-$F$88)/$B$27*$B$26 -> 292487.41 | BB75: =($F$78+$F$80+$F$82+$F$86-$F$88)/$B$27*($E$26+$H$26) -> 0 | BI75: =SUM(BA75:BB75) -> 292487.41
AH76: =$AH$15*$AN76 -> 0 | AL76: MLAB01 (o/t) | AM76: 610215 | AN76: 0.3 | AZ76: KS | BA76: 0 | BB76: =($F$79+$F$81+$F$84)/$E$26*($E$26+$H$26) -> #VALUE! | BI76: =SUM(BA76:BB76) -> #VALUE!
B77: Jan | C77: Feb | D77: Mar | E77: Apr | F77: May | G77: Jun | H77: Jul | AH77: =SUM(AH75:AH76) -> 0 | AK77: hr | AL77: MLAB01 | AM77: Total | AR77: =$BJ$77*BK77*$B$26 -> 0 | AS77: =$BJ$77*BL77*($E$26+$H$26) -> #VALUE! | AZ77: =SUM(AR77:AS77) -> #VALUE! | BA77: =SUM(BA75:BA76) -> 292487.41 | BB77: =SUM(BB75:BB76) -> #VALUE! | BI77: =SUM(BI75:BI76) -> #VALUE! | BJ77: =$BG$15 -> 0 | BK77: =BA77/$B$26 -> 19.49916 | BL77: =BB77/($E$26+$H$26) -> #VALUE!
A78: Production Labor | B78: 231312.9 | C78: 229610.56 | D78: 285430.3 | E78: 270512.12 | F78: 206981.29 | G78: 189320.29 | H78: 222304.29 | AO78: No-21 YTD
A79: R & M Labor | B79: 46297.03 | C79: 54769.68 | D79: 76487.82 | E79: 65800.98 | F79: 61521.11 | G79: 75465.61 | H79: 77901.19 | AH79: =$AH$16*$AN79 -> 0 | AL79: IPC01 (vac) | AM79: 610220 | AN79: =AO79/$AO$86 -> 0.18435254 | AO79: 94156.32
A80: IPC | B80: 70295.96 | C80: 66308.38 | D80: 77548.14 | E80: 76254.47 | F80: 84379.95 | G80: 64019.88 | H80: 64580.93 | AH80: =$AH$16*$AN80 -> 0 | AL80: IPC01 (hol) | AM80: 610510 | AN80: =AO80/$AO$86 -> 0.099466255 | AO80: 50801.45
A81: Temp | B81: 42351 | C81: 46279 | D81: 42944 | E81: 54316 | F81: 33117 | G81: 17619 | H81: 35008 | AH81: =$AH$16*$AN81 -> 0 | AL81: IPC01 (401k) | AM81: 610600 | AN81: =AO81/$AO$86 -> 0.067696074 | AO81: 34575.13
A82: IPC (estimated) | B82: =B80/(B78+B79-B81) -> 0.29880252 | C82: =C80/(C78+C79-C81) -> 0.27848818 | D82: =D80/(D78+D79-D81) -> 0.24311734 | E82: =E80/(E78+E79-E81) -> 0.2704087 | F82: =F80/(F78+F79-F81) -> 0.35847572 | G82: =G80/(G78+G79-G81) -> 0.25901478 | H82: =H80/(H78+H79-H81) -> 0.24352015 | AH82: =$AH$16*$AN82 -> 0 | AL82: IPC01 (ins) | AM82: 610610 | AN82: =AO82/$AO$86 -> 0.31666105 | AO82: 161731.64
D84: $/FTE/month | F84: $ Rolling Total | AH84: =$AH$16*$AN84 -> 0 | AL84: IPC01 (tax) | AM84: 612000 | AN84: =AO84/$AO$86 -> 0.29782562 | AO84: 152111.62
A85: Current Production Labor | B85: 31 | D85: =(AVERAGE((F78-F81),(G78-G81),(H78-H81)))/31 -> 5729.6975 | F85: =D85*B85 -> 177620.62 | AH85: =$AH$16*$AN85 -> 0 | AL85: IPC01 (w/c) | AM85: 612100 | AN85: =AO85/$AO$86 -> 0.033998456 | AO85: 17364.39
A86: Current R & M Labor | B86: 12 | D86: =AVERAGE($F$79:$H$79)/12 -> 5969.1086 | F86: =D86*B86 -> 71629.303 | AH86: =SUM(AH79:AH85) -> 0 | AK86: hr | AL86: IPC01 | AM86: Total | AN86: =SUM(AN79:AN85) -> 1 | AO86: =SUM(AO79:AO85) -> 510740.55
A88: Future Production Labor Increase | B88: 12 | D88: =(AVERAGE((F78-F81),(G78-G81),(H78-H81)))/31 -> 5729.6975 | F88: =D88*B88 -> 68756.37
A89: Future R&M Labor Increase | B89: 2 | D89: =AVERAGE($F$79:$H$79)/12 -> 5969.1086 | F89: =D89*B89 -> 11938.217
A91: Total Production Labor | B91: =B85+B88 -> 43 | D91: =(AVERAGE((F78-F81),(G78-G81),(H78-H81)))/31 -> 5729.6975 | F91: =D91*B91 -> 246376.99 | AR91: Alternate IPC01 Allocation per Product Line
A92: Total R & M Labor | B92: =B86+B89 -> 14 | D92: =AVERAGE($F$79:$H$79)/12 -> 5969.1086 | F92: =D92*B92 -> 83567.521 | AZ92: NIRO | BA92: =($B$78+$B$80+$B$82+#REF!-$B$88)/$B$27*$B$26 -> #REF! | BB92: =($B$78+$B$80+$B$82+#REF!-$B$88)/$B$27*($E$26+$H$26) -> #REF! | BI92: =SUM(BA92:BB92) -> #REF!
A93: Temp | F93: 0 | AZ93: KS | BA93: 0 | BB93: =($B$79+$B$81+$B$84)/($E$26+$H$26)*($E$26+$H$26) -> #DIV/0! | BI93: =SUM(BA93:BB93) -> #DIV/0!
A94: IPC | F94: =(F91+F92)*0.29 -> 95683.909 | AR94: =$BJ$94*BK94*$B$26 -> #REF! | AS94: =$BJ$94*BL94*($E$26+$H$26) -> #REF! | AZ94: =SUM(AR94:AS94) -> #REF! | BA94: =SUM(BA92:BA93) -> #REF! | BB94: =SUM(BB92:BB93) -> #REF! | BI94: =SUM(BI92:BI93) -> #REF! | BJ94: =$BG$16 -> 0 | BK94: =BA94/$B$26 -> #REF! | BL94: =BB94/($E$26+$H$26) -> #REF!
A105: Variable Costs - Utilities
B106: Gas | C106: mmbtu | D106: price/mmbtu | F106: Electricity | G106: kwh | H106: price/kwh
B107: Contract | C107: =IF(($B$120*($B$26+$K$26+$T$26+$W$26)+$F$120*($E$26+$H$26+$Q$26))*1000<=0,($B$120*($B$26+$K$26+$T$26+$W$26)+$F$120*($E$26+$H$26+$Q$26))*1000,0) -> 0 | F107: NIRO | G107: =(B113*($B$26+$K$26+$T$26+$W$26)+F113*($E$26+$H$26+$Q$26))*1000 -> 2559196.2 | H107: 0.1
B108: Spot | C108: =IF(C107>=0,(((B117+B118+B119)*($B$26+$K$26+$T$26+$W$26)*1000)+((F117+F118+F119)*($E$26+$H$26+$Q$26)*1000))-0,0) -> 89028.64 | D108: 4.2 | F108: KS | G108: =(B114*($B$26+$K$26+$T$26+$W$26)+F114*($E$26+$H$26+$Q$26))*1000 -> 0 | H108: 0.1
C109: =SUM(C107:C108) -> 89028.64 | D109: =(C107*D107+C108*D108)/C109 -> 4.2 | G109: =SUM(G107:G108) -> 2559196.2 | H109: =(G107*H107+G108*H108)/G109 -> 0.1
B111: NIRO | F111: KS
B112: Usage (Unit/lb) | C112: Unit Price | D112: Std. Cost Contribution | F112: Usage (Unit/lb) | G112: Unit Price | H112: Std. Cost Contribution
A113: Electricity (kwh) - NIRO | B113: 0.1696 | C113: =$H$109 -> 0.1 | D113: =B113*C113 -> 0.01696 | G113: =$H$109 -> 0.1 | H113: =F113*G113 -> 0
A114: Electricity (kwh) - KS | B114: 0 | C114: =$H$109 -> 0.1 | D114: =B114*C114 -> 0 | F114: 0.7652 | G114: =$H$109 -> 0.1 | H114: =F114*G114 -> 0.07652
A115: Total Electricity | B115: =SUM(B113:B114) -> 0.1696 | C115: =D115/B115 -> 0.1 | D115: =SUM(D113:D114) -> 0.01696 | F115: =SUM(F113:F114) -> 0.7652 | G115: =H115/F115 -> 0.1 | H115: =SUM(H113:H114) -> 0.07652
A117: Gas (mmbtu) - Kiln | B117: =0.0059/2 -> 0.00295 | C117: =$D$109 -> 4.2 | D117: =B117*C117 -> 0.01239 | F117: =0.0071/2 -> 0.00355 | G117: =$D$109 -> 4.2 | H117: =F117*G117 -> 0.01491
A118: Gas (mmbtu) - NIRO | B118: =0.0059/2 -> 0.00295 | C118: =$D$109 -> 4.2 | D118: =B118*C118 -> 0.01239 | F118: 0 | G118: =$D$109 -> 4.2 | H118: =F118*G118 -> 0
A119: Gas (mmbtu) - Fluid Bed | B119: 0 | C119: =$D$109 -> 4.2 | D119: =B119*C119 -> 0 | F119: =0.0071/2 -> 0.00355 | G119: =$D$109 -> 4.2 | H119: =F119*G119 -> 0.01491
A120: Total Gas | B120: =SUM(B117:B119) -> 0.0059 | C120: =D120/B120 -> 4.2 | D120: =SUM(D117:D119) -> 0.02478 | F120: =SUM(F117:F119) -> 0.0071 | G120: =H120/F120 -> 4.2 | H120: =SUM(H117:H119) -> 0.02982
A122: Total Utilities | D122: =D115+D120 -> 0.04174 | H122: =H115+H120 -> 0.10634
A126: Variable Costs - R&M Supplies, Mfg. Supplies & Other
B128: Jan | C128: Feb | D128: Mar | E128: Apr | F128: May | G128: Jun | H128: Jul
A129: Repairs & Maintenance | B129: 78399.79 | C129: 167568.38 | D129: 183018.16 | E129: 167613.41 | F129: 199564.5 | G129: 144612.57 | H129: 244208.81 | AO129: Nov-21 YTD
...

Sheet Feb
A1: EUFAULA PLANT STANDARD 2025 | BO1: CG300
BO2: Qty/1000 lbs
B3: CEP/CL/HP | E3: KSLD | H3: KSHD | K3: NRT/FUSION | N3: NRT+ | Q3: NRT KSLD | T3: CG280 | W3: CG300 | AA3: COMPOSITE
B4: 25 Standard | C4: 23 Actual | D4: 22 Standard | E4: =+B4 -> 25 Standard | F4: =+C4 -> 23 Actual | G4: =+D4 -> 22 Standard | H4: =+B4 -> 25 Standard | I4: 22 Actual | J4: =+D4 -> 22 Standard | K4: =+B4 -> 25 Standard | L4: 22 Actual | M4: =+D4 -> 22 Standard | N4: =+B4 -> 25 Standard | O4: 19 Actual | P4: =+D4 -> 22 Standard | Q4: =+B4 -> 25 Standard | R4: 19 Actual | S4: =+D4 -> 22 Standard | T4: =+B4 -> 25 Standard | U4: =+C4 -> 23 Actual | V4: =+D4 -> 22 Standard | W4: =+B4 -> 25 Standard | X4: 19 Actual | Y4: =+D4 -> 22 Standard | AA4: 22 Std | AB4: 22 Absorb | AC4: 22 Underabs
C5: (Jan-Mar) | F5: (Jan-Mar) | I5: (Jan-Aug) | L5: (Jan-Feb) | O5: (Jan-Sept) | R5: (Mar & May) | U5: (Jan-Aug) | X5: (Jan-Sept)
A6: Materials | B6: =IF($B$26<>0,$D$66,0) -> 0 | C6: 0.1339 | D6: 0.079895748 | E6: =IF(E26<>0,$F$66,0) -> 0.1744158 | F6: 0.2541 | G6: 0.14867672 | H6: =IF(H26<>0,$H$66,0) -> 0.8069657 | I6: 0.59389054 | J6: 0.41403491 | K6: =IF(K26<>0,$J$66,0) -> 0 | L6: 0.158 | M6: 0.52415863 | N6: =IF(N26<>0,$L$66,0) -> 0 | O6: 1.3654495 | P6: 2.009955 | Q6: =IF(Q26<>0,$N$66,0) -> 0 | R6: 0.3128638 | S6: 0.16351092 | T6: =IF($T$26<>0,$P$66,0) -> 0 | U6: 0 | V6: 0.21393973 | W6: =IF($W$26<>0,$R$66,0) -> 0 | X6: 0.38538493 | Y6: 0.35185707 | AA6: =(B6*B$26+E6*E$26+H6*H$26+K6*K$26+N6*N$26+Q6*Q$26+T6*T$26+W6*W$26)/AA$26 -> 0.59611573 | AB6: =AA6 -> 0.59611573 | AC6: =AA6-AB6 -> 0
A7: Electricity | B7: =IF($B$26<>0,$D$115,0) -> 0 | C7: 0.0199 | D7: 0.017174113 | E7: =IF(E26<>0,$H$115,0) -> 0.07652 | F7: 0.0841 | G7: 0.088307347 | H7: =IF(H26<>0,$H$115,0) -> 0.07652 | I7: 0.068525916 | J7: 0.090176734 | K7: =IF(K26<>0,$D$115,0) -> 0 | L7: 0.0186 | M7: 0.088307347 | N7: =IF(N26<>0,$D$115,0) -> 0 | O7: 0.0073991531 | P7: 0.022101421 | Q7: =IF(Q26<>0,$H$115,0) -> 0 | R7: 0.070627226 | S7: 0.090176734 | T7: =IF($T$26<>0,$D$115,0) -> 0 | U7: 0 | V7: 0.088307347 | W7: =IF($W$26<>0,$D$115,0) -> 0 | X7: 0.0063876044 | Y7: 0.022101421 | AA7: =(B7*B$26+E7*E$26+H7*H$26+K7*K$26+N7*N$26+Q7*Q$26+T7*T$26+W7*W$26)/AA$26 -> 0.07652 | AB7: =AA7 -> 0.07652 | AC7: =AA7-AB7 -> 0 | BH7: =ROUND(AX7/$B$26,3) -> #DIV/0! | BI7: =ROUND(AY7/$E$26,3) -> 0 | BJ7: =IF($H$26<>0,ROUND(AZ7/$H$26,3),0) -> 0 | BK7: =ROUND(BA7/$K$26,3) -> #DIV/0! | BN7: =ROUND(BD7/$T$26,3) -> #DIV/0! | BO7: =ROUND(BE7/$W$26,3) -> #DIV/0!
A8: Gas | B8: =IF(B26<>0,$D$120,0) -> 0 | C8: 0.0272 | D8: 0.077202409 | E8: =IF(E26<>0,$H$120,0) -> 0.02982 | F8: 0.0288 | G8: 0.043356204 | H8: =IF($H$26<>0,$H$120,0) -> 0.02982 | I8: 0.06584205 | J8: 0.012775 | K8: =IF(K26<>0,$D$120,0) -> 0 | L8: 0.0275 | M8: 0.043356204 | N8: =IF(N26<>0,$D$120,0) -> 0 | O8: 0.020068106 | P8: 0.020075 | Q8: =IF(Q26<>0,$H$120,0) -> 0 | R8: 0.012631134 | S8: 0.012775 | T8: =IF(T26<>0,$D$120,0) -> 0 | U8: 0 | V8: 0.043356204 | W8: =IF(W26<>0,$D$120,0) -> 0 | X8: 0.010829289 | Y8: 0.020075 | AA8: =(B8*B$26+E8*E$26+H8*H$26+K8*K$26+N8*N$26+Q8*Q$26+T8*T$26+W8*W$26)/AA$26 -> 0.02982 | AB8: =AA8 -> 0.02982 | AC8: =AA8-AB8 -> 0 | BH8: =ROUND(AX8/$B$26,3) -> #DIV/0! | BI8: =ROUND(AY8/$E$26,3) -> 0 | BJ8: =IF($H$26<>0,ROUND(AZ8/$H$26,3),0) -> 0 | BK8: =ROUND(BA8/$K$26,3) -> #DIV/0! | BN8: =ROUND(BD8/$T$26,3) -> #DIV/0! | BO8: =ROUND(BE8/$W$26,3) -> #DIV/0!
A9: R&M Supplies and Service | B9: =IF(B26<>0,$B$133/$B$27/1000,0) -> 0 | C9: 0.0395 | D9: 0.025157233 | E9: =IF(E26<>0,$B$133/$B$27/1000,0) -> 0.043584139 | F9: 0.0419 | G9: 0.025157233 | H9: =IF(H26<>0,$B$133/$B$27/1000,0) -> 0.043584139 | I9: 0.073013915 | J9: 0.020211742 | K9: =IF(K26<>0,$B$133/$B$27/1000,0) -> 0 | L9: 0.0431 | M9: 0.025157233 | N9: =IF(N26<>0,$B$133/$B$27/1000,0) -> 0 | O9: 0.029693532 | P9: 0.020211742 | Q9: =IF(Q26<>0,$B$133/$B$27/1000,0) -> 0 | R9: 0.0050277646 | S9: 0.020211742 | T9: =IF(T26<>0,$B$133/$B$27/1000,0) -> 0 | U9: 0 | V9: 0.025157233 | W9: =IF(W26<>0,$B$133/$B$27/1000,0) -> 0 | X9: 0.032578496 | Y9: 0.020211742 | AA9: =(B9*B$26+E9*E$26+H9*H$26+K9*K$26+N9*N$26+Q9*Q$26+T9*T$26+W9*W$26)/AA$26 -> 0.043584139 | AB9: =AA9 -> 0.043584139 | AC9: =AA9-AB9 -> 0 | BH9: =ROUND(AX9/$B$26,3) -> #DIV/0! | BI9: =ROUND(AY9/$E$26,3) -> 0 | BJ9: =IF($H$26<>0,ROUND(AZ9/$H$26,3),0) -> 0 | BK9: =ROUND(BA9/$K$26,3) -> #DIV/0! | BN9: =ROUND(BD9/$T$26,3) -> #DIV/0! | BO9: =ROUND(BE9/$W$26,3) -> #DIV/0!
A10: Manufacturing Supplies | B10: =IF(B26<>0,$B$134/$B$27/1000,0) -> 0 | C10: 0.0049 | D10: 0.0041928721 | E10: =IF(E26<>0,$B$134/$B$27/1000,0) -> 0.008883697 | F10: 0.0041 | G10: 0.0041928721 | H10: =IF(H26<>0,$B$134/$B$27/1000,0) -> 0.008883697 | I10: 0.0022798529 | J10: 0.0048123195 | K10: =IF(K26<>0,$B$134/$B$27/1000,0) -> 0 | L10: 0.006 | M10: 0.0041928721 | N10: =IF(N26<>0,$B$134/$B$27/1000,0) -> 0 | O10: 0.0077779148 | P10: 0.0048123195 | Q10: =IF(Q26<>0,$B$134/$B$27/1000,0) -> 0 | R10: 0.0023705607 | S10: 0.0048123195 | T10: =IF(T26<>0,$B$134/$B$27/1000,0) -> 0 | U10: 0 | V10: 0.0041928721 | W10: =IF(W26<>0,$B$134/$B$27/1000,0) -> 0 | X10: 0.0047472399 | Y10: 0.0048123195 | AA10: =(B10*B$26+E10*E$26+H10*H$26+K10*K$26+N10*N$26+Q10*Q$26+T10*T$26+W10*W$26)/AA$26 -> 0.008883697 | AB10: =AA10 -> 0.008883697 | AC10: =AA10-AB10 -> 0 | BH10: =ROUND(AX10/$B$26,3) -> #DIV/0! | BI10: =ROUND(AY10/$E$26,3) -> 0 | BJ10: =IF($H$26<>0,ROUND(AZ10/$H$26,3),0) -> 0 | BK10: =ROUND(BA10/$K$26,3) -> #DIV/0! | BN10: =ROUND(BD10/$T$26,3) -> #DIV/0! | BO10: =ROUND(BE10/$W$26,3) -> #DIV/0!
A11: Other variable | B11: =IF(B26<>0,$B$135/$B$27/1000,0) -> 0 | C11: 0.0136 | D11: 0.0083857442 | E11: =IF(E26<>0,$B$135/$B$27/1000,0) -> 0.020984964 | F11: 0.0282 | G11: 0.0083857442 | H11: =IF(H26<>0,$B$135/$B$27/1000,0) -> 0.020984964 | I11: 0.029140105 | J11: 0.0076997113 | K11: =IF(K26<>0,$B$135/$B$27/1000,0) -> 0 | L11: 0.0256 | M11: 0.0083857442 | N11: =IF(N26<>0,$B$135/$B$27/1000,0) -> 0 | O11: 0.012628237 | P11: 0.0076997113 | Q11: =IF(Q26<>0,$B$135/$B$27/1000,0) -> 0 | R11: 0.0093357827 | S11: 0.0076997113 | T11: =IF(T26<>0,$B$135/$B$27/1000,0) -> 0 | U11: 0 | V11: 0.0083857442 | W11: =IF(W26<>0,$B$135/$B$27/1000,0) -> 0 | X11: 0.0096675993 | Y11: 0.0076997113 | AA11: =(B11*B$26+E11*E$26+H11*H$26+K11*K$26+N11*N$26+Q11*Q$26+T11*T$26+W11*W$26)/AA$26 -> 0.020984964 | AB11: =AA11 -> 0.020984964 | AC11: =AA11-AB11 -> 0 | BH11: =ROUND(AX11/$B$26,3) -> #DIV/0! | BI11: =ROUND(AY11/$E$26,3) -> 0 | BJ11: =IF($H$26<>0,ROUND(AZ11/$H$26,3),0) -> 0 | BK11: =ROUND(BA11/$K$26,3) -> #DIV/0! | BN11: =ROUND(BD11/$T$26,3) -> #DIV/0! | BO11: =ROUND(BE11/$W$26,3) -> #DIV/0!
A12: Total Variable Costs | B12: =SUM(B6:B11) -> 0 | C12: =SUM(C6:C11) -> 0.239 | D12: 0.21200812 | E12: =SUM(E6:E11) -> 0.3542086 | F12: =SUM(F6:F11) -> 0.4412 | G12: 0.31807612 | H12: =SUM(H6:H11) -> 0.9867585 | I12: =SUM(I6:I11) -> 0.83269238 | J12: =SUM(J6:J11) -> 0.54971042 | K12: =SUM(K6:K11) -> 0 | L12: =SUM(L6:L11) -> 0.2788 | M12: 0.69355803 | N12: =SUM(N6:N11) -> 0 | O12: =SUM(O6:O11) -> 1.4430164 | P12: =SUM(P6:P11) -> 2.0848552 | Q12: =SUM(Q6:Q11) -> 0 | R12: =SUM(R6:R11) -> 0.41285626 | S12: =SUM(S6:S11) -> 0.29918642 | T12: =SUM(T6:T11) -> 0 | U12: =SUM(U6:U11) -> 0 | V12: 0.38333913 | W12: =SUM(W6:W11) -> 0 | X12: =SUM(X6:X11) -> 0.44959516 | Y12: =SUM(Y6:Y11) -> 0.42675726 | AA12: =SUM(AA6:AA11) -> 0.77590853 | AB12: =SUM(AB6:AB11) -> 0.77590853 | AC12: =SUM(AC6:AC11) -> 0
A14: Production Labor | B14: =IF(B26<>0,$F$91/$B$27/1000,0) -> 0 | C14: 0.0477 | D14: 0.01509434 | E14: =IF(E26<>0,$F$91/$B$27/1000,0) -> 0.054750443 | F14: 0.0821 | G14: 0.01509434 | H14: =IF(H26<>0,$F$91/$B$27/1000,0) -> 0.054750443 | I14: 0.075578634 | J14: 0.020862907 | K14: =IF(K26<>0,$F$91/$B$27/1000,0) -> 0 | L14: 0.0726 | M14: 0.01509434 | N14: =IF(N26<>0,$F$91/$B$27/1000,0) -> 0 | O14: 0.029535802 | P14: 0.025328546 | Q14: =IF(Q26<>0,$F$91/$B$27/1000,0) -> 0 | R14: 0.039889444 | S14: 0.020862907 | T14: =IF(T26<>0,$F$91/$B$27/1000,0) -> 0 | U14: 0 | V14: 0.01509434 | W14: =IF(W26<>0,$F$91/$B$27/1000,0) -> 0 | X14: 0.0021692465 | Y14: 0.025328546 | AA14: =(B14*B$26+E14*E$26+H14*H$26+K14*K$26+N14*N$26+Q14*Q$26+T14*T$26+W14*W$26)/AA$26 -> 0.054750443 | AB14: =AB22-AB12 -> -0.0031261333 | AC14: =AA14-AB14 -> 0.057876576 | BH14: =ROUND(AX14/$B$26,3) -> #DIV/0! | BI14: =ROUND(AY14/$E$26,3) -> 0 | BJ14: =IF($H$26<>0,ROUND(AZ14/$H$26,3),0) -> 0 | BK14: =ROUND(BA14/$K$26,3) -> #DIV/0! | BN14: =ROUND(BD14/$T$26,3) -> #DIV/0! | BO14: =ROUND(BE14/$W$26,3) -> #DIV/0!
A15: Repairs & Maintenance Labor | B15: =IF(B26<>0,$F$92/$B$27/1000,0) -> 0 | C15: 0.0134 | D15: 0.0051091399 | E15: =IF(E26<>0,$F$92/$B$27/1000,0) -> 0.01857056 | F15: 0.0264 | G15: 0.0051091399 | H15: =IF(H26<>0,$F$92/$B$27/1000,0) -> 0.01857056 | I15: 0.014677876 | J15: 0.010844159 | K15: =IF(K26<>0,$F$92/$B$27/1000,0) -> 0 | L15: 0.0231 | M15: 0.0051091399 | N15: =IF(N26<>0,$F$92/$B$27/1000,0) -> 0 | O15: 0.011565104 | P15: 0.013165317 | Q15: =IF(Q26<>0,$F$92/$B$27/1000,0) -> 0 | R15: 0.012338214 | S15: 0.010844159 | T15: =IF(T26<>0,$F$92/$B$27/1000,0) -> 0 | U15: 0 | V15: 0.0068056863 | W15: =IF(W26<>0,$F$92/$B$27/1000,0) -> 0 | X15: 0.0012020313 | Y15: 0.013165317 | AA15: =(B15*B$26+E15*E$26+H15*H$26+K15*K$26+N15*N$26+Q15*Q$26+T15*T$26+W15*W$26)/AA$26 -> 0.01857056 | AB15: =AB22-AB12-AB14 -> 0 | AC15: =AA15-AB15 -> 0.01857056 | BH15: =ROUND(AX15/$B$26,3) -> #DIV/0! | BI15: =ROUND(AY15/$E$26,3) -> 0 | BJ15: =IF($H$26<>0,ROUND(AZ15/$H$26,3),0) -> 0 | BK15: =ROUND(BA15/$K$26,3) -> #DIV/0! | BL15: =ROUND(BB15/$K$26,3) -> #DIV/0! | BM15: =ROUND(BC15/$K$26,3) -> #DIV/0! | BN15: =ROUND(BD15/$T$26,3) -> #DIV/0! | BO15: =ROUND(BE15/$W$26,3) -> #DIV/0!
A16: Indirect Payroll Costs (Benefits) | B16: =IF(B26<>0,$F$94/$B$27/1000,0) -> 0 | C16: 0.0166 | D16: 0.0070087903 | E16: =IF(E26<>0,$F$94/$B$27/1000,0) -> 0.021263091 | F16: 0.0296 | G16: 0.0070087903 | H16: =IF(H26<>0,$F$94/$B$27/1000,0) -> 0.021263091 | I16: 0.017771004 | J16: 0.014114022 | K16: =IF(K26<>0,$F$94/$B$27/1000,0) -> 0 | L16: 0.027 | M16: 0.0070087903 | N16: =IF(N26<>0,$F$94/$B$27/1000,0) -> 0 | O16: 0.016622212 | P16: 0.017135083 | Q16: =IF(Q26<>0,$F$94/$B$27/1000,0) -> 0 | R16: 0.012631134 | S16: 0.014114022 | T16: =IF(T26<>0,$F$94/$B$27/1000,0) -> 0 | U16: 0 | V16: 0.0093361366 | W16: =IF(W26<>0,$F$94/$B$27/1000,0) -> 0 | X16: 0.0011939818 | Y16: 0.017135083 | AA16: =(B16*B$26+E16*E$26+H16*H$26+K16*K$26+N16*N$26+Q16*Q$26+T16*T$26+W16*W$26)/AA$26 -> 0.021263091 | AB16: =AB22-AB12-AB14-AB15 -> 0 | AC16: =AA16-AB16 -> 0.021263091 | BH16: =ROUND(AX16/$B$26,3) -> #DIV/0! | BI16: =ROUND(AY16/$E$26,3) -> 0 | BJ16: =IF($H$26<>0,ROUND(AZ16/$H$26,3),0) -> 0 | BK16: =ROUND(BA16/$K$26,3) -> #DIV/0! | BN16: =ROUND(BD16/$T$26,3) -> #DIV/0! | BO16: =ROUND(BE16/$W$26,3) -> #DIV/0!
A17: Supervision | B17: 0 | C17: 1.8003774e-05 | D17: 0.0020935849 | E17: 0 | F17: 0.0004720951 | G17: 0.0020935849 | H17: 0 | I17: 0.00015175772 | J17: 0.0036519731 | K17: 0 | L17: 0 | M17: 0.0020935849 | N17: 0 | O17: 0.0042622241 | P17: 0.0036519731 | Q17: 0 | R17: 0.0046532453 | S17: 0.0036519731 | T17: 0 | U17: 0 | V17: 0.0020935849 | W17: 0 | X17: 0.0042504432 | Y17: 0.0036519731 | AA17: =(B17*B$26+E17*E$26+H17*H$26+K17*K$26+N17*N$26+Q17*Q$26+T17*T$26+W17*W$26)/AA$26 -> 0 | AB17: =AB22-AB12-AB14-AB15-AB16 -> 0 | AC17: =AA17-AB17 -> 0 | BH17: =ROUND(AX17/$B$26,3) -> #DIV/0! | BI17: =ROUND(AY17/$E$26,3) -> 0 | BJ17: =IF($H$26<>0,ROUND(AZ17/$H$26,3),0) -> 0 | BK17: =ROUND(BA17/$K$26,3) -> #DIV/0! | BN17: =ROUND(BD17/$T$26,3) -> #DIV/0! | BO17: =ROUND(BE17/$W$26,3) -> #DIV/0!
A18: Depreciation | B18: =IF(B26<>0,$B$148/$B$27/1000,0) -> 0 | C18: 0.0048 | D18: 0.00099233644 | E18: =IF(E26<>0,$B$148/$B$27/1000,0) -> 0.0042165067 | F18: 0.0081 | G18: 0.00099233644 | H18: =IF(H26<>0,$B$148/$B$27/1000,0) -> 0.0042165067 | I18: 0.005932162 | J18: 0.12150298 | K18: =IF(K26<>0,$B$148/$B$27/1000,0) -> 0 | L18: 0.0073 | M18: 0.00099233644 | N18: =IF(N26<>0,$B$148/$B$27/1000,0) -> 0 | O18: 0.014490934 | P18: 0.0069002299 | Q18: =IF(Q26<>0,$B$148/$B$27/1000,0) -> 0 | R18: 0.052077013 | S18: 0.12150298 | T18: =IF(T26<>0,$B$148/$B$27/1000,0) -> 0 | U18: 0 | V18: 0.00099233644 | W18: =IF(W26<>0,$B$148/$B$27/1000,0) -> 0 | X18: 0.01440759 | Y18: 0.0069002299 | AA18: =(B18*B$26+E18*E$26+H18*H$26+K18*K$26+N18*N$26+Q18*Q$26+T18*T$26+W18*W$26)/AA$26 -> 0.0042165067 | AB18: =AB22-AB12-AB14-AB15-AB16-AB17-AB19 -> 0 | AC18: =AA18-AB18 -> 0.0042165067 | BH18: =ROUND(AX18/$B$26,3) -> #DIV/0! | BI18: =ROUND(AY18/$E$26,3) -> 0 | BJ18: =IF($H$26<>0,ROUND(AZ18/$H$26,3),0) -> 0 | BK18: =ROUND(BA18/$K$26,3) -> #DIV/0! | BL18: =ROUND(BB18/$K$26,3) -> #DIV/0! | BM18: =ROUND(BC18/$K$26,3) -> #DIV/0! | BN18: =ROUND(BD18/$T$26,3) -> #DIV/0! | BO18: =ROUND(BE18/$W$26,3) -> #DIV/0!
A19: Insurance & Taxes | B19: =IF(B26<>0,$B$149/$B$27/1000,0) -> 0 | C19: 0.0078 | D19: 0.0072955975 | E19: =IF(E26<>0,$B$149/$B$27/1000,0) -> 0.0078010333 | F19: 0.0152 | G19: 0.0072955975 | H19: =IF(H26<>0,$B$149/$B$27/1000,0) -> 0.0078010333 | I19: 0.0097673443 | J19: 0.0045524543 | K19: =IF(K26<>0,$B$149/$B$27/1000,0) -> 0 | L19: 0.0132 | M19: 0.0072955975 | N19: =IF(N26<>0,$B$149/$B$27/1000,0) -> 0 | O19: 0.0079899726 | P19: 0.0045524543 | Q19: =IF(Q26<>0,$B$149/$B$27/1000,0) -> 0 | R19: 0.0077079837 | S19: 0.0045524543 | T19: =IF(T26<>0,$B$149/$B$27/1000,0) -> 0 | U19: 0 | V19: 0.0072955975 | W19: =IF(W26<>0,$B$149/$B$27/1000,0) -> 0 | X19: 0.007303301 | Y19: 0.0045524543 | AA19: =(B19*B$26+E19*E$26+H19*H$26+K19*K$26+N19*N$26+Q19*Q$26+T19*T$26+W19*W$26)/AA$26 -> 0.0078010333 | AB19: =AB22-AB12-AB14-AB15-AB16-AB17 -> 0 | AC19: =AA19-AB19 -> 0.0078010333 | BH19: =ROUND(AX19/$B$26,3) -> #DIV/0! | BI19: =ROUND(AY19/$E$26,3) -> 0 | BJ19: =IF($H$26<>0,ROUND(AZ19/$H$26,3),0) -> 0 | BK19: =ROUND(BA19/$K$26,3) -> #DIV/0! | BL19: =ROUND(BB19/$K$26,3) -> #DIV/0! | BM19: =ROUND(BC19/$K$26,3) -> #DIV/0! | BN19: =ROUND(BD19/$T$26,3) -> #DIV/0! | BO19: =ROUND(BE19/$W$26,3) -> #DIV/0!
A20: Total Fixed Costs | B20: =SUM(B14:B19) -> 0 | C20: =SUM(C14:C19) -> 0.090318004 | D20: 0.037593789 | E20: =SUM(E14:E19) -> 0.10660163 | F20: =SUM(F14:F19) -> 0.1618721 | G20: 0.037593789 | H20: =SUM(H14:H19) -> 0.10660163 | I20: =SUM(I14:I19) -> 0.12387878 | J20: =SUM(J14:J19) -> 0.1755285 | K20: =SUM(K14:K19) -> 0 | L20: =SUM(L14:L19) -> 0.1432 | M20: 0.037593789 | N20: =SUM(N14:N19) -> 0 | O20: =SUM(O14:O19) -> 0.084466248 | P20: =SUM(P14:P19) -> 0.070733603 | Q20: =SUM(Q14:Q19) -> 0 | R20: =SUM(R14:R19) -> 0.12929703 | S20: =SUM(S14:S19) -> 0.1755285 | T20: =SUM(T14:T19) -> 0 | U20: =SUM(U14:U19) -> 0 | V20: 0.041617681 | W20: =SUM(W14:W19) -> 0 | X20: =SUM(X14:X19) -> 0.030526594 | Y20: =SUM(Y14:Y19) -> 0.070733603 | AA20: =SUM(AA14:AA19) -> 0.10660163 | AB20: =SUM(AB14:AB19) -> -0.0031261333 | AC20: =SUM(AC14:AC19) -> 0.10972777
A22: TOTAL COST PER POUND | B22: =B12+B20 -> 0 | C22: =C12+C20 -> 0.329318 | D22: =D12+D20 -> 0.24960191 | E22: =E12+E20 -> 0.46081023 | F22: =F12+F20 -> 0.6030721 | G22: =G12+G20 -> 0.35566991 | H22: =H12+H20 -> 1.0933601 | I22: =I12+I20 -> 0.95657116 | ... Y22: =Y12+Y20 -> 0.49749086 | AA22: =AA12+AA20 -> 0.88251017 | AB22: =AB6+((0.084*(B26+K26+T26+W26))+(0.134*(E26+Q26))+(0.198*H26))/B27 -> 0.7727824 | AC22: =AC12+AC20 -> 0.10972777
A23: LESS: EXCESS FIXED COSTS | B23: 0 | C23: -0.001395186 | E23: 0 | F23: -0.017495998 | H23: 0 | I23: -0.019688076 | K23: 0 | N23: 0 | Q23: =+Q24-Q22 -> 0 | T23: 0 | U23: 0 | W23: 0 | AA23: =+AA24-AA22 -> 0
A24: ABSORBED COST PER POUND | B24: =+B22+B23 -> 0 | C24: =+C22+C23 -> 0.32792282 | E24: =+E22+E23 -> 0.46081023 | F24: =+F22+F23 -> 0.5855761 | H24: =+H22+H23 -> 1.0933601 | I24: =+I22+I23 -> 0.93688308 | K24: =+K22+K23 -> 0 | L24: =+L22+L23 -> 0.422 | N24: =+N22+N23 -> 0 | Q24: =IF(Q7+Q8+Q9+Q10+Q11+Q20<0.134,Q22,Q6+0.134) -> 0 | T24: =+T22+T23 -> 0 | U24: =+U22+U23 -> 0 | W24: =+W22+W23 -> 0 | AA24: =(B24*B$26+E24*E$26+H24*H$26+K24*K$26+N24*N$26+Q24*Q$26+T24*T$26+W24*W$26)/AA$26 -> 0.88251017
A26: TOTAL PRODUCTION (000 lbs) | B26: =+B32 -> 0 | C26: 23473 | D26: 17100 | E26: =+B33 -> 1500 | F26: 9975 | G26: 10100 | H26: =+B34 -> 3000 | I26: 4086 | J26: 7700 | K26: =+B35 -> 0 | L26: 354 | M26: 3700 | N26: =+B36 -> 0 | O26: 234 | P26: 0 | Q26: =+B37 -> 0 | R26: 478 | S26: 0 | T26: =+B38 -> 0 | U26: 0 | V26: 9100 | W26: =+B40 -> 0 | X26: 784 | Y26: 0 | AA26: =B27 -> 4500
A27: TOTAL PLANT PRODUCTION (000 lbs) | B27: =B26+E26+H26+K26+N26+Q26+T26+W26 -> 4500 | C27: =C26+F26+I26+L26+R26+U26+X26 -> 39150 | D27: =D26+G26+J26+M26+V26+P26+S26+Y26 -> 47700 | L27: .
AB29: Total | AC29: Variable | AD29: Fixed
A30: Production Plan: | B30: Pounds (000) | C30: Product Split | D30: Days | E30: Under absorption days | AA30: 22 Annual: | AB30: ($ in 000s)
A31: CARBO EconoProp | B31: ='2025 Summary'!#REF! -> #REF! | C31: =+B31/$B$41 -> #REF! | AA31: Abs by Prodn | AB31: =SUM(AC31:AD31) -> 3477.5208 | AC31: =AB12*$AA$26 -> 3491.5884 | AD31: =AB20*$AA$26 -> -14.0676
A32: CARBO Lite | B32: ='2025 Summary'!D6 -> 0 | C32: =+B32/$B$41 -> #REF! | D32: =B32*1000/600000 -> 0 | AA32: Under-abs Exp | AB32: =SUM(AC32:AD32) -> 493.77495 | AC32: =AC12*AA26 -> 0 | AD32: =AC20*AA26 -> 493.77495
A33: Kryptosphere LD (includes XT) | B33: ='2025 Summary'!E6 -> 1500 | C33: =+B33/$B$41 -> #REF! | D33: =B33*1000/150000 -> 10 | AA33: Gas Net Settled | AB33: =SUM(AC33:AD33) -> 0 | AC33: =IF(C108<>0,0,(((((D107/1.06564)-0.33)*0.974)-D108)*(240000-C107))/1000) -> 0 | AD33: 0
A34: Kryptosphere HD | B34: ='2025 Summary'!F6 -> 3000 | C34: =+B34/$B$41 -> #REF! | D34: =B34*1000/150000 -> 20 | AA34: Total Cost | AB34: =SUM(AB31:AB33) -> 3971.2958 | AC34: =SUM(AC31:AC33) -> 3491.5884 | AD34: =SUM(AD31:AD33) -> 479.70735
A35: NRT / Fusion | B35: ='2025 Summary'!G6 -> 0 | C35: =+B35/$B$41 -> #REF! | D35: =B35*1000/175000 -> 0 | AA35: Less: Non-cash | AB35: =SUM(AC35:AD35) -> -18.97428 | AC35: 0 | AD35: =-AA18*AA26 -> -18.97428
A36: NRT+ | B36: ='2025 Summary'!H6 -> 0 | C36: =+B36/$B$41 -> #REF! | AA36: Cash | AB36: =SUM(AB34:AB35) -> 3952.3215 | AC36: =SUM(AC34:AC35) -> 3491.5884 | AD36: =SUM(AD34:AD35) -> 460.73307
A37: NRT KSLD | B37: ='2025 Summary'!I6 -> 0 | C37: =+B37/$B$41 -> #REF! | D37: =B37*1000/150000 -> 0
A38: CG280 | B38: ='2025 Summary'!J6 -> 0 | C38: =+B38/$B$41 -> #REF! | D38: =B38*1000/150000 -> 0 | AA38: 22 Monthly:
A39: CG300 | B39: ='2025 Summary'!K6 -> 0 | C39: =+B39/$B$41 -> #REF! | AA39: Abs by Prodn | AB39: =SUM(AC39:AD39) -> 289.7934 | AC39: =AC31/12 -> 290.9657 | AD39: =AD31/12 -> -1.1723
B40: 0 | C40: =+B40/$B$41 -> #REF! | AA40: Under-abs Exp | AB40: =SUM(AC40:AD40) -> 41.147913 | AC40: =AC32/12 -> 0 | AD40: =AD32/12 -> 41.147913
A41: Total | B41: =SUM(B31:B40) -> #REF! | C41: =SUM(C31:C40) -> #REF! | D41: =SUM(D31:D40) -> 30 | E41: =30-D41 -> 0 | AA41: Gas Net Settled | AB41: =SUM(AC41:AD41) -> 0 | AC41: =AC33/12 -> 0 | AD41: =AD33/12 -> 0
AA42: Total Cost | AB42: =SUM(AB39:AB41) -> 330.94131 | AC42: =SUM(AC39:AC41) -> 290.9657 | AD42: =SUM(AD39:AD41) -> 39.975613
AA43: Less: Non-cash | AB43: =SUM(AC43:AD43) -> -1.58119 | AC43: =AC35/12 -> 0 | AD43: =AD35/12 -> -1.58119
A44: Variable Costs - Material | AA44: Cash | AB44: =SUM(AB42:AB43) -> 329.36012 | AC44: =SUM(AC42:AC43) -> 290.9657 | AD44: =SUM(AD42:AD43) -> 38.394423
C45: CEP/CL/HP | E45: KSLD | G45: KSHD | I45: NRT/FUSION | K45: NRT+ | M45: NRT KSLD | O45: CG280 | Q45: CG300
A46: Raw Material: | B46: Price ($/NT) | C46: Ratio/Mix | E46: Ratio/Mix | G46: Ratio/Mix | I46: Ratio/Mix | K46: Ratio/Mix | M46: Ratio/Mix | O46: Ratio/Mix | Q46: Ratio/Mix
A47: Arcilla | B47: =40*2 -> 80 | C47: 0.1 | E47: 0.1 | G47: 0.6 | I47: 0.1 | K47: 0.6 | M47: 0.6 | O47: 0.6 | Q47: 0.6
A48: Minerals Manufacturing Co | B48: =36 -> 36 | C48: 0.9 | E48: 0.9 | G48: 0.4 | I48: 0.9 | K48: 0.4 | M48: 0.4 | O48: 0.4 | Q48: 0.4
A49: Weighted Average (LW) | B49: =+B47*C47+B48*C48 -> 40.4 | C49: =SUM(C47:C48) -> 1 | E49: =SUM(E47:E48) -> 1 | G49: =SUM(G47:G48) -> 1 | I49: =SUM(I47:I48) -> 1 | K49: =SUM(K47:K48) -> 1 | M49: =SUM(M47:M48) -> 1 | O49: =SUM(O47:O48) -> 1 | Q49: =SUM(Q47:Q48) -> 1
A51: Materials: | B51: Price ($/lb) | C51: BOM Use/lb | D51: Std $ Contrib | E51: BOM Use/lb | F51: Std $ Contrib | G51: BOM Use/lb | H51: Std $ Contrib | I51: BOM Use/lb | J51: Std $ Contrib | K51: BOM Use/lb | L51: Std $ Contrib | M51: BOM Use/lb | N51: Std $ Contrib | O51: BOM Use/lb | P51: Std $ Contrib | Q51: BOM Use/lb | R51: Std $ Contrib | BP51: lbs required | BQ51: 10/31/16 Inv | BR51: % of requ | BS51: cost per lb | BT51: cost per lb | BV51: cost per lb | BW51: cost per lb | BX51: cost per lb
A52: Clay/Kaolin (30015) | B52: =$B$49/2000 -> 0.0202 | C52: 2.19 | D52: =B52*C52 -> 0.044238 | E52: 2.18 | F52: =B52*E52 -> 0.044036 | G52: 0 | H52: =$B52*G52 -> 0 | I52: 2.2 | J52: =$B52*I52 -> 0.04444 | K52: 2.2880632 | L52: =$B52*K52 -> 0.046218877 | M52: =1781289/745600 -> 2.3890679 | N52: =$B52*M52 -> 0.048259171 | O52: =10229046/4674328 -> 2.1883458 | P52: =$B52*O52 -> 0.044204585 | Q52: =559444.75/783756 -> 0.71379964 | R52: =$B52*Q52 -> 0.014418753 | AE52: =D52*$B$26+F52*$E$26+H52*$H$26+J52*$K$26+L52*$N$26+N52*$Q$26+P52*$T$26+R52*$W$26 -> 66.054 | AJ52: =B52*1000 -> 20.2 | AK52: lb | AL52: 30015/U102 | BH52: =IF(B52<>0,D52/B52*1000,0) -> 2190 | BI52: =IF(B52<>0,F52/B52*1000,0) -> 2180 | BJ52: =IF($B$52<>0,H52/$B$52*1000,0) -> 0 | BK52: =IF($B$52<>0,J52/$B$52*1000,0) -> 2200 | BN52: =IF($B52<>0,P52/$B52*1000,0) -> 2188.3458 | BO52: =IF($B52<>0,R52/$B52*1000,0) -> 713.79964 | BP52: =BH52*$B$26+BI52*$E$26+BJ52*$H$26 -> 3270000 | BQ52: 202343432 | BR52: =BQ52/BP52 -> 61.878725 | BS52: =343597.02/24291676.299 -> 0.01414464 | BT52: =343597.02/24291676.299 -> 0.01414464 | BV52: =343597.02/24291676.299 -> 0.01414464 | BW52: =343597.02/24291676.299 -> 0.01414464 | BX52: =343597.02/24291676.299 -> 0.01414464
A53: Bauxite Pellets (30282) | B53: 0.25 | C53: 0 | D53: =B53*C53 -> 0 | E53: 0 | F53: =B53*E53 -> 0 | G53: 2.4 | H53: =$B53*G53 -> 0.6 | I53: 0 | J53: =$B53*I53 -> 0 | L53: =$B53*K53 -> 0 | M53: 0 | N53: =$B53*M53 -> 0 | O53: =3334227/4674328 -> 0.71330617 | P53: =$B53*O53 -> 0.17832654 | Q53: =1729064.25/783756 -> 2.2061257 | R53: =$B53*Q53 -> 0.55153142 | AE53: =D53*$B$26+F53*$E$26+H53*$H$26+J53*$K$26+L53*$N$26+N53*$Q$26+P53*$T$26+R53*$W$26 -> 1800 | AJ53: =B53*1000 -> 250 | AK53: lb | AL53: 30282/U102 | BH53: =IF(B53<>0,D53/B53*1000,0) -> 0 | BI53: =IF(B53<>0,F53/B53*1000,0) -> 0 | BJ53: =IF($B$53<>0,H53/$B$53*1000,0) -> 2400 | BK53: =IF($B$53<>0,J53/$B$53*1000,0) -> 0 | BN53: =IF($B53<>0,P53/$B53*1000,0) -> 713.30617 | BO53: =IF($B53<>0,R53/$B53*1000,0) -> 2206.1257 | BP53: =BH53*$B$26+BI53*$E$26+BJ53*$H$26 -> 7200000 | BQ53: 0 | BR53: =BQ53/BP53 -> 0 | BS53: 0.06274 | BT53: 0.06274 | BV53: 0.06274 | BW53: 0.06274 | BX53: 0.06274
A54: CarboGrind 280 - Green (70180) | B54: 0 | C54: 0 | D54: =B54*C54 -> 0 | E54: 0 | F54: =B54*E54 -> 0 | G54: 0 | H54: =$B54*G54 -> 0 | I54: 0 | J54: =$B54*I54 -> 0 | L54: =$B54*K54 -> 0 | M54: 0 | N54: =$B54*M54 -> 0 | O54: 0 | P54: =$B54*O54 -> 0 | Q54: 0 | R54: =$B54*Q54 -> 0 | AE54: =D54*$B$26+F54*$E$26+H54*$H$26+J54*$K$26+L54*$N$26+N54*$Q$26+P54*$T$26+R54*$W$26 -> 0 | AJ54: =B54*1000 -> 0 | AK54: lb | AL54: 70180/U102 | BH54: =IF(B54<>0,D54/B54*1000,0) -> 0 | BI54: =IF(B54<>0,F54/B54*1000,0) -> 0 | BJ54: =IF($B$54<>0,H54/$B$54*1000,0) -> 0 | BK54: =IF($B$54<>0,J54/$B$54*1000,0) -> 0 | BN54: =IF($B54<>0,P54/$B54*1000,0) -> 0 | BO54: =IF($B54<>0,R54/$B54*1000,0) -> 0
A55: CarboGrind 300 - Green (70186) | B55: 0 | C55: 0 | D55: =B55*C55 -> 0 | E55: 0 | F55: =B55*E55 -> 0 | G55: 0 | H55: =$B55*G55 -> 0 | I55: 0 | J55: =$B55*I55 -> 0 | L55: =$B55*K55 -> 0 | M55: 0 | N55: =$B55*M55 -> 0 | O55: 0 | P55: =$B55*O55 -> 0 | Q55: 0 | R55: =$B55*Q55 -> 0 | AE55: =D55*$B$26+F55*$E$26+H55*$H$26+J55*$K$26+L55*$N$26+N55*$Q$26+P55*$T$26+R55*$W$26 -> 0 | AJ55: =B55*1000 -> 0 | AK55: lb | AL55: 70186/U102 | BH55: =IF(B55<>0,D55/B55*1000,0) -> 0 | BI55: =IF(B55<>0,F55/B55*1000,0) -> 0 | BJ55: =IF($B$55<>0,H55/$B$55*1000,0) -> 0 | BK55: =IF($B$55<>0,J55/$B$55*1000,0) -> 0 | BN55: =IF($B55<>0,P55/$B55*1000,0) -> 0 | BO55: =IF($B55<>0,R55/$B55*1000,0) -> 0
A56: PVA (30017) | B56: 2.257 | C56: 0.012 | D56: =B56*C56 -> 0.027084 | E56: 0 | F56: =B56*E56 -> 0 | G56: 0 | H56: =$B56*G56 -> 0 | I56: 0.01 | J56: =$B56*I56 -> 0.02257 | K56: 0.010276842 | L56: =$B56*K56 -> 0.023194832 | M56: 0 | N56: =$B56*M56 -> 0 | O56: =69706/4674328 -> 0.014912518 | P56: =$B56*O56 -> 0.033657553 | Q56: =12367.22/783756 -> 0.015779426 | R56: =$B56*Q56 -> 0.035614165 | AE56: =D56*$B$26+F56*$E$26+H56*$H$26+J56*$K$26+L56*$N$26+N56*$Q$26+P56*$T$26+R56*$W$26 -> 0 | AJ56: =B56*1000 -> 2257 | AK56: lb | AL56: 30017/U102 | BH56: =IF(B56<>0,D56/B56*1000,0) -> 12 | BI56: =IF(B56<>0,F56/B56*1000,0) -> 0 | BJ56: =IF($B$56<>0,H56/$B$56*1000,0) -> 0 | BK56: =IF($B$56<>0,J56/$B$56*1000,0) -> 10 | BN56: =IF($B56<>0,P56/$B56*1000,0) -> 14.912518 | BO56: =IF($B56<>0,R56/$B56*1000,0) -> 15.779426 | BP56: =BH56*$B$26+BI56*$E$26+BJ56*$H$26 -> 0 | BQ56: 101933 | BR56: =BQ56/BP56 -> #DIV/0! | BS56: =143105.19/BQ56 -> 1.4039142 | BT56: =143105.19/BR56 -> #DIV/0! | BV56: =143105.19/BS56 -> 101933 | BW56: =143105.19/BT56 -> #DIV/0! | BX56: =143105.19/BV56 -> 1.4039142
A57: Dispersant (30011) | B57: =750/1000 -> 0.75 | C57: 0.012 | D57: =B57*C57 -> 0.009 | E57: 0.013 | F57: =B57*E57 -> 0.00975 | G57: 0.05 | H57: =$B57*G57 -> 0.0375 | I57: 0.013 | J57: =$B57*I57 -> 0.00975 | K57: 0.0088472583 | L57: =$B57*K57 -> 0.0066354438 | M57: =12051.2/745600 -> 0.01616309 | N57: =$B57*M57 -> 0.012122318 | O57: =131000/4674328 -> 0.028025419 | P57: =$B57*O57 -> 0.021019064 | Q57: =11579.528/783756 -> 0.014774404 | R57: =$B57*Q57 -> 0.011080803 | AE57: =D57*$B$26+F57*$E$26+H57*$H$26+J57*$K$26+L57*$N$26+N57*$Q$26+P57*$T$26+R57*$W$26 -> 127.125 | AJ57: =B57*1000 -> 750 | AK57: lb | AL57: 30011/U102 | BH57: =IF(B57<>0,D57/B57*1000,0) -> 12 | BI57: =IF(B57<>0,F57/B57*1000,0) -> 13 | BJ57: =IF($B$57<>0,H57/$B$57*1000,0) -> 50 | BK57: =IF($B$57<>0,J57/$B$57*1000,0) -> 13 | BN57: =IF($B57<>0,P57/$B57*1000,0) -> 28.025419 | BO57: =IF($B57<>0,R57/$B57*1000,0) -> 14.774404 | BP57: =BH57*$B$26+BI57*$E$26+BJ57*$H$26 -> 169500 | BQ57: 84108 | BR57: =BQ57/BP57 -> 0.49621239 | BS57: =38613.79/BQ57 -> 0.45909771 | BT57: =38613.79/BR57 -> 77817.061 | BV57: =38613.79/BS57 -> 84108 | BW57: =38613.79/BT57 -> 0.49621239 | BX57: =38613.79/BV57 -> 0.45909771
A58: Ammonia (30000) | B58: 0.226 | C58: 0.012 | D58: =B58*C58 -> 0.002712 | E58: 0.012 | F58: =B58*E58 -> 0.002712 | G58: 0 | H58: =$B58*G58 -> 0 | I58: 0.0113 | J58: =$B58*I58 -> 0.0025538 | K58: 0.0098592667 | L58: =$B58*K58 -> 0.0022281943 | M58: =8236.2/745600 -> 0.011046406 | N58: =$B58*M58 -> 0.0024964877 | O58: =72861/4674328 -> 0.015587481 | P58: =$B58*O58 -> 0.0035227708 | Q58: =7307.749/783756 -> 0.0093240103 | R58: =$B58*Q58 -> 0.0021072263 | AE58: =D58*$B$26+F58*$E$26+H58*$H$26+J58*$K$26+L58*$N$26+N58*$Q$26+P58*$T$26+R58*$W$26 -> 4.068 | AJ58: =B58*1000 -> 226 | AK58: lb | AL58: 30000/U102 | BH58: =IF(B58<>0,D58/B58*1000,0) -> 12 | BI58: =IF(B58<>0,F58/B58*1000,0) -> 12 | BJ58: =IF($B$58<>0,H58/$B$58*1000,0) -> 0 | BK58: =IF($B$58<>0,J58/$B$58*1000,0) -> 11.3 | BN58: =IF($B58<>0,P58/$B58*1000,0) -> 15.587481 | BO58: =IF($B58<>0,R58/$B58*1000,0) -> 9.3240103 | BP58: =BH58*$B$26+BI58*$E$26+BJ58*$H$26 -> 18000 | BQ58: 47388 | BR58: =BQ58/BP58 -> 2.6326667 | BS58: =2705.86/BQ58 -> 0.05710011 | BT58: =2705.86/BR58 -> 1027.802 | BV58: =2705.86/BS58 -> 47388 | BW58: =2705.86/BT58 -> 2.6326667 | BX58: =2705.86/BV58 -> 0.05710011
A59: CaCL (30114) | B59: 0.158 | C59: 0 | D59: =B59*C59 -> 0 | E59: 0.1641 | F59: =B59*E59 -> 0.0259278 | G59: 0.24 | H59: =$B59*G59 -> 0.03792 | I59: 0 | J59: =$B59*I59 -> 0 | L59: =$B59*K59 -> 0 | M59: =127002/745600 -> 0.1703353 | N59: =$B59*M59 -> 0.026912977 | O59: 0 | P59: =$B59*O59 -> 0 | Q59: 0 | R59: =$B59*Q59 -> 0 | AE59: =D59*$B$26+F59*$E$26+H59*$H$26+J59*$K$26+L59*$N$26+N59*$Q$26+P59*$T$26+R59*$W$26 -> 152.6517 | AJ59: =B59*1000 -> 158 | AK59: lb | AL59: 30114/U102 | BH59: =IF(B59<>0,D59/B59*1000,0) -> 0 | BI59: =IF(B59<>0,F59/B59*1000,0) -> 164.1 | BJ59: =IF($B$59<>0,H59/$B$59*1000,0) -> 240 | BK59: =IF($B$59<>0,J59/$B$59*1000,0) -> 0 | BN59: =IF($B59<>0,P59/$B59*1000,0) -> 0 | BO59: =IF($B59<>0,R59/$B59*1000,0) -> 0 | BP59: =BH59*$B$26+BI59*$E$26+BJ59*$H$26 -> 966150 | BQ59: 560786 | BR59: =BQ59/BP59 -> 0.58043368 | BS59: =49077.4/BQ59 -> 0.08751538 | BT59: =49077.4/BR59 -> 84552.985 | BV59: =49077.4/BS59 -> 560786 | BW59: =49077.4/BT59 -> 0.58043368 | BX59: =49077.4/BV59 -> 0.08751538
A60: Algenate (30170) | B60: 9.199 | C60: 0 | D60: =B60*C60 -> 0 | E60: 0.01 | F60: =B60*E60 -> 0.09199 | G60: 0.0143 | H60: =$B60*G60 -> 0.1315457 | I60: 0 | J60: =$B60*I60 -> 0 | L60: =$B60*K60 -> 0 | M60: =4610.8/745600 -> 0.0061840129 | N60: =$B60*M60 -> 0.056886734 | O60: 0 | P60: =$B60*O60 -> 0 | Q60: 0 | R60: =$B60*Q60 -> 0 | AE60: =D60*$B$26+F60*$E$26+H60*$H$26+J60*$K$26+L60*$N$26+N60*$Q$26+P60*$T$26+R60*$W$26 -> 532.6221 | AJ60: =B60*1000 -> 9199 | AK60: lb | AL60: 30170/U102 | BH60: =IF(B60<>0,D60/B60*1000,0) -> 0 | BI60: =IF(B60<>0,F60/B60*1000,0) -> 10 | BJ60: =IF($B$60<>0,H60/$B$60*1000,0) -> 14.3 | BK60: =IF($B$60<>0,J60/$B$60*1000,0) -> 0 | BN60: =IF($B60<>0,P60/$B60*1000,0) -> 0 | BO60: =IF($B60<>0,R60/$B60*1000,0) -> 0 | BP60: =BH60*$B$26+BI60*$E$26+BJ60*$H$26 -> 57900 | BQ60: 208883 | BR60: =BQ60/BP60 -> 3.6076511 | BS60: =1269211.15/BQ60 -> 6.0761821 | BT60: =1269211.15/BR60 -> 351810.94 | BV60: =1269211.15/BS60 -> 208883 | BW60: =1269211.15/BT60 -> 3.6076511 | BX60: =1269211.15/BV60 -> 6.0761821
A61: Taggant (30021) | B61: 25.29 | C61: 0 | D61: =B61*C61 -> 0 | E61: 0 | F61: =B61*E61 -> 0 | G61: 0 | H61: =$B61*G61 -> 0 | I61: 0.004 | J61: =$B61*I61 -> 0.10116 | K61: 0.16275833 | L61: =$B61*K61 -> 4.1161582 | M61: =3511/745600 -> 0.0047089592 | N61: =$B61*M61 -> 0.11908958 | O61: 0 | P61: =$B61*O61 -> 0 | Q61: 0 | R61: =$B61*Q61 -> 0 | AE61: =D61*$B$26+F61*$E$26+H61*$H$26+J61*$K$26+L61*$N$26+N61*$Q$26+P61*$T$26+R61*$W$26 -> 0 | AJ61: =B61*1000 -> 25290 | AK61: lb | AL61: 30021/U102 | BH61: =IF(B61<>0,D61/B61*1000,0) -> 0 | BI61: =IF(B61<>0,F61/B61*1000,0) -> 0 | BJ61: =IF($B$61<>0,H61/$B$61*1000,0) -> 0 | BK61: =IF($B$61<>0,J61/$B$61*1000,0) -> 4 | BN61: =IF($B61<>0,P61/$B61*1000,0) -> 0 | BO61: =IF($B61<>0,R61/$B61*1000,0) -> 0 | BP61: =BH61*$B$26+BI61*$E$26+BJ61*$H$26 -> 0
A63: Standard Cost Contribution | D63: $/lb | F63: $/lb | H63: $/lb | J63: $/lb | L63: $/lb | N63: $/lb | P63: $/lb | R63: $/lb
A64: Clay/Bauxite | D64: =D52+D53+D54 -> 0.044238 | F64: =F52+F53+F54 -> 0.044036 | H64: =H52+H53+H54 -> 0.6 | J64: =J52+J53+J54 -> 0.04444 | L64: =L52+L53+L54 -> 0.046218877 | N64: =N52+N53+N54 -> 0.048259171 | P64: =P52+P53+P54 -> 0.22253113 | R64: =R52+R53+R54 -> 0.56595018 | AE64: =AE52+AE53+AE54 -> 1866.054
A65: Chemical | D65: =SUM(D56:D61) -> 0.038796 | F65: =SUM(F56:F61) -> 0.1303798 | H65: =SUM(H56:H61) -> 0.2069657 | J65: =SUM(J56:J61) -> 0.1360338 | L65: =SUM(L56:L61) -> 4.1482167 | N65: =SUM(N56:N61) -> 0.2175081 | P65: =SUM(P56:P61) -> 0.058199388 | R65: =SUM(R56:R61) -> 0.048802195 | AE65: =SUM(AE56:AE61) -> 816.4668
A66: Total Material Cost Per Pound | D66: =SUM(D64:D65) -> 0.083034 | F66: =SUM(F64:F65) -> 0.1744158 | H66: =SUM(H64:H65) -> 0.8069657 | J66: =SUM(J64:J65) -> 0.1804738 | L66: =SUM(L64:L65) -> 4.1944356 | N66: =SUM(N64:N65) -> 0.26576727 | P66: =SUM(P64:P65) -> 0.28073052 | R66: =SUM(R64:R65) -> 0.61475237 | AE66: =SUM(AE64:AE65) -> 2682.5208
A70: Variable Cost - Labor & Benefits - 12 hour shift | AR70: Alternate DLAB01 Allocation per Product Line
AH71: =$AH$14*$AN71 -> 0 | AL71: DLAB01 (s/t) | AM71: 611030 | AN71: 0.7 | AZ71: NIRO | BA71: =($B$78+$B$80+$B$82+#REF!-$B$88)/$B$27*$B$26 -> #REF! | BB71: =($B$78+$B$80+$B$82+#REF!-$B$88)/$B$27*($E$26+$H$26) -> #REF! | BI71: =SUM(BA71:BB71) -> #REF!
AH72: =$AH$14*$AN72 -> 0 | AL72: DLAB01 (o/t) | AM72: 610210 | AN72: 0.3 | AZ72: KS | BA72: 0 | BB72: =($B$79+$B$81+$B$84)/$E$26*($E$26+$H$26) -> 265944.09 | BI72: =SUM(BA72:BB72) -> 265944.09
AH73: =SUM(AH71:AH72) -> 0 | AK73: hr | AL73: DLAB01 | AM73: Total | AR73: =$BJ$73*BK73*$B$26 -> #REF! | AS73: =$BJ$73*BL73*($E$26+$H$26) -> #REF! | AZ73: =SUM(AR73:AS73) -> #REF! | BA73: =SUM(BA71:BA72) -> #REF! | BB73: =SUM(BB71:BB72) -> #REF! | BI73: =SUM(BI71:BI72) -> #REF! | BJ73: =$BG$14 -> 0 | BK73: =BA73/$B$26 -> #REF! | BL73: =BB73/($E$26+$H$26) -> #REF!
AR74: Alternate MLAB01 Allocation per Product Line
AH75: =$AH$15*$AN75 -> 0 | AL75: MLAB01 (s/t) | AM75: 611040 | AN75: 0.7 | AZ75: NIRO | BA75: =($F$78+$F$80+$F$82+$F$86-$F$88)/$B$27*$B$26 -> 0 | BB75: =($F$78+$F$80+$F$82+$F$86-$F$88)/$B$27*($E$26+$H$26) -> 294234.53 | BI75: =SUM(BA75:BB75) -> 294234.53
AH76: =$AH$15*$AN76 -> 0 | AL76: MLAB01 (o/t) | AM76: 610215 | AN76: 0.3 | AZ76: KS | BA76: 0 | BB76: =($F$79+$F$81+$F$84)/$E$26*($E$26+$H$26) -> #VALUE! | BI76: =SUM(BA76:BB76) -> #VALUE!
B77: Jan | C77: Feb | D77: Mar | E77: Apr | F77: May | G77: Jun | H77: Jul | AH77: =SUM(AH75:AH76) -> 0 | AK77: hr | AL77: MLAB01 | AM77: Total | AR77: =$BJ$77*BK77*$B$26 -> #DIV/0! | AS77: =$BJ$77*BL77*($E$26+$H$26) -> #VALUE! | AZ77: =SUM(AR77:AS77) -> #DIV/0! | BA77: =SUM(BA75:BA76) -> 0 | BB77: =SUM(BB75:BB76) -> #VALUE! | BI77: =SUM(BI75:BI76) -> #VALUE! | BJ77: =$BG$15 -> 0 | BK77: =BA77/$B$26 -> #DIV/0! | BL77: =BB77/($E$26+$H$26) -> #VALUE!
A78: Production Labor | B78: 231312.9 | C78: 229610.56 | D78: 285430.3 | E78: 270512.12 | F78: 206981.29 | G78: 189320.29 | H78: 222304.29 | AO78: No-21 YTD
A79: R & M Labor | B79: 46297.03 | C79: 54769.68 | D79: 76487.82 | E79: 65800.98 | F79: 61521.11 | G79: 75465.61 | H79: 77901.19 | AH79: =$AH$16*$AN79 -> 0 | AL79: IPC01 (vac) | AM79: 610220 | AN79: =AO79/$AO$86 -> 0.18435254 | AO79: 94156.32
A80: IPC | B80: 70295.96 | C80: 66308.38 | D80: 77548.14 | E80: 76254.47 | F80: 84379.95 | G80: 64019.88 | H80: 64580.93 | AH80: =$AH$16*$AN80 -> 0 | AL80: IPC01 (hol) | AM80: 610510 | AN80: =AO80/$AO$86 -> 0.099466255 | AO80: 50801.45
A81: Temp | B81: 42351 | C81: 46279 | D81: 42944 | E81: 54316 | F81: 33117 | G81: 17619 | H81: 35008 | AH81: =$AH$16*$AN81 -> 0 | AL81: IPC01 (401k) | AM81: 610600 | AN81: =AO81/$AO$86 -> 0.067696074 | AO81: 34575.13
A82: IPC (estimated) | B82: =B80/(B78+B79-B81) -> 0.29880252 | C82: =C80/(C78+C79-C81) -> 0.27848818 | D82: =D80/(D78+D79-D81) -> 0.24311734 | E82: =E80/(E78+E79-E81) -> 0.2704087 | F82: =F80/(F78+F79-F81) -> 0.35847572 | G82: =G80/(G78+G79-G81) -> 0.25901478 | H82: =H80/(H78+H79-H81) -> 0.24352015 | AH82: =$AH$16*$AN82 -> 0 | AL82: IPC01 (ins) | AM82: 610610 | AN82: =AO82/$AO$86 -> 0.31666105 | AO82: 161731.64
D84: $/FTE/month | F84: $ Rolling Total | AH84: =$AH$16*$AN84 -> 0 | AL84: IPC01 (tax) | AM84: 612000 | AN84: =AO84/$AO$86 -> 0.29782562 | AO84: 152111.62
A85: Current Production Labor | B85: 31 | D85: =(AVERAGE((F78-F81),(G78-G81),(H78-H81)))/31 -> 5729.6975 | F85: =D85*B85 -> 177620.62 | AH85: =$AH$16*$AN85 -> 0 | AL85: IPC01 (w/c) | AM85: 612100 | AN85: =AO85/$AO$86 -> 0.033998456 | AO85: 17364.39
A86: Current R & M Labor | B86: 12 | D86: =AVERAGE($F$79:$H$79)/12 -> 5969.1086 | F86: =D86*B86 -> 71629.303 | AH86: =SUM(AH79:AH85) -> 0 | AK86: hr | AL86: IPC01 | AM86: Total | AN86: =SUM(AN79:AN85) -> 1 | AO86: =SUM(AO79:AO85) -> 510740.55
A88: Future Production Labor Increase | B88: 12 | D88: =(AVERAGE((F78-F81),(G78-G81),(H78-H81)))/31 -> 5729.6975 | F88: =D88*B88 -> 68756.37
A89: Future R&M Labor Increase | B89: 2 | D89: =AVERAGE($F$79:$H$79)/12 -> 5969.1086 | F89: =D89*B89 -> 11938.217
A91: Total Production Labor | B91: =B85+B88 -> 43 | D91: =(AVERAGE((F78-F81),(G78-G81),(H78-H81)))/31 -> 5729.6975 | F91: =D91*B91 -> 246376.99 | AR91: Alternate IPC01 Allocation per Product Line
A92: Total R & M Labor | B92: =B86+B89 -> 14 | D92: =AVERAGE($F$79:$H$79)/12 -> 5969.1086 | F92: =D92*B92 -> 83567.521 | AZ92: NIRO | BA92: =($B$78+$B$80+$B$82+#REF!-$B$88)/$B$27*$B$26 -> #REF! | BB92: =($B$78+$B$80+$B$82+#REF!-$B$88)/$B$27*($E$26+$H$26) -> #REF! | BI92: =SUM(BA92:BB92) -> #REF!
A93: Temp | F93: 0 | AZ93: KS | BA93: 0 | BB93: =($B$79+$B$81+$B$84)/($E$26+$H$26)*($E$26+$H$26) -> 88648.03 | BI93: =SUM(BA93:BB93) -> 88648.03
A94: IPC | F94: =(F91+F92)*0.29 -> 95683.909 | AR94: =$BJ$94*BK94*$B$26 -> #REF! | AS94: =$BJ$94*BL94*($E$26+$H$26) -> #REF! | AZ94: =SUM(AR94:AS94) -> #REF! | BA94: =SUM(BA92:BA93) -> #REF! | BB94: =SUM(BB92:BB93) -> #REF! | BI94: =SUM(BI92:BI93) -> #REF! | BJ94: =$BG$16 -> 0 | BK94: =BA94/$B$26 -> #REF! | BL94: =BB94/($E$26+$H$26) -> #REF!
A105: Variable Costs - Utilities
B106: Gas | C106: mmbtu | D106: price/mmbtu | F106: Electricity | G106: kwh | H106: price/kwh
B107: Contract | C107: =IF(($B$120*($B$26+$K$26+$T$26+$W$26)+$F$120*($E$26+$H$26+$Q$26))*1000<=0,($B$120*($B$26+$K$26+$T$26+$W$26)+$F$120*($E$26+$H$26+$Q$26))*1000,0) -> 0 | F107: NIRO | G107: =(B113*($B$26+$K$26+$T$26+$W$26)+F113*($E$26+$H$26+$Q$26))*1000 -> 0 | H107: 0.1
B108: Spot | C108: =IF(C107>=0,(((B117+B118+B119)*($B$26+$K$26+$T$26+$W$26)*1000)+((F117+F118+F119)*($E$26+$H$26+$Q$26)*1000))-0,0) -> 31950 | D108: 4.2 | F108: KS | G108: =(B114*($B$26+$K$26+$T$26+$W$26)+F114*($E$26+$H$26+$Q$26))*1000 -> 3443400 | H108: 0.1
C109: =SUM(C107:C108) -> 31950 | D109: =(C107*D107+C108*D108)/C109 -> 4.2 | G109: =SUM(G107:G108) -> 3443400 | H109: =(G107*H107+G108*H108)/G109 -> 0.1
B111: NIRO | F111: KS
B112: Usage (Unit/lb) | C112: Unit Price | D112: Std. Cost Contribution | F112: Usage (Unit/lb) | G112: Unit Price | H112: Std. Cost Contribution
A113: Electricity (kwh) - NIRO | B113: 0.1696 | C113: =$H$109 -> 0.1 | D113: =B113*C113 -> 0.01696 | G113: =$H$109 -> 0.1 | H113: =F113*G113 -> 0
A114: Electricity (kwh) - KS | B114: 0 | C114: =$H$109 -> 0.1 | D114: =B114*C114 -> 0 | F114: 0.7652 | G114: =$H$109 -> 0.1 | H114: =F114*G114 -> 0.07652
A115: Total Electricity | B115: =SUM(B113:B114) -> 0.1696 | C115: =D115/B115 -> 0.1 | D115: =SUM(D113:D114) -> 0.01696 | F115: =SUM(F113:F114) -> 0.7652 | G115: =H115/F115 -> 0.1 | H115: =SUM(H113:H114) -> 0.07652
A117: Gas (mmbtu) - Kiln | B117: =0.0059/2 -> 0.00295 | C117: =$D$109 -> 4.2 | D117: =B117*C117 -> 0.01239 | F117: =0.0071/2 -> 0.00355 | G117: =$D$109 -> 4.2 | H117: =F117*G117 -> 0.01491
A118: Gas (mmbtu) - NIRO | B118: =0.0059/2 -> 0.00295 | C118: =$D$109 -> 4.2 | D118: =B118*C118 -> 0.01239 | F118: 0 | G118: =$D$109 -> 4.2 | H118: =F118*G118 -> 0
A119: Gas (mmbtu) - Fluid Bed | B119: 0 | C119: =$D$109 -> 4.2 | D119: =B119*C119 -> 0 | F119: =0.0071/2 -> 0.00355 | G119: =$D$109 -> 4.2 | H119: =F119*G119 -> 0.01491
A120: Total Gas | B120: =SUM(B117:B119) -> 0.0059 | C120: =D120/B120 -> 4.2 | D120: =SUM(D117:D119) -> 0.02478 | F120: =SUM(F117:F119) -> 0.0071 | G120: =H120/F120 -> 4.2 | H120: =SUM(H117:H119) -> 0.02982
A122: Total Utilities | D122: =D115+D120 -> 0.04174 | H122: =H115+H120 -> 0.10634
A126: Variable Costs - R&M Supplies, Mfg. Supplies & Other
B128: Jan | C128: Feb | D128: Mar | E128: Apr | F128: May | G128: Jun | H128: Jul
A129: Repairs & Maintenance | B129: 78399.79 | C129: 167568.38 | D129: 183018.16 | E129: 167613.41 | F129: 199564.5 | G129: 144612.57 | H129: 244208.81 | AO129: Nov-21 YTD
...

Sheet Mar
A1: EUFAULA PLANT STANDARD 2025 | BO1: CG300
BO2: Qty/1000 lbs
B3: CEP/CL/HP | E3: KSLD | H3: KSHD | K3: NRT/FUSION | N3: NRT+ | Q3: NRT KSLD | T3: CG280 | W3: CG300 | AA3: COMPOSITE
B4: 25 Standard | C4: 23 Actual | D4: 22 Standard | E4: =+B4 -> 25 Standard | F4: =+C4 -> 23 Actual | G4: =+D4 -> 22 Standard | H4: =+B4 -> 25 Standard | I4: 22 Actual | J4: =+D4 -> 22 Standard | K4: =+B4 -> 25 Standard | L4: 22 Actual | M4: =+D4 -> 22 Standard | N4: =+B4 -> 25 Standard | O4: 19 Actual | P4: =+D4 -> 22 Standard | Q4: =+B4 -> 25 Standard | R4: 19 Actual | S4: =+D4 -> 22 Standard | T4: =+B4 -> 25 Standard | U4: =+C4 -> 23 Actual | V4: =+D4 -> 22 Standard | W4: =+B4 -> 25 Standard | X4: 19 Actual | Y4: =+D4 -> 22 Standard | AA4: 22 Std | AB4: 22 Absorb | AC4: 22 Underabs
C5: (Jan-Mar) | F5: (Jan-Mar) | I5: (Jan-Aug) | L5: (Jan-Feb) | O5: (Jan-Sept) | R5: (Mar & May) | U5: (Jan-Aug) | X5: (Jan-Sept)
A6: Materials | B6: =IF($B$26<>0,$D$66,0) -> 0 | C6: 0.1339 | D6: 0.079895748 | E6: =IF(E26<>0,$F$66,0) -> 0.1744158 | F6: 0.2541 | G6: 0.14867672 | H6: =IF(H26<>0,$H$66,0) -> 0 | I6: 0.59389054 | J6: 0.41403491 | K6: =IF(K26<>0,$J$66,0) -> 0 | L6: 0.158 | M6: 0.52415863 | N6: =IF(N26<>0,$L$66,0) -> 0 | O6: 1.3654495 | P6: 2.009955 | Q6: =IF(Q26<>0,$N$66,0) -> 0 | R6: 0.3128638 | S6: 0.16351092 | T6: =IF($T$26<>0,$P$66,0) -> 0 | U6: 0 | V6: 0.21393973 | W6: =IF($W$26<>0,$R$66,0) -> 0 | X6: 0.38538493 | Y6: 0.35185707 | AA6: =(B6*B$26+E6*E$26+H6*H$26+K6*K$26+N6*N$26+Q6*Q$26+T6*T$26+W6*W$26)/AA$26 -> 0.1744158 | AB6: =AA6 -> 0.1744158 | AC6: =AA6-AB6 -> 0
A7: Electricity | B7: =IF($B$26<>0,$D$115,0) -> 0 | C7: 0.0199 | D7: 0.017174113 | E7: =IF(E26<>0,$H$115,0) -> 0.07652 | F7: 0.0841 | G7: 0.088307347 | H7: =IF(H26<>0,$H$115,0) -> 0 | I7: 0.068525916 | J7: 0.090176734 | K7: =IF(K26<>0,$D$115,0) -> 0 | L7: 0.0186 | M7: 0.088307347 | N7: =IF(N26<>0,$D$115,0) -> 0 | O7: 0.0073991531 | P7: 0.022101421 | Q7: =IF(Q26<>0,$H$115,0) -> 0 | R7: 0.070627226 | S7: 0.090176734 | T7: =IF($T$26<>0,$D$115,0) -> 0 | U7: 0 | V7: 0.088307347 | W7: =IF($W$26<>0,$D$115,0) -> 0 | X7: 0.0063876044 | Y7: 0.022101421 | AA7: =(B7*B$26+E7*E$26+H7*H$26+K7*K$26+N7*N$26+Q7*Q$26+T7*T$26+W7*W$26)/AA$26 -> 0.07652 | AB7: =AA7 -> 0.07652 | AC7: =AA7-AB7 -> 0 | BH7: =ROUND(AX7/$B$26,3) -> #DIV/0! | BI7: =ROUND(AY7/$E$26,3) -> 0 | BJ7: =IF($H$26<>0,ROUND(AZ7/$H$26,3),0) -> 0 | BK7: =ROUND(BA7/$K$26,3) -> #DIV/0! | BN7: =ROUND(BD7/$T$26,3) -> #DIV/0! | BO7: =ROUND(BE7/$W$26,3) -> #DIV/0!
A8: Gas | B8: =IF(B26<>0,$D$120,0) -> 0 | C8: 0.0272 | D8: 0.077202409 | E8: =IF(E26<>0,$H$120,0) -> 0.02982 | F8: 0.0288 | G8: 0.043356204 | H8: =IF($H$26<>0,$H$120,0) -> 0 | I8: 0.06584205 | J8: 0.012775 | K8: =IF(K26<>0,$D$120,0) -> 0 | L8: 0.0275 | M8: 0.043356204 | N8: =IF(N26<>0,$D$120,0) -> 0 | O8: 0.020068106 | P8: 0.020075 | Q8: =IF(Q26<>0,$H$120,0) -> 0 | R8: 0.012631134 | S8: 0.012775 | T8: =IF(T26<>0,$D$120,0) -> 0 | U8: 0 | V8: 0.043356204 | W8: =IF(W26<>0,$D$120,0) -> 0 | X8: 0.010829289 | Y8: 0.020075 | AA8: =(B8*B$26+E8*E$26+H8*H$26+K8*K$26+N8*N$26+Q8*Q$26+T8*T$26+W8*W$26)/AA$26 -> 0.02982 | AB8: =AA8 -> 0.02982 | AC8: =AA8-AB8 -> 0 | BH8: =ROUND(AX8/$B$26,3) -> #DIV/0! | BI8: =ROUND(AY8/$E$26,3) -> 0 | BJ8: =IF($H$26<>0,ROUND(AZ8/$H$26,3),0) -> 0 | BK8: =ROUND(BA8/$K$26,3) -> #DIV/0! | BN8: =ROUND(BD8/$T$26,3) -> #DIV/0! | BO8: =ROUND(BE8/$W$26,3) -> #DIV/0!
A9: R&M Supplies and Service | B9: =IF(B26<>0,$B$133/$B$27/1000,0) -> 0 | C9: 0.0395 | D9: 0.025157233 | E9: =IF(E26<>0,$B$133/$B$27/1000,0) -> 0.043584139 | F9: 0.0419 | G9: 0.025157233 | H9: =IF(H26<>0,$B$133/$B$27/1000,0) -> 0 | I9: 0.073013915 | J9: 0.020211742 | K9: =IF(K26<>0,$B$133/$B$27/1000,0) -> 0 | L9: 0.0431 | M9: 0.025157233 | N9: =IF(N26<>0,$B$133/$B$27/1000,0) -> 0 | O9: 0.029693532 | P9: 0.020211742 | Q9: =IF(Q26<>0,$B$133/$B$27/1000,0) -> 0 | R9: 0.0050277646 | S9: 0.020211742 | T9: =IF(T26<>0,$B$133/$B$27/1000,0) -> 0 | U9: 0 | V9: 0.025157233 | W9: =IF(W26<>0,$B$133/$B$27/1000,0) -> 0 | X9: 0.032578496 | Y9: 0.020211742 | AA9: =(B9*B$26+E9*E$26+H9*H$26+K9*K$26+N9*N$26+Q9*Q$26+T9*T$26+W9*W$26)/AA$26 -> 0.043584139 | AB9: =AA9 -> 0.043584139 | AC9: =AA9-AB9 -> 0 | BH9: =ROUND(AX9/$B$26,3) -> #DIV/0! | BI9: =ROUND(AY9/$E$26,3) -> 0 | BJ9: =IF($H$26<>0,ROUND(AZ9/$H$26,3),0) -> 0 | BK9: =ROUND(BA9/$K$26,3) -> #DIV/0! | BN9: =ROUND(BD9/$T$26,3) -> #DIV/0! | BO9: =ROUND(BE9/$W$26,3) -> #DIV/0!
A10: Manufacturing Supplies | B10: =IF(B26<>0,$B$134/$B$27/1000,0) -> 0 | C10: 0.0049 | D10: 0.0041928721 | E10: =IF(E26<>0,$B$134/$B$27/1000,0) -> 0.008883697 | F10: 0.0041 | G10: 0.0041928721 | H10: =IF(H26<>0,$B$134/$B$27/1000,0) -> 0 | I10: 0.0022798529 | J10: 0.0048123195 | K10: =IF(K26<>0,$B$134/$B$27/1000,0) -> 0 | L10: 0.006 | M10: 0.0041928721 | N10: =IF(N26<>0,$B$134/$B$27/1000,0) -> 0 | O10: 0.0077779148 | P10: 0.0048123195 | Q10: =IF(Q26<>0,$B$134/$B$27/1000,0) -> 0 | R10: 0.0023705607 | S10: 0.0048123195 | T10: =IF(T26<>0,$B$134/$B$27/1000,0) -> 0 | U10: 0 | V10: 0.0041928721 | W10: =IF(W26<>0,$B$134/$B$27/1000,0) -> 0 | X10: 0.0047472399 | Y10: 0.0048123195 | AA10: =(B10*B$26+E10*E$26+H10*H$26+K10*K$26+N10*N$26+Q10*Q$26+T10*T$26+W10*W$26)/AA$26 -> 0.008883697 | AB10: =AA10 -> 0.008883697 | AC10: =AA10-AB10 -> 0 | BH10: =ROUND(AX10/$B$26,3) -> #DIV/0! | BI10: =ROUND(AY10/$E$26,3) -> 0 | BJ10: =IF($H$26<>0,ROUND(AZ10/$H$26,3),0) -> 0 | BK10: =ROUND(BA10/$K$26,3) -> #DIV/0! | BN10: =ROUND(BD10/$T$26,3) -> #DIV/0! | BO10: =ROUND(BE10/$W$26,3) -> #DIV/0!
A11: Other variable | B11: =IF(B26<>0,$B$135/$B$27/1000,0) -> 0 | C11: 0.0136 | D11: 0.0083857442 | E11: =IF(E26<>0,$B$135/$B$27/1000,0) -> 0.020984964 | F11: 0.0282 | G11: 0.0083857442 | H11: =IF(H26<>0,$B$135/$B$27/1000,0) -> 0 | I11: 0.029140105 | J11: 0.0076997113 | K11: =IF(K26<>0,$B$135/$B$27/1000,0) -> 0 | L11: 0.0256 | M11: 0.0083857442 | N11: =IF(N26<>0,$B$135/$B$27/1000,0) -> 0 | O11: 0.012628237 | P11: 0.0076997113 | Q11: =IF(Q26<>0,$B$135/$B$27/1000,0) -> 0 | R11: 0.0093357827 | S11: 0.0076997113 | T11: =IF(T26<>0,$B$135/$B$27/1000,0) -> 0 | U11: 0 | V11: 0.0083857442 | W11: =IF(W26<>0,$B$135/$B$27/1000,0) -> 0 | X11: 0.0096675993 | Y11: 0.0076997113 | AA11: =(B11*B$26+E11*E$26+H11*H$26+K11*K$26+N11*N$26+Q11*Q$26+T11*T$26+W11*W$26)/AA$26 -> 0.020984964 | AB11: =AA11 -> 0.020984964 | AC11: =AA11-AB11 -> 0 | BH11: =ROUND(AX11/$B$26,3) -> #DIV/0! | BI11: =ROUND(AY11/$E$26,3) -> 0 | BJ11: =IF($H$26<>0,ROUND(AZ11/$H$26,3),0) -> 0 | BK11: =ROUND(BA11/$K$26,3) -> #DIV/0! | BN11: =ROUND(BD11/$T$26,3) -> #DIV/0! | BO11: =ROUND(BE11/$W$26,3) -> #DIV/0!
